Workbook
Name Bi_Weekly: Sheet2!$Q$3
Name int: Sheet1!$D$4
Name Monthly: Sheet2!$Q$4
Name None: Sheet2!$Q$7
Name plot_date: OFFSET(Sheet1!$C$31,0,0,COUNTA(Sheet1!$C:$C)-1)
Name plot_return: OFFSET(Sheet1!$Y$31,0,0,COUNTA(Sheet1!$Y:$Y)-1)
Name plot_return2: OFFSET(Sheet1!$AD$31,0,0,COUNTA(Sheet1!$AD:$AD)-1)
Name Quarterly: Sheet2!$Q$5
Name Weekly: Sheet2!$Q$2
Name Yearly: Sheet2!$Q$6

Sheet Sheet1
C1: Dollar Cost Average Method (DCA)
C3: Initial Investment | D3: 50
C4: Interval | D4: Monthly
C5: Increment | D5: 100
C6: Amount | D6: 15000
C7: Date Range
C9: ROI | D9: =Y30 -> 0.45033962
C10: IRR | D10: =XIRR(AF31:AF930,$C31:$C930) -> #VALUE!
C11: Time-weighted | D11: =(U30-U31-(AF30+U30))/(U31-AJ30) -> -1.4219434
C12: annual
C23: Symbol | D23: T
C24: Weight | D24: 1
C25: Return(%) | D25: {=(LOOKUP(2,1/(D:D<>""),D:D)-INDEX(D:D,31))/INDEX(D:D,31)} -> -0.024652744
B29: No | C29: Date | D29: Price($) | E29: Dividends | F29: Cash Flow | J29: Shares | L29: Total Shares | N29: Dividends | O29: Cash Flow | Q29: Shares | R29: Total Shares | S29: Total Shares | T29: Cost Basis($) | U29: Mkt Value($) | W29: Gain($) | X29: Dividends($) | Y29: Return(%) | AA29: Cost Basis($) | AB29: Mkt Value($) | AC29: Gain($) | AD29: Return (%) | AF29: Cash Flows | AH29: Di | AI29: Wi | AJ29: Wi x Fi
T30: {=LOOKUP(2,1/(T:T<>""),T:T)} -> 22450 | U30: {=LOOKUP(2,1/(U:U<>""),U:U)} -> 20479.731 | V30: {=LOOKUP(2,1/(V:V<>""),V:V)} -> -0.087762554 | W30: {=LOOKUP(2,1/(W:W<>""),W:W)} -> -1970.2693 | X30: {=LOOKUP(2,1/(X:X<>""),X:X)} -> 12080.394 | Y30: {=LOOKUP(2,1/(Y:Y<>""),Y:Y)} -> 0.45033962 | AA30: {=LOOKUP(2,1/(AA:AA<>""),AA:AA)} -> 34530.394 | AB30: {=LOOKUP(2,1/(AB:AB<>""),AB:AB)} -> 30688.142 | AC30: {=LOOKUP(2,1/(AC:AC<>""),AC:AC)} -> -3842.252 | AD30: {=LOOKUP(2,1/(AD:AD<>""),AD:AD)} -> -0.11127159 | AF30: =SUM(AF31:AF929) -> -10369.606 | AG30: =SUM(AG31:AG929) -> -22450 | AH30: {=LOOKUP(2,1/(AH:AH<>""),AH:AH)} -> 6286 | AJ30: =-SUM(AJ31:AJ929) -> 7307.396 | AK30: =-SUM(AK31:AK929) -> 11225.056
B31: =IF(C30="","",IF(C$30<C31,"",B30+1)) | C31: =IF(Sheet3!A2="","",Sheet3!A2) -> 37627 | D31: =IF(C31="","",Sheet3!E2) -> 28.799999 | E31: =_xlfn.XLOOKUP(WEEKNUM(C31)&YEAR(C31),Sheet4!C:C,Sheet4!B:B,0) -> 0.27 | F31: =-D3 -> -50 | H31: =F31 -> -50 | J31: =IF(D$24=0,"",ABS($F31*D$24)/D31) -> 1.7361112 | L31: =IF(D31=0,"",J31) -> 1.7361112 | N31: =IF(D31=0,"",L31*E31) -> 0.46875002 | O31: =-(IF(D31=0,"",N31)) -> -0.46875002 | P31: =F31 -> -50 | Q31: =ABS(O31)/D31 -> 0.016276043 | R31: =Q31 -> 0.016276043 | S31: =IF(D31=0,"",L31+R31) -> 1.7523872 | T31: =D31*J31 -> 50 | U31: =IF(D31=0,"",L31*D31) -> 50 | V31: =(U31/T31)-1 -> 0 | W31: =U31-T31 -> 0 | X31: =ABS(O31) -> 0.46875002 | Y31: =((U31+X31)/T31)-1 -> 0.0093750003 | AA31: =(D31*Q31)+(D31*J31) -> 50.46875 | AB31: =(L31*D31)+(D31*R31) -> 50.46875 | AC31: =AB31-AA31 -> 0 | AD31: =(AB31/AA31)-1 -> 0 | AF31: =F31+ABS(O31) -> -49.53125 | AG31: =F31 -> -50 | AH31: =DATEDIF($C$31,C31,"d") -> 0 | AI31: =(AH$30-AH31)/AH$30 -> 1 | AJ31: =$AI31*AF31 -> -49.53125 | AK31: =$AI31*AG31 -> -50
B32: =IF(C31="","",IF(C$30<C32,"",B31+1)) | C32: =IF(Sheet3!A3="","",Sheet3!A3) -> 37634 | D32: =IF(C32="","",Sheet3!E3) -> 27.280001 | E32: =_xlfn.XLOOKUP(WEEKNUM(C32)&YEAR(C32),Sheet4!C:C,Sheet4!B:B,0) -> 0 | F32: =IF(int=Weekly,-$D$5,IF(int=Bi_Weekly,0,IF(int=Monthly,0,IF(int=Quarterly,0,IF(int=Yearly,0,IF(int=None,0,0)))))) -> 0 | H32: =H31+F32 -> -50 | J32: =IF(D$24=0,"",ABS($F32*D$24)/D32) -> 0 | L32: =IF(D32=0,"",L31+J32) -> 1.7361112 | N32: =IF(D32=0,"",L32*E32) -> 0 | O32: =-(IF(D32=0,"",N32)) -> 0 | P32: =P31+F32+O32 -> -50 | Q32: =IF(D32=0,"",ABS($O32)/D32) -> 0 | R32: =IF(D32=0,"",Q32+R31) -> 0.016276043 | S32: =IF(D32=0,"",L32+R32) -> 1.7523872 | T32: =IF(D32=0,"",D32*J32)+T31 -> 50 | U32: =IF(D32=0,"",L32*D32) -> 47.361114 | V32: =(U32/T32)-1 -> -0.05277771 | W32: =U32-T32 -> -2.6388855 | X32: =ABS(O32)+X31 -> 0.46875002 | Y32: =((U32+X32)/T32)-1 -> -0.04340271 | AA32: =(D32*Q32)+(D32*J32)+AA31 -> 50.46875 | AB32: =(L32*D32)+(D32*R32) -> 47.805125 | AC32: =AB32-AA32 -> -2.6636251 | AD32: =(AB32/AA32)-1 -> -0.05277771 | AF32: =F32+ABS(O32) -> 0 | AG32: =F32 -> 0 | AH32: =DATEDIF($C$31,C32,"d") -> 7 | AI32: =(AH$30-AH32)/AH$30 -> 0.99888641 | AJ32: =AI32*AF32 -> 0 | AK32: =$AI32*AG32 -> 0
B33: =IF(C32="","",IF(C$30<C33,"",B32+1)) | C33: =IF(Sheet3!A4="","",Sheet3!A4) -> 37641 | D33: =IF(C33="","",Sheet3!E4) -> 24.540001 | E33: =_xlfn.XLOOKUP(WEEKNUM(C33)&YEAR(C33),Sheet4!C:C,Sheet4!B:B,0) -> 0 | F33: =IF(int=Weekly,-$D$5,IF(int=Bi_Weekly,-$D$5,IF(int=Monthly,0,IF(int=Quarterly,0,IF(int=Yearly,0,IF(int=None,0,0)))))) -> 0 | H33: =H32+F33 -> -50 | J33: =IF(D$24=0,"",ABS($F33*D$24)/D33) -> 0 | L33: =IF(D33=0,"",L32+J33) -> 1.7361112 | N33: =IF(D33=0,"",L33*E33) -> 0 | O33: =-(IF(D33=0,"",N33)) -> 0 | P33: =P32+F33+O33 -> -50 | Q33: =IF(D33=0,"",ABS($O33)/D33) -> 0 | R33: =IF(D33=0,"",Q33+R32) -> 0.016276043 | S33: =IF(D33=0,"",L33+R33) -> 1.7523872 | T33: =IF(D33=0,"",D33*J33)+T32 -> 50 | U33: =IF(D33=0,"",L33*D33) -> 42.60417 | V33: =(U33/T33)-1 -> -0.1479166 | W33: =U33-T33 -> -7.3958301 | X33: =ABS(O33)+X32 -> 0.46875002 | Y33: =((U33+X33)/T33)-1 -> -0.1385416 | AA33: =(D33*Q33)+(D33*J33)+AA32 -> 50.46875 | AB33: =(L33*D33)+(D33*R33) -> 43.003584 | AC33: =AB33-AA33 -> -7.465166 | AD33: =(AB33/AA33)-1 -> -0.1479166 | AF33: =F33+ABS(O33) -> 0 | AG33: =F33 -> 0 | AH33: =DATEDIF($C$31,C33,"d") -> 14 | AI33: =(AH$30-AH33)/AH$30 -> 0.99777283 | AJ33: =AI33*AF33 -> 0 | AK33: =$AI33*AG33 -> 0
B34: =IF(C33="","",IF(C$30<C34,"",B33+1)) | C34: =IF(Sheet3!A5="","",Sheet3!A5) -> 37648 | D34: =IF(C34="","",Sheet3!E5) -> 24.440001 | E34: =_xlfn.XLOOKUP(WEEKNUM(C34)&YEAR(C34),Sheet4!C:C,Sheet4!B:B,0) -> 0 | F34: =IF(int=Weekly,-$D$5,IF(int=Bi_Weekly,0,IF(int=Monthly,0,IF(int=Quarterly,0,IF(int=Yearly,0,IF(int=None,0,0)))))) -> 0 | H34: =H33+F34 -> -50 | J34: =IF(D$24=0,"",ABS($F34*D$24)/D34) -> 0 | L34: =IF(D34=0,"",L33+J34) -> 1.7361112 | N34: =IF(D34=0,"",L34*E34) -> 0 | O34: =-(IF(D34=0,"",N34)) -> 0 | P34: =P33+F34+O34 -> -50 | Q34: =IF(D34=0,"",ABS($O34)/D34) -> 0 | R34: =IF(D34=0,"",Q34+R33) -> 0.016276043 | S34: =IF(D34=0,"",L34+R34) -> 1.7523872 | T34: =IF(D34=0,"",D34*J34)+T33 -> 50 | U34: =IF(D34=0,"",L34*D34) -> 42.430559 | V34: =(U34/T34)-1 -> -0.15138882 | W34: =U34-T34 -> -7.5694412 | X34: =ABS(O34)+X33 -> 0.46875002 | Y34: =((U34+X34)/T34)-1 -> -0.14201382 | AA34: =(D34*Q34)+(D34*J34)+AA33 -> 50.46875 | AB34: =(L34*D34)+(D34*R34) -> 42.828345 | AC34: =AB34-AA34 -> -7.6404047 | AD34: =(AB34/AA34)-1 -> -0.15138882 | AF34: =F34+ABS(O34) -> 0 | AG34: =F34 -> 0 | AH34: =DATEDIF($C$31,C34,"d") -> 21 | AI34: =(AH$30-AH34)/AH$30 -> 0.99665924 | AJ34: =AI34*AF34 -> 0 | AK34: =$AI34*AG34 -> 0
B35: =IF(C34="","",IF(C$30<C35,"",B34+1)) | C35: =IF(Sheet3!A6="","",Sheet3!A6) -> 37655 | D35: =IF(C35="","",Sheet3!E6) -> 25.18 | E35: =_xlfn.XLOOKUP(WEEKNUM(C35)&YEAR(C35),Sheet4!C:C,Sheet4!B:B,0) -> 0 | F35: =IF(int=Weekly,-$D$5,IF(int=Bi_Weekly,-$D$5,IF(int=Monthly,-$D$5,IF(int=Quarterly,0,IF(int=Yearly,0,IF(int=None,0,0)))))) -> -100 | H35: =H34+F35 -> -150 | J35: =IF(D$24=0,"",ABS($F35*D$24)/D35) -> 3.9714059 | L35: =IF(D35=0,"",L34+J35) -> 5.707517 | N35: =IF(D35=0,"",L35*E35) -> 0 | O35: =-(IF(D35=0,"",N35)) -> 0 | P35: =P34+F35+O35 -> -150 | Q35: =IF(D35=0,"",ABS($O35)/D35) -> 0 | R35: =IF(D35=0,"",Q35+R34) -> 0.016276043 | S35: =IF(D35=0,"",L35+R35) -> 5.7237931 | T35: =IF(D35=0,"",D35*J35)+T34 -> 150 | U35: =IF(D35=0,"",L35*D35) -> 143.71528 | V35: =(U35/T35)-1 -> -0.041898138 | W35: =U35-T35 -> -6.2847207 | X35: =ABS(O35)+X34 -> 0.46875002 | Y35: =((U35+X35)/T35)-1 -> -0.038773138 | AA35: =(D35*Q35)+(D35*J35)+AA34 -> 150.46875 | AB35: =(L35*D35)+(D35*R35) -> 144.12511 | AC35: =AB35-AA35 -> -6.34364 | AD35: =(AB35/AA35)-1 -> -0.042159186 | AF35: =F35+ABS(O35) -> -100 | AG35: =F35 -> -100 | AH35: =DATEDIF($C$31,C35,"d") -> 28 | AI35: =(AH$30-AH35)/AH$30 -> 0.99554566 | AJ35: =AI35*AF35 -> -99.554566 | AK35: =$AI35*AG35 -> -99.554566
B36: =IF(C35="","",IF(C$30<C36,"",B35+1)) | C36: =IF(Sheet3!A7="","",Sheet3!A7) -> 37662 | D36: =IF(C36="","",Sheet3!E7) -> 23.35 | E36: =_xlfn.XLOOKUP(WEEKNUM(C36)&YEAR(C36),Sheet4!C:C,Sheet4!B:B,0) -> 0 | F36: =IF(int=Weekly,-$D$5,IF(int=Bi_Weekly,0,IF(int=Monthly,0,IF(int=Quarterly,0,IF(int=Yearly,0,IF(int=None,0,0)))))) -> 0 | H36: =H35+F36 -> -150 | J36: =IF(D$24=0,"",ABS($F36*D$24)/D36) -> 0 | L36: =IF(D36=0,"",L35+J36) -> 5.707517 | N36: =IF(D36=0,"",L36*E36) -> 0 | O36: =-(IF(D36=0,"",N36)) -> 0 | P36: =P35+F36+O36 -> -150 | Q36: =IF(D36=0,"",ABS($O36)/D36) -> 0 | R36: =IF(D36=0,"",Q36+R35) -> 0.016276043 | S36: =IF(D36=0,"",L36+R36) -> 5.7237931 | T36: =IF(D36=0,"",D36*J36)+T35 -> 150 | U36: =IF(D36=0,"",L36*D36) -> 133.27052 | V36: =(U36/T36)-1 -> -0.11152985 | W36: =U36-T36 -> -16.729477 | X36: =ABS(O36)+X35 -> 0.46875002 | Y36: =((U36+X36)/T36)-1 -> -0.10840485 | AA36: =(D36*Q36)+(D36*J36)+AA35 -> 150.46875 | AB36: =(L36*D36)+(D36*R36) -> 133.65057 | AC36: =AB36-AA36 -> -16.818181 | AD36: =(AB36/AA36)-1 -> -0.11177192 | AF36: =F36+ABS(O36) -> 0 | AG36: =F36 -> 0 | AH36: =DATEDIF($C$31,C36,"d") -> 35 | AI36: =(AH$30-AH36)/AH$30 -> 0.99443207 | AJ36: =AI36*AF36 -> 0 | AK36: =$AI36*AG36 -> 0
B37: =IF(C36="","",IF(C$30<C37,"",B36+1)) | C37: =IF(Sheet3!A8="","",Sheet3!A8) -> 37669 | D37: =IF(C37="","",Sheet3!E8) -> 20.73 | E37: =_xlfn.XLOOKUP(WEEKNUM(C37)&YEAR(C37),Sheet4!C:C,Sheet4!B:B,0) -> 0 | F37: =IF(int=Weekly,-$D$5,IF(int=Bi_Weekly,-$D$5,IF(int=Monthly,0,IF(int=Quarterly,0,IF(int=Yearly,0,IF(int=None,0,0)))))) -> 0 | H37: =H36+F37 -> -150 | J37: =IF(D$24=0,"",ABS($F37*D$24)/D37) -> 0 | L37: =IF(D37=0,"",L36+J37) -> 5.707517 | N37: =IF(D37=0,"",L37*E37) -> 0 | O37: =-(IF(D37=0,"",N37)) -> 0 | P37: =P36+F37+O37 -> -150 | Q37: =IF(D37=0,"",ABS($O37)/D37) -> 0 | R37: =IF(D37=0,"",Q37+R36) -> 0.016276043 | S37: =IF(D37=0,"",L37+R37) -> 5.7237931 | T37: =IF(D37=0,"",D37*J37)+T36 -> 150 | U37: =IF(D37=0,"",L37*D37) -> 118.31683 | V37: =(U37/T37)-1 -> -0.21122114 | W37: =U37-T37 -> -31.683172 | X37: =ABS(O37)+X36 -> 0.46875002 | Y37: =((U37+X37)/T37)-1 -> -0.20809614 | AA37: =(D37*Q37)+(D37*J37)+AA36 -> 150.46875 | AB37: =(L37*D37)+(D37*R37) -> 118.65423 | AC37: =AB37-AA37 -> -31.814519 | AD37: =(AB37/AA37)-1 -> -0.21143606 | AF37: =F37+ABS(O37) -> 0 | AG37: =F37 -> 0 | AH37: =DATEDIF($C$31,C37,"d") -> 42 | AI37: =(AH$30-AH37)/AH$30 -> 0.99331849 | AJ37: =AI37*AF37 -> 0 | AK37: =$AI37*AG37 -> 0
B38: =IF(C37="","",IF(C$30<C38,"",B37+1)) | C38: =IF(Sheet3!A9="","",Sheet3!A9) -> 37676 | D38: =IF(C38="","",Sheet3!E9) -> 20.799999 | E38: =_xlfn.XLOOKUP(WEEKNUM(C38)&YEAR(C38),Sheet4!C:C,Sheet4!B:B,0) -> 0 | F38: =IF(int=Weekly,-$D$5,IF(int=Bi_Weekly,0,IF(int=Monthly,0,IF(int=Quarterly,0,IF(int=Yearly,0,IF(int=None,0,0)))))) -> 0 | H38: =H37+F38 -> -150 | J38: =IF(D$24=0,"",ABS($F38*D$24)/D38) -> 0 | L38: =IF(D38=0,"",L37+J38) -> 5.707517 | N38: =IF(D38=0,"",L38*E38) -> 0 | O38: =-(IF(D38=0,"",N38)) -> 0 | P38: =P37+F38+O38 -> -150 | Q38: =IF(D38=0,"",ABS($O38)/D38) -> 0 | R38: =IF(D38=0,"",Q38+R37) -> 0.016276043 | S38: =IF(D38=0,"",L38+R38) -> 5.7237931 | T38: =IF(D38=0,"",D38*J38)+T37 -> 150 | U38: =IF(D38=0,"",L38*D38) -> 118.71635 | V38: =(U38/T38)-1 -> -0.20855767 | W38: =U38-T38 -> -31.283651 | X38: =ABS(O38)+X37 -> 0.46875002 | Y38: =((U38+X38)/T38)-1 -> -0.20543267 | AA38: =(D38*Q38)+(D38*J38)+AA37 -> 150.46875 | AB38: =(L38*D38)+(D38*R38) -> 119.05489 | AC38: =AB38-AA38 -> -31.413859 | AD38: =(AB38/AA38)-1 -> -0.20877331 | AF38: =F38+ABS(O38) -> 0 | AG38: =F38 -> 0 | AH38: =DATEDIF($C$31,C38,"d") -> 49 | AI38: =(AH$30-AH38)/AH$30 -> 0.9922049 | AJ38: =AI38*AF38 -> 0 | AK38: =$AI38*AG38 -> 0
B39: =IF(C38="","",IF(C$30<C39,"",B38+1)) | C39: =IF(Sheet3!A10="","",Sheet3!A10) -> 37683 | D39: =IF(C39="","",Sheet3!E10) -> 20.49 | E39: =_xlfn.XLOOKUP(WEEKNUM(C39)&YEAR(C39),Sheet4!C:C,Sheet4!B:B,0) -> 0 | F39: =IF(int=Weekly,-$D$5,IF(int=Bi_Weekly,-$D$5,IF(int=Monthly,-$D$5,IF(int=Quarterly,0,IF(int=Yearly,0,IF(int=None,0,0)))))) -> -100 | H39: =H38+F39 -> -250 | J39: =IF(D$24=0,"",ABS($F39*D$24)/D39) -> 4.8804295 | L39: =IF(D39=0,"",L38+J39) -> 10.587947 | N39: =IF(D39=0,"",L39*E39) -> 0 | O39: =-(IF(D39=0,"",N39)) -> 0 | P39: =P38+F39+O39 -> -250 | Q39: =IF(D39=0,"",ABS($O39)/D39) -> 0 | R39: =IF(D39=0,"",Q39+R38) -> 0.016276043 | S39: =IF(D39=0,"",L39+R39) -> 10.604223 | T39: =IF(D39=0,"",D39*J39)+T38 -> 250 | U39: =IF(D39=0,"",L39*D39) -> 216.94702 | V39: =(U39/T39)-1 -> -0.1322119 | W39: =U39-T39 -> -33.052976 | X39: =ABS(O39)+X38 -> 0.46875002 | Y39: =((U39+X39)/T39)-1 -> -0.1303369 | AA39: =(D39*Q39)+(D39*J39)+AA38 -> 250.46875 | AB39: =(L39*D39)+(D39*R39) -> 217.28052 | AC39: =AB39-AA39 -> -33.18823 | AD39: =(AB39/AA39)-1 -> -0.13250447 | AF39: =F39+ABS(O39) -> -100 | AG39: =F39 -> -100 | AH39: =DATEDIF($C$31,C39,"d") -> 56 | AI39: =(AH$30-AH39)/AH$30 -> 0.99109131 | AJ39: =AI39*AF39 -> -99.109131 | AK39: =$AI39*AG39 -> -99.109131
B40: =IF(C39="","",IF(C$30<C40,"",B39+1)) | C40: =IF(Sheet3!A11="","",Sheet3!A11) -> 37690 | D40: =IF(C40="","",Sheet3!E11) -> 20.85 | E40: =_xlfn.XLOOKUP(WEEKNUM(C40)&YEAR(C40),Sheet4!C:C,Sheet4!B:B,0) -> 0 | F40: =IF(int=Weekly,-$D$5,IF(int=Bi_Weekly,0,IF(int=Monthly,0,IF(int=Quarterly,0,IF(int=Yearly,0,IF(int=None,0,0)))))) -> 0 | H40: =H39+F40 -> -250 | J40: =IF(D$24=0,"",ABS($F40*D$24)/D40) -> 0 | L40: =IF(D40=0,"",L39+J40) -> 10.587947 | N40: =IF(D40=0,"",L40*E40) -> 0 | O40: =-(IF(D40=0,"",N40)) -> 0 | P40: =P39+F40+O40 -> -250 | Q40: =IF(D40=0,"",ABS($O40)/D40) -> 0 | R40: =IF(D40=0,"",Q40+R39) -> 0.016276043 | S40: =IF(D40=0,"",L40+R40) -> 10.604223 | T40: =IF(D40=0,"",D40*J40)+T39 -> 250 | U40: =IF(D40=0,"",L40*D40) -> 220.75869 | V40: =(U40/T40)-1 -> -0.11696526 | W40: =U40-T40 -> -29.241315 | X40: =ABS(O40)+X39 -> 0.46875002 | Y40: =((U40+X40)/T40)-1 -> -0.11509026 | AA40: =(D40*Q40)+(D40*J40)+AA39 -> 250.46875 | AB40: =(L40*D40)+(D40*R40) -> 221.09804 | AC40: =AB40-AA40 -> -29.370709 | AD40: =(AB40/AA40)-1 -> -0.11726297 | AF40: =F40+ABS(O40) -> 0 | AG40: =F40 -> 0 | AH40: =DATEDIF($C$31,C40,"d") -> 63 | AI40: =(AH$30-AH40)/AH$30 -> 0.98997773 | AJ40: =AI40*AF40 -> 0 | AK40: =$AI40*AG40 -> 0
B41: =IF(C40="","",IF(C$30<C41,"",B40+1)) | C41: =IF(Sheet3!A12="","",Sheet3!A12) -> 37697 | D41: =IF(C41="","",Sheet3!E12) -> 21.639999 | E41: =_xlfn.XLOOKUP(WEEKNUM(C41)&YEAR(C41),Sheet4!C:C,Sheet4!B:B,0) -> 0 | F41: =IF(int=Weekly,-$D$5,IF(int=Bi_Weekly,-$D$5,IF(int=Monthly,0,IF(int=Quarterly,0,IF(int=Yearly,0,IF(int=None,0,0)))))) -> 0 | H41: =H40+F41 -> -250 | J41: =IF(D$24=0,"",ABS($F41*D$24)/D41) -> 0 | L41: =IF(D41=0,"",L40+J41) -> 10.587947 | N41: =IF(D41=0,"",L41*E41) -> 0 | O41: =-(IF(D41=0,"",N41)) -> 0 | P41: =P40+F41+O41 -> -250 | Q41: =IF(D41=0,"",ABS($O41)/D41) -> 0 | R41: =IF(D41=0,"",Q41+R40) -> 0.016276043 | S41: =IF(D41=0,"",L41+R41) -> 10.604223 | T41: =IF(D41=0,"",D41*J41)+T40 -> 250 | U41: =IF(D41=0,"",L41*D41) -> 229.12315 | V41: =(U41/T41)-1 -> -0.083507391 | W41: =U41-T41 -> -20.876848 | X41: =ABS(O41)+X40 -> 0.46875002 | Y41: =((U41+X41)/T41)-1 -> -0.081632391 | AA41: =(D41*Q41)+(D41*J41)+AA40 -> 250.46875 | AB41: =(L41*D41)+(D41*R41) -> 229.47537 | AC41: =AB41-AA41 -> -20.993384 | AD41: =(AB41/AA41)-1 -> -0.083816381 | AF41: =F41+ABS(O41) -> 0 | AG41: =F41 -> 0 | AH41: =DATEDIF($C$31,C41,"d") -> 70 | AI41: =(AH$30-AH41)/AH$30 -> 0.98886414 | AJ41: =AI41*AF41 -> 0 | AK41: =$AI41*AG41 -> 0
B42: =IF(C41="","",IF(C$30<C42,"",B41+1)) | C42: =IF(Sheet3!A13="","",Sheet3!A13) -> 37704 | D42: =IF(C42="","",Sheet3!E13) -> 20.24 | E42: =_xlfn.XLOOKUP(WEEKNUM(C42)&YEAR(C42),Sheet4!C:C,Sheet4!B:B,0) -> 0 | F42: =IF(int=Weekly,-$D$5,IF(int=Bi_Weekly,0,IF(int=Monthly,0,IF(int=Quarterly,0,IF(int=Yearly,0,IF(int=None,0,0)))))) -> 0 | H42: =H41+F42 -> -250 | J42: =IF(D$24=0,"",ABS($F42*D$24)/D42) -> 0 | L42: =IF(D42=0,"",L41+J42) -> 10.587947 | N42: =IF(D42=0,"",L42*E42) -> 0 | O42: =-(IF(D42=0,"",N42)) -> 0 | P42: =P41+F42+O42 -> -250 | Q42: =IF(D42=0,"",ABS($O42)/D42) -> 0 | R42: =IF(D42=0,"",Q42+R41) -> 0.016276043 | S42: =IF(D42=0,"",L42+R42) -> 10.604223 | T42: =IF(D42=0,"",D42*J42)+T41 -> 250 | U42: =IF(D42=0,"",L42*D42) -> 214.30004 | V42: =(U42/T42)-1 -> -0.14279985 | W42: =U42-T42 -> -35.699962 | X42: =ABS(O42)+X41 -> 0.46875002 | Y42: =((U42+X42)/T42)-1 -> -0.14092485 | AA42: =(D42*Q42)+(D42*J42)+AA41 -> 250.46875 | AB42: =(L42*D42)+(D42*R42) -> 214.62946 | AC42: =AB42-AA42 -> -35.839285 | AD42: =(AB42/AA42)-1 -> -0.14308885 | AF42: =F42+ABS(O42) -> 0 | AG42: =F42 -> 0 | AH42: =DATEDIF($C$31,C42,"d") -> 77 | AI42: =(AH$30-AH42)/AH$30 -> 0.98775056 | AJ42: =AI42*AF42 -> 0 | AK42: =$AI42*AG42 -> 0
B43: =IF(C42="","",IF(C$30<C43,"",B42+1)) | C43: =IF(Sheet3!A14="","",Sheet3!A14) -> 37711 | D43: =IF(C43="","",Sheet3!E14) -> 21.9 | E43: =_xlfn.XLOOKUP(WEEKNUM(C43)&YEAR(C43),Sheet4!C:C,Sheet4!B:B,0) -> 0 | F43: =IF(int=Weekly,-$D$5,IF(int=Bi_Weekly,-$D$5,IF(int=Monthly,-$D$5,IF(int=Quarterly,0,IF(int=Yearly,0,IF(int=None,0,0)))))) -> -100 | H43: =H42+F43 -> -350 | J43: =IF(D$24=0,"",ABS($F43*D$24)/D43) -> 4.56621 | L43: =IF(D43=0,"",L42+J43) -> 15.154157 | N43: =IF(D43=0,"",L43*E43) -> 0 | O43: =-(IF(D43=0,"",N43)) -> 0 | P43: =P42+F43+O43 -> -350 | Q43: =IF(D43=0,"",ABS($O43)/D43) -> 0 | R43: =IF(D43=0,"",Q43+R42) -> 0.016276043 | S43: =IF(D43=0,"",L43+R43) -> 15.170433 | T43: =IF(D43=0,"",D43*J43)+T42 -> 350 | U43: =IF(D43=0,"",L43*D43) -> 331.87603 | V43: =(U43/T43)-1 -> -0.051782774 | W43: =U43-T43 -> -18.123971 | X43: =ABS(O43)+X42 -> 0.46875002 | Y43: =((U43+X43)/T43)-1 -> -0.050443489 | AA43: =(D43*Q43)+(D43*J43)+AA42 -> 350.46875 | AB43: =(L43*D43)+(D43*R43) -> 332.23247 | AC43: =AB43-AA43 -> -18.236276 | AD43: =(AB43/AA43)-1 -> -0.052033957 | AF43: =F43+ABS(O43) -> -100 | AG43: =F43 -> -100 | AH43: =DATEDIF($C$31,C43,"d") -> 84 | AI43: =(AH$30-AH43)/AH$30 -> 0.98663697 | AJ43: =AI43*AF43 -> -98.663697 | AK43: =$AI43*AG43 -> -98.663697
B44: =IF(C43="","",IF(C$30<C44,"",B43+1)) | C44: =IF(Sheet3!A15="","",Sheet3!A15) -> 37718 | D44: =IF(C44="","",Sheet3!E15) -> 20.709999 | E44: =_xlfn.XLOOKUP(WEEKNUM(C44)&YEAR(C44),Sheet4!C:C,Sheet4!B:B,0) -> 0.2825 | F44: =IF(int=Weekly,-$D$5,IF(int=Bi_Weekly,0,IF(int=Monthly,0,IF(int=Quarterly,-$D$5,IF(int=Yearly,0,IF(int=None,0,0)))))) -> 0 | H44: =H43+F44 -> -350 | J44: =IF(D$24=0,"",ABS($F44*D$24)/D44) -> 0 | L44: =IF(D44=0,"",L43+J44) -> 15.154157 | N44: =IF(D44=0,"",L44*E44) -> 4.2810492 | O44: =-(IF(D44=0,"",N44)) -> -4.2810492 | P44: =P43+F44+O44 -> -354.28105 | Q44: =IF(D44=0,"",ABS($O44)/D44) -> 0.20671412 | R44: =IF(D44=0,"",Q44+R43) -> 0.22299016 | S44: =IF(D44=0,"",L44+R44) -> 15.377147 | T44: =IF(D44=0,"",D44*J44)+T43 -> 350 | U44: =IF(D44=0,"",L44*D44) -> 313.84257 | V44: =(U44/T44)-1 -> -0.10330695 | W44: =U44-T44 -> -36.157433 | X44: =ABS(O44)+X43 -> 4.7497992 | Y44: =((U44+X44)/T44)-1 -> -0.089736095 | AA44: =(D44*Q44)+(D44*J44)+AA43 -> 354.7498 | AB44: =(L44*D44)+(D44*R44) -> 318.46069 | AC44: =AB44-AA44 -> -36.289106 | AD44: =(AB44/AA44)-1 -> -0.10229493 | AF44: =F44+ABS(O44) -> 4.2810492 | AG44: =F44 -> 0 | AH44: =DATEDIF($C$31,C44,"d") -> 91 | AI44: =(AH$30-AH44)/AH$30 -> 0.98552339 | AJ44: =AI44*AF44 -> 4.2190741 | AK44: =$AI44*AG44 -> 0
B45: =IF(C44="","",IF(C$30<C45,"",B44+1)) | C45: =IF(Sheet3!A16="","",Sheet3!A16) -> 37725 | D45: =IF(C45="","",Sheet3!E16) -> 20.6 | E45: =_xlfn.XLOOKUP(WEEKNUM(C45)&YEAR(C45),Sheet4!C:C,Sheet4!B:B,0) -> 0 | F45: =IF(int=Weekly,-$D$5,IF(int=Bi_Weekly,-$D$5,IF(int=Monthly,0,IF(int=Quarterly,0,IF(int=Yearly,0,IF(int=None,0,0)))))) -> 0 | H45: =H44+F45 -> -350 | J45: =IF(D$24=0,"",ABS($F45*D$24)/D45) -> 0 | L45: =IF(D45=0,"",L44+J45) -> 15.154157 | N45: =IF(D45=0,"",L45*E45) -> 0 | O45: =-(IF(D45=0,"",N45)) -> 0 | P45: =P44+F45+O45 -> -354.28105 | Q45: =IF(D45=0,"",ABS($O45)/D45) -> 0 | R45: =IF(D45=0,"",Q45+R44) -> 0.22299016 | S45: =IF(D45=0,"",L45+R45) -> 15.377147 | T45: =IF(D45=0,"",D45*J45)+T44 -> 350 | U45: =IF(D45=0,"",L45*D45) -> 312.17563 | V45: =(U45/T45)-1 -> -0.10806964 | W45: =U45-T45 -> -37.824375 | X45: =ABS(O45)+X44 -> 4.7497992 | Y45: =((U45+X45)/T45)-1 -> -0.094498787 | AA45: =(D45*Q45)+(D45*J45)+AA44 -> 354.7498 | AB45: =(L45*D45)+(D45*R45) -> 316.76922 | AC45: =AB45-AA45 -> -37.980576 | AD45: =(AB45/AA45)-1 -> -0.107063 | AF45: =F45+ABS(O45) -> 0 | AG45: =F45 -> 0 | AH45: =DATEDIF($C$31,C45,"d") -> 98 | AI45: =(AH$30-AH45)/AH$30 -> 0.9844098 | AJ45: =AI45*AF45 -> 0 | AK45: =$AI45*AG45 -> 0
B46: =IF(C45="","",IF(C$30<C46,"",B45+1)) | C46: =IF(Sheet3!A17="","",Sheet3!A17) -> 37732 | D46: =IF(C46="","",Sheet3!E17) -> 22.120001 | E46: =_xlfn.XLOOKUP(WEEKNUM(C46)&YEAR(C46),Sheet4!C:C,Sheet4!B:B,0) -> 0 | F46: =IF(int=Weekly,-$D$5,IF(int=Bi_Weekly,0,IF(int=Monthly,0,IF(int=Quarterly,0,IF(int=Yearly,0,IF(int=None,0,0)))))) -> 0 | H46: =H45+F46 -> -350 | J46: =IF(D$24=0,"",ABS($F46*D$24)/D46) -> 0 | L46: =IF(D46=0,"",L45+J46) -> 15.154157 | N46: =IF(D46=0,"",L46*E46) -> 0 | O46: =-(IF(D46=0,"",N46)) -> 0 | P46: =P45+F46+O46 -> -354.28105 | Q46: =IF(D46=0,"",ABS($O46)/D46) -> 0 | R46: =IF(D46=0,"",Q46+R45) -> 0.22299016 | S46: =IF(D46=0,"",L46+R46) -> 15.377147 | T46: =IF(D46=0,"",D46*J46)+T45 -> 350 | U46: =IF(D46=0,"",L46*D46) -> 335.20996 | V46: =(U46/T46)-1 -> -0.042257261 | W46: =U46-T46 -> -14.790041 | X46: =ABS(O46)+X45 -> 4.7497992 | Y46: =((U46+X46)/T46)-1 -> -0.028686406 | AA46: =(D46*Q46)+(D46*J46)+AA45 -> 354.7498 | AB46: =(L46*D46)+(D46*R46) -> 340.1425 | AC46: =AB46-AA46 -> -14.607298 | AD46: =(AB46/AA46)-1 -> -0.041176339 | AF46: =F46+ABS(O46) -> 0 | AG46: =F46 -> 0 | AH46: =DATEDIF($C$31,C46,"d") -> 105 | AI46: =(AH$30-AH46)/AH$30 -> 0.98329621 | AJ46: =AI46*AF46 -> 0 | AK46: =$AI46*AG46 -> 0
B47: =IF(C46="","",IF(C$30<C47,"",B46+1)) | C47: =IF(Sheet3!A18="","",Sheet3!A18) -> 37739 | D47: =IF(C47="","",Sheet3!E18) -> 24.01 | E47: =_xlfn.XLOOKUP(WEEKNUM(C47)&YEAR(C47),Sheet4!C:C,Sheet4!B:B,0) -> 0 | F47: =IF(int=Weekly,-$D$5,IF(int=Bi_Weekly,-$D$5,IF(int=Monthly,-$D$5,IF(int=Quarterly,0,IF(int=Yearly,0,IF(int=None,0,0)))))) -> -100 | H47: =H46+F47 -> -450 | J47: =IF(D$24=0,"",ABS($F47*D$24)/D47) -> 4.1649313 | L47: =IF(D47=0,"",L46+J47) -> 19.319088 | N47: =IF(D47=0,"",L47*E47) -> 0 | O47: =-(IF(D47=0,"",N47)) -> 0 | P47: =P46+F47+O47 -> -454.28105 | Q47: =IF(D47=0,"",ABS($O47)/D47) -> 0 | R47: =IF(D47=0,"",Q47+R46) -> 0.22299016 | S47: =IF(D47=0,"",L47+R47) -> 19.542078 | T47: =IF(D47=0,"",D47*J47)+T46 -> 450 | U47: =IF(D47=0,"",L47*D47) -> 463.8513 | V47: =(U47/T47)-1 -> 0.030780665 | W47: =U47-T47 -> 13.851299 | X47: =ABS(O47)+X46 -> 4.7497992 | Y47: =((U47+X47)/T47)-1 -> 0.041335775 | AA47: =(D47*Q47)+(D47*J47)+AA46 -> 454.7498 | AB47: =(L47*D47)+(D47*R47) -> 469.20529 | AC47: =AB47-AA47 -> 14.455494 | AD47: =(AB47/AA47)-1 -> 0.031787796 | AF47: =F47+ABS(O47) -> -100 | AG47: =F47 -> -100 | AH47: =DATEDIF($C$31,C47,"d") -> 112 | AI47: =(AH$30-AH47)/AH$30 -> 0.98218263 | AJ47: =AI47*AF47 -> -98.218263 | AK47: =$AI47*AG47 -> -98.218263
B48: =IF(C47="","",IF(C$30<C48,"",B47+1)) | C48: =IF(Sheet3!A19="","",Sheet3!A19) -> 37746 | D48: =IF(C48="","",Sheet3!E19) -> 23.67 | E48: =_xlfn.XLOOKUP(WEEKNUM(C48)&YEAR(C48),Sheet4!C:C,Sheet4!B:B,0) -> 0 | F48: =IF(int=Weekly,-$D$5,IF(int=Bi_Weekly,0,IF(int=Monthly,0,IF(int=Quarterly,0,IF(int=Yearly,0,IF(int=None,0,0)))))) -> 0 | H48: =H47+F48 -> -450 | J48: =IF(D$24=0,"",ABS($F48*D$24)/D48) -> 0 | L48: =IF(D48=0,"",L47+J48) -> 19.319088 | N48: =IF(D48=0,"",L48*E48) -> 0 | O48: =-(IF(D48=0,"",N48)) -> 0 | P48: =P47+F48+O48 -> -454.28105 | Q48: =IF(D48=0,"",ABS($O48)/D48) -> 0 | R48: =IF(D48=0,"",Q48+R47) -> 0.22299016 | S48: =IF(D48=0,"",L48+R48) -> 19.542078 | T48: =IF(D48=0,"",D48*J48)+T47 -> 450 | U48: =IF(D48=0,"",L48*D48) -> 457.28281 | V48: =(U48/T48)-1 -> 0.016184021 | W48: =U48-T48 -> 7.2828094 | X48: =ABS(O48)+X47 -> 4.7497992 | Y48: =((U48+X48)/T48)-1 -> 0.02673913 | AA48: =(D48*Q48)+(D48*J48)+AA47 -> 454.7498 | AB48: =(L48*D48)+(D48*R48) -> 462.56099 | AC48: =AB48-AA48 -> 7.8111874 | AD48: =(AB48/AA48)-1 -> 0.01717689 | AF48: =F48+ABS(O48) -> 0 | AG48: =F48 -> 0 | AH48: =DATEDIF($C$31,C48,"d") -> 119 | AI48: =(AH$30-AH48)/AH$30 -> 0.98106904 | AJ48: =AI48*AF48 -> 0 | AK48: =$AI48*AG48 -> 0
B49: =IF(C48="","",IF(C$30<C49,"",B48+1)) | C49: =IF(Sheet3!A20="","",Sheet3!A20) -> 37753 | D49: =IF(C49="","",Sheet3!E20) -> 24.950001 | E49: =_xlfn.XLOOKUP(WEEKNUM(C49)&YEAR(C49),Sheet4!C:C,Sheet4!B:B,0) -> 0 | F49: =IF(int=Weekly,-$D$5,IF(int=Bi_Weekly,-$D$5,IF(int=Monthly,0,IF(int=Quarterly,0,IF(int=Yearly,0,IF(int=None,0,0)))))) -> 0 | H49: =H48+F49 -> -450 | J49: =IF(D$24=0,"",ABS($F49*D$24)/D49) -> 0 | L49: =IF(D49=0,"",L48+J49) -> 19.319088 | N49: =IF(D49=0,"",L49*E49) -> 0 | O49: =-(IF(D49=0,"",N49)) -> 0 | P49: =P48+F49+O49 -> -454.28105 | Q49: =IF(D49=0,"",ABS($O49)/D49) -> 0 | R49: =IF(D49=0,"",Q49+R48) -> 0.22299016 | S49: =IF(D49=0,"",L49+R49) -> 19.542078 | T49: =IF(D49=0,"",D49*J49)+T48 -> 450 | U49: =IF(D49=0,"",L49*D49) -> 482.01126 | V49: =(U49/T49)-1 -> 0.071136136 | W49: =U49-T49 -> 32.011261 | X49: =ABS(O49)+X48 -> 4.7497992 | Y49: =((U49+X49)/T49)-1 -> 0.081691245 | AA49: =(D49*Q49)+(D49*J49)+AA48 -> 454.7498 | AB49: =(L49*D49)+(D49*R49) -> 487.57487 | AC49: =AB49-AA49 -> 32.825067 | AD49: =(AB49/AA49)-1 -> 0.072182697 | AF49: =F49+ABS(O49) -> 0 | AG49: =F49 -> 0 | AH49: =DATEDIF($C$31,C49,"d") -> 126 | AI49: =(AH$30-AH49)/AH$30 -> 0.97995546 | AJ49: =AI49*AF49 -> 0 | AK49: =$AI49*AG49 -> 0
B50: =IF(C49="","",IF(C$30<C50,"",B49+1)) | C50: =IF(Sheet3!A21="","",Sheet3!A21) -> 37760 | D50: =IF(C50="","",Sheet3!E21) -> 25.15 | E50: =_xlfn.XLOOKUP(WEEKNUM(C50)&YEAR(C50),Sheet4!C:C,Sheet4!B:B,0) -> 0 | F50: =IF(int=Weekly,-$D$5,IF(int=Bi_Weekly,0,IF(int=Monthly,0,IF(int=Quarterly,0,IF(int=Yearly,0,IF(int=None,0,0)))))) -> 0 | H50: =H49+F50 -> -450 | J50: =IF(D$24=0,"",ABS($F50*D$24)/D50) -> 0 | L50: =IF(D50=0,"",L49+J50) -> 19.319088 | N50: =IF(D50=0,"",L50*E50) -> 0 | O50: =-(IF(D50=0,"",N50)) -> 0 | P50: =P49+F50+O50 -> -454.28105 | Q50: =IF(D50=0,"",ABS($O50)/D50) -> 0 | R50: =IF(D50=0,"",Q50+R49) -> 0.22299016 | S50: =IF(D50=0,"",L50+R50) -> 19.542078 | T50: =IF(D50=0,"",D50*J50)+T49 -> 450 | U50: =IF(D50=0,"",L50*D50) -> 485.87506 | V50: =(U50/T50)-1 -> 0.079722354 | W50: =U50-T50 -> 35.875059 | X50: =ABS(O50)+X49 -> 4.7497992 | Y50: =((U50+X50)/T50)-1 -> 0.090277464 | AA50: =(D50*Q50)+(D50*J50)+AA49 -> 454.7498 | AB50: =(L50*D50)+(D50*R50) -> 491.48326 | AC50: =AB50-AA50 -> 36.733463 | AD50: =(AB50/AA50)-1 -> 0.080777304 | AF50: =F50+ABS(O50) -> 0 | AG50: =F50 -> 0 | AH50: =DATEDIF($C$31,C50,"d") -> 133 | AI50: =(AH$30-AH50)/AH$30 -> 0.97884187 | AJ50: =AI50*AF50 -> 0 | AK50: =$AI50*AG50 -> 0
B51: =IF(C50="","",IF(C$30<C51,"",B50+1)) | C51: =IF(Sheet3!A22="","",Sheet3!A22) -> 37767 | D51: =IF(C51="","",Sheet3!E22) -> 25.459999 | E51: =_xlfn.XLOOKUP(WEEKNUM(C51)&YEAR(C51),Sheet4!C:C,Sheet4!B:B,0) -> 0 | F51: =IF(int=Weekly,-$D$5,IF(int=Bi_Weekly,-$D$5,IF(int=Monthly,-$D$5,IF(int=Quarterly,0,IF(int=Yearly,0,IF(int=None,0,0)))))) -> -100 | H51: =H50+F51 -> -550 | J51: =IF(D$24=0,"",ABS($F51*D$24)/D51) -> 3.9277299 | L51: =IF(D51=0,"",L50+J51) -> 23.246818 | N51: =IF(D51=0,"",L51*E51) -> 0 | O51: =-(IF(D51=0,"",N51)) -> 0 | P51: =P50+F51+O51 -> -554.28105 | Q51: =IF(D51=0,"",ABS($O51)/D51) -> 0 | R51: =IF(D51=0,"",Q51+R50) -> 0.22299016 | S51: =IF(D51=0,"",L51+R51) -> 23.469808 | T51: =IF(D51=0,"",D51*J51)+T50 -> 550 | U51: =IF(D51=0,"",L51*D51) -> 591.86396 | V51: =(U51/T51)-1 -> 0.076116286 | W51: =U51-T51 -> 41.863957 | X51: =ABS(O51)+X50 -> 4.7497992 | Y51: =((U51+X51)/T51)-1 -> 0.084752285 | AA51: =(D51*Q51)+(D51*J51)+AA50 -> 554.7498 | AB51: =(L51*D51)+(D51*R51) -> 597.54129 | AC51: =AB51-AA51 -> 42.791487 | AD51: =(AB51/AA51)-1 -> 0.077136553 | AF51: =F51+ABS(O51) -> -100 | AG51: =F51 -> -100 | AH51: =DATEDIF($C$31,C51,"d") -> 140 | AI51: =(AH$30-AH51)/AH$30 -> 0.97772829 | AJ51: =AI51*AF51 -> -97.772829 | AK51: =$AI51*AG51 -> -97.772829
B52: =IF(C51="","",IF(C$30<C52,"",B51+1)) | C52: =IF(Sheet3!A23="","",Sheet3!A23) -> 37774 | D52: =IF(C52="","",Sheet3!E23) -> 26.42 | E52: =_xlfn.XLOOKUP(WEEKNUM(C52)&YEAR(C52),Sheet4!C:C,Sheet4!B:B,0) -> 0 | F52: =IF(int=Weekly,-$D$5,IF(int=Bi_Weekly,0,IF(int=Monthly,0,IF(int=Quarterly,0,IF(int=Yearly,0,IF(int=None,0,0)))))) -> 0 | H52: =H51+F52 -> -550 | J52: =IF(D$24=0,"",ABS($F52*D$24)/D52) -> 0 | L52: =IF(D52=0,"",L51+J52) -> 23.246818 | N52: =IF(D52=0,"",L52*E52) -> 0 | O52: =-(IF(D52=0,"",N52)) -> 0 | P52: =P51+F52+O52 -> -554.28105 | Q52: =IF(D52=0,"",ABS($O52)/D52) -> 0 | R52: =IF(D52=0,"",Q52+R51) -> 0.22299016 | S52: =IF(D52=0,"",L52+R52) -> 23.469808 | T52: =IF(D52=0,"",D52*J52)+T51 -> 550 | U52: =IF(D52=0,"",L52*D52) -> 614.18093 | V52: =(U52/T52)-1 -> 0.11669259 | W52: =U52-T52 -> 64.180926 | X52: =ABS(O52)+X51 -> 4.7497992 | Y52: =((U52+X52)/T52)-1 -> 0.12532859 | AA52: =(D52*Q52)+(D52*J52)+AA51 -> 554.7498 | AB52: =(L52*D52)+(D52*R52) -> 620.07233 | AC52: =AB52-AA52 -> 65.322527 | AD52: =(AB52/AA52)-1 -> 0.11775133 | AF52: =F52+ABS(O52) -> 0 | AG52: =F52 -> 0 | AH52: =DATEDIF($C$31,C52,"d") -> 147 | AI52: =(AH$30-AH52)/AH$30 -> 0.9766147 | AJ52: =AI52*AF52 -> 0 | AK52: =$AI52*AG52 -> 0
B53: =IF(C52="","",IF(C$30<C53,"",B52+1)) | C53: =IF(Sheet3!A24="","",Sheet3!A24) -> 37781 | D53: =IF(C53="","",Sheet3!E24) -> 25.32 | E53: =_xlfn.XLOOKUP(WEEKNUM(C53)&YEAR(C53),Sheet4!C:C,Sheet4!B:B,0) -> 0 | F53: =IF(int=Weekly,-$D$5,IF(int=Bi_Weekly,-$D$5,IF(int=Monthly,0,IF(int=Quarterly,0,IF(int=Yearly,0,IF(int=None,0,0)))))) -> 0 | H53: =H52+F53 -> -550 | J53: =IF(D$24=0,"",ABS($F53*D$24)/D53) -> 0 | L53: =IF(D53=0,"",L52+J53) -> 23.246818 | N53: =IF(D53=0,"",L53*E53) -> 0 | O53: =-(IF(D53=0,"",N53)) -> 0 | P53: =P52+F53+O53 -> -554.28105 | Q53: =IF(D53=0,"",ABS($O53)/D53) -> 0 | R53: =IF(D53=0,"",Q53+R52) -> 0.22299016 | S53: =IF(D53=0,"",L53+R53) -> 23.469808 | T53: =IF(D53=0,"",D53*J53)+T52 -> 550 | U53: =IF(D53=0,"",L53*D53) -> 588.60943 | V53: =(U53/T53)-1 -> 0.070198957 | W53: =U53-T53 -> 38.609426 | X53: =ABS(O53)+X52 -> 4.7497992 | Y53: =((U53+X53)/T53)-1 -> 0.078834955 | AA53: =(D53*Q53)+(D53*J53)+AA52 -> 554.7498 | AB53: =(L53*D53)+(D53*R53) -> 594.25554 | AC53: =AB53-AA53 -> 39.505738 | AD53: =(AB53/AA53)-1 -> 0.071213614 | AF53: =F53+ABS(O53) -> 0 | AG53: =F53 -> 0 | AH53: =DATEDIF($C$31,C53,"d") -> 154 | AI53: =(AH$30-AH53)/AH$30 -> 0.97550111 | AJ53: =AI53*AF53 -> 0 | AK53: =$AI53*AG53 -> 0
B54: =IF(C53="","",IF(C$30<C54,"",B53+1)) | C54: =IF(Sheet3!A25="","",Sheet3!A25) -> 37788 | D54: =IF(C54="","",Sheet3!E25) -> 26.1 | E54: =_xlfn.XLOOKUP(WEEKNUM(C54)&YEAR(C54),Sheet4!C:C,Sheet4!B:B,0) -> 0 | F54: =IF(int=Weekly,-$D$5,IF(int=Bi_Weekly,0,IF(int=Monthly,0,IF(int=Quarterly,0,IF(int=Yearly,0,IF(int=None,0,0)))))) -> 0 | H54: =H53+F54 -> -550 | J54: =IF(D$24=0,"",ABS($F54*D$24)/D54) -> 0 | L54: =IF(D54=0,"",L53+J54) -> 23.246818 | N54: =IF(D54=0,"",L54*E54) -> 0 | O54: =-(IF(D54=0,"",N54)) -> 0 | P54: =P53+F54+O54 -> -554.28105 | Q54: =IF(D54=0,"",ABS($O54)/D54) -> 0 | R54: =IF(D54=0,"",Q54+R53) -> 0.22299016 | S54: =IF(D54=0,"",L54+R54) -> 23.469808 | T54: =IF(D54=0,"",D54*J54)+T53 -> 550 | U54: =IF(D54=0,"",L54*D54) -> 606.74194 | V54: =(U54/T54)-1 -> 0.10316717 | W54: =U54-T54 -> 56.741944 | X54: =ABS(O54)+X53 -> 4.7497992 | Y54: =((U54+X54)/T54)-1 -> 0.11180317 | AA54: =(D54*Q54)+(D54*J54)+AA53 -> 554.7498 | AB54: =(L54*D54)+(D54*R54) -> 612.56199 | AC54: =AB54-AA54 -> 57.812188 | AD54: =(AB54/AA54)-1 -> 0.10421309 | AF54: =F54+ABS(O54) -> 0 | AG54: =F54 -> 0 | AH54: =DATEDIF($C$31,C54,"d") -> 161 | AI54: =(AH$30-AH54)/AH$30 -> 0.97438753 | AJ54: =AI54*AF54 -> 0 | AK54: =$AI54*AG54 -> 0
B55: =IF(C54="","",IF(C$30<C55,"",B54+1)) | C55: =IF(Sheet3!A26="","",Sheet3!A26) -> 37795 | D55: =IF(C55="","",Sheet3!E26) -> 25.440001 | E55: =_xlfn.XLOOKUP(WEEKNUM(C55)&YEAR(C55),Sheet4!C:C,Sheet4!B:B,0) -> 0 | F55: =IF(int=Weekly,-$D$5,IF(int=Bi_Weekly,-$D$5,IF(int=Monthly,-$D$5,IF(int=Quarterly,0,IF(int=Yearly,0,IF(int=None,0,0)))))) -> -100 | H55: =H54+F55 -> -650 | J55: =IF(D$24=0,"",ABS($F55*D$24)/D55) -> 3.9308175 | L55: =IF(D55=0,"",L54+J55) -> 27.177635 | N55: =IF(D55=0,"",L55*E55) -> 0 | O55: =-(IF(D55=0,"",N55)) -> 0 | P55: =P54+F55+O55 -> -654.28105 | Q55: =IF(D55=0,"",ABS($O55)/D55) -> 0 | R55: =IF(D55=0,"",Q55+R54) -> 0.22299016 | S55: =IF(D55=0,"",L55+R55) -> 27.400625 | T55: =IF(D55=0,"",D55*J55)+T54 -> 650 | U55: =IF(D55=0,"",L55*D55) -> 691.39907 | V55: =(U55/T55)-1 -> 0.063690873 | W55: =U55-T55 -> 41.399068 | X55: =ABS(O55)+X54 -> 4.7497992 | Y55: =((U55+X55)/T55)-1 -> 0.070998257 | AA55: =(D55*Q55)+(D55*J55)+AA54 -> 654.7498 | AB55: =(L55*D55)+(D55*R55) -> 697.07194 | AC55: =AB55-AA55 -> 42.322138 | AD55: =(AB55/AA55)-1 -> 0.064638643 | AF55: =F55+ABS(O55) -> -100 | AG55: =F55 -> -100 | AH55: =DATEDIF($C$31,C55,"d") -> 168 | AI55: =(AH$30-AH55)/AH$30 -> 0.97327394 | AJ55: =AI55*AF55 -> -97.327394 | AK55: =$AI55*AG55 -> -97.327394
B56: =IF(C55="","",IF(C$30<C56,"",B55+1)) | C56: =IF(Sheet3!A27="","",Sheet3!A27) -> 37802 | D56: =IF(C56="","",Sheet3!E27) -> 26.23 | E56: =_xlfn.XLOOKUP(WEEKNUM(C56)&YEAR(C56),Sheet4!C:C,Sheet4!B:B,0) -> 0 | F56: =IF(int=Weekly,-$D$5,IF(int=Bi_Weekly,0,IF(int=Monthly,0,IF(int=Quarterly,0,IF(int=Yearly,0,IF(int=None,0,0)))))) -> 0 | H56: =H55+F56 -> -650 | J56: =IF(D$24=0,"",ABS($F56*D$24)/D56) -> 0 | L56: =IF(D56=0,"",L55+J56) -> 27.177635 | N56: =IF(D56=0,"",L56*E56) -> 0 | O56: =-(IF(D56=0,"",N56)) -> 0 | P56: =P55+F56+O56 -> -654.28105 | Q56: =IF(D56=0,"",ABS($O56)/D56) -> 0 | R56: =IF(D56=0,"",Q56+R55) -> 0.22299016 | S56: =IF(D56=0,"",L56+R56) -> 27.400625 | T56: =IF(D56=0,"",D56*J56)+T55 -> 650 | U56: =IF(D56=0,"",L56*D56) -> 712.86937 | V56: =(U56/T56)-1 -> 0.096722111 | W56: =U56-T56 -> 62.869372 | X56: =ABS(O56)+X55 -> 4.7497992 | Y56: =((U56+X56)/T56)-1 -> 0.10402949 | AA56: =(D56*Q56)+(D56*J56)+AA55 -> 654.7498 | AB56: =(L56*D56)+(D56*R56) -> 718.7184 | AC56: =AB56-AA56 -> 63.968605 | AD56: =(AB56/AA56)-1 -> 0.097699312 | AF56: =F56+ABS(O56) -> 0 | AG56: =F56 -> 0 | AH56: =DATEDIF($C$31,C56,"d") -> 175 | AI56: =(AH$30-AH56)/AH$30 -> 0.97216036 | AJ56: =AI56*AF56 -> 0 | AK56: =$AI56*AG56 -> 0
B57: =IF(C56="","",IF(C$30<C57,"",B56+1)) | C57: =IF(Sheet3!A28="","",Sheet3!A28) -> 37809 | D57: =IF(C57="","",Sheet3!E28) -> 25.41 | E57: =_xlfn.XLOOKUP(WEEKNUM(C57)&YEAR(C57),Sheet4!C:C,Sheet4!B:B,0) -> 0.2825 | F57: =IF(int=Weekly,-$D$5,IF(int=Bi_Weekly,-$D$5,IF(int=Monthly,0,IF(int=Quarterly,-$D$5,IF(int=Yearly,0,IF(int=None,0,0)))))) -> 0 | H57: =H56+F57 -> -650 | J57: =IF(D$24=0,"",ABS($F57*D$24)/D57) -> 0 | L57: =IF(D57=0,"",L56+J57) -> 27.177635 | N57: =IF(D57=0,"",L57*E57) -> 7.677682 | O57: =-(IF(D57=0,"",N57)) -> -7.677682 | P57: =P56+F57+O57 -> -661.95873 | Q57: =IF(D57=0,"",ABS($O57)/D57) -> 0.30215199 | R57: =IF(D57=0,"",Q57+R56) -> 0.52514215 | S57: =IF(D57=0,"",L57+R57) -> 27.702777 | T57: =IF(D57=0,"",D57*J57)+T56 -> 650 | U57: =IF(D57=0,"",L57*D57) -> 690.58371 | V57: =(U57/T57)-1 -> 0.062436479 | W57: =U57-T57 -> 40.583711 | X57: =ABS(O57)+X56 -> 12.427481 | Y57: =((U57+X57)/T57)-1 -> 0.081555681 | AA57: =(D57*Q57)+(D57*J57)+AA56 -> 662.42748 | AB57: =(L57*D57)+(D57*R57) -> 703.92757 | AC57: =AB57-AA57 -> 41.500092 | AD57: =(AB57/AA57)-1 -> 0.062648506 | AF57: =F57+ABS(O57) -> 7.677682 | AG57: =F57 -> 0 | AH57: =DATEDIF($C$31,C57,"d") -> 182 | AI57: =(AH$30-AH57)/AH$30 -> 0.97104677 | AJ57: =AI57*AF57 -> 7.4553883 | AK57: =$AI57*AG57 -> 0
B58: =IF(C57="","",IF(C$30<C58,"",B57+1)) | C58: =IF(Sheet3!A29="","",Sheet3!A29) -> 37816 | D58: =IF(C58="","",Sheet3!E29) -> 24.18 | E58: =_xlfn.XLOOKUP(WEEKNUM(C58)&YEAR(C58),Sheet4!C:C,Sheet4!B:B,0) -> 0 | F58: =IF(int=Weekly,-$D$5,IF(int=Bi_Weekly,0,IF(int=Monthly,0,IF(int=Quarterly,0,IF(int=Yearly,0,IF(int=None,0,0)))))) -> 0 | H58: =H57+F58 -> -650 | J58: =IF(D$24=0,"",ABS($F58*D$24)/D58) -> 0 | L58: =IF(D58=0,"",L57+J58) -> 27.177635 | N58: =IF(D58=0,"",L58*E58) -> 0 | O58: =-(IF(D58=0,"",N58)) -> 0 | P58: =P57+F58+O58 -> -661.95873 | Q58: =IF(D58=0,"",ABS($O58)/D58) -> 0 | R58: =IF(D58=0,"",Q58+R57) -> 0.52514215 | S58: =IF(D58=0,"",L58+R58) -> 27.702777 | T58: =IF(D58=0,"",D58*J58)+T57 -> 650 | U58: =IF(D58=0,"",L58*D58) -> 657.15522 | V58: =(U58/T58)-1 -> 0.011008031 | W58: =U58-T58 -> 7.1552199 | X58: =ABS(O58)+X57 -> 12.427481 | Y58: =((U58+X58)/T58)-1 -> 0.030127233 | AA58: =(D58*Q58)+(D58*J58)+AA57 -> 662.42748 | AB58: =(L58*D58)+(D58*R58) -> 669.85316 | AC58: =AB58-AA58 -> 7.4256759 | AD58: =(AB58/AA58)-1 -> 0.011209794 | AF58: =F58+ABS(O58) -> 0 | AG58: =F58 -> 0 | AH58: =DATEDIF($C$31,C58,"d") -> 189 | AI58: =(AH$30-AH58)/AH$30 -> 0.96993318 | AJ58: =AI58*AF58 -> 0 | AK58: =$AI58*AG58 -> 0
B59: =IF(C58="","",IF(C$30<C59,"",B58+1)) | C59: =IF(Sheet3!A30="","",Sheet3!A30) -> 37823 | D59: =IF(C59="","",Sheet3!E30) -> 23.540001 | E59: =_xlfn.XLOOKUP(WEEKNUM(C59)&YEAR(C59),Sheet4!C:C,Sheet4!B:B,0) -> 0 | F59: =IF(int=Weekly,-$D$5,IF(int=Bi_Weekly,-$D$5,IF(int=Monthly,-$D$5,IF(int=Quarterly,0,IF(int=Yearly,0,IF(int=None,0,0)))))) -> -100 | H59: =H58+F59 -> -750 | J59: =IF(D$24=0,"",ABS($F59*D$24)/D59) -> 4.2480882 | L59: =IF(D59=0,"",L58+J59) -> 31.425723 | N59: =IF(D59=0,"",L59*E59) -> 0 | O59: =-(IF(D59=0,"",N59)) -> 0 | P59: =P58+F59+O59 -> -761.95873 | Q59: =IF(D59=0,"",ABS($O59)/D59) -> 0 | R59: =IF(D59=0,"",Q59+R58) -> 0.52514215 | S59: =IF(D59=0,"",L59+R59) -> 31.950866 | T59: =IF(D59=0,"",D59*J59)+T58 -> 750 | U59: =IF(D59=0,"",L59*D59) -> 739.76156 | V59: =(U59/T59)-1 -> -0.013651253 | W59: =U59-T59 -> -10.238439 | X59: =ABS(O59)+X58 -> 12.427481 | Y59: =((U59+X59)/T59)-1 -> 0.0029187224 | AA59: =(D59*Q59)+(D59*J59)+AA58 -> 762.42748 | AB59: =(L59*D59)+(D59*R59) -> 752.12341 | AC59: =AB59-AA59 -> -10.304074 | AD59: =(AB59/AA59)-1 -> -0.013514825 | AF59: =F59+ABS(O59) -> -100 | AG59: =F59 -> -100 | AH59: =DATEDIF($C$31,C59,"d") -> 196 | AI59: =(AH$30-AH59)/AH$30 -> 0.9688196 | AJ59: =AI59*AF59 -> -96.88196 | AK59: =$AI59*AG59 -> -96.88196
B60: =IF(C59="","",IF(C$30<C60,"",B59+1)) | C60: =IF(Sheet3!A31="","",Sheet3!A31) -> 37830 | D60: =IF(C60="","",Sheet3!E31) -> 23.4 | E60: =_xlfn.XLOOKUP(WEEKNUM(C60)&YEAR(C60),Sheet4!C:C,Sheet4!B:B,0) -> 0 | F60: =IF(int=Weekly,-$D$5,IF(int=Bi_Weekly,0,IF(int=Monthly,0,IF(int=Quarterly,0,IF(int=Yearly,0,IF(int=None,0,0)))))) -> 0 | H60: =H59+F60 -> -750 | J60: =IF(D$24=0,"",ABS($F60*D$24)/D60) -> 0 | L60: =IF(D60=0,"",L59+J60) -> 31.425723 | N60: =IF(D60=0,"",L60*E60) -> 0 | O60: =-(IF(D60=0,"",N60)) -> 0 | P60: =P59+F60+O60 -> -761.95873 | Q60: =IF(D60=0,"",ABS($O60)/D60) -> 0 | R60: =IF(D60=0,"",Q60+R59) -> 0.52514215 | S60: =IF(D60=0,"",L60+R60) -> 31.950866 | T60: =IF(D60=0,"",D60*J60)+T59 -> 750 | U60: =IF(D60=0,"",L60*D60) -> 735.36193 | V60: =(U60/T60)-1 -> -0.01951743 | W60: =U60-T60 -> -14.638072 | X60: =ABS(O60)+X59 -> 12.427481 | Y60: =((U60+X60)/T60)-1 -> -0.0029474546 | AA60: =(D60*Q60)+(D60*J60)+AA59 -> 762.42748 | AB60: =(L60*D60)+(D60*R60) -> 747.65025 | AC60: =AB60-AA60 -> -14.777227 | AD60: =(AB60/AA60)-1 -> -0.019381813 | AF60: =F60+ABS(O60) -> 0 | AG60: =F60 -> 0 | AH60: =DATEDIF($C$31,C60,"d") -> 203 | AI60: =(AH$30-AH60)/AH$30 -> 0.96770601 | AJ60: =AI60*AF60 -> 0 | AK60: =$AI60*AG60 -> 0
B61: =IF(C60="","",IF(C$30<C61,"",B60+1)) | C61: =IF(Sheet3!A32="","",Sheet3!A32) -> 37837 | D61: =IF(C61="","",Sheet3!E32) -> 23.4 | E61: =_xlfn.XLOOKUP(WEEKNUM(C61)&YEAR(C61),Sheet4!C:C,Sheet4!B:B,0) -> 0 | F61: =IF(int=Weekly,-$D$5,IF(int=Bi_Weekly,-$D$5,IF(int=Monthly,0,IF(int=Quarterly,0,IF(int=Yearly,0,IF(int=None,0,0)))))) -> 0 | H61: =H60+F61 -> -750 | J61: =IF(D$24=0,"",ABS($F61*D$24)/D61) -> 0 | L61: =IF(D61=0,"",L60+J61) -> 31.425723 | N61: =IF(D61=0,"",L61*E61) -> 0 | O61: =-(IF(D61=0,"",N61)) -> 0 | P61: =P60+F61+O61 -> -761.95873 | Q61: =IF(D61=0,"",ABS($O61)/D61) -> 0 | R61: =IF(D61=0,"",Q61+R60) -> 0.52514215 | S61: =IF(D61=0,"",L61+R61) -> 31.950866 | T61: =IF(D61=0,"",D61*J61)+T60 -> 750 | U61: =IF(D61=0,"",L61*D61) -> 735.36193 | V61: =(U61/T61)-1 -> -0.01951743 | W61: =U61-T61 -> -14.638072 | X61: =ABS(O61)+X60 -> 12.427481 | Y61: =((U61+X61)/T61)-1 -> -0.0029474546 | AA61: =(D61*Q61)+(D61*J61)+AA60 -> 762.42748 | AB61: =(L61*D61)+(D61*R61) -> 747.65025 | AC61: =AB61-AA61 -> -14.777227 | AD61: =(AB61/AA61)-1 -> -0.019381813 | AF61: =F61+ABS(O61) -> 0 | AG61: =F61 -> 0 | AH61: =DATEDIF($C$31,C61,"d") -> 210 | AI61: =(AH$30-AH61)/AH$30 -> 0.96659243 | AJ61: =AI61*AF61 -> 0 | AK61: =$AI61*AG61 -> 0
B62: =IF(C61="","",IF(C$30<C62,"",B61+1)) | C62: =IF(Sheet3!A33="","",Sheet3!A33) -> 37844 | D62: =IF(C62="","",Sheet3!E33) -> 23.23 | E62: =_xlfn.XLOOKUP(WEEKNUM(C62)&YEAR(C62),Sheet4!C:C,Sheet4!B:B,0) -> 0 | F62: =IF(int=Weekly,-$D$5,IF(int=Bi_Weekly,0,IF(int=Monthly,0,IF(int=Quarterly,0,IF(int=Yearly,0,IF(int=None,0,0)))))) -> 0 | H62: =H61+F62 -> -750 | J62: =IF(D$24=0,"",ABS($F62*D$24)/D62) -> 0 | L62: =IF(D62=0,"",L61+J62) -> 31.425723 | N62: =IF(D62=0,"",L62*E62) -> 0 | O62: =-(IF(D62=0,"",N62)) -> 0 | P62: =P61+F62+O62 -> -761.95873 | Q62: =IF(D62=0,"",ABS($O62)/D62) -> 0 | R62: =IF(D62=0,"",Q62+R61) -> 0.52514215 | S62: =IF(D62=0,"",L62+R62) -> 31.950866 | T62: =IF(D62=0,"",D62*J62)+T61 -> 750 | U62: =IF(D62=0,"",L62*D62) -> 730.01955 | V62: =(U62/T62)-1 -> -0.026640593 | W62: =U62-T62 -> -19.980445 | X62: =ABS(O62)+X61 -> 12.427481 | Y62: =((U62+X62)/T62)-1 -> -0.010070619 | AA62: =(D62*Q62)+(D62*J62)+AA61 -> 762.42748 | AB62: =(L62*D62)+(D62*R62) -> 742.21861 | AC62: =AB62-AA62 -> -20.208874 | AD62: =(AB62/AA62)-1 -> -0.026505962 | AF62: =F62+ABS(O62) -> 0 | AG62: =F62 -> 0 | AH62: =DATEDIF($C$31,C62,"d") -> 217 | AI62: =(AH$30-AH62)/AH$30 -> 0.96547884 | AJ62: =AI62*AF62 -> 0 | AK62: =$AI62*AG62 -> 0
B63: =IF(C62="","",IF(C$30<C63,"",B62+1)) | C63: =IF(Sheet3!A34="","",Sheet3!A34) -> 37851 | D63: =IF(C63="","",Sheet3!E34) -> 23.15 | E63: =_xlfn.XLOOKUP(WEEKNUM(C63)&YEAR(C63),Sheet4!C:C,Sheet4!B:B,0) -> 0 | F63: =IF(int=Weekly,-$D$5,IF(int=Bi_Weekly,-$D$5,IF(int=Monthly,-$D$5,IF(int=Quarterly,0,IF(int=Yearly,0,IF(int=None,0,0)))))) -> -100 | H63: =H62+F63 -> -850 | J63: =IF(D$24=0,"",ABS($F63*D$24)/D63) -> 4.3196544 | L63: =IF(D63=0,"",L62+J63) -> 35.745378 | N63: =IF(D63=0,"",L63*E63) -> 0 | O63: =-(IF(D63=0,"",N63)) -> 0 | P63: =P62+F63+O63 -> -861.95873 | Q63: =IF(D63=0,"",ABS($O63)/D63) -> 0 | R63: =IF(D63=0,"",Q63+R62) -> 0.52514215 | S63: =IF(D63=0,"",L63+R63) -> 36.27052 | T63: =IF(D63=0,"",D63*J63)+T62 -> 850 | U63: =IF(D63=0,"",L63*D63) -> 827.5055 | V63: =(U63/T63)-1 -> -0.026464121 | W63: =U63-T63 -> -22.494503 | X63: =ABS(O63)+X62 -> 12.427481 | Y63: =((U63+X63)/T63)-1 -> -0.011843555 | AA63: =(D63*Q63)+(D63*J63)+AA62 -> 862.42748 | AB63: =(L63*D63)+(D63*R63) -> 839.66254 | AC63: =AB63-AA63 -> -22.764943 | AD63: =(AB63/AA63)-1 -> -0.026396357 | AF63: =F63+ABS(O63) -> -100 | AG63: =F63 -> -100 | AH63: =DATEDIF($C$31,C63,"d") -> 224 | AI63: =(AH$30-AH63)/AH$30 -> 0.96436526 | AJ63: =AI63*AF63 -> -96.436526 | AK63: =$AI63*AG63 -> -96.436526
B64: =IF(C63="","",IF(C$30<C64,"",B63+1)) | C64: =IF(Sheet3!A35="","",Sheet3!A35) -> 37858 | D64: =IF(C64="","",Sheet3!E35) -> 22.459999 | E64: =_xlfn.XLOOKUP(WEEKNUM(C64)&YEAR(C64),Sheet4!C:C,Sheet4!B:B,0) -> 0 | F64: =IF(int=Weekly,-$D$5,IF(int=Bi_Weekly,0,IF(int=Monthly,0,IF(int=Quarterly,0,IF(int=Yearly,0,IF(int=None,0,0)))))) -> 0 | H64: =H63+F64 -> -850 | J64: =IF(D$24=0,"",ABS($F64*D$24)/D64) -> 0 | L64: =IF(D64=0,"",L63+J64) -> 35.745378 | N64: =IF(D64=0,"",L64*E64) -> 0 | O64: =-(IF(D64=0,"",N64)) -> 0 | P64: =P63+F64+O64 -> -861.95873 | Q64: =IF(D64=0,"",ABS($O64)/D64) -> 0 | R64: =IF(D64=0,"",Q64+R63) -> 0.52514215 | S64: =IF(D64=0,"",L64+R64) -> 36.27052 | T64: =IF(D64=0,"",D64*J64)+T63 -> 850 | U64: =IF(D64=0,"",L64*D64) -> 802.84115 | V64: =(U64/T64)-1 -> -0.055480999 | W64: =U64-T64 -> -47.158849 | X64: =ABS(O64)+X63 -> 12.427481 | Y64: =((U64+X64)/T64)-1 -> -0.040860433 | AA64: =(D64*Q64)+(D64*J64)+AA63 -> 862.42748 | AB64: =(L64*D64)+(D64*R64) -> 814.63584 | AC64: =AB64-AA64 -> -47.791639 | AD64: =(AB64/AA64)-1 -> -0.055415255 | AF64: =F64+ABS(O64) -> 0 | AG64: =F64 -> 0 | AH64: =DATEDIF($C$31,C64,"d") -> 231 | AI64: =(AH$30-AH64)/AH$30 -> 0.96325167 | AJ64: =AI64*AF64 -> 0 | AK64: =$AI64*AG64 -> 0
B65: =IF(C64="","",IF(C$30<C65,"",B64+1)) | C65: =IF(Sheet3!A36="","",Sheet3!A36) -> 37865 | D65: =IF(C65="","",Sheet3!E36) -> 23 | E65: =_xlfn.XLOOKUP(WEEKNUM(C65)&YEAR(C65),Sheet4!C:C,Sheet4!B:B,0) -> 0 | F65: =IF(int=Weekly,-$D$5,IF(int=Bi_Weekly,-$D$5,IF(int=Monthly,0,IF(int=Quarterly,0,IF(int=Yearly,0,IF(int=None,0,0)))))) -> 0 | H65: =H64+F65 -> -850 | J65: =IF(D$24=0,"",ABS($F65*D$24)/D65) -> 0 | L65: =IF(D65=0,"",L64+J65) -> 35.745378 | N65: =IF(D65=0,"",L65*E65) -> 0 | O65: =-(IF(D65=0,"",N65)) -> 0 | P65: =P64+F65+O65 -> -861.95873 | Q65: =IF(D65=0,"",ABS($O65)/D65) -> 0 | R65: =IF(D65=0,"",Q65+R64) -> 0.52514215 | S65: =IF(D65=0,"",L65+R65) -> 36.27052 | T65: =IF(D65=0,"",D65*J65)+T64 -> 850 | U65: =IF(D65=0,"",L65*D65) -> 822.14369 | V65: =(U65/T65)-1 -> -0.032772129 | W65: =U65-T65 -> -27.85631 | X65: =ABS(O65)+X64 -> 12.427481 | Y65: =((U65+X65)/T65)-1 -> -0.018151563 | AA65: =(D65*Q65)+(D65*J65)+AA64 -> 862.42748 | AB65: =(L65*D65)+(D65*R65) -> 834.22196 | AC65: =AB65-AA65 -> -28.205521 | AD65: =(AB65/AA65)-1 -> -0.032704804 | AF65: =F65+ABS(O65) -> 0 | AG65: =F65 -> 0 | AH65: =DATEDIF($C$31,C65,"d") -> 238 | AI65: =(AH$30-AH65)/AH$30 -> 0.96213808 | AJ65: =AI65*AF65 -> 0 | AK65: =$AI65*AG65 -> 0
B66: =IF(C65="","",IF(C$30<C66,"",B65+1)) | C66: =IF(Sheet3!A37="","",Sheet3!A37) -> 37872 | D66: =IF(C66="","",Sheet3!E37) -> 23.43 | E66: =_xlfn.XLOOKUP(WEEKNUM(C66)&YEAR(C66),Sheet4!C:C,Sheet4!B:B,0) -> 0 | F66: =IF(int=Weekly,-$D$5,IF(int=Bi_Weekly,0,IF(int=Monthly,0,IF(int=Quarterly,0,IF(int=Yearly,0,IF(int=None,0,0)))))) -> 0 | H66: =H65+F66 -> -850 | J66: =IF(D$24=0,"",ABS($F66*D$24)/D66) -> 0 | L66: =IF(D66=0,"",L65+J66) -> 35.745378 | N66: =IF(D66=0,"",L66*E66) -> 0 | O66: =-(IF(D66=0,"",N66)) -> 0 | P66: =P65+F66+O66 -> -861.95873 | Q66: =IF(D66=0,"",ABS($O66)/D66) -> 0 | R66: =IF(D66=0,"",Q66+R65) -> 0.52514215 | S66: =IF(D66=0,"",L66+R66) -> 36.27052 | T66: =IF(D66=0,"",D66*J66)+T65 -> 850 | U66: =IF(D66=0,"",L66*D66) -> 837.5142 | V66: =(U66/T66)-1 -> -0.014689173 | W66: =U66-T66 -> -12.485797 | X66: =ABS(O66)+X65 -> 12.427481 | Y66: =((U66+X66)/T66)-1 -> -6.8607051e-05 | AA66: =(D66*Q66)+(D66*J66)+AA65 -> 862.42748 | AB66: =(L66*D66)+(D66*R66) -> 849.81828 | AC66: =AB66-AA66 -> -12.609198 | AD66: =(AB66/AA66)-1 -> -0.014620589 | AF66: =F66+ABS(O66) -> 0 | AG66: =F66 -> 0 | AH66: =DATEDIF($C$31,C66,"d") -> 245 | AI66: =(AH$30-AH66)/AH$30 -> 0.9610245 | AJ66: =AI66*AF66 -> 0 | AK66: =$AI66*AG66 -> 0
B67: =IF(C66="","",IF(C$30<C67,"",B66+1)) | C67: =IF(Sheet3!A38="","",Sheet3!A38) -> 37879 | D67: =IF(C67="","",Sheet3!E38) -> 23.860001 | E67: =_xlfn.XLOOKUP(WEEKNUM(C67)&YEAR(C67),Sheet4!C:C,Sheet4!B:B,0) -> 0 | F67: =IF(int=Weekly,-$D$5,IF(int=Bi_Weekly,-$D$5,IF(int=Monthly,-$D$5,IF(int=Quarterly,0,IF(int=Yearly,0,IF(int=None,0,0)))))) -> -100 | H67: =H66+F67 -> -950 | J67: =IF(D$24=0,"",ABS($F67*D$24)/D67) -> 4.1911147 | L67: =IF(D67=0,"",L66+J67) -> 39.936493 | N67: =IF(D67=0,"",L67*E67) -> 0 | O67: =-(IF(D67=0,"",N67)) -> 0 | P67: =P66+F67+O67 -> -961.95873 | Q67: =IF(D67=0,"",ABS($O67)/D67) -> 0 | R67: =IF(D67=0,"",Q67+R66) -> 0.52514215 | S67: =IF(D67=0,"",L67+R67) -> 40.461635 | T67: =IF(D67=0,"",D67*J67)+T66 -> 950 | U67: =IF(D67=0,"",L67*D67) -> 952.88475 | V67: =(U67/T67)-1 -> 0.00303658 | W67: =U67-T67 -> 2.884751 | X67: =ABS(O67)+X66 -> 12.427481 | Y67: =((U67+X67)/T67)-1 -> 0.016118139 | AA67: =(D67*Q67)+(D67*J67)+AA66 -> 962.42748 | AB67: =(L67*D67)+(D67*R67) -> 965.41464 | AC67: =AB67-AA67 -> 2.987162 | AD67: =(AB67/AA67)-1 -> 0.0031037788 | AF67: =F67+ABS(O67) -> -100 | AG67: =F67 -> -100 | AH67: =DATEDIF($C$31,C67,"d") -> 252 | AI67: =(AH$30-AH67)/AH$30 -> 0.95991091 | AJ67: =AI67*AF67 -> -95.991091 | AK67: =$AI67*AG67 -> -95.991091
B68: =IF(C67="","",IF(C$30<C68,"",B67+1)) | C68: =IF(Sheet3!A39="","",Sheet3!A39) -> 37886 | D68: =IF(C68="","",Sheet3!E39) -> 21.82 | E68: =_xlfn.XLOOKUP(WEEKNUM(C68)&YEAR(C68),Sheet4!C:C,Sheet4!B:B,0) -> 0 | F68: =IF(int=Weekly,-$D$5,IF(int=Bi_Weekly,0,IF(int=Monthly,0,IF(int=Quarterly,0,IF(int=Yearly,0,IF(int=None,0,0)))))) -> 0 | H68: =H67+F68 -> -950 | J68: =IF(D$24=0,"",ABS($F68*D$24)/D68) -> 0 | L68: =IF(D68=0,"",L67+J68) -> 39.936493 | N68: =IF(D68=0,"",L68*E68) -> 0 | O68: =-(IF(D68=0,"",N68)) -> 0 | P68: =P67+F68+O68 -> -961.95873 | Q68: =IF(D68=0,"",ABS($O68)/D68) -> 0 | R68: =IF(D68=0,"",Q68+R67) -> 0.52514215 | S68: =IF(D68=0,"",L68+R68) -> 40.461635 | T68: =IF(D68=0,"",D68*J68)+T67 -> 950 | U68: =IF(D68=0,"",L68*D68) -> 871.41427 | V68: =(U68/T68)-1 -> -0.082721825 | W68: =U68-T68 -> -78.585734 | X68: =ABS(O68)+X67 -> 12.427481 | Y68: =((U68+X68)/T68)-1 -> -0.069640266 | AA68: =(D68*Q68)+(D68*J68)+AA67 -> 962.42748 | AB68: =(L68*D68)+(D68*R68) -> 882.87287 | AC68: =AB68-AA68 -> -79.554613 | AD68: =(AB68/AA68)-1 -> -0.082660371 | AF68: =F68+ABS(O68) -> 0 | AG68: =F68 -> 0 | AH68: =DATEDIF($C$31,C68,"d") -> 259 | AI68: =(AH$30-AH68)/AH$30 -> 0.95879733 | AJ68: =AI68*AF68 -> 0 | AK68: =$AI68*AG68 -> 0
B69: =IF(C68="","",IF(C$30<C69,"",B68+1)) | C69: =IF(Sheet3!A40="","",Sheet3!A40) -> 37893 | D69: =IF(C69="","",Sheet3!E40) -> 22.610001 | E69: =_xlfn.XLOOKUP(WEEKNUM(C69)&YEAR(C69),Sheet4!C:C,Sheet4!B:B,0) -> 0 | F69: =IF(int=Weekly,-$D$5,IF(int=Bi_Weekly,-$D$5,IF(int=Monthly,0,IF(int=Quarterly,0,IF(int=Yearly,0,IF(int=None,0,0)))))) -> 0 | H69: =H68+F69 -> -950 | J69: =IF(D$24=0,"",ABS($F69*D$24)/D69) -> 0 | L69: =IF(D69=0,"",L68+J69) -> 39.936493 | N69: =IF(D69=0,"",L69*E69) -> 0 | O69: =-(IF(D69=0,"",N69)) -> 0 | P69: =P68+F69+O69 -> -961.95873 | Q69: =IF(D69=0,"",ABS($O69)/D69) -> 0 | R69: =IF(D69=0,"",Q69+R68) -> 0.52514215 | S69: =IF(D69=0,"",L69+R69) -> 40.461635 | T69: =IF(D69=0,"",D69*J69)+T68 -> 950 | U69: =IF(D69=0,"",L69*D69) -> 902.96414 | V69: =(U69/T69)-1 -> -0.049511436 | W69: =U69-T69 -> -47.035865 | X69: =ABS(O69)+X68 -> 12.427481 | Y69: =((U69+X69)/T69)-1 -> -0.036429877 | AA69: =(D69*Q69)+(D69*J69)+AA68 -> 962.42748 | AB69: =(L69*D69)+(D69*R69) -> 914.8376 | AC69: =AB69-AA69 -> -47.589881 | AD69: =(AB69/AA69)-1 -> -0.049447758 | AF69: =F69+ABS(O69) -> 0 | AG69: =F69 -> 0 | AH69: =DATEDIF($C$31,C69,"d") -> 266 | AI69: =(AH$30-AH69)/AH$30 -> 0.95768374 | AJ69: =AI69*AF69 -> 0 | AK69: =$AI69*AG69 -> 0
B70: =IF(C69="","",IF(C$30<C70,"",B69+1)) | C70: =IF(Sheet3!A41="","",Sheet3!A41) -> 37900 | D70: =IF(C70="","",Sheet3!E41) -> 21.950001 | E70: =_xlfn.XLOOKUP(WEEKNUM(C70)&YEAR(C70),Sheet4!C:C,Sheet4!B:B,0) -> 0.2825 | F70: =IF(int=Weekly,-$D$5,IF(int=Bi_Weekly,0,IF(int=Monthly,0,IF(int=Quarterly,-$D$5,IF(int=Yearly,0,IF(int=None,0,0)))))) -> 0 | H70: =H69+F70 -> -950 | J70: =IF(D$24=0,"",ABS($F70*D$24)/D70) -> 0 | L70: =IF(D70=0,"",L69+J70) -> 39.936493 | N70: =IF(D70=0,"",L70*E70) -> 11.282059 | O70: =-(IF(D70=0,"",N70)) -> -11.282059 | P70: =P69+F70+O70 -> -973.24079 | Q70: =IF(D70=0,"",ABS($O70)/D70) -> 0.513989 | R70: =IF(D70=0,"",Q70+R69) -> 1.0391312 | S70: =IF(D70=0,"",L70+R70) -> 40.975624 | T70: =IF(D70=0,"",D70*J70)+T69 -> 950 | U70: =IF(D70=0,"",L70*D70) -> 876.60605 | V70: =(U70/T70)-1 -> -0.077256789 | W70: =U70-T70 -> -73.39395 | X70: =ABS(O70)+X69 -> 23.70954 | Y70: =((U70+X70)/T70)-1 -> -0.052299378 | AA70: =(D70*Q70)+(D70*J70)+AA69 -> 973.70954 | AB70: =(L70*D70)+(D70*R70) -> 899.41498 | AC70: =AB70-AA70 -> -74.29456 | AD70: =(AB70/AA70)-1 -> -0.076300536 | AF70: =F70+ABS(O70) -> 11.282059 | AG70: =F70 -> 0 | AH70: =DATEDIF($C$31,C70,"d") -> 273 | AI70: =(AH$30-AH70)/AH$30 -> 0.95657016 | AJ70: =AI70*AF70 -> 10.792081 | AK70: =$AI70*AG70 -> 0
B71: =IF(C70="","",IF(C$30<C71,"",B70+1)) | C71: =IF(Sheet3!A42="","",Sheet3!A42) -> 37907 | D71: =IF(C71="","",Sheet3!E42) -> 22 | E71: =_xlfn.XLOOKUP(WEEKNUM(C71)&YEAR(C71),Sheet4!C:C,Sheet4!B:B,0) -> 0 | F71: =IF(int=Weekly,-$D$5,IF(int=Bi_Weekly,-$D$5,IF(int=Monthly,-$D$5,IF(int=Quarterly,0,IF(int=Yearly,0,IF(int=None,0,0)))))) -> -100 | H71: =H70+F71 -> -1050 | J71: =IF(D$24=0,"",ABS($F71*D$24)/D71) -> 4.5454545 | L71: =IF(D71=0,"",L70+J71) -> 44.481947 | N71: =IF(D71=0,"",L71*E71) -> 0 | O71: =-(IF(D71=0,"",N71)) -> 0 | P71: =P70+F71+O71 -> -1073.2408 | Q71: =IF(D71=0,"",ABS($O71)/D71) -> 0 | R71: =IF(D71=0,"",Q71+R70) -> 1.0391312 | S71: =IF(D71=0,"",L71+R71) -> 45.521078 | T71: =IF(D71=0,"",D71*J71)+T70 -> 1050 | U71: =IF(D71=0,"",L71*D71) -> 978.60284 | V71: =(U71/T71)-1 -> -0.0679973 | W71: =U71-T71 -> -71.397165 | X71: =ABS(O71)+X70 -> 23.70954 | Y71: =((U71+X71)/T71)-1 -> -0.045416785 | AA71: =(D71*Q71)+(D71*J71)+AA70 -> 1073.7095 | AB71: =(L71*D71)+(D71*R71) -> 1001.4637 | AC71: =AB71-AA71 -> -72.24582 | AD71: =(AB71/AA71)-1 -> -0.067286186 | AF71: =F71+ABS(O71) -> -100 | AG71: =F71 -> -100 | AH71: =DATEDIF($C$31,C71,"d") -> 280 | AI71: =(AH$30-AH71)/AH$30 -> 0.95545657 | AJ71: =AI71*AF71 -> -95.545657 | AK71: =$AI71*AG71 -> -95.545657
B72: =IF(C71="","",IF(C$30<C72,"",B71+1)) | C72: =IF(Sheet3!A43="","",Sheet3!A43) -> 37914 | D72: =IF(C72="","",Sheet3!E43) -> 22.940001 | E72: =_xlfn.XLOOKUP(WEEKNUM(C72)&YEAR(C72),Sheet4!C:C,Sheet4!B:B,0) -> 0 | F72: =IF(int=Weekly,-$D$5,IF(int=Bi_Weekly,0,IF(int=Monthly,0,IF(int=Quarterly,0,IF(int=Yearly,0,IF(int=None,0,0)))))) -> 0 | H72: =H71+F72 -> -1050 | J72: =IF(D$24=0,"",ABS($F72*D$24)/D72) -> 0 | L72: =IF(D72=0,"",L71+J72) -> 44.481947 | N72: =IF(D72=0,"",L72*E72) -> 0 | O72: =-(IF(D72=0,"",N72)) -> 0 | P72: =P71+F72+O72 -> -1073.2408 | Q72: =IF(D72=0,"",ABS($O72)/D72) -> 0 | R72: =IF(D72=0,"",Q72+R71) -> 1.0391312 | S72: =IF(D72=0,"",L72+R72) -> 45.521078 | T72: =IF(D72=0,"",D72*J72)+T71 -> 1050 | U72: =IF(D72=0,"",L72*D72) -> 1020.4159 | V72: =(U72/T72)-1 -> -0.028175324 | W72: =U72-T72 -> -29.58409 | X72: =ABS(O72)+X71 -> 23.70954 | Y72: =((U72+X72)/T72)-1 -> -0.0055948095 | AA72: =(D72*Q72)+(D72*J72)+AA71 -> 1073.7095 | AB72: =(L72*D72)+(D72*R72) -> 1044.2536 | AC72: =AB72-AA72 -> -29.455961 | AD72: =(AB72/AA72)-1 -> -0.027433826 | AF72: =F72+ABS(O72) -> 0 | AG72: =F72 -> 0 | AH72: =DATEDIF($C$31,C72,"d") -> 287 | AI72: =(AH$30-AH72)/AH$30 -> 0.95434298 | AJ72: =AI72*AF72 -> 0 | AK72: =$AI72*AG72 -> 0
B73: =IF(C72="","",IF(C$30<C73,"",B72+1)) | C73: =IF(Sheet3!A44="","",Sheet3!A44) -> 37921 | D73: =IF(C73="","",Sheet3!E44) -> 23.98 | E73: =_xlfn.XLOOKUP(WEEKNUM(C73)&YEAR(C73),Sheet4!C:C,Sheet4!B:B,0) -> 0 | F73: =IF(int=Weekly,-$D$5,IF(int=Bi_Weekly,-$D$5,IF(int=Monthly,0,IF(int=Quarterly,0,IF(int=Yearly,0,IF(int=None,0,0)))))) -> 0 | H73: =H72+F73 -> -1050 | J73: =IF(D$24=0,"",ABS($F73*D$24)/D73) -> 0 | L73: =IF(D73=0,"",L72+J73) -> 44.481947 | N73: =IF(D73=0,"",L73*E73) -> 0 | O73: =-(IF(D73=0,"",N73)) -> 0 | P73: =P72+F73+O73 -> -1073.2408 | Q73: =IF(D73=0,"",ABS($O73)/D73) -> 0 | R73: =IF(D73=0,"",Q73+R72) -> 1.0391312 | S73: =IF(D73=0,"",L73+R73) -> 45.521078 | T73: =IF(D73=0,"",D73*J73)+T72 -> 1050 | U73: =IF(D73=0,"",L73*D73) -> 1066.6771 | V73: =(U73/T73)-1 -> 0.015882943 | W73: =U73-T73 -> 16.67709 | X73: =ABS(O73)+X72 -> 23.70954 | Y73: =((U73+X73)/T73)-1 -> 0.038463458 | AA73: =(D73*Q73)+(D73*J73)+AA72 -> 1073.7095 | AB73: =(L73*D73)+(D73*R73) -> 1091.5955 | AC73: =AB73-AA73 -> 17.885915 | AD73: =(AB73/AA73)-1 -> 0.016658057 | AF73: =F73+ABS(O73) -> 0 | AG73: =F73 -> 0 | AH73: =DATEDIF($C$31,C73,"d") -> 294 | AI73: =(AH$30-AH73)/AH$30 -> 0.9532294 | AJ73: =AI73*AF73 -> 0 | AK73: =$AI73*AG73 -> 0
B74: =IF(C73="","",IF(C$30<C74,"",B73+1)) | C74: =IF(Sheet3!A45="","",Sheet3!A45) -> 37928 | D74: =IF(C74="","",Sheet3!E45) -> 22.959999 | E74: =_xlfn.XLOOKUP(WEEKNUM(C74)&YEAR(C74),Sheet4!C:C,Sheet4!B:B,0) -> 0 | F74: =IF(int=Weekly,-$D$5,IF(int=Bi_Weekly,0,IF(int=Monthly,0,IF(int=Quarterly,0,IF(int=Yearly,0,IF(int=None,0,0)))))) -> 0 | H74: =H73+F74 -> -1050 | J74: =IF(D$24=0,"",ABS($F74*D$24)/D74) -> 0 | L74: =IF(D74=0,"",L73+J74) -> 44.481947 | N74: =IF(D74=0,"",L74*E74) -> 0 | O74: =-(IF(D74=0,"",N74)) -> 0 | P74: =P73+F74+O74 -> -1073.2408 | Q74: =IF(D74=0,"",ABS($O74)/D74) -> 0 | R74: =IF(D74=0,"",Q74+R73) -> 1.0391312 | S74: =IF(D74=0,"",L74+R74) -> 45.521078 | T74: =IF(D74=0,"",D74*J74)+T73 -> 1050 | U74: =IF(D74=0,"",L74*D74) -> 1021.3055 | V74: =(U74/T74)-1 -> -0.027328134 | W74: =U74-T74 -> -28.69454 | X74: =ABS(O74)+X73 -> 23.70954 | Y74: =((U74+X74)/T74)-1 -> -0.004747619 | AA74: =(D74*Q74)+(D74*J74)+AA73 -> 1073.7095 | AB74: =(L74*D74)+(D74*R74) -> 1045.1639 | AC74: =AB74-AA74 -> -28.54563 | AD74: =(AB74/AA74)-1 -> -0.026585989 | AF74: =F74+ABS(O74) -> 0 | AG74: =F74 -> 0 | AH74: =DATEDIF($C$31,C74,"d") -> 301 | AI74: =(AH$30-AH74)/AH$30 -> 0.95211581 | AJ74: =AI74*AF74 -> 0 | AK74: =$AI74*AG74 -> 0
B75: =IF(C74="","",IF(C$30<C75,"",B74+1)) | C75: =IF(Sheet3!A46="","",Sheet3!A46) -> 37935 | D75: =IF(C75="","",Sheet3!E46) -> 23.610001 | E75: =_xlfn.XLOOKUP(WEEKNUM(C75)&YEAR(C75),Sheet4!C:C,Sheet4!B:B,0) -> 0 | F75: =IF(int=Weekly,-$D$5,IF(int=Bi_Weekly,-$D$5,IF(int=Monthly,-$D$5,IF(int=Quarterly,0,IF(int=Yearly,0,IF(int=None,0,0)))))) -> -100 | H75: =H74+F75 -> -1150 | J75: =IF(D$24=0,"",ABS($F75*D$24)/D75) -> 4.2354933 | L75: =IF(D75=0,"",L74+J75) -> 48.71744 | N75: =IF(D75=0,"",L75*E75) -> 0 | O75: =-(IF(D75=0,"",N75)) -> 0 | P75: =P74+F75+O75 -> -1173.2408 | Q75: =IF(D75=0,"",ABS($O75)/D75) -> 0 | R75: =IF(D75=0,"",Q75+R74) -> 1.0391312 | S75: =IF(D75=0,"",L75+R75) -> 49.756571 | T75: =IF(D75=0,"",D75*J75)+T74 -> 1150 | U75: =IF(D75=0,"",L75*D75) -> 1150.2188 | V75: =(U75/T75)-1 -> 0.00019027327 | W75: =U75-T75 -> 0.21881426 | X75: =ABS(O75)+X74 -> 23.70954 | Y75: =((U75+X75)/T75)-1 -> 0.020807265 | AA75: =(D75*Q75)+(D75*J75)+AA74 -> 1173.7095 | AB75: =(L75*D75)+(D75*R75) -> 1174.7527 | AC75: =AB75-AA75 -> 1.0431615 | AD75: =(AB75/AA75)-1 -> 0.0008887731 | AF75: =F75+ABS(O75) -> -100 | AG75: =F75 -> -100 | AH75: =DATEDIF($C$31,C75,"d") -> 308 | AI75: =(AH$30-AH75)/AH$30 -> 0.95100223 | AJ75: =AI75*AF75 -> -95.100223 | AK75: =$AI75*AG75 -> -95.100223
B76: =IF(C75="","",IF(C$30<C76,"",B75+1)) | C76: =IF(Sheet3!A47="","",Sheet3!A47) -> 37942 | D76: =IF(C76="","",Sheet3!E47) -> 23.030001 | E76: =_xlfn.XLOOKUP(WEEKNUM(C76)&YEAR(C76),Sheet4!C:C,Sheet4!B:B,0) -> 0 | F76: =IF(int=Weekly,-$D$5,IF(int=Bi_Weekly,0,IF(int=Monthly,0,IF(int=Quarterly,0,IF(int=Yearly,0,IF(int=None,0,0)))))) -> 0 | H76: =H75+F76 -> -1150 | J76: =IF(D$24=0,"",ABS($F76*D$24)/D76) -> 0 | L76: =IF(D76=0,"",L75+J76) -> 48.71744 | N76: =IF(D76=0,"",L76*E76) -> 0 | O76: =-(IF(D76=0,"",N76)) -> 0 | P76: =P75+F76+O76 -> -1173.2408 | Q76: =IF(D76=0,"",ABS($O76)/D76) -> 0 | R76: =IF(D76=0,"",Q76+R75) -> 1.0391312 | S76: =IF(D76=0,"",L76+R76) -> 49.756571 | T76: =IF(D76=0,"",D76*J76)+T75 -> 1150 | U76: =IF(D76=0,"",L76*D76) -> 1121.9627 | V76: =(U76/T76)-1 -> -0.024380262 | W76: =U76-T76 -> -28.037301 | X76: =ABS(O76)+X75 -> 23.70954 | Y76: =((U76+X76)/T76)-1 -> -0.0037632702 | AA76: =(D76*Q76)+(D76*J76)+AA75 -> 1173.7095 | AB76: =(L76*D76)+(D76*R76) -> 1145.8939 | AC76: =AB76-AA76 -> -27.81565 | AD76: =(AB76/AA76)-1 -> -0.023698921 | AF76: =F76+ABS(O76) -> 0 | AG76: =F76 -> 0 | AH76: =DATEDIF($C$31,C76,"d") -> 315 | AI76: =(AH$30-AH76)/AH$30 -> 0.94988864 | AJ76: =AI76*AF76 -> 0 | AK76: =$AI76*AG76 -> 0
B77: =IF(C76="","",IF(C$30<C77,"",B76+1)) | C77: =IF(Sheet3!A48="","",Sheet3!A48) -> 37949 | D77: =IF(C77="","",Sheet3!E48) -> 23.280001 | E77: =_xlfn.XLOOKUP(WEEKNUM(C77)&YEAR(C77),Sheet4!C:C,Sheet4!B:B,0) -> 0 | F77: =IF(int=Weekly,-$D$5,IF(int=Bi_Weekly,-$D$5,IF(int=Monthly,0,IF(int=Quarterly,0,IF(int=Yearly,0,IF(int=None,0,0)))))) -> 0 | H77: =H76+F77 -> -1150 | J77: =IF(D$24=0,"",ABS($F77*D$24)/D77) -> 0 | L77: =IF(D77=0,"",L76+J77) -> 48.71744 | N77: =IF(D77=0,"",L77*E77) -> 0 | O77: =-(IF(D77=0,"",N77)) -> 0 | P77: =P76+F77+O77 -> -1173.2408 | Q77: =IF(D77=0,"",ABS($O77)/D77) -> 0 | R77: =IF(D77=0,"",Q77+R76) -> 1.0391312 | S77: =IF(D77=0,"",L77+R77) -> 49.756571 | T77: =IF(D77=0,"",D77*J77)+T76 -> 1150 | U77: =IF(D77=0,"",L77*D77) -> 1134.1421 | V77: =(U77/T77)-1 -> -0.013789514 | W77: =U77-T77 -> -15.857941 | X77: =ABS(O77)+X76 -> 23.70954 | Y77: =((U77+X77)/T77)-1 -> 0.0068274776 | AA77: =(D77*Q77)+(D77*J77)+AA76 -> 1173.7095 | AB77: =(L77*D77)+(D77*R77) -> 1158.333 | AC77: =AB77-AA77 -> -15.376507 | AD77: =(AB77/AA77)-1 -> -0.013100777 | AF77: =F77+ABS(O77) -> 0 | AG77: =F77 -> 0 | AH77: =DATEDIF($C$31,C77,"d") -> 322 | AI77: =(AH$30-AH77)/AH$30 -> 0.94877506 | AJ77: =AI77*AF77 -> 0 | AK77: =$AI77*AG77 -> 0
B78: =IF(C77="","",IF(C$30<C78,"",B77+1)) | C78: =IF(Sheet3!A49="","",Sheet3!A49) -> 37956 | D78: =IF(C78="","",Sheet3!E49) -> 24.389999 | E78: =_xlfn.XLOOKUP(WEEKNUM(C78)&YEAR(C78),Sheet4!C:C,Sheet4!B:B,0) -> 0 | F78: =IF(int=Weekly,-$D$5,IF(int=Bi_Weekly,0,IF(int=Monthly,0,IF(int=Quarterly,0,IF(int=Yearly,0,IF(int=None,0,0)))))) -> 0 | H78: =H77+F78 -> -1150 | J78: =IF(D$24=0,"",ABS($F78*D$24)/D78) -> 0 | L78: =IF(D78=0,"",L77+J78) -> 48.71744 | N78: =IF(D78=0,"",L78*E78) -> 0 | O78: =-(IF(D78=0,"",N78)) -> 0 | P78: =P77+F78+O78 -> -1173.2408 | Q78: =IF(D78=0,"",ABS($O78)/D78) -> 0 | R78: =IF(D78=0,"",Q78+R77) -> 1.0391312 | S78: =IF(D78=0,"",L78+R78) -> 49.756571 | T78: =IF(D78=0,"",D78*J78)+T77 -> 1150 | U78: =IF(D78=0,"",L78*D78) -> 1188.2183 | V78: =(U78/T78)-1 -> 0.033233322 | W78: =U78-T78 -> 38.21832 | X78: =ABS(O78)+X77 -> 23.70954 | Y78: =((U78+X78)/T78)-1 -> 0.053850314 | AA78: =(D78*Q78)+(D78*J78)+AA77 -> 1173.7095 | AB78: =(L78*D78)+(D78*R78) -> 1213.5627 | AC78: =AB78-AA78 -> 39.853188 | AD78: =(AB78/AA78)-1 -> 0.033954898 | AF78: =F78+ABS(O78) -> 0 | AG78: =F78 -> 0 | AH78: =DATEDIF($C$31,C78,"d") -> 329 | AI78: =(AH$30-AH78)/AH$30 -> 0.94766147 | AJ78: =AI78*AF78 -> 0 | AK78: =$AI78*AG78 -> 0
B79: =IF(C78="","",IF(C$30<C79,"",B78+1)) | C79: =IF(Sheet3!A50="","",Sheet3!A50) -> 37963 | D79: =IF(C79="","",Sheet3!E50) -> 24.559999 | E79: =_xlfn.XLOOKUP(WEEKNUM(C79)&YEAR(C79),Sheet4!C:C,Sheet4!B:B,0) -> 0 | F79: =IF(int=Weekly,-$D$5,IF(int=Bi_Weekly,-$D$5,IF(int=Monthly,-$D$5,IF(int=Quarterly,0,IF(int=Yearly,0,IF(int=None,0,0)))))) -> -100 | H79: =H78+F79 -> -1250 | J79: =IF(D$24=0,"",ABS($F79*D$24)/D79) -> 4.0716614 | L79: =IF(D79=0,"",L78+J79) -> 52.789102 | N79: =IF(D79=0,"",L79*E79) -> 0 | O79: =-(IF(D79=0,"",N79)) -> 0 | P79: =P78+F79+O79 -> -1273.2408 | Q79: =IF(D79=0,"",ABS($O79)/D79) -> 0 | R79: =IF(D79=0,"",Q79+R78) -> 1.0391312 | S79: =IF(D79=0,"",L79+R79) -> 53.828233 | T79: =IF(D79=0,"",D79*J79)+T78 -> 1250 | U79: =IF(D79=0,"",L79*D79) -> 1296.5003 | V79: =(U79/T79)-1 -> 0.037200228 | W79: =U79-T79 -> 46.500285 | X79: =ABS(O79)+X78 -> 23.70954 | Y79: =((U79+X79)/T79)-1 -> 0.05616786 | AA79: =(D79*Q79)+(D79*J79)+AA78 -> 1273.7095 | AB79: =(L79*D79)+(D79*R79) -> 1322.0213 | AC79: =AB79-AA79 -> 48.311805 | AD79: =(AB79/AA79)-1 -> 0.037930002 | AF79: =F79+ABS(O79) -> -100 | AG79: =F79 -> -100 | AH79: =DATEDIF($C$31,C79,"d") -> 336 | AI79: =(AH$30-AH79)/AH$30 -> 0.94654788 | AJ79: =AI79*AF79 -> -94.654788 | AK79: =$AI79*AG79 -> -94.654788
B80: =IF(C79="","",IF(C$30<C80,"",B79+1)) | C80: =IF(Sheet3!A51="","",Sheet3!A51) -> 37970 | D80: =IF(C80="","",Sheet3!E51) -> 25.24 | E80: =_xlfn.XLOOKUP(WEEKNUM(C80)&YEAR(C80),Sheet4!C:C,Sheet4!B:B,0) -> 0 | F80: =IF(int=Weekly,-$D$5,IF(int=Bi_Weekly,0,IF(int=Monthly,0,IF(int=Quarterly,0,IF(int=Yearly,0,IF(int=None,0,0)))))) -> 0 | H80: =H79+F80 -> -1250 | J80: =IF(D$24=0,"",ABS($F80*D$24)/D80) -> 0 | L80: =IF(D80=0,"",L79+J80) -> 52.789102 | N80: =IF(D80=0,"",L80*E80) -> 0 | O80: =-(IF(D80=0,"",N80)) -> 0 | P80: =P79+F80+O80 -> -1273.2408 | Q80: =IF(D80=0,"",ABS($O80)/D80) -> 0 | R80: =IF(D80=0,"",Q80+R79) -> 1.0391312 | S80: =IF(D80=0,"",L80+R80) -> 53.828233 | T80: =IF(D80=0,"",D80*J80)+T79 -> 1250 | U80: =IF(D80=0,"",L80*D80) -> 1332.3969 | V80: =(U80/T80)-1 -> 0.065917542 | W80: =U80-T80 -> 82.396927 | X80: =ABS(O80)+X79 -> 23.70954 | Y80: =((U80+X80)/T80)-1 -> 0.084885174 | AA80: =(D80*Q80)+(D80*J80)+AA79 -> 1273.7095 | AB80: =(L80*D80)+(D80*R80) -> 1358.6246 | AC80: =AB80-AA80 -> 84.915057 | AD80: =(AB80/AA80)-1 -> 0.066667521 | AF80: =F80+ABS(O80) -> 0 | AG80: =F80 -> 0 | AH80: =DATEDIF($C$31,C80,"d") -> 343 | AI80: =(AH$30-AH80)/AH$30 -> 0.9454343 | AJ80: =AI80*AF80 -> 0 | AK80: =$AI80*AG80 -> 0
B81: =IF(C80="","",IF(C$30<C81,"",B80+1)) | C81: =IF(Sheet3!A52="","",Sheet3!A52) -> 37977 | D81: =IF(C81="","",Sheet3!E52) -> 25.209999 | E81: =_xlfn.XLOOKUP(WEEKNUM(C81)&YEAR(C81),Sheet4!C:C,Sheet4!B:B,0) -> 0 | F81: =IF(int=Weekly,-$D$5,IF(int=Bi_Weekly,-$D$5,IF(int=Monthly,0,IF(int=Quarterly,0,IF(int=Yearly,0,IF(int=None,0,0)))))) -> 0 | H81: =H80+F81 -> -1250 | J81: =IF(D$24=0,"",ABS($F81*D$24)/D81) -> 0 | L81: =IF(D81=0,"",L80+J81) -> 52.789102 | N81: =IF(D81=0,"",L81*E81) -> 0 | O81: =-(IF(D81=0,"",N81)) -> 0 | P81: =P80+F81+O81 -> -1273.2408 | Q81: =IF(D81=0,"",ABS($O81)/D81) -> 0 | R81: =IF(D81=0,"",Q81+R80) -> 1.0391312 | S81: =IF(D81=0,"",L81+R81) -> 53.828233 | T81: =IF(D81=0,"",D81*J81)+T80 -> 1250 | U81: =IF(D81=0,"",L81*D81) -> 1330.8132 | V81: =(U81/T81)-1 -> 0.064650561 | W81: =U81-T81 -> 80.813201 | X81: =ABS(O81)+X80 -> 23.70954 | Y81: =((U81+X81)/T81)-1 -> 0.083618193 | AA81: =(D81*Q81)+(D81*J81)+AA80 -> 1273.7095 | AB81: =(L81*D81)+(D81*R81) -> 1357.0097 | AC81: =AB81-AA81 -> 83.300156 | AD81: =(AB81/AA81)-1 -> 0.065399648 | AF81: =F81+ABS(O81) -> 0 | AG81: =F81 -> 0 | AH81: =DATEDIF($C$31,C81,"d") -> 350 | AI81: =(AH$30-AH81)/AH$30 -> 0.94432071 | AJ81: =AI81*AF81 -> 0 | AK81: =$AI81*AG81 -> 0
B82: =IF(C81="","",IF(C$30<C82,"",B81+1)) | C82: =IF(Sheet3!A53="","",Sheet3!A53) -> 37984 | D82: =IF(C82="","",Sheet3!E53) -> 26.139999 | E82: =_xlfn.XLOOKUP(WEEKNUM(C82)&YEAR(C82),Sheet4!C:C,Sheet4!B:B,0) -> 0 | F82: =IF(int=Weekly,-$D$5,IF(int=Bi_Weekly,0,IF(int=Monthly,0,IF(int=Quarterly,0,IF(int=Yearly,0,IF(int=None,0,0)))))) -> 0 | H82: =H81+F82 -> -1250 | J82: =IF(D$24=0,"",ABS($F82*D$24)/D82) -> 0 | L82: =IF(D82=0,"",L81+J82) -> 52.789102 | N82: =IF(D82=0,"",L82*E82) -> 0 | O82: =-(IF(D82=0,"",N82)) -> 0 | P82: =P81+F82+O82 -> -1273.2408 | Q82: =IF(D82=0,"",ABS($O82)/D82) -> 0 | R82: =IF(D82=0,"",Q82+R81) -> 1.0391312 | S82: =IF(D82=0,"",L82+R82) -> 53.828233 | T82: =IF(D82=0,"",D82*J82)+T81 -> 1250 | U82: =IF(D82=0,"",L82*D82) -> 1379.9071 | V82: =(U82/T82)-1 -> 0.10392565 | W82: =U82-T82 -> 129.90707 | X82: =ABS(O82)+X81 -> 23.70954 | Y82: =((U82+X82)/T82)-1 -> 0.12289328 | AA82: =(D82*Q82)+(D82*J82)+AA81 -> 1273.7095 | AB82: =(L82*D82)+(D82*R82) -> 1407.07 | AC82: =AB82-AA82 -> 133.36041 | AD82: =(AB82/AA82)-1 -> 0.10470237 | AF82: =F82+ABS(O82) -> 0 | AG82: =F82 -> 0 | AH82: =DATEDIF($C$31,C82,"d") -> 357 | AI82: =(AH$30-AH82)/AH$30 -> 0.94320713 | AJ82: =AI82*AF82 -> 0 | AK82: =$AI82*AG82 -> 0
B83: =IF(C82="","",IF(C$30<C83,"",B82+1)) | C83: =IF(Sheet3!A54="","",Sheet3!A54) -> 37991 | D83: =IF(C83="","",Sheet3!E54) -> 26.200001 | E83: =_xlfn.XLOOKUP(WEEKNUM(C83)&YEAR(C83),Sheet4!C:C,Sheet4!B:B,0) -> 0.3125 | F83: =IF(int=Weekly,-$D$5,IF(int=Bi_Weekly,-$D$5,IF(int=Monthly,-$D$5,IF(int=Quarterly,-$D$5,IF(int=Yearly,-$D$5,IF(int=None,0,0)))))) -> -100 | H83: =H82+F83 -> -1350 | J83: =IF(D$24=0,"",ABS($F83*D$24)/D83) -> 3.8167937 | L83: =IF(D83=0,"",L82+J83) -> 56.605895 | N83: =IF(D83=0,"",L83*E83) -> 17.689342 | O83: =-(IF(D83=0,"",N83)) -> -17.689342 | P83: =P82+F83+O83 -> -1390.9301 | Q83: =IF(D83=0,"",ABS($O83)/D83) -> 0.67516571 | R83: =IF(D83=0,"",Q83+R82) -> 1.7142969 | S83: =IF(D83=0,"",L83+R83) -> 58.320192 | T83: =IF(D83=0,"",D83*J83)+T82 -> 1350 | U83: =IF(D83=0,"",L83*D83) -> 1483.0745 | V83: =(U83/T83)-1 -> 0.098573717 | W83: =U83-T83 -> 133.07452 | X83: =ABS(O83)+X82 -> 41.398883 | Y83: =((U83+X83)/T83)-1 -> 0.12923956 | AA83: =(D83*Q83)+(D83*J83)+AA82 -> 1391.3989 | AB83: =(L83*D83)+(D83*R83) -> 1527.9891 | AC83: =AB83-AA83 -> 136.59021 | AD83: =(AB83/AA83)-1 -> 0.098167546 | AF83: =F83+ABS(O83) -> -82.310658 | AG83: =F83 -> -100 | AH83: =DATEDIF($C$31,C83,"d") -> 364 | AI83: =(AH$30-AH83)/AH$30 -> 0.94209354 | AJ83: =AI83*AF83 -> -77.544339 | AK83: =$AI83*AG83 -> -94.209354
B84: =IF(C83="","",IF(C$30<C84,"",B83+1)) | C84: =IF(Sheet3!A55="","",Sheet3!A55) -> 37998 | D84: =IF(C84="","",Sheet3!E55) -> 26.469999 | E84: =_xlfn.XLOOKUP(WEEKNUM(C84)&YEAR(C84),Sheet4!C:C,Sheet4!B:B,0) -> 0 | F84: =IF(int=Weekly,-$D$5,IF(int=Bi_Weekly,0,IF(int=Monthly,0,IF(int=Quarterly,0,IF(int=Yearly,0,IF(int=None,0,0)))))) -> 0 | H84: =H83+F84 -> -1350 | J84: =IF(D$24=0,"",ABS($F84*D$24)/D84) -> 0 | L84: =IF(D84=0,"",L83+J84) -> 56.605895 | N84: =IF(D84=0,"",L84*E84) -> 0 | O84: =-(IF(D84=0,"",N84)) -> 0 | P84: =P83+F84+O84 -> -1390.9301 | Q84: =IF(D84=0,"",ABS($O84)/D84) -> 0 | R84: =IF(D84=0,"",Q84+R83) -> 1.7142969 | S84: =IF(D84=0,"",L84+R84) -> 58.320192 | T84: =IF(D84=0,"",D84*J84)+T83 -> 1350 | U84: =IF(D84=0,"",L84*D84) -> 1498.358 | V84: =(U84/T84)-1 -> 0.10989481 | W84: =U84-T84 -> 148.358 | X84: =ABS(O84)+X83 -> 41.398883 | Y84: =((U84+X84)/T84)-1 -> 0.14056065 | AA84: =(D84*Q84)+(D84*J84)+AA83 -> 1391.3989 | AB84: =(L84*D84)+(D84*R84) -> 1543.7354 | AC84: =AB84-AA84 -> 152.33655 | AD84: =(AB84/AA84)-1 -> 0.10948446 | AF84: =F84+ABS(O84) -> 0 | AG84: =F84 -> 0 | AH84: =DATEDIF($C$31,C84,"d") -> 371 | AI84: =(AH$30-AH84)/AH$30 -> 0.94097996 | AJ84: =AI84*AF84 -> 0 | AK84: =$AI84*AG84 -> 0
B85: =IF(C84="","",IF(C$30<C85,"",B84+1)) | C85: =IF(Sheet3!A56="","",Sheet3!A56) -> 38005 | D85: =IF(C85="","",Sheet3!E56) -> 26.42 | E85: =_xlfn.XLOOKUP(WEEKNUM(C85)&YEAR(C85),Sheet4!C:C,Sheet4!B:B,0) -> 0 | F85: =IF(int=Weekly,-$D$5,IF(int=Bi_Weekly,-$D$5,IF(int=Monthly,0,IF(int=Quarterly,0,IF(int=Yearly,0,IF(int=None,0,0)))))) -> 0 | H85: =H84+F85 -> -1350 | J85: =IF(D$24=0,"",ABS($F85*D$24)/D85) -> 0 | L85: =IF(D85=0,"",L84+J85) -> 56.605895 | N85: =IF(D85=0,"",L85*E85) -> 0 | O85: =-(IF(D85=0,"",N85)) -> 0 | P85: =P84+F85+O85 -> -1390.9301 | Q85: =IF(D85=0,"",ABS($O85)/D85) -> 0 | R85: =IF(D85=0,"",Q85+R84) -> 1.7142969 | S85: =IF(D85=0,"",L85+R85) -> 58.320192 | T85: =IF(D85=0,"",D85*J85)+T84 -> 1350 | U85: =IF(D85=0,"",L85*D85) -> 1495.5278 | V85: =(U85/T85)-1 -> 0.10779834 | W85: =U85-T85 -> 145.52776 | X85: =ABS(O85)+X84 -> 41.398883 | Y85: =((U85+X85)/T85)-1 -> 0.13846418 | AA85: =(D85*Q85)+(D85*J85)+AA84 -> 1391.3989 | AB85: =(L85*D85)+(D85*R85) -> 1540.8195 | AC85: =AB85-AA85 -> 149.4206 | AD85: =(AB85/AA85)-1 -> 0.10738876 | AF85: =F85+ABS(O85) -> 0 | AG85: =F85 -> 0 | AH85: =DATEDIF($C$31,C85,"d") -> 378 | AI85: =(AH$30-AH85)/AH$30 -> 0.93986637 | AJ85: =AI85*AF85 -> 0 | AK85: =$AI85*AG85 -> 0
B86: =IF(C85="","",IF(C$30<C86,"",B85+1)) | C86: =IF(Sheet3!A57="","",Sheet3!A57) -> 38012 | D86: =IF(C86="","",Sheet3!E57) -> 25.5 | E86: =_xlfn.XLOOKUP(WEEKNUM(C86)&YEAR(C86),Sheet4!C:C,Sheet4!B:B,0) -> 0 | F86: =IF(int=Weekly,-$D$5,IF(int=Bi_Weekly,0,IF(int=Monthly,0,IF(int=Quarterly,0,IF(int=Yearly,0,IF(int=None,0,0)))))) -> 0 | H86: =H85+F86 -> -1350 | J86: =IF(D$24=0,"",ABS($F86*D$24)/D86) -> 0 | L86: =IF(D86=0,"",L85+J86) -> 56.605895 | N86: =IF(D86=0,"",L86*E86) -> 0 | O86: =-(IF(D86=0,"",N86)) -> 0 | P86: =P85+F86+O86 -> -1390.9301 | Q86: =IF(D86=0,"",ABS($O86)/D86) -> 0 | R86: =IF(D86=0,"",Q86+R85) -> 1.7142969 | S86: =IF(D86=0,"",L86+R86) -> 58.320192 | T86: =IF(D86=0,"",D86*J86)+T85 -> 1350 | U86: =IF(D86=0,"",L86*D86) -> 1443.4503 | V86: =(U86/T86)-1 -> 0.06922247 | W86: =U86-T86 -> 93.450334 | X86: =ABS(O86)+X85 -> 41.398883 | Y86: =((U86+X86)/T86)-1 -> 0.099888309 | AA86: =(D86*Q86)+(D86*J86)+AA85 -> 1391.3989 | AB86: =(L86*D86)+(D86*R86) -> 1487.1649 | AC86: =AB86-AA86 -> 95.766021 | AD86: =(AB86/AA86)-1 -> 0.068827151 | AF86: =F86+ABS(O86) -> 0 | AG86: =F86 -> 0 | AH86: =DATEDIF($C$31,C86,"d") -> 385 | AI86: =(AH$30-AH86)/AH$30 -> 0.93875278 | AJ86: =AI86*AF86 -> 0 | AK86: =$AI86*AG86 -> 0
B87: =IF(C86="","",IF(C$30<C87,"",B86+1)) | C87: =IF(Sheet3!A58="","",Sheet3!A58) -> 38019 | D87: =IF(C87="","",Sheet3!E58) -> 26.02 | E87: =_xlfn.XLOOKUP(WEEKNUM(C87)&YEAR(C87),Sheet4!C:C,Sheet4!B:B,0) -> 0 | F87: =IF(int=Weekly,-$D$5,IF(int=Bi_Weekly,-$D$5,IF(int=Monthly,-$D$5,IF(int=Quarterly,0,IF(int=Yearly,0,IF(int=None,0,0)))))) -> -100 | H87: =H86+F87 -> -1450 | J87: =IF(D$24=0,"",ABS($F87*D$24)/D87) -> 3.8431975 | L87: =IF(D87=0,"",L86+J87) -> 60.449093 | N87: =IF(D87=0,"",L87*E87) -> 0 | O87: =-(IF(D87=0,"",N87)) -> 0 | P87: =P86+F87+O87 -> -1490.9301 | Q87: =IF(D87=0,"",ABS($O87)/D87) -> 0 | R87: =IF(D87=0,"",Q87+R86) -> 1.7142969 | S87: =IF(D87=0,"",L87+R87) -> 62.16339 | T87: =IF(D87=0,"",D87*J87)+T86 -> 1450 | U87: =IF(D87=0,"",L87*D87) -> 1572.8854 | V87: =(U87/T87)-1 -> 0.084748552 | W87: =U87-T87 -> 122.8854 | X87: =ABS(O87)+X86 -> 41.398883 | Y87: =((U87+X87)/T87)-1 -> 0.11329951 | AA87: =(D87*Q87)+(D87*J87)+AA86 -> 1491.3989 | AB87: =(L87*D87)+(D87*R87) -> 1617.4914 | AC87: =AB87-AA87 -> 126.09252 | AD87: =(AB87/AA87)-1 -> 0.084546477 | AF87: =F87+ABS(O87) -> -100 | AG87: =F87 -> -100 | AH87: =DATEDIF($C$31,C87,"d") -> 392 | AI87: =(AH$30-AH87)/AH$30 -> 0.9376392 | AJ87: =AI87*AF87 -> -93.76392 | AK87: =$AI87*AG87 -> -93.76392
B88: =IF(C87="","",IF(C$30<C88,"",B87+1)) | C88: =IF(Sheet3!A59="","",Sheet3!A59) -> 38026 | D88: =IF(C88="","",Sheet3!E59) -> 25.049999 | E88: =_xlfn.XLOOKUP(WEEKNUM(C88)&YEAR(C88),Sheet4!C:C,Sheet4!B:B,0) -> 0 | F88: =IF(int=Weekly,-$D$5,IF(int=Bi_Weekly,0,IF(int=Monthly,0,IF(int=Quarterly,0,IF(int=Yearly,0,IF(int=None,0,0)))))) -> 0 | H88: =H87+F88 -> -1450 | J88: =IF(D$24=0,"",ABS($F88*D$24)/D88) -> 0 | L88: =IF(D88=0,"",L87+J88) -> 60.449093 | N88: =IF(D88=0,"",L88*E88) -> 0 | O88: =-(IF(D88=0,"",N88)) -> 0 | P88: =P87+F88+O88 -> -1490.9301 | Q88: =IF(D88=0,"",ABS($O88)/D88) -> 0 | R88: =IF(D88=0,"",Q88+R87) -> 1.7142969 | S88: =IF(D88=0,"",L88+R88) -> 62.16339 | T88: =IF(D88=0,"",D88*J88)+T87 -> 1450 | U88: =IF(D88=0,"",L88*D88) -> 1514.2497 | V88: =(U88/T88)-1 -> 0.044310151 | W88: =U88-T88 -> 64.249719 | X88: =ABS(O88)+X87 -> 41.398883 | Y88: =((U88+X88)/T88)-1 -> 0.072861105 | AA88: =(D88*Q88)+(D88*J88)+AA87 -> 1491.3989 | AB88: =(L88*D88)+(D88*R88) -> 1557.1929 | AC88: =AB88-AA88 -> 65.793971 | AD88: =(AB88/AA88)-1 -> 0.04411561 | AF88: =F88+ABS(O88) -> 0 | AG88: =F88 -> 0 | AH88: =DATEDIF($C$31,C88,"d") -> 399 | AI88: =(AH$30-AH88)/AH$30 -> 0.93652561 | AJ88: =AI88*AF88 -> 0 | AK88: =$AI88*AG88 -> 0
B89: =IF(C88="","",IF(C$30<C89,"",B88+1)) | C89: =IF(Sheet3!A60="","",Sheet3!A60) -> 38033 | D89: =IF(C89="","",Sheet3!E60) -> 23.879999 | E89: =_xlfn.XLOOKUP(WEEKNUM(C89)&YEAR(C89),Sheet4!C:C,Sheet4!B:B,0) -> 0 | F89: =IF(int=Weekly,-$D$5,IF(int=Bi_Weekly,-$D$5,IF(int=Monthly,0,IF(int=Quarterly,0,IF(int=Yearly,0,IF(int=None,0,0)))))) -> 0 | H89: =H88+F89 -> -1450 | J89: =IF(D$24=0,"",ABS($F89*D$24)/D89) -> 0 | L89: =IF(D89=0,"",L88+J89) -> 60.449093 | N89: =IF(D89=0,"",L89*E89) -> 0 | O89: =-(IF(D89=0,"",N89)) -> 0 | P89: =P88+F89+O89 -> -1490.9301 | Q89: =IF(D89=0,"",ABS($O89)/D89) -> 0 | R89: =IF(D89=0,"",Q89+R88) -> 1.7142969 | S89: =IF(D89=0,"",L89+R89) -> 62.16339 | T89: =IF(D89=0,"",D89*J89)+T88 -> 1450 | U89: =IF(D89=0,"",L89*D89) -> 1443.5243 | V89: =(U89/T89)-1 -> -0.0044660136 | W89: =U89-T89 -> -6.4757198 | X89: =ABS(O89)+X88 -> 41.398883 | Y89: =((U89+X89)/T89)-1 -> 0.02408494 | AA89: =(D89*Q89)+(D89*J89)+AA88 -> 1491.3989 | AB89: =(L89*D89)+(D89*R89) -> 1484.4617 | AC89: =AB89-AA89 -> -6.937195 | AD89: =(AB89/AA89)-1 -> -0.0046514686 | AF89: =F89+ABS(O89) -> 0 | AG89: =F89 -> 0 | AH89: =DATEDIF($C$31,C89,"d") -> 406 | AI89: =(AH$30-AH89)/AH$30 -> 0.93541203 | AJ89: =AI89*AF89 -> 0 | AK89: =$AI89*AG89 -> 0
B90: =IF(C89="","",IF(C$30<C90,"",B89+1)) | C90: =IF(Sheet3!A61="","",Sheet3!A61) -> 38040 | D90: =IF(C90="","",Sheet3!E61) -> 24.01 | E90: =_xlfn.XLOOKUP(WEEKNUM(C90)&YEAR(C90),Sheet4!C:C,Sheet4!B:B,0) -> 0 | F90: =IF(int=Weekly,-$D$5,IF(int=Bi_Weekly,0,IF(int=Monthly,0,IF(int=Quarterly,0,IF(int=Yearly,0,IF(int=None,0,0)))))) -> 0 | H90: =H89+F90 -> -1450 | J90: =IF(D$24=0,"",ABS($F90*D$24)/D90) -> 0 | L90: =IF(D90=0,"",L89+J90) -> 60.449093 | N90: =IF(D90=0,"",L90*E90) -> 0 | O90: =-(IF(D90=0,"",N90)) -> 0 | P90: =P89+F90+O90 -> -1490.9301 | Q90: =IF(D90=0,"",ABS($O90)/D90) -> 0 | R90: =IF(D90=0,"",Q90+R89) -> 1.7142969 | S90: =IF(D90=0,"",L90+R90) -> 62.16339 | T90: =IF(D90=0,"",D90*J90)+T89 -> 1450 | U90: =IF(D90=0,"",L90*D90) -> 1451.3827 | V90: =(U90/T90)-1 -> 0.00095360192 | W90: =U90-T90 -> 1.3827228 | X90: =ABS(O90)+X89 -> 41.398883 | Y90: =((U90+X90)/T90)-1 -> 0.029504555 | AA90: =(D90*Q90)+(D90*J90)+AA89 -> 1491.3989 | AB90: =(L90*D90)+(D90*R90) -> 1492.543 | AC90: =AB90-AA90 -> 1.1441078 | AD90: =(AB90/AA90)-1 -> 0.00076713738 | AF90: =F90+ABS(O90) -> 0 | AG90: =F90 -> 0 | AH90: =DATEDIF($C$31,C90,"d") -> 413 | AI90: =(AH$30-AH90)/AH$30 -> 0.93429844 | AJ90: =AI90*AF90 -> 0 | AK90: =$AI90*AG90 -> 0
B91: =IF(C90="","",IF(C$30<C91,"",B90+1)) | C91: =IF(Sheet3!A62="","",Sheet3!A62) -> 38047 | D91: =IF(C91="","",Sheet3!E62) -> 25.02 | E91: =_xlfn.XLOOKUP(WEEKNUM(C91)&YEAR(C91),Sheet4!C:C,Sheet4!B:B,0) -> 0 | F91: =IF(int=Weekly,-$D$5,IF(int=Bi_Weekly,-$D$5,IF(int=Monthly,-$D$5,IF(int=Quarterly,0,IF(int=Yearly,0,IF(int=None,0,0)))))) -> -100 | H91: =H90+F91 -> -1550 | J91: =IF(D$24=0,"",ABS($F91*D$24)/D91) -> 3.9968026 | L91: =IF(D91=0,"",L90+J91) -> 64.445896 | N91: =IF(D91=0,"",L91*E91) -> 0 | O91: =-(IF(D91=0,"",N91)) -> 0 | P91: =P90+F91+O91 -> -1590.9301 | Q91: =IF(D91=0,"",ABS($O91)/D91) -> 0 | R91: =IF(D91=0,"",Q91+R90) -> 1.7142969 | S91: =IF(D91=0,"",L91+R91) -> 66.160192 | T91: =IF(D91=0,"",D91*J91)+T90 -> 1550 | U91: =IF(D91=0,"",L91*D91) -> 1612.4363 | V91: =(U91/T91)-1 -> 0.040281488 | W91: =U91-T91 -> 62.436307 | X91: =ABS(O91)+X90 -> 41.398883 | Y91: =((U91+X91)/T91)-1 -> 0.066990445 | AA91: =(D91*Q91)+(D91*J91)+AA90 -> 1591.3989 | AB91: =(L91*D91)+(D91*R91) -> 1655.328 | AC91: =AB91-AA91 -> 63.929132 | AD91: =(AB91/AA91)-1 -> 0.040171658 | AF91: =F91+ABS(O91) -> -100 | AG91: =F91 -> -100 | AH91: =DATEDIF($C$31,C91,"d") -> 420 | AI91: =(AH$30-AH91)/AH$30 -> 0.93318486 | AJ91: =AI91*AF91 -> -93.318486 | AK91: =$AI91*AG91 -> -93.318486
B92: =IF(C91="","",IF(C$30<C92,"",B91+1)) | C92: =IF(Sheet3!A63="","",Sheet3!A63) -> 38054 | D92: =IF(C92="","",Sheet3!E63) -> 24.360001 | E92: =_xlfn.XLOOKUP(WEEKNUM(C92)&YEAR(C92),Sheet4!C:C,Sheet4!B:B,0) -> 0 | F92: =IF(int=Weekly,-$D$5,IF(int=Bi_Weekly,0,IF(int=Monthly,0,IF(int=Quarterly,0,IF(int=Yearly,0,IF(int=None,0,0)))))) -> 0 | H92: =H91+F92 -> -1550 | J92: =IF(D$24=0,"",ABS($F92*D$24)/D92) -> 0 | L92: =IF(D92=0,"",L91+J92) -> 64.445896 | N92: =IF(D92=0,"",L92*E92) -> 0 | O92: =-(IF(D92=0,"",N92)) -> 0 | P92: =P91+F92+O92 -> -1590.9301 | Q92: =IF(D92=0,"",ABS($O92)/D92) -> 0 | R92: =IF(D92=0,"",Q92+R91) -> 1.7142969 | S92: =IF(D92=0,"",L92+R92) -> 66.160192 | T92: =IF(D92=0,"",D92*J92)+T91 -> 1550 | U92: =IF(D92=0,"",L92*D92) -> 1569.9021 | V92: =(U92/T92)-1 -> 0.012840052 | W92: =U92-T92 -> 19.90208 | X92: =ABS(O92)+X91 -> 41.398883 | Y92: =((U92+X92)/T92)-1 -> 0.039549008 | AA92: =(D92*Q92)+(D92*J92)+AA91 -> 1591.3989 | AB92: =(L92*D92)+(D92*R92) -> 1611.6624 | AC92: =AB92-AA92 -> 20.263471 | AD92: =(AB92/AA92)-1 -> 0.012733119 | AF92: =F92+ABS(O92) -> 0 | AG92: =F92 -> 0 | AH92: =DATEDIF($C$31,C92,"d") -> 427 | AI92: =(AH$30-AH92)/AH$30 -> 0.93207127 | AJ92: =AI92*AF92 -> 0 | AK92: =$AI92*AG92 -> 0
B93: =IF(C92="","",IF(C$30<C93,"",B92+1)) | C93: =IF(Sheet3!A64="","",Sheet3!A64) -> 38061 | D93: =IF(C93="","",Sheet3!E64) -> 24.620001 | E93: =_xlfn.XLOOKUP(WEEKNUM(C93)&YEAR(C93),Sheet4!C:C,Sheet4!B:B,0) -> 0 | F93: =IF(int=Weekly,-$D$5,IF(int=Bi_Weekly,-$D$5,IF(int=Monthly,0,IF(int=Quarterly,0,IF(int=Yearly,0,IF(int=None,0,0)))))) -> 0 | H93: =H92+F93 -> -1550 | J93: =IF(D$24=0,"",ABS($F93*D$24)/D93) -> 0 | L93: =IF(D93=0,"",L92+J93) -> 64.445896 | N93: =IF(D93=0,"",L93*E93) -> 0 | O93: =-(IF(D93=0,"",N93)) -> 0 | P93: =P92+F93+O93 -> -1590.9301 | Q93: =IF(D93=0,"",ABS($O93)/D93) -> 0 | R93: =IF(D93=0,"",Q93+R92) -> 1.7142969 | S93: =IF(D93=0,"",L93+R93) -> 66.160192 | T93: =IF(D93=0,"",D93*J93)+T92 -> 1550 | U93: =IF(D93=0,"",L93*D93) -> 1586.658 | V93: =(U93/T93)-1 -> 0.023650331 | W93: =U93-T93 -> 36.658013 | X93: =ABS(O93)+X92 -> 41.398883 | Y93: =((U93+X93)/T93)-1 -> 0.050359287 | AA93: =(D93*Q93)+(D93*J93)+AA92 -> 1591.3989 | AB93: =(L93*D93)+(D93*R93) -> 1628.864 | AC93: =AB93-AA93 -> 37.465121 | AD93: =(AB93/AA93)-1 -> 0.023542257 | AF93: =F93+ABS(O93) -> 0 | AG93: =F93 -> 0 | AH93: =DATEDIF($C$31,C93,"d") -> 434 | AI93: =(AH$30-AH93)/AH$30 -> 0.93095768 | AJ93: =AI93*AF93 -> 0 | AK93: =$AI93*AG93 -> 0
B94: =IF(C93="","",IF(C$30<C94,"",B93+1)) | C94: =IF(Sheet3!A65="","",Sheet3!A65) -> 38068 | D94: =IF(C94="","",Sheet3!E65) -> 23.92 | E94: =_xlfn.XLOOKUP(WEEKNUM(C94)&YEAR(C94),Sheet4!C:C,Sheet4!B:B,0) -> 0 | F94: =IF(int=Weekly,-$D$5,IF(int=Bi_Weekly,0,IF(int=Monthly,0,IF(int=Quarterly,0,IF(int=Yearly,0,IF(int=None,0,0)))))) -> 0 | H94: =H93+F94 -> -1550 | J94: =IF(D$24=0,"",ABS($F94*D$24)/D94) -> 0 | L94: =IF(D94=0,"",L93+J94) -> 64.445896 | N94: =IF(D94=0,"",L94*E94) -> 0 | O94: =-(IF(D94=0,"",N94)) -> 0 | P94: =P93+F94+O94 -> -1590.9301 | Q94: =IF(D94=0,"",ABS($O94)/D94) -> 0 | R94: =IF(D94=0,"",Q94+R93) -> 1.7142969 | S94: =IF(D94=0,"",L94+R94) -> 66.160192 | T94: =IF(D94=0,"",D94*J94)+T93 -> 1550 | U94: =IF(D94=0,"",L94*D94) -> 1541.5458 | V94: =(U94/T94)-1 -> -0.0054543086 | W94: =U94-T94 -> -8.4541784 | X94: =ABS(O94)+X93 -> 41.398883 | Y94: =((U94+X94)/T94)-1 -> 0.021254648 | AA94: =(D94*Q94)+(D94*J94)+AA93 -> 1591.3989 | AB94: =(L94*D94)+(D94*R94) -> 1582.5518 | AC94: =AB94-AA94 -> -8.8470801 | AD94: =(AB94/AA94)-1 -> -0.0055593102 | AF94: =F94+ABS(O94) -> 0 | AG94: =F94 -> 0 | AH94: =DATEDIF($C$31,C94,"d") -> 441 | AI94: =(AH$30-AH94)/AH$30 -> 0.9298441 | AJ94: =AI94*AF94 -> 0 | AK94: =$AI94*AG94 -> 0
B95: =IF(C94="","",IF(C$30<C95,"",B94+1)) | C95: =IF(Sheet3!A66="","",Sheet3!A66) -> 38075 | D95: =IF(C95="","",Sheet3!E66) -> 24.870001 | E95: =_xlfn.XLOOKUP(WEEKNUM(C95)&YEAR(C95),Sheet4!C:C,Sheet4!B:B,0) -> 0 | F95: =IF(int=Weekly,-$D$5,IF(int=Bi_Weekly,-$D$5,IF(int=Monthly,-$D$5,IF(int=Quarterly,0,IF(int=Yearly,0,IF(int=None,0,0)))))) -> -100 | H95: =H94+F95 -> -1650 | J95: =IF(D$24=0,"",ABS($F95*D$24)/D95) -> 4.0209086 | L95: =IF(D95=0,"",L94+J95) -> 68.466804 | N95: =IF(D95=0,"",L95*E95) -> 0 | O95: =-(IF(D95=0,"",N95)) -> 0 | P95: =P94+F95+O95 -> -1690.9301 | Q95: =IF(D95=0,"",ABS($O95)/D95) -> 0 | R95: =IF(D95=0,"",Q95+R94) -> 1.7142969 | S95: =IF(D95=0,"",L95+R95) -> 70.181101 | T95: =IF(D95=0,"",D95*J95)+T94 -> 1650 | U95: =IF(D95=0,"",L95*D95) -> 1702.7695 | V95: =(U95/T95)-1 -> 0.031981507 | W95: =U95-T95 -> 52.769487 | X95: =ABS(O95)+X94 -> 41.398883 | Y95: =((U95+X95)/T95)-1 -> 0.057071739 | AA95: =(D95*Q95)+(D95*J95)+AA94 -> 1691.3989 | AB95: =(L95*D95)+(D95*R95) -> 1745.4041 | AC95: =AB95-AA95 -> 54.005169 | AD95: =(AB95/AA95)-1 -> 0.031929292 | AF95: =F95+ABS(O95) -> -100 | AG95: =F95 -> -100 | AH95: =DATEDIF($C$31,C95,"d") -> 448 | AI95: =(AH$30-AH95)/AH$30 -> 0.92873051 | AJ95: =AI95*AF95 -> -92.873051 | AK95: =$AI95*AG95 -> -92.873051
B96: =IF(C95="","",IF(C$30<C96,"",B95+1)) | C96: =IF(Sheet3!A67="","",Sheet3!A67) -> 38082 | D96: =IF(C96="","",Sheet3!E67) -> 24.459999 | E96: =_xlfn.XLOOKUP(WEEKNUM(C96)&YEAR(C96),Sheet4!C:C,Sheet4!B:B,0) -> 0.3125 | F96: =IF(int=Weekly,-$D$5,IF(int=Bi_Weekly,0,IF(int=Monthly,0,IF(int=Quarterly,-$D$5,IF(int=Yearly,0,IF(int=None,0,0)))))) -> 0 | H96: =H95+F96 -> -1650 | J96: =IF(D$24=0,"",ABS($F96*D$24)/D96) -> 0 | L96: =IF(D96=0,"",L95+J96) -> 68.466804 | N96: =IF(D96=0,"",L96*E96) -> 21.395876 | O96: =-(IF(D96=0,"",N96)) -> -21.395876 | P96: =P95+F96+O96 -> -1712.326 | Q96: =IF(D96=0,"",ABS($O96)/D96) -> 0.87472924 | R96: =IF(D96=0,"",Q96+R95) -> 2.5890261 | S96: =IF(D96=0,"",L96+R96) -> 71.05583 | T96: =IF(D96=0,"",D96*J96)+T95 -> 1650 | U96: =IF(D96=0,"",L96*D96) -> 1674.698 | V96: =(U96/T96)-1 -> 0.014968461 | W96: =U96-T96 -> 24.69796 | X96: =ABS(O96)+X95 -> 62.794759 | Y96: =((U96+X96)/T96)-1 -> 0.05302589 | AA96: =(D96*Q96)+(D96*J96)+AA95 -> 1712.7948 | AB96: =(L96*D96)+(D96*R96) -> 1738.0255 | AC96: =AB96-AA96 -> 25.230777 | AD96: =(AB96/AA96)-1 -> 0.014730765 | AF96: =F96+ABS(O96) -> 21.395876 | AG96: =F96 -> 0 | AH96: =DATEDIF($C$31,C96,"d") -> 455 | AI96: =(AH$30-AH96)/AH$30 -> 0.92761693 | AJ96: =AI96*AF96 -> 19.847177 | AK96: =$AI96*AG96 -> 0
B97: =IF(C96="","",IF(C$30<C97,"",B96+1)) | C97: =IF(Sheet3!A68="","",Sheet3!A68) -> 38089 | D97: =IF(C97="","",Sheet3!E68) -> 24.17 | E97: =_xlfn.XLOOKUP(WEEKNUM(C97)&YEAR(C97),Sheet4!C:C,Sheet4!B:B,0) -> 0 | F97: =IF(int=Weekly,-$D$5,IF(int=Bi_Weekly,-$D$5,IF(int=Monthly,0,IF(int=Quarterly,0,IF(int=Yearly,0,IF(int=None,0,0)))))) -> 0 | H97: =H96+F97 -> -1650 | J97: =IF(D$24=0,"",ABS($F97*D$24)/D97) -> 0 | L97: =IF(D97=0,"",L96+J97) -> 68.466804 | N97: =IF(D97=0,"",L97*E97) -> 0 | O97: =-(IF(D97=0,"",N97)) -> 0 | P97: =P96+F97+O97 -> -1712.326 | Q97: =IF(D97=0,"",ABS($O97)/D97) -> 0 | R97: =IF(D97=0,"",Q97+R96) -> 2.5890261 | S97: =IF(D97=0,"",L97+R97) -> 71.05583 | T97: =IF(D97=0,"",D97*J97)+T96 -> 1650 | U97: =IF(D97=0,"",L97*D97) -> 1654.8427 | V97: =(U97/T97)-1 -> 0.0029349427 | W97: =U97-T97 -> 4.8426555 | X97: =ABS(O97)+X96 -> 62.794759 | Y97: =((U97+X97)/T97)-1 -> 0.040992372 | AA97: =(D97*Q97)+(D97*J97)+AA96 -> 1712.7948 | AB97: =(L97*D97)+(D97*R97) -> 1717.4194 | AC97: =AB97-AA97 -> 4.6246574 | AD97: =(AB97/AA97)-1 -> 0.0027000651 | AF97: =F97+ABS(O97) -> 0 | AG97: =F97 -> 0 | AH97: =DATEDIF($C$31,C97,"d") -> 462 | AI97: =(AH$30-AH97)/AH$30 -> 0.92650334 | AJ97: =AI97*AF97 -> 0 | AK97: =$AI97*AG97 -> 0
B98: =IF(C97="","",IF(C$30<C98,"",B97+1)) | C98: =IF(Sheet3!A69="","",Sheet3!A69) -> 38096 | D98: =IF(C98="","",Sheet3!E69) -> 25.42 | E98: =_xlfn.XLOOKUP(WEEKNUM(C98)&YEAR(C98),Sheet4!C:C,Sheet4!B:B,0) -> 0 | F98: =IF(int=Weekly,-$D$5,IF(int=Bi_Weekly,0,IF(int=Monthly,0,IF(int=Quarterly,0,IF(int=Yearly,0,IF(int=None,0,0)))))) -> 0 | H98: =H97+F98 -> -1650 | J98: =IF(D$24=0,"",ABS($F98*D$24)/D98) -> 0 | L98: =IF(D98=0,"",L97+J98) -> 68.466804 | N98: =IF(D98=0,"",L98*E98) -> 0 | O98: =-(IF(D98=0,"",N98)) -> 0 | P98: =P97+F98+O98 -> -1712.326 | Q98: =IF(D98=0,"",ABS($O98)/D98) -> 0 | R98: =IF(D98=0,"",Q98+R97) -> 2.5890261 | S98: =IF(D98=0,"",L98+R98) -> 71.05583 | T98: =IF(D98=0,"",D98*J98)+T97 -> 1650 | U98: =IF(D98=0,"",L98*D98) -> 1740.4262 | V98: =(U98/T98)-1 -> 0.054803734 | W98: =U98-T98 -> 90.426161 | X98: =ABS(O98)+X97 -> 62.794759 | Y98: =((U98+X98)/T98)-1 -> 0.092861163 | AA98: =(D98*Q98)+(D98*J98)+AA97 -> 1712.7948 | AB98: =(L98*D98)+(D98*R98) -> 1806.2392 | AC98: =AB98-AA98 -> 93.444445 | AD98: =(AB98/AA98)-1 -> 0.054556709 | AF98: =F98+ABS(O98) -> 0 | AG98: =F98 -> 0 | AH98: =DATEDIF($C$31,C98,"d") -> 469 | AI98: =(AH$30-AH98)/AH$30 -> 0.92538976 | AJ98: =AI98*AF98 -> 0 | AK98: =$AI98*AG98 -> 0
B99: =IF(C98="","",IF(C$30<C99,"",B98+1)) | C99: =IF(Sheet3!A70="","",Sheet3!A70) -> 38103 | D99: =IF(C99="","",Sheet3!E70) -> 24.9 | E99: =_xlfn.XLOOKUP(WEEKNUM(C99)&YEAR(C99),Sheet4!C:C,Sheet4!B:B,0) -> 0 | F99: =IF(int=Weekly,-$D$5,IF(int=Bi_Weekly,-$D$5,IF(int=Monthly,-$D$5,IF(int=Quarterly,0,IF(int=Yearly,0,IF(int=None,0,0)))))) -> -100 | H99: =H98+F99 -> -1750 | J99: =IF(D$24=0,"",ABS($F99*D$24)/D99) -> 4.0160643 | L99: =IF(D99=0,"",L98+J99) -> 72.482868 | N99: =IF(D99=0,"",L99*E99) -> 0 | O99: =-(IF(D99=0,"",N99)) -> 0 | P99: =P98+F99+O99 -> -1812.326 | Q99: =IF(D99=0,"",ABS($O99)/D99) -> 0 | R99: =IF(D99=0,"",Q99+R98) -> 2.5890261 | S99: =IF(D99=0,"",L99+R99) -> 75.071894 | T99: =IF(D99=0,"",D99*J99)+T98 -> 1750 | U99: =IF(D99=0,"",L99*D99) -> 1804.8234 | V99: =(U99/T99)-1 -> 0.03132767 | W99: =U99-T99 -> 54.823422 | X99: =ABS(O99)+X98 -> 62.794759 | Y99: =((U99+X99)/T99)-1 -> 0.067210389 | AA99: =(D99*Q99)+(D99*J99)+AA98 -> 1812.7948 | AB99: =(L99*D99)+(D99*R99) -> 1869.2902 | AC99: =AB99-AA99 -> 56.495413 | AD99: =(AB99/AA99)-1 -> 0.031164815 | AF99: =F99+ABS(O99) -> -100 | AG99: =F99 -> -100 | AH99: =DATEDIF($C$31,C99,"d") -> 476 | AI99: =(AH$30-AH99)/AH$30 -> 0.92427617 | AJ99: =AI99*AF99 -> -92.427617 | AK99: =$AI99*AG99 -> -92.427617
B100: =IF(C99="","",IF(C$30<C100,"",B99+1)) | C100: =IF(Sheet3!A71="","",Sheet3!A71) -> 38110 | D100: =IF(C100="","",Sheet3!E71) -> 24.74 | E100: =_xlfn.XLOOKUP(WEEKNUM(C100)&YEAR(C100),Sheet4!C:C,Sheet4!B:B,0) -> 0 | F100: =IF(int=Weekly,-$D$5,IF(int=Bi_Weekly,0,IF(int=Monthly,0,IF(int=Quarterly,0,IF(int=Yearly,0,IF(int=None,0,0)))))) -> 0 | H100: =H99+F100 -> -1750 | J100: =IF(D$24=0,"",ABS($F100*D$24)/D100) -> 0 | L100: =IF(D100=0,"",L99+J100) -> 72.482868 | N100: =IF(D100=0,"",L100*E100) -> 0 | O100: =-(IF(D100=0,"",N100)) -> 0 | P100: =P99+F100+O100 -> -1812.326 | Q100: =IF(D100=0,"",ABS($O100)/D100) -> 0 | R100: =IF(D100=0,"",Q100+R99) -> 2.5890261 | S100: =IF(D100=0,"",L100+R100) -> 75.071894 | T100: =IF(D100=0,"",D100*J100)+T99 -> 1750 | U100: =IF(D100=0,"",L100*D100) -> 1793.2262 | V100: =(U100/T100)-1 -> 0.024700665 | W100: =U100-T100 -> 43.226164 | X100: =ABS(O100)+X99 -> 62.794759 | Y100: =((U100+X100)/T100)-1 -> 0.060583384 | AA100: =(D100*Q100)+(D100*J100)+AA99 -> 1812.7948 | AB100: =(L100*D100)+(D100*R100) -> 1857.2787 | AC100: =AB100-AA100 -> 44.48391 | AD100: =(AB100/AA100)-1 -> 0.024538856 | AF100: =F100+ABS(O100) -> 0 | AG100: =F100 -> 0 | AH100: =DATEDIF($C$31,C100,"d") -> 483 | AI100: =(AH$30-AH100)/AH$30 -> 0.92316258 | AJ100: =AI100*AF100 -> 0 | AK100: =$AI100*AG100 -> 0
B101: =IF(C100="","",IF(C$30<C101,"",B100+1)) | C101: =IF(Sheet3!A72="","",Sheet3!A72) -> 38117 | D101: =IF(C101="","",Sheet3!E72) -> 24.5 | E101: =_xlfn.XLOOKUP(WEEKNUM(C101)&YEAR(C101),Sheet4!C:C,Sheet4!B:B,0) -> 0 | F101: =IF(int=Weekly,-$D$5,IF(int=Bi_Weekly,-$D$5,IF(int=Monthly,0,IF(int=Quarterly,0,IF(int=Yearly,0,IF(int=None,0,0)))))) -> 0 | H101: =H100+F101 -> -1750 | J101: =IF(D$24=0,"",ABS($F101*D$24)/D101) -> 0 | L101: =IF(D101=0,"",L100+J101) -> 72.482868 | N101: =IF(D101=0,"",L101*E101) -> 0 | O101: =-(IF(D101=0,"",N101)) -> 0 | P101: =P100+F101+O101 -> -1812.326 | Q101: =IF(D101=0,"",ABS($O101)/D101) -> 0 | R101: =IF(D101=0,"",Q101+R100) -> 2.5890261 | S101: =IF(D101=0,"",L101+R101) -> 75.071894 | T101: =IF(D101=0,"",D101*J101)+T100 -> 1750 | U101: =IF(D101=0,"",L101*D101) -> 1775.8303 | V101: =(U101/T101)-1 -> 0.014760157 | W101: =U101-T101 -> 25.830275 | X101: =ABS(O101)+X100 -> 62.794759 | Y101: =((U101+X101)/T101)-1 -> 0.050642877 | AA101: =(D101*Q101)+(D101*J101)+AA100 -> 1812.7948 | AB101: =(L101*D101)+(D101*R101) -> 1839.2614 | AC101: =AB101-AA101 -> 26.466656 | AD101: =(AB101/AA101)-1 -> 0.014599918 | AF101: =F101+ABS(O101) -> 0 | AG101: =F101 -> 0 | AH101: =DATEDIF($C$31,C101,"d") -> 490 | AI101: =(AH$30-AH101)/AH$30 -> 0.922049 | AJ101: =AI101*AF101 -> 0 | AK101: =$AI101*AG101 -> 0
B102: =IF(C101="","",IF(C$30<C102,"",B101+1)) | C102: =IF(Sheet3!A73="","",Sheet3!A73) -> 38124 | D102: =IF(C102="","",Sheet3!E73) -> 24.33 | E102: =_xlfn.XLOOKUP(WEEKNUM(C102)&YEAR(C102),Sheet4!C:C,Sheet4!B:B,0) -> 0 | F102: =IF(int=Weekly,-$D$5,IF(int=Bi_Weekly,0,IF(int=Monthly,0,IF(int=Quarterly,0,IF(int=Yearly,0,IF(int=None,0,0)))))) -> 0 | H102: =H101+F102 -> -1750 | J102: =IF(D$24=0,"",ABS($F102*D$24)/D102) -> 0 | L102: =IF(D102=0,"",L101+J102) -> 72.482868 | N102: =IF(D102=0,"",L102*E102) -> 0 | O102: =-(IF(D102=0,"",N102)) -> 0 | P102: =P101+F102+O102 -> -1812.326 | Q102: =IF(D102=0,"",ABS($O102)/D102) -> 0 | R102: =IF(D102=0,"",Q102+R101) -> 2.5890261 | S102: =IF(D102=0,"",L102+R102) -> 75.071894 | T102: =IF(D102=0,"",D102*J102)+T101 -> 1750 | U102: =IF(D102=0,"",L102*D102) -> 1763.5082 | V102: =(U102/T102)-1 -> 0.0077189643 | W102: =U102-T102 -> 13.508188 | X102: =ABS(O102)+X101 -> 62.794759 | Y102: =((U102+X102)/T102)-1 -> 0.043601684 | AA102: =(D102*Q102)+(D102*J102)+AA101 -> 1812.7948 | AB102: =(L102*D102)+(D102*R102) -> 1826.4992 | AC102: =AB102-AA102 -> 13.704434 | AD102: =(AB102/AA102)-1 -> 0.0075598374 | AF102: =F102+ABS(O102) -> 0 | AG102: =F102 -> 0 | AH102: =DATEDIF($C$31,C102,"d") -> 497 | AI102: =(AH$30-AH102)/AH$30 -> 0.92093541 | AJ102: =AI102*AF102 -> 0 | AK102: =$AI102*AG102 -> 0
B103: =IF(C102="","",IF(C$30<C103,"",B102+1)) | C103: =IF(Sheet3!A74="","",Sheet3!A74) -> 38131 | D103: =IF(C103="","",Sheet3!E74) -> 23.700001 | E103: =_xlfn.XLOOKUP(WEEKNUM(C103)&YEAR(C103),Sheet4!C:C,Sheet4!B:B,0) -> 0 | F103: =IF(int=Weekly,-$D$5,IF(int=Bi_Weekly,-$D$5,IF(int=Monthly,-$D$5,IF(int=Quarterly,0,IF(int=Yearly,0,IF(int=None,0,0)))))) -> -100 | H103: =H102+F103 -> -1850 | J103: =IF(D$24=0,"",ABS($F103*D$24)/D103) -> 4.2194091 | L103: =IF(D103=0,"",L102+J103) -> 76.702277 | N103: =IF(D103=0,"",L103*E103) -> 0 | O103: =-(IF(D103=0,"",N103)) -> 0 | P103: =P102+F103+O103 -> -1912.326 | Q103: =IF(D103=0,"",ABS($O103)/D103) -> 0 | R103: =IF(D103=0,"",Q103+R102) -> 2.5890261 | S103: =IF(D103=0,"",L103+R103) -> 79.291304 | T103: =IF(D103=0,"",D103*J103)+T102 -> 1850 | U103: =IF(D103=0,"",L103*D103) -> 1817.8441 | V103: =(U103/T103)-1 -> -0.017381593 | W103: =U103-T103 -> -32.155947 | X103: =ABS(O103)+X102 -> 62.794759 | Y103: =((U103+X103)/T103)-1 -> 0.01656152 | AA103: =(D103*Q103)+(D103*J103)+AA102 -> 1912.7948 | AB103: =(L103*D103)+(D103*R103) -> 1879.204 | AC103: =AB103-AA103 -> -33.590785 | AD103: =(AB103/AA103)-1 -> -0.017561103 | AF103: =F103+ABS(O103) -> -100 | AG103: =F103 -> -100 | AH103: =DATEDIF($C$31,C103,"d") -> 504 | AI103: =(AH$30-AH103)/AH$30 -> 0.91982183 | AJ103: =AI103*AF103 -> -91.982183 | AK103: =$AI103*AG103 -> -91.982183
B104: =IF(C103="","",IF(C$30<C104,"",B103+1)) | C104: =IF(Sheet3!A75="","",Sheet3!A75) -> 38138 | D104: =IF(C104="","",Sheet3!E75) -> 23.93 | E104: =_xlfn.XLOOKUP(WEEKNUM(C104)&YEAR(C104),Sheet4!C:C,Sheet4!B:B,0) -> 0 | F104: =IF(int=Weekly,-$D$5,IF(int=Bi_Weekly,0,IF(int=Monthly,0,IF(int=Quarterly,0,IF(int=Yearly,0,IF(int=None,0,0)))))) -> 0 | H104: =H103+F104 -> -1850 | J104: =IF(D$24=0,"",ABS($F104*D$24)/D104) -> 0 | L104: =IF(D104=0,"",L103+J104) -> 76.702277 | N104: =IF(D104=0,"",L104*E104) -> 0 | O104: =-(IF(D104=0,"",N104)) -> 0 | P104: =P103+F104+O104 -> -1912.326 | Q104: =IF(D104=0,"",ABS($O104)/D104) -> 0 | R104: =IF(D104=0,"",Q104+R103) -> 2.5890261 | S104: =IF(D104=0,"",L104+R104) -> 79.291304 | T104: =IF(D104=0,"",D104*J104)+T103 -> 1850 | U104: =IF(D104=0,"",L104*D104) -> 1835.4855 | V104: =(U104/T104)-1 -> -0.0078456757 | W104: =U104-T104 -> -14.5145 | X104: =ABS(O104)+X103 -> 62.794759 | Y104: =((U104+X104)/T104)-1 -> 0.026097437 | AA104: =(D104*Q104)+(D104*J104)+AA103 -> 1912.7948 | AB104: =(L104*D104)+(D104*R104) -> 1897.4409 | AC104: =AB104-AA104 -> -15.353864 | AD104: =(AB104/AA104)-1 -> -0.0080269272 | AF104: =F104+ABS(O104) -> 0 | AG104: =F104 -> 0 | AH104: =DATEDIF($C$31,C104,"d") -> 511 | AI104: =(AH$30-AH104)/AH$30 -> 0.91870824 | AJ104: =AI104*AF104 -> 0 | AK104: =$AI104*AG104 -> 0
B105: =IF(C104="","",IF(C$30<C105,"",B104+1)) | C105: =IF(Sheet3!A76="","",Sheet3!A76) -> 38145 | D105: =IF(C105="","",Sheet3!E76) -> 24.809999 | E105: =_xlfn.XLOOKUP(WEEKNUM(C105)&YEAR(C105),Sheet4!C:C,Sheet4!B:B,0) -> 0 | F105: =IF(int=Weekly,-$D$5,IF(int=Bi_Weekly,-$D$5,IF(int=Monthly,0,IF(int=Quarterly,0,IF(int=Yearly,0,IF(int=None,0,0)))))) -> 0 | H105: =H104+F105 -> -1850 | J105: =IF(D$24=0,"",ABS($F105*D$24)/D105) -> 0 | L105: =IF(D105=0,"",L104+J105) -> 76.702277 | N105: =IF(D105=0,"",L105*E105) -> 0 | O105: =-(IF(D105=0,"",N105)) -> 0 | P105: =P104+F105+O105 -> -1912.326 | Q105: =IF(D105=0,"",ABS($O105)/D105) -> 0 | R105: =IF(D105=0,"",Q105+R104) -> 2.5890261 | S105: =IF(D105=0,"",L105+R105) -> 79.291304 | T105: =IF(D105=0,"",D105*J105)+T104 -> 1850 | U105: =IF(D105=0,"",L105*D105) -> 1902.9834 | V105: =(U105/T105)-1 -> 0.028639691 | W105: =U105-T105 -> 52.983428 | X105: =ABS(O105)+X104 -> 62.794759 | Y105: =((U105+X105)/T105)-1 -> 0.062582803 | AA105: =(D105*Q105)+(D105*J105)+AA104 -> 1912.7948 | AB105: =(L105*D105)+(D105*R105) -> 1967.2172 | AC105: =AB105-AA105 -> 54.422404 | AD105: =(AB105/AA105)-1 -> 0.028451774 | AF105: =F105+ABS(O105) -> 0 | AG105: =F105 -> 0 | AH105: =DATEDIF($C$31,C105,"d") -> 518 | AI105: =(AH$30-AH105)/AH$30 -> 0.91759465 | AJ105: =AI105*AF105 -> 0 | AK105: =$AI105*AG105 -> 0
B106: =IF(C105="","",IF(C$30<C106,"",B105+1)) | C106: =IF(Sheet3!A77="","",Sheet3!A77) -> 38152 | D106: =IF(C106="","",Sheet3!E77) -> 24.6 | E106: =_xlfn.XLOOKUP(WEEKNUM(C106)&YEAR(C106),Sheet4!C:C,Sheet4!B:B,0) -> 0 | F106: =IF(int=Weekly,-$D$5,IF(int=Bi_Weekly,0,IF(int=Monthly,0,IF(int=Quarterly,0,IF(int=Yearly,0,IF(int=None,0,0)))))) -> 0 | H106: =H105+F106 -> -1850 | J106: =IF(D$24=0,"",ABS($F106*D$24)/D106) -> 0 | L106: =IF(D106=0,"",L105+J106) -> 76.702277 | N106: =IF(D106=0,"",L106*E106) -> 0 | O106: =-(IF(D106=0,"",N106)) -> 0 | P106: =P105+F106+O106 -> -1912.326 | Q106: =IF(D106=0,"",ABS($O106)/D106) -> 0 | R106: =IF(D106=0,"",Q106+R105) -> 2.5890261 | S106: =IF(D106=0,"",L106+R106) -> 79.291304 | T106: =IF(D106=0,"",D106*J106)+T105 -> 1850 | U106: =IF(D106=0,"",L106*D106) -> 1886.876 | V106: =(U106/T106)-1 -> 0.019932987 | W106: =U106-T106 -> 36.876026 | X106: =ABS(O106)+X105 -> 62.794759 | Y106: =((U106+X106)/T106)-1 -> 0.0538761 | AA106: =(D106*Q106)+(D106*J106)+AA105 -> 1912.7948 | AB106: =(L106*D106)+(D106*R106) -> 1950.5661 | AC106: =AB106-AA106 -> 37.771309 | AD106: =(AB106/AA106)-1 -> 0.019746661 | AF106: =F106+ABS(O106) -> 0 | AG106: =F106 -> 0 | AH106: =DATEDIF($C$31,C106,"d") -> 525 | AI106: =(AH$30-AH106)/AH$30 -> 0.91648107 | AJ106: =AI106*AF106 -> 0 | AK106: =$AI106*AG106 -> 0
B107: =IF(C106="","",IF(C$30<C107,"",B106+1)) | C107: =IF(Sheet3!A78="","",Sheet3!A78) -> 38159 | D107: =IF(C107="","",Sheet3!E78) -> 23.799999 | E107: =_xlfn.XLOOKUP(WEEKNUM(C107)&YEAR(C107),Sheet4!C:C,Sheet4!B:B,0) -> 0 | F107: =IF(int=Weekly,-$D$5,IF(int=Bi_Weekly,-$D$5,IF(int=Monthly,-$D$5,IF(int=Quarterly,0,IF(int=Yearly,0,IF(int=None,0,0)))))) -> -100 | H107: =H106+F107 -> -1950 | J107: =IF(D$24=0,"",ABS($F107*D$24)/D107) -> 4.2016808 | L107: =IF(D107=0,"",L106+J107) -> 80.903958 | N107: =IF(D107=0,"",L107*E107) -> 0 | O107: =-(IF(D107=0,"",N107)) -> 0 | P107: =P106+F107+O107 -> -2012.326 | Q107: =IF(D107=0,"",ABS($O107)/D107) -> 0 | R107: =IF(D107=0,"",Q107+R106) -> 2.5890261 | S107: =IF(D107=0,"",L107+R107) -> 83.492984 | T107: =IF(D107=0,"",D107*J107)+T106 -> 1950 | U107: =IF(D107=0,"",L107*D107) -> 1925.5141 | V107: =(U107/T107)-1 -> -0.012556858 | W107: =U107-T107 -> -24.485873 | X107: =ABS(O107)+X106 -> 62.794759 | Y107: =((U107+X107)/T107)-1 -> 0.019645583 | AA107: =(D107*Q107)+(D107*J107)+AA106 -> 2012.7948 | AB107: =(L107*D107)+(D107*R107) -> 1987.1329 | AC107: =AB107-AA107 -> -25.661813 | AD107: =(AB107/AA107)-1 -> -0.012749344 | AF107: =F107+ABS(O107) -> -100 | AG107: =F107 -> -100 | AH107: =DATEDIF($C$31,C107,"d") -> 532 | AI107: =(AH$30-AH107)/AH$30 -> 0.91536748 | AJ107: =AI107*AF107 -> -91.536748 | AK107: =$AI107*AG107 -> -91.536748
B108: =IF(C107="","",IF(C$30<C108,"",B107+1)) | C108: =IF(Sheet3!A79="","",Sheet3!A79) -> 38166 | D108: =IF(C108="","",Sheet3!E79) -> 24.110001 | E108: =_xlfn.XLOOKUP(WEEKNUM(C108)&YEAR(C108),Sheet4!C:C,Sheet4!B:B,0) -> 0 | F108: =IF(int=Weekly,-$D$5,IF(int=Bi_Weekly,0,IF(int=Monthly,0,IF(int=Quarterly,0,IF(int=Yearly,0,IF(int=None,0,0)))))) -> 0 | H108: =H107+F108 -> -1950 | J108: =IF(D$24=0,"",ABS($F108*D$24)/D108) -> 0 | L108: =IF(D108=0,"",L107+J108) -> 80.903958 | N108: =IF(D108=0,"",L108*E108) -> 0 | O108: =-(IF(D108=0,"",N108)) -> 0 | P108: =P107+F108+O108 -> -2012.326 | Q108: =IF(D108=0,"",ABS($O108)/D108) -> 0 | R108: =IF(D108=0,"",Q108+R107) -> 2.5890261 | S108: =IF(D108=0,"",L108+R108) -> 83.492984 | T108: =IF(D108=0,"",D108*J108)+T107 -> 1950 | U108: =IF(D108=0,"",L108*D108) -> 1950.5945 | V108: =(U108/T108)-1 -> 0.00030488007 | W108: =U108-T108 -> 0.59451615 | X108: =ABS(O108)+X107 -> 62.794759 | Y108: =((U108+X108)/T108)-1 -> 0.032507321 | AA108: =(D108*Q108)+(D108*J108)+AA107 -> 2012.7948 | AB108: =(L108*D108)+(D108*R108) -> 2013.0159 | AC108: =AB108-AA108 -> 0.22117911 | AD108: =(AB108/AA108)-1 -> 0.00010988657 | AF108: =F108+ABS(O108) -> 0 | AG108: =F108 -> 0 | AH108: =DATEDIF($C$31,C108,"d") -> 539 | AI108: =(AH$30-AH108)/AH$30 -> 0.9142539 | AJ108: =AI108*AF108 -> 0 | AK108: =$AI108*AG108 -> 0
B109: =IF(C108="","",IF(C$30<C109,"",B108+1)) | C109: =IF(Sheet3!A80="","",Sheet3!A80) -> 38173 | D109: =IF(C109="","",Sheet3!E80) -> 23.59 | E109: =_xlfn.XLOOKUP(WEEKNUM(C109)&YEAR(C109),Sheet4!C:C,Sheet4!B:B,0) -> 0.3125 | F109: =IF(int=Weekly,-$D$5,IF(int=Bi_Weekly,-$D$5,IF(int=Monthly,0,IF(int=Quarterly,-$D$5,IF(int=Yearly,0,IF(int=None,0,0)))))) -> 0 | H109: =H108+F109 -> -1950 | J109: =IF(D$24=0,"",ABS($F109*D$24)/D109) -> 0 | L109: =IF(D109=0,"",L108+J109) -> 80.903958 | N109: =IF(D109=0,"",L109*E109) -> 25.282487 | O109: =-(IF(D109=0,"",N109)) -> -25.282487 | P109: =P108+F109+O109 -> -2037.6085 | Q109: =IF(D109=0,"",ABS($O109)/D109) -> 1.071746 | R109: =IF(D109=0,"",Q109+R108) -> 3.6607721 | S109: =IF(D109=0,"",L109+R109) -> 84.56473 | T109: =IF(D109=0,"",D109*J109)+T108 -> 1950 | U109: =IF(D109=0,"",L109*D109) -> 1908.5244 | V109: =(U109/T109)-1 -> -0.02126955 | W109: =U109-T109 -> -41.475623 | X109: =ABS(O109)+X108 -> 88.077246 | Y109: =((U109+X109)/T109)-1 -> 0.023898268 | AA109: =(D109*Q109)+(D109*J109)+AA108 -> 2038.0772 | AB109: =(L109*D109)+(D109*R109) -> 1994.882 | AC109: =AB109-AA109 -> -43.195256 | AD109: =(AB109/AA109)-1 -> -0.021194121 | AF109: =F109+ABS(O109) -> 25.282487 | AG109: =F109 -> 0 | AH109: =DATEDIF($C$31,C109,"d") -> 546 | AI109: =(AH$30-AH109)/AH$30 -> 0.91314031 | AJ109: =AI109*AF109 -> 23.086458 | AK109: =$AI109*AG109 -> 0
B110: =IF(C109="","",IF(C$30<C110,"",B109+1)) | C110: =IF(Sheet3!A81="","",Sheet3!A81) -> 38180 | D110: =IF(C110="","",Sheet3!E81) -> 23.1 | E110: =_xlfn.XLOOKUP(WEEKNUM(C110)&YEAR(C110),Sheet4!C:C,Sheet4!B:B,0) -> 0 | F110: =IF(int=Weekly,-$D$5,IF(int=Bi_Weekly,0,IF(int=Monthly,0,IF(int=Quarterly,0,IF(int=Yearly,0,IF(int=None,0,0)))))) -> 0 | H110: =H109+F110 -> -1950 | J110: =IF(D$24=0,"",ABS($F110*D$24)/D110) -> 0 | L110: =IF(D110=0,"",L109+J110) -> 80.903958 | N110: =IF(D110=0,"",L110*E110) -> 0 | O110: =-(IF(D110=0,"",N110)) -> 0 | P110: =P109+F110+O110 -> -2037.6085 | Q110: =IF(D110=0,"",ABS($O110)/D110) -> 0 | R110: =IF(D110=0,"",Q110+R109) -> 3.6607721 | S110: =IF(D110=0,"",L110+R110) -> 84.56473 | T110: =IF(D110=0,"",D110*J110)+T109 -> 1950 | U110: =IF(D110=0,"",L110*D110) -> 1868.8814 | V110: =(U110/T110)-1 -> -0.041599263 | W110: =U110-T110 -> -81.118563 | X110: =ABS(O110)+X109 -> 88.077246 | Y110: =((U110+X110)/T110)-1 -> 0.0035685555 | AA110: =(D110*Q110)+(D110*J110)+AA109 -> 2038.0772 | AB110: =(L110*D110)+(D110*R110) -> 1953.4453 | AC110: =AB110-AA110 -> -84.631974 | AD110: =(AB110/AA110)-1 -> -0.041525401 | AF110: =F110+ABS(O110) -> 0 | AG110: =F110 -> 0 | AH110: =DATEDIF($C$31,C110,"d") -> 553 | AI110: =(AH$30-AH110)/AH$30 -> 0.91202673 | AJ110: =AI110*AF110 -> 0 | AK110: =$AI110*AG110 -> 0
B111: =IF(C110="","",IF(C$30<C111,"",B110+1)) | C111: =IF(Sheet3!A82="","",Sheet3!A82) -> 38187 | D111: =IF(C111="","",Sheet3!E82) -> 24.219999 | E111: =_xlfn.XLOOKUP(WEEKNUM(C111)&YEAR(C111),Sheet4!C:C,Sheet4!B:B,0) -> 0 | F111: =IF(int=Weekly,-$D$5,IF(int=Bi_Weekly,-$D$5,IF(int=Monthly,-$D$5,IF(int=Quarterly,0,IF(int=Yearly,0,IF(int=None,0,0)))))) -> -100 | H111: =H110+F111 -> -2050 | J111: =IF(D$24=0,"",ABS($F111*D$24)/D111) -> 4.1288193 | L111: =IF(D111=0,"",L110+J111) -> 85.032778 | N111: =IF(D111=0,"",L111*E111) -> 0 | O111: =-(IF(D111=0,"",N111)) -> 0 | P111: =P110+F111+O111 -> -2137.6085 | Q111: =IF(D111=0,"",ABS($O111)/D111) -> 0 | R111: =IF(D111=0,"",Q111+R110) -> 3.6607721 | S111: =IF(D111=0,"",L111+R111) -> 88.69355 | T111: =IF(D111=0,"",D111*J111)+T110 -> 2050 | U111: =IF(D111=0,"",L111*D111) -> 2059.4938 | V111: =(U111/T111)-1 -> 0.004631117 | W111: =U111-T111 -> 9.4937898 | X111: =ABS(O111)+X110 -> 88.077246 | Y111: =((U111+X111)/T111)-1 -> 0.047595627 | AA111: =(D111*Q111)+(D111*J111)+AA110 -> 2138.0772 | AB111: =(L111*D111)+(D111*R111) -> 2148.1577 | AC111: =AB111-AA111 -> 10.080439 | AD111: =(AB111/AA111)-1 -> 0.0047147217 | AF111: =F111+ABS(O111) -> -100 | AG111: =F111 -> -100 | AH111: =DATEDIF($C$31,C111,"d") -> 560 | AI111: =(AH$30-AH111)/AH$30 -> 0.91091314 | AJ111: =AI111*AF111 -> -91.091314 | AK111: =$AI111*AG111 -> -91.091314
B112: =IF(C111="","",IF(C$30<C112,"",B111+1)) | C112: =IF(Sheet3!A83="","",Sheet3!A83) -> 38194 | D112: =IF(C112="","",Sheet3!E83) -> 25.34 | E112: =_xlfn.XLOOKUP(WEEKNUM(C112)&YEAR(C112),Sheet4!C:C,Sheet4!B:B,0) -> 0 | F112: =IF(int=Weekly,-$D$5,IF(int=Bi_Weekly,0,IF(int=Monthly,0,IF(int=Quarterly,0,IF(int=Yearly,0,IF(int=None,0,0)))))) -> 0 | H112: =H111+F112 -> -2050 | J112: =IF(D$24=0,"",ABS($F112*D$24)/D112) -> 0 | L112: =IF(D112=0,"",L111+J112) -> 85.032778 | N112: =IF(D112=0,"",L112*E112) -> 0 | O112: =-(IF(D112=0,"",N112)) -> 0 | P112: =P111+F112+O112 -> -2137.6085 | Q112: =IF(D112=0,"",ABS($O112)/D112) -> 0 | R112: =IF(D112=0,"",Q112+R111) -> 3.6607721 | S112: =IF(D112=0,"",L112+R112) -> 88.69355 | T112: =IF(D112=0,"",D112*J112)+T111 -> 2050 | U112: =IF(D112=0,"",L112*D112) -> 2154.7306 | V112: =(U112/T112)-1 -> 0.051088091 | W112: =U112-T112 -> 104.73059 | X112: =ABS(O112)+X111 -> 88.077246 | Y112: =((U112+X112)/T112)-1 -> 0.094052601 | AA112: =(D112*Q112)+(D112*J112)+AA111 -> 2138.0772 | AB112: =(L112*D112)+(D112*R112) -> 2247.4945 | AC112: =AB112-AA112 -> 109.4173 | AD112: =(AB112/AA112)-1 -> 0.051175562 | AF112: =F112+ABS(O112) -> 0 | AG112: =F112 -> 0 | AH112: =DATEDIF($C$31,C112,"d") -> 567 | AI112: =(AH$30-AH112)/AH$30 -> 0.90979955 | AJ112: =AI112*AF112 -> 0 | AK112: =$AI112*AG112 -> 0
B113: =IF(C112="","",IF(C$30<C113,"",B112+1)) | C113: =IF(Sheet3!A84="","",Sheet3!A84) -> 38201 | D113: =IF(C113="","",Sheet3!E84) -> 24.85 | E113: =_xlfn.XLOOKUP(WEEKNUM(C113)&YEAR(C113),Sheet4!C:C,Sheet4!B:B,0) -> 0 | F113: =IF(int=Weekly,-$D$5,IF(int=Bi_Weekly,-$D$5,IF(int=Monthly,0,IF(int=Quarterly,0,IF(int=Yearly,0,IF(int=None,0,0)))))) -> 0 | H113: =H112+F113 -> -2050 | J113: =IF(D$24=0,"",ABS($F113*D$24)/D113) -> 0 | L113: =IF(D113=0,"",L112+J113) -> 85.032778 | N113: =IF(D113=0,"",L113*E113) -> 0 | O113: =-(IF(D113=0,"",N113)) -> 0 | P113: =P112+F113+O113 -> -2137.6085 | Q113: =IF(D113=0,"",ABS($O113)/D113) -> 0 | R113: =IF(D113=0,"",Q113+R112) -> 3.6607721 | S113: =IF(D113=0,"",L113+R113) -> 88.69355 | T113: =IF(D113=0,"",D113*J113)+T112 -> 2050 | U113: =IF(D113=0,"",L113*D113) -> 2113.0645 | V113: =(U113/T113)-1 -> 0.030763183 | W113: =U113-T113 -> 63.064525 | X113: =ABS(O113)+X112 -> 88.077246 | Y113: =((U113+X113)/T113)-1 -> 0.073727693 | AA113: =(D113*Q113)+(D113*J113)+AA112 -> 2138.0772 | AB113: =(L113*D113)+(D113*R113) -> 2204.0347 | AC113: =AB113-AA113 -> 65.957464 | AD113: =(AB113/AA113)-1 -> 0.030848962 | AF113: =F113+ABS(O113) -> 0 | AG113: =F113 -> 0 | AH113: =DATEDIF($C$31,C113,"d") -> 574 | AI113: =(AH$30-AH113)/AH$30 -> 0.90868597 | AJ113: =AI113*AF113 -> 0 | AK113: =$AI113*AG113 -> 0
B114: =IF(C113="","",IF(C$30<C114,"",B113+1)) | C114: =IF(Sheet3!A85="","",Sheet3!A85) -> 38208 | D114: =IF(C114="","",Sheet3!E85) -> 25.059999 | E114: =_xlfn.XLOOKUP(WEEKNUM(C114)&YEAR(C114),Sheet4!C:C,Sheet4!B:B,0) -> 0 | F114: =IF(int=Weekly,-$D$5,IF(int=Bi_Weekly,0,IF(int=Monthly,0,IF(int=Quarterly,0,IF(int=Yearly,0,IF(int=None,0,0)))))) -> 0 | H114: =H113+F114 -> -2050 | J114: =IF(D$24=0,"",ABS($F114*D$24)/D114) -> 0 | L114: =IF(D114=0,"",L113+J114) -> 85.032778 | N114: =IF(D114=0,"",L114*E114) -> 0 | O114: =-(IF(D114=0,"",N114)) -> 0 | P114: =P113+F114+O114 -> -2137.6085 | Q114: =IF(D114=0,"",ABS($O114)/D114) -> 0 | R114: =IF(D114=0,"",Q114+R113) -> 3.6607721 | S114: =IF(D114=0,"",L114+R114) -> 88.69355 | T114: =IF(D114=0,"",D114*J114)+T113 -> 2050 | U114: =IF(D114=0,"",L114*D114) -> 2130.9213 | V114: =(U114/T114)-1 -> 0.039473816 | W114: =U114-T114 -> 80.921323 | X114: =ABS(O114)+X113 -> 88.077246 | Y114: =((U114+X114)/T114)-1 -> 0.082438326 | AA114: =(D114*Q114)+(D114*J114)+AA113 -> 2138.0772 | AB114: =(L114*D114)+(D114*R114) -> 2222.6603 | AC114: =AB114-AA114 -> 84.583021 | AD114: =(AB114/AA114)-1 -> 0.03956032 | AF114: =F114+ABS(O114) -> 0 | AG114: =F114 -> 0 | AH114: =DATEDIF($C$31,C114,"d") -> 581 | AI114: =(AH$30-AH114)/AH$30 -> 0.90757238 | AJ114: =AI114*AF114 -> 0 | AK114: =$AI114*AG114 -> 0
B115: =IF(C114="","",IF(C$30<C115,"",B114+1)) | C115: =IF(Sheet3!A86="","",Sheet3!A86) -> 38215 | D115: =IF(C115="","",Sheet3!E86) -> 25.57 | E115: =_xlfn.XLOOKUP(WEEKNUM(C115)&YEAR(C115),Sheet4!C:C,Sheet4!B:B,0) -> 0 | F115: =IF(int=Weekly,-$D$5,IF(int=Bi_Weekly,-$D$5,IF(int=Monthly,-$D$5,IF(int=Quarterly,0,IF(int=Yearly,0,IF(int=None,0,0)))))) -> -100 | H115: =H114+F115 -> -2150 | J115: =IF(D$24=0,"",ABS($F115*D$24)/D115) -> 3.910833 | L115: =IF(D115=0,"",L114+J115) -> 88.943611 | N115: =IF(D115=0,"",L115*E115) -> 0 | O115: =-(IF(D115=0,"",N115)) -> 0 | P115: =P114+F115+O115 -> -2237.6085 | Q115: =IF(D115=0,"",ABS($O115)/D115) -> 0 | R115: =IF(D115=0,"",Q115+R114) -> 3.6607721 | S115: =IF(D115=0,"",L115+R115) -> 92.604383 | T115: =IF(D115=0,"",D115*J115)+T114 -> 2150 | U115: =IF(D115=0,"",L115*D115) -> 2274.2881 | V115: =(U115/T115)-1 -> 0.05780843 | W115: =U115-T115 -> 124.28812 | X115: =ABS(O115)+X114 -> 88.077246 | Y115: =((U115+X115)/T115)-1 -> 0.098774591 | AA115: =(D115*Q115)+(D115*J115)+AA114 -> 2238.0772 | AB115: =(L115*D115)+(D115*R115) -> 2367.8941 | AC115: =AB115-AA115 -> 129.81682 | AD115: =(AB115/AA115)-1 -> 0.058003726 | AF115: =F115+ABS(O115) -> -100 | AG115: =F115 -> -100 | AH115: =DATEDIF($C$31,C115,"d") -> 588 | AI115: =(AH$30-AH115)/AH$30 -> 0.9064588 | AJ115: =AI115*AF115 -> -90.64588 | AK115: =$AI115*AG115 -> -90.64588
...

Sheet Sheet3
A1: Date | B1: Open | C1: High | D1: Low | E1: Close | G1: Date | H1: Open | I1: High | J1: Low
A2: 37627 | B2: 29.969999 | C2: 31.65 | D2: 28.549999 | E2: 28.799999 | G2: 37627 | H2: 29.969999 | I2: 31.65 | J2: 28.549999
A3: 37634 | B3: 29.25 | C3: 29.99 | D3: 27.059999 | E3: 27.280001 | G3: 37634 | H3: 29.25 | I3: 29.99 | J3: 27.059999
A4: 37641 | B4: 27.549999 | C4: 27.65 | D4: 24.25 | E4: 24.540001 | G4: 37641 | H4: 27.549999 | I4: 27.65 | J4: 24.25
A5: 37648 | B5: 24.5 | C5: 25.379999 | D5: 23.4 | E5: 24.440001 | G5: 37648 | H5: 24.5 | I5: 25.379999 | J5: 23.4
A6: 37655 | B6: 25.049999 | C6: 26.299999 | D6: 24.65 | E6: 25.18 | G6: 37655 | H6: 25.049999 | I6: 26.299999 | J6: 24.65
A7: 37662 | B7: 24.549999 | C7: 25 | D7: 22.15 | E7: 23.35 | G7: 37662 | H7: 24.549999 | I7: 25 | J7: 22.15
A8: 37669 | B8: 23.5 | C8: 23.85 | D8: 20.200001 | E8: 20.73 | G8: 37669 | H8: 23.5 | I8: 23.85 | J8: 20.200001
A9: 37676 | B9: 20.65 | C9: 21.450001 | D9: 20.120001 | E9: 20.799999 | G9: 37676 | H9: 20.65 | I9: 21.450001 | J9: 20.120001
A10: 37683 | B10: 21.200001 | C10: 21.34 | D10: 20.120001 | E10: 20.49 | G10: 37683 | H10: 21.200001 | I10: 21.34 | J10: 20.120001
A11: 37690 | B11: 20.15 | C11: 21.23 | D11: 18.85 | E11: 20.85 | G11: 37690 | H11: 20.15 | I11: 21.23 | J11: 18.85
A12: 37697 | B12: 20.85 | C12: 23.08 | D12: 20.58 | E12: 21.639999 | G12: 37697 | H12: 20.85 | I12: 23.08 | J12: 20.58
A13: 37704 | B13: 21.6 | C13: 21.6 | D13: 20.200001 | E13: 20.24 | G13: 37704 | H13: 21.6 | I13: 21.6 | J13: 20.200001
... A900: 43913 | B900: 27.389999 | C900: 28.299999 | D900: 26.08 | E900: 28.09 | G900: 43913 | H900: 27.389999 | I900: 28.299999 | J900: 26.08

Sheet Sheet4
A1: Date | B1: Dividends
A2: 37629 | B2: 0.27 | C2: =WEEKNUM(A2)&YEAR(A2) -> 22003 | E2: 37629 | F2: 0.27 | G2: =WEEKNUM(E2)&YEAR(E2) -> 22003 | I2: 37629 | J2: 0.27 | K2: =WEEKNUM(I2)&YEAR(I2) -> 22003 | M2: 37629 | N2: 0.27 | O2: =WEEKNUM(M2)&YEAR(M2) -> 22003 | Q2: 37629 | R2: 0.27 | S2: =WEEKNUM(Q2)&YEAR(Q2) -> 22003 | U2: 37629 | V2: 0.27 | W2: =WEEKNUM(U2)&YEAR(U2) -> 22003
A3: 37719 | B3: 0.2825 | C3: =WEEKNUM(A3)&YEAR(A3) -> 152003 | E3: 37719 | F3: 0.2825 | G3: =WEEKNUM(E3)&YEAR(E3) -> 152003 | I3: 37719 | J3: 0.2825 | K3: =WEEKNUM(I3)&YEAR(I3) -> 152003 | M3: 37719 | N3: 0.2825 | O3: =WEEKNUM(M3)&YEAR(M3) -> 152003 | Q3: 37719 | R3: 0.2825 | S3: =WEEKNUM(Q3)&YEAR(Q3) -> 152003 | U3: 37719 | V3: 0.2825 | W3: =WEEKNUM(U3)&YEAR(U3) -> 152003
A4: 37810 | B4: 0.2825 | C4: =WEEKNUM(A4)&YEAR(A4) -> 282003 | E4: 37810 | F4: 0.2825 | G4: =WEEKNUM(E4)&YEAR(E4) -> 282003 | I4: 37810 | J4: 0.2825 | K4: =WEEKNUM(I4)&YEAR(I4) -> 282003 | M4: 37810 | N4: 0.2825 | O4: =WEEKNUM(M4)&YEAR(M4) -> 282003 | Q4: 37810 | R4: 0.2825 | S4: =WEEKNUM(Q4)&YEAR(Q4) -> 282003 | U4: 37810 | V4: 0.2825 | W4: =WEEKNUM(U4)&YEAR(U4) -> 282003
A5: 37902 | B5: 0.2825 | C5: =WEEKNUM(A5)&YEAR(A5) -> 412003 | E5: 37902 | F5: 0.2825 | G5: =WEEKNUM(E5)&YEAR(E5) -> 412003 | I5: 37902 | J5: 0.2825 | K5: =WEEKNUM(I5)&YEAR(I5) -> 412003 | M5: 37902 | N5: 0.2825 | O5: =WEEKNUM(M5)&YEAR(M5) -> 412003 | Q5: 37902 | R5: 0.2825 | S5: =WEEKNUM(Q5)&YEAR(Q5) -> 412003 | U5: 37902 | V5: 0.2825 | W5: =WEEKNUM(U5)&YEAR(U5) -> 412003
A6: 37993 | B6: 0.3125 | C6: =WEEKNUM(A6)&YEAR(A6) -> 22004 | E6: 37993 | F6: 0.3125 | G6: =WEEKNUM(E6)&YEAR(E6) -> 22004 | I6: 37993 | J6: 0.3125 | K6: =WEEKNUM(I6)&YEAR(I6) -> 22004 | M6: 37993 | N6: 0.3125 | O6: =WEEKNUM(M6)&YEAR(M6) -> 22004 | Q6: 37993 | R6: 0.3125 | S6: =WEEKNUM(Q6)&YEAR(Q6) -> 22004 | U6: 37993 | V6: 0.3125 | W6: =WEEKNUM(U6)&YEAR(U6) -> 22004
A7: 38083 | B7: 0.3125 | C7: =WEEKNUM(A7)&YEAR(A7) -> 152004 | E7: 38083 | F7: 0.3125 | G7: =WEEKNUM(E7)&YEAR(E7) -> 152004 | I7: 38083 | J7: 0.3125 | K7: =WEEKNUM(I7)&YEAR(I7) -> 152004 | M7: 38083 | N7: 0.3125 | O7: =WEEKNUM(M7)&YEAR(M7) -> 152004 | Q7: 38083 | R7: 0.3125 | S7: =WEEKNUM(Q7)&YEAR(Q7) -> 152004 | U7: 38083 | V7: 0.3125 | W7: =WEEKNUM(U7)&YEAR(U7) -> 152004
A8: 38175 | B8: 0.3125 | C8: =WEEKNUM(A8)&YEAR(A8) -> 282004 | E8: 38175 | F8: 0.3125 | G8: =WEEKNUM(E8)&YEAR(E8) -> 282004 | I8: 38175 | J8: 0.3125 | K8: =WEEKNUM(I8)&YEAR(I8) -> 282004 | M8: 38175 | N8: 0.3125 | O8: =WEEKNUM(M8)&YEAR(M8) -> 282004 | Q8: 38175 | R8: 0.3125 | S8: =WEEKNUM(Q8)&YEAR(Q8) -> 282004 | U8: 38175 | V8: 0.3125 | W8: =WEEKNUM(U8)&YEAR(U8) -> 282004
A9: 38266 | B9: 0.3125 | C9: =WEEKNUM(A9)&YEAR(A9) -> 412004 | E9: 38266 | F9: 0.3125 | G9: =WEEKNUM(E9)&YEAR(E9) -> 412004 | I9: 38266 | J9: 0.3125 | K9: =WEEKNUM(I9)&YEAR(I9) -> 412004 | M9: 38266 | N9: 0.3125 | O9: =WEEKNUM(M9)&YEAR(M9) -> 412004 | Q9: 38266 | R9: 0.3125 | S9: =WEEKNUM(Q9)&YEAR(Q9) -> 412004 | U9: 38266 | V9: 0.3125 | W9: =WEEKNUM(U9)&YEAR(U9) -> 412004
A10: 38358 | B10: 0.3225 | C10: =WEEKNUM(A10)&YEAR(A10) -> 22005 | E10: 38358 | F10: 0.3225 | G10: =WEEKNUM(E10)&YEAR(E10) -> 22005 | I10: 38358 | J10: 0.3225 | K10: =WEEKNUM(I10)&YEAR(I10) -> 22005 | M10: 38358 | N10: 0.3225 | O10: =WEEKNUM(M10)&YEAR(M10) -> 22005 | Q10: 38358 | R10: 0.3225 | S10: =WEEKNUM(Q10)&YEAR(Q10) -> 22005 | U10: 38358 | V10: 0.3225 | W10: =WEEKNUM(U10)&YEAR(U10) -> 22005
A11: 38448 | B11: 0.3225 | C11: =WEEKNUM(A11)&YEAR(A11) -> 152005 | E11: 38448 | F11: 0.3225 | G11: =WEEKNUM(E11)&YEAR(E11) -> 152005 | I11: 38448 | J11: 0.3225 | K11: =WEEKNUM(I11)&YEAR(I11) -> 152005 | M11: 38448 | N11: 0.3225 | O11: =WEEKNUM(M11)&YEAR(M11) -> 152005 | Q11: 38448 | R11: 0.3225 | S11: =WEEKNUM(Q11)&YEAR(Q11) -> 152005 | U11: 38448 | V11: 0.3225 | W11: =WEEKNUM(U11)&YEAR(U11) -> 152005
A12: 38539 | B12: 0.3225 | C12: =WEEKNUM(A12)&YEAR(A12) -> 282005 | E12: 38539 | F12: 0.3225 | G12: =WEEKNUM(E12)&YEAR(E12) -> 282005 | I12: 38539 | J12: 0.3225 | K12: =WEEKNUM(I12)&YEAR(I12) -> 282005 | M12: 38539 | N12: 0.3225 | O12: =WEEKNUM(M12)&YEAR(M12) -> 282005 | Q12: 38539 | R12: 0.3225 | S12: =WEEKNUM(Q12)&YEAR(Q12) -> 282005 | U12: 38539 | V12: 0.3225 | W12: =WEEKNUM(U12)&YEAR(U12) -> 282005
A13: 38630 | B13: 0.3225 | C13: =WEEKNUM(A13)&YEAR(A13) -> 412005 | E13: 38630 | F13: 0.3225 | G13: =WEEKNUM(E13)&YEAR(E13) -> 412005 | I13: 38630 | J13: 0.3225 | K13: =WEEKNUM(I13)&YEAR(I13) -> 412005 | M13: 38630 | N13: 0.3225 | O13: =WEEKNUM(M13)&YEAR(M13) -> 412005 | Q13: 38630 | R13: 0.3225 | S13: =WEEKNUM(Q13)&YEAR(Q13) -> 412005 | U13: 38630 | V13: 0.3225 | W13: =WEEKNUM(U13)&YEAR(U13) -> 412005
... A70: 43839 | B70: 0.52 | C70: =WEEKNUM(A70)&YEAR(A70) -> 22020 | E70: 43839 | F70: 0.52 | G70: =WEEKNUM(E70)&YEAR(E70) -> 22020 | I70: 43839 | J70: 0.52 | K70: =WEEKNUM(I70)&YEAR(I70) -> 22020 | M70: 43839 | N70: 0.52 | O70: =WEEKNUM(M70)&YEAR(M70) -> 22020 | Q70: 43839 | R70: 0.52 | S70: =WEEKNUM(Q70)&YEAR(Q70) -> 22020 | U70: 43839 | V70: 0.52 | W70: =WEEKNUM(U70)&YEAR(U70) -> 22020

Sheet Sheet2
A1: S&P 500 | D1: NIKKEI | G1: IBEX | J1: 10-Yr Bond | M1: DJI
A2: Total | B2: =B497/B6-1 -> 0.56227233 | D2: Total | E2: =E494/E6-1 -> 0.12570833 | G2: Total | H2: =H497/H6-1 -> -0.3565497 | J2: Total | K2: =K497/K6-1 -> -0.47957447 | M2: Total | N2: =N497/N6-1 -> 0.49922123 | Q2: Weekly
A3: Annual | B3: =((B497/ABS(B6))^(1/(COUNT(B6:B497)/52)))-1 -> 0.048282546 | D3: Annual | E3: =((E494/ABS(E6))^(1/(COUNT(E6:E494)/52)))-1 -> 0.01267153 | G3: Annual | H3: =((H497/ABS(H6))^(1/(COUNT(H6:H497)/52)))-1 -> -0.045531173 | J3: Annual | K3: =((K497/ABS(K6))^(1/(COUNT(K6:K497)/52)))-1 -> -0.066699196 | M3: Annual | N3: =((N497/ABS(N6))^(1/(COUNT(N6:N497)/52)))-1 -> 0.04372824 | Q3: Bi-weekly
Q4: Monthly
A5: Date | B5: Close | C5: Return | D5: Date | E5: Close | F5: Return | G5: Date | H5: Close | I5: Return | J5: Date | K5: Close | L5: Return | M5: Date | N5: Close | O5: Return | Q5: Quarterly
A6: 39293 | B6: 1433.0601 | C6: =(B7-$B$6)/$B$6 -> 0.014360847 | D6: 39293 | E6: 16979.859 | F6: =(E7-$E$6)/$E$6 -> -0.01270738 | G6: 39293 | H6: 14534.3 | I6: =(H7-$H$6)/$H$6 -> -0.0055317019 | J6: 39293 | K6: 4.7 | L6: =(K7-$K$6)/$K$6 -> 0.016170213 | M6: 39293 | N6: 13181.91 | O6: =(N7-$N$6)/$N$6 -> 0.0043718917 | Q6: Yearly
A7: 39300 | B7: 1453.64 | C7: =(B8-$B$6)/$B$6 -> 0.0089876777 | D7: 39300 | E7: 16764.09 | F7: =(E8-$E$6)/$E$6 -> -0.10048256 | G7: 39300 | H7: 14453.9 | I7: =(H8-$H$6)/$H$6 -> -0.020420647 | J7: 39300 | K7: 4.776 | L7: =(K8-$K$6)/$K$6 -> -0.0057446809 | M7: 39300 | N7: 13239.54 | O7: =(N8-$N$6)/$N$6 -> -0.007800848 | Q7: None
A8: 39307 | B8: 1445.9399 | C8: =(B9-$B$6)/$B$6 -> 0.032315419 | D8: 39307 | E8: 15273.68 | F8: =(E9-$E$6)/$E$6 -> -0.043044505 | G8: 39307 | H8: 14237.5 | I8: =(H9-$H$6)/$H$6 -> -0.013753632 | J8: 39307 | K8: 4.673 | L8: =(K9-$K$6)/$K$6 -> -0.014255319 | M8: 39307 | N8: 13079.08 | O8: =(N9-$N$6)/$N$6 -> 0.014941686
A9: 39314 | B9: 1479.37 | C9: =(B10-$B$6)/$B$6 -> 0.028561211 | D9: 39314 | E9: 16248.97 | F9: =(E10-$E$6)/$E$6 -> -0.024191574 | G9: 39314 | H9: 14334.4 | I9: =(H10-$H$6)/$H$6 -> -0.0037497506 | J9: 39314 | K9: 4.633 | L9: =(K10-$K$6)/$K$6 -> -0.034680851 | M9: 39314 | N9: 13378.87 | O9: =(N10-$N$6)/$N$6 -> 0.01333874
A10: 39321 | B10: 1473.99 | C10: =(B11-$B$6)/$B$6 -> 0.014298068 | D10: 39321 | E10: 16569.09 | F10: =(E11-$E$6)/$E$6 -> -0.05051274 | G10: 39321 | H10: 14479.8 | I10: =(H11-$H$6)/$H$6 -> -0.045471706 | J10: 39321 | K10: 4.537 | L10: =(K11-$K$6)/$K$6 -> -0.070638298 | M10: 39321 | N10: 13357.74 | O10: =(N11-$N$6)/$N$6 -> -0.005198812
A11: 39329 | B11: 1453.55 | C11: =(B12-$B$6)/$B$6 -> 0.035720723 | D11: 39328 | E11: 16122.16 | F11: =(E12-$E$6)/$E$6 -> -0.050202975 | G11: 39328 | H11: 13873.4 | I11: =(H12-$H$6)/$H$6 -> -0.046324888 | J11: 39329 | K11: 4.368 | L11: =(K12-$K$6)/$K$6 -> -0.050638298 | M11: 39329 | N11: 13113.38 | O11: =(N12-$N$6)/$N$6 -> 0.019770228
A12: 39335 | B12: 1484.25 | C12: =(B13-$B$6)/$B$6 -> 0.064679732 | D12: 39335 | E12: 16127.42 | F12: =(E13-$E$6)/$E$6 -> -0.039296499 | G12: 39335 | H12: 13861 | I12: =(H13-$H$6)/$H$6 -> -0.0057588048 | J12: 39335 | K12: 4.462 | L12: =(K13-$K$6)/$K$6 -> -0.014468085 | M12: 39335 | N12: 13442.52 | O12: =(N13-$N$6)/$N$6 -> 0.048420924
A13: 39342 | B13: 1525.75 | C13: =(B14-$B$6)/$B$6 -> 0.06537754 | D13: 39343 | E13: 16312.61 | F13: =(E14-$E$6)/$E$6 -> -0.011435308 | G13: 39342 | H13: 14450.6 | I13: =(H14-$H$6)/$H$6 -> 0.0029034901 | J13: 39342 | K13: 4.632 | L13: =(K14-$K$6)/$K$6 -> -0.025744681 | M13: 39342 | N13: 13820.19 | O13: =(N14-$N$6)/$N$6 -> 0.054143877
A14: 39349 | B14: 1526.75 | C14: =(B15-$B$6)/$B$6 -> 0.086897898 | D14: 39350 | E14: 16785.689 | F14: =(E15-$E$6)/$E$6 -> 0.0050165131 | G14: 39349 | H14: 14576.5 | I14: =(H15-$H$6)/$H$6 -> 0.024617615 | J14: 39349 | K14: 4.579 | L14: =(K15-$K$6)/$K$6 -> -0.012765957 | M14: 39349 | N14: 13895.63 | O14: =(N15-$N$6)/$N$6 -> 0.067069158
A15: 39356 | B15: 1557.59 | C15: =(B16-$B$6)/$B$6 -> 0.089835725 | D15: 39356 | E15: 17065.039 | F15: =(E16-$E$6)/$E$6 -> 0.020689838 | G15: 39356 | H15: 14892.1 | I15: =(H16-$H$6)/$H$6 -> 0.050019609 | J15: 39356 | K15: 4.64 | L15: =(K16-$K$6)/$K$6 -> -0.0027659574 | M15: 39356 | N15: 14066.01 | O15: =(N16-$N$6)/$N$6 -> 0.069122753
A16: 39363 | B16: 1561.8 | C16: =(B17-$B$6)/$B$6 -> 0.047150812 | D16: 39364 | E16: 17331.17 | F16: =(E17-$E$6)/$E$6 -> -0.0097462665 | G16: 39363 | H16: 15261.3 | I16: =(H17-$H$6)/$H$6 -> 0.068486298 | J16: 39363 | K16: 4.687 | L16: =(K17-$K$6)/$K$6 -> -0.063617021 | M16: 39363 | N16: 14093.08 | O16: =(N17-$N$6)/$N$6 -> 0.025801221
A17: 39370 | B17: 1500.63 | C17: =(B18-$B$6)/$B$6 -> 0.071329858 | D17: 39370 | E17: 16814.369 | F17: =(E18-$E$6)/$E$6 -> -0.027928884 | G17: 39370 | H17: 15529.7 | I17: =(H18-$H$6)/$H$6 -> 0.073591477 | J17: 39370 | K17: 4.401 | L17: =(K18-$K$6)/$K$6 -> -0.066170213 | M17: 39370 | N17: 13522.02 | O17: =(N18-$N$6)/$N$6 -> 0.047397534
A18: 39377 | B18: 1535.28 | C18: =(B19-$B$6)/$B$6 -> 0.053445049 | D18: 39377 | E18: 16505.631 | F18: =(E19-$E$6)/$E$6 -> -0.027231021 | G18: 39377 | H18: 15603.9 | I18: =(H19-$H$6)/$H$6 -> 0.088714311 | J18: 39377 | K18: 4.389 | L18: =(K19-$K$6)/$K$6 -> -0.087021277 | M18: 39377 | N18: 13806.7 | O18: =(N19-$N$6)/$N$6 -> 0.031345188
A19: 39384 | B19: 1509.65 | C19: =(B20-$B$6)/$B$6 -> 0.014402671 | D19: 39384 | E19: 16517.48 | F19: =(E20-$E$6)/$E$6 -> -0.082240932 | G19: 39384 | H19: 15823.7 | I19: =(H20-$H$6)/$H$6 -> 0.082350055 | J19: 39384 | K19: 4.291 | L19: =(K20-$K$6)/$K$6 -> -0.10106383 | M19: 39384 | N19: 13595.1 | O19: =(N20-$N$6)/$N$6 -> -0.010557645
... A493: 42702 | B493: 2191.95 | C493: =(B494-$B$6)/$B$6 -> 0.57671691 | D493: 42723 | E493: 19427.67 | F493: =(E494-$E$6)/$E$6 -> 0.12570833 | G493: 42702 | H493: 8607.0996 | I493: =(H494-$H$6)/$H$6 -> -0.3691062 | J493: 42702 | K493: 2.39 | L493: =(K494-$K$6)/$K$6 -> -0.47574468 | M493: 42702 | N493: 19170.42 | O493: =(N494-$N$6)/$N$6 -> 0.49878503
A494: 42709 | B494: 2259.53 | C494: =(B495-$B$6)/$B$6 -> 0.57569814 | D494: 42730 | E494: 19114.369 | G494: 42709 | H494: 9169.5996 | I494: =(H495-$H$6)/$H$6 -> -0.35237336 | J494: 42709 | K494: 2.464 | L494: =(K495-$K$6)/$K$6 -> -0.44744681 | M494: 42709 | N494: 19756.85 | O494: =(N495-$N$6)/$N$6 -> 0.50535165
A495: 42716 | B495: 2258.0701 | C495: =(B496-$B$6)/$B$6 -> 0.57968958 | G495: 42716 | H495: 9412.7998 | I495: =(H496-$H$6)/$H$6 -> -0.35547633 | J495: 42716 | K495: 2.597 | L495: =(K496-$K$6)/$K$6 -> -0.45893617 | M495: 42716 | N495: 19843.41 | O495: =(N496-$N$6)/$N$6 -> 0.51220956
A496: 42723 | B496: 2263.79 | C496: =(B497-$B$6)/$B$6 -> 0.56227233 | G496: 42723 | H496: 9367.7002 | I496: =(H497-$H$6)/$H$6 -> -0.3565497 | J496: 42723 | K496: 2.543 | L496: =(K497-$K$6)/$K$6 -> -0.47957447 | M496: 42723 | N496: 19933.811 | O496: =(N497-$N$6)/$N$6 -> 0.49922123
A497: 42731 | B497: 2238.8301 | G497: 42731 | H497: 9352.0996 | J497: 42731 | K497: 2.446 | M497: 42731 | N497: 19762.6
