Workbook
Name data_type: 'Sheet 2'!#REF!
Name debt: 'Sheet 1'!$Z$3
Name effc: 'Sheet 1'!$AD$3
Name proft: 'Sheet 1'!$AA$3
Name ratio: 'Sheet 1'!$X$3

Sheet Sheet 1
B2: Quote | G2: Valuation | X2: Financial Health | AA2: Profitability | AD2: Effectiveness | AG2: Growth | AP2: Dividend
A3: Symbol | B3: Last Price | C3: Market Capitalization | D3: Enterprise Value | E3: Book Value | F3: Sales | I3: P / E | K3: P / S | M3: P / B | O3: P / FCF | Q3: P / CFO | S3: EV / EBITDA | U3: EV / S | X3: Current Ratio | Y3: Financial Leverage | Z3: Debt / Equity | AA3: Gross Margin | AB3: Net Margin | AC3: Operating Margin | AD3: Return on Equity | AE3: Return on Assets | AF3: Asset Turnover | AH3: Revenue | AJ3: Operating Income % | AL3: Net Income | AN3: Earnings Per Share | AP3: Yield
I4: =AVERAGE(I5:I500) -> 27.300703 | K4: =AVERAGE(K5:K500) -> #DIV/0! | M4: =AVERAGE(M5:M500) -> #DIV/0! | O4: =AVERAGE(O5:O500) -> #DIV/0! | Q4: =AVERAGE(Q5:Q500) -> #DIV/0! | S4: =AVERAGE(S5:S500) -> #DIV/0! | U4: =AVERAGE(U5:U500) -> #DIV/0! | X4: =AVERAGE(X5:X500) -> #DIV/0! | Y4: =AVERAGE(Y5:Y500) -> #DIV/0! | Z4: =AVERAGE(Z5:Z500) -> #DIV/0! | AA4: =AVERAGE(AA5:AA500) -> #DIV/0! | AB4: =AVERAGE(AB5:AB500) -> #DIV/0! | AC4: =AVERAGE(AC5:AC500) -> #DIV/0! | AD4: =AVERAGE(AD5:AD39) -> #DIV/0! | AE4: =AVERAGE(AE5:AE39) -> #DIV/0! | AF4: =AVERAGE(AF5:AF39) -> #DIV/0! | AH4: =AVERAGE(AH5:AH500) -> #DIV/0! | AI4: =AVERAGE(AI5:AI500) -> #DIV/0! | AJ4: =AVERAGE(AJ5:AJ500) -> #NUM! | AL4: =AVERAGE(AL5:AL500) -> #DIV/0! | AN4: =AVERAGE(AN5:AN500) -> #DIV/0! | AP4: =AVERAGE(AP5:AP500) -> #DIV/0!
A5: {=INDEX('Sheet 2'!T$2:T$3173,SMALL(IF(A$3='Sheet 2'!$S$2:$S$3173,ROW('Sheet 2'!T$2:T$3173)-ROW('Sheet 2'!$T$2)+1),ROW(1:1)))} -> CCUR | B5: {=INDEX('Sheet 2'!V$5:V$3173,SMALL(IF(B$3='Sheet 2'!S$5:S$3173,ROW('Sheet 2'!V$5:V$3173)-ROW('Sheet 2'!V$5)+1),ROW(1:1)))} -> 5.42 | C5: {=INDEX('Sheet 2'!V$5:V$3173,SMALL(IF(C$3='Sheet 2'!S$5:S$3173,ROW('Sheet 2'!V$5:V$3173)-ROW('Sheet 2'!V$5)+1),ROW(1:1)))} -> 50682702 | D5: {=INDEX('Sheet 2'!V$5:V$3173,SMALL(IF(D$3='Sheet 2'!S$5:S$3173,ROW('Sheet 2'!V$5:V$3173)-ROW('Sheet 2'!V$5)+1),ROW(1:1)))} -> -6864298.2 | E5: {=INDEX('Sheet 2'!V$5:V$3173,SMALL(IF(E$3='Sheet 2'!S$5:S$3173,ROW('Sheet 2'!V$5:V$3173)-ROW('Sheet 2'!V$5)+1),ROW(1:1)))} -> 62117000 | F5: {=INDEX('Sheet 2'!V$5:V$3173,SMALL(IF(F$3='Sheet 2'!S$5:S$3173,ROW('Sheet 2'!V$5:V$3173)-ROW('Sheet 2'!V$5)+1),ROW(1:1)))} -> 250000000 | I5: {=INDEX('Sheet 2'!V$5:V$3173,SMALL(IF(I$3='Sheet 2'!S$5:S$3173,ROW('Sheet 2'!V$5:V$3173)-ROW('Sheet 2'!V$5)+1),ROW(1:1)))} -> 1.0037037 | K5: {=INDEX('Sheet 2'!V$5:V$3173,SMALL(IF(K$3='Sheet 2'!S$5:S$3173,ROW('Sheet 2'!V$5:V$3173)-ROW('Sheet 2'!V$5)+1),ROW(1:1)))} -> 0.20273081 | M5: {=INDEX('Sheet 2'!V$5:V$3173,SMALL(IF(M$3='Sheet 2'!S$5:S$3173,ROW('Sheet 2'!V$5:V$3173)-ROW('Sheet 2'!V$5)+1),ROW(1:1)))} -> 0.82340905 | O5: {=INDEX('Sheet 2'!V$5:V$3173,SMALL(IF(O$3='Sheet 2'!S$5:S$3173,ROW('Sheet 2'!V$5:V$3173)-ROW('Sheet 2'!V$5)+1),ROW(1:1)))} | Q5: {=INDEX('Sheet 2'!V$5:V$3173,SMALL(IF(Q$3='Sheet 2'!S$5:S$3173,ROW('Sheet 2'!V$5:V$3173)-ROW('Sheet 2'!V$5)+1),ROW(1:1)))} | S5: {=INDEX('Sheet 2'!V$5:V$3173,SMALL(IF(S$3='Sheet 2'!S$5:S$3173,ROW('Sheet 2'!V$5:V$3173)-ROW('Sheet 2'!V$5)+1),ROW(1:1)))} -> 1.9163311 | U5: {=INDEX('Sheet 2'!V$5:V$3173,SMALL(IF(U$3='Sheet 2'!S$5:S$3173,ROW('Sheet 2'!V$5:V$3173)-ROW('Sheet 2'!V$5)+1),ROW(1:1)))} -> 4.2943763 | X5: {=INDEX('Sheet 2'!AA$13:AA$3173,SMALL(IF(X$3='Sheet 2'!X$13:X$3173,ROW('Sheet 2'!AA$13:AA$3173)-ROW('Sheet 2'!AA$13)+1),ROW(1:1)))} -> 5.4407029 | Y5: {=INDEX('Sheet 2'!AA$13:AA$3173,SMALL(IF(Y$3='Sheet 2'!X$13:X$3173,ROW('Sheet 2'!AA$13:AA$3173)-ROW('Sheet 2'!AA$13)+1),ROW(1:1)))} -> 1.3644479 | Z5: {=INDEX('Sheet 2'!AA$13:AA$3173,SMALL(IF(Z$3='Sheet 2'!X$13:X$3173,ROW('Sheet 2'!AA$13:AA$3173)-ROW('Sheet 2'!AA$13)+1),ROW(1:1)))} -> #DIV/0! | AA5: {=INDEX('Sheet 2'!V$5:V$3173,SMALL(IF(AA$3='Sheet 2'!S$5:S$3173,ROW('Sheet 2'!V$5:V$3173)-ROW('Sheet 2'!V$5)+1),ROW(1:1)))} -> 1 | AB5: {=INDEX('Sheet 2'!V$5:V$3173,SMALL(IF(AB$3='Sheet 2'!S$5:S$3173,ROW('Sheet 2'!V$5:V$3173)-ROW('Sheet 2'!V$5)+1),ROW(1:1)))} -> 0.2011 | AC5: {=INDEX('Sheet 2'!V$5:V$3173,SMALL(IF(AC$3='Sheet 2'!S$5:S$3173,ROW('Sheet 2'!V$5:V$3173)-ROW('Sheet 2'!V$5)+1),ROW(1:1)))} -> -0.119164 | AD5: {=INDEX('Sheet 2'!V$5:V$3173,SMALL(IF(AD$3='Sheet 2'!S$5:S$3173,ROW('Sheet 2'!V$5:V$3173)-ROW('Sheet 2'!V$5)+1),ROW(1:1)))} -> 1.2536 | AE5: {=INDEX('Sheet 2'!V$5:V$3173,SMALL(IF(AE$3='Sheet 2'!S$5:S$3173,ROW('Sheet 2'!V$5:V$3173)-ROW('Sheet 2'!V$5)+1),ROW(1:1)))} -> 0.91875988 | AF5: {=INDEX('Sheet 2'!V$5:V$3173,SMALL(IF(AF$3='Sheet 2'!S$5:S$3173,ROW('Sheet 2'!V$5:V$3173)-ROW('Sheet 2'!V$5)+1),ROW(1:1)))} -> 4.5686717 | AH5: {=INDEX('Sheet 2'!AA$5:AA$3173,SMALL(IF(AH$3='Sheet 2'!X$5:X$3173,ROW('Sheet 2'!AA$5:AA$3173)-ROW('Sheet 2'!AA$5)+1),ROW(1:1)))} -> -0.14293524 | AJ5: {=INDEX('Sheet 2'!V$5:V$3173,SMALL(IF(AJ$3='Sheet 2'!S$5:S$3173,ROW('Sheet 2'!V$5:V$3173)-ROW('Sheet 2'!V$5)+1),ROW(1:1)))} -> #NUM! | AL5: {=INDEX('Sheet 2'!AA$5:AA$3173,SMALL(IF(AL$3='Sheet 2'!X$5:X$3173,ROW('Sheet 2'!AA$5:AA$3173)-ROW('Sheet 2'!AA$5)+1),ROW(1:1)))} -> -13.927713 | AN5: {=INDEX('Sheet 2'!AA$5:AA$3173,SMALL(IF(AN$3='Sheet 2'!X$5:X$3173,ROW('Sheet 2'!AA$5:AA$3173)-ROW('Sheet 2'!AA$5)+1),ROW(1:1)))} -> -13.002551
A6: {=INDEX('Sheet 2'!T$2:T$3173,SMALL(IF(A$3='Sheet 2'!$S$2:$S$3173,ROW('Sheet 2'!T$2:T$3173)-ROW('Sheet 2'!$T$2)+1),ROW(2:2)))} -> CRAY | B6: {=INDEX('Sheet 2'!V$5:V$3173,SMALL(IF(B$3='Sheet 2'!S$5:S$3173,ROW('Sheet 2'!V$5:V$3173)-ROW('Sheet 2'!V$5)+1),ROW(2:2)))} -> 21.25 | C6: {=INDEX('Sheet 2'!V$5:V$3173,SMALL(IF(C$3='Sheet 2'!S$5:S$3173,ROW('Sheet 2'!V$5:V$3173)-ROW('Sheet 2'!V$5)+1),ROW(2:2)))} -> 852953750 | D6: {=INDEX('Sheet 2'!V$5:V$3173,SMALL(IF(D$3='Sheet 2'!S$5:S$3173,ROW('Sheet 2'!V$5:V$3173)-ROW('Sheet 2'!V$5)+1),ROW(2:2)))} -> 715627750 | E6: {=INDEX('Sheet 2'!V$5:V$3173,SMALL(IF(E$3='Sheet 2'!S$5:S$3173,ROW('Sheet 2'!V$5:V$3173)-ROW('Sheet 2'!V$5)+1),ROW(2:2)))} -> 400297000 | F6: {=INDEX('Sheet 2'!V$5:V$3173,SMALL(IF(F$3='Sheet 2'!S$5:S$3173,ROW('Sheet 2'!V$5:V$3173)-ROW('Sheet 2'!V$5)+1),ROW(2:2)))} -> 392509000 | I6: {=INDEX('Sheet 2'!V$5:V$3173,SMALL(IF(I$3='Sheet 2'!S$5:S$3173,ROW('Sheet 2'!V$5:V$3173)-ROW('Sheet 2'!V$5)+1),ROW(2:2)))} | K6: {=INDEX('Sheet 2'!V$5:V$3173,SMALL(IF(K$3='Sheet 2'!S$5:S$3173,ROW('Sheet 2'!V$5:V$3173)-ROW('Sheet 2'!V$5)+1),ROW(2:2)))} -> 2.1730807 | M6: {=INDEX('Sheet 2'!V$5:V$3173,SMALL(IF(M$3='Sheet 2'!S$5:S$3173,ROW('Sheet 2'!V$5:V$3173)-ROW('Sheet 2'!V$5)+1),ROW(2:2)))} -> 2.1398799 | O6: {=INDEX('Sheet 2'!V$5:V$3173,SMALL(IF(O$3='Sheet 2'!S$5:S$3173,ROW('Sheet 2'!V$5:V$3173)-ROW('Sheet 2'!V$5)+1),ROW(2:2)))} | Q6: {=INDEX('Sheet 2'!V$5:V$3173,SMALL(IF(Q$3='Sheet 2'!S$5:S$3173,ROW('Sheet 2'!V$5:V$3173)-ROW('Sheet 2'!V$5)+1),ROW(2:2)))} -> 115.7751 | S6: {=INDEX('Sheet 2'!V$5:V$3173,SMALL(IF(S$3='Sheet 2'!S$5:S$3173,ROW('Sheet 2'!V$5:V$3173)-ROW('Sheet 2'!V$5)+1),ROW(2:2)))} -> 77.090138 | U6: {=INDEX('Sheet 2'!V$5:V$3173,SMALL(IF(U$3='Sheet 2'!S$5:S$3173,ROW('Sheet 2'!V$5:V$3173)-ROW('Sheet 2'!V$5)+1),ROW(2:2)))} -> #DIV/0! | X6: {=INDEX('Sheet 2'!AA$13:AA$3173,SMALL(IF(X$3='Sheet 2'!X$13:X$3173,ROW('Sheet 2'!AA$13:AA$3173)-ROW('Sheet 2'!AA$13)+1),ROW(2:2)))} -> 3.4293805 | Y6: {=INDEX('Sheet 2'!AA$13:AA$3173,SMALL(IF(Y$3='Sheet 2'!X$13:X$3173,ROW('Sheet 2'!AA$13:AA$3173)-ROW('Sheet 2'!AA$13)+1),ROW(2:2)))} -> 1.3927086 | Z6: {=INDEX('Sheet 2'!AA$13:AA$3173,SMALL(IF(Z$3='Sheet 2'!X$13:X$3173,ROW('Sheet 2'!AA$13:AA$3173)-ROW('Sheet 2'!AA$13)+1),ROW(2:2)))} -> #DIV/0! | AA6: {=INDEX('Sheet 2'!V$5:V$3173,SMALL(IF(AA$3='Sheet 2'!S$5:S$3173,ROW('Sheet 2'!V$5:V$3173)-ROW('Sheet 2'!V$5)+1),ROW(2:2)))} -> 0.33299619 | AB6: {=INDEX('Sheet 2'!V$5:V$3173,SMALL(IF(AB$3='Sheet 2'!S$5:S$3173,ROW('Sheet 2'!V$5:V$3173)-ROW('Sheet 2'!V$5)+1),ROW(2:2)))} -> -0.34095779 | AC6: {=INDEX('Sheet 2'!V$5:V$3173,SMALL(IF(AC$3='Sheet 2'!S$5:S$3173,ROW('Sheet 2'!V$5:V$3173)-ROW('Sheet 2'!V$5)+1),ROW(2:2)))} -> -0.16725222 | AD6: {=INDEX('Sheet 2'!V$5:V$3173,SMALL(IF(AD$3='Sheet 2'!S$5:S$3173,ROW('Sheet 2'!V$5:V$3173)-ROW('Sheet 2'!V$5)+1),ROW(2:2)))} -> -0.28077865 | AE6: {=INDEX('Sheet 2'!V$5:V$3173,SMALL(IF(AE$3='Sheet 2'!S$5:S$3173,ROW('Sheet 2'!V$5:V$3173)-ROW('Sheet 2'!V$5)+1),ROW(2:2)))} -> -0.20160617 | AF6: {=INDEX('Sheet 2'!V$5:V$3173,SMALL(IF(AF$3='Sheet 2'!S$5:S$3173,ROW('Sheet 2'!V$5:V$3173)-ROW('Sheet 2'!V$5)+1),ROW(2:2)))} -> 0.59129365 | AH6: {=INDEX('Sheet 2'!AA$5:AA$3173,SMALL(IF(AH$3='Sheet 2'!X$5:X$3173,ROW('Sheet 2'!AA$5:AA$3173)-ROW('Sheet 2'!AA$5)+1),ROW(2:2)))} -> 250000000 | AJ6: {=INDEX('Sheet 2'!V$5:V$3173,SMALL(IF(AJ$3='Sheet 2'!S$5:S$3173,ROW('Sheet 2'!V$5:V$3173)-ROW('Sheet 2'!V$5)+1),ROW(2:2)))} -> #NUM! | AL6: {=INDEX('Sheet 2'!AA$5:AA$3173,SMALL(IF(AL$3='Sheet 2'!X$5:X$3173,ROW('Sheet 2'!AA$5:AA$3173)-ROW('Sheet 2'!AA$5)+1),ROW(2:2)))} -> 50275000 | AN6: {=INDEX('Sheet 2'!AA$5:AA$3173,SMALL(IF(AN$3='Sheet 2'!X$5:X$3173,ROW('Sheet 2'!AA$5:AA$3173)-ROW('Sheet 2'!AA$5)+1),ROW(2:2)))} -> 5.4
A7: {=INDEX('Sheet 2'!T$2:T$3173,SMALL(IF(A$3='Sheet 2'!$S$2:$S$3173,ROW('Sheet 2'!T$2:T$3173)-ROW('Sheet 2'!$T$2)+1),ROW(3:3)))} -> ADI | B7: {=INDEX('Sheet 2'!V$5:V$3173,SMALL(IF(B$3='Sheet 2'!S$5:S$3173,ROW('Sheet 2'!V$5:V$3173)-ROW('Sheet 2'!V$5)+1),ROW(3:3)))} -> 88.54 | C7: {=INDEX('Sheet 2'!V$5:V$3173,SMALL(IF(C$3='Sheet 2'!S$5:S$3173,ROW('Sheet 2'!V$5:V$3173)-ROW('Sheet 2'!V$5)+1),ROW(3:3)))} -> 0 | D7: {=INDEX('Sheet 2'!V$5:V$3173,SMALL(IF(D$3='Sheet 2'!S$5:S$3173,ROW('Sheet 2'!V$5:V$3173)-ROW('Sheet 2'!V$5)+1),ROW(3:3)))} -> 0 | E7: {=INDEX('Sheet 2'!V$5:V$3173,SMALL(IF(E$3='Sheet 2'!S$5:S$3173,ROW('Sheet 2'!V$5:V$3173)-ROW('Sheet 2'!V$5)+1),ROW(3:3)))} -> 0 | F7: {=INDEX('Sheet 2'!V$5:V$3173,SMALL(IF(F$3='Sheet 2'!S$5:S$3173,ROW('Sheet 2'!V$5:V$3173)-ROW('Sheet 2'!V$5)+1),ROW(3:3)))} -> 0 | I7: {=INDEX('Sheet 2'!V$5:V$3173,SMALL(IF(I$3='Sheet 2'!S$5:S$3173,ROW('Sheet 2'!V$5:V$3173)-ROW('Sheet 2'!V$5)+1),ROW(3:3)))} | K7: {=INDEX('Sheet 2'!V$5:V$3173,SMALL(IF(K$3='Sheet 2'!S$5:S$3173,ROW('Sheet 2'!V$5:V$3173)-ROW('Sheet 2'!V$5)+1),ROW(3:3)))} -> #DIV/0! | M7: {=INDEX('Sheet 2'!V$5:V$3173,SMALL(IF(M$3='Sheet 2'!S$5:S$3173,ROW('Sheet 2'!V$5:V$3173)-ROW('Sheet 2'!V$5)+1),ROW(3:3)))} -> #DIV/0! | O7: {=INDEX('Sheet 2'!V$5:V$3173,SMALL(IF(O$3='Sheet 2'!S$5:S$3173,ROW('Sheet 2'!V$5:V$3173)-ROW('Sheet 2'!V$5)+1),ROW(3:3)))} -> #DIV/0! | Q7: {=INDEX('Sheet 2'!V$5:V$3173,SMALL(IF(Q$3='Sheet 2'!S$5:S$3173,ROW('Sheet 2'!V$5:V$3173)-ROW('Sheet 2'!V$5)+1),ROW(3:3)))} -> #DIV/0! | S7: {=INDEX('Sheet 2'!V$5:V$3173,SMALL(IF(S$3='Sheet 2'!S$5:S$3173,ROW('Sheet 2'!V$5:V$3173)-ROW('Sheet 2'!V$5)+1),ROW(3:3)))} -> #DIV/0! | U7: {=INDEX('Sheet 2'!V$5:V$3173,SMALL(IF(U$3='Sheet 2'!S$5:S$3173,ROW('Sheet 2'!V$5:V$3173)-ROW('Sheet 2'!V$5)+1),ROW(3:3)))} -> 4.799019 | X7: {=INDEX('Sheet 2'!AA$13:AA$3173,SMALL(IF(X$3='Sheet 2'!X$13:X$3173,ROW('Sheet 2'!AA$13:AA$3173)-ROW('Sheet 2'!AA$13)+1),ROW(3:3)))} -> #DIV/0! | Y7: {=INDEX('Sheet 2'!AA$13:AA$3173,SMALL(IF(Y$3='Sheet 2'!X$13:X$3173,ROW('Sheet 2'!AA$13:AA$3173)-ROW('Sheet 2'!AA$13)+1),ROW(3:3)))} -> #DIV/0! | Z7: {=INDEX('Sheet 2'!AA$13:AA$3173,SMALL(IF(Z$3='Sheet 2'!X$13:X$3173,ROW('Sheet 2'!AA$13:AA$3173)-ROW('Sheet 2'!AA$13)+1),ROW(3:3)))} -> #DIV/0! | AA7: {=INDEX('Sheet 2'!V$5:V$3173,SMALL(IF(AA$3='Sheet 2'!S$5:S$3173,ROW('Sheet 2'!V$5:V$3173)-ROW('Sheet 2'!V$5)+1),ROW(3:3)))} -> #DIV/0! | AB7: {=INDEX('Sheet 2'!V$5:V$3173,SMALL(IF(AB$3='Sheet 2'!S$5:S$3173,ROW('Sheet 2'!V$5:V$3173)-ROW('Sheet 2'!V$5)+1),ROW(3:3)))} -> #DIV/0! | AC7: {=INDEX('Sheet 2'!V$5:V$3173,SMALL(IF(AC$3='Sheet 2'!S$5:S$3173,ROW('Sheet 2'!V$5:V$3173)-ROW('Sheet 2'!V$5)+1),ROW(3:3)))} -> #DIV/0! | AD7: {=INDEX('Sheet 2'!V$5:V$3173,SMALL(IF(AD$3='Sheet 2'!S$5:S$3173,ROW('Sheet 2'!V$5:V$3173)-ROW('Sheet 2'!V$5)+1),ROW(3:3)))} -> #DIV/0! | AE7: {=INDEX('Sheet 2'!V$5:V$3173,SMALL(IF(AE$3='Sheet 2'!S$5:S$3173,ROW('Sheet 2'!V$5:V$3173)-ROW('Sheet 2'!V$5)+1),ROW(3:3)))} -> #DIV/0! | AF7: {=INDEX('Sheet 2'!V$5:V$3173,SMALL(IF(AF$3='Sheet 2'!S$5:S$3173,ROW('Sheet 2'!V$5:V$3173)-ROW('Sheet 2'!V$5)+1),ROW(3:3)))} -> #DIV/0! | AH7: {=INDEX('Sheet 2'!AA$5:AA$3173,SMALL(IF(AH$3='Sheet 2'!X$5:X$3173,ROW('Sheet 2'!AA$5:AA$3173)-ROW('Sheet 2'!AA$5)+1),ROW(3:3)))} -> -0.037279356 | AJ7: {=INDEX('Sheet 2'!V$5:V$3173,SMALL(IF(AJ$3='Sheet 2'!S$5:S$3173,ROW('Sheet 2'!V$5:V$3173)-ROW('Sheet 2'!V$5)+1),ROW(3:3)))} -> #NUM! | AL7: {=INDEX('Sheet 2'!AA$5:AA$3173,SMALL(IF(AL$3='Sheet 2'!X$5:X$3173,ROW('Sheet 2'!AA$5:AA$3173)-ROW('Sheet 2'!AA$5)+1),ROW(3:3)))} -> -0.079519988 | AN7: {=INDEX('Sheet 2'!AA$5:AA$3173,SMALL(IF(AN$3='Sheet 2'!X$5:X$3173,ROW('Sheet 2'!AA$5:AA$3173)-ROW('Sheet 2'!AA$5)+1),ROW(3:3)))} -> -0.095128486
A8: {=INDEX('Sheet 2'!T$2:T$3173,SMALL(IF(A$3='Sheet 2'!$S$2:$S$3173,ROW('Sheet 2'!T$2:T$3173)-ROW('Sheet 2'!$T$2)+1),ROW(4:4)))} -> HPE | B8: {=INDEX('Sheet 2'!V$5:V$3173,SMALL(IF(B$3='Sheet 2'!S$5:S$3173,ROW('Sheet 2'!V$5:V$3173)-ROW('Sheet 2'!V$5)+1),ROW(4:4)))} -> 18.780001 | C8: {=INDEX('Sheet 2'!V$5:V$3173,SMALL(IF(C$3='Sheet 2'!S$5:S$3173,ROW('Sheet 2'!V$5:V$3173)-ROW('Sheet 2'!V$5)+1),ROW(4:4)))} -> 3.0545672e+10 | D8: {=INDEX('Sheet 2'!V$5:V$3173,SMALL(IF(D$3='Sheet 2'!S$5:S$3173,ROW('Sheet 2'!V$5:V$3173)-ROW('Sheet 2'!V$5)+1),ROW(4:4)))} -> 3.6827672e+10 | E8: {=INDEX('Sheet 2'!V$5:V$3173,SMALL(IF(E$3='Sheet 2'!S$5:S$3173,ROW('Sheet 2'!V$5:V$3173)-ROW('Sheet 2'!V$5)+1),ROW(4:4)))} -> 23951000000 | F8: {=INDEX('Sheet 2'!V$5:V$3173,SMALL(IF(F$3='Sheet 2'!S$5:S$3173,ROW('Sheet 2'!V$5:V$3173)-ROW('Sheet 2'!V$5)+1),ROW(4:4)))} -> 29643000000 | I8: {=INDEX('Sheet 2'!V$5:V$3173,SMALL(IF(I$3='Sheet 2'!S$5:S$3173,ROW('Sheet 2'!V$5:V$3173)-ROW('Sheet 2'!V$5)+1),ROW(4:4)))} -> 19.768422 | K8: {=INDEX('Sheet 2'!V$5:V$3173,SMALL(IF(K$3='Sheet 2'!S$5:S$3173,ROW('Sheet 2'!V$5:V$3173)-ROW('Sheet 2'!V$5)+1),ROW(4:4)))} -> 1.0304514 | M8: {=INDEX('Sheet 2'!V$5:V$3173,SMALL(IF(M$3='Sheet 2'!S$5:S$3173,ROW('Sheet 2'!V$5:V$3173)-ROW('Sheet 2'!V$5)+1),ROW(4:4)))} -> 1.2475046 | O8: {=INDEX('Sheet 2'!V$5:V$3173,SMALL(IF(O$3='Sheet 2'!S$5:S$3173,ROW('Sheet 2'!V$5:V$3173)-ROW('Sheet 2'!V$5)+1),ROW(4:4)))} | Q8: {=INDEX('Sheet 2'!V$5:V$3173,SMALL(IF(Q$3='Sheet 2'!S$5:S$3173,ROW('Sheet 2'!V$5:V$3173)-ROW('Sheet 2'!V$5)+1),ROW(4:4)))} -> 9.6378855 | S8: {=INDEX('Sheet 2'!V$5:V$3173,SMALL(IF(S$3='Sheet 2'!S$5:S$3173,ROW('Sheet 2'!V$5:V$3173)-ROW('Sheet 2'!V$5)+1),ROW(4:4)))} -> 32.024062 | U8: {=INDEX('Sheet 2'!V$5:V$3173,SMALL(IF(U$3='Sheet 2'!S$5:S$3173,ROW('Sheet 2'!V$5:V$3173)-ROW('Sheet 2'!V$5)+1),ROW(4:4)))} -> 2.8502006 | X8: {=INDEX('Sheet 2'!AA$13:AA$3173,SMALL(IF(X$3='Sheet 2'!X$13:X$3173,ROW('Sheet 2'!AA$13:AA$3173)-ROW('Sheet 2'!AA$13)+1),ROW(4:4)))} -> 1.1515703 | Y8: {=INDEX('Sheet 2'!AA$13:AA$3173,SMALL(IF(Y$3='Sheet 2'!X$13:X$3173,ROW('Sheet 2'!AA$13:AA$3173)-ROW('Sheet 2'!AA$13)+1),ROW(4:4)))} -> 2.4793816 | Z8: {=INDEX('Sheet 2'!AA$13:AA$3173,SMALL(IF(Z$3='Sheet 2'!X$13:X$3173,ROW('Sheet 2'!AA$13:AA$3173)-ROW('Sheet 2'!AA$13)+1),ROW(4:4)))} -> 0.44246017 | AA8: {=INDEX('Sheet 2'!V$5:V$3173,SMALL(IF(AA$3='Sheet 2'!S$5:S$3173,ROW('Sheet 2'!V$5:V$3173)-ROW('Sheet 2'!V$5)+1),ROW(4:4)))} -> 0.29227811 | AB8: {=INDEX('Sheet 2'!V$5:V$3173,SMALL(IF(AB$3='Sheet 2'!S$5:S$3173,ROW('Sheet 2'!V$5:V$3173)-ROW('Sheet 2'!V$5)+1),ROW(4:4)))} -> 0.051040718 | AC8: {=INDEX('Sheet 2'!V$5:V$3173,SMALL(IF(AC$3='Sheet 2'!S$5:S$3173,ROW('Sheet 2'!V$5:V$3173)-ROW('Sheet 2'!V$5)+1),ROW(4:4)))} -> 0.018520393 | AD8: {=INDEX('Sheet 2'!V$5:V$3173,SMALL(IF(AD$3='Sheet 2'!S$5:S$3173,ROW('Sheet 2'!V$5:V$3173)-ROW('Sheet 2'!V$5)+1),ROW(4:4)))} -> 0.057397572 | AE8: {=INDEX('Sheet 2'!V$5:V$3173,SMALL(IF(AE$3='Sheet 2'!S$5:S$3173,ROW('Sheet 2'!V$5:V$3173)-ROW('Sheet 2'!V$5)+1),ROW(4:4)))} -> 0.023149954 | AF8: {=INDEX('Sheet 2'!V$5:V$3173,SMALL(IF(AF$3='Sheet 2'!S$5:S$3173,ROW('Sheet 2'!V$5:V$3173)-ROW('Sheet 2'!V$5)+1),ROW(4:4)))} -> 0.45355856 | AH8: {=INDEX('Sheet 2'!AA$5:AA$3173,SMALL(IF(AH$3='Sheet 2'!X$5:X$3173,ROW('Sheet 2'!AA$5:AA$3173)-ROW('Sheet 2'!AA$5)+1),ROW(4:4)))} -> 392509000 | AJ8: {=INDEX('Sheet 2'!V$5:V$3173,SMALL(IF(AJ$3='Sheet 2'!S$5:S$3173,ROW('Sheet 2'!V$5:V$3173)-ROW('Sheet 2'!V$5)+1),ROW(4:4)))} -> #NUM! | AL8: {=INDEX('Sheet 2'!AA$5:AA$3173,SMALL(IF(AL$3='Sheet 2'!X$5:X$3173,ROW('Sheet 2'!AA$5:AA$3173)-ROW('Sheet 2'!AA$5)+1),ROW(4:4)))} -> -133829000 | AN8: {=INDEX('Sheet 2'!AA$5:AA$3173,SMALL(IF(AN$3='Sheet 2'!X$5:X$3173,ROW('Sheet 2'!AA$5:AA$3173)-ROW('Sheet 2'!AA$5)+1),ROW(4:4)))} -> -3.33
A9: {=INDEX('Sheet 2'!T$2:T$3173,SMALL(IF(A$3='Sheet 2'!$S$2:$S$3173,ROW('Sheet 2'!T$2:T$3173)-ROW('Sheet 2'!$T$2)+1),ROW(5:5)))} -> HPQ | B9: {=INDEX('Sheet 2'!V$5:V$3173,SMALL(IF(B$3='Sheet 2'!S$5:S$3173,ROW('Sheet 2'!V$5:V$3173)-ROW('Sheet 2'!V$5)+1),ROW(5:5)))} -> 23.280001 | C9: {=INDEX('Sheet 2'!V$5:V$3173,SMALL(IF(C$3='Sheet 2'!S$5:S$3173,ROW('Sheet 2'!V$5:V$3173)-ROW('Sheet 2'!V$5)+1),ROW(5:5)))} -> 3.8982362e+10 | D9: {=INDEX('Sheet 2'!V$5:V$3173,SMALL(IF(D$3='Sheet 2'!S$5:S$3173,ROW('Sheet 2'!V$5:V$3173)-ROW('Sheet 2'!V$5)+1),ROW(5:5)))} -> 4.1376362e+10 | E9: {=INDEX('Sheet 2'!V$5:V$3173,SMALL(IF(E$3='Sheet 2'!S$5:S$3173,ROW('Sheet 2'!V$5:V$3173)-ROW('Sheet 2'!V$5)+1),ROW(5:5)))} -> -2742000000 | F9: {=INDEX('Sheet 2'!V$5:V$3173,SMALL(IF(F$3='Sheet 2'!S$5:S$3173,ROW('Sheet 2'!V$5:V$3173)-ROW('Sheet 2'!V$5)+1),ROW(5:5)))} -> 53889000000 | I9: {=INDEX('Sheet 2'!V$5:V$3173,SMALL(IF(I$3='Sheet 2'!S$5:S$3173,ROW('Sheet 2'!V$5:V$3173)-ROW('Sheet 2'!V$5)+1),ROW(5:5)))} -> 10.077923 | K9: {=INDEX('Sheet 2'!V$5:V$3173,SMALL(IF(K$3='Sheet 2'!S$5:S$3173,ROW('Sheet 2'!V$5:V$3173)-ROW('Sheet 2'!V$5)+1),ROW(5:5)))} -> 0.72338254 | M9: {=INDEX('Sheet 2'!V$5:V$3173,SMALL(IF(M$3='Sheet 2'!S$5:S$3173,ROW('Sheet 2'!V$5:V$3173)-ROW('Sheet 2'!V$5)+1),ROW(5:5)))} -> -14.008753 | O9: {=INDEX('Sheet 2'!V$5:V$3173,SMALL(IF(O$3='Sheet 2'!S$5:S$3173,ROW('Sheet 2'!V$5:V$3173)-ROW('Sheet 2'!V$5)+1),ROW(5:5)))} -> 13.053587 | Q9: {=INDEX('Sheet 2'!V$5:V$3173,SMALL(IF(Q$3='Sheet 2'!S$5:S$3173,ROW('Sheet 2'!V$5:V$3173)-ROW('Sheet 2'!V$5)+1),ROW(5:5)))} -> 8.7293487 | S9: {=INDEX('Sheet 2'!V$5:V$3173,SMALL(IF(S$3='Sheet 2'!S$5:S$3173,ROW('Sheet 2'!V$5:V$3173)-ROW('Sheet 2'!V$5)+1),ROW(5:5)))} -> 36.910225 | U9: {=INDEX('Sheet 2'!V$5:V$3173,SMALL(IF(U$3='Sheet 2'!S$5:S$3173,ROW('Sheet 2'!V$5:V$3173)-ROW('Sheet 2'!V$5)+1),ROW(5:5)))} -> 3.6331437 | X9: {=INDEX('Sheet 2'!AA$13:AA$3173,SMALL(IF(X$3='Sheet 2'!X$13:X$3173,ROW('Sheet 2'!AA$13:AA$3173)-ROW('Sheet 2'!AA$13)+1),ROW(5:5)))} -> 0.96361007 | Y9: {=INDEX('Sheet 2'!AA$13:AA$3173,SMALL(IF(Y$3='Sheet 2'!X$13:X$3173,ROW('Sheet 2'!AA$13:AA$3173)-ROW('Sheet 2'!AA$13)+1),ROW(5:5)))} -> -8.9156743 | Z9: {=INDEX('Sheet 2'!AA$13:AA$3173,SMALL(IF(Z$3='Sheet 2'!X$13:X$3173,ROW('Sheet 2'!AA$13:AA$3173)-ROW('Sheet 2'!AA$13)+1),ROW(5:5)))} -> -1.8375104 | AA9: {=INDEX('Sheet 2'!V$5:V$3173,SMALL(IF(AA$3='Sheet 2'!S$5:S$3173,ROW('Sheet 2'!V$5:V$3173)-ROW('Sheet 2'!V$5)+1),ROW(5:5)))} -> 0.18393364 | AB9: {=INDEX('Sheet 2'!V$5:V$3173,SMALL(IF(AB$3='Sheet 2'!S$5:S$3173,ROW('Sheet 2'!V$5:V$3173)-ROW('Sheet 2'!V$5)+1),ROW(5:5)))} -> 0.071498822 | AC9: {=INDEX('Sheet 2'!V$5:V$3173,SMALL(IF(AC$3='Sheet 2'!S$5:S$3173,ROW('Sheet 2'!V$5:V$3173)-ROW('Sheet 2'!V$5)+1),ROW(5:5)))} -> 0.067472026 | AD9: {=INDEX('Sheet 2'!V$5:V$3173,SMALL(IF(AD$3='Sheet 2'!S$5:S$3173,ROW('Sheet 2'!V$5:V$3173)-ROW('Sheet 2'!V$5)+1),ROW(5:5)))} -> -1.0670174 | AE9: {=INDEX('Sheet 2'!V$5:V$3173,SMALL(IF(AE$3='Sheet 2'!S$5:S$3173,ROW('Sheet 2'!V$5:V$3173)-ROW('Sheet 2'!V$5)+1),ROW(5:5)))} -> 0.11967883 | AF9: {=INDEX('Sheet 2'!V$5:V$3173,SMALL(IF(AF$3='Sheet 2'!S$5:S$3173,ROW('Sheet 2'!V$5:V$3173)-ROW('Sheet 2'!V$5)+1),ROW(5:5)))} -> 1.6738573 | AH9: {=INDEX('Sheet 2'!AA$5:AA$3173,SMALL(IF(AH$3='Sheet 2'!X$5:X$3173,ROW('Sheet 2'!AA$5:AA$3173)-ROW('Sheet 2'!AA$5)+1),ROW(5:5)))} -> #DIV/0! | AJ9: {=INDEX('Sheet 2'!V$5:V$3173,SMALL(IF(AJ$3='Sheet 2'!S$5:S$3173,ROW('Sheet 2'!V$5:V$3173)-ROW('Sheet 2'!V$5)+1),ROW(5:5)))} -> #NUM! | AL9: {=INDEX('Sheet 2'!AA$5:AA$3173,SMALL(IF(AL$3='Sheet 2'!X$5:X$3173,ROW('Sheet 2'!AA$5:AA$3173)-ROW('Sheet 2'!AA$5)+1),ROW(5:5)))} -> #DIV/0! | AN9: {=INDEX('Sheet 2'!AA$5:AA$3173,SMALL(IF(AN$3='Sheet 2'!X$5:X$3173,ROW('Sheet 2'!AA$5:AA$3173)-ROW('Sheet 2'!AA$5)+1),ROW(5:5)))} -> #DIV/0!
A10: {=INDEX('Sheet 2'!T$2:T$3173,SMALL(IF(A$3='Sheet 2'!$S$2:$S$3173,ROW('Sheet 2'!T$2:T$3173)-ROW('Sheet 2'!$T$2)+1),ROW(6:6)))} -> NCR | B10: {=INDEX('Sheet 2'!V$5:V$3173,SMALL(IF(B$3='Sheet 2'!S$5:S$3173,ROW('Sheet 2'!V$5:V$3173)-ROW('Sheet 2'!V$5)+1),ROW(6:6)))} -> 32.98 | C10: {=INDEX('Sheet 2'!V$5:V$3173,SMALL(IF(C$3='Sheet 2'!S$5:S$3173,ROW('Sheet 2'!V$5:V$3173)-ROW('Sheet 2'!V$5)+1),ROW(6:6)))} -> 4.020262e+09 | D10: {=INDEX('Sheet 2'!V$5:V$3173,SMALL(IF(D$3='Sheet 2'!S$5:S$3173,ROW('Sheet 2'!V$5:V$3173)-ROW('Sheet 2'!V$5)+1),ROW(6:6)))} -> 6474262000 | E10: {=INDEX('Sheet 2'!V$5:V$3173,SMALL(IF(E$3='Sheet 2'!S$5:S$3173,ROW('Sheet 2'!V$5:V$3173)-ROW('Sheet 2'!V$5)+1),ROW(6:6)))} -> 719000000 | F10: {=INDEX('Sheet 2'!V$5:V$3173,SMALL(IF(F$3='Sheet 2'!S$5:S$3173,ROW('Sheet 2'!V$5:V$3173)-ROW('Sheet 2'!V$5)+1),ROW(6:6)))} -> 6516000000 | I10: {=INDEX('Sheet 2'!V$5:V$3173,SMALL(IF(I$3='Sheet 2'!S$5:S$3173,ROW('Sheet 2'!V$5:V$3173)-ROW('Sheet 2'!V$5)+1),ROW(6:6)))} -> 32.653465 | K10: {=INDEX('Sheet 2'!V$5:V$3173,SMALL(IF(K$3='Sheet 2'!S$5:S$3173,ROW('Sheet 2'!V$5:V$3173)-ROW('Sheet 2'!V$5)+1),ROW(6:6)))} -> 0.61698312 | M10: {=INDEX('Sheet 2'!V$5:V$3173,SMALL(IF(M$3='Sheet 2'!S$5:S$3173,ROW('Sheet 2'!V$5:V$3173)-ROW('Sheet 2'!V$5)+1),ROW(6:6)))} -> 5.5914631 | O10: {=INDEX('Sheet 2'!V$5:V$3173,SMALL(IF(O$3='Sheet 2'!S$5:S$3173,ROW('Sheet 2'!V$5:V$3173)-ROW('Sheet 2'!V$5)+1),ROW(6:6)))} -> 7.6334089 | Q10: {=INDEX('Sheet 2'!V$5:V$3173,SMALL(IF(Q$3='Sheet 2'!S$5:S$3173,ROW('Sheet 2'!V$5:V$3173)-ROW('Sheet 2'!V$5)+1),ROW(6:6)))} -> 5.176303 | S10: {=INDEX('Sheet 2'!V$5:V$3173,SMALL(IF(S$3='Sheet 2'!S$5:S$3173,ROW('Sheet 2'!V$5:V$3173)-ROW('Sheet 2'!V$5)+1),ROW(6:6)))} -> 24.616966 | U10: {=INDEX('Sheet 2'!V$5:V$3173,SMALL(IF(U$3='Sheet 2'!S$5:S$3173,ROW('Sheet 2'!V$5:V$3173)-ROW('Sheet 2'!V$5)+1),ROW(6:6)))} -> 6.6043093 | X10: {=INDEX('Sheet 2'!AA$13:AA$3173,SMALL(IF(X$3='Sheet 2'!X$13:X$3173,ROW('Sheet 2'!AA$13:AA$3173)-ROW('Sheet 2'!AA$13)+1),ROW(6:6)))} -> 1.3800414 | Y10: {=INDEX('Sheet 2'!AA$13:AA$3173,SMALL(IF(Y$3='Sheet 2'!X$13:X$3173,ROW('Sheet 2'!AA$13:AA$3173)-ROW('Sheet 2'!AA$13)+1),ROW(6:6)))} -> 11.648253 | Z10: {=INDEX('Sheet 2'!AA$13:AA$3173,SMALL(IF(Z$3='Sheet 2'!X$13:X$3173,ROW('Sheet 2'!AA$13:AA$3173)-ROW('Sheet 2'!AA$13)+1),ROW(6:6)))} -> 4.514844 | AA10: {=INDEX('Sheet 2'!V$5:V$3173,SMALL(IF(AA$3='Sheet 2'!S$5:S$3173,ROW('Sheet 2'!V$5:V$3173)-ROW('Sheet 2'!V$5)+1),ROW(6:6)))} -> 0.28606507 | AB10: {=INDEX('Sheet 2'!V$5:V$3173,SMALL(IF(AB$3='Sheet 2'!S$5:S$3173,ROW('Sheet 2'!V$5:V$3173)-ROW('Sheet 2'!V$5)+1),ROW(6:6)))} -> 0.035604665 | AC10: {=INDEX('Sheet 2'!V$5:V$3173,SMALL(IF(AC$3='Sheet 2'!S$5:S$3173,ROW('Sheet 2'!V$5:V$3173)-ROW('Sheet 2'!V$5)+1),ROW(6:6)))} -> 0.10374463 | AD10: {=INDEX('Sheet 2'!V$5:V$3173,SMALL(IF(AD$3='Sheet 2'!S$5:S$3173,ROW('Sheet 2'!V$5:V$3173)-ROW('Sheet 2'!V$5)+1),ROW(6:6)))} -> 0.34874107 | AE10: {=INDEX('Sheet 2'!V$5:V$3173,SMALL(IF(AE$3='Sheet 2'!S$5:S$3173,ROW('Sheet 2'!V$5:V$3173)-ROW('Sheet 2'!V$5)+1),ROW(6:6)))} -> 0.029939347 | AF10: {=INDEX('Sheet 2'!V$5:V$3173,SMALL(IF(AF$3='Sheet 2'!S$5:S$3173,ROW('Sheet 2'!V$5:V$3173)-ROW('Sheet 2'!V$5)+1),ROW(6:6)))} -> 0.84088269 | AH10: {=INDEX('Sheet 2'!AA$5:AA$3173,SMALL(IF(AH$3='Sheet 2'!X$5:X$3173,ROW('Sheet 2'!AA$5:AA$3173)-ROW('Sheet 2'!AA$5)+1),ROW(6:6)))} -> 0 | AJ10: {=INDEX('Sheet 2'!V$5:V$3173,SMALL(IF(AJ$3='Sheet 2'!S$5:S$3173,ROW('Sheet 2'!V$5:V$3173)-ROW('Sheet 2'!V$5)+1),ROW(6:6)))} -> #NUM! | AL10: {=INDEX('Sheet 2'!AA$5:AA$3173,SMALL(IF(AL$3='Sheet 2'!X$5:X$3173,ROW('Sheet 2'!AA$5:AA$3173)-ROW('Sheet 2'!AA$5)+1),ROW(6:6)))} -> 0 | AN10: {=INDEX('Sheet 2'!AA$5:AA$3173,SMALL(IF(AN$3='Sheet 2'!X$5:X$3173,ROW('Sheet 2'!AA$5:AA$3173)-ROW('Sheet 2'!AA$5)+1),ROW(6:6)))} -> 0
A11: {=INDEX('Sheet 2'!T$2:T$3173,SMALL(IF(A$3='Sheet 2'!$S$2:$S$3173,ROW('Sheet 2'!T$2:T$3173)-ROW('Sheet 2'!$T$2)+1),ROW(7:7)))} -> OSS | B11: {=INDEX('Sheet 2'!V$5:V$3173,SMALL(IF(B$3='Sheet 2'!S$5:S$3173,ROW('Sheet 2'!V$5:V$3173)-ROW('Sheet 2'!V$5)+1),ROW(7:7)))} -> 5.065 | C11: {=INDEX('Sheet 2'!V$5:V$3173,SMALL(IF(C$3='Sheet 2'!S$5:S$3173,ROW('Sheet 2'!V$5:V$3173)-ROW('Sheet 2'!V$5)+1),ROW(7:7)))} -> 39606036 | D11: {=INDEX('Sheet 2'!V$5:V$3173,SMALL(IF(D$3='Sheet 2'!S$5:S$3173,ROW('Sheet 2'!V$5:V$3173)-ROW('Sheet 2'!V$5)+1),ROW(7:7)))} -> 42892598 | E11: {=INDEX('Sheet 2'!V$5:V$3173,SMALL(IF(E$3='Sheet 2'!S$5:S$3173,ROW('Sheet 2'!V$5:V$3173)-ROW('Sheet 2'!V$5)+1),ROW(7:7)))} -> 6241885 | F11: {=INDEX('Sheet 2'!V$5:V$3173,SMALL(IF(F$3='Sheet 2'!S$5:S$3173,ROW('Sheet 2'!V$5:V$3173)-ROW('Sheet 2'!V$5)+1),ROW(7:7)))} -> 26980014 | I11: {=INDEX('Sheet 2'!V$5:V$3173,SMALL(IF(I$3='Sheet 2'!S$5:S$3173,ROW('Sheet 2'!V$5:V$3173)-ROW('Sheet 2'!V$5)+1),ROW(7:7)))} | K11: {=INDEX('Sheet 2'!V$5:V$3173,SMALL(IF(K$3='Sheet 2'!S$5:S$3173,ROW('Sheet 2'!V$5:V$3173)-ROW('Sheet 2'!V$5)+1),ROW(7:7)))} -> 1.4679768 | M11: {=INDEX('Sheet 2'!V$5:V$3173,SMALL(IF(M$3='Sheet 2'!S$5:S$3173,ROW('Sheet 2'!V$5:V$3173)-ROW('Sheet 2'!V$5)+1),ROW(7:7)))} -> #DIV/0! | O11: {=INDEX('Sheet 2'!V$5:V$3173,SMALL(IF(O$3='Sheet 2'!S$5:S$3173,ROW('Sheet 2'!V$5:V$3173)-ROW('Sheet 2'!V$5)+1),ROW(7:7)))} | Q11: {=INDEX('Sheet 2'!V$5:V$3173,SMALL(IF(Q$3='Sheet 2'!S$5:S$3173,ROW('Sheet 2'!V$5:V$3173)-ROW('Sheet 2'!V$5)+1),ROW(7:7)))} -> 459.76546 | S11: {=INDEX('Sheet 2'!V$5:V$3173,SMALL(IF(S$3='Sheet 2'!S$5:S$3173,ROW('Sheet 2'!V$5:V$3173)-ROW('Sheet 2'!V$5)+1),ROW(7:7)))} -> -447.01209 | U11: {=INDEX('Sheet 2'!V$5:V$3173,SMALL(IF(U$3='Sheet 2'!S$5:S$3173,ROW('Sheet 2'!V$5:V$3173)-ROW('Sheet 2'!V$5)+1),ROW(7:7)))} -> 3.3251578 | X11: {=INDEX('Sheet 2'!AA$13:AA$3173,SMALL(IF(X$3='Sheet 2'!X$13:X$3173,ROW('Sheet 2'!AA$13:AA$3173)-ROW('Sheet 2'!AA$13)+1),ROW(7:7)))} -> 1.1417412 | Y11: {=INDEX('Sheet 2'!AA$13:AA$3173,SMALL(IF(Y$3='Sheet 2'!X$13:X$3173,ROW('Sheet 2'!AA$13:AA$3173)-ROW('Sheet 2'!AA$13)+1),ROW(7:7)))} -> 1.2286032 | Z11: {=INDEX('Sheet 2'!AA$13:AA$3173,SMALL(IF(Z$3='Sheet 2'!X$13:X$3173,ROW('Sheet 2'!AA$13:AA$3173)-ROW('Sheet 2'!AA$13)+1),ROW(7:7)))} -> 0.13852941 | AA11: {=INDEX('Sheet 2'!V$5:V$3173,SMALL(IF(AA$3='Sheet 2'!S$5:S$3173,ROW('Sheet 2'!V$5:V$3173)-ROW('Sheet 2'!V$5)+1),ROW(7:7)))} -> 0.31959568 | AB11: {=INDEX('Sheet 2'!V$5:V$3173,SMALL(IF(AB$3='Sheet 2'!S$5:S$3173,ROW('Sheet 2'!V$5:V$3173)-ROW('Sheet 2'!V$5)+1),ROW(7:7)))} -> 0.0019291688 | AC11: {=INDEX('Sheet 2'!V$5:V$3173,SMALL(IF(AC$3='Sheet 2'!S$5:S$3173,ROW('Sheet 2'!V$5:V$3173)-ROW('Sheet 2'!V$5)+1),ROW(7:7)))} -> 0.00033198648 | AD11: {=INDEX('Sheet 2'!V$5:V$3173,SMALL(IF(AD$3='Sheet 2'!S$5:S$3173,ROW('Sheet 2'!V$5:V$3173)-ROW('Sheet 2'!V$5)+1),ROW(7:7)))} -> 0.008629793 | AE11: {=INDEX('Sheet 2'!V$5:V$3173,SMALL(IF(AE$3='Sheet 2'!S$5:S$3173,ROW('Sheet 2'!V$5:V$3173)-ROW('Sheet 2'!V$5)+1),ROW(7:7)))} -> 0.0070240684 | AF11: {=INDEX('Sheet 2'!V$5:V$3173,SMALL(IF(AF$3='Sheet 2'!S$5:S$3173,ROW('Sheet 2'!V$5:V$3173)-ROW('Sheet 2'!V$5)+1),ROW(7:7)))} -> 3.6409818 | AH11: {=INDEX('Sheet 2'!AA$5:AA$3173,SMALL(IF(AH$3='Sheet 2'!X$5:X$3173,ROW('Sheet 2'!AA$5:AA$3173)-ROW('Sheet 2'!AA$5)+1),ROW(7:7)))} -> -0.13899251 | AJ11: {=INDEX('Sheet 2'!V$5:V$3173,SMALL(IF(AJ$3='Sheet 2'!S$5:S$3173,ROW('Sheet 2'!V$5:V$3173)-ROW('Sheet 2'!V$5)+1),ROW(7:7)))} -> #NUM! | AL11: {=INDEX('Sheet 2'!AA$5:AA$3173,SMALL(IF(AL$3='Sheet 2'!X$5:X$3173,ROW('Sheet 2'!AA$5:AA$3173)-ROW('Sheet 2'!AA$5)+1),ROW(7:7)))} -> -0.077475183 | AN11: {=INDEX('Sheet 2'!AA$5:AA$3173,SMALL(IF(AN$3='Sheet 2'!X$5:X$3173,ROW('Sheet 2'!AA$5:AA$3173)-ROW('Sheet 2'!AA$5)+1),ROW(7:7)))} -> 0.085515098
A12: {=INDEX('Sheet 2'!T$2:T$3173,SMALL(IF(A$3='Sheet 2'!$S$2:$S$3173,ROW('Sheet 2'!T$2:T$3173)-ROW('Sheet 2'!$T$2)+1),ROW(8:8)))} -> PAR | B12: {=INDEX('Sheet 2'!V$5:V$3173,SMALL(IF(B$3='Sheet 2'!S$5:S$3173,ROW('Sheet 2'!V$5:V$3173)-ROW('Sheet 2'!V$5)+1),ROW(8:8)))} -> 11.91 | C12: {=INDEX('Sheet 2'!V$5:V$3173,SMALL(IF(C$3='Sheet 2'!S$5:S$3173,ROW('Sheet 2'!V$5:V$3173)-ROW('Sheet 2'!V$5)+1),ROW(8:8)))} -> 189952590 | D12: {=INDEX('Sheet 2'!V$5:V$3173,SMALL(IF(D$3='Sheet 2'!S$5:S$3173,ROW('Sheet 2'!V$5:V$3173)-ROW('Sheet 2'!V$5)+1),ROW(8:8)))} -> 184682590 | E12: {=INDEX('Sheet 2'!V$5:V$3173,SMALL(IF(E$3='Sheet 2'!S$5:S$3173,ROW('Sheet 2'!V$5:V$3173)-ROW('Sheet 2'!V$5)+1),ROW(8:8)))} -> 68986000 | F12: {=INDEX('Sheet 2'!V$5:V$3173,SMALL(IF(F$3='Sheet 2'!S$5:S$3173,ROW('Sheet 2'!V$5:V$3173)-ROW('Sheet 2'!V$5)+1),ROW(8:8)))} -> 232605000 | I12: {=INDEX('Sheet 2'!V$5:V$3173,SMALL(IF(I$3='Sheet 2'!S$5:S$3173,ROW('Sheet 2'!V$5:V$3173)-ROW('Sheet 2'!V$5)+1),ROW(8:8)))} | K12: {=INDEX('Sheet 2'!V$5:V$3173,SMALL(IF(K$3='Sheet 2'!S$5:S$3173,ROW('Sheet 2'!V$5:V$3173)-ROW('Sheet 2'!V$5)+1),ROW(8:8)))} -> 0.81663159 | M12: {=INDEX('Sheet 2'!V$5:V$3173,SMALL(IF(M$3='Sheet 2'!S$5:S$3173,ROW('Sheet 2'!V$5:V$3173)-ROW('Sheet 2'!V$5)+1),ROW(8:8)))} -> 2.7534948 | O12: {=INDEX('Sheet 2'!V$5:V$3173,SMALL(IF(O$3='Sheet 2'!S$5:S$3173,ROW('Sheet 2'!V$5:V$3173)-ROW('Sheet 2'!V$5)+1),ROW(8:8)))} | Q12: {=INDEX('Sheet 2'!V$5:V$3173,SMALL(IF(Q$3='Sheet 2'!S$5:S$3173,ROW('Sheet 2'!V$5:V$3173)-ROW('Sheet 2'!V$5)+1),ROW(8:8)))} -> 47.871116 | S12: {=INDEX('Sheet 2'!V$5:V$3173,SMALL(IF(S$3='Sheet 2'!S$5:S$3173,ROW('Sheet 2'!V$5:V$3173)-ROW('Sheet 2'!V$5)+1),ROW(8:8)))} -> -142.94318 | U12: {=INDEX('Sheet 2'!V$5:V$3173,SMALL(IF(U$3='Sheet 2'!S$5:S$3173,ROW('Sheet 2'!V$5:V$3173)-ROW('Sheet 2'!V$5)+1),ROW(8:8)))} -> 7.9715845 | X12: {=INDEX('Sheet 2'!AA$13:AA$3173,SMALL(IF(X$3='Sheet 2'!X$13:X$3173,ROW('Sheet 2'!AA$13:AA$3173)-ROW('Sheet 2'!AA$13)+1),ROW(8:8)))} -> 1.6735686 | Y12: {=INDEX('Sheet 2'!AA$13:AA$3173,SMALL(IF(Y$3='Sheet 2'!X$13:X$3173,ROW('Sheet 2'!AA$13:AA$3173)-ROW('Sheet 2'!AA$13)+1),ROW(8:8)))} -> 1.661484 | Z12: {=INDEX('Sheet 2'!AA$13:AA$3173,SMALL(IF(Z$3='Sheet 2'!X$13:X$3173,ROW('Sheet 2'!AA$13:AA$3173)-ROW('Sheet 2'!AA$13)+1),ROW(8:8)))} -> 0.0035863718 | AA12: {=INDEX('Sheet 2'!V$5:V$3173,SMALL(IF(AA$3='Sheet 2'!S$5:S$3173,ROW('Sheet 2'!V$5:V$3173)-ROW('Sheet 2'!V$5)+1),ROW(8:8)))} -> 0.22712323 | AB12: {=INDEX('Sheet 2'!V$5:V$3173,SMALL(IF(AB$3='Sheet 2'!S$5:S$3173,ROW('Sheet 2'!V$5:V$3173)-ROW('Sheet 2'!V$5)+1),ROW(8:8)))} -> -0.014556867 | AC12: {=INDEX('Sheet 2'!V$5:V$3173,SMALL(IF(AC$3='Sheet 2'!S$5:S$3173,ROW('Sheet 2'!V$5:V$3173)-ROW('Sheet 2'!V$5)+1),ROW(8:8)))} -> -0.00052019518 | AD12: {=INDEX('Sheet 2'!V$5:V$3173,SMALL(IF(AD$3='Sheet 2'!S$5:S$3173,ROW('Sheet 2'!V$5:V$3173)-ROW('Sheet 2'!V$5)+1),ROW(8:8)))} -> -0.047067655 | AE12: {=INDEX('Sheet 2'!V$5:V$3173,SMALL(IF(AE$3='Sheet 2'!S$5:S$3173,ROW('Sheet 2'!V$5:V$3173)-ROW('Sheet 2'!V$5)+1),ROW(8:8)))} -> -0.028328683 | AF12: {=INDEX('Sheet 2'!V$5:V$3173,SMALL(IF(AF$3='Sheet 2'!S$5:S$3173,ROW('Sheet 2'!V$5:V$3173)-ROW('Sheet 2'!V$5)+1),ROW(8:8)))} -> 1.9460701 | AH12: {=INDEX('Sheet 2'!AA$5:AA$3173,SMALL(IF(AH$3='Sheet 2'!X$5:X$3173,ROW('Sheet 2'!AA$5:AA$3173)-ROW('Sheet 2'!AA$5)+1),ROW(8:8)))} -> 29643000000 | AJ12: {=INDEX('Sheet 2'!V$5:V$3173,SMALL(IF(AJ$3='Sheet 2'!S$5:S$3173,ROW('Sheet 2'!V$5:V$3173)-ROW('Sheet 2'!V$5)+1),ROW(8:8)))} -> #NUM! | AL12: {=INDEX('Sheet 2'!AA$5:AA$3173,SMALL(IF(AL$3='Sheet 2'!X$5:X$3173,ROW('Sheet 2'!AA$5:AA$3173)-ROW('Sheet 2'!AA$5)+1),ROW(8:8)))} -> 1513000000 | AN12: {=INDEX('Sheet 2'!AA$5:AA$3173,SMALL(IF(AN$3='Sheet 2'!X$5:X$3173,ROW('Sheet 2'!AA$5:AA$3173)-ROW('Sheet 2'!AA$5)+1),ROW(8:8)))} -> 0.95
A13: {=INDEX('Sheet 2'!T$2:T$3173,SMALL(IF(A$3='Sheet 2'!$S$2:$S$3173,ROW('Sheet 2'!T$2:T$3173)-ROW('Sheet 2'!$T$2)+1),ROW(9:9)))} -> TDC | B13: {=INDEX('Sheet 2'!V$5:V$3173,SMALL(IF(B$3='Sheet 2'!S$5:S$3173,ROW('Sheet 2'!V$5:V$3173)-ROW('Sheet 2'!V$5)+1),ROW(9:9)))} -> 42.139999 | C13: {=INDEX('Sheet 2'!V$5:V$3173,SMALL(IF(C$3='Sheet 2'!S$5:S$3173,ROW('Sheet 2'!V$5:V$3173)-ROW('Sheet 2'!V$5)+1),ROW(9:9)))} -> 5.3012119e+09 | D13: {=INDEX('Sheet 2'!V$5:V$3173,SMALL(IF(D$3='Sheet 2'!S$5:S$3173,ROW('Sheet 2'!V$5:V$3173)-ROW('Sheet 2'!V$5)+1),ROW(9:9)))} -> 4.9902119e+09 | E13: {=INDEX('Sheet 2'!V$5:V$3173,SMALL(IF(E$3='Sheet 2'!S$5:S$3173,ROW('Sheet 2'!V$5:V$3173)-ROW('Sheet 2'!V$5)+1),ROW(9:9)))} -> 668000000 | F13: {=INDEX('Sheet 2'!V$5:V$3173,SMALL(IF(F$3='Sheet 2'!S$5:S$3173,ROW('Sheet 2'!V$5:V$3173)-ROW('Sheet 2'!V$5)+1),ROW(9:9)))} -> 2156000000 | I13: {=INDEX('Sheet 2'!V$5:V$3173,SMALL(IF(I$3='Sheet 2'!S$5:S$3173,ROW('Sheet 2'!V$5:V$3173)-ROW('Sheet 2'!V$5)+1),ROW(9:9)))} | K13: {=INDEX('Sheet 2'!V$5:V$3173,SMALL(IF(K$3='Sheet 2'!S$5:S$3173,ROW('Sheet 2'!V$5:V$3173)-ROW('Sheet 2'!V$5)+1),ROW(9:9)))} -> 2.4588181 | M13: {=INDEX('Sheet 2'!V$5:V$3173,SMALL(IF(M$3='Sheet 2'!S$5:S$3173,ROW('Sheet 2'!V$5:V$3173)-ROW('Sheet 2'!V$5)+1),ROW(9:9)))} -> 7.6520687 | O13: {=INDEX('Sheet 2'!V$5:V$3173,SMALL(IF(O$3='Sheet 2'!S$5:S$3173,ROW('Sheet 2'!V$5:V$3173)-ROW('Sheet 2'!V$5)+1),ROW(9:9)))} -> 18.798624 | Q13: {=INDEX('Sheet 2'!V$5:V$3173,SMALL(IF(Q$3='Sheet 2'!S$5:S$3173,ROW('Sheet 2'!V$5:V$3173)-ROW('Sheet 2'!V$5)+1),ROW(9:9)))} -> 13.581243 | S13: {=INDEX('Sheet 2'!V$5:V$3173,SMALL(IF(S$3='Sheet 2'!S$5:S$3173,ROW('Sheet 2'!V$5:V$3173)-ROW('Sheet 2'!V$5)+1),ROW(9:9)))} -> 51.981374 | U13: {=INDEX('Sheet 2'!V$5:V$3173,SMALL(IF(U$3='Sheet 2'!S$5:S$3173,ROW('Sheet 2'!V$5:V$3173)-ROW('Sheet 2'!V$5)+1),ROW(9:9)))} -> 2.28219 | X13: {=INDEX('Sheet 2'!AA$13:AA$3173,SMALL(IF(X$3='Sheet 2'!X$13:X$3173,ROW('Sheet 2'!AA$13:AA$3173)-ROW('Sheet 2'!AA$13)+1),ROW(9:9)))} -> 1.7953668 | Y13: {=INDEX('Sheet 2'!AA$13:AA$3173,SMALL(IF(Y$3='Sheet 2'!X$13:X$3173,ROW('Sheet 2'!AA$13:AA$3173)-ROW('Sheet 2'!AA$13)+1),ROW(9:9)))} -> 3.0140056 | Z13: {=INDEX('Sheet 2'!AA$13:AA$3173,SMALL(IF(Z$3='Sheet 2'!X$13:X$3173,ROW('Sheet 2'!AA$13:AA$3173)-ROW('Sheet 2'!AA$13)+1),ROW(9:9)))} -> 0.62309368 | AA13: {=INDEX('Sheet 2'!V$5:V$3173,SMALL(IF(AA$3='Sheet 2'!S$5:S$3173,ROW('Sheet 2'!V$5:V$3173)-ROW('Sheet 2'!V$5)+1),ROW(9:9)))} -> 0.47402597 | AB13: {=INDEX('Sheet 2'!V$5:V$3173,SMALL(IF(AB$3='Sheet 2'!S$5:S$3173,ROW('Sheet 2'!V$5:V$3173)-ROW('Sheet 2'!V$5)+1),ROW(9:9)))} -> -0.031076067 | AC13: {=INDEX('Sheet 2'!V$5:V$3173,SMALL(IF(AC$3='Sheet 2'!S$5:S$3173,ROW('Sheet 2'!V$5:V$3173)-ROW('Sheet 2'!V$5)+1),ROW(9:9)))} -> 0.029684601 | AD13: {=INDEX('Sheet 2'!V$5:V$3173,SMALL(IF(AD$3='Sheet 2'!S$5:S$3173,ROW('Sheet 2'!V$5:V$3173)-ROW('Sheet 2'!V$5)+1),ROW(9:9)))} -> -0.083411142 | AE13: {=INDEX('Sheet 2'!V$5:V$3173,SMALL(IF(AE$3='Sheet 2'!S$5:S$3173,ROW('Sheet 2'!V$5:V$3173)-ROW('Sheet 2'!V$5)+1),ROW(9:9)))} -> -0.027674515 | AF13: {=INDEX('Sheet 2'!V$5:V$3173,SMALL(IF(AF$3='Sheet 2'!S$5:S$3173,ROW('Sheet 2'!V$5:V$3173)-ROW('Sheet 2'!V$5)+1),ROW(9:9)))} -> 0.8905411 | AH13: {=INDEX('Sheet 2'!AA$5:AA$3173,SMALL(IF(AH$3='Sheet 2'!X$5:X$3173,ROW('Sheet 2'!AA$5:AA$3173)-ROW('Sheet 2'!AA$5)+1),ROW(9:9)))} -> -0.13357794 | AJ13: {=INDEX('Sheet 2'!V$5:V$3173,SMALL(IF(AJ$3='Sheet 2'!S$5:S$3173,ROW('Sheet 2'!V$5:V$3173)-ROW('Sheet 2'!V$5)+1),ROW(9:9)))} -> #NUM! | AL13: {=INDEX('Sheet 2'!AA$5:AA$3173,SMALL(IF(AL$3='Sheet 2'!X$5:X$3173,ROW('Sheet 2'!AA$5:AA$3173)-ROW('Sheet 2'!AA$5)+1),ROW(9:9)))} -> -0.13775278 | AN13: {=INDEX('Sheet 2'!AA$5:AA$3173,SMALL(IF(AN$3='Sheet 2'!X$5:X$3173,ROW('Sheet 2'!AA$5:AA$3173)-ROW('Sheet 2'!AA$5)+1),ROW(9:9)))} -> -0.10836084
A14: {=INDEX('Sheet 2'!T$2:T$3173,SMALL(IF(A$3='Sheet 2'!$S$2:$S$3173,ROW('Sheet 2'!T$2:T$3173)-ROW('Sheet 2'!$T$2)+1),ROW(10:10)))} -> XPLR | B14: {=INDEX('Sheet 2'!V$5:V$3173,SMALL(IF(B$3='Sheet 2'!S$5:S$3173,ROW('Sheet 2'!V$5:V$3173)-ROW('Sheet 2'!V$5)+1),ROW(10:10)))} -> 3.65 | C14: {=INDEX('Sheet 2'!V$5:V$3173,SMALL(IF(C$3='Sheet 2'!S$5:S$3173,ROW('Sheet 2'!V$5:V$3173)-ROW('Sheet 2'!V$5)+1),ROW(10:10)))} -> 40137079 | D14: {=INDEX('Sheet 2'!V$5:V$3173,SMALL(IF(D$3='Sheet 2'!S$5:S$3173,ROW('Sheet 2'!V$5:V$3173)-ROW('Sheet 2'!V$5)+1),ROW(10:10)))} -> 54437079 | E14: {=INDEX('Sheet 2'!V$5:V$3173,SMALL(IF(E$3='Sheet 2'!S$5:S$3173,ROW('Sheet 2'!V$5:V$3173)-ROW('Sheet 2'!V$5)+1),ROW(10:10)))} -> 30655000 | F14: {=INDEX('Sheet 2'!V$5:V$3173,SMALL(IF(F$3='Sheet 2'!S$5:S$3173,ROW('Sheet 2'!V$5:V$3173)-ROW('Sheet 2'!V$5)+1),ROW(10:10)))} -> 83548000 | I14: {=INDEX('Sheet 2'!V$5:V$3173,SMALL(IF(I$3='Sheet 2'!S$5:S$3173,ROW('Sheet 2'!V$5:V$3173)-ROW('Sheet 2'!V$5)+1),ROW(10:10)))} -> 73 | K14: {=INDEX('Sheet 2'!V$5:V$3173,SMALL(IF(K$3='Sheet 2'!S$5:S$3173,ROW('Sheet 2'!V$5:V$3173)-ROW('Sheet 2'!V$5)+1),ROW(10:10)))} -> 0.48040742 | M14: {=INDEX('Sheet 2'!V$5:V$3173,SMALL(IF(M$3='Sheet 2'!S$5:S$3173,ROW('Sheet 2'!V$5:V$3173)-ROW('Sheet 2'!V$5)+1),ROW(10:10)))} -> 1.3122265 | O14: {=INDEX('Sheet 2'!V$5:V$3173,SMALL(IF(O$3='Sheet 2'!S$5:S$3173,ROW('Sheet 2'!V$5:V$3173)-ROW('Sheet 2'!V$5)+1),ROW(10:10)))} | Q14: {=INDEX('Sheet 2'!V$5:V$3173,SMALL(IF(Q$3='Sheet 2'!S$5:S$3173,ROW('Sheet 2'!V$5:V$3173)-ROW('Sheet 2'!V$5)+1),ROW(10:10)))} | S14: {=INDEX('Sheet 2'!V$5:V$3173,SMALL(IF(S$3='Sheet 2'!S$5:S$3173,ROW('Sheet 2'!V$5:V$3173)-ROW('Sheet 2'!V$5)+1),ROW(10:10)))} -> 60.418512 | U14: {=INDEX('Sheet 2'!V$5:V$3173,SMALL(IF(U$3='Sheet 2'!S$5:S$3173,ROW('Sheet 2'!V$5:V$3173)-ROW('Sheet 2'!V$5)+1),ROW(10:10)))} -> #NUM! | X14: {=INDEX('Sheet 2'!AA$13:AA$3173,SMALL(IF(X$3='Sheet 2'!X$13:X$3173,ROW('Sheet 2'!AA$13:AA$3173)-ROW('Sheet 2'!AA$13)+1),ROW(10:10)))} -> 1.6510462 | Y14: {=INDEX('Sheet 2'!AA$13:AA$3173,SMALL(IF(Y$3='Sheet 2'!X$13:X$3173,ROW('Sheet 2'!AA$13:AA$3173)-ROW('Sheet 2'!AA$13)+1),ROW(10:10)))} -> 1.9037288 | Z14: {=INDEX('Sheet 2'!AA$13:AA$3173,SMALL(IF(Z$3='Sheet 2'!X$13:X$3173,ROW('Sheet 2'!AA$13:AA$3173)-ROW('Sheet 2'!AA$13)+1),ROW(10:10)))} -> #DIV/0! | AA14: {=INDEX('Sheet 2'!V$5:V$3173,SMALL(IF(AA$3='Sheet 2'!S$5:S$3173,ROW('Sheet 2'!V$5:V$3173)-ROW('Sheet 2'!V$5)+1),ROW(10:10)))} -> 0.29822378 | AB14: {=INDEX('Sheet 2'!V$5:V$3173,SMALL(IF(AB$3='Sheet 2'!S$5:S$3173,ROW('Sheet 2'!V$5:V$3173)-ROW('Sheet 2'!V$5)+1),ROW(10:10)))} -> 0.0053861253 | AC14: {=INDEX('Sheet 2'!V$5:V$3173,SMALL(IF(AC$3='Sheet 2'!S$5:S$3173,ROW('Sheet 2'!V$5:V$3173)-ROW('Sheet 2'!V$5)+1),ROW(10:10)))} -> 0.0081390338 | AD14: {=INDEX('Sheet 2'!V$5:V$3173,SMALL(IF(AD$3='Sheet 2'!S$5:S$3173,ROW('Sheet 2'!V$5:V$3173)-ROW('Sheet 2'!V$5)+1),ROW(10:10)))} -> 0.015025418 | AE14: {=INDEX('Sheet 2'!V$5:V$3173,SMALL(IF(AE$3='Sheet 2'!S$5:S$3173,ROW('Sheet 2'!V$5:V$3173)-ROW('Sheet 2'!V$5)+1),ROW(10:10)))} -> 0.0078926252 | AF14: {=INDEX('Sheet 2'!V$5:V$3173,SMALL(IF(AF$3='Sheet 2'!S$5:S$3173,ROW('Sheet 2'!V$5:V$3173)-ROW('Sheet 2'!V$5)+1),ROW(10:10)))} -> 1.4653623 | AH14: {=INDEX('Sheet 2'!AA$5:AA$3173,SMALL(IF(AH$3='Sheet 2'!X$5:X$3173,ROW('Sheet 2'!AA$5:AA$3173)-ROW('Sheet 2'!AA$5)+1),ROW(10:10)))} -> 53889000000 | AJ14: {=INDEX('Sheet 2'!V$5:V$3173,SMALL(IF(AJ$3='Sheet 2'!S$5:S$3173,ROW('Sheet 2'!V$5:V$3173)-ROW('Sheet 2'!V$5)+1),ROW(10:10)))} -> #NUM! | AL14: {=INDEX('Sheet 2'!AA$5:AA$3173,SMALL(IF(AL$3='Sheet 2'!X$5:X$3173,ROW('Sheet 2'!AA$5:AA$3173)-ROW('Sheet 2'!AA$5)+1),ROW(10:10)))} -> 3853000000 | AN14: {=INDEX('Sheet 2'!AA$5:AA$3173,SMALL(IF(AN$3='Sheet 2'!X$5:X$3173,ROW('Sheet 2'!AA$5:AA$3173)-ROW('Sheet 2'!AA$5)+1),ROW(10:10)))} -> 2.31

Sheet Sheet 2
A2: 1 | S2: Symbol | T2: CCUR | V2: USD
D4: Income Statement | F4: 2016-10 | G4: 2017-01 | H4: 2017-04 | I4: 2017-07 | J4: 2017-10 | L4: 2013 | M4: 2014 | N4: 2015 | O4: 2016 | P4: 2017 | Q4: TTM | S4: Quote | X4: Growth | AA4: 5-Year Average | AC4: Key Ratios ― Growth, YOY | AF4: =M4 -> 2014 | AG4: =N4 -> 2015 | AH4: =O4 -> 2016 | AI4: =P4 -> 2017
D5: Revenue | F5: 15547000 | G5: 14981000 | H5: -15997000 | I5: 7870000 | L5: 63444000 | M5: 71171000 | N5: 64459000 | O5: 61149000 | P5: 27647000 | Q5: 250000000 | S5: Last Price | V5: 5.42 | X5: Revenue | AA5: =IF(AA4="Year over Year",AI5,IF(AA4="3-Year Average",AVERAGE(AH5:AI5),IF(AA4="5-Year Average",AVERAGE(AF5:AI5),""))) -> -0.14293524 | AC5: Revenue % | AF5: =IF(AND(M5>0,L5>0,L5<>""),M5/L5-1,IF(AND(L5<0,M5<0,L5<>""),(M5-L5)/ABS(L5),IF(AND(L5>0,M5<0,L5<>""),"L",IF(AND(L5<0,M5>0,L5<>""),"P","")))) -> 0.12179245 | AG5: =IF(AND(N5>0,M5>0,M5<>""),N5/M5-1,IF(AND(M5<0,N5<0,M5<>""),(N5-M5)/ABS(M5),IF(AND(M5>0,N5<0,M5<>""),"L",IF(AND(M5<0,N5>0,M5<>""),"P","")))) -> -0.094308075 | AH5: =IF(AND(O5>0,N5>0,N5<>""),O5/N5-1,IF(AND(N5<0,O5<0,N5<>""),(O5-N5)/ABS(N5),IF(AND(N5>0,O5<0,N5<>""),"L",IF(AND(N5<0,O5>0,N5<>""),"P","")))) -> -0.051350471 | AI5: =IF(AND(P5>0,O5>0,O5<>""),P5/O5-1,IF(AND(O5<0,P5<0,O5<>""),(P5-O5)/ABS(O5),IF(AND(O5>0,P5<0,O5<>""),"L",IF(AND(O5<0,P5>0,O5<>""),"P","")))) -> -0.54787486
D6: Cost of revenue | F6: 6098000 | G6: 6477000 | H6: -6056000 | I6: 3220000 | L6: 26607000 | M6: 30758000 | N6: 28069000 | O6: 24893000 | P6: 12452000 | S6: Market Capitalization | V6: =V5*Q13 -> 50682702 | X6: Operating Income | AA6: =IF(AA4="Year over Year",AI6,IF(AA4="3-Year Average",AVERAGE(AH6:AI6),IF(AA4="5-Year Average",AVERAGE(AF6:AI6),""))) -> 0.095715838 | AC6: Operating Income % | AF6: =IF(AND(M8>0,L8>0,L8<>""),M8/L8-1,IF(AND(L8<0,M8<0,L8<>""),(M8-L8)/ABS(L8),IF(AND(L8>0,M8<0,L8<>""),"L",IF(AND(L8<0,M8>0,L8<>""),"P","")))) -> 0.052631579 | AG6: =IF(AND(N8>0,M8>0,M8<>""),N8/M8-1,IF(AND(M8<0,N8<0,M8<>""),(N8-M8)/ABS(M8),IF(AND(M8>0,N8<0,M8<>""),"L",IF(AND(M8<0,N8>0,M8<>""),"P","")))) -> -0.82150943 | AH6: =IF(AND(O8>0,N8>0,N8<>""),O8/N8-1,IF(AND(N8<0,O8<0,N8<>""),(O8-N8)/ABS(N8),IF(AND(N8>0,O8<0,N8<>""),"L",IF(AND(N8<0,O8>0,N8<>""),"P","")))) -> 1.0560254 | AI6: =IF(AND(P8>0,O8>0,O8<>""),P8/O8-1,IF(AND(O8<0,P8<0,O8<>""),(P8-O8)/ABS(O8),IF(AND(O8>0,P8<0,O8<>""),"L",IF(AND(O8<0,P8>0,O8<>""),"P","")))) -> L
D7: Gross profit | F7: 9449000 | G7: 8504000 | H7: -9941000 | I7: 4650000 | J7: 0 | L7: 36837000 | M7: 40413000 | N7: 36390000 | O7: 36256000 | P7: 15195000 | Q7: 0 | S7: Enterprise Value | V7: =V6+(J21+J23)-J17 -> -6864298.2 | X7: Net Income | AA7: =IF(AA4="Year over Year",AI7,IF(AA4="3-Year Average",AVERAGE(AH7:AI7),IF(AA4="5-Year Average",AVERAGE(AF7:AI7),""))) -> -13.927713 | AC7: Net Income % | AF7: =IF(AND(M9>0,L9>0,L9<>""),M9/L9-1,IF(AND(L9<0,M9<0,L9<>""),(M9-L9)/ABS(L9),IF(AND(L9>0,M9<0,L9<>""),"L",IF(AND(L9<0,M9>0,L9<>""),"P","")))) -> 3.3561676 | AG7: =IF(AND(N9>0,M9>0,M9<>""),N9/M9-1,IF(AND(M9<0,N9<0,M9<>""),(N9-M9)/ABS(M9),IF(AND(M9>0,N9<0,M9<>""),"L",IF(AND(M9<0,N9>0,M9<>""),"P","")))) -> L | AH7: =IF(AND(O9>0,N9>0,N9<>""),O9/N9-1,IF(AND(N9<0,O9<0,N9<>""),(O9-N9)/ABS(N9),IF(AND(N9>0,O9<0,N9<>""),"L",IF(AND(N9<0,O9>0,N9<>""),"P","")))) -> -31.211594 | AI7: =IF(AND(P9>0,O9>0,O9<>""),P9/O9-1,IF(AND(O9<0,P9<0,O9<>""),(P9-O9)/ABS(O9),IF(AND(O9>0,P9<0,O9<>""),"L",IF(AND(O9<0,P9>0,O9<>""),"P","")))) -> P
D8: Operating income | F8: -48000 | G8: -1573000 | H8: -7672000 | I8: -1115000 | J8: -3859000 | L8: 5035000 | M8: 5300000 | N8: 946000 | O8: 1945000 | P8: -12236000 | Q8: -29791000 | S8: Book Value | V8: =J20-J24 -> 62117000 | X8: Earnings Per Share | AA8: =IF(AA4="Year over Year",AI8,IF(AA4="3-Year Average",AVERAGE(AH8:AI8),IF(AA4="5-Year Average",AVERAGE(AF8:AI8),""))) -> -13.002551 | AC8: Earnings per share % | AF8: =IF(AND(M10>0,L10>0,L10<>""),M10/L10-1,IF(AND(L10<0,M10<0,L10<>""),(M10-L10)/ABS(L10),IF(AND(L10>0,M10<0,L10<>""),"L",IF(AND(L10<0,M10>0,L10<>""),"P","")))) -> 3.244898 | AG8: =IF(AND(N10>0,M10>0,M10<>""),N10/M10-1,IF(AND(M10<0,N10<0,M10<>""),(N10-M10)/ABS(M10),IF(AND(M10>0,N10<0,M10<>""),"L",IF(AND(M10<0,N10>0,M10<>""),"P","")))) -> L | AH8: =IF(AND(O10>0,N10>0,N10<>""),O10/N10-1,IF(AND(N10<0,O10<0,N10<>""),(O10-N10)/ABS(N10),IF(AND(N10>0,O10<0,N10<>""),"L",IF(AND(N10<0,O10>0,N10<>""),"P","")))) -> -29.25 | AI8: =IF(AND(P10>0,O10>0,O10<>""),P10/O10-1,IF(AND(O10<0,P10<0,O10<>""),(P10-O10)/ABS(O10),IF(AND(O10>0,P10<0,O10<>""),"L",IF(AND(O10<0,P10>0,O10<>""),"P","")))) -> P
D9: Net income | F9: -88000 | G9: -1658000 | H9: 33055000 | I9: -1010000 | J9: 19888000 | L9: 4248000 | M9: 18505000 | N9: -345000 | O9: -11113000 | P9: 28381000 | Q9: 50275000 | S9: Type | V9: =IF(V6>10000,"Large Cap",IF(AND(10000>V6,2000<V6),"Mid Cap",IF(AND(2000>V6,V6>50),"Small Cap",IF(V6<50,"Micro Cap",NA)))) -> Large Cap
D10: Earnings per share | F10: -0.01 | G10: -0.18 | H10: 3.58 | I10: -0.11 | J10: 2.11 | L10: 0.49 | M10: 2.08 | N10: -0.04 | O10: -1.21 | P10: 3.07 | Q10: 5.4 | S10: Dividend Yield | X10: Financial Health | AC10: Financials | AE10: =L4 -> 2013 | AF10: =M4 -> 2014 | AG10: =N4 -> 2015 | AH10: =O4 -> 2016 | AI10: =P4 -> 2017
F11: 9244590 | G11: 9261862 | H11: 9313304 | I11: 9392197 | J11: 9436845 | L11: 8736000 | M11: 8911000 | N11: 9067697 | O11: 9154437 | P11: 9252275 | Q11: 9351052
F12: -0.01 | G12: -0.18 | H12: 3.58 | I12: -0.11 | J12: 2.11 | L12: 0.49 | M12: 2.08 | N12: -0.04 | O12: -1.21 | P12: 3.07 | Q12: 5.4
D13: Weighted average share… | F13: 9244590 | G13: 9261862 | H13: 9313304 | I13: 9392197 | J13: 9436845 | L13: 8736000 | M13: 8911000 | N13: 9067697 | O13: 9154437 | P13: 9252275 | Q13: 9351052 | X13: Current Ratio | AA13: =AVERAGE(G19:J19)/AVERAGE(G22:J22) -> 5.4407029 | AC13: Revenue | AE13: =IF(L5="","",L5) -> 63444000 | AF13: =IF(M5="","",M5) -> 71171000 | AG13: =IF(N5="","",N5) -> 64459000 | AH13: =IF(O5="","",O5) -> 61149000 | AI13: =IF(P5="","",P5) -> 27647000
D14: EBITDA | F14: 478000 | G14: -1093000 | H14: -7467000 | I14: -786000 | J14: -3582000 | L14: 7845000 | M14: 7461000 | N14: 2102000 | O14: 4516000 | P14: -10421000 | Q14: -13095000 | S14: Valuation | X14: Financial Leverage | AA14: =AVERAGE(G20:J20)/AVERAGE(G25:J25) -> 1.3644479 | AC14: Gross Margin % | AE14: =IF(OR(L5="",L7=""),"",L7/L5) -> 0.58062228 | AF14: =IF(OR(M5="",M7=""),"",M7/M5) -> 0.56782959 | AG14: =IF(OR(N5="",N7=""),"",N7/N5) -> 0.5645449 | AH14: =IF(OR(O5="",O7=""),"",O7/O5) -> 0.59291239 | AI14: =IF(OR(P5="",P7=""),"",P7/P5) -> 0.54960755
S15: P / E | V15: =IF(Q10>0,V5/Q10,"") -> 1.0037037 | X15: Debt / Equity | AA15: =AVERAGE(G23:J23)/AVERAGE(G25:J25) -> #DIV/0! | AC15: Operating Income | AE15: =IF(L8="","",L8) -> 5035000 | AF15: =IF(M8="","",M8) -> 5300000 | AG15: =IF(N8="","",N8) -> 946000 | AH15: =IF(O8="","",O8) -> 1945000 | AI15: =IF(P8="","",P8) -> -12236000
D16: Balance Sheet | F16: =F4 -> 2016-10 | G16: =G4 -> 2017-01 | H16: =H4 -> 2017-04 | I16: =I4 -> 2017-07 | J16: =J4 -> 2017-10 | L16: =L4 -> 2013 | M16: =M4 -> 2014 | N16: =N4 -> 2015 | O16: =O4 -> 2016 | P16: =P4 -> 2017 | S16: P / B | V16: =V5/((J20-J24)/J13) -> 0.82340905 | AC16: Operating Margin % | AE16: =IF(OR(L5="",L8=""),"",L8/L5) -> 0.079361327 | AF16: =IF(OR(M5="",M8=""),"",M8/M5) -> 0.074468534 | AG16: =IF(OR(N5="",N8=""),"",N8/N5) -> 0.014675996 | AH16: =IF(OR(O5="",O8=""),"",O8/O5) -> 0.031807552 | AI16: =IF(OR(P5="",P8=""),"",P8/P5) -> -0.44257967
D17: Cash and cash equivale… | F17: 18804000 | G17: 15750000 | H17: 35893000 | I17: 31624000 | J17: 57547000 | L17: 27927000 | M17: 28074000 | N17: 25451000 | O17: 20268000 | P17: 35893000 | S17: P / S | V17: =V5/(Q5/Q13) -> 0.20273081 | X17: Income Statement | AC17: Net Income | AE17: =IF(L9="","",L9) -> 4248000 | AF17: =IF(M9="","",M9) -> 18505000 | AG17: =IF(N9="","",N9) -> -345000 | AH17: =IF(O9="","",O9) -> -11113000 | AI17: =IF(P9="","",P9) -> 28381000
D18: Total cash | F18: 18804000 | G18: 18173000 | H18: 42763000 | I18: 37908000 | J18: 65514000 | L18: 27927000 | M18: 28074000 | N18: 25451000 | O18: 20268000 | P18: 42763000 | S18: P / CFO | V18: =IF(AVERAGE(N28:P28)>0,V5/(AVERAGE(N28:P28)/Q13),"") | X18: Revenue | AA18: =Q5 -> 250000000 | AC18: Earnings Per Share | AE18: =IF(L10="","",L10) -> 0.49 | AF18: =IF(M10="","",M10) -> 2.08 | AG18: =IF(N10="","",N10) -> -0.04 | AH18: =IF(O10="","",O10) -> -1.21 | AI18: =IF(P10="","",P10) -> 3.07
D19: Total current assets | F19: 29921000 | G19: 31911000 | H19: 54924000 | I19: 50227000 | J19: 69750000 | L19: 43796000 | M19: 44963000 | N19: 41213000 | O19: 39928000 | P19: 54924000 | S19: P / FCF | V19: =IF(AVERAGE(N30:P30)>0,V6/AVERAGE(N30:P30),"") | X19: Gross Profit | AA19: =Q7 -> 0 | AC19: Shares | AE19: =IF(L13="","",L13) -> 8736000 | AF19: =IF(M13="","",M13) -> 8911000 | AG19: =IF(N13="","",N13) -> 9067697 | AH19: =IF(O13="","",O13) -> 9154437 | AI19: =IF(P13="","",P13) -> 9252275
D20: Total assets | F20: 34785000 | G20: 36347000 | H20: 57807000 | I20: 53132000 | J20: 71596000 | L20: 48469000 | M20: 62386000 | N20: 57873000 | O20: 45236000 | P20: 57807000 | S20: EV / EBITDA | V20: =(V6+(J21+J23)-J17)/J14 -> 1.9163311 | X20: Net Income | AA20: =Q9 -> 50275000 | AC20: Book Value Per Share | AE20: =IF(OR(L25="",L13="",L20="",L24=""),"",(L20-L24)/L13) -> 2.9515797 | AF20: =IF(OR(M25="",M13="",M20="",M24=""),"",(M20-M24)/M13) -> 4.5397823 | AG20: =IF(OR(N25="",N13="",N20="",N24=""),"",(N20-N24)/N13) -> 4.0369677 | AH20: =IF(OR(O25="",O13="",O20="",O24=""),"",(O20-O24)/O13) -> 2.2937511 | AI20: =IF(OR(P25="",P13="",P20="",P24=""),"",(P20-P24)/P13) -> 4.6981958
D21: Short-term debt | X21: Earnings Per Share | AA21: =Q10 -> 5.4
D22: Total current liabilities | F22: 12513000 | G22: 16619000 | H22: 9618000 | I22: 6946000 | J22: 4829000 | L22: 16054000 | M22: 15032000 | N22: 14704000 | O22: 17317000 | P22: 9618000 | AC22: Profitability | AE22: =L4 -> 2013 | AF22: =M4 -> 2014 | AG22: =N4 -> 2015 | AH22: =O4 -> 2016 | AI22: =P4 -> 2017
D23: Long-term debt | S23: Profitability | X23: Balance Sheet | AC23: Net Margin % | AE23: =IF(OR(L5="",L9="",L5=0,L9=0),"",L9/L5) -> 0.066956686 | AF23: =IF(OR(M5="",M9="",M5=0,M9=0),"",M9/M5) -> 0.26000759 | AG23: =IF(OR(N5="",N9="",N5=0,N9=0),"",N9/N5) -> -0.0053522394 | AH23: =IF(OR(O5="",O9="",O5=0,O9=0),"",O9/O5) -> -0.18173641 | AI23: =IF(OR(P5="",P9="",P5=0,P9=0),"",P9/P5) -> 1.026549
D24: Total liabilities | F24: 18780000 | G24: 22978000 | H24: 14338000 | I24: 11669000 | J24: 9479000 | L24: 22684000 | M24: 21932000 | N24: 21267000 | O24: 24238000 | P24: 14338000 | S24: Sales | V24: =Q5 -> 250000000 | X24: Total Cash | AA24: =J18 -> 65514000 | AC24: Return on Equity % | AE24: =IF(OR(L9="",L23="",L9=0,L23=0),"",L9/L23) | AF24: =IF(OR(M9="",M23="",M9=0,M23=0),"",M9/M23) | AG24: =IF(OR(N9="",N23="",N9=0,N23=0),"",N9/N23) | AH24: =IF(OR(O9="",O23="",O9=0,O23=0),"",O9/O23) | AI24: =IF(OR(P9="",P23="",P9=0,P23=0),"",P9/P23)
D25: Total stockholders' eq… | F25: 16005000 | G25: 13369000 | H25: 43469000 | I25: 41463000 | J25: 62117000 | L25: 25785000 | M25: 40454000 | N25: 36606000 | O25: 20998000 | P25: 43469000 | S25: Gross Margin | V25: =(Q5-Q6)/Q5 -> 1 | X25: Current Assets | AA25: =J19 -> 69750000 | AC25: Return on Assets % | AE25: =IF(OR(L9="",L20="",L9=0,L20=0),"",L9/L20) -> 0.087643649 | AF25: =IF(OR(M9="",M20="",M9=0,M20=0),"",M9/M20) -> 0.29662104 | AG25: =IF(OR(N9="",N20="",N9=0,N20=0),"",N9/N20) -> -0.0059613291 | AH25: =IF(OR(O9="",O20="",O9=0,O20=0),"",O9/O20) -> -0.24566717 | AI25: =IF(OR(P9="",P20="",P9=0,P20=0),"",P9/P20) -> 0.4909613
S26: Net Margin | V26: =Q9/Q5 -> 0.2011 | X26: Current Liabilities | AA26: =J22 -> 4829000 | AC26: Asset Turnover | AE26: =IF(OR(L5="",L20="",L5=0,L20=0),"",L5/L20) -> 1.3089604 | AF26: =IF(OR(M5="",M20="",M5=0,M20=0),"",M5/M20) -> 1.1408168 | AG26: =IF(OR(N5="",N20="",N5=0,N20=0),"",N5/N20) -> 1.1138009 | AH26: =IF(OR(O5="",O20="",O5=0,O20=0),"",O5/O20) -> 1.3517773 | AI26: =IF(OR(P5="",P20="",P5=0,P20=0),"",P5/P20) -> 0.47826388
D27: Cash Flow | F27: =F4 -> 2016-10 | G27: =G4 -> 2017-01 | H27: =H4 -> 2017-04 | I27: =I4 -> 2017-07 | J27: =J4 -> 2017-10 | L27: =L4 -> 2013 | M27: =M4 -> 2014 | N27: =N4 -> 2015 | O27: =O4 -> 2016 | P27: =P4 -> 2017 | Q27: TTM | S27: Operating Margin | V27: =Q8/Q5 -> -0.119164 | X27: Total Debt | AA27: =J21+J23 -> 0
D28: Operating cash flow | F28: 1134000 | G28: 622000 | H28: -5190000 | I28: -3505000 | J28: -113000 | L28: 4924000 | M28: 6768000 | N28: 3544000 | O28: -2221000 | P28: -3004000 | Q28: -8186000 | AC28: Financial Health | AE28: =L4 -> 2013 | AF28: =M4 -> 2014 | AG28: =N4 -> 2015 | AH28: =O4 -> 2016 | AI28: =P4 -> 2017
D29: Capital expenditure | F29: -190000 | G29: -182000 | H29: -193000 | I29: -222000 | J29: -53000 | L29: -1447000 | M29: -1900000 | N29: -1949000 | O29: -2286000 | P29: -912000 | Q29: -650000 | S29: Effectiveness | X29: Cash Flow Statement | AC29: Current Ratio | AE29: =IF(OR(L19="",L22="",L19=0,L22=0),"",L19/L22) -> 2.7280429 | AF29: =IF(OR(M19="",M22="",M19=0,M22=0),"",M19/M22) -> 2.9911522 | AG29: =IF(OR(N19="",N22="",N19=0,N22=0),"",N19/N22) -> 2.8028428 | AH29: =IF(OR(O19="",O22="",O19=0,O22=0),"",O19/O22) -> 2.3057112 | AI29: =IF(OR(P19="",P22="",P19=0,P22=0),"",P19/P22) -> 5.7105427
D30: Free cash flow | F30: 944000 | G30: 440000 | H30: -5383000 | I30: -3727000 | J30: -166000 | L30: 3477000 | M30: 4868000 | N30: 1595000 | O30: -4507000 | P30: -3916000 | Q30: -8836000 | S30: Return on Equity | V30: =Q9/AVERAGE(G25:J25) -> 1.2536 | X30: Operating Cash Flow | AA30: =AVERAGE(N28:P28) -> -560333.33 | AC30: Financial Leverage | AE30: =IF(OR(L20="",L23="",L20=0,L23=0),"",L20/L23) | AF30: =IF(OR(M20="",M23="",M20=0,M23=0),"",M20/M23) | AG30: =IF(OR(N20="",N23="",N20=0,N23=0),"",N20/N23) | AH30: =IF(OR(O20="",O23="",O20=0,O23=0),"",O20/O23) | AI30: =IF(OR(P20="",P23="",P20=0,P23=0),"",P20/P23)
S31: Return on Assets | V31: =Q9/AVERAGE(G20:J20) -> 0.91875988 | X31: Capital Expenditure | AA31: =ABS(AVERAGE(N29:P29)) -> 1715666.7 | AC31: Debt / Equity | AE31: =IF(OR(L25="",L23="",L23=0,L25=0),"",L25/L23) | AF31: =IF(OR(M25="",M23="",M23=0,M25=0),"",M25/M23) | AG31: =IF(OR(N25="",N23="",N23=0,N25=0),"",N25/N23) | AH31: =IF(OR(O25="",O23="",O23=0,O25=0),"",O25/O23) | AI31: =IF(OR(P25="",P23="",P23=0,P25=0),"",P25/P23)
S32: Return on Capital Employed | V32: =Q8/(AVERAGE(G25:J25)+(AVERAGE(G20:J20)-AVERAGE(G22:J22))) -> -0.34915965 | X32: Free Cash Flow | AA32: =AVERAGE(N30:P30) -> -2276000
S33: Asset Turnover | V33: =Q5/AVERAGE(G20:J20) -> 4.5686717
A36: 2 | S36: Symbol | T36: CRAY | V36: USD
D38: Income Statement | F38: 2016-10 | G38: 2017-01 | H38: 2017-04 | I38: 2017-07 | J38: 2017-10 | L38: 2013 | M38: 2014 | N38: 2015 | O38: 2016 | P38: 2017 | Q38: TTM | S38: Quote | X38: Growth | AA38: 5-Year Average | AC38: Key Ratios ― Growth, YOY | AF38: =M38 -> 2014 | AG38: =N38 -> 2015 | AH38: =O38 -> 2016 | AI38: =P38 -> 2017
D39: Revenue | F39: 346574000 | G39: 59031000 | H39: 87135000 | I39: 79700000 | J39: 166643000 | L39: 525749000 | M39: 561606000 | N39: 724689000 | O39: 629809000 | P39: 392509000 | Q39: 392509000 | S39: Last Price | V39: 21.25 | X39: Revenue | AA39: =IF(AA38="Year over Year",AI39,IF(AA38="3-Year Average",AVERAGE(AH39:AI39),IF(AA38="5-Year Average",AVERAGE(AF39:AI39),""))) -> -0.037279356 | AC39: Revenue % | AF39: =IF(AND(M39>0,L39>0,L39<>""),M39/L39-1,IF(AND(L39<0,M39<0,L39<>""),(M39-L39)/ABS(L39),IF(AND(L39>0,M39<0,L39<>""),"L",IF(AND(L39<0,M39>0,L39<>""),"P","")))) -> 0.068201746 | AG39: =IF(AND(N39>0,M39>0,M39<>""),N39/M39-1,IF(AND(M39<0,N39<0,M39<>""),(N39-M39)/ABS(M39),IF(AND(M39>0,N39<0,M39<>""),"L",IF(AND(M39<0,N39>0,M39<>""),"P","")))) -> 0.29038685 | AH39: =IF(AND(O39>0,N39>0,N39<>""),O39/N39-1,IF(AND(N39<0,O39<0,N39<>""),(O39-N39)/ABS(N39),IF(AND(N39>0,O39<0,N39<>""),"L",IF(AND(N39<0,O39>0,N39<>""),"P","")))) -> -0.13092513 | AI39: =IF(AND(P39>0,O39>0,O39<>""),P39/O39-1,IF(AND(O39<0,P39<0,O39<>""),(P39-O39)/ABS(O39),IF(AND(O39>0,P39<0,O39<>""),"L",IF(AND(O39<0,P39>0,O39<>""),"P","")))) -> -0.3767809
D40: Cost of revenue | F40: 226083000 | G40: 35222000 | H40: 58792000 | I40: 51208000 | J40: 116583000 | L40: 341423000 | M40: 377192000 | N40: 499006000 | O40: 409594000 | P40: 261805000 | Q40: 261805000 | S40: Market Capitalization | V40: =V39*Q47 -> 852953750 | X40: Operating Income | AA40: =IF(AA38="Year over Year",AI40,IF(AA38="3-Year Average",AVERAGE(AH40:AI40),IF(AA38="5-Year Average",AVERAGE(AF40:AI40),""))) -> 0.70159316 | AC40: Operating Income % | AF40: =IF(AND(M42>0,L42>0,L42<>""),M42/L42-1,IF(AND(L42<0,M42<0,L42<>""),(M42-L42)/ABS(L42),IF(AND(L42>0,M42<0,L42<>""),"L",IF(AND(L42<0,M42>0,L42<>""),"P","")))) -> -0.57505774 | AG40: =IF(AND(N42>0,M42>0,M42<>""),N42/M42-1,IF(AND(M42<0,N42<0,M42<>""),(N42-M42)/ABS(M42),IF(AND(M42>0,N42<0,M42<>""),"L",IF(AND(M42<0,N42>0,M42<>""),"P","")))) -> 3.4569565 | AH40: =IF(AND(O42>0,N42>0,N42<>""),O42/N42-1,IF(AND(N42<0,O42<0,N42<>""),(O42-N42)/ABS(N42),IF(AND(N42>0,O42<0,N42<>""),"L",IF(AND(N42<0,O42>0,N42<>""),"P","")))) -> -0.77711931 | AI40: =IF(AND(P42>0,O42>0,O42<>""),P42/O42-1,IF(AND(O42<0,P42<0,O42<>""),(P42-O42)/ABS(O42),IF(AND(O42>0,P42<0,O42<>""),"L",IF(AND(O42<0,P42>0,O42<>""),"P","")))) -> L
D41: Gross profit | F41: 120491000 | G41: 23809000 | H41: 28343000 | I41: 28492000 | J41: 50060000 | L41: 184326000 | M41: 184414000 | N41: 225683000 | O41: 220215000 | P41: 130704000 | Q41: 130704000 | S41: Enterprise Value | V41: =V40+(J55+J57)-J51 -> 715627750 | X41: Net Income | AA41: =IF(AA38="Year over Year",AI41,IF(AA38="3-Year Average",AVERAGE(AH41:AI41),IF(AA38="5-Year Average",AVERAGE(AF41:AI41),""))) -> -0.079519988 | AC41: Net Income % | AF41: =IF(AND(M43>0,L43>0,L43<>""),M43/L43-1,IF(AND(L43<0,M43<0,L43<>""),(M43-L43)/ABS(L43),IF(AND(L43>0,M43<0,L43<>""),"L",IF(AND(L43<0,M43>0,L43<>""),"P","")))) -> 0.93411538 | AG41: =IF(AND(N43>0,M43>0,M43<>""),N43/M43-1,IF(AND(M43<0,N43<0,M43<>""),(N43-M43)/ABS(M43),IF(AND(M43>0,N43<0,M43<>""),"L",IF(AND(M43<0,N43>0,M43<>""),"P","")))) -> -0.5581567 | AH41: =IF(AND(O43>0,N43>0,N43<>""),O43/N43-1,IF(AND(N43<0,O43<0,N43<>""),(O43-N43)/ABS(N43),IF(AND(N43>0,O43<0,N43<>""),"L",IF(AND(N43<0,O43>0,N43<>""),"P","")))) -> -0.61451865 | AI41: =IF(AND(P43>0,O43>0,O43<>""),P43/O43-1,IF(AND(O43<0,P43<0,O43<>""),(P43-O43)/ABS(O43),IF(AND(O43>0,P43<0,O43<>""),"L",IF(AND(O43<0,P43>0,O43<>""),"P","")))) -> L
D42: Operating income | F42: 62454000 | G42: -32281000 | H42: -11434000 | I42: -26201000 | J42: 4268000 | L42: 21650000 | M42: 9200000 | N42: 41004000 | O42: 9139000 | P42: -65648000 | Q42: -65648000 | S42: Book Value | V42: =J54-J58 -> 400297000 | X42: Earnings Per Share | AA42: =IF(AA38="Year over Year",AI42,IF(AA38="3-Year Average",AVERAGE(AH42:AI42),IF(AA38="5-Year Average",AVERAGE(AF42:AI42),""))) -> -0.095128486 | AC42: Earnings per share % | AF42: =IF(AND(M44>0,L44>0,L44<>""),M44/L44-1,IF(AND(L44<0,M44<0,L44<>""),(M44-L44)/ABS(L44),IF(AND(L44>0,M44<0,L44<>""),"L",IF(AND(L44<0,M44>0,L44<>""),"P","")))) -> 0.89411765 | AG42: =IF(AND(N44>0,M44>0,M44<>""),N44/M44-1,IF(AND(M44<0,N44<0,M44<>""),(N44-M44)/ABS(M44),IF(AND(M44>0,N44<0,M44<>""),"L",IF(AND(M44<0,N44>0,M44<>""),"P","")))) -> -0.56521739 | AH42: =IF(AND(O44>0,N44>0,N44<>""),O44/N44-1,IF(AND(N44<0,O44<0,N44<>""),(O44-N44)/ABS(N44),IF(AND(N44>0,O44<0,N44<>""),"L",IF(AND(N44<0,O44>0,N44<>""),"P","")))) -> -0.61428571 | AI42: =IF(AND(P44>0,O44>0,O44<>""),P44/O44-1,IF(AND(O44<0,P44<0,O44<>""),(P44-O44)/ABS(O44),IF(AND(O44>0,P44<0,O44<>""),"L",IF(AND(O44<0,P44>0,O44<>""),"P","")))) -> L
D43: Net income | F43: 51775000 | G43: -19215000 | H43: -6840000 | I43: -10232000 | J43: -97542000 | L43: 32223000 | M43: 62323000 | N43: 27537000 | O43: 10615000 | P43: -133829000 | Q43: -133829000 | S43: Type | V43: =IF(V40>10000,"Large Cap",IF(AND(10000>V40,2000<V40),"Mid Cap",IF(AND(2000>V40,V40>50),"Small Cap",IF(V40<50,"Micro Cap",NA)))) -> Large Cap
D44: Earnings per share | F44: 1.3 | G44: -0.48 | H44: -0.17 | I44: -0.25 | J44: -2.42 | L44: 0.85 | M44: 1.61 | N44: 0.7 | O44: 0.27 | P44: -3.33 | Q44: -3.33 | S44: Dividend Yield | X44: Financial Health | AC44: Financials | AE44: =L38 -> 2013 | AF44: =M38 -> 2014 | AG44: =N38 -> 2015 | AH44: =O38 -> 2016 | AI44: =P38 -> 2017
F45: 39974000 | G45: 39994000 | H45: 40051000 | I45: 40199000 | J45: 40310000 | L45: 37832000 | M45: 38634000 | N45: 39257000 | O45: 39833000 | P45: 40139000 | Q45: 40139000
F46: 1.3 | G46: -0.48 | H46: -0.17 | I46: -0.25 | J46: -2.42 | L46: 0.85 | M46: 1.61 | N46: 0.7 | O46: 0.27 | P46: -3.33 | Q46: -3.33
D47: Weighted average share… | F47: 39974000 | G47: 39994000 | H47: 40051000 | I47: 40199000 | J47: 40310000 | L47: 37832000 | M47: 38634000 | N47: 39257000 | O47: 39833000 | P47: 40139000 | Q47: 40139000 | X47: Current Ratio | AA47: =AVERAGE(G53:J53)/AVERAGE(G56:J56) -> 3.4293805 | AC47: Revenue | AE47: =IF(L39="","",L39) -> 525749000 | AF47: =IF(M39="","",M39) -> 561606000 | AG47: =IF(N39="","",N39) -> 724689000 | AH47: =IF(O39="","",O39) -> 629809000 | AI47: =IF(P39="","",P39) -> 392509000
D48: EBITDA | F48: 66342000 | G48: -26573000 | H48: -6260000 | I48: -12469000 | J48: 9283000 | L48: 35408000 | M48: 26158000 | N48: 59851000 | O48: 24632000 | P48: -36020000 | Q48: -36020000 | S48: Valuation | X48: Financial Leverage | AA48: =AVERAGE(G54:J54)/AVERAGE(G59:J59) -> 1.3927086 | AC48: Gross Margin % | AE48: =IF(OR(L39="",L41=""),"",L41/L39) -> 0.35059696 | AF48: =IF(OR(M39="",M41=""),"",M41/M39) -> 0.328369 | AG48: =IF(OR(N39="",N41=""),"",N41/N39) -> 0.31142049 | AH48: =IF(OR(O39="",O41=""),"",O41/O39) -> 0.34965363 | AI48: =IF(OR(P39="",P41=""),"",P41/P39) -> 0.33299619
S49: P / E | V49: =IF(Q44>0,V39/Q44,"") | X49: Debt / Equity | AA49: =AVERAGE(G57:J57)/AVERAGE(G59:J59) -> #DIV/0! | AC49: Operating Income | AE49: =IF(L42="","",L42) -> 21650000 | AF49: =IF(M42="","",M42) -> 9200000 | AG49: =IF(N42="","",N42) -> 41004000 | AH49: =IF(O42="","",O42) -> 9139000 | AI49: =IF(P42="","",P42) -> -65648000
D50: Balance Sheet | F50: =F38 -> 2016-10 | G50: =G38 -> 2017-01 | H50: =H38 -> 2017-04 | I50: =I38 -> 2017-07 | J50: =J38 -> 2017-10 | L50: =L38 -> 2013 | M50: =M38 -> 2014 | N50: =N38 -> 2015 | O50: =O38 -> 2016 | P50: =P38 -> 2017 | S50: P / B | V50: =V39/((J54-J58)/J47) -> 2.1398799 | AC50: Operating Margin % | AE50: =IF(OR(L39="",L42=""),"",L42/L39) -> 0.041179346 | AF50: =IF(OR(M39="",M42=""),"",M42/M39) -> 0.016381591 | AG50: =IF(OR(N39="",N42=""),"",N42/N39) -> 0.056581513 | AH50: =IF(OR(O39="",O42=""),"",O42/O39) -> 0.014510748 | AI50: =IF(OR(P39="",P42=""),"",P42/P39) -> -0.16725222
D51: Cash and cash equivale… | F51: 222962000 | G51: 198320000 | H51: 170950000 | I51: 151886000 | J51: 137326000 | L51: 192633000 | M51: 112633000 | N51: 266660000 | O51: 222962000 | P51: 137326000 | S51: P / S | V51: =V39/(Q39/Q47) -> 2.1730807 | X51: Income Statement | AC51: Net Income | AE51: =IF(L43="","",L43) -> 32223000 | AF51: =IF(M43="","",M43) -> 62323000 | AG51: =IF(N43="","",N43) -> 27537000 | AH51: =IF(O43="","",O43) -> 10615000 | AI51: =IF(P43="","",P43) -> -133829000
D52: Total cash | F52: 222962000 | G52: 283133000 | H52: 250783000 | I52: 179812000 | J52: 144323000 | L52: 206681000 | M52: 128922000 | N52: 281585000 | O52: 222962000 | P52: 144323000 | S52: P / CFO | V52: =IF(AVERAGE(N62:P62)>0,V39/(AVERAGE(N62:P62)/Q47),"") -> 115.7751 | X52: Revenue | AA52: =Q39 -> 392509000 | AC52: Earnings Per Share | AE52: =IF(L44="","",L44) -> 0.85 | AF52: =IF(M44="","",M44) -> 1.61 | AG52: =IF(N44="","",N44) -> 0.7 | AH52: =IF(O44="","",O44) -> 0.27 | AI52: =IF(P44="","",P44) -> -3.33
D53: Total current assets | F53: 548280000 | G53: 468375000 | H53: 501485000 | I53: 463224000 | J53: 519643000 | L53: 505336000 | M53: 508562000 | N53: 581286000 | O53: 548280000 | P53: 519643000 | S53: P / FCF | V53: =IF(AVERAGE(N64:P64)>0,V40/AVERAGE(N64:P64),"") | X53: Gross Profit | AA53: =Q41 -> 130704000 | AC53: Shares | AE53: =IF(L47="","",L47) -> 37832000 | AF53: =IF(M47="","",M47) -> 38634000 | AG53: =IF(N47="","",N47) -> 39257000 | AH53: =IF(O47="","",O47) -> 39833000 | AI53: =IF(P47="","",P47) -> 40139000
D54: Total assets | F54: 714572000 | G54: 668684000 | H54: 700750000 | I54: 667065000 | J54: 618757000 | L54: 603366000 | M54: 651434000 | N54: 694175000 | O54: 714572000 | P54: 618757000 | S54: EV / EBITDA | V54: =(V40+(J55+J57)-J51)/J48 -> 77.090138 | X54: Net Income | AA54: =Q43 -> -133829000 | AC54: Book Value Per Share | AE54: =IF(OR(L59="",L47="",L54="",L58=""),"",(L54-L58)/L47) -> 9.9277596 | AF54: =IF(OR(M59="",M47="",M54="",M58=""),"",(M54-M58)/M47) -> 11.747528 | AG54: =IF(OR(N59="",N47="",N54="",N58=""),"",(N54-N58)/N47) -> 12.545788 | AH54: =IF(OR(O59="",O47="",O54="",O58=""),"",(O54-O58)/O47) -> 13.191977 | AI54: =IF(OR(P59="",P47="",P54="",P58=""),"",(P54-P58)/P47) -> 9.9727696
D55: Short-term debt | S55: EV / S | V55: =(V40+(J55+J57)-J51)/J39 -> 4.2943763 | X55: Earnings Per Share | AA55: =Q44 -> -3.33
D56: Total current liabilities | F56: 156135000 | G56: 118661000 | H56: 159025000 | I56: 126382000 | J56: 165343000 | L56: 170408000 | M56: 146948000 | N56: 166099000 | O56: 156135000 | P56: 165343000 | AC56: Profitability | AE56: =L38 -> 2013 | AF56: =M38 -> 2014 | AG56: =N38 -> 2015 | AH56: =O38 -> 2016 | AI56: =P38 -> 2017
D57: Long-term debt | S57: Profitability | X57: Balance Sheet | AC57: Net Margin % | AE57: =IF(OR(L39="",L43="",L39=0,L43=0),"",L43/L39) -> 0.061289703 | AF57: =IF(OR(M39="",M43="",M39=0,M43=0),"",M43/M39) -> 0.11097282 | AG57: =IF(OR(N39="",N43="",N39=0,N43=0),"",N43/N39) -> 0.037998369 | AH57: =IF(OR(O39="",O43="",O39=0,O43=0),"",O43/O39) -> 0.016854316 | AI57: =IF(OR(P39="",P43="",P39=0,P43=0),"",P43/P39) -> -0.34095779
D58: Total liabilities | F58: 189096000 | G58: 159511000 | H58: 197933000 | I58: 172811000 | J58: 218460000 | L58: 227779000 | M58: 197580000 | N58: 201665000 | O58: 189096000 | P58: 218460000 | S58: Sales | V58: =Q39 -> 392509000 | X58: Total Cash | AA58: =J52 -> 144323000 | AC58: Return on Equity % | AE58: =IF(OR(L43="",L57="",L43=0,L57=0),"",L43/L57) | AF58: =IF(OR(M43="",M57="",M43=0,M57=0),"",M43/M57) | AG58: =IF(OR(N43="",N57="",N43=0,N57=0),"",N43/N57) | AH58: =IF(OR(O43="",O57="",O43=0,O57=0),"",O43/O57) | AI58: =IF(OR(P43="",P57="",P43=0,P57=0),"",P43/P57)
D59: Total stockholders' eq… | F59: 525476000 | G59: 509173000 | H59: 502817000 | I59: 494254000 | J59: 400297000 | L59: 375587000 | M59: 453854000 | N59: 492510000 | O59: 525476000 | P59: 400297000 | S59: Gross Margin | V59: =(Q39-Q40)/Q39 -> 0.33299619 | X59: Current Assets | AA59: =J53 -> 519643000 | AC59: Return on Assets % | AE59: =IF(OR(L43="",L54="",L43=0,L54=0),"",L43/L54) -> 0.053405396 | AF59: =IF(OR(M43="",M54="",M43=0,M54=0),"",M43/M54) -> 0.095670475 | AG59: =IF(OR(N43="",N54="",N43=0,N54=0),"",N43/N54) -> 0.039668671 | AH59: =IF(OR(O43="",O54="",O43=0,O54=0),"",O43/O54) -> 0.014855046 | AI59: =IF(OR(P43="",P54="",P43=0,P54=0),"",P43/P54) -> -0.21628685
S60: Net Margin | V60: =Q43/Q39 -> -0.34095779 | X60: Current Liabilities | AA60: =J56 -> 165343000 | AC60: Asset Turnover | AE60: =IF(OR(L39="",L54="",L39=0,L54=0),"",L39/L54) -> 0.87136 | AF60: =IF(OR(M39="",M54="",M39=0,M54=0),"",M39/M54) -> 0.86210729 | AG60: =IF(OR(N39="",N54="",N39=0,N54=0),"",N39/N54) -> 1.0439572 | AH60: =IF(OR(O39="",O54="",O39=0,O54=0),"",O39/O54) -> 0.88137934 | AI60: =IF(OR(P39="",P54="",P39=0,P54=0),"",P39/P54) -> 0.6343508
D61: Cash Flow | F61: =F38 -> 2016-10 | G61: =G38 -> 2017-01 | H61: =H38 -> 2017-04 | I61: =I38 -> 2017-07 | J61: =J38 -> 2017-10 | L61: =L38 -> 2013 | M61: =M38 -> 2014 | N61: =N38 -> 2015 | O61: =O38 -> 2016 | P61: =P38 -> 2017 | Q61: TTM | S61: Operating Margin | V61: =Q42/Q39 -> -0.16725222 | X61: Total Debt | AA61: =J55+J57 -> 0
D62: Operating cash flow | F62: 81176000 | G62: 69922000 | H62: -28264000 | I62: -80342000 | J62: -34657000 | L62: -87350000 | M62: -58109000 | N62: 147756000 | O62: -52313000 | P62: -73341000 | Q62: -73341000 | AC62: Financial Health | AE62: =L38 -> 2013 | AF62: =M38 -> 2014 | AG62: =N38 -> 2015 | AH62: =O38 -> 2016 | AI62: =P38 -> 2017
D63: Capital expenditure | F63: -3695000 | G63: -10289000 | H63: -3299000 | I63: -2059000 | J63: -1820000 | L63: -13136000 | M63: -17193000 | N63: -7467000 | O63: -7503000 | P63: -17467000 | Q63: -17467000 | S63: Effectiveness | X63: Cash Flow Statement | AC63: Current Ratio | AE63: =IF(OR(L53="",L56="",L53=0,L56=0),"",L53/L56) -> 2.9654476 | AF63: =IF(OR(M53="",M56="",M53=0,M56=0),"",M53/M56) -> 3.4608297 | AG63: =IF(OR(N53="",N56="",N53=0,N56=0),"",N53/N56) -> 3.4996358 | AH63: =IF(OR(O53="",O56="",O53=0,O56=0),"",O53/O56) -> 3.5115765 | AI63: =IF(OR(P53="",P56="",P53=0,P56=0),"",P53/P56) -> 3.1428183
D64: Free cash flow | F64: 77481000 | G64: 59633000 | H64: -31563000 | I64: -82401000 | J64: -36477000 | L64: -100486000 | M64: -75302000 | N64: 140289000 | O64: -59816000 | P64: -90808000 | Q64: -90808000 | S64: Return on Equity | V64: =Q43/AVERAGE(G59:J59) -> -0.28077865 | X64: Operating Cash Flow | AA64: =AVERAGE(N62:P62) -> 7367333.3 | AC64: Financial Leverage | AE64: =IF(OR(L54="",L57="",L54=0,L57=0),"",L54/L57) | AF64: =IF(OR(M54="",M57="",M54=0,M57=0),"",M54/M57) | AG64: =IF(OR(N54="",N57="",N54=0,N57=0),"",N54/N57) | AH64: =IF(OR(O54="",O57="",O54=0,O57=0),"",O54/O57) | AI64: =IF(OR(P54="",P57="",P54=0,P57=0),"",P54/P57)
S65: Return on Assets | V65: =Q43/AVERAGE(G54:J54) -> -0.20160617 | X65: Capital Expenditure | AA65: =ABS(AVERAGE(N63:P63)) -> 10812333 | AC65: Debt / Equity | AE65: =IF(OR(L59="",L57="",L57=0,L59=0),"",L59/L57) | AF65: =IF(OR(M59="",M57="",M57=0,M59=0),"",M59/M57) | AG65: =IF(OR(N59="",N57="",N57=0,N59=0),"",N59/N57) | AH65: =IF(OR(O59="",O57="",O57=0,O59=0),"",O59/O57) | AI65: =IF(OR(P59="",P57="",P57=0,P59=0),"",P59/P57)
S66: Return on Capital Employed | V66: =Q42/(AVERAGE(G59:J59)+(AVERAGE(G54:J54)-AVERAGE(G56:J56))) -> -0.065773199 | X66: Free Cash Flow | AA66: =AVERAGE(N64:P64) -> -3445000
S67: Asset Turnover | V67: =Q39/AVERAGE(G54:J54) -> 0.59129365
A70: 3 | S70: Symbol | T70: ADI | V70: USD
D72: Income Statement | F72: 2016-10 | G72: 2017-01 | H72: 2017-04 | I72: 2017-07 | J72: 2017-10 | L72: 2013 | M72: 2014 | N72: 2015 | O72: 2016 | P72: 2017 | Q72: TTM | S72: Quote | X72: Growth | AA72: 5-Year Average | AC72: Key Ratios ― Growth, YOY | AF72: =M72 -> 2014 | AG72: =N72 -> 2015 | AH72: =O72 -> 2016 | AI72: =P72 -> 2017
D73: Revenue | S73: Last Price | V73: 88.54 | X73: Revenue | AA73: =IF(AA72="Year over Year",AI73,IF(AA72="3-Year Average",AVERAGE(AH73:AI73),IF(AA72="5-Year Average",AVERAGE(AF73:AI73),""))) -> #DIV/0! | AC73: Revenue % | AF73: =IF(AND(M73>0,L73>0,L73<>""),M73/L73-1,IF(AND(L73<0,M73<0,L73<>""),(M73-L73)/ABS(L73),IF(AND(L73>0,M73<0,L73<>""),"L",IF(AND(L73<0,M73>0,L73<>""),"P","")))) | AG73: =IF(AND(N73>0,M73>0,M73<>""),N73/M73-1,IF(AND(M73<0,N73<0,M73<>""),(N73-M73)/ABS(M73),IF(AND(M73>0,N73<0,M73<>""),"L",IF(AND(M73<0,N73>0,M73<>""),"P","")))) | AH73: =IF(AND(O73>0,N73>0,N73<>""),O73/N73-1,IF(AND(N73<0,O73<0,N73<>""),(O73-N73)/ABS(N73),IF(AND(N73>0,O73<0,N73<>""),"L",IF(AND(N73<0,O73>0,N73<>""),"P","")))) | AI73: =IF(AND(P73>0,O73>0,O73<>""),P73/O73-1,IF(AND(O73<0,P73<0,O73<>""),(P73-O73)/ABS(O73),IF(AND(O73>0,P73<0,O73<>""),"L",IF(AND(O73<0,P73>0,O73<>""),"P",""))))
D74: Cost of revenue | S74: Market Capitalization | V74: =V73*Q81 -> 0 | X74: Operating Income | AA74: =IF(AA72="Year over Year",AI74,IF(AA72="3-Year Average",AVERAGE(AH74:AI74),IF(AA72="5-Year Average",AVERAGE(AF74:AI74),""))) -> #DIV/0! | AC74: Operating Income % | AF74: =IF(AND(M76>0,L76>0,L76<>""),M76/L76-1,IF(AND(L76<0,M76<0,L76<>""),(M76-L76)/ABS(L76),IF(AND(L76>0,M76<0,L76<>""),"L",IF(AND(L76<0,M76>0,L76<>""),"P","")))) | AG74: =IF(AND(N76>0,M76>0,M76<>""),N76/M76-1,IF(AND(M76<0,N76<0,M76<>""),(N76-M76)/ABS(M76),IF(AND(M76>0,N76<0,M76<>""),"L",IF(AND(M76<0,N76>0,M76<>""),"P","")))) | AH74: =IF(AND(O76>0,N76>0,N76<>""),O76/N76-1,IF(AND(N76<0,O76<0,N76<>""),(O76-N76)/ABS(N76),IF(AND(N76>0,O76<0,N76<>""),"L",IF(AND(N76<0,O76>0,N76<>""),"P","")))) | AI74: =IF(AND(P76>0,O76>0,O76<>""),P76/O76-1,IF(AND(O76<0,P76<0,O76<>""),(P76-O76)/ABS(O76),IF(AND(O76>0,P76<0,O76<>""),"L",IF(AND(O76<0,P76>0,O76<>""),"P",""))))
D75: Gross profit | S75: Enterprise Value | V75: =V74+(J89+J91)-J85 -> 0 | X75: Net Income | AA75: =IF(AA72="Year over Year",AI75,IF(AA72="3-Year Average",AVERAGE(AH75:AI75),IF(AA72="5-Year Average",AVERAGE(AF75:AI75),""))) -> #DIV/0! | AC75: Net Income % | AF75: =IF(AND(M77>0,L77>0,L77<>""),M77/L77-1,IF(AND(L77<0,M77<0,L77<>""),(M77-L77)/ABS(L77),IF(AND(L77>0,M77<0,L77<>""),"L",IF(AND(L77<0,M77>0,L77<>""),"P","")))) | AG75: =IF(AND(N77>0,M77>0,M77<>""),N77/M77-1,IF(AND(M77<0,N77<0,M77<>""),(N77-M77)/ABS(M77),IF(AND(M77>0,N77<0,M77<>""),"L",IF(AND(M77<0,N77>0,M77<>""),"P","")))) | AH75: =IF(AND(O77>0,N77>0,N77<>""),O77/N77-1,IF(AND(N77<0,O77<0,N77<>""),(O77-N77)/ABS(N77),IF(AND(N77>0,O77<0,N77<>""),"L",IF(AND(N77<0,O77>0,N77<>""),"P","")))) | AI75: =IF(AND(P77>0,O77>0,O77<>""),P77/O77-1,IF(AND(O77<0,P77<0,O77<>""),(P77-O77)/ABS(O77),IF(AND(O77>0,P77<0,O77<>""),"L",IF(AND(O77<0,P77>0,O77<>""),"P",""))))
D76: Operating income | S76: Book Value | V76: =J88-J92 -> 0 | X76: Earnings Per Share | AA76: =IF(AA72="Year over Year",AI76,IF(AA72="3-Year Average",AVERAGE(AH76:AI76),IF(AA72="5-Year Average",AVERAGE(AF76:AI76),""))) -> #DIV/0! | AC76: Earnings per share % | AF76: =IF(AND(M78>0,L78>0,L78<>""),M78/L78-1,IF(AND(L78<0,M78<0,L78<>""),(M78-L78)/ABS(L78),IF(AND(L78>0,M78<0,L78<>""),"L",IF(AND(L78<0,M78>0,L78<>""),"P","")))) | AG76: =IF(AND(N78>0,M78>0,M78<>""),N78/M78-1,IF(AND(M78<0,N78<0,M78<>""),(N78-M78)/ABS(M78),IF(AND(M78>0,N78<0,M78<>""),"L",IF(AND(M78<0,N78>0,M78<>""),"P","")))) | AH76: =IF(AND(O78>0,N78>0,N78<>""),O78/N78-1,IF(AND(N78<0,O78<0,N78<>""),(O78-N78)/ABS(N78),IF(AND(N78>0,O78<0,N78<>""),"L",IF(AND(N78<0,O78>0,N78<>""),"P","")))) | AI76: =IF(AND(P78>0,O78>0,O78<>""),P78/O78-1,IF(AND(O78<0,P78<0,O78<>""),(P78-O78)/ABS(O78),IF(AND(O78>0,P78<0,O78<>""),"L",IF(AND(O78<0,P78>0,O78<>""),"P",""))))
D77: Net income | S77: Type | V77: =IF(V74>10000,"Large Cap",IF(AND(10000>V74,2000<V74),"Mid Cap",IF(AND(2000>V74,V74>50),"Small Cap",IF(V74<50,"Micro Cap",NA)))) -> Micro Cap
D78: Earnings per share | S78: Dividend Yield | X78: Financial Health | AC78: Financials | AE78: =L72 -> 2013 | AF78: =M72 -> 2014 | AG78: =N72 -> 2015 | AH78: =O72 -> 2016 | AI78: =P72 -> 2017
D81: Weighted average share… | X81: Current Ratio | AA81: =AVERAGE(G87:J87)/AVERAGE(G90:J90) -> #DIV/0! | AC81: Revenue | AE81: =IF(L73="","",L73) | AF81: =IF(M73="","",M73) | AG81: =IF(N73="","",N73) | AH81: =IF(O73="","",O73) | AI81: =IF(P73="","",P73)
D82: EBITDA | S82: Valuation | X82: Financial Leverage | AA82: =AVERAGE(G88:J88)/AVERAGE(G93:J93) -> #DIV/0! | AC82: Gross Margin % | AE82: =IF(OR(L73="",L75=""),"",L75/L73) | AF82: =IF(OR(M73="",M75=""),"",M75/M73) | AG82: =IF(OR(N73="",N75=""),"",N75/N73) | AH82: =IF(OR(O73="",O75=""),"",O75/O73) | AI82: =IF(OR(P73="",P75=""),"",P75/P73)
S83: P / E | V83: =IF(Q78>0,V73/Q78,"") | X83: Debt / Equity | AA83: =AVERAGE(G91:J91)/AVERAGE(G93:J93) -> #DIV/0! | AC83: Operating Income | AE83: =IF(L76="","",L76) | AF83: =IF(M76="","",M76) | AG83: =IF(N76="","",N76) | AH83: =IF(O76="","",O76) | AI83: =IF(P76="","",P76)
D84: Balance Sheet | F84: =F72 -> 2016-10 | G84: =G72 -> 2017-01 | H84: =H72 -> 2017-04 | I84: =I72 -> 2017-07 | J84: =J72 -> 2017-10 | L84: =L72 -> 2013 | M84: =M72 -> 2014 | N84: =N72 -> 2015 | O84: =O72 -> 2016 | P84: =P72 -> 2017 | S84: P / B | V84: =V73/((J88-J92)/J81) -> #DIV/0! | AC84: Operating Margin % | AE84: =IF(OR(L73="",L76=""),"",L76/L73) | AF84: =IF(OR(M73="",M76=""),"",M76/M73) | AG84: =IF(OR(N73="",N76=""),"",N76/N73) | AH84: =IF(OR(O73="",O76=""),"",O76/O73) | AI84: =IF(OR(P73="",P76=""),"",P76/P73)
D85: Cash and cash equivale… | S85: P / S | V85: =V73/(Q73/Q81) -> #DIV/0! | X85: Income Statement | AC85: Net Income | AE85: =IF(L77="","",L77) | AF85: =IF(M77="","",M77) | AG85: =IF(N77="","",N77) | AH85: =IF(O77="","",O77) | AI85: =IF(P77="","",P77)
D86: Total cash | S86: P / CFO | V86: =IF(AVERAGE(N96:P96)>0,V73/(AVERAGE(N96:P96)/Q81),"") -> #DIV/0! | X86: Revenue | AA86: =Q73 -> 0 | AC86: Earnings Per Share | AE86: =IF(L78="","",L78) | AF86: =IF(M78="","",M78) | AG86: =IF(N78="","",N78) | AH86: =IF(O78="","",O78) | AI86: =IF(P78="","",P78)
D87: Total current assets | S87: P / FCF | V87: =IF(AVERAGE(N98:P98)>0,V74/AVERAGE(N98:P98),"") -> #DIV/0! | X87: Gross Profit | AA87: =Q75 -> 0 | AC87: Shares | AE87: =IF(L81="","",L81) | AF87: =IF(M81="","",M81) | AG87: =IF(N81="","",N81) | AH87: =IF(O81="","",O81) | AI87: =IF(P81="","",P81)
D88: Total assets | S88: EV / EBITDA | V88: =(V74+(J89+J91)-J85)/J82 -> #DIV/0! | X88: Net Income | AA88: =Q77 -> 0 | AC88: Book Value Per Share | AE88: =IF(OR(L93="",L81="",L88="",L92=""),"",(L88-L92)/L81) | AF88: =IF(OR(M93="",M81="",M88="",M92=""),"",(M88-M92)/M81) | AG88: =IF(OR(N93="",N81="",N88="",N92=""),"",(N88-N92)/N81) | AH88: =IF(OR(O93="",O81="",O88="",O92=""),"",(O88-O92)/O81) | AI88: =IF(OR(P93="",P81="",P88="",P92=""),"",(P88-P92)/P81)
D89: Short-term debt | S89: EV / S | V89: =(V74+(J89+J91)-J85)/J73 -> #DIV/0! | X89: Earnings Per Share | AA89: =Q78 -> 0
D90: Total current liabilities | AC90: Profitability | AE90: =L72 -> 2013 | AF90: =M72 -> 2014 | AG90: =N72 -> 2015 | AH90: =O72 -> 2016 | AI90: =P72 -> 2017
D91: Long-term debt | S91: Profitability | X91: Balance Sheet | AC91: Net Margin % | AE91: =IF(OR(L73="",L77="",L73=0,L77=0),"",L77/L73) | AF91: =IF(OR(M73="",M77="",M73=0,M77=0),"",M77/M73) | AG91: =IF(OR(N73="",N77="",N73=0,N77=0),"",N77/N73) | AH91: =IF(OR(O73="",O77="",O73=0,O77=0),"",O77/O73) | AI91: =IF(OR(P73="",P77="",P73=0,P77=0),"",P77/P73)
D92: Total liabilities | S92: Sales | V92: =Q73 -> 0 | X92: Total Cash | AA92: =J86 -> 0 | AC92: Return on Equity % | AE92: =IF(OR(L77="",L91="",L77=0,L91=0),"",L77/L91) | AF92: =IF(OR(M77="",M91="",M77=0,M91=0),"",M77/M91) | AG92: =IF(OR(N77="",N91="",N77=0,N91=0),"",N77/N91) | AH92: =IF(OR(O77="",O91="",O77=0,O91=0),"",O77/O91) | AI92: =IF(OR(P77="",P91="",P77=0,P91=0),"",P77/P91)
D93: Total stockholders' eq… | S93: Gross Margin | V93: =(Q73-Q74)/Q73 -> #DIV/0! | X93: Current Assets | AA93: =J87 -> 0 | AC93: Return on Assets % | AE93: =IF(OR(L77="",L88="",L77=0,L88=0),"",L77/L88) | AF93: =IF(OR(M77="",M88="",M77=0,M88=0),"",M77/M88) | AG93: =IF(OR(N77="",N88="",N77=0,N88=0),"",N77/N88) | AH93: =IF(OR(O77="",O88="",O77=0,O88=0),"",O77/O88) | AI93: =IF(OR(P77="",P88="",P77=0,P88=0),"",P77/P88)
S94: Net Margin | V94: =Q77/Q73 -> #DIV/0! | X94: Current Liabilities | AA94: =J90 -> 0 | AC94: Asset Turnover | AE94: =IF(OR(L73="",L88="",L73=0,L88=0),"",L73/L88) | AF94: =IF(OR(M73="",M88="",M73=0,M88=0),"",M73/M88) | AG94: =IF(OR(N73="",N88="",N73=0,N88=0),"",N73/N88) | AH94: =IF(OR(O73="",O88="",O73=0,O88=0),"",O73/O88) | AI94: =IF(OR(P73="",P88="",P73=0,P88=0),"",P73/P88)
D95: Cash Flow | F95: =F72 -> 2016-10 | G95: =G72 -> 2017-01 | H95: =H72 -> 2017-04 | I95: =I72 -> 2017-07 | J95: =J72 -> 2017-10 | L95: =L72 -> 2013 | M95: =M72 -> 2014 | N95: =N72 -> 2015 | O95: =O72 -> 2016 | P95: =P72 -> 2017 | Q95: TTM | S95: Operating Margin | V95: =Q76/Q73 -> #DIV/0! | X95: Total Debt | AA95: =J89+J91 -> 0
D96: Operating cash flow | AC96: Financial Health | AE96: =L72 -> 2013 | AF96: =M72 -> 2014 | AG96: =N72 -> 2015 | AH96: =O72 -> 2016 | AI96: =P72 -> 2017
D97: Capital expenditure | S97: Effectiveness | X97: Cash Flow Statement | AC97: Current Ratio | AE97: =IF(OR(L87="",L90="",L87=0,L90=0),"",L87/L90) | AF97: =IF(OR(M87="",M90="",M87=0,M90=0),"",M87/M90) | AG97: =IF(OR(N87="",N90="",N87=0,N90=0),"",N87/N90) | AH97: =IF(OR(O87="",O90="",O87=0,O90=0),"",O87/O90) | AI97: =IF(OR(P87="",P90="",P87=0,P90=0),"",P87/P90)
D98: Free cash flow | S98: Return on Equity | V98: =Q77/AVERAGE(G93:J93) -> #DIV/0! | X98: Operating Cash Flow | AA98: =AVERAGE(N96:P96) -> #DIV/0! | AC98: Financial Leverage | AE98: =IF(OR(L88="",L91="",L88=0,L91=0),"",L88/L91) | AF98: =IF(OR(M88="",M91="",M88=0,M91=0),"",M88/M91) | AG98: =IF(OR(N88="",N91="",N88=0,N91=0),"",N88/N91) | AH98: =IF(OR(O88="",O91="",O88=0,O91=0),"",O88/O91) | AI98: =IF(OR(P88="",P91="",P88=0,P91=0),"",P88/P91)
S99: Return on Assets | V99: =Q77/AVERAGE(G88:J88) -> #DIV/0! | X99: Capital Expenditure | AA99: =ABS(AVERAGE(N97:P97)) -> #DIV/0! | AC99: Debt / Equity | AE99: =IF(OR(L93="",L91="",L91=0,L93=0),"",L93/L91) | AF99: =IF(OR(M93="",M91="",M91=0,M93=0),"",M93/M91) | AG99: =IF(OR(N93="",N91="",N91=0,N93=0),"",N93/N91) | AH99: =IF(OR(O93="",O91="",O91=0,O93=0),"",O93/O91) | AI99: =IF(OR(P93="",P91="",P91=0,P93=0),"",P93/P91)
S100: Return on Capital Employed | V100: =Q76/(AVERAGE(G93:J93)+(AVERAGE(G88:J88)-AVERAGE(G90:J90))) -> #DIV/0! | X100: Free Cash Flow | AA100: =AVERAGE(N98:P98) -> #DIV/0!
S101: Asset Turnover | V101: =Q73/AVERAGE(G88:J88) -> #DIV/0!
A104: 4 | S104: Symbol | T104: HPE | V104: USD
D106: Income Statement | F106: 2016-10 | G106: 2017-01 | H106: 2017-04 | I106: 2017-07 | J106: 2017-10 | L106: 2013 | M106: 2014 | N106: 2015 | O106: 2016 | P106: 2017 | Q106: TTM | S106: Quote | X106: Growth | AA106: 5-Year Average | AC106: Key Ratios ― Growth, YOY | AF106: =M106 -> 2014 | AG106: =N106 -> 2015 | AH106: =O106 -> 2016 | AI106: =P106 -> 2017
D107: Revenue | F107: 11407000000 | G107: 7445000000 | H107: 8209000000 | I107: 5661000000 | J107: 7674000000 | L107: 57371000000 | M107: 55123000000 | N107: 52107000000 | O107: 50123000000 | P107: 28871000000 | Q107: 29643000000 | S107: Last Price | V107: 18.780001 | X107: Revenue | AA107: =IF(AA106="Year over Year",AI107,IF(AA106="3-Year Average",AVERAGE(AH107:AI107),IF(AA106="5-Year Average",AVERAGE(AF107:AI107),""))) -> -0.13899251 | AC107: Revenue % | AF107: =IF(AND(M107>0,L107>0,L107<>""),M107/L107-1,IF(AND(L107<0,M107<0,L107<>""),(M107-L107)/ABS(L107),IF(AND(L107>0,M107<0,L107<>""),"L",IF(AND(L107<0,M107>0,L107<>""),"P","")))) -> -0.03918356 | AG107: =IF(AND(N107>0,M107>0,M107<>""),N107/M107-1,IF(AND(M107<0,N107<0,M107<>""),(N107-M107)/ABS(M107),IF(AND(M107>0,N107<0,M107<>""),"L",IF(AND(M107<0,N107>0,M107<>""),"P","")))) -> -0.054714003 | AH107: =IF(AND(O107>0,N107>0,N107<>""),O107/N107-1,IF(AND(N107<0,O107<0,N107<>""),(O107-N107)/ABS(N107),IF(AND(N107>0,O107<0,N107<>""),"L",IF(AND(N107<0,O107>0,N107<>""),"P","")))) -> -0.038075498 | AI107: =IF(AND(P107>0,O107>0,O107<>""),P107/O107-1,IF(AND(O107<0,P107<0,O107<>""),(P107-O107)/ABS(O107),IF(AND(O107>0,P107<0,O107<>""),"L",IF(AND(O107<0,P107>0,O107<>""),"P","")))) -> -0.42399697
D108: Cost of revenue | F108: 8108000000 | G108: 4927000000 | H108: 5496000000 | I108: 4930000000 | J108: 5491000000 | L108: 41630000000 | M108: 39486000000 | N108: 37168000000 | O108: 35507000000 | P108: 20177000000 | Q108: 20979000000 | S108: Market Capitalization | V108: =V107*Q115 -> 3.0545672e+10 | X108: Operating Income | AA108: =IF(AA106="Year over Year",AI108,IF(AA106="3-Year Average",AVERAGE(AH108:AI108),IF(AA106="5-Year Average",AVERAGE(AF108:AI108),""))) -> 0.079681265 | AC108: Operating Income % | AF108: =IF(AND(M110>0,L110>0,L110<>""),M110/L110-1,IF(AND(L110<0,M110<0,L110<>""),(M110-L110)/ABS(L110),IF(AND(L110>0,M110<0,L110<>""),"L",IF(AND(L110<0,M110>0,L110<>""),"P","")))) -> -0.20901084 | AG108: =IF(AND(N110>0,M110>0,M110<>""),N110/M110-1,IF(AND(M110<0,N110<0,M110<>""),(N110-M110)/ABS(M110),IF(AND(M110>0,N110<0,M110<>""),"L",IF(AND(M110<0,N110>0,M110<>""),"P","")))) -> -0.34775161 | AH108: =IF(AND(O110>0,N110>0,N110<>""),O110/N110-1,IF(AND(N110<0,O110<0,N110<>""),(O110-N110)/ABS(N110),IF(AND(N110>0,O110<0,N110<>""),"L",IF(AND(N110<0,O110>0,N110<>""),"P","")))) -> 1.7248851 | AI108: =IF(AND(P110>0,O110>0,O110<>""),P110/O110-1,IF(AND(O110<0,P110<0,O110<>""),(P110-O110)/ABS(O110),IF(AND(O110>0,P110<0,O110<>""),"L",IF(AND(O110<0,P110>0,O110<>""),"P","")))) -> -0.84939759
D109: Gross profit | F109: 3299000000 | G109: 2518000000 | H109: 2713000000 | I109: 731000000 | J109: 2183000000 | L109: 15741000000 | M109: 15637000000 | N109: 14939000000 | O109: 14616000000 | P109: 8694000000 | Q109: 8664000000 | S109: Enterprise Value | V109: =V108+(J123+J125)-J119 -> 3.6827672e+10 | X109: Net Income | AA109: =IF(AA106="Year over Year",AI109,IF(AA106="3-Year Average",AVERAGE(AH109:AI109),IF(AA106="5-Year Average",AVERAGE(AF109:AI109),""))) -> -0.077475183 | AC109: Net Income % | AF109: =IF(AND(M111>0,L111>0,L111<>""),M111/L111-1,IF(AND(L111<0,M111<0,L111<>""),(M111-L111)/ABS(L111),IF(AND(L111>0,M111<0,L111<>""),"L",IF(AND(L111<0,M111>0,L111<>""),"P","")))) -> -0.19648952 | AG109: =IF(AND(N111>0,M111>0,M111<>""),N111/M111-1,IF(AND(M111<0,N111<0,M111<>""),(N111-M111)/ABS(M111),IF(AND(M111>0,N111<0,M111<>""),"L",IF(AND(M111<0,N111>0,M111<>""),"P","")))) -> 0.49332524 | AH109: =IF(AND(O111>0,N111>0,N111<>""),O111/N111-1,IF(AND(N111<0,O111<0,N111<>""),(O111-N111)/ABS(N111),IF(AND(N111>0,O111<0,N111<>""),"L",IF(AND(N111<0,O111>0,N111<>""),"P","")))) -> 0.28443722 | AI109: =IF(AND(P111>0,O111>0,O111<>""),P111/O111-1,IF(AND(O111<0,P111<0,O111<>""),(P111-O111)/ABS(O111),IF(AND(O111>0,P111<0,O111<>""),"L",IF(AND(O111<0,P111>0,O111<>""),"P","")))) -> -0.89117368
D110: Operating income | F110: 463000000 | G110: 182000000 | H110: 147000000 | I110: -160000000 | J110: 515000000 | L110: 2952000000 | M110: 2335000000 | N110: 1523000000 | O110: 4150000000 | P110: 625000000 | Q110: 549000000 | S110: Book Value | V110: =J122-J126 -> 23951000000 | X110: Earnings Per Share | AA110: =IF(AA106="Year over Year",AI110,IF(AA106="3-Year Average",AVERAGE(AH110:AI110),IF(AA106="5-Year Average",AVERAGE(AF110:AI110),""))) -> 0.085515098 | AC110: Earnings per share % | AF110: =IF(AND(M112>0,L112>0,L112<>""),M112/L112-1,IF(AND(L112<0,M112<0,L112<>""),(M112-L112)/ABS(L112),IF(AND(L112>0,M112<0,L112<>""),"L",IF(AND(L112<0,M112>0,L112<>""),"P","")))) | AG110: =IF(AND(N112>0,M112>0,M112<>""),N112/M112-1,IF(AND(M112<0,N112<0,M112<>""),(N112-M112)/ABS(M112),IF(AND(M112>0,N112<0,M112<>""),"L",IF(AND(M112<0,N112>0,M112<>""),"P","")))) -> 0.78947368 | AH110: =IF(AND(O112>0,N112>0,N112<>""),O112/N112-1,IF(AND(N112<0,O112<0,N112<>""),(O112-N112)/ABS(N112),IF(AND(N112>0,O112<0,N112<>""),"L",IF(AND(N112<0,O112>0,N112<>""),"P","")))) -> 0.35294118 | AI110: =IF(AND(P112>0,O112>0,O112<>""),P112/O112-1,IF(AND(O112<0,P112<0,O112<>""),(P112-O112)/ABS(O112),IF(AND(O112>0,P112<0,O112<>""),"L",IF(AND(O112<0,P112>0,O112<>""),"P","")))) -> -0.88586957
D111: Net income | F111: 267000000 | G111: -612000000 | H111: 165000000 | I111: 524000000 | J111: 1436000000 | L111: 2051000000 | M111: 1648000000 | N111: 2461000000 | O111: 3161000000 | P111: 344000000 | Q111: 1513000000 | S111: Type | V111: =IF(V108>10000,"Large Cap",IF(AND(10000>V108,2000<V108),"Mid Cap",IF(AND(2000>V108,V108>50),"Small Cap",IF(V108<50,"Micro Cap",NA)))) -> Large Cap
D112: Earnings per share | F112: 0.16 | G112: -0.37 | H112: 0.1 | I112: 0.32 | J112: 0.9 | M112: 0.76 | N112: 1.36 | O112: 1.84 | P112: 0.21 | Q112: 0.95 | S112: Dividend Yield | X112: Financial Health | AC112: Financials | AE112: =L106 -> 2013 | AF112: =M106 -> 2014 | AG112: =N106 -> 2015 | AH112: =O106 -> 2016 | AI112: =P106 -> 2017
F113: 1669000000 | G113: 1658000000 | H113: 1641000000 | I113: 1616000000 | J113: 1591000000 | M113: 1839000000 | N113: 1804000000 | O113: 1715000000 | P113: 1646000000 | Q113: 1626500000
...

Sheet Sheet 3
A1: source
A2: Gross Margin % | C2: Return on Equity % | E2: Debt / Equity | G2: Current Ratio | I2: USD in Billion | K2: Year over Year
A3: Net Margin % | C3: Return on Assets % | E3: Financial Leverage | G3: Quick Ratio | I3: USD in Million | K3: 3-Year Average
A4: Operating Margin % | I4: USD in Thousand | K4: 5-Year Average
I5: USD
