Workbook
Name data_type: 'Sheet 2'!#REF!
Name debt: 'Sheet 1'!$Z$3
Name effc: 'Sheet 1'!$AD$3
Name proft: 'Sheet 1'!$AA$3
Name ratio: 'Sheet 1'!$X$3

Sheet Sheet 1
B2: Quote | G2: Valuation | X2: Financial Health | AA2: Profitability | AD2: Effectiveness | AG2: Growth | AP2: Dividend
A3: Symbol | B3: Last Price | C3: Market Capitalization | D3: Enterprise Value | E3: Book Value | F3: Sales | I3: P / E | K3: P / S | M3: P / B | O3: P / FCF | Q3: P / CFO | S3: EV / EBITDA | U3: EV / S | X3: Current Ratio | Y3: Financial Leverage | Z3: Debt / Equity | AA3: Gross Margin | AB3: Net Margin | AC3: Operating Margin | AD3: Return on Equity | AE3: Return on Assets | AF3: Asset Turnover | AH3: Revenue | AJ3: Operating Income % | AL3: Net Income | AN3: Earnings Per Share | AP3: Yield
I4: =AVERAGE(I5:I500) -> 24.471061 | K4: =AVERAGE(K5:K500) -> #DIV/0! | M4: =AVERAGE(M5:M500) -> #DIV/0! | O4: =AVERAGE(O5:O500) -> #DIV/0! | Q4: =AVERAGE(Q5:Q500) -> #DIV/0! | S4: =AVERAGE(S5:S500) -> #DIV/0! | U4: =AVERAGE(U5:U500) -> #NUM! | X4: =AVERAGE(X5:X500) -> #DIV/0! | Y4: =AVERAGE(Y5:Y500) -> #DIV/0! | Z4: =AVERAGE(Z5:Z500) -> #DIV/0! | AA4: =AVERAGE(AA5:AA500) -> #DIV/0! | AB4: =AVERAGE(AB5:AB500) -> #DIV/0! | AC4: =AVERAGE(AC5:AC500) -> #DIV/0! | AD4: =AVERAGE(AD5:AD39) -> #DIV/0! | AE4: =AVERAGE(AE5:AE39) -> #DIV/0! | AF4: =AVERAGE(AF5:AF39) -> #DIV/0! | AH4: =AVERAGE(AH5:AH500) -> #DIV/0! | AI4: =AVERAGE(AI5:AI500) -> #DIV/0! | AJ4: =AVERAGE(AJ5:AJ500) -> #NUM! | AL4: =AVERAGE(AL5:AL500) -> #DIV/0! | AN4: =AVERAGE(AN5:AN500) -> #DIV/0! | AP4: =AVERAGE(AP5:AP500) -> #DIV/0!
A5: {=INDEX('Sheet 2'!U$2:U$3178,SMALL(IF(A$3='Sheet 2'!$T$2:$T$3178,ROW('Sheet 2'!U$2:U$3178)-ROW('Sheet 2'!$U$2)+1),ROW(1:1)))} -> AES | B5: {=INDEX('Sheet 2'!W$5:W$3178,SMALL(IF(B$3='Sheet 2'!T$5:T$3178,ROW('Sheet 2'!W$5:W$3178)-ROW('Sheet 2'!W$5)+1),ROW(1:1)))} -> 14.77 | C5: {=INDEX('Sheet 2'!W$5:W$3178,SMALL(IF(C$3='Sheet 2'!T$5:T$3178,ROW('Sheet 2'!W$5:W$3178)-ROW('Sheet 2'!W$5)+1),ROW(1:1)))} -> 9.8042905e+09 | D5: {=INDEX('Sheet 2'!W$5:W$3178,SMALL(IF(D$3='Sheet 2'!T$5:T$3178,ROW('Sheet 2'!W$5:W$3178)-ROW('Sheet 2'!W$5)+1),ROW(1:1)))} -> 2.839029e+10 | E5: {=INDEX('Sheet 2'!W$5:W$3178,SMALL(IF(E$3='Sheet 2'!T$5:T$3178,ROW('Sheet 2'!W$5:W$3178)-ROW('Sheet 2'!W$5)+1),ROW(1:1)))} -> 5468000000 | F5: {=INDEX('Sheet 2'!W$5:W$3178,SMALL(IF(F$3='Sheet 2'!T$5:T$3178,ROW('Sheet 2'!W$5:W$3178)-ROW('Sheet 2'!W$5)+1),ROW(1:1)))} -> 10592000000 | I5: {=INDEX('Sheet 2'!W$5:W$3178,SMALL(IF(I$3='Sheet 2'!T$5:T$3178,ROW('Sheet 2'!W$5:W$3178)-ROW('Sheet 2'!W$5)+1),ROW(1:1)))} -> 24.471061 | K5: {=INDEX('Sheet 2'!W$5:W$3178,SMALL(IF(K$3='Sheet 2'!T$5:T$3178,ROW('Sheet 2'!W$5:W$3178)-ROW('Sheet 2'!W$5)+1),ROW(1:1)))} -> 0.92413373 | M5: {=INDEX('Sheet 2'!W$5:W$3178,SMALL(IF(M$3='Sheet 2'!T$5:T$3178,ROW('Sheet 2'!W$5:W$3178)-ROW('Sheet 2'!W$5)+1),ROW(1:1)))} -> 1.7930304 | O5: {=INDEX('Sheet 2'!W$5:W$3178,SMALL(IF(O$3='Sheet 2'!T$5:T$3178,ROW('Sheet 2'!W$5:W$3178)-ROW('Sheet 2'!W$5)+1),ROW(1:1)))} -> #DIV/0! | Q5: {=INDEX('Sheet 2'!W$5:W$3178,SMALL(IF(Q$3='Sheet 2'!T$5:T$3178,ROW('Sheet 2'!W$5:W$3178)-ROW('Sheet 2'!W$5)+1),ROW(1:1)))} -> #DIV/0! | S5: {=INDEX('Sheet 2'!W$5:W$3178,SMALL(IF(S$3='Sheet 2'!T$5:T$3178,ROW('Sheet 2'!W$5:W$3178)-ROW('Sheet 2'!W$5)+1),ROW(1:1)))} -> #DIV/0! | U5: {=INDEX('Sheet 2'!W$5:W$3178,SMALL(IF(U$3='Sheet 2'!T$5:T$3178,ROW('Sheet 2'!W$5:W$3178)-ROW('Sheet 2'!W$5)+1),ROW(1:1)))} -> #NUM! | X5: {=INDEX('Sheet 2'!AB$13:AB$3178,SMALL(IF(X$3='Sheet 2'!Y$13:Y$3178,ROW('Sheet 2'!AB$13:AB$3178)-ROW('Sheet 2'!AB$13)+1),ROW(1:1)))} -> 1.2705254 | Y5: {=INDEX('Sheet 2'!AB$13:AB$3178,SMALL(IF(Y$3='Sheet 2'!Y$13:Y$3178,ROW('Sheet 2'!AB$13:AB$3178)-ROW('Sheet 2'!AB$13)+1),ROW(1:1)))} -> 5.8724476 | Z5: {=INDEX('Sheet 2'!AB$13:AB$3178,SMALL(IF(Z$3='Sheet 2'!Y$13:Y$3178,ROW('Sheet 2'!AB$13:AB$3178)-ROW('Sheet 2'!AB$13)+1),ROW(1:1)))} -> 3.2473027 | AA5: {=INDEX('Sheet 2'!W$5:W$3178,SMALL(IF(AA$3='Sheet 2'!T$5:T$3178,ROW('Sheet 2'!W$5:W$3178)-ROW('Sheet 2'!W$5)+1),ROW(1:1)))} -> 1.7729418 | AB5: {=INDEX('Sheet 2'!W$5:W$3178,SMALL(IF(AB$3='Sheet 2'!T$5:T$3178,ROW('Sheet 2'!W$5:W$3178)-ROW('Sheet 2'!W$5)+1),ROW(1:1)))} -> 0.03776435 | AC5: {=INDEX('Sheet 2'!W$5:W$3178,SMALL(IF(AC$3='Sheet 2'!T$5:T$3178,ROW('Sheet 2'!W$5:W$3178)-ROW('Sheet 2'!W$5)+1),ROW(1:1)))} -> 0.20817598 | AD5: {=INDEX('Sheet 2'!W$5:W$3178,SMALL(IF(AD$3='Sheet 2'!T$5:T$3178,ROW('Sheet 2'!W$5:W$3178)-ROW('Sheet 2'!W$5)+1),ROW(1:1)))} -> 0.071333036 | AE5: {=INDEX('Sheet 2'!W$5:W$3178,SMALL(IF(AE$3='Sheet 2'!T$5:T$3178,ROW('Sheet 2'!W$5:W$3178)-ROW('Sheet 2'!W$5)+1),ROW(1:1)))} -> 0.012147071 | AF5: {=INDEX('Sheet 2'!W$5:W$3178,SMALL(IF(AF$3='Sheet 2'!T$5:T$3178,ROW('Sheet 2'!W$5:W$3178)-ROW('Sheet 2'!W$5)+1),ROW(1:1)))} -> 0.32165443 | AH5: {=INDEX('Sheet 2'!AB$5:AB$3178,SMALL(IF(AH$3='Sheet 2'!Y$5:Y$3178,ROW('Sheet 2'!AB$5:AB$3178)-ROW('Sheet 2'!AB$5)+1),ROW(1:1)))} -> -0.1061799 | AJ5: {=INDEX('Sheet 2'!W$5:W$3178,SMALL(IF(AJ$3='Sheet 2'!T$5:T$3178,ROW('Sheet 2'!W$5:W$3178)-ROW('Sheet 2'!W$5)+1),ROW(1:1)))} -> #NUM! | AL5: {=INDEX('Sheet 2'!AB$5:AB$3178,SMALL(IF(AL$3='Sheet 2'!Y$5:Y$3178,ROW('Sheet 2'!AB$5:AB$3178)-ROW('Sheet 2'!AB$5)+1),ROW(1:1)))} -> -0.31475713 | AN5: {=INDEX('Sheet 2'!AB$5:AB$3178,SMALL(IF(AN$3='Sheet 2'!Y$5:Y$3178,ROW('Sheet 2'!AB$5:AB$3178)-ROW('Sheet 2'!AB$5)+1),ROW(1:1)))} -> #DIV/0!
A6: {=INDEX('Sheet 2'!U$2:U$3178,SMALL(IF(A$3='Sheet 2'!$T$2:$T$3178,ROW('Sheet 2'!U$2:U$3178)-ROW('Sheet 2'!$U$2)+1),ROW(2:2)))} -> CCUR | B6: {=INDEX('Sheet 2'!W$5:W$3178,SMALL(IF(B$3='Sheet 2'!T$5:T$3178,ROW('Sheet 2'!W$5:W$3178)-ROW('Sheet 2'!W$5)+1),ROW(2:2)))} -> 5.42 | C6: {=INDEX('Sheet 2'!W$5:W$3178,SMALL(IF(C$3='Sheet 2'!T$5:T$3178,ROW('Sheet 2'!W$5:W$3178)-ROW('Sheet 2'!W$5)+1),ROW(2:2)))} -> 0 | D6: {=INDEX('Sheet 2'!W$5:W$3178,SMALL(IF(D$3='Sheet 2'!T$5:T$3178,ROW('Sheet 2'!W$5:W$3178)-ROW('Sheet 2'!W$5)+1),ROW(2:2)))} -> 0 | E6: {=INDEX('Sheet 2'!W$5:W$3178,SMALL(IF(E$3='Sheet 2'!T$5:T$3178,ROW('Sheet 2'!W$5:W$3178)-ROW('Sheet 2'!W$5)+1),ROW(2:2)))} -> 0 | F6: {=INDEX('Sheet 2'!W$5:W$3178,SMALL(IF(F$3='Sheet 2'!T$5:T$3178,ROW('Sheet 2'!W$5:W$3178)-ROW('Sheet 2'!W$5)+1),ROW(2:2)))} -> 0 | I6: {=INDEX('Sheet 2'!W$5:W$3178,SMALL(IF(I$3='Sheet 2'!T$5:T$3178,ROW('Sheet 2'!W$5:W$3178)-ROW('Sheet 2'!W$5)+1),ROW(2:2)))} | K6: {=INDEX('Sheet 2'!W$5:W$3178,SMALL(IF(K$3='Sheet 2'!T$5:T$3178,ROW('Sheet 2'!W$5:W$3178)-ROW('Sheet 2'!W$5)+1),ROW(2:2)))} -> #DIV/0! | M6: {=INDEX('Sheet 2'!W$5:W$3178,SMALL(IF(M$3='Sheet 2'!T$5:T$3178,ROW('Sheet 2'!W$5:W$3178)-ROW('Sheet 2'!W$5)+1),ROW(2:2)))} -> #DIV/0! | O6: {=INDEX('Sheet 2'!W$5:W$3178,SMALL(IF(O$3='Sheet 2'!T$5:T$3178,ROW('Sheet 2'!W$5:W$3178)-ROW('Sheet 2'!W$5)+1),ROW(2:2)))} -> #DIV/0! | Q6: {=INDEX('Sheet 2'!W$5:W$3178,SMALL(IF(Q$3='Sheet 2'!T$5:T$3178,ROW('Sheet 2'!W$5:W$3178)-ROW('Sheet 2'!W$5)+1),ROW(2:2)))} -> #DIV/0! | S6: {=INDEX('Sheet 2'!W$5:W$3178,SMALL(IF(S$3='Sheet 2'!T$5:T$3178,ROW('Sheet 2'!W$5:W$3178)-ROW('Sheet 2'!W$5)+1),ROW(2:2)))} -> #DIV/0! | U6: {=INDEX('Sheet 2'!W$5:W$3178,SMALL(IF(U$3='Sheet 2'!T$5:T$3178,ROW('Sheet 2'!W$5:W$3178)-ROW('Sheet 2'!W$5)+1),ROW(2:2)))} -> #NUM! | X6: {=INDEX('Sheet 2'!AB$13:AB$3178,SMALL(IF(X$3='Sheet 2'!Y$13:Y$3178,ROW('Sheet 2'!AB$13:AB$3178)-ROW('Sheet 2'!AB$13)+1),ROW(2:2)))} -> #DIV/0! | Y6: {=INDEX('Sheet 2'!AB$13:AB$3178,SMALL(IF(Y$3='Sheet 2'!Y$13:Y$3178,ROW('Sheet 2'!AB$13:AB$3178)-ROW('Sheet 2'!AB$13)+1),ROW(2:2)))} -> #DIV/0! | Z6: {=INDEX('Sheet 2'!AB$13:AB$3178,SMALL(IF(Z$3='Sheet 2'!Y$13:Y$3178,ROW('Sheet 2'!AB$13:AB$3178)-ROW('Sheet 2'!AB$13)+1),ROW(2:2)))} -> #DIV/0! | AA6: {=INDEX('Sheet 2'!W$5:W$3178,SMALL(IF(AA$3='Sheet 2'!T$5:T$3178,ROW('Sheet 2'!W$5:W$3178)-ROW('Sheet 2'!W$5)+1),ROW(2:2)))} -> #DIV/0! | AB6: {=INDEX('Sheet 2'!W$5:W$3178,SMALL(IF(AB$3='Sheet 2'!T$5:T$3178,ROW('Sheet 2'!W$5:W$3178)-ROW('Sheet 2'!W$5)+1),ROW(2:2)))} -> #DIV/0! | AC6: {=INDEX('Sheet 2'!W$5:W$3178,SMALL(IF(AC$3='Sheet 2'!T$5:T$3178,ROW('Sheet 2'!W$5:W$3178)-ROW('Sheet 2'!W$5)+1),ROW(2:2)))} -> #DIV/0! | AD6: {=INDEX('Sheet 2'!W$5:W$3178,SMALL(IF(AD$3='Sheet 2'!T$5:T$3178,ROW('Sheet 2'!W$5:W$3178)-ROW('Sheet 2'!W$5)+1),ROW(2:2)))} -> #DIV/0! | AE6: {=INDEX('Sheet 2'!W$5:W$3178,SMALL(IF(AE$3='Sheet 2'!T$5:T$3178,ROW('Sheet 2'!W$5:W$3178)-ROW('Sheet 2'!W$5)+1),ROW(2:2)))} -> #DIV/0! | AF6: {=INDEX('Sheet 2'!W$5:W$3178,SMALL(IF(AF$3='Sheet 2'!T$5:T$3178,ROW('Sheet 2'!W$5:W$3178)-ROW('Sheet 2'!W$5)+1),ROW(2:2)))} -> #DIV/0! | AH6: {=INDEX('Sheet 2'!AB$5:AB$3178,SMALL(IF(AH$3='Sheet 2'!Y$5:Y$3178,ROW('Sheet 2'!AB$5:AB$3178)-ROW('Sheet 2'!AB$5)+1),ROW(2:2)))} -> 10592000000 | AJ6: {=INDEX('Sheet 2'!W$5:W$3178,SMALL(IF(AJ$3='Sheet 2'!T$5:T$3178,ROW('Sheet 2'!W$5:W$3178)-ROW('Sheet 2'!W$5)+1),ROW(2:2)))} -> #NUM! | AL6: {=INDEX('Sheet 2'!AB$5:AB$3178,SMALL(IF(AL$3='Sheet 2'!Y$5:Y$3178,ROW('Sheet 2'!AB$5:AB$3178)-ROW('Sheet 2'!AB$5)+1),ROW(2:2)))} -> 400000000 | AN6: {=INDEX('Sheet 2'!AB$5:AB$3178,SMALL(IF(AN$3='Sheet 2'!Y$5:Y$3178,ROW('Sheet 2'!AB$5:AB$3178)-ROW('Sheet 2'!AB$5)+1),ROW(2:2)))} -> 0
A7: {=INDEX('Sheet 2'!U$2:U$3178,SMALL(IF(A$3='Sheet 2'!$T$2:$T$3178,ROW('Sheet 2'!U$2:U$3178)-ROW('Sheet 2'!$U$2)+1),ROW(3:3)))} -> CCUR | B7: {=INDEX('Sheet 2'!W$5:W$3178,SMALL(IF(B$3='Sheet 2'!T$5:T$3178,ROW('Sheet 2'!W$5:W$3178)-ROW('Sheet 2'!W$5)+1),ROW(3:3)))} -> 5.42 | C7: {=INDEX('Sheet 2'!W$5:W$3178,SMALL(IF(C$3='Sheet 2'!T$5:T$3178,ROW('Sheet 2'!W$5:W$3178)-ROW('Sheet 2'!W$5)+1),ROW(3:3)))} -> 0 | D7: {=INDEX('Sheet 2'!W$5:W$3178,SMALL(IF(D$3='Sheet 2'!T$5:T$3178,ROW('Sheet 2'!W$5:W$3178)-ROW('Sheet 2'!W$5)+1),ROW(3:3)))} -> 0 | E7: {=INDEX('Sheet 2'!W$5:W$3178,SMALL(IF(E$3='Sheet 2'!T$5:T$3178,ROW('Sheet 2'!W$5:W$3178)-ROW('Sheet 2'!W$5)+1),ROW(3:3)))} -> 0 | F7: {=INDEX('Sheet 2'!W$5:W$3178,SMALL(IF(F$3='Sheet 2'!T$5:T$3178,ROW('Sheet 2'!W$5:W$3178)-ROW('Sheet 2'!W$5)+1),ROW(3:3)))} -> 0 | I7: {=INDEX('Sheet 2'!W$5:W$3178,SMALL(IF(I$3='Sheet 2'!T$5:T$3178,ROW('Sheet 2'!W$5:W$3178)-ROW('Sheet 2'!W$5)+1),ROW(3:3)))} | K7: {=INDEX('Sheet 2'!W$5:W$3178,SMALL(IF(K$3='Sheet 2'!T$5:T$3178,ROW('Sheet 2'!W$5:W$3178)-ROW('Sheet 2'!W$5)+1),ROW(3:3)))} -> #DIV/0! | M7: {=INDEX('Sheet 2'!W$5:W$3178,SMALL(IF(M$3='Sheet 2'!T$5:T$3178,ROW('Sheet 2'!W$5:W$3178)-ROW('Sheet 2'!W$5)+1),ROW(3:3)))} -> #DIV/0! | O7: {=INDEX('Sheet 2'!W$5:W$3178,SMALL(IF(O$3='Sheet 2'!T$5:T$3178,ROW('Sheet 2'!W$5:W$3178)-ROW('Sheet 2'!W$5)+1),ROW(3:3)))} -> #DIV/0! | Q7: {=INDEX('Sheet 2'!W$5:W$3178,SMALL(IF(Q$3='Sheet 2'!T$5:T$3178,ROW('Sheet 2'!W$5:W$3178)-ROW('Sheet 2'!W$5)+1),ROW(3:3)))} -> #DIV/0! | S7: {=INDEX('Sheet 2'!W$5:W$3178,SMALL(IF(S$3='Sheet 2'!T$5:T$3178,ROW('Sheet 2'!W$5:W$3178)-ROW('Sheet 2'!W$5)+1),ROW(3:3)))} -> #DIV/0! | U7: {=INDEX('Sheet 2'!W$5:W$3178,SMALL(IF(U$3='Sheet 2'!T$5:T$3178,ROW('Sheet 2'!W$5:W$3178)-ROW('Sheet 2'!W$5)+1),ROW(3:3)))} -> #NUM! | X7: {=INDEX('Sheet 2'!AB$13:AB$3178,SMALL(IF(X$3='Sheet 2'!Y$13:Y$3178,ROW('Sheet 2'!AB$13:AB$3178)-ROW('Sheet 2'!AB$13)+1),ROW(3:3)))} -> #DIV/0! | Y7: {=INDEX('Sheet 2'!AB$13:AB$3178,SMALL(IF(Y$3='Sheet 2'!Y$13:Y$3178,ROW('Sheet 2'!AB$13:AB$3178)-ROW('Sheet 2'!AB$13)+1),ROW(3:3)))} -> #DIV/0! | Z7: {=INDEX('Sheet 2'!AB$13:AB$3178,SMALL(IF(Z$3='Sheet 2'!Y$13:Y$3178,ROW('Sheet 2'!AB$13:AB$3178)-ROW('Sheet 2'!AB$13)+1),ROW(3:3)))} -> #DIV/0! | AA7: {=INDEX('Sheet 2'!W$5:W$3178,SMALL(IF(AA$3='Sheet 2'!T$5:T$3178,ROW('Sheet 2'!W$5:W$3178)-ROW('Sheet 2'!W$5)+1),ROW(3:3)))} -> #DIV/0! | AB7: {=INDEX('Sheet 2'!W$5:W$3178,SMALL(IF(AB$3='Sheet 2'!T$5:T$3178,ROW('Sheet 2'!W$5:W$3178)-ROW('Sheet 2'!W$5)+1),ROW(3:3)))} -> #DIV/0! | AC7: {=INDEX('Sheet 2'!W$5:W$3178,SMALL(IF(AC$3='Sheet 2'!T$5:T$3178,ROW('Sheet 2'!W$5:W$3178)-ROW('Sheet 2'!W$5)+1),ROW(3:3)))} -> #DIV/0! | AD7: {=INDEX('Sheet 2'!W$5:W$3178,SMALL(IF(AD$3='Sheet 2'!T$5:T$3178,ROW('Sheet 2'!W$5:W$3178)-ROW('Sheet 2'!W$5)+1),ROW(3:3)))} -> #DIV/0! | AE7: {=INDEX('Sheet 2'!W$5:W$3178,SMALL(IF(AE$3='Sheet 2'!T$5:T$3178,ROW('Sheet 2'!W$5:W$3178)-ROW('Sheet 2'!W$5)+1),ROW(3:3)))} -> #DIV/0! | AF7: {=INDEX('Sheet 2'!W$5:W$3178,SMALL(IF(AF$3='Sheet 2'!T$5:T$3178,ROW('Sheet 2'!W$5:W$3178)-ROW('Sheet 2'!W$5)+1),ROW(3:3)))} -> #DIV/0! | AH7: {=INDEX('Sheet 2'!AB$5:AB$3178,SMALL(IF(AH$3='Sheet 2'!Y$5:Y$3178,ROW('Sheet 2'!AB$5:AB$3178)-ROW('Sheet 2'!AB$5)+1),ROW(3:3)))} -> #DIV/0! | AJ7: {=INDEX('Sheet 2'!W$5:W$3178,SMALL(IF(AJ$3='Sheet 2'!T$5:T$3178,ROW('Sheet 2'!W$5:W$3178)-ROW('Sheet 2'!W$5)+1),ROW(3:3)))} -> #NUM! | AL7: {=INDEX('Sheet 2'!AB$5:AB$3178,SMALL(IF(AL$3='Sheet 2'!Y$5:Y$3178,ROW('Sheet 2'!AB$5:AB$3178)-ROW('Sheet 2'!AB$5)+1),ROW(3:3)))} -> #DIV/0! | AN7: {=INDEX('Sheet 2'!AB$5:AB$3178,SMALL(IF(AN$3='Sheet 2'!Y$5:Y$3178,ROW('Sheet 2'!AB$5:AB$3178)-ROW('Sheet 2'!AB$5)+1),ROW(3:3)))} -> #DIV/0!
A8: {=INDEX('Sheet 2'!U$2:U$3178,SMALL(IF(A$3='Sheet 2'!$T$2:$T$3178,ROW('Sheet 2'!U$2:U$3178)-ROW('Sheet 2'!$U$2)+1),ROW(4:4)))} -> CCUR | B8: {=INDEX('Sheet 2'!W$5:W$3178,SMALL(IF(B$3='Sheet 2'!T$5:T$3178,ROW('Sheet 2'!W$5:W$3178)-ROW('Sheet 2'!W$5)+1),ROW(4:4)))} -> 5.42 | C8: {=INDEX('Sheet 2'!W$5:W$3178,SMALL(IF(C$3='Sheet 2'!T$5:T$3178,ROW('Sheet 2'!W$5:W$3178)-ROW('Sheet 2'!W$5)+1),ROW(4:4)))} -> 0 | D8: {=INDEX('Sheet 2'!W$5:W$3178,SMALL(IF(D$3='Sheet 2'!T$5:T$3178,ROW('Sheet 2'!W$5:W$3178)-ROW('Sheet 2'!W$5)+1),ROW(4:4)))} -> 0 | E8: {=INDEX('Sheet 2'!W$5:W$3178,SMALL(IF(E$3='Sheet 2'!T$5:T$3178,ROW('Sheet 2'!W$5:W$3178)-ROW('Sheet 2'!W$5)+1),ROW(4:4)))} -> 0 | F8: {=INDEX('Sheet 2'!W$5:W$3178,SMALL(IF(F$3='Sheet 2'!T$5:T$3178,ROW('Sheet 2'!W$5:W$3178)-ROW('Sheet 2'!W$5)+1),ROW(4:4)))} -> 0 | I8: {=INDEX('Sheet 2'!W$5:W$3178,SMALL(IF(I$3='Sheet 2'!T$5:T$3178,ROW('Sheet 2'!W$5:W$3178)-ROW('Sheet 2'!W$5)+1),ROW(4:4)))} | K8: {=INDEX('Sheet 2'!W$5:W$3178,SMALL(IF(K$3='Sheet 2'!T$5:T$3178,ROW('Sheet 2'!W$5:W$3178)-ROW('Sheet 2'!W$5)+1),ROW(4:4)))} -> #DIV/0! | M8: {=INDEX('Sheet 2'!W$5:W$3178,SMALL(IF(M$3='Sheet 2'!T$5:T$3178,ROW('Sheet 2'!W$5:W$3178)-ROW('Sheet 2'!W$5)+1),ROW(4:4)))} -> #DIV/0! | O8: {=INDEX('Sheet 2'!W$5:W$3178,SMALL(IF(O$3='Sheet 2'!T$5:T$3178,ROW('Sheet 2'!W$5:W$3178)-ROW('Sheet 2'!W$5)+1),ROW(4:4)))} -> #DIV/0! | Q8: {=INDEX('Sheet 2'!W$5:W$3178,SMALL(IF(Q$3='Sheet 2'!T$5:T$3178,ROW('Sheet 2'!W$5:W$3178)-ROW('Sheet 2'!W$5)+1),ROW(4:4)))} -> #DIV/0! | S8: {=INDEX('Sheet 2'!W$5:W$3178,SMALL(IF(S$3='Sheet 2'!T$5:T$3178,ROW('Sheet 2'!W$5:W$3178)-ROW('Sheet 2'!W$5)+1),ROW(4:4)))} -> #DIV/0! | U8: {=INDEX('Sheet 2'!W$5:W$3178,SMALL(IF(U$3='Sheet 2'!T$5:T$3178,ROW('Sheet 2'!W$5:W$3178)-ROW('Sheet 2'!W$5)+1),ROW(4:4)))} -> #NUM! | X8: {=INDEX('Sheet 2'!AB$13:AB$3178,SMALL(IF(X$3='Sheet 2'!Y$13:Y$3178,ROW('Sheet 2'!AB$13:AB$3178)-ROW('Sheet 2'!AB$13)+1),ROW(4:4)))} -> #DIV/0! | Y8: {=INDEX('Sheet 2'!AB$13:AB$3178,SMALL(IF(Y$3='Sheet 2'!Y$13:Y$3178,ROW('Sheet 2'!AB$13:AB$3178)-ROW('Sheet 2'!AB$13)+1),ROW(4:4)))} -> #DIV/0! | Z8: {=INDEX('Sheet 2'!AB$13:AB$3178,SMALL(IF(Z$3='Sheet 2'!Y$13:Y$3178,ROW('Sheet 2'!AB$13:AB$3178)-ROW('Sheet 2'!AB$13)+1),ROW(4:4)))} -> #DIV/0! | AA8: {=INDEX('Sheet 2'!W$5:W$3178,SMALL(IF(AA$3='Sheet 2'!T$5:T$3178,ROW('Sheet 2'!W$5:W$3178)-ROW('Sheet 2'!W$5)+1),ROW(4:4)))} -> #DIV/0! | AB8: {=INDEX('Sheet 2'!W$5:W$3178,SMALL(IF(AB$3='Sheet 2'!T$5:T$3178,ROW('Sheet 2'!W$5:W$3178)-ROW('Sheet 2'!W$5)+1),ROW(4:4)))} -> #DIV/0! | AC8: {=INDEX('Sheet 2'!W$5:W$3178,SMALL(IF(AC$3='Sheet 2'!T$5:T$3178,ROW('Sheet 2'!W$5:W$3178)-ROW('Sheet 2'!W$5)+1),ROW(4:4)))} -> #DIV/0! | AD8: {=INDEX('Sheet 2'!W$5:W$3178,SMALL(IF(AD$3='Sheet 2'!T$5:T$3178,ROW('Sheet 2'!W$5:W$3178)-ROW('Sheet 2'!W$5)+1),ROW(4:4)))} -> #DIV/0! | AE8: {=INDEX('Sheet 2'!W$5:W$3178,SMALL(IF(AE$3='Sheet 2'!T$5:T$3178,ROW('Sheet 2'!W$5:W$3178)-ROW('Sheet 2'!W$5)+1),ROW(4:4)))} -> #DIV/0! | AF8: {=INDEX('Sheet 2'!W$5:W$3178,SMALL(IF(AF$3='Sheet 2'!T$5:T$3178,ROW('Sheet 2'!W$5:W$3178)-ROW('Sheet 2'!W$5)+1),ROW(4:4)))} -> #DIV/0! | AH8: {=INDEX('Sheet 2'!AB$5:AB$3178,SMALL(IF(AH$3='Sheet 2'!Y$5:Y$3178,ROW('Sheet 2'!AB$5:AB$3178)-ROW('Sheet 2'!AB$5)+1),ROW(4:4)))} -> 0 | AJ8: {=INDEX('Sheet 2'!W$5:W$3178,SMALL(IF(AJ$3='Sheet 2'!T$5:T$3178,ROW('Sheet 2'!W$5:W$3178)-ROW('Sheet 2'!W$5)+1),ROW(4:4)))} -> #NUM! | AL8: {=INDEX('Sheet 2'!AB$5:AB$3178,SMALL(IF(AL$3='Sheet 2'!Y$5:Y$3178,ROW('Sheet 2'!AB$5:AB$3178)-ROW('Sheet 2'!AB$5)+1),ROW(4:4)))} -> 0 | AN8: {=INDEX('Sheet 2'!AB$5:AB$3178,SMALL(IF(AN$3='Sheet 2'!Y$5:Y$3178,ROW('Sheet 2'!AB$5:AB$3178)-ROW('Sheet 2'!AB$5)+1),ROW(4:4)))} -> 0
A9: {=INDEX('Sheet 2'!U$2:U$3178,SMALL(IF(A$3='Sheet 2'!$T$2:$T$3178,ROW('Sheet 2'!U$2:U$3178)-ROW('Sheet 2'!$U$2)+1),ROW(5:5)))} -> CCUR | B9: {=INDEX('Sheet 2'!W$5:W$3178,SMALL(IF(B$3='Sheet 2'!T$5:T$3178,ROW('Sheet 2'!W$5:W$3178)-ROW('Sheet 2'!W$5)+1),ROW(5:5)))} -> 5.42 | C9: {=INDEX('Sheet 2'!W$5:W$3178,SMALL(IF(C$3='Sheet 2'!T$5:T$3178,ROW('Sheet 2'!W$5:W$3178)-ROW('Sheet 2'!W$5)+1),ROW(5:5)))} -> 0 | D9: {=INDEX('Sheet 2'!W$5:W$3178,SMALL(IF(D$3='Sheet 2'!T$5:T$3178,ROW('Sheet 2'!W$5:W$3178)-ROW('Sheet 2'!W$5)+1),ROW(5:5)))} -> 0 | E9: {=INDEX('Sheet 2'!W$5:W$3178,SMALL(IF(E$3='Sheet 2'!T$5:T$3178,ROW('Sheet 2'!W$5:W$3178)-ROW('Sheet 2'!W$5)+1),ROW(5:5)))} -> 0 | F9: {=INDEX('Sheet 2'!W$5:W$3178,SMALL(IF(F$3='Sheet 2'!T$5:T$3178,ROW('Sheet 2'!W$5:W$3178)-ROW('Sheet 2'!W$5)+1),ROW(5:5)))} -> 0 | I9: {=INDEX('Sheet 2'!W$5:W$3178,SMALL(IF(I$3='Sheet 2'!T$5:T$3178,ROW('Sheet 2'!W$5:W$3178)-ROW('Sheet 2'!W$5)+1),ROW(5:5)))} | K9: {=INDEX('Sheet 2'!W$5:W$3178,SMALL(IF(K$3='Sheet 2'!T$5:T$3178,ROW('Sheet 2'!W$5:W$3178)-ROW('Sheet 2'!W$5)+1),ROW(5:5)))} -> #DIV/0! | M9: {=INDEX('Sheet 2'!W$5:W$3178,SMALL(IF(M$3='Sheet 2'!T$5:T$3178,ROW('Sheet 2'!W$5:W$3178)-ROW('Sheet 2'!W$5)+1),ROW(5:5)))} -> #DIV/0! | O9: {=INDEX('Sheet 2'!W$5:W$3178,SMALL(IF(O$3='Sheet 2'!T$5:T$3178,ROW('Sheet 2'!W$5:W$3178)-ROW('Sheet 2'!W$5)+1),ROW(5:5)))} -> #DIV/0! | Q9: {=INDEX('Sheet 2'!W$5:W$3178,SMALL(IF(Q$3='Sheet 2'!T$5:T$3178,ROW('Sheet 2'!W$5:W$3178)-ROW('Sheet 2'!W$5)+1),ROW(5:5)))} -> #DIV/0! | S9: {=INDEX('Sheet 2'!W$5:W$3178,SMALL(IF(S$3='Sheet 2'!T$5:T$3178,ROW('Sheet 2'!W$5:W$3178)-ROW('Sheet 2'!W$5)+1),ROW(5:5)))} -> #DIV/0! | U9: {=INDEX('Sheet 2'!W$5:W$3178,SMALL(IF(U$3='Sheet 2'!T$5:T$3178,ROW('Sheet 2'!W$5:W$3178)-ROW('Sheet 2'!W$5)+1),ROW(5:5)))} -> #NUM! | X9: {=INDEX('Sheet 2'!AB$13:AB$3178,SMALL(IF(X$3='Sheet 2'!Y$13:Y$3178,ROW('Sheet 2'!AB$13:AB$3178)-ROW('Sheet 2'!AB$13)+1),ROW(5:5)))} -> #DIV/0! | Y9: {=INDEX('Sheet 2'!AB$13:AB$3178,SMALL(IF(Y$3='Sheet 2'!Y$13:Y$3178,ROW('Sheet 2'!AB$13:AB$3178)-ROW('Sheet 2'!AB$13)+1),ROW(5:5)))} -> #DIV/0! | Z9: {=INDEX('Sheet 2'!AB$13:AB$3178,SMALL(IF(Z$3='Sheet 2'!Y$13:Y$3178,ROW('Sheet 2'!AB$13:AB$3178)-ROW('Sheet 2'!AB$13)+1),ROW(5:5)))} -> #DIV/0! | AA9: {=INDEX('Sheet 2'!W$5:W$3178,SMALL(IF(AA$3='Sheet 2'!T$5:T$3178,ROW('Sheet 2'!W$5:W$3178)-ROW('Sheet 2'!W$5)+1),ROW(5:5)))} -> #DIV/0! | AB9: {=INDEX('Sheet 2'!W$5:W$3178,SMALL(IF(AB$3='Sheet 2'!T$5:T$3178,ROW('Sheet 2'!W$5:W$3178)-ROW('Sheet 2'!W$5)+1),ROW(5:5)))} -> #DIV/0! | AC9: {=INDEX('Sheet 2'!W$5:W$3178,SMALL(IF(AC$3='Sheet 2'!T$5:T$3178,ROW('Sheet 2'!W$5:W$3178)-ROW('Sheet 2'!W$5)+1),ROW(5:5)))} -> #DIV/0! | AD9: {=INDEX('Sheet 2'!W$5:W$3178,SMALL(IF(AD$3='Sheet 2'!T$5:T$3178,ROW('Sheet 2'!W$5:W$3178)-ROW('Sheet 2'!W$5)+1),ROW(5:5)))} -> #DIV/0! | AE9: {=INDEX('Sheet 2'!W$5:W$3178,SMALL(IF(AE$3='Sheet 2'!T$5:T$3178,ROW('Sheet 2'!W$5:W$3178)-ROW('Sheet 2'!W$5)+1),ROW(5:5)))} -> #DIV/0! | AF9: {=INDEX('Sheet 2'!W$5:W$3178,SMALL(IF(AF$3='Sheet 2'!T$5:T$3178,ROW('Sheet 2'!W$5:W$3178)-ROW('Sheet 2'!W$5)+1),ROW(5:5)))} -> #DIV/0! | AH9: {=INDEX('Sheet 2'!AB$5:AB$3178,SMALL(IF(AH$3='Sheet 2'!Y$5:Y$3178,ROW('Sheet 2'!AB$5:AB$3178)-ROW('Sheet 2'!AB$5)+1),ROW(5:5)))} -> #DIV/0! | AJ9: {=INDEX('Sheet 2'!W$5:W$3178,SMALL(IF(AJ$3='Sheet 2'!T$5:T$3178,ROW('Sheet 2'!W$5:W$3178)-ROW('Sheet 2'!W$5)+1),ROW(5:5)))} -> #NUM! | AL9: {=INDEX('Sheet 2'!AB$5:AB$3178,SMALL(IF(AL$3='Sheet 2'!Y$5:Y$3178,ROW('Sheet 2'!AB$5:AB$3178)-ROW('Sheet 2'!AB$5)+1),ROW(5:5)))} -> #DIV/0! | AN9: {=INDEX('Sheet 2'!AB$5:AB$3178,SMALL(IF(AN$3='Sheet 2'!Y$5:Y$3178,ROW('Sheet 2'!AB$5:AB$3178)-ROW('Sheet 2'!AB$5)+1),ROW(5:5)))} -> #DIV/0!
A10: {=INDEX('Sheet 2'!U$2:U$3178,SMALL(IF(A$3='Sheet 2'!$T$2:$T$3178,ROW('Sheet 2'!U$2:U$3178)-ROW('Sheet 2'!$U$2)+1),ROW(6:6)))} -> CCUR | B10: {=INDEX('Sheet 2'!W$5:W$3178,SMALL(IF(B$3='Sheet 2'!T$5:T$3178,ROW('Sheet 2'!W$5:W$3178)-ROW('Sheet 2'!W$5)+1),ROW(6:6)))} -> 5.42 | C10: {=INDEX('Sheet 2'!W$5:W$3178,SMALL(IF(C$3='Sheet 2'!T$5:T$3178,ROW('Sheet 2'!W$5:W$3178)-ROW('Sheet 2'!W$5)+1),ROW(6:6)))} -> 0 | D10: {=INDEX('Sheet 2'!W$5:W$3178,SMALL(IF(D$3='Sheet 2'!T$5:T$3178,ROW('Sheet 2'!W$5:W$3178)-ROW('Sheet 2'!W$5)+1),ROW(6:6)))} -> 0 | E10: {=INDEX('Sheet 2'!W$5:W$3178,SMALL(IF(E$3='Sheet 2'!T$5:T$3178,ROW('Sheet 2'!W$5:W$3178)-ROW('Sheet 2'!W$5)+1),ROW(6:6)))} -> 0 | F10: {=INDEX('Sheet 2'!W$5:W$3178,SMALL(IF(F$3='Sheet 2'!T$5:T$3178,ROW('Sheet 2'!W$5:W$3178)-ROW('Sheet 2'!W$5)+1),ROW(6:6)))} -> 0 | I10: {=INDEX('Sheet 2'!W$5:W$3178,SMALL(IF(I$3='Sheet 2'!T$5:T$3178,ROW('Sheet 2'!W$5:W$3178)-ROW('Sheet 2'!W$5)+1),ROW(6:6)))} | K10: {=INDEX('Sheet 2'!W$5:W$3178,SMALL(IF(K$3='Sheet 2'!T$5:T$3178,ROW('Sheet 2'!W$5:W$3178)-ROW('Sheet 2'!W$5)+1),ROW(6:6)))} -> #DIV/0! | M10: {=INDEX('Sheet 2'!W$5:W$3178,SMALL(IF(M$3='Sheet 2'!T$5:T$3178,ROW('Sheet 2'!W$5:W$3178)-ROW('Sheet 2'!W$5)+1),ROW(6:6)))} -> #DIV/0! | O10: {=INDEX('Sheet 2'!W$5:W$3178,SMALL(IF(O$3='Sheet 2'!T$5:T$3178,ROW('Sheet 2'!W$5:W$3178)-ROW('Sheet 2'!W$5)+1),ROW(6:6)))} -> #DIV/0! | Q10: {=INDEX('Sheet 2'!W$5:W$3178,SMALL(IF(Q$3='Sheet 2'!T$5:T$3178,ROW('Sheet 2'!W$5:W$3178)-ROW('Sheet 2'!W$5)+1),ROW(6:6)))} -> #DIV/0! | S10: {=INDEX('Sheet 2'!W$5:W$3178,SMALL(IF(S$3='Sheet 2'!T$5:T$3178,ROW('Sheet 2'!W$5:W$3178)-ROW('Sheet 2'!W$5)+1),ROW(6:6)))} -> #DIV/0! | U10: {=INDEX('Sheet 2'!W$5:W$3178,SMALL(IF(U$3='Sheet 2'!T$5:T$3178,ROW('Sheet 2'!W$5:W$3178)-ROW('Sheet 2'!W$5)+1),ROW(6:6)))} -> #NUM! | X10: {=INDEX('Sheet 2'!AB$13:AB$3178,SMALL(IF(X$3='Sheet 2'!Y$13:Y$3178,ROW('Sheet 2'!AB$13:AB$3178)-ROW('Sheet 2'!AB$13)+1),ROW(6:6)))} -> #DIV/0! | Y10: {=INDEX('Sheet 2'!AB$13:AB$3178,SMALL(IF(Y$3='Sheet 2'!Y$13:Y$3178,ROW('Sheet 2'!AB$13:AB$3178)-ROW('Sheet 2'!AB$13)+1),ROW(6:6)))} -> #DIV/0! | Z10: {=INDEX('Sheet 2'!AB$13:AB$3178,SMALL(IF(Z$3='Sheet 2'!Y$13:Y$3178,ROW('Sheet 2'!AB$13:AB$3178)-ROW('Sheet 2'!AB$13)+1),ROW(6:6)))} -> #DIV/0! | AA10: {=INDEX('Sheet 2'!W$5:W$3178,SMALL(IF(AA$3='Sheet 2'!T$5:T$3178,ROW('Sheet 2'!W$5:W$3178)-ROW('Sheet 2'!W$5)+1),ROW(6:6)))} -> #DIV/0! | AB10: {=INDEX('Sheet 2'!W$5:W$3178,SMALL(IF(AB$3='Sheet 2'!T$5:T$3178,ROW('Sheet 2'!W$5:W$3178)-ROW('Sheet 2'!W$5)+1),ROW(6:6)))} -> #DIV/0! | AC10: {=INDEX('Sheet 2'!W$5:W$3178,SMALL(IF(AC$3='Sheet 2'!T$5:T$3178,ROW('Sheet 2'!W$5:W$3178)-ROW('Sheet 2'!W$5)+1),ROW(6:6)))} -> #DIV/0! | AD10: {=INDEX('Sheet 2'!W$5:W$3178,SMALL(IF(AD$3='Sheet 2'!T$5:T$3178,ROW('Sheet 2'!W$5:W$3178)-ROW('Sheet 2'!W$5)+1),ROW(6:6)))} -> #DIV/0! | AE10: {=INDEX('Sheet 2'!W$5:W$3178,SMALL(IF(AE$3='Sheet 2'!T$5:T$3178,ROW('Sheet 2'!W$5:W$3178)-ROW('Sheet 2'!W$5)+1),ROW(6:6)))} -> #DIV/0! | AF10: {=INDEX('Sheet 2'!W$5:W$3178,SMALL(IF(AF$3='Sheet 2'!T$5:T$3178,ROW('Sheet 2'!W$5:W$3178)-ROW('Sheet 2'!W$5)+1),ROW(6:6)))} -> #DIV/0! | AH10: {=INDEX('Sheet 2'!AB$5:AB$3178,SMALL(IF(AH$3='Sheet 2'!Y$5:Y$3178,ROW('Sheet 2'!AB$5:AB$3178)-ROW('Sheet 2'!AB$5)+1),ROW(6:6)))} -> 0 | AJ10: {=INDEX('Sheet 2'!W$5:W$3178,SMALL(IF(AJ$3='Sheet 2'!T$5:T$3178,ROW('Sheet 2'!W$5:W$3178)-ROW('Sheet 2'!W$5)+1),ROW(6:6)))} -> #NUM! | AL10: {=INDEX('Sheet 2'!AB$5:AB$3178,SMALL(IF(AL$3='Sheet 2'!Y$5:Y$3178,ROW('Sheet 2'!AB$5:AB$3178)-ROW('Sheet 2'!AB$5)+1),ROW(6:6)))} -> 0 | AN10: {=INDEX('Sheet 2'!AB$5:AB$3178,SMALL(IF(AN$3='Sheet 2'!Y$5:Y$3178,ROW('Sheet 2'!AB$5:AB$3178)-ROW('Sheet 2'!AB$5)+1),ROW(6:6)))} -> 0
A11: {=INDEX('Sheet 2'!U$2:U$3178,SMALL(IF(A$3='Sheet 2'!$T$2:$T$3178,ROW('Sheet 2'!U$2:U$3178)-ROW('Sheet 2'!$U$2)+1),ROW(7:7)))} -> CCUR | B11: {=INDEX('Sheet 2'!W$5:W$3178,SMALL(IF(B$3='Sheet 2'!T$5:T$3178,ROW('Sheet 2'!W$5:W$3178)-ROW('Sheet 2'!W$5)+1),ROW(7:7)))} -> 5.42 | C11: {=INDEX('Sheet 2'!W$5:W$3178,SMALL(IF(C$3='Sheet 2'!T$5:T$3178,ROW('Sheet 2'!W$5:W$3178)-ROW('Sheet 2'!W$5)+1),ROW(7:7)))} -> 0 | D11: {=INDEX('Sheet 2'!W$5:W$3178,SMALL(IF(D$3='Sheet 2'!T$5:T$3178,ROW('Sheet 2'!W$5:W$3178)-ROW('Sheet 2'!W$5)+1),ROW(7:7)))} -> 0 | E11: {=INDEX('Sheet 2'!W$5:W$3178,SMALL(IF(E$3='Sheet 2'!T$5:T$3178,ROW('Sheet 2'!W$5:W$3178)-ROW('Sheet 2'!W$5)+1),ROW(7:7)))} -> 0 | F11: {=INDEX('Sheet 2'!W$5:W$3178,SMALL(IF(F$3='Sheet 2'!T$5:T$3178,ROW('Sheet 2'!W$5:W$3178)-ROW('Sheet 2'!W$5)+1),ROW(7:7)))} -> 0 | I11: {=INDEX('Sheet 2'!W$5:W$3178,SMALL(IF(I$3='Sheet 2'!T$5:T$3178,ROW('Sheet 2'!W$5:W$3178)-ROW('Sheet 2'!W$5)+1),ROW(7:7)))} | K11: {=INDEX('Sheet 2'!W$5:W$3178,SMALL(IF(K$3='Sheet 2'!T$5:T$3178,ROW('Sheet 2'!W$5:W$3178)-ROW('Sheet 2'!W$5)+1),ROW(7:7)))} -> #DIV/0! | M11: {=INDEX('Sheet 2'!W$5:W$3178,SMALL(IF(M$3='Sheet 2'!T$5:T$3178,ROW('Sheet 2'!W$5:W$3178)-ROW('Sheet 2'!W$5)+1),ROW(7:7)))} -> #DIV/0! | O11: {=INDEX('Sheet 2'!W$5:W$3178,SMALL(IF(O$3='Sheet 2'!T$5:T$3178,ROW('Sheet 2'!W$5:W$3178)-ROW('Sheet 2'!W$5)+1),ROW(7:7)))} -> #DIV/0! | Q11: {=INDEX('Sheet 2'!W$5:W$3178,SMALL(IF(Q$3='Sheet 2'!T$5:T$3178,ROW('Sheet 2'!W$5:W$3178)-ROW('Sheet 2'!W$5)+1),ROW(7:7)))} -> #DIV/0! | S11: {=INDEX('Sheet 2'!W$5:W$3178,SMALL(IF(S$3='Sheet 2'!T$5:T$3178,ROW('Sheet 2'!W$5:W$3178)-ROW('Sheet 2'!W$5)+1),ROW(7:7)))} -> #DIV/0! | U11: {=INDEX('Sheet 2'!W$5:W$3178,SMALL(IF(U$3='Sheet 2'!T$5:T$3178,ROW('Sheet 2'!W$5:W$3178)-ROW('Sheet 2'!W$5)+1),ROW(7:7)))} -> #NUM! | X11: {=INDEX('Sheet 2'!AB$13:AB$3178,SMALL(IF(X$3='Sheet 2'!Y$13:Y$3178,ROW('Sheet 2'!AB$13:AB$3178)-ROW('Sheet 2'!AB$13)+1),ROW(7:7)))} -> #DIV/0! | Y11: {=INDEX('Sheet 2'!AB$13:AB$3178,SMALL(IF(Y$3='Sheet 2'!Y$13:Y$3178,ROW('Sheet 2'!AB$13:AB$3178)-ROW('Sheet 2'!AB$13)+1),ROW(7:7)))} -> #DIV/0! | Z11: {=INDEX('Sheet 2'!AB$13:AB$3178,SMALL(IF(Z$3='Sheet 2'!Y$13:Y$3178,ROW('Sheet 2'!AB$13:AB$3178)-ROW('Sheet 2'!AB$13)+1),ROW(7:7)))} -> #DIV/0! | AA11: {=INDEX('Sheet 2'!W$5:W$3178,SMALL(IF(AA$3='Sheet 2'!T$5:T$3178,ROW('Sheet 2'!W$5:W$3178)-ROW('Sheet 2'!W$5)+1),ROW(7:7)))} -> #DIV/0! | AB11: {=INDEX('Sheet 2'!W$5:W$3178,SMALL(IF(AB$3='Sheet 2'!T$5:T$3178,ROW('Sheet 2'!W$5:W$3178)-ROW('Sheet 2'!W$5)+1),ROW(7:7)))} -> #DIV/0! | AC11: {=INDEX('Sheet 2'!W$5:W$3178,SMALL(IF(AC$3='Sheet 2'!T$5:T$3178,ROW('Sheet 2'!W$5:W$3178)-ROW('Sheet 2'!W$5)+1),ROW(7:7)))} -> #DIV/0! | AD11: {=INDEX('Sheet 2'!W$5:W$3178,SMALL(IF(AD$3='Sheet 2'!T$5:T$3178,ROW('Sheet 2'!W$5:W$3178)-ROW('Sheet 2'!W$5)+1),ROW(7:7)))} -> #DIV/0! | AE11: {=INDEX('Sheet 2'!W$5:W$3178,SMALL(IF(AE$3='Sheet 2'!T$5:T$3178,ROW('Sheet 2'!W$5:W$3178)-ROW('Sheet 2'!W$5)+1),ROW(7:7)))} -> #DIV/0! | AF11: {=INDEX('Sheet 2'!W$5:W$3178,SMALL(IF(AF$3='Sheet 2'!T$5:T$3178,ROW('Sheet 2'!W$5:W$3178)-ROW('Sheet 2'!W$5)+1),ROW(7:7)))} -> #DIV/0! | AH11: {=INDEX('Sheet 2'!AB$5:AB$3178,SMALL(IF(AH$3='Sheet 2'!Y$5:Y$3178,ROW('Sheet 2'!AB$5:AB$3178)-ROW('Sheet 2'!AB$5)+1),ROW(7:7)))} -> #DIV/0! | AJ11: {=INDEX('Sheet 2'!W$5:W$3178,SMALL(IF(AJ$3='Sheet 2'!T$5:T$3178,ROW('Sheet 2'!W$5:W$3178)-ROW('Sheet 2'!W$5)+1),ROW(7:7)))} -> #NUM! | AL11: {=INDEX('Sheet 2'!AB$5:AB$3178,SMALL(IF(AL$3='Sheet 2'!Y$5:Y$3178,ROW('Sheet 2'!AB$5:AB$3178)-ROW('Sheet 2'!AB$5)+1),ROW(7:7)))} -> #DIV/0! | AN11: {=INDEX('Sheet 2'!AB$5:AB$3178,SMALL(IF(AN$3='Sheet 2'!Y$5:Y$3178,ROW('Sheet 2'!AB$5:AB$3178)-ROW('Sheet 2'!AB$5)+1),ROW(7:7)))} -> #DIV/0!
A12: {=INDEX('Sheet 2'!U$2:U$3178,SMALL(IF(A$3='Sheet 2'!$T$2:$T$3178,ROW('Sheet 2'!U$2:U$3178)-ROW('Sheet 2'!$U$2)+1),ROW(8:8)))} -> CCUR | B12: {=INDEX('Sheet 2'!W$5:W$3178,SMALL(IF(B$3='Sheet 2'!T$5:T$3178,ROW('Sheet 2'!W$5:W$3178)-ROW('Sheet 2'!W$5)+1),ROW(8:8)))} -> 5.42 | C12: {=INDEX('Sheet 2'!W$5:W$3178,SMALL(IF(C$3='Sheet 2'!T$5:T$3178,ROW('Sheet 2'!W$5:W$3178)-ROW('Sheet 2'!W$5)+1),ROW(8:8)))} -> 0 | D12: {=INDEX('Sheet 2'!W$5:W$3178,SMALL(IF(D$3='Sheet 2'!T$5:T$3178,ROW('Sheet 2'!W$5:W$3178)-ROW('Sheet 2'!W$5)+1),ROW(8:8)))} -> 0 | E12: {=INDEX('Sheet 2'!W$5:W$3178,SMALL(IF(E$3='Sheet 2'!T$5:T$3178,ROW('Sheet 2'!W$5:W$3178)-ROW('Sheet 2'!W$5)+1),ROW(8:8)))} -> 0 | F12: {=INDEX('Sheet 2'!W$5:W$3178,SMALL(IF(F$3='Sheet 2'!T$5:T$3178,ROW('Sheet 2'!W$5:W$3178)-ROW('Sheet 2'!W$5)+1),ROW(8:8)))} -> 0 | I12: {=INDEX('Sheet 2'!W$5:W$3178,SMALL(IF(I$3='Sheet 2'!T$5:T$3178,ROW('Sheet 2'!W$5:W$3178)-ROW('Sheet 2'!W$5)+1),ROW(8:8)))} | K12: {=INDEX('Sheet 2'!W$5:W$3178,SMALL(IF(K$3='Sheet 2'!T$5:T$3178,ROW('Sheet 2'!W$5:W$3178)-ROW('Sheet 2'!W$5)+1),ROW(8:8)))} -> #DIV/0! | M12: {=INDEX('Sheet 2'!W$5:W$3178,SMALL(IF(M$3='Sheet 2'!T$5:T$3178,ROW('Sheet 2'!W$5:W$3178)-ROW('Sheet 2'!W$5)+1),ROW(8:8)))} -> #DIV/0! | O12: {=INDEX('Sheet 2'!W$5:W$3178,SMALL(IF(O$3='Sheet 2'!T$5:T$3178,ROW('Sheet 2'!W$5:W$3178)-ROW('Sheet 2'!W$5)+1),ROW(8:8)))} -> #DIV/0! | Q12: {=INDEX('Sheet 2'!W$5:W$3178,SMALL(IF(Q$3='Sheet 2'!T$5:T$3178,ROW('Sheet 2'!W$5:W$3178)-ROW('Sheet 2'!W$5)+1),ROW(8:8)))} -> #DIV/0! | S12: {=INDEX('Sheet 2'!W$5:W$3178,SMALL(IF(S$3='Sheet 2'!T$5:T$3178,ROW('Sheet 2'!W$5:W$3178)-ROW('Sheet 2'!W$5)+1),ROW(8:8)))} -> #DIV/0! | U12: {=INDEX('Sheet 2'!W$5:W$3178,SMALL(IF(U$3='Sheet 2'!T$5:T$3178,ROW('Sheet 2'!W$5:W$3178)-ROW('Sheet 2'!W$5)+1),ROW(8:8)))} -> #NUM! | X12: {=INDEX('Sheet 2'!AB$13:AB$3178,SMALL(IF(X$3='Sheet 2'!Y$13:Y$3178,ROW('Sheet 2'!AB$13:AB$3178)-ROW('Sheet 2'!AB$13)+1),ROW(8:8)))} -> #DIV/0! | Y12: {=INDEX('Sheet 2'!AB$13:AB$3178,SMALL(IF(Y$3='Sheet 2'!Y$13:Y$3178,ROW('Sheet 2'!AB$13:AB$3178)-ROW('Sheet 2'!AB$13)+1),ROW(8:8)))} -> #DIV/0! | Z12: {=INDEX('Sheet 2'!AB$13:AB$3178,SMALL(IF(Z$3='Sheet 2'!Y$13:Y$3178,ROW('Sheet 2'!AB$13:AB$3178)-ROW('Sheet 2'!AB$13)+1),ROW(8:8)))} -> #DIV/0! | AA12: {=INDEX('Sheet 2'!W$5:W$3178,SMALL(IF(AA$3='Sheet 2'!T$5:T$3178,ROW('Sheet 2'!W$5:W$3178)-ROW('Sheet 2'!W$5)+1),ROW(8:8)))} -> #DIV/0! | AB12: {=INDEX('Sheet 2'!W$5:W$3178,SMALL(IF(AB$3='Sheet 2'!T$5:T$3178,ROW('Sheet 2'!W$5:W$3178)-ROW('Sheet 2'!W$5)+1),ROW(8:8)))} -> #DIV/0! | AC12: {=INDEX('Sheet 2'!W$5:W$3178,SMALL(IF(AC$3='Sheet 2'!T$5:T$3178,ROW('Sheet 2'!W$5:W$3178)-ROW('Sheet 2'!W$5)+1),ROW(8:8)))} -> #DIV/0! | AD12: {=INDEX('Sheet 2'!W$5:W$3178,SMALL(IF(AD$3='Sheet 2'!T$5:T$3178,ROW('Sheet 2'!W$5:W$3178)-ROW('Sheet 2'!W$5)+1),ROW(8:8)))} -> #DIV/0! | AE12: {=INDEX('Sheet 2'!W$5:W$3178,SMALL(IF(AE$3='Sheet 2'!T$5:T$3178,ROW('Sheet 2'!W$5:W$3178)-ROW('Sheet 2'!W$5)+1),ROW(8:8)))} -> #DIV/0! | AF12: {=INDEX('Sheet 2'!W$5:W$3178,SMALL(IF(AF$3='Sheet 2'!T$5:T$3178,ROW('Sheet 2'!W$5:W$3178)-ROW('Sheet 2'!W$5)+1),ROW(8:8)))} -> #DIV/0! | AH12: {=INDEX('Sheet 2'!AB$5:AB$3178,SMALL(IF(AH$3='Sheet 2'!Y$5:Y$3178,ROW('Sheet 2'!AB$5:AB$3178)-ROW('Sheet 2'!AB$5)+1),ROW(8:8)))} -> 0 | AJ12: {=INDEX('Sheet 2'!W$5:W$3178,SMALL(IF(AJ$3='Sheet 2'!T$5:T$3178,ROW('Sheet 2'!W$5:W$3178)-ROW('Sheet 2'!W$5)+1),ROW(8:8)))} -> #NUM! | AL12: {=INDEX('Sheet 2'!AB$5:AB$3178,SMALL(IF(AL$3='Sheet 2'!Y$5:Y$3178,ROW('Sheet 2'!AB$5:AB$3178)-ROW('Sheet 2'!AB$5)+1),ROW(8:8)))} -> 0 | AN12: {=INDEX('Sheet 2'!AB$5:AB$3178,SMALL(IF(AN$3='Sheet 2'!Y$5:Y$3178,ROW('Sheet 2'!AB$5:AB$3178)-ROW('Sheet 2'!AB$5)+1),ROW(8:8)))} -> 0
A13: {=INDEX('Sheet 2'!U$2:U$3178,SMALL(IF(A$3='Sheet 2'!$T$2:$T$3178,ROW('Sheet 2'!U$2:U$3178)-ROW('Sheet 2'!$U$2)+1),ROW(9:9)))} -> CCUR | B13: {=INDEX('Sheet 2'!W$5:W$3178,SMALL(IF(B$3='Sheet 2'!T$5:T$3178,ROW('Sheet 2'!W$5:W$3178)-ROW('Sheet 2'!W$5)+1),ROW(9:9)))} -> 5.42 | C13: {=INDEX('Sheet 2'!W$5:W$3178,SMALL(IF(C$3='Sheet 2'!T$5:T$3178,ROW('Sheet 2'!W$5:W$3178)-ROW('Sheet 2'!W$5)+1),ROW(9:9)))} -> 0 | D13: {=INDEX('Sheet 2'!W$5:W$3178,SMALL(IF(D$3='Sheet 2'!T$5:T$3178,ROW('Sheet 2'!W$5:W$3178)-ROW('Sheet 2'!W$5)+1),ROW(9:9)))} -> 0 | E13: {=INDEX('Sheet 2'!W$5:W$3178,SMALL(IF(E$3='Sheet 2'!T$5:T$3178,ROW('Sheet 2'!W$5:W$3178)-ROW('Sheet 2'!W$5)+1),ROW(9:9)))} -> 0 | F13: {=INDEX('Sheet 2'!W$5:W$3178,SMALL(IF(F$3='Sheet 2'!T$5:T$3178,ROW('Sheet 2'!W$5:W$3178)-ROW('Sheet 2'!W$5)+1),ROW(9:9)))} -> 0 | I13: {=INDEX('Sheet 2'!W$5:W$3178,SMALL(IF(I$3='Sheet 2'!T$5:T$3178,ROW('Sheet 2'!W$5:W$3178)-ROW('Sheet 2'!W$5)+1),ROW(9:9)))} | K13: {=INDEX('Sheet 2'!W$5:W$3178,SMALL(IF(K$3='Sheet 2'!T$5:T$3178,ROW('Sheet 2'!W$5:W$3178)-ROW('Sheet 2'!W$5)+1),ROW(9:9)))} -> #DIV/0! | M13: {=INDEX('Sheet 2'!W$5:W$3178,SMALL(IF(M$3='Sheet 2'!T$5:T$3178,ROW('Sheet 2'!W$5:W$3178)-ROW('Sheet 2'!W$5)+1),ROW(9:9)))} -> #DIV/0! | O13: {=INDEX('Sheet 2'!W$5:W$3178,SMALL(IF(O$3='Sheet 2'!T$5:T$3178,ROW('Sheet 2'!W$5:W$3178)-ROW('Sheet 2'!W$5)+1),ROW(9:9)))} -> #DIV/0! | Q13: {=INDEX('Sheet 2'!W$5:W$3178,SMALL(IF(Q$3='Sheet 2'!T$5:T$3178,ROW('Sheet 2'!W$5:W$3178)-ROW('Sheet 2'!W$5)+1),ROW(9:9)))} -> #DIV/0! | S13: {=INDEX('Sheet 2'!W$5:W$3178,SMALL(IF(S$3='Sheet 2'!T$5:T$3178,ROW('Sheet 2'!W$5:W$3178)-ROW('Sheet 2'!W$5)+1),ROW(9:9)))} -> #DIV/0! | U13: {=INDEX('Sheet 2'!W$5:W$3178,SMALL(IF(U$3='Sheet 2'!T$5:T$3178,ROW('Sheet 2'!W$5:W$3178)-ROW('Sheet 2'!W$5)+1),ROW(9:9)))} -> #NUM! | X13: {=INDEX('Sheet 2'!AB$13:AB$3178,SMALL(IF(X$3='Sheet 2'!Y$13:Y$3178,ROW('Sheet 2'!AB$13:AB$3178)-ROW('Sheet 2'!AB$13)+1),ROW(9:9)))} -> #DIV/0! | Y13: {=INDEX('Sheet 2'!AB$13:AB$3178,SMALL(IF(Y$3='Sheet 2'!Y$13:Y$3178,ROW('Sheet 2'!AB$13:AB$3178)-ROW('Sheet 2'!AB$13)+1),ROW(9:9)))} -> #DIV/0! | Z13: {=INDEX('Sheet 2'!AB$13:AB$3178,SMALL(IF(Z$3='Sheet 2'!Y$13:Y$3178,ROW('Sheet 2'!AB$13:AB$3178)-ROW('Sheet 2'!AB$13)+1),ROW(9:9)))} -> #DIV/0! | AA13: {=INDEX('Sheet 2'!W$5:W$3178,SMALL(IF(AA$3='Sheet 2'!T$5:T$3178,ROW('Sheet 2'!W$5:W$3178)-ROW('Sheet 2'!W$5)+1),ROW(9:9)))} -> #DIV/0! | AB13: {=INDEX('Sheet 2'!W$5:W$3178,SMALL(IF(AB$3='Sheet 2'!T$5:T$3178,ROW('Sheet 2'!W$5:W$3178)-ROW('Sheet 2'!W$5)+1),ROW(9:9)))} -> #DIV/0! | AC13: {=INDEX('Sheet 2'!W$5:W$3178,SMALL(IF(AC$3='Sheet 2'!T$5:T$3178,ROW('Sheet 2'!W$5:W$3178)-ROW('Sheet 2'!W$5)+1),ROW(9:9)))} -> #DIV/0! | AD13: {=INDEX('Sheet 2'!W$5:W$3178,SMALL(IF(AD$3='Sheet 2'!T$5:T$3178,ROW('Sheet 2'!W$5:W$3178)-ROW('Sheet 2'!W$5)+1),ROW(9:9)))} -> #DIV/0! | AE13: {=INDEX('Sheet 2'!W$5:W$3178,SMALL(IF(AE$3='Sheet 2'!T$5:T$3178,ROW('Sheet 2'!W$5:W$3178)-ROW('Sheet 2'!W$5)+1),ROW(9:9)))} -> #DIV/0! | AF13: {=INDEX('Sheet 2'!W$5:W$3178,SMALL(IF(AF$3='Sheet 2'!T$5:T$3178,ROW('Sheet 2'!W$5:W$3178)-ROW('Sheet 2'!W$5)+1),ROW(9:9)))} -> #DIV/0! | AH13: {=INDEX('Sheet 2'!AB$5:AB$3178,SMALL(IF(AH$3='Sheet 2'!Y$5:Y$3178,ROW('Sheet 2'!AB$5:AB$3178)-ROW('Sheet 2'!AB$5)+1),ROW(9:9)))} -> #DIV/0! | AJ13: {=INDEX('Sheet 2'!W$5:W$3178,SMALL(IF(AJ$3='Sheet 2'!T$5:T$3178,ROW('Sheet 2'!W$5:W$3178)-ROW('Sheet 2'!W$5)+1),ROW(9:9)))} -> #NUM! | AL13: {=INDEX('Sheet 2'!AB$5:AB$3178,SMALL(IF(AL$3='Sheet 2'!Y$5:Y$3178,ROW('Sheet 2'!AB$5:AB$3178)-ROW('Sheet 2'!AB$5)+1),ROW(9:9)))} -> #DIV/0! | AN13: {=INDEX('Sheet 2'!AB$5:AB$3178,SMALL(IF(AN$3='Sheet 2'!Y$5:Y$3178,ROW('Sheet 2'!AB$5:AB$3178)-ROW('Sheet 2'!AB$5)+1),ROW(9:9)))} -> #DIV/0!
A14: {=INDEX('Sheet 2'!U$2:U$3178,SMALL(IF(A$3='Sheet 2'!$T$2:$T$3178,ROW('Sheet 2'!U$2:U$3178)-ROW('Sheet 2'!$U$2)+1),ROW(10:10)))} -> CCUR | B14: {=INDEX('Sheet 2'!W$5:W$3178,SMALL(IF(B$3='Sheet 2'!T$5:T$3178,ROW('Sheet 2'!W$5:W$3178)-ROW('Sheet 2'!W$5)+1),ROW(10:10)))} -> 5.42 | C14: {=INDEX('Sheet 2'!W$5:W$3178,SMALL(IF(C$3='Sheet 2'!T$5:T$3178,ROW('Sheet 2'!W$5:W$3178)-ROW('Sheet 2'!W$5)+1),ROW(10:10)))} -> 0 | D14: {=INDEX('Sheet 2'!W$5:W$3178,SMALL(IF(D$3='Sheet 2'!T$5:T$3178,ROW('Sheet 2'!W$5:W$3178)-ROW('Sheet 2'!W$5)+1),ROW(10:10)))} -> 0 | E14: {=INDEX('Sheet 2'!W$5:W$3178,SMALL(IF(E$3='Sheet 2'!T$5:T$3178,ROW('Sheet 2'!W$5:W$3178)-ROW('Sheet 2'!W$5)+1),ROW(10:10)))} -> 0 | F14: {=INDEX('Sheet 2'!W$5:W$3178,SMALL(IF(F$3='Sheet 2'!T$5:T$3178,ROW('Sheet 2'!W$5:W$3178)-ROW('Sheet 2'!W$5)+1),ROW(10:10)))} -> 0 | I14: {=INDEX('Sheet 2'!W$5:W$3178,SMALL(IF(I$3='Sheet 2'!T$5:T$3178,ROW('Sheet 2'!W$5:W$3178)-ROW('Sheet 2'!W$5)+1),ROW(10:10)))} | K14: {=INDEX('Sheet 2'!W$5:W$3178,SMALL(IF(K$3='Sheet 2'!T$5:T$3178,ROW('Sheet 2'!W$5:W$3178)-ROW('Sheet 2'!W$5)+1),ROW(10:10)))} -> #DIV/0! | M14: {=INDEX('Sheet 2'!W$5:W$3178,SMALL(IF(M$3='Sheet 2'!T$5:T$3178,ROW('Sheet 2'!W$5:W$3178)-ROW('Sheet 2'!W$5)+1),ROW(10:10)))} -> #DIV/0! | O14: {=INDEX('Sheet 2'!W$5:W$3178,SMALL(IF(O$3='Sheet 2'!T$5:T$3178,ROW('Sheet 2'!W$5:W$3178)-ROW('Sheet 2'!W$5)+1),ROW(10:10)))} -> #DIV/0! | Q14: {=INDEX('Sheet 2'!W$5:W$3178,SMALL(IF(Q$3='Sheet 2'!T$5:T$3178,ROW('Sheet 2'!W$5:W$3178)-ROW('Sheet 2'!W$5)+1),ROW(10:10)))} -> #DIV/0! | S14: {=INDEX('Sheet 2'!W$5:W$3178,SMALL(IF(S$3='Sheet 2'!T$5:T$3178,ROW('Sheet 2'!W$5:W$3178)-ROW('Sheet 2'!W$5)+1),ROW(10:10)))} -> #DIV/0! | U14: {=INDEX('Sheet 2'!W$5:W$3178,SMALL(IF(U$3='Sheet 2'!T$5:T$3178,ROW('Sheet 2'!W$5:W$3178)-ROW('Sheet 2'!W$5)+1),ROW(10:10)))} -> #NUM! | X14: {=INDEX('Sheet 2'!AB$13:AB$3178,SMALL(IF(X$3='Sheet 2'!Y$13:Y$3178,ROW('Sheet 2'!AB$13:AB$3178)-ROW('Sheet 2'!AB$13)+1),ROW(10:10)))} -> #DIV/0! | Y14: {=INDEX('Sheet 2'!AB$13:AB$3178,SMALL(IF(Y$3='Sheet 2'!Y$13:Y$3178,ROW('Sheet 2'!AB$13:AB$3178)-ROW('Sheet 2'!AB$13)+1),ROW(10:10)))} -> #DIV/0! | Z14: {=INDEX('Sheet 2'!AB$13:AB$3178,SMALL(IF(Z$3='Sheet 2'!Y$13:Y$3178,ROW('Sheet 2'!AB$13:AB$3178)-ROW('Sheet 2'!AB$13)+1),ROW(10:10)))} -> #DIV/0! | AA14: {=INDEX('Sheet 2'!W$5:W$3178,SMALL(IF(AA$3='Sheet 2'!T$5:T$3178,ROW('Sheet 2'!W$5:W$3178)-ROW('Sheet 2'!W$5)+1),ROW(10:10)))} -> #DIV/0! | AB14: {=INDEX('Sheet 2'!W$5:W$3178,SMALL(IF(AB$3='Sheet 2'!T$5:T$3178,ROW('Sheet 2'!W$5:W$3178)-ROW('Sheet 2'!W$5)+1),ROW(10:10)))} -> #DIV/0! | AC14: {=INDEX('Sheet 2'!W$5:W$3178,SMALL(IF(AC$3='Sheet 2'!T$5:T$3178,ROW('Sheet 2'!W$5:W$3178)-ROW('Sheet 2'!W$5)+1),ROW(10:10)))} -> #DIV/0! | AD14: {=INDEX('Sheet 2'!W$5:W$3178,SMALL(IF(AD$3='Sheet 2'!T$5:T$3178,ROW('Sheet 2'!W$5:W$3178)-ROW('Sheet 2'!W$5)+1),ROW(10:10)))} -> #DIV/0! | AE14: {=INDEX('Sheet 2'!W$5:W$3178,SMALL(IF(AE$3='Sheet 2'!T$5:T$3178,ROW('Sheet 2'!W$5:W$3178)-ROW('Sheet 2'!W$5)+1),ROW(10:10)))} -> #DIV/0! | AF14: {=INDEX('Sheet 2'!W$5:W$3178,SMALL(IF(AF$3='Sheet 2'!T$5:T$3178,ROW('Sheet 2'!W$5:W$3178)-ROW('Sheet 2'!W$5)+1),ROW(10:10)))} -> #DIV/0! | AH14: {=INDEX('Sheet 2'!AB$5:AB$3178,SMALL(IF(AH$3='Sheet 2'!Y$5:Y$3178,ROW('Sheet 2'!AB$5:AB$3178)-ROW('Sheet 2'!AB$5)+1),ROW(10:10)))} -> 0 | AJ14: {=INDEX('Sheet 2'!W$5:W$3178,SMALL(IF(AJ$3='Sheet 2'!T$5:T$3178,ROW('Sheet 2'!W$5:W$3178)-ROW('Sheet 2'!W$5)+1),ROW(10:10)))} -> #NUM! | AL14: {=INDEX('Sheet 2'!AB$5:AB$3178,SMALL(IF(AL$3='Sheet 2'!Y$5:Y$3178,ROW('Sheet 2'!AB$5:AB$3178)-ROW('Sheet 2'!AB$5)+1),ROW(10:10)))} -> 0 | AN14: {=INDEX('Sheet 2'!AB$5:AB$3178,SMALL(IF(AN$3='Sheet 2'!Y$5:Y$3178,ROW('Sheet 2'!AB$5:AB$3178)-ROW('Sheet 2'!AB$5)+1),ROW(10:10)))} -> 0

Sheet Sheet 2
A2: 1 | T2: Symbol | U2: AES
D4: Income Statement | F4: Q2 2018 | G4: Q3 2018 | H4: Q4 2018 | I4: Q1 2019 | J4: Q2 2019 | K4: TTM | M4: 2014 | N4: 2015 | O4: 2016 | P4: 2017 | Q4: 2018 | T4: Quote | Y4: Growth | AB4: 5-Year Average | AD4: Key Ratios ― Growth, YOY | AG4: =N4 -> 2015 | AH4: =O4 -> 2016 | AI4: =P4 -> 2017 | AJ4: =Q4 -> 2018
D5: Gross Profit | F5: 600000000 | G5: 671000000 | H5: 646000000 | I5: 586000000 | J5: 502000000 | K5: 2405000000 | M5: 3088000000 | N5: 2866000000 | O5: 2433000000 | P5: 2464000000 | Q5: 2573000000 | T5: Last Price | W5: 14.77 | Y5: Revenue | AB5: =IF(AB4="Year over Year",AJ6,IF(AB4="3-Year Average",AVERAGE(AI6:AJ6),IF(AB4="5-Year Average",AVERAGE(AG6:AJ6),""))) -> -0.1061799
D6: Total Revenue | F6: 2537000000 | G6: 2837000000 | H6: 2622000000 | I6: 2650000000 | J6: 2483000000 | K6: 10592000000 | M6: 17146000000 | N6: 14963000000 | O6: 13586000000 | P6: 10530000000 | Q6: 10736000000 | T6: Market Capitalization | W6: =W5*J27 -> 9.8042905e+09 | Y6: Operating Income | AB6: =IF(AB4="Year over Year",AJ7,IF(AB4="3-Year Average",AVERAGE(AI7:AJ7),IF(AB4="5-Year Average",AVERAGE(AG7:AJ7),""))) -> -0.043849644 | AD6: Revenue % | AG6: =IF(AND(N6>0,M6>0,M6<>""),N6/M6-1,IF(AND(M6<0,N6<0,M6<>""),(N6-M6)/ABS(M6),IF(AND(M6>0,N6<0,M6<>""),"L",IF(AND(M6<0,N6>0,M6<>""),"P","")))) -> -0.12731832 | AH6: =IF(AND(O6>0,N6>0,N6<>""),O6/N6-1,IF(AND(N6<0,O6<0,N6<>""),(O6-N6)/ABS(N6),IF(AND(N6>0,O6<0,N6<>""),"L",IF(AND(N6<0,O6>0,N6<>""),"P","")))) -> -0.092027 | AI6: =IF(AND(P6>0,O6>0,O6<>""),P6/O6-1,IF(AND(O6<0,P6<0,O6<>""),(P6-O6)/ABS(O6),IF(AND(O6>0,P6<0,O6<>""),"L",IF(AND(O6<0,P6>0,O6<>""),"P","")))) -> -0.22493744 | AJ6: =IF(AND(Q6>0,P6>0,P6<>""),Q6/P6-1,IF(AND(P6<0,Q6<0,P6<>""),(Q6-P6)/ABS(P6),IF(AND(P6>0,Q6<0,P6<>""),"L",IF(AND(P6<0,Q6>0,P6<>""),"P","")))) -> 0.019563153
D7: Cost of Revenue | F7: -1937000000 | G7: -2166000000 | H7: -1976000000 | I7: -2064000000 | J7: -1981000000 | K7: -8187000000 | M7: -14058000000 | N7: -12097000000 | O7: -11153000000 | P7: -8066000000 | Q7: -8163000000 | T7: Enterprise Value | W7: =W6+(J24+J25)-J21 -> 2.839029e+10 | Y7: Net Income | AB7: =IF(AB4="Year over Year",AJ8,IF(AB4="3-Year Average",AVERAGE(AI8:AJ8),IF(AB4="5-Year Average",AVERAGE(AG8:AJ8),""))) -> -0.31475713 | AD7: Operating Income % | AG7: =IF(AND(N8>0,M8>0,M8<>""),N8/M8-1,IF(AND(M8<0,N8<0,M8<>""),(N8-M8)/ABS(M8),IF(AND(M8>0,N8<0,M8<>""),"L",IF(AND(M8<0,N8>0,M8<>""),"P","")))) -> -0.073767666 | AH7: =IF(AND(O8>0,N8>0,N8<>""),O8/N8-1,IF(AND(N8<0,O8<0,N8<>""),(O8-N8)/ABS(N8),IF(AND(N8>0,O8<0,N8<>""),"L",IF(AND(N8<0,O8>0,N8<>""),"P","")))) -> -0.17528843 | AI7: =IF(AND(P8>0,O8>0,O8<>""),P8/O8-1,IF(AND(O8<0,P8<0,O8<>""),(P8-O8)/ABS(O8),IF(AND(O8>0,P8<0,O8<>""),"L",IF(AND(O8<0,P8>0,O8<>""),"P","")))) -> 0.026624549 | AJ7: =IF(AND(Q8>0,P8>0,P8<>""),Q8/P8-1,IF(AND(P8<0,Q8<0,P8<>""),(Q8-P8)/ABS(P8),IF(AND(P8>0,Q8<0,P8<>""),"L",IF(AND(P8<0,Q8>0,P8<>""),"P","")))) -> 0.047032967
D8: Total Operating Profit/Loss | F8: 567000000 | G8: 629000000 | H8: 581000000 | I8: 541000000 | J8: 454000000 | K8: 2205000000 | M8: 2901000000 | N8: 2687000000 | O8: 2216000000 | P8: 2275000000 | Q8: 2382000000 | T8: Book Value | W8: =J18-J22 -> 5468000000 | Y8: Earnings Per Share | AB8: =IF(AB4="Year over Year",AJ9,IF(AB4="3-Year Average",AVERAGE(AI9:AJ9),IF(AB4="5-Year Average",AVERAGE(AG9:AJ9),""))) -> #DIV/0! | AD8: Net Income % | AG8: =IF(AND(N9>0,M9>0,M9<>""),N9/M9-1,IF(AND(M9<0,N9<0,M9<>""),(N9-M9)/ABS(M9),IF(AND(M9>0,N9<0,M9<>""),"L",IF(AND(M9<0,N9>0,M9<>""),"P","")))) -> -0.60208062 | AH8: =IF(AND(O9>0,N9>0,N9<>""),O9/N9-1,IF(AND(N9<0,O9<0,N9<>""),(O9-N9)/ABS(N9),IF(AND(N9>0,O9<0,N9<>""),"L",IF(AND(N9<0,O9>0,N9<>""),"P","")))) -> L | AI8: =IF(AND(P9>0,O9>0,O9<>""),P9/O9-1,IF(AND(O9<0,P9<0,O9<>""),(P9-O9)/ABS(O9),IF(AND(O9>0,P9<0,O9<>""),"L",IF(AND(O9<0,P9>0,O9<>""),"P","")))) -> -0.027433628 | AJ8: =IF(AND(Q9>0,P9>0,P9<>""),Q9/P9-1,IF(AND(P9<0,Q9<0,P9<>""),(Q9-P9)/ABS(P9),IF(AND(P9>0,Q9<0,P9<>""),"L",IF(AND(P9<0,Q9>0,P9<>""),"P","")))) -> P
D9: Net Income | F9: 290000000 | G9: 101000000 | H9: 128000000 | I9: 154000000 | J9: 17000000 | K9: 400000000 | M9: 769000000 | N9: 306000000 | O9: -1130000000 | P9: -1161000000 | Q9: 1203000000 | T9: Type | W9: =IF(W6>10000000000,"Large Cap",IF(AND(10000000000>W6,2000000000<W6),"Mid Cap",IF(AND(2000000000>W6,W6>50000000),"Small Cap",IF(W6<50000000,"Micro Cap",NA)))) -> Mid Cap | AD9: Earnings per share % | AG9: =IF(AND(N10>0,M10>0,M10<>""),N10/M10-1,IF(AND(M10<0,N10<0,M10<>""),(N10-M10)/ABS(M10),IF(AND(M10>0,N10<0,M10<>""),"L",IF(AND(M10<0,N10>0,M10<>""),"P","")))) | AH9: =IF(AND(O10>0,N10>0,N10<>""),O10/N10-1,IF(AND(N10<0,O10<0,N10<>""),(O10-N10)/ABS(N10),IF(AND(N10>0,O10<0,N10<>""),"L",IF(AND(N10<0,O10>0,N10<>""),"P","")))) | AI9: =IF(AND(P10>0,O10>0,O10<>""),P10/O10-1,IF(AND(O10<0,P10<0,O10<>""),(P10-O10)/ABS(O10),IF(AND(O10>0,P10<0,O10<>""),"L",IF(AND(O10<0,P10>0,O10<>""),"P","")))) | AJ9: =IF(AND(Q10>0,P10>0,P10<>""),Q10/P10-1,IF(AND(P10<0,Q10<0,P10<>""),(Q10-P10)/ABS(P10),IF(AND(P10>0,Q10<0,P10<>""),"L",IF(AND(P10<0,Q10>0,P10<>""),"P",""))))
D10: Earnings Per Share | F10: =F9/F27 -> 0.43837847 | G10: =G9/G27 -> 0.15249945 | H10: =H9/H27 -> 0.19326645 | I10: =I9/I27 -> 0.23203431 | J10: =J9/J27 -> 0.025610216 | T10: Dividend Yield | Y10: Financial Health
AD11: Financials | AF11: =M4 -> 2014 | AG11: =N4 -> 2015 | AH11: =O4 -> 2016 | AI11: =P4 -> 2017 | AJ11: =Q4 -> 2018
Y13: Current Ratio | AB13: =AVERAGE(G19:J19)/AVERAGE(G23:J23) -> 1.2705254
Y14: Financial Leverage | AB14: =AVERAGE(G18:J18)/AVERAGE(G26:J26) -> 5.8724476 | AD14: Revenue | AF14: =IF(M6="","",M6) -> 17146000000 | AG14: =IF(N6="","",N6) -> 14963000000 | AH14: =IF(O6="","",O6) -> 13586000000 | AI14: =IF(P6="","",P6) -> 10530000000 | AJ14: =IF(Q6="","",Q6) -> 10736000000
D15: EBITDA | T15: Valuation | Y15: Debt / Equity | AB15: =AVERAGE(G25:J25)/AVERAGE(G26:J26) -> 3.2473027 | AD15: Gross Margin % | AF15: =IF(OR(M6="",M5=""),"",M5/M6) -> 0.18010031 | AG15: =IF(OR(N6="",N5=""),"",N5/N6) -> 0.19153913 | AH15: =IF(OR(O6="",O5=""),"",O5/O6) -> 0.17908141 | AI15: =IF(OR(P6="",P5=""),"",P5/P6) -> 0.2339981 | AJ15: =IF(OR(Q6="",Q5=""),"",Q5/Q6) -> 0.23966095
T16: P / E | W16: =IF(K9>0,W5/(K9/AVERAGE(F27:J27)),"") -> 24.471061 | AD16: Operating Income | AF16: =IF(M8="","",M8) -> 2901000000 | AG16: =IF(N8="","",N8) -> 2687000000 | AH16: =IF(O8="","",O8) -> 2216000000 | AI16: =IF(P8="","",P8) -> 2275000000 | AJ16: =IF(Q8="","",Q8) -> 2382000000
D17: Balance Sheet | F17: Q2 2018 | G17: Q3 2018 | H17: Q4 2018 | I17: Q1 2019 | J17: Q2 2019 | M17: 2014 | N17: 2015 | O17: 2016 | P17: 2017 | Q17: 2018 | T17: P / B | W17: =W5/((J18-J22)/J27) -> 1.7930304 | Y17: Income Statement | AD17: Operating Margin % | AF17: =IF(OR(M6="",M8=""),"",M8/M6) -> 0.16919398 | AG17: =IF(OR(N6="",N8=""),"",N8/N6) -> 0.17957629 | AH17: =IF(OR(O6="",O8=""),"",O8/O6) -> 0.16310908 | AI17: =IF(OR(P6="",P8=""),"",P8/P6) -> 0.21604938 | AJ17: =IF(OR(Q6="",Q8=""),"",Q8/Q6) -> 0.22187034
D18: Total Assets | F18: 32597000000 | G18: 32489000000 | H18: 32521000000 | I18: 33471000000 | J18: 33238000000 | M18: 38966000000 | N18: 36850000000 | O18: 36119000000 | P18: 33112000000 | Q18: 32521000000 | T18: P / S | W18: =W5/(K6/AVERAGE(F27:J27)) -> 0.92413373 | Y18: Revenue | AB18: =K6 -> 10592000000
D19: Total Current Assets | F19: 5287000000 | G19: 5015000000 | H19: 5015000000 | I19: 5855000000 | J19: 5517000000 | M19: 7826000000 | N19: 6866000000 | O19: 6411000000 | P19: 6398000000 | Q19: 5015000000 | T19: P / CFO | W19: =IF(AVERAGE(O33:Q33)>0,W5/(AVERAGE(O33:Q33)/K27),"") -> #DIV/0! | Y19: Gross Profit | AB19: =K5 -> 2405000000
D20: Cash, Cash Equivalents and Short Term Investments | F20: 1996000000 | G20: 1588000000 | H20: 1479000000 | I20: 1804000000 | J20: 1579000000 | M20: 2248000000 | N20: 1746000000 | O20: 2103000000 | P20: 1373000000 | Q20: 1479000000 | T20: P / FCF | W20: =IF(AVERAGE(O35:Q35)>0,W6/AVERAGE(O35:Q35),"") -> #DIV/0! | Y20: Net Income | AB20: =K9 -> 400000000
D21: Cash and Cash Equivalents | F21: 1140000000 | G21: 1187000000 | H21: 1166000000 | I21: 1426000000 | J21: 1169000000 | M21: 1539000000 | N21: 1262000000 | O21: 1305000000 | P21: 949000000 | Q21: 1166000000 | T21: EV / EBITDA | W21: =(W6+(J24+J25)-J21)/J15 -> #DIV/0! | Y21: Earnings Per Share | AB21: =K10 -> 0 | AD21: Net Income | AF21: =IF(M9="","",M9) -> 769000000 | AG21: =IF(N9="","",N9) -> 306000000 | AH21: =IF(O9="","",O9) -> -1130000000 | AI21: =IF(P9="","",P9) -> -1161000000 | AJ21: =IF(Q9="","",Q9) -> 1203000000
D22: Total Liabilities | F22: 26940000000 | G22: 26780000000 | H22: 26917000000 | I22: 27822000000 | J22: 27770000000 | M22: 31641000000 | N22: 30679000000 | O22: 30419000000 | P22: 28267000000 | Q22: 26917000000 | AD22: Earnings Per Share | AF22: =IF(M10="","",M10) | AG22: =IF(N10="","",N10) | AH22: =IF(O10="","",O10) | AI22: =IF(P10="","",P10) | AJ22: =IF(Q10="","",Q10)
D23: Total Current Liabilities | F23: 3994000000 | G23: 4047000000 | H23: 4399000000 | I23: 4357000000 | J23: 4042000000 | M23: 6997000000 | N23: 6950000000 | O23: 5272000000 | P23: 6028000000 | Q23: 4399000000 | T23: Profitability | AD23: Shares | AF23: =IF(M27="","",M27) -> 703851297 | AG23: =IF(N27="","",N27) -> 666808790 | AH23: =IF(O27="","",O27) -> 659182232 | AI23: =IF(P27="","",P27) -> 660388128 | AJ23: =IF(Q27="","",Q27) -> 662298096
D24: Current Debt | F24: 1235000000 | G24: 1308000000 | H24: 1659000000 | I24: 1265000000 | J24: 1087000000 | M24: 2133000000 | N24: 2529000000 | O24: 1303000000 | P24: 2164000000 | Q24: 1659000000 | T24: Sales | W24: =K6 -> 10592000000 | Y24: Balance Sheet | AD24: Book Value Per Share | AF24: =IF(OR(M26="",M27="",M18="",M22=""),"",(M18-M22)/M27) -> 10.407028 | AG24: =IF(OR(N26="",N27="",N18="",N22=""),"",(N18-N22)/N27) -> 9.2545271 | AH24: =IF(OR(O26="",O27="",O18="",O22=""),"",(O18-O22)/O27) -> 8.6470777 | AI24: =IF(OR(P26="",P27="",P18="",P22=""),"",(P18-P22)/P27) -> 7.3365946 | AJ24: =IF(OR(Q26="",Q27="",Q18="",Q22=""),"",(Q18-Q22)/Q27) -> 8.4614466
D25: Long Term Debt | F25: 18356000000 | G25: 18088000000 | H25: 17636000000 | I25: 18445000000 | J25: 18668000000 | M25: 18725000000 | N25: 18278000000 | O25: 19160000000 | P25: 17801000000 | Q25: 17636000000 | T25: Gross Margin | W25: =(K6-K7)/K6 -> 1.7729418 | Y25: Total Cash | AB25: =J20 -> 1579000000
D26: Total Equity | F26: 5657000000 | G26: 5709000000 | H26: 5604000000 | I26: 5649000000 | J26: 5468000000 | M26: 7325000000 | N26: 6171000000 | O26: 5700000000 | P26: 4845000000 | Q26: 5604000000 | T26: Net Margin | W26: =K9/K6 -> 0.03776435 | Y26: Current Assets | AB26: =J19 -> 5517000000 | AD26: Profitability | AF26: =M4 -> 2014 | AG26: =N4 -> 2015 | AH26: =O4 -> 2016 | AI26: =P4 -> 2017 | AJ26: =Q4 -> 2018
D27: Common Shares Outstanding | F27: 661528835 | G27: 662297479 | H27: 662298096 | I27: 663694956 | J27: 663797594 | M27: 703851297 | N27: 666808790 | O27: 659182232 | P27: 660388128 | Q27: 662298096 | T27: Operating Margin | W27: =K8/K6 -> 0.20817598 | Y27: Current Liabilities | AB27: =J23 -> 4042000000
Y28: Total Debt | AB28: =J24+J25 -> 19755000000 | AD28: Net Margin % | AF28: =IF(OR(M6="",M9="",M6=0,M9=0),"",M9/M6) -> 0.044850111 | AG28: =IF(OR(N6="",N9="",N6=0,N9=0),"",N9/N6) -> 0.020450444 | AH28: =IF(OR(O6="",O9="",O6=0,O9=0),"",O9/O6) -> -0.083173855 | AI28: =IF(OR(P6="",P9="",P6=0,P9=0),"",P9/P6) -> -0.11025641 | AJ28: =IF(OR(Q6="",Q9="",Q6=0,Q9=0),"",Q9/Q6) -> 0.11205291
T29: Effectiveness | AD29: Return on Equity % | AF29: =IF(OR(M9="",M25="",M9=0,M25=0),"",M9/M25) -> 0.041068091 | AG29: =IF(OR(N9="",N25="",N9=0,N25=0),"",N9/N25) -> 0.016741438 | AH29: =IF(OR(O9="",O25="",O9=0,O25=0),"",O9/O25) -> -0.058977035 | AI29: =IF(OR(P9="",P25="",P9=0,P25=0),"",P9/P25) -> -0.065221055 | AJ29: =IF(OR(Q9="",Q25="",Q9=0,Q25=0),"",Q9/Q25) -> 0.068212747
T30: Return on Equity | W30: =K9/AVERAGE(G26:J26) -> 0.071333036 | Y30: Cash Flow Statement | AD30: Return on Assets % | AF30: =IF(OR(M9="",M18="",M9=0,M18=0),"",M9/M18) -> 0.019735154 | AG30: =IF(OR(N9="",N18="",N9=0,N18=0),"",N9/N18) -> 0.0083039349 | AH30: =IF(OR(O9="",O18="",O9=0,O18=0),"",O9/O18) -> -0.031285473 | AI30: =IF(OR(P9="",P18="",P9=0,P18=0),"",P9/P18) -> -0.035062817 | AJ30: =IF(OR(Q9="",Q18="",Q9=0,Q18=0),"",Q9/Q18) -> 0.036991482
T31: Return on Assets | W31: =K9/AVERAGE(G18:J18) -> 0.012147071 | Y31: Operating Cash Flow | AB31: =AVERAGE(O33:Q33) -> #DIV/0! | AD31: Asset Turnover | AF31: =IF(OR(M6="",M18="",M6=0,M18=0),"",M6/M18) -> 0.44002464 | AG31: =IF(OR(N6="",N18="",N6=0,N18=0),"",N6/N18) -> 0.40605156 | AH31: =IF(OR(O6="",O18="",O6=0,O18=0),"",O6/O18) -> 0.37614552 | AI31: =IF(OR(P6="",P18="",P6=0,P18=0),"",P6/P18) -> 0.3180116 | AJ31: =IF(OR(Q6="",Q18="",Q6=0,Q18=0),"",Q6/Q18) -> 0.33012515
D32: Cash Flow | F32: =F4 -> Q2 2018 | G32: =G4 -> Q3 2018 | H32: =H4 -> Q4 2018 | I32: =I4 -> Q1 2019 | J32: =J4 -> Q2 2019 | K32: TTM | M32: =M4 -> 2014 | N32: =N4 -> 2015 | O32: =O4 -> 2016 | P32: =P4 -> 2017 | Q32: =Q4 -> 2018 | T32: Return on Capital Employed | W32: =K8/(AVERAGE(G26:J26)+(AVERAGE(G18:J18)-AVERAGE(G23:J23))) -> 0.064237021 | Y32: Capital Expenditure | AB32: =ABS(AVERAGE(O34:Q34)) -> #DIV/0!
D33: Operating cash flow | T33: Asset Turnover | W33: =K6/AVERAGE(G18:J18) -> 0.32165443 | Y33: Free Cash Flow | AB33: =AVERAGE(O35:Q35) -> #DIV/0! | AD33: Financial Health | AF33: =M4 -> 2014 | AG33: =N4 -> 2015 | AH33: =O4 -> 2016 | AI33: =P4 -> 2017 | AJ33: =Q4 -> 2018
D34: Capital expenditure | AD34: Current Ratio | AF34: =IF(OR(M19="",M23="",M19=0,M23=0),"",M19/M23) -> 1.1184793 | AG34: =IF(OR(N19="",N23="",N19=0,N23=0),"",N19/N23) -> 0.98791367 | AH34: =IF(OR(O19="",O23="",O19=0,O23=0),"",O19/O23) -> 1.216047 | AI34: =IF(OR(P19="",P23="",P19=0,P23=0),"",P19/P23) -> 1.0613802 | AJ34: =IF(OR(Q19="",Q23="",Q19=0,Q23=0),"",Q19/Q23) -> 1.1400318
D35: Free cash flow | AD35: Financial Leverage | AF35: =IF(OR(M18="",M25="",M18=0,M25=0),"",M18/M25) -> 2.0809613 | AG35: =IF(OR(N18="",N25="",N18=0,N25=0),"",N18/N25) -> 2.0160849 | AH35: =IF(OR(O18="",O25="",O18=0,O25=0),"",O18/O25) -> 1.8851253 | AI35: =IF(OR(P18="",P25="",P18=0,P25=0),"",P18/P25) -> 1.8601202 | AJ35: =IF(OR(Q18="",Q25="",Q18=0,Q25=0),"",Q18/Q25) -> 1.8440122
AD36: Debt / Equity | AF36: =IF(OR(M26="",M25="",M25=0,M26=0),"",M26/M25) -> 0.39118825 | AG36: =IF(OR(N26="",N25="",N25=0,N26=0),"",N26/N25) -> 0.337619 | AH36: =IF(OR(O26="",O25="",O25=0,O26=0),"",O26/O25) -> 0.29749478 | AI36: =IF(OR(P26="",P25="",P25=0,P26=0),"",P26/P25) -> 0.27217572 | AJ36: =IF(OR(Q26="",Q25="",Q25=0,Q26=0),"",Q26/Q25) -> 0.31775913
A41: 2 | T41: Symbol | U41: CCUR
D43: Income Statement | F43: 2016-10 | G43: 2017-01 | H43: 2017-04 | I43: 2017-07 | J43: 2017-10 | M43: 2013 | N43: 2014 | O43: 2015 | P43: 2016 | Q43: 2017 | R43: TTM | T43: Quote | Y43: Growth | AB43: 5-Year Average | AD43: Key Ratios ― Growth, YOY | AG43: =N43 -> 2014 | AH43: =O43 -> 2015 | AI43: =P43 -> 2016 | AJ43: =Q43 -> 2017
D44: Revenue | T44: Last Price | W44: 5.42 | Y44: Revenue | AB44: =IF(AB43="Year over Year",AJ44,IF(AB43="3-Year Average",AVERAGE(AI44:AJ44),IF(AB43="5-Year Average",AVERAGE(AG44:AJ44),""))) -> #DIV/0! | AD44: Revenue % | AG44: =IF(AND(N44>0,M44>0,M44<>""),N44/M44-1,IF(AND(M44<0,N44<0,M44<>""),(N44-M44)/ABS(M44),IF(AND(M44>0,N44<0,M44<>""),"L",IF(AND(M44<0,N44>0,M44<>""),"P","")))) | AH44: =IF(AND(O44>0,N44>0,N44<>""),O44/N44-1,IF(AND(N44<0,O44<0,N44<>""),(O44-N44)/ABS(N44),IF(AND(N44>0,O44<0,N44<>""),"L",IF(AND(N44<0,O44>0,N44<>""),"P","")))) | AI44: =IF(AND(P44>0,O44>0,O44<>""),P44/O44-1,IF(AND(O44<0,P44<0,O44<>""),(P44-O44)/ABS(O44),IF(AND(O44>0,P44<0,O44<>""),"L",IF(AND(O44<0,P44>0,O44<>""),"P","")))) | AJ44: =IF(AND(Q44>0,P44>0,P44<>""),Q44/P44-1,IF(AND(P44<0,Q44<0,P44<>""),(Q44-P44)/ABS(P44),IF(AND(P44>0,Q44<0,P44<>""),"L",IF(AND(P44<0,Q44>0,P44<>""),"P",""))))
D45: Cost of revenue | T45: Market Capitalization | W45: =W44*R52 -> 0 | Y45: Operating Income | AB45: =IF(AB43="Year over Year",AJ45,IF(AB43="3-Year Average",AVERAGE(AI45:AJ45),IF(AB43="5-Year Average",AVERAGE(AG45:AJ45),""))) -> #DIV/0! | AD45: Operating Income % | AG45: =IF(AND(N47>0,M47>0,M47<>""),N47/M47-1,IF(AND(M47<0,N47<0,M47<>""),(N47-M47)/ABS(M47),IF(AND(M47>0,N47<0,M47<>""),"L",IF(AND(M47<0,N47>0,M47<>""),"P","")))) | AH45: =IF(AND(O47>0,N47>0,N47<>""),O47/N47-1,IF(AND(N47<0,O47<0,N47<>""),(O47-N47)/ABS(N47),IF(AND(N47>0,O47<0,N47<>""),"L",IF(AND(N47<0,O47>0,N47<>""),"P","")))) | AI45: =IF(AND(P47>0,O47>0,O47<>""),P47/O47-1,IF(AND(O47<0,P47<0,O47<>""),(P47-O47)/ABS(O47),IF(AND(O47>0,P47<0,O47<>""),"L",IF(AND(O47<0,P47>0,O47<>""),"P","")))) | AJ45: =IF(AND(Q47>0,P47>0,P47<>""),Q47/P47-1,IF(AND(P47<0,Q47<0,P47<>""),(Q47-P47)/ABS(P47),IF(AND(P47>0,Q47<0,P47<>""),"L",IF(AND(P47<0,Q47>0,P47<>""),"P",""))))
D46: Gross profit | T46: Enterprise Value | W46: =W45+(J60+J62)-J56 -> 0 | Y46: Net Income | AB46: =IF(AB43="Year over Year",AJ46,IF(AB43="3-Year Average",AVERAGE(AI46:AJ46),IF(AB43="5-Year Average",AVERAGE(AG46:AJ46),""))) -> #DIV/0! | AD46: Net Income % | AG46: =IF(AND(N48>0,M48>0,M48<>""),N48/M48-1,IF(AND(M48<0,N48<0,M48<>""),(N48-M48)/ABS(M48),IF(AND(M48>0,N48<0,M48<>""),"L",IF(AND(M48<0,N48>0,M48<>""),"P","")))) | AH46: =IF(AND(O48>0,N48>0,N48<>""),O48/N48-1,IF(AND(N48<0,O48<0,N48<>""),(O48-N48)/ABS(N48),IF(AND(N48>0,O48<0,N48<>""),"L",IF(AND(N48<0,O48>0,N48<>""),"P","")))) | AI46: =IF(AND(P48>0,O48>0,O48<>""),P48/O48-1,IF(AND(O48<0,P48<0,O48<>""),(P48-O48)/ABS(O48),IF(AND(O48>0,P48<0,O48<>""),"L",IF(AND(O48<0,P48>0,O48<>""),"P","")))) | AJ46: =IF(AND(Q48>0,P48>0,P48<>""),Q48/P48-1,IF(AND(P48<0,Q48<0,P48<>""),(Q48-P48)/ABS(P48),IF(AND(P48>0,Q48<0,P48<>""),"L",IF(AND(P48<0,Q48>0,P48<>""),"P",""))))
D47: Operating income | T47: Book Value | W47: =J59-J63 -> 0 | Y47: Earnings Per Share | AB47: =IF(AB43="Year over Year",AJ47,IF(AB43="3-Year Average",AVERAGE(AI47:AJ47),IF(AB43="5-Year Average",AVERAGE(AG47:AJ47),""))) -> #DIV/0! | AD47: Earnings per share % | AG47: =IF(AND(N49>0,M49>0,M49<>""),N49/M49-1,IF(AND(M49<0,N49<0,M49<>""),(N49-M49)/ABS(M49),IF(AND(M49>0,N49<0,M49<>""),"L",IF(AND(M49<0,N49>0,M49<>""),"P","")))) | AH47: =IF(AND(O49>0,N49>0,N49<>""),O49/N49-1,IF(AND(N49<0,O49<0,N49<>""),(O49-N49)/ABS(N49),IF(AND(N49>0,O49<0,N49<>""),"L",IF(AND(N49<0,O49>0,N49<>""),"P","")))) | AI47: =IF(AND(P49>0,O49>0,O49<>""),P49/O49-1,IF(AND(O49<0,P49<0,O49<>""),(P49-O49)/ABS(O49),IF(AND(O49>0,P49<0,O49<>""),"L",IF(AND(O49<0,P49>0,O49<>""),"P","")))) | AJ47: =IF(AND(Q49>0,P49>0,P49<>""),Q49/P49-1,IF(AND(P49<0,Q49<0,P49<>""),(Q49-P49)/ABS(P49),IF(AND(P49>0,Q49<0,P49<>""),"L",IF(AND(P49<0,Q49>0,P49<>""),"P",""))))
D48: Net income | T48: Type | W48: =IF(W45>10000,"Large Cap",IF(AND(10000>W45,2000<W45),"Mid Cap",IF(AND(2000>W45,W45>50),"Small Cap",IF(W45<50,"Micro Cap",NA)))) -> Micro Cap
D49: Earnings per share | T49: Dividend Yield | Y49: Financial Health | AD49: Financials | AF49: =M43 -> 2013 | AG49: =N43 -> 2014 | AH49: =O43 -> 2015 | AI49: =P43 -> 2016 | AJ49: =Q43 -> 2017
D52: Weighted average share… | Y52: Current Ratio | AB52: =AVERAGE(G58:J58)/AVERAGE(G61:J61) -> #DIV/0! | AD52: Revenue | AF52: =IF(M44="","",M44) | AG52: =IF(N44="","",N44) | AH52: =IF(O44="","",O44) | AI52: =IF(P44="","",P44) | AJ52: =IF(Q44="","",Q44)
D53: EBITDA | T53: Valuation | Y53: Financial Leverage | AB53: =AVERAGE(G59:J59)/AVERAGE(G64:J64) -> #DIV/0! | AD53: Gross Margin % | AF53: =IF(OR(M44="",M46=""),"",M46/M44) | AG53: =IF(OR(N44="",N46=""),"",N46/N44) | AH53: =IF(OR(O44="",O46=""),"",O46/O44) | AI53: =IF(OR(P44="",P46=""),"",P46/P44) | AJ53: =IF(OR(Q44="",Q46=""),"",Q46/Q44)
T54: P / E | W54: =IF(R49>0,W44/R49,"") | Y54: Debt / Equity | AB54: =AVERAGE(G62:J62)/AVERAGE(G64:J64) -> #DIV/0! | AD54: Operating Income | AF54: =IF(M47="","",M47) | AG54: =IF(N47="","",N47) | AH54: =IF(O47="","",O47) | AI54: =IF(P47="","",P47) | AJ54: =IF(Q47="","",Q47)
D55: Balance Sheet | F55: =F43 -> 2016-10 | G55: =G43 -> 2017-01 | H55: =H43 -> 2017-04 | I55: =I43 -> 2017-07 | J55: =J43 -> 2017-10 | M55: =M43 -> 2013 | N55: =N43 -> 2014 | O55: =O43 -> 2015 | P55: =P43 -> 2016 | Q55: =Q43 -> 2017 | T55: P / B | W55: =W44/((J59-J63)/J52) -> #DIV/0! | AD55: Operating Margin % | AF55: =IF(OR(M44="",M47=""),"",M47/M44) | AG55: =IF(OR(N44="",N47=""),"",N47/N44) | AH55: =IF(OR(O44="",O47=""),"",O47/O44) | AI55: =IF(OR(P44="",P47=""),"",P47/P44) | AJ55: =IF(OR(Q44="",Q47=""),"",Q47/Q44)
D56: Cash and cash equivale… | T56: P / S | W56: =W44/(R44/R52) -> #DIV/0! | Y56: Income Statement | AD56: Net Income | AF56: =IF(M48="","",M48) | AG56: =IF(N48="","",N48) | AH56: =IF(O48="","",O48) | AI56: =IF(P48="","",P48) | AJ56: =IF(Q48="","",Q48)
D57: Total cash | T57: P / CFO | W57: =IF(AVERAGE(O67:Q67)>0,W44/(AVERAGE(O67:Q67)/R52),"") -> #DIV/0! | Y57: Revenue | AB57: =R44 -> 0 | AD57: Earnings Per Share | AF57: =IF(M49="","",M49) | AG57: =IF(N49="","",N49) | AH57: =IF(O49="","",O49) | AI57: =IF(P49="","",P49) | AJ57: =IF(Q49="","",Q49)
D58: Total current assets | T58: P / FCF | W58: =IF(AVERAGE(O69:Q69)>0,W45/AVERAGE(O69:Q69),"") -> #DIV/0! | Y58: Gross Profit | AB58: =R46 -> 0 | AD58: Shares | AF58: =IF(M52="","",M52) | AG58: =IF(N52="","",N52) | AH58: =IF(O52="","",O52) | AI58: =IF(P52="","",P52) | AJ58: =IF(Q52="","",Q52)
D59: Total assets | T59: EV / EBITDA | W59: =(W45+(J60+J62)-J56)/J53 -> #DIV/0! | Y59: Net Income | AB59: =R48 -> 0 | AD59: Book Value Per Share | AF59: =IF(OR(M64="",M52="",M59="",M63=""),"",(M59-M63)/M52) | AG59: =IF(OR(N64="",N52="",N59="",N63=""),"",(N59-N63)/N52) | AH59: =IF(OR(O64="",O52="",O59="",O63=""),"",(O59-O63)/O52) | AI59: =IF(OR(P64="",P52="",P59="",P63=""),"",(P59-P63)/P52) | AJ59: =IF(OR(Q64="",Q52="",Q59="",Q63=""),"",(Q59-Q63)/Q52)
D60: Short-term debt | Y60: Earnings Per Share | AB60: =R49 -> 0
D61: Total current liabilities | AD61: Profitability | AF61: =M43 -> 2013 | AG61: =N43 -> 2014 | AH61: =O43 -> 2015 | AI61: =P43 -> 2016 | AJ61: =Q43 -> 2017
D62: Long-term debt | T62: Profitability | Y62: Balance Sheet | AD62: Net Margin % | AF62: =IF(OR(M44="",M48="",M44=0,M48=0),"",M48/M44) | AG62: =IF(OR(N44="",N48="",N44=0,N48=0),"",N48/N44) | AH62: =IF(OR(O44="",O48="",O44=0,O48=0),"",O48/O44) | AI62: =IF(OR(P44="",P48="",P44=0,P48=0),"",P48/P44) | AJ62: =IF(OR(Q44="",Q48="",Q44=0,Q48=0),"",Q48/Q44)
D63: Total liabilities | T63: Sales | W63: =R44 -> 0 | Y63: Total Cash | AB63: =J57 -> 0 | AD63: Return on Equity % | AF63: =IF(OR(M48="",M62="",M48=0,M62=0),"",M48/M62) | AG63: =IF(OR(N48="",N62="",N48=0,N62=0),"",N48/N62) | AH63: =IF(OR(O48="",O62="",O48=0,O62=0),"",O48/O62) | AI63: =IF(OR(P48="",P62="",P48=0,P62=0),"",P48/P62) | AJ63: =IF(OR(Q48="",Q62="",Q48=0,Q62=0),"",Q48/Q62)
D64: Total stockholders' eq… | T64: Gross Margin | W64: =(R44-R45)/R44 -> #DIV/0! | Y64: Current Assets | AB64: =J58 -> 0 | AD64: Return on Assets % | AF64: =IF(OR(M48="",M59="",M48=0,M59=0),"",M48/M59) | AG64: =IF(OR(N48="",N59="",N48=0,N59=0),"",N48/N59) | AH64: =IF(OR(O48="",O59="",O48=0,O59=0),"",O48/O59) | AI64: =IF(OR(P48="",P59="",P48=0,P59=0),"",P48/P59) | AJ64: =IF(OR(Q48="",Q59="",Q48=0,Q59=0),"",Q48/Q59)
T65: Net Margin | W65: =R48/R44 -> #DIV/0! | Y65: Current Liabilities | AB65: =J61 -> 0 | AD65: Asset Turnover | AF65: =IF(OR(M44="",M59="",M44=0,M59=0),"",M44/M59) | AG65: =IF(OR(N44="",N59="",N44=0,N59=0),"",N44/N59) | AH65: =IF(OR(O44="",O59="",O44=0,O59=0),"",O44/O59) | AI65: =IF(OR(P44="",P59="",P44=0,P59=0),"",P44/P59) | AJ65: =IF(OR(Q44="",Q59="",Q44=0,Q59=0),"",Q44/Q59)
D66: Cash Flow | F66: =F43 -> 2016-10 | G66: =G43 -> 2017-01 | H66: =H43 -> 2017-04 | I66: =I43 -> 2017-07 | J66: =J43 -> 2017-10 | M66: =M43 -> 2013 | N66: =N43 -> 2014 | O66: =O43 -> 2015 | P66: =P43 -> 2016 | Q66: =Q43 -> 2017 | R66: TTM | T66: Operating Margin | W66: =R47/R44 -> #DIV/0! | Y66: Total Debt | AB66: =J60+J62 -> 0
D67: Operating cash flow | AD67: Financial Health | AF67: =M43 -> 2013 | AG67: =N43 -> 2014 | AH67: =O43 -> 2015 | AI67: =P43 -> 2016 | AJ67: =Q43 -> 2017
D68: Capital expenditure | T68: Effectiveness | Y68: Cash Flow Statement | AD68: Current Ratio | AF68: =IF(OR(M58="",M61="",M58=0,M61=0),"",M58/M61) | AG68: =IF(OR(N58="",N61="",N58=0,N61=0),"",N58/N61) | AH68: =IF(OR(O58="",O61="",O58=0,O61=0),"",O58/O61) | AI68: =IF(OR(P58="",P61="",P58=0,P61=0),"",P58/P61) | AJ68: =IF(OR(Q58="",Q61="",Q58=0,Q61=0),"",Q58/Q61)
D69: Free cash flow | T69: Return on Equity | W69: =R48/AVERAGE(G64:J64) -> #DIV/0! | Y69: Operating Cash Flow | AB69: =AVERAGE(O67:Q67) -> #DIV/0! | AD69: Financial Leverage | AF69: =IF(OR(M59="",M62="",M59=0,M62=0),"",M59/M62) | AG69: =IF(OR(N59="",N62="",N59=0,N62=0),"",N59/N62) | AH69: =IF(OR(O59="",O62="",O59=0,O62=0),"",O59/O62) | AI69: =IF(OR(P59="",P62="",P59=0,P62=0),"",P59/P62) | AJ69: =IF(OR(Q59="",Q62="",Q59=0,Q62=0),"",Q59/Q62)
T70: Return on Assets | W70: =R48/AVERAGE(G59:J59) -> #DIV/0! | Y70: Capital Expenditure | AB70: =ABS(AVERAGE(O68:Q68)) -> #DIV/0! | AD70: Debt / Equity | AF70: =IF(OR(M64="",M62="",M62=0,M64=0),"",M64/M62) | AG70: =IF(OR(N64="",N62="",N62=0,N64=0),"",N64/N62) | AH70: =IF(OR(O64="",O62="",O62=0,O64=0),"",O64/O62) | AI70: =IF(OR(P64="",P62="",P62=0,P64=0),"",P64/P62) | AJ70: =IF(OR(Q64="",Q62="",Q62=0,Q64=0),"",Q64/Q62)
T71: Return on Capital Employed | W71: =R47/(AVERAGE(G64:J64)+(AVERAGE(G59:J59)-AVERAGE(G61:J61))) -> #DIV/0! | Y71: Free Cash Flow | AB71: =AVERAGE(O69:Q69) -> #DIV/0!
T72: Asset Turnover | W72: =R44/AVERAGE(G59:J59) -> #DIV/0!
A75: 3 | T75: Symbol | U75: CCUR
D77: Income Statement | F77: 2016-10 | G77: 2017-01 | H77: 2017-04 | I77: 2017-07 | J77: 2017-10 | M77: 2013 | N77: 2014 | O77: 2015 | P77: 2016 | Q77: 2017 | R77: TTM | T77: Quote | Y77: Growth | AB77: 5-Year Average | AD77: Key Ratios ― Growth, YOY | AG77: =N77 -> 2014 | AH77: =O77 -> 2015 | AI77: =P77 -> 2016 | AJ77: =Q77 -> 2017
D78: Revenue | T78: Last Price | W78: 5.42 | Y78: Revenue | AB78: =IF(AB77="Year over Year",AJ78,IF(AB77="3-Year Average",AVERAGE(AI78:AJ78),IF(AB77="5-Year Average",AVERAGE(AG78:AJ78),""))) -> #DIV/0! | AD78: Revenue % | AG78: =IF(AND(N78>0,M78>0,M78<>""),N78/M78-1,IF(AND(M78<0,N78<0,M78<>""),(N78-M78)/ABS(M78),IF(AND(M78>0,N78<0,M78<>""),"L",IF(AND(M78<0,N78>0,M78<>""),"P","")))) | AH78: =IF(AND(O78>0,N78>0,N78<>""),O78/N78-1,IF(AND(N78<0,O78<0,N78<>""),(O78-N78)/ABS(N78),IF(AND(N78>0,O78<0,N78<>""),"L",IF(AND(N78<0,O78>0,N78<>""),"P","")))) | AI78: =IF(AND(P78>0,O78>0,O78<>""),P78/O78-1,IF(AND(O78<0,P78<0,O78<>""),(P78-O78)/ABS(O78),IF(AND(O78>0,P78<0,O78<>""),"L",IF(AND(O78<0,P78>0,O78<>""),"P","")))) | AJ78: =IF(AND(Q78>0,P78>0,P78<>""),Q78/P78-1,IF(AND(P78<0,Q78<0,P78<>""),(Q78-P78)/ABS(P78),IF(AND(P78>0,Q78<0,P78<>""),"L",IF(AND(P78<0,Q78>0,P78<>""),"P",""))))
D79: Cost of revenue | T79: Market Capitalization | W79: =W78*R86 -> 0 | Y79: Operating Income | AB79: =IF(AB77="Year over Year",AJ79,IF(AB77="3-Year Average",AVERAGE(AI79:AJ79),IF(AB77="5-Year Average",AVERAGE(AG79:AJ79),""))) -> #DIV/0! | AD79: Operating Income % | AG79: =IF(AND(N81>0,M81>0,M81<>""),N81/M81-1,IF(AND(M81<0,N81<0,M81<>""),(N81-M81)/ABS(M81),IF(AND(M81>0,N81<0,M81<>""),"L",IF(AND(M81<0,N81>0,M81<>""),"P","")))) | AH79: =IF(AND(O81>0,N81>0,N81<>""),O81/N81-1,IF(AND(N81<0,O81<0,N81<>""),(O81-N81)/ABS(N81),IF(AND(N81>0,O81<0,N81<>""),"L",IF(AND(N81<0,O81>0,N81<>""),"P","")))) | AI79: =IF(AND(P81>0,O81>0,O81<>""),P81/O81-1,IF(AND(O81<0,P81<0,O81<>""),(P81-O81)/ABS(O81),IF(AND(O81>0,P81<0,O81<>""),"L",IF(AND(O81<0,P81>0,O81<>""),"P","")))) | AJ79: =IF(AND(Q81>0,P81>0,P81<>""),Q81/P81-1,IF(AND(P81<0,Q81<0,P81<>""),(Q81-P81)/ABS(P81),IF(AND(P81>0,Q81<0,P81<>""),"L",IF(AND(P81<0,Q81>0,P81<>""),"P",""))))
D80: Gross profit | T80: Enterprise Value | W80: =W79+(J94+J96)-J90 -> 0 | Y80: Net Income | AB80: =IF(AB77="Year over Year",AJ80,IF(AB77="3-Year Average",AVERAGE(AI80:AJ80),IF(AB77="5-Year Average",AVERAGE(AG80:AJ80),""))) -> #DIV/0! | AD80: Net Income % | AG80: =IF(AND(N82>0,M82>0,M82<>""),N82/M82-1,IF(AND(M82<0,N82<0,M82<>""),(N82-M82)/ABS(M82),IF(AND(M82>0,N82<0,M82<>""),"L",IF(AND(M82<0,N82>0,M82<>""),"P","")))) | AH80: =IF(AND(O82>0,N82>0,N82<>""),O82/N82-1,IF(AND(N82<0,O82<0,N82<>""),(O82-N82)/ABS(N82),IF(AND(N82>0,O82<0,N82<>""),"L",IF(AND(N82<0,O82>0,N82<>""),"P","")))) | AI80: =IF(AND(P82>0,O82>0,O82<>""),P82/O82-1,IF(AND(O82<0,P82<0,O82<>""),(P82-O82)/ABS(O82),IF(AND(O82>0,P82<0,O82<>""),"L",IF(AND(O82<0,P82>0,O82<>""),"P","")))) | AJ80: =IF(AND(Q82>0,P82>0,P82<>""),Q82/P82-1,IF(AND(P82<0,Q82<0,P82<>""),(Q82-P82)/ABS(P82),IF(AND(P82>0,Q82<0,P82<>""),"L",IF(AND(P82<0,Q82>0,P82<>""),"P",""))))
D81: Operating income | T81: Book Value | W81: =J93-J97 -> 0 | Y81: Earnings Per Share | AB81: =IF(AB77="Year over Year",AJ81,IF(AB77="3-Year Average",AVERAGE(AI81:AJ81),IF(AB77="5-Year Average",AVERAGE(AG81:AJ81),""))) -> #DIV/0! | AD81: Earnings per share % | AG81: =IF(AND(N83>0,M83>0,M83<>""),N83/M83-1,IF(AND(M83<0,N83<0,M83<>""),(N83-M83)/ABS(M83),IF(AND(M83>0,N83<0,M83<>""),"L",IF(AND(M83<0,N83>0,M83<>""),"P","")))) | AH81: =IF(AND(O83>0,N83>0,N83<>""),O83/N83-1,IF(AND(N83<0,O83<0,N83<>""),(O83-N83)/ABS(N83),IF(AND(N83>0,O83<0,N83<>""),"L",IF(AND(N83<0,O83>0,N83<>""),"P","")))) | AI81: =IF(AND(P83>0,O83>0,O83<>""),P83/O83-1,IF(AND(O83<0,P83<0,O83<>""),(P83-O83)/ABS(O83),IF(AND(O83>0,P83<0,O83<>""),"L",IF(AND(O83<0,P83>0,O83<>""),"P","")))) | AJ81: =IF(AND(Q83>0,P83>0,P83<>""),Q83/P83-1,IF(AND(P83<0,Q83<0,P83<>""),(Q83-P83)/ABS(P83),IF(AND(P83>0,Q83<0,P83<>""),"L",IF(AND(P83<0,Q83>0,P83<>""),"P",""))))
D82: Net income | T82: Type | W82: =IF(W79>10000,"Large Cap",IF(AND(10000>W79,2000<W79),"Mid Cap",IF(AND(2000>W79,W79>50),"Small Cap",IF(W79<50,"Micro Cap",NA)))) -> Micro Cap
D83: Earnings per share | T83: Dividend Yield | Y83: Financial Health | AD83: Financials | AF83: =M77 -> 2013 | AG83: =N77 -> 2014 | AH83: =O77 -> 2015 | AI83: =P77 -> 2016 | AJ83: =Q77 -> 2017
D86: Weighted average share… | Y86: Current Ratio | AB86: =AVERAGE(G92:J92)/AVERAGE(G95:J95) -> #DIV/0! | AD86: Revenue | AF86: =IF(M78="","",M78) | AG86: =IF(N78="","",N78) | AH86: =IF(O78="","",O78) | AI86: =IF(P78="","",P78) | AJ86: =IF(Q78="","",Q78)
D87: EBITDA | T87: Valuation | Y87: Financial Leverage | AB87: =AVERAGE(G93:J93)/AVERAGE(G98:J98) -> #DIV/0! | AD87: Gross Margin % | AF87: =IF(OR(M78="",M80=""),"",M80/M78) | AG87: =IF(OR(N78="",N80=""),"",N80/N78) | AH87: =IF(OR(O78="",O80=""),"",O80/O78) | AI87: =IF(OR(P78="",P80=""),"",P80/P78) | AJ87: =IF(OR(Q78="",Q80=""),"",Q80/Q78)
T88: P / E | W88: =IF(R83>0,W78/R83,"") | Y88: Debt / Equity | AB88: =AVERAGE(G96:J96)/AVERAGE(G98:J98) -> #DIV/0! | AD88: Operating Income | AF88: =IF(M81="","",M81) | AG88: =IF(N81="","",N81) | AH88: =IF(O81="","",O81) | AI88: =IF(P81="","",P81) | AJ88: =IF(Q81="","",Q81)
D89: Balance Sheet | F89: =F77 -> 2016-10 | G89: =G77 -> 2017-01 | H89: =H77 -> 2017-04 | I89: =I77 -> 2017-07 | J89: =J77 -> 2017-10 | M89: =M77 -> 2013 | N89: =N77 -> 2014 | O89: =O77 -> 2015 | P89: =P77 -> 2016 | Q89: =Q77 -> 2017 | T89: P / B | W89: =W78/((J93-J97)/J86) -> #DIV/0! | AD89: Operating Margin % | AF89: =IF(OR(M78="",M81=""),"",M81/M78) | AG89: =IF(OR(N78="",N81=""),"",N81/N78) | AH89: =IF(OR(O78="",O81=""),"",O81/O78) | AI89: =IF(OR(P78="",P81=""),"",P81/P78) | AJ89: =IF(OR(Q78="",Q81=""),"",Q81/Q78)
D90: Cash and cash equivale… | T90: P / S | W90: =W78/(R78/R86) -> #DIV/0! | Y90: Income Statement | AD90: Net Income | AF90: =IF(M82="","",M82) | AG90: =IF(N82="","",N82) | AH90: =IF(O82="","",O82) | AI90: =IF(P82="","",P82) | AJ90: =IF(Q82="","",Q82)
D91: Total cash | T91: P / CFO | W91: =IF(AVERAGE(O101:Q101)>0,W78/(AVERAGE(O101:Q101)/R86),"") -> #DIV/0! | Y91: Revenue | AB91: =R78 -> 0 | AD91: Earnings Per Share | AF91: =IF(M83="","",M83) | AG91: =IF(N83="","",N83) | AH91: =IF(O83="","",O83) | AI91: =IF(P83="","",P83) | AJ91: =IF(Q83="","",Q83)
D92: Total current assets | T92: P / FCF | W92: =IF(AVERAGE(O103:Q103)>0,W79/AVERAGE(O103:Q103),"") -> #DIV/0! | Y92: Gross Profit | AB92: =R80 -> 0 | AD92: Shares | AF92: =IF(M86="","",M86) | AG92: =IF(N86="","",N86) | AH92: =IF(O86="","",O86) | AI92: =IF(P86="","",P86) | AJ92: =IF(Q86="","",Q86)
D93: Total assets | T93: EV / EBITDA | W93: =(W79+(J94+J96)-J90)/J87 -> #DIV/0! | Y93: Net Income | AB93: =R82 -> 0 | AD93: Book Value Per Share | AF93: =IF(OR(M98="",M86="",M93="",M97=""),"",(M93-M97)/M86) | AG93: =IF(OR(N98="",N86="",N93="",N97=""),"",(N93-N97)/N86) | AH93: =IF(OR(O98="",O86="",O93="",O97=""),"",(O93-O97)/O86) | AI93: =IF(OR(P98="",P86="",P93="",P97=""),"",(P93-P97)/P86) | AJ93: =IF(OR(Q98="",Q86="",Q93="",Q97=""),"",(Q93-Q97)/Q86)
D94: Short-term debt | Y94: Earnings Per Share | AB94: =R83 -> 0
D95: Total current liabilities | AD95: Profitability | AF95: =M77 -> 2013 | AG95: =N77 -> 2014 | AH95: =O77 -> 2015 | AI95: =P77 -> 2016 | AJ95: =Q77 -> 2017
D96: Long-term debt | T96: Profitability | Y96: Balance Sheet | AD96: Net Margin % | AF96: =IF(OR(M78="",M82="",M78=0,M82=0),"",M82/M78) | AG96: =IF(OR(N78="",N82="",N78=0,N82=0),"",N82/N78) | AH96: =IF(OR(O78="",O82="",O78=0,O82=0),"",O82/O78) | AI96: =IF(OR(P78="",P82="",P78=0,P82=0),"",P82/P78) | AJ96: =IF(OR(Q78="",Q82="",Q78=0,Q82=0),"",Q82/Q78)
D97: Total liabilities | T97: Sales | W97: =R78 -> 0 | Y97: Total Cash | AB97: =J91 -> 0 | AD97: Return on Equity % | AF97: =IF(OR(M82="",M96="",M82=0,M96=0),"",M82/M96) | AG97: =IF(OR(N82="",N96="",N82=0,N96=0),"",N82/N96) | AH97: =IF(OR(O82="",O96="",O82=0,O96=0),"",O82/O96) | AI97: =IF(OR(P82="",P96="",P82=0,P96=0),"",P82/P96) | AJ97: =IF(OR(Q82="",Q96="",Q82=0,Q96=0),"",Q82/Q96)
D98: Total stockholders' eq… | T98: Gross Margin | W98: =(R78-R79)/R78 -> #DIV/0! | Y98: Current Assets | AB98: =J92 -> 0 | AD98: Return on Assets % | AF98: =IF(OR(M82="",M93="",M82=0,M93=0),"",M82/M93) | AG98: =IF(OR(N82="",N93="",N82=0,N93=0),"",N82/N93) | AH98: =IF(OR(O82="",O93="",O82=0,O93=0),"",O82/O93) | AI98: =IF(OR(P82="",P93="",P82=0,P93=0),"",P82/P93) | AJ98: =IF(OR(Q82="",Q93="",Q82=0,Q93=0),"",Q82/Q93)
T99: Net Margin | W99: =R82/R78 -> #DIV/0! | Y99: Current Liabilities | AB99: =J95 -> 0 | AD99: Asset Turnover | AF99: =IF(OR(M78="",M93="",M78=0,M93=0),"",M78/M93) | AG99: =IF(OR(N78="",N93="",N78=0,N93=0),"",N78/N93) | AH99: =IF(OR(O78="",O93="",O78=0,O93=0),"",O78/O93) | AI99: =IF(OR(P78="",P93="",P78=0,P93=0),"",P78/P93) | AJ99: =IF(OR(Q78="",Q93="",Q78=0,Q93=0),"",Q78/Q93)
D100: Cash Flow | F100: =F77 -> 2016-10 | G100: =G77 -> 2017-01 | H100: =H77 -> 2017-04 | I100: =I77 -> 2017-07 | J100: =J77 -> 2017-10 | M100: =M77 -> 2013 | N100: =N77 -> 2014 | O100: =O77 -> 2015 | P100: =P77 -> 2016 | Q100: =Q77 -> 2017 | R100: TTM | T100: Operating Margin | W100: =R81/R78 -> #DIV/0! | Y100: Total Debt | AB100: =J94+J96 -> 0
D101: Operating cash flow | AD101: Financial Health | AF101: =M77 -> 2013 | AG101: =N77 -> 2014 | AH101: =O77 -> 2015 | AI101: =P77 -> 2016 | AJ101: =Q77 -> 2017
D102: Capital expenditure | T102: Effectiveness | Y102: Cash Flow Statement | AD102: Current Ratio | AF102: =IF(OR(M92="",M95="",M92=0,M95=0),"",M92/M95) | AG102: =IF(OR(N92="",N95="",N92=0,N95=0),"",N92/N95) | AH102: =IF(OR(O92="",O95="",O92=0,O95=0),"",O92/O95) | AI102: =IF(OR(P92="",P95="",P92=0,P95=0),"",P92/P95) | AJ102: =IF(OR(Q92="",Q95="",Q92=0,Q95=0),"",Q92/Q95)
D103: Free cash flow | T103: Return on Equity | W103: =R82/AVERAGE(G98:J98) -> #DIV/0! | Y103: Operating Cash Flow | AB103: =AVERAGE(O101:Q101) -> #DIV/0! | AD103: Financial Leverage | AF103: =IF(OR(M93="",M96="",M93=0,M96=0),"",M93/M96) | AG103: =IF(OR(N93="",N96="",N93=0,N96=0),"",N93/N96) | AH103: =IF(OR(O93="",O96="",O93=0,O96=0),"",O93/O96) | AI103: =IF(OR(P93="",P96="",P93=0,P96=0),"",P93/P96) | AJ103: =IF(OR(Q93="",Q96="",Q93=0,Q96=0),"",Q93/Q96)
T104: Return on Assets | W104: =R82/AVERAGE(G93:J93) -> #DIV/0! | Y104: Capital Expenditure | AB104: =ABS(AVERAGE(O102:Q102)) -> #DIV/0! | AD104: Debt / Equity | AF104: =IF(OR(M98="",M96="",M96=0,M98=0),"",M98/M96) | AG104: =IF(OR(N98="",N96="",N96=0,N98=0),"",N98/N96) | AH104: =IF(OR(O98="",O96="",O96=0,O98=0),"",O98/O96) | AI104: =IF(OR(P98="",P96="",P96=0,P98=0),"",P98/P96) | AJ104: =IF(OR(Q98="",Q96="",Q96=0,Q98=0),"",Q98/Q96)
T105: Return on Capital Employed | W105: =R81/(AVERAGE(G98:J98)+(AVERAGE(G93:J93)-AVERAGE(G95:J95))) -> #DIV/0! | Y105: Free Cash Flow | AB105: =AVERAGE(O103:Q103) -> #DIV/0!
T106: Asset Turnover | W106: =R78/AVERAGE(G93:J93) -> #DIV/0!
A109: 4 | T109: Symbol | U109: CCUR
D111: Income Statement | F111: 2016-10 | G111: 2017-01 | H111: 2017-04 | I111: 2017-07 | J111: 2017-10 | M111: 2013 | N111: 2014 | O111: 2015 | P111: 2016 | Q111: 2017 | R111: TTM | T111: Quote | Y111: Growth | AB111: 5-Year Average | AD111: Key Ratios ― Growth, YOY | AG111: =N111 -> 2014 | AH111: =O111 -> 2015 | AI111: =P111 -> 2016 | AJ111: =Q111 -> 2017
D112: Revenue | T112: Last Price | W112: 5.42 | Y112: Revenue | AB112: =IF(AB111="Year over Year",AJ112,IF(AB111="3-Year Average",AVERAGE(AI112:AJ112),IF(AB111="5-Year Average",AVERAGE(AG112:AJ112),""))) -> #DIV/0! | AD112: Revenue % | AG112: =IF(AND(N112>0,M112>0,M112<>""),N112/M112-1,IF(AND(M112<0,N112<0,M112<>""),(N112-M112)/ABS(M112),IF(AND(M112>0,N112<0,M112<>""),"L",IF(AND(M112<0,N112>0,M112<>""),"P","")))) | AH112: =IF(AND(O112>0,N112>0,N112<>""),O112/N112-1,IF(AND(N112<0,O112<0,N112<>""),(O112-N112)/ABS(N112),IF(AND(N112>0,O112<0,N112<>""),"L",IF(AND(N112<0,O112>0,N112<>""),"P","")))) | AI112: =IF(AND(P112>0,O112>0,O112<>""),P112/O112-1,IF(AND(O112<0,P112<0,O112<>""),(P112-O112)/ABS(O112),IF(AND(O112>0,P112<0,O112<>""),"L",IF(AND(O112<0,P112>0,O112<>""),"P","")))) | AJ112: =IF(AND(Q112>0,P112>0,P112<>""),Q112/P112-1,IF(AND(P112<0,Q112<0,P112<>""),(Q112-P112)/ABS(P112),IF(AND(P112>0,Q112<0,P112<>""),"L",IF(AND(P112<0,Q112>0,P112<>""),"P",""))))
D113: Cost of revenue | T113: Market Capitalization | W113: =W112*R120 -> 0 | Y113: Operating Income | AB113: =IF(AB111="Year over Year",AJ113,IF(AB111="3-Year Average",AVERAGE(AI113:AJ113),IF(AB111="5-Year Average",AVERAGE(AG113:AJ113),""))) -> #DIV/0! | AD113: Operating Income % | AG113: =IF(AND(N115>0,M115>0,M115<>""),N115/M115-1,IF(AND(M115<0,N115<0,M115<>""),(N115-M115)/ABS(M115),IF(AND(M115>0,N115<0,M115<>""),"L",IF(AND(M115<0,N115>0,M115<>""),"P","")))) | AH113: =IF(AND(O115>0,N115>0,N115<>""),O115/N115-1,IF(AND(N115<0,O115<0,N115<>""),(O115-N115)/ABS(N115),IF(AND(N115>0,O115<0,N115<>""),"L",IF(AND(N115<0,O115>0,N115<>""),"P","")))) | AI113: =IF(AND(P115>0,O115>0,O115<>""),P115/O115-1,IF(AND(O115<0,P115<0,O115<>""),(P115-O115)/ABS(O115),IF(AND(O115>0,P115<0,O115<>""),"L",IF(AND(O115<0,P115>0,O115<>""),"P","")))) | AJ113: =IF(AND(Q115>0,P115>0,P115<>""),Q115/P115-1,IF(AND(P115<0,Q115<0,P115<>""),(Q115-P115)/ABS(P115),IF(AND(P115>0,Q115<0,P115<>""),"L",IF(AND(P115<0,Q115>0,P115<>""),"P",""))))
D114: Gross profit | T114: Enterprise Value | W114: =W113+(J128+J130)-J124 -> 0 | Y114: Net Income | AB114: =IF(AB111="Year over Year",AJ114,IF(AB111="3-Year Average",AVERAGE(AI114:AJ114),IF(AB111="5-Year Average",AVERAGE(AG114:AJ114),""))) -> #DIV/0! | AD114: Net Income % | AG114: =IF(AND(N116>0,M116>0,M116<>""),N116/M116-1,IF(AND(M116<0,N116<0,M116<>""),(N116-M116)/ABS(M116),IF(AND(M116>0,N116<0,M116<>""),"L",IF(AND(M116<0,N116>0,M116<>""),"P","")))) | AH114: =IF(AND(O116>0,N116>0,N116<>""),O116/N116-1,IF(AND(N116<0,O116<0,N116<>""),(O116-N116)/ABS(N116),IF(AND(N116>0,O116<0,N116<>""),"L",IF(AND(N116<0,O116>0,N116<>""),"P","")))) | AI114: =IF(AND(P116>0,O116>0,O116<>""),P116/O116-1,IF(AND(O116<0,P116<0,O116<>""),(P116-O116)/ABS(O116),IF(AND(O116>0,P116<0,O116<>""),"L",IF(AND(O116<0,P116>0,O116<>""),"P","")))) | AJ114: =IF(AND(Q116>0,P116>0,P116<>""),Q116/P116-1,IF(AND(P116<0,Q116<0,P116<>""),(Q116-P116)/ABS(P116),IF(AND(P116>0,Q116<0,P116<>""),"L",IF(AND(P116<0,Q116>0,P116<>""),"P",""))))
D115: Operating income | T115: Book Value | W115: =J127-J131 -> 0 | Y115: Earnings Per Share | AB115: =IF(AB111="Year over Year",AJ115,IF(AB111="3-Year Average",AVERAGE(AI115:AJ115),IF(AB111="5-Year Average",AVERAGE(AG115:AJ115),""))) -> #DIV/0! | AD115: Earnings per share % | AG115: =IF(AND(N117>0,M117>0,M117<>""),N117/M117-1,IF(AND(M117<0,N117<0,M117<>""),(N117-M117)/ABS(M117),IF(AND(M117>0,N117<0,M117<>""),"L",IF(AND(M117<0,N117>0,M117<>""),"P","")))) | AH115: =IF(AND(O117>0,N117>0,N117<>""),O117/N117-1,IF(AND(N117<0,O117<0,N117<>""),(O117-N117)/ABS(N117),IF(AND(N117>0,O117<0,N117<>""),"L",IF(AND(N117<0,O117>0,N117<>""),"P","")))) | AI115: =IF(AND(P117>0,O117>0,O117<>""),P117/O117-1,IF(AND(O117<0,P117<0,O117<>""),(P117-O117)/ABS(O117),IF(AND(O117>0,P117<0,O117<>""),"L",IF(AND(O117<0,P117>0,O117<>""),"P","")))) | AJ115: =IF(AND(Q117>0,P117>0,P117<>""),Q117/P117-1,IF(AND(P117<0,Q117<0,P117<>""),(Q117-P117)/ABS(P117),IF(AND(P117>0,Q117<0,P117<>""),"L",IF(AND(P117<0,Q117>0,P117<>""),"P",""))))
D116: Net income | T116: Type | W116: =IF(W113>10000,"Large Cap",IF(AND(10000>W113,2000<W113),"Mid Cap",IF(AND(2000>W113,W113>50),"Small Cap",IF(W113<50,"Micro Cap",NA)))) -> Micro Cap
D117: Earnings per share | T117: Dividend Yield | Y117: Financial Health | AD117: Financials | AF117: =M111 -> 2013 | AG117: =N111 -> 2014 | AH117: =O111 -> 2015 | AI117: =P111 -> 2016 | AJ117: =Q111 -> 2017
D120: Weighted average share… | Y120: Current Ratio | AB120: =AVERAGE(G126:J126)/AVERAGE(G129:J129) -> #DIV/0! | AD120: Revenue | AF120: =IF(M112="","",M112) | AG120: =IF(N112="","",N112) | AH120: =IF(O112="","",O112) | AI120: =IF(P112="","",P112) | AJ120: =IF(Q112="","",Q112)
...

Sheet Sheet 3
A1: source
A2: Gross Margin % | C2: Return on Equity % | E2: Debt / Equity | G2: Current Ratio | I2: USD in Billion | K2: Year over Year
A3: Net Margin % | C3: Return on Assets % | E3: Financial Leverage | G3: Quick Ratio | I3: USD in Million | K3: 3-Year Average
A4: Operating Margin % | I4: USD in Thousand | K4: 5-Year Average
I5: USD
