Workbook
Name Bi_Weekly: 'Dollar Average (Model) (2)'!$B$16
Name Bi_Weekly: Overview!$N$6
Name Bi_Weekly: 'Principal 401k'!$B$7
Name Bi_Weekly: 'Dollar Average (Model)'!$B$16
Name Bi_weekly_2: 'Value Average (Model)'!$B$16
Name div: 'Dollar Average (Model) (2)'!$B$5
Name div: 'Dollar Average (Model)'!$B$5
Name divi: 'Dollar Average (Model) (2)'!$B$5
Name divi: 'Dollar Average (Model)'!$B$5
Name int: 'Dollar Average (Model) (2)'!$B$3
Name int: 'Principal 401k'!$B$3
Name int: 'Dollar Average (Model)'!$B$3
Name inte: 'Dollar Average (Model) (2)'!$B$3
Name inte: 'Principal 401k'!$B$3
Name inte: 'Dollar Average (Model)'!$B$3
Name inter: 'Value Average (Model)'!$B$3
Name Monthly: 'Dollar Average (Model) (2)'!$B$17
Name Monthly: Overview!$N$9
Name Monthly: 'Principal 401k'!$B$8
Name Monthly: 'Dollar Average (Model)'!$B$17
Name Monthly_2: 'Value Average (Model)'!$B$17
Name None: 'Dollar Average (Model) (2)'!$B$20
Name None: 'Principal 401k'!$B$11
Name None: 'Dollar Average (Model)'!$B$20
Name None_2: 'Value Average (Model)'!$B$20
Name Quarterly: 'Dollar Average (Model) (2)'!$B$18
Name Quarterly: Overview!$N$10
Name Quarterly: 'Principal 401k'!$B$9
Name Quarterly: 'Dollar Average (Model)'!$B$18
Name Quarterly_2: 'Value Average (Model)'!$B$18
Name Weekly: 'Dollar Average (Model) (2)'!$B$15
Name Weekly: 'Principal 401k'!$B$6
Name Weekly: 'Dollar Average (Model)'!$B$15
Name Weekly_2: 'Value Average (Model)'!$B$15
Name Yearly: 'Dollar Average (Model) (2)'!$B$19
Name Yearly: 'Principal 401k'!$B$10
Name Yearly: 'Dollar Average (Model)'!$B$19
Name Yearly_2: 'Value Average (Model)'!$B$19

Sheet Overview
A1: Snapshot | E1: Dollar Cost | F1: Value Cost | G1: Dollar Cost | H1: Value Cost | I1: Dollar Cost | J1: Value Cost
B2: Portfolio Funds | C2: Portfolio Weight | D2: Average Price | E2: Average Cost per Share | G2: Discount Rate | I2: Average Shares Purchased | K2: Total Fund IRR | N2: Dollar Cost Average | O2: Value Cost Average
B3: VTI | C3: 0.176 | D3: ='Dollar Average (Model)'!B30 -> 77.831077 | E3: ='Dollar Average (Model)'!M30 -> 77.051582 | F3: ='Value Average (Model)'!M30 -> 75.514545 | G3: ='Dollar Average (Model)'!M29 -> -0.77949533 | H3: ='Value Average (Model)'!M29 -> -2.3165325 | I3: ='Dollar Average (Model)'!M31 -> 0.090531688 | J3: ='Value Average (Model)'!M31 -> 0.036592087 | K3: ='Dollar Average (Model)'!B31 -> 0.61989038 | M3: Initial Investment | N3: =ABS('Dollar Average (Model)'!L35) -> 1000 | O3: =ABS('Value Average (Model)'!L35) -> 5000
B4: VTV | C4: 0.176 | D4: ='Dollar Average (Model)'!C30 -> 63.830793 | E4: ='Dollar Average (Model)'!N30 -> 60.368293 | F4: ='Value Average (Model)'!N30 -> 48.61672 | G4: ='Dollar Average (Model)'!N29 -> -3.4624995 | H4: ='Value Average (Model)'!N29 -> -15.214073 | I4: ='Dollar Average (Model)'!N31 -> 0.11555089 | J4: ='Value Average (Model)'!N31 -> 0.065323765 | K4: ='Dollar Average (Model)'!C31 -> 0.38407747 | M4: Interval | N4: ='Dollar Average (Model)'!B3 -> Quarterly | O4: =inter -> Monthly
B5: VOE | C5: 0.056 | D5: ='Dollar Average (Model)'!D30 -> 63.394837 | E5: ='Dollar Average (Model)'!O30 -> 57.28289 | F5: ='Value Average (Model)'!O30 -> 35.660738 | G5: ='Dollar Average (Model)'!O29 -> -6.1119472 | H5: ='Value Average (Model)'!O29 -> -27.7341 | I5: ='Dollar Average (Model)'!O31 -> 0.038746512 | J5: ='Value Average (Model)'!O31 -> 0.019528415 | K5: ='Dollar Average (Model)'!D31 -> 0.73895158 | M5: Amount Invested | N5: ='Dollar Average (Model)'!B4 -> 500 | O5: ='Value Average (Model)'!B4 -> 100
B6: VBR | C6: 0.049 | D6: ='Dollar Average (Model)'!E30 -> 76.877317 | E6: ='Dollar Average (Model)'!P30 -> 70.419112 | F6: ='Value Average (Model)'!P30 -> 38.843664 | G6: ='Dollar Average (Model)'!P29 -> -6.4582054 | H6: ='Value Average (Model)'!P29 -> -38.033652 | I6: ='Dollar Average (Model)'!P31 -> 0.02757878 | J6: ='Value Average (Model)'!P31 -> 0.013795669 | K6: ='Dollar Average (Model)'!E31 -> 0.79845425
B7: VEA | C7: 0.411 | D7: ='Dollar Average (Model)'!F30 -> 36.556667 | E7: ='Dollar Average (Model)'!Q30 -> 36.365026 | F7: ='Value Average (Model)'!Q30 -> 34.393503 | G7: ='Dollar Average (Model)'!Q29 -> -0.19164065 | H7: ='Value Average (Model)'!Q29 -> -2.1631635 | I7: ='Dollar Average (Model)'!Q31 -> 0.44794782 | J7: ='Value Average (Model)'!Q31 -> 0.38707686 | K7: ='Dollar Average (Model)'!F31 -> -0.22535504 | M7: Total Invested | O7: =ABS('Value Average (Model)'!BJ33) -> 12184.608
B8: VWO | C8: 0.132 | D8: ='Dollar Average (Model)'!G30 -> 40.316646 | E8: ='Dollar Average (Model)'!R30 -> 41.764143 | F8: ='Value Average (Model)'!R30 -> 39.179513 | G8: ='Dollar Average (Model)'!R29 -> 1.4474964 | H8: ='Value Average (Model)'!R29 -> -1.1371332 | I8: ='Dollar Average (Model)'!R31 -> 0.12526792 | J8: ='Value Average (Model)'!R31 -> 0.10927139 | K8: ='Dollar Average (Model)'!G31 -> -0.20665188 | M8: Total Value | O8: ='Value Average (Model)'!BK33 -> 16896.5
M9: Total Return | N9: ='Dollar Average (Model)'!F4 -> 0.264261 | O9: ='Value Average (Model)'!F3 -> 9.4615385
A10: Unweighted Avg | C10: =SUM(C3:C8) -> 1 | D10: =AVERAGE(D3:D8) -> 59.801223 | E10: =AVERAGE(E3:E8) -> 57.208508 | F10: =AVERAGE(F3:F8) -> 45.368114 | G10: =AVERAGE(G3:G8) -> -2.5927153 | H10: =AVERAGE(H3:H8) -> -14.433109 | I10: =AVERAGE(I3:I8) -> 0.14093727 | J10: =AVERAGE(J3:J8) -> 0.1052647 | K10: =AVERAGE(K3:K8) -> 0.35156113 | M10: Capital Gain/Loss | O10: ='Value Average (Model)'!F4 -> 0.38670859
A11: Weighted Avg | C11: =SUM(C3:C8) -> 1 | D11: =AVERAGE(($C$3*D3)+($C$4*D4)+($C$5*D5)+($C$6*D6)+($C$7*D7)+($C$8*D8)) -> 52.596176 | E11: =AVERAGE(($C$3*E3)+($C$4*E4)+($C$5*E5)+($C$6*E6)+($C$7*E7)+($C$8*E8)) -> 51.303169 | F11: =AVERAGE(($C$3*F3)+($C$4*F4)+($C$5*F5)+($C$6*F6)+($C$7*F7)+($C$8*F8)) -> 45.054869 | G11: =AVERAGE(($C$3*G3)+($C$4*G4)+($C$5*G5)+($C$6*G6)+($C$7*G7)+($C$8*G8)) -> -1.293007 | H11: =AVERAGE(($C$3*H3)+($C$4*H4)+($C$5*H5)+($C$6*H6)+($C$7*H7)+($C$8*H8)) -> -7.5413069 | I11: =AVERAGE(($C$3*I3)+($C$4*I4)+($C$5*I5)+($C$6*I6)+($C$7*I7)+($C$8*I8)) -> 0.24043362 | J11: =AVERAGE(($C$3*J3)+($C$4*J4)+($C$5*J5)+($C$6*J6)+($C$7*J7)+($C$8*J8)) -> 0.19321918 | K11: =AVERAGE((C3*K3)+(C4*K4)+(C5*K5)+(C6*K6)+(C7*K7)+(C8*K8)) -> 0.13730492 | M11: Total Shares Bought | N11: =SUM('Dollar Average (Model)'!S33:X33) -> 422.48965 | O11: =SUM('Value Average (Model)'!S33:X33) -> 310.74139
M12: Total Shares Owned | N12: =SUM('Dollar Average (Model)'!S33:X33) -> 422.48965 | O12: =SUM('Value Average (Model)'!Y33:AD33) -> 326.68069

Sheet Dollar Average (Model)
A1: Dollar Cost Average Method (DCA)
A2: Initial Investment | B2: 1000 | E2: % Change | F2: =AVERAGE((B31*B29)+(C31*C29)+(D31*D29)+(E31*E29)+(F31*F29)+(G31*G29)) -> 0.13730492
A3: Interval | B3: Quarterly | E3: Period (Yr.) | F3: =COUNT(A35:A526)/52 -> 9.4615385
A4: Amount Invested | B4: 500 | E4: Return on Principal | F4: =BF33 -> 0.264261
E5: Gain/Loss | F5: =BE33+BD33 -> 5153.0896
E6: Annual Return | F6: =((BE33/ABS(BD33))^(1/F3))-1 -> 0.025092918
F7: Dividends Retained | H7: Dividends Reinvested
E8: Total Return (%) | F8: =BI33 -> 0.41379345 | H8: =BL33 -> 0.43697166
E9: Gain/Loss | F9: =BH33+BD33 -> 8068.9724 | H9: =BK33+BD33 -> 8520.9474
E10: Annual Return | F10: =((BH33/ABS(BD33))^(1/F3))-1 -> 0.037276292 | H10: =((BK33/ABS(BD33))^(1/F3))-1 -> 0.039060576
B15: Weekly
B16: Bi-weekly
B17: Monthly
B18: Quarterly
B19: Yearly
B20: None
A28: Symbol | B28: VTI | C28: VTV | D28: VOE | E28: VBR | F28: VEA | G28: VWO | M28: =B28 -> VTI | N28: =C28 -> VTV | O28: =D28 -> VOE | P28: =E28 -> VBR | Q28: =F28 -> VEA | R28: =G28 -> VWO
A29: Weight | B29: 0.176 | C29: 0.176 | D29: 0.056 | E29: 0.049 | F29: 0.411 | G29: 0.132 | J29: =SUM(B29:G29) -> 1 | L29: Discount Rate | M29: =M30-B30 -> -0.77949533 | N29: =N30-C30 -> -3.4624995 | O29: =O30-D30 -> -6.1119472 | P29: =P30-E30 -> -6.4582054 | Q29: =Q30-F30 -> -0.19164065 | R29: =R30-G30 -> 1.4474964
A30: Average Price | B30: =AVERAGE(BQ35:BQ80,B81:B526) -> 77.831077 | C30: =AVERAGE(C35:C526) -> 63.830793 | D30: =AVERAGE(D35:D526) -> 63.394837 | E30: =AVERAGE(E35:E526) -> 76.877317 | F30: =AVERAGE(F35:F526) -> 36.556667 | G30: =AVERAGE(BR35:BR80,G81:G526) -> 40.316646 | L30: Average Cost per Share | M30: =($M$32*B29)/M31 -> 77.051582 | N30: =($M$32*C29)/N31 -> 60.368293 | O30: =($M$32*D29)/O31 -> 57.28289 | P30: =($M$32*E29)/P31 -> 70.419112 | Q30: =($M$32*F29)/Q31 -> 36.365026 | R30: =($M$32*G29)/R31 -> 41.764143
A31: Return | B31: =(B526-($B$35/2))/($B$35/2) -> 0.61989038 | C31: =(C526-$C$35)/$C$35 -> 0.38407747 | D31: =(D526-$D$35)/$D$35 -> 0.73895158 | E31: =(E526-$E$35)/$E$35 -> 0.79845425 | F31: =(F526-$F$35)/$F$35 -> -0.22535504 | G31: =(G526-($G$35/2))/($G$35/2) -> -0.20665188 | L31: Average Shares Purchased | M31: =AVERAGE(M35:M526) -> 0.090531688 | N31: =AVERAGE(N35:N526) -> 0.11555089 | O31: =AVERAGE(O35:O526) -> 0.038746512 | P31: =AVERAGE(P35:P526) -> 0.02757878 | Q31: =AVERAGE(Q35:Q526) -> 0.44794782 | R31: =AVERAGE(R35:R526) -> 0.12526792
L32: Average Amount Invested | M32: =ABS(AVERAGE($L$35:$L$526)) -> 39.634146
A33: Date | B33: NAV ($) | C33: NAV ($) | D33: NAV ($) | E33: NAV ($) | F33: NAV ($) | G33: NAV ($) | L33: Totals | M33: =SUM(M35:M526) -> 44.54159 | N33: =SUM(N35:N526) -> 56.851036 | O33: =SUM(O35:O526) -> 19.063284 | P33: =SUM(P35:P526) -> 13.56876 | Q33: =SUM(Q35:Q526) -> 220.39033 | R33: =SUM(R35:R526) -> 61.631817 | S33: =S526 -> 47.627887 | T33: =T526 -> 56.851036 | U33: =U526 -> 19.063284 | V33: =V526 -> 13.56876 | W33: =W526 -> 220.39033 | X33: =X526 -> 64.988357 | BC33: =ABS(SUM(BC35:BC526)) -> 2915.8828 | BD33: =BD526 -> -19500 | BE33: =BE526 -> 24653.09 | BF33: =BF526 -> 0.264261 | BG33: =BG526 -> 2915.8828 | BH33: =BH526 -> 27568.972 | BI33: =BI526 -> 0.41379345 | BJ33: =BJ526 -> 3367.8578 | BK33: =BK526 -> 28020.947 | BL33: =BL526 -> 0.43697166 | BO33: =BO526 -> 28020.947
L34: Amount Invested | M34: Shares (#) | S34: Total Shares (#) | Y34: Dividend Payout/Share ($) | AE34: Dividend ($) | AK34: Additional Shares | AQ34: Total Additional Shares | AW34: New Total Shares (#) | BC34: Dividend Payout ($) | BD34: Principal ($) | BE34: Value ($) | BF34: Return (%) | BG34: Dividend Value ($) | BH34: Total Value ($) | BI34: Return (%) | BJ34: Dividend Value ($) | BK34: Total Value ($) | BL34: Return (%) | BN34: Absolute Total Invested | BQ34: VTI | BR34: VWO
A35: 39293 | B35: 142.38001 | C35: 67.199997 | D35: 55.889999 | E35: 67.279999 | F35: 47.169998 | G35: 90.199997 | L35: =-B2 -> -1000 | M35: =(ABS((L35*$B$29)/B35)) -> 1.2361286 | N35: =(ABS((L35*$C$29)/C35)) -> 2.6190477 | O35: =(ABS((L35*$D$29)/D35)) -> 1.0019682 | P35: =(ABS((L35*$E$29)/E35)) -> 0.72829965 | Q35: =(ABS((L35*$F$29)/F35)) -> 8.7131655 | R35: =(ABS((L35*$G$29)/G35)) -> 1.4634147 | S35: =M35 -> 1.2361286 | T35: =N35 -> 2.6190477 | U35: =O35 -> 1.0019682 | V35: =P35 -> 0.72829965 | W35: =Q35 -> 8.7131655 | X35: =R35 -> 1.4634147 | AE35: =(S35*Y35) -> 0 | AF35: =(T35*Z35) -> 0 | AG35: =(U35*AA35) -> 0 | AH35: =(V35*AB35) -> 0 | AI35: =(W35*AC35) -> 0 | AJ35: =(X35*AD35) -> 0 | AK35: =IF(AE35>0,AE35/B35,0) -> 0 | AL35: =IF(AF35>0,AF35/C35,0) -> 0 | AM35: =IF(AG35>0,AG35/D35,0) -> 0 | AN35: =IF(AH35>0,AH35/E35,0) -> 0 | AO35: =IF(AI35>0,AI35/F35,0) -> 0 | AP35: =IF(AJ35>0,AJ35/G35,0) -> 0 | AQ35: =AK35 -> 0 | AR35: =AL35 -> 0 | AS35: =AM35 -> 0 | AT35: =AN35 -> 0 | AU35: =AO35 -> 0 | AV35: =AP35 -> 0 | AW35: =S35+AK35 -> 1.2361286 | AX35: =T35+AL35 -> 2.6190477 | AY35: =U35+AM35 -> 1.0019682 | AZ35: =V35+AN35 -> 0.72829965 | BA35: =W35+AO35 -> 8.7131655 | BB35: =X35+AP35 -> 1.4634147 | BC35: =(AE35+AF35+AG35+AH35+AI35+AJ35) -> 0 | BD35: =L35+BC35 -> -1000 | BE35: =(S35*B35)+(T35*C35)+(U35*D35)+(V35*E35)+(W35*F35)+(X35*G35) -> 1000 | BF35: =(BE35/ABS(BD35))-1 -> 0 | BG35: =BC35 -> 0 | BH35: =BE35+BG35 -> 1000 | BI35: =(BH35/ABS(BD35))-1 -> 0 | BJ35: =(B35*AQ35)+(C35*AR35)+(D35*AS35)+(E35*AT35)+(F35*AU35)+(G35*AV35) -> 0 | BK35: =BE35+BJ35 -> 1000 | BL35: =(BK35/ABS(BD35))-1 -> 0 | BN35: =ABS(BD35) -> 1000 | BO35: =(B35*AW35)+(C35*AX35)+(D35*AY35)+(E35*AZ35)+(F35*BA35)+(G35*BB35) -> 1000 | BQ35: =B35/2 -> 71.190003 | BR35: =G35/2 -> 45.099998
A36: 39300 | B36: 143.72 | C36: 68.300003 | D36: 56.41 | E36: 69.68 | F36: 46.59 | G36: 90.449997 | L36: =IF(int=Weekly,-$B$4,IF(int=Bi_Weekly,0,IF(int=Monthly,0,IF(int=Quarterly,0,IF(int=Yearly,0,IF(int=None,0,0)))))) -> 0 | M36: =(ABS((L36*$B$29)/B36)) -> 0 | N36: =(ABS((L36*$C$29)/C36)) -> 0 | O36: =(ABS((L36*$D$29)/D36)) -> 0 | P36: =(ABS((L36*$E$29)/E36)) -> 0 | Q36: =(ABS((L36*$F$29)/F36)) -> 0 | R36: =(ABS((L36*$G$29)/G36)) -> 0 | S36: =S35+M36 -> 1.2361286 | T36: =T35+N36 -> 2.6190477 | U36: =U35+O36 -> 1.0019682 | V36: =V35+P36 -> 0.72829965 | W36: =W35+Q36 -> 8.7131655 | X36: =X35+R36 -> 1.4634147 | AE36: =(S36*Y36) -> 0 | AF36: =(T36*Z36) -> 0 | AG36: =(U36*AA36) -> 0 | AH36: =(V36*AB36) -> 0 | AI36: =(W36*AC36) -> 0 | AJ36: =(X36*AD36) -> 0 | AK36: =IF(AE36>0,AE36/B36,0) -> 0 | AL36: =IF(AF36>0,AF36/C36,0) -> 0 | AM36: =IF(AG36>0,AG36/D36,0) -> 0 | AN36: =IF(AH36>0,AH36/E36,0) -> 0 | AO36: =IF(AI36>0,AI36/F36,0) -> 0 | AP36: =IF(AJ36>0,AJ36/G36,0) -> 0 | AQ36: =AK36+AQ35+IF(AK36<0,AK36,0) -> 0 | AR36: =AL36+AR35+IF(AL36<0,AL36,0) -> 0 | AS36: =AM36+AS35+IF(AM36<0,AM36,0) -> 0 | AT36: =AN36+AT35+IF(AN36<0,AN36,0) -> 0 | AU36: =AO36+AU35+IF(AO36<0,AO36,0) -> 0 | AV36: =AP36+AV35+IF(AP36<0,AP36,0) -> 0 | AW36: =S36+AQ36 -> 1.2361286 | AX36: =T36+AR36 -> 2.6190477 | AY36: =U36+AS36 -> 1.0019682 | AZ36: =V36+AT36 -> 0.72829965 | BA36: =W36+AU36 -> 8.7131655 | BB36: =X36+AV36 -> 1.4634147 | BC36: =(AE36+AF36+AG36+AH36+AI36+AJ36) -> 0 | BD36: =BD35+L36 -> -1000 | BE36: =(S36*B36)+(T36*C36)+(U36*D36)+(V36*E36)+(W36*F36)+(X36*G36) -> 1002.1186 | BF36: =(BE36/ABS(BD36))-1 -> 0.0021185551 | BG36: =-(BG35+BC36) -> 0 | BH36: =BE36+BG36 -> 1002.1186 | BI36: =(BH36/ABS(BD36))-1 -> 0.0021185551 | BJ36: =(B36*AQ36)+(C36*AR36)+(D36*AS36)+(E36*AT36)+(F36*AU36)+(G36*AV36) -> 0 | BK36: =BE36+BJ36 -> 1002.1186 | BL36: =(BK36/ABS(BD36))-1 -> 0.0021185551 | BN36: =ABS(BD36) -> 1000 | BO36: =(B36*AW36)+(C36*AX36)+(D36*AY36)+(E36*AZ36)+(F36*BA36)+(G36*BB36) -> 1002.1186 | BQ36: =B36/2 -> 71.86 | BR36: =G36/2 -> 45.224998
A37: 39307 | B37: 143.06 | C37: 68.809998 | D37: 55.959999 | E37: 69.309998 | F37: 45.400002 | G37: 85.559998 | L37: =IF(int=Weekly,-$B$4,IF(int=Bi_Weekly,-$B$4,IF(int=Monthly,0,IF(int=Quarterly,0,IF(int=Yearly,0,IF(int=None,0,0)))))) -> 0 | M37: =(ABS((L37*$B$29)/B37)) -> 0 | N37: =(ABS((L37*$C$29)/C37)) -> 0 | O37: =(ABS((L37*$D$29)/D37)) -> 0 | P37: =(ABS((L37*$E$29)/E37)) -> 0 | Q37: =(ABS((L37*$F$29)/F37)) -> 0 | R37: =(ABS((L37*$G$29)/G37)) -> 0 | S37: =S36+M37 -> 1.2361286 | T37: =T36+N37 -> 2.6190477 | U37: =U36+O37 -> 1.0019682 | V37: =V36+P37 -> 0.72829965 | W37: =W36+Q37 -> 8.7131655 | X37: =X36+R37 -> 1.4634147 | AE37: =(S37*Y37) -> 0 | AF37: =(T37*Z37) -> 0 | AG37: =(U37*AA37) -> 0 | AH37: =(V37*AB37) -> 0 | AI37: =(W37*AC37) -> 0 | AJ37: =(X37*AD37) -> 0 | AK37: =IF(AE37>0,AE37/B37,0) -> 0 | AL37: =IF(AF37>0,AF37/C37,0) -> 0 | AM37: =IF(AG37>0,AG37/D37,0) -> 0 | AN37: =IF(AH37>0,AH37/E37,0) -> 0 | AO37: =IF(AI37>0,AI37/F37,0) -> 0 | AP37: =IF(AJ37>0,AJ37/G37,0) -> 0 | AQ37: =AK37+AQ36+IF(AK37<0,AK37,0) -> 0 | AR37: =AL37+AR36+IF(AL37<0,AL37,0) -> 0 | AS37: =AM37+AS36+IF(AM37<0,AM37,0) -> 0 | AT37: =AN37+AT36+IF(AN37<0,AN37,0) -> 0 | AU37: =AO37+AU36+IF(AO37<0,AO37,0) -> 0 | AV37: =AP37+AV36+IF(AP37<0,AP37,0) -> 0 | AW37: =S37+AQ37 -> 1.2361286 | AX37: =T37+AR37 -> 2.6190477 | AY37: =U37+AS37 -> 1.0019682 | AZ37: =V37+AT37 -> 0.72829965 | BA37: =W37+AU37 -> 8.7131655 | BB37: =X37+AV37 -> 1.4634147 | BC37: =(AE37+AF37+AG37+AH37+AI37+AJ37) -> 0 | BD37: =BD36+L37 -> -1000 | BE37: =(S37*B37)+(T37*C37)+(U37*D37)+(V37*E37)+(W37*F37)+(X37*G37) -> 984.3933 | BF37: =(BE37/ABS(BD37))-1 -> -0.015606697 | BG37: =BG36+BC37 -> 0 | BH37: =BE37+BG37 -> 984.3933 | BI37: =(BH37/ABS(BD37))-1 -> -0.015606697 | BJ37: =(B37*AQ37)+(C37*AR37)+(D37*AS37)+(E37*AT37)+(F37*AU37)+(G37*AV37) -> 0 | BK37: =BE37+BJ37 -> 984.3933 | BL37: =(BK37/ABS(BD37))-1 -> -0.015606697 | BN37: =ABS(BD37) -> 1000 | BO37: =(B37*AW37)+(C37*AX37)+(D37*AY37)+(E37*AZ37)+(F37*BA37)+(G37*BB37) -> 984.3933 | BQ37: =B37/2 -> 71.529999 | BR37: =G37/2 -> 42.779999
A38: 39314 | B38: 146.85001 | C38: 70.290001 | D38: 57.66 | E38: 70.949997 | F38: 47.540001 | G38: 91.620003 | L38: =IF(int=Weekly,-$B$4,IF(int=Bi_Weekly,0,IF(int=Monthly,0,IF(int=Quarterly,0,IF(int=Yearly,0,IF(int=None,0,0)))))) -> 0 | M38: =(ABS((L38*$B$29)/B38)) -> 0 | N38: =(ABS((L38*$C$29)/C38)) -> 0 | O38: =(ABS((L38*$D$29)/D38)) -> 0 | P38: =(ABS((L38*$E$29)/E38)) -> 0 | Q38: =(ABS((L38*$F$29)/F38)) -> 0 | R38: =(ABS((L38*$G$29)/G38)) -> 0 | S38: =S37+M38 -> 1.2361286 | T38: =T37+N38 -> 2.6190477 | U38: =U37+O38 -> 1.0019682 | V38: =V37+P38 -> 0.72829965 | W38: =W37+Q38 -> 8.7131655 | X38: =X37+R38 -> 1.4634147 | AE38: =(S38*Y38) -> 0 | AF38: =(T38*Z38) -> 0 | AG38: =(U38*AA38) -> 0 | AH38: =(V38*AB38) -> 0 | AI38: =(W38*AC38) -> 0 | AJ38: =(X38*AD38) -> 0 | AK38: =IF(AE38>0,AE38/B38,0) -> 0 | AL38: =IF(AF38>0,AF38/C38,0) -> 0 | AM38: =IF(AG38>0,AG38/D38,0) -> 0 | AN38: =IF(AH38>0,AH38/E38,0) -> 0 | AO38: =IF(AI38>0,AI38/F38,0) -> 0 | AP38: =IF(AJ38>0,AJ38/G38,0) -> 0 | AQ38: =AK38+AQ37+IF(AK38<0,AK38,0) -> 0 | AR38: =AL38+AR37+IF(AL38<0,AL38,0) -> 0 | AS38: =AM38+AS37+IF(AM38<0,AM38,0) -> 0 | AT38: =AN38+AT37+IF(AN38<0,AN38,0) -> 0 | AU38: =AO38+AU37+IF(AO38<0,AO38,0) -> 0 | AV38: =AP38+AV37+IF(AP38<0,AP38,0) -> 0 | AW38: =S38+AQ38 -> 1.2361286 | AX38: =T38+AR38 -> 2.6190477 | AY38: =U38+AS38 -> 1.0019682 | AZ38: =V38+AT38 -> 0.72829965 | BA38: =W38+AU38 -> 8.7131655 | BB38: =X38+AV38 -> 1.4634147 | BC38: =(AE38+AF38+AG38+AH38+AI38+AJ38) -> 0 | BD38: =BD37+L38 -> -1000 | BE38: =(S38*B38)+(T38*C38)+(U38*D38)+(V38*E38)+(W38*F38)+(X38*G38) -> 1023.3667 | BF38: =(BE38/ABS(BD38))-1 -> 0.023366662 | BG38: =BG37+BC38 -> 0 | BH38: =BE38+BG38 -> 1023.3667 | BI38: =(BH38/ABS(BD38))-1 -> 0.023366662 | BJ38: =(B38*AQ38)+(C38*AR38)+(D38*AS38)+(E38*AT38)+(F38*AU38)+(G38*AV38) -> 0 | BK38: =BE38+BJ38 -> 1023.3667 | BL38: =(BK38/ABS(BD38))-1 -> 0.023366662 | BN38: =ABS(BD38) -> 1000 | BO38: =(B38*AW38)+(C38*AX38)+(D38*AY38)+(E38*AZ38)+(F38*BA38)+(G38*BB38) -> 1023.3667 | BQ38: =B38/2 -> 73.425003 | BR38: =G38/2 -> 45.810001
A39: 39321 | B39: 146.22 | C39: 69.5 | D39: 57.259998 | E39: 70.220001 | F39: 47.860001 | G39: 94.489998 | L39: =IF(int=Weekly,-$B$4,IF(int=Bi_Weekly,-$B$4,IF(int=Monthly,-$B$4,IF(int=Quarterly,0,IF(int=Yearly,0,IF(int=None,0,0)))))) -> 0 | M39: =(ABS((L39*$B$29)/B39)) -> 0 | N39: =(ABS((L39*$C$29)/C39)) -> 0 | O39: =(ABS((L39*$D$29)/D39)) -> 0 | P39: =(ABS((L39*$E$29)/E39)) -> 0 | Q39: =(ABS((L39*$F$29)/F39)) -> 0 | R39: =(ABS((L39*$G$29)/G39)) -> 0 | S39: =S38+M39 -> 1.2361286 | T39: =T38+N39 -> 2.6190477 | U39: =U38+O39 -> 1.0019682 | V39: =V38+P39 -> 0.72829965 | W39: =W38+Q39 -> 8.7131655 | X39: =X38+R39 -> 1.4634147 | AE39: =(S39*Y39) -> 0 | AF39: =(T39*Z39) -> 0 | AG39: =(U39*AA39) -> 0 | AH39: =(V39*AB39) -> 0 | AI39: =(W39*AC39) -> 0 | AJ39: =(X39*AD39) -> 0 | AK39: =IF(AE39>0,AE39/B39,0) -> 0 | AL39: =IF(AF39>0,AF39/C39,0) -> 0 | AM39: =IF(AG39>0,AG39/D39,0) -> 0 | AN39: =IF(AH39>0,AH39/E39,0) -> 0 | AO39: =IF(AI39>0,AI39/F39,0) -> 0 | AP39: =IF(AJ39>0,AJ39/G39,0) -> 0 | AQ39: =AK39+AQ38+IF(AK39<0,AK39,0) -> 0 | AR39: =AL39+AR38+IF(AL39<0,AL39,0) -> 0 | AS39: =AM39+AS38+IF(AM39<0,AM39,0) -> 0 | AT39: =AN39+AT38+IF(AN39<0,AN39,0) -> 0 | AU39: =AO39+AU38+IF(AO39<0,AO39,0) -> 0 | AV39: =AP39+AV38+IF(AP39<0,AP39,0) -> 0 | AW39: =S39+AQ39 -> 1.2361286 | AX39: =T39+AR39 -> 2.6190477 | AY39: =U39+AS39 -> 1.0019682 | AZ39: =V39+AT39 -> 0.72829965 | BA39: =W39+AU39 -> 8.7131655 | BB39: =X39+AV39 -> 1.4634147 | BC39: =(AE39+AF39+AG39+AH39+AI39+AJ39) -> 0 | BD39: =BD38+L39 -> -1000 | BE39: =(S39*B39)+(T39*C39)+(U39*D39)+(V39*E39)+(W39*F39)+(X39*G39) -> 1026.5746 | BF39: =(BE39/ABS(BD39))-1 -> 0.026574605 | BG39: =BG38+BC39 -> 0 | BH39: =BE39+BG39 -> 1026.5746 | BI39: =(BH39/ABS(BD39))-1 -> 0.026574605 | BJ39: =(B39*AQ39)+(C39*AR39)+(D39*AS39)+(E39*AT39)+(F39*AU39)+(G39*AV39) -> 0 | BK39: =BE39+BJ39 -> 1026.5746 | BL39: =(BK39/ABS(BD39))-1 -> 0.026574605 | BN39: =ABS(BD39) -> 1000 | BO39: =(B39*AW39)+(C39*AX39)+(D39*AY39)+(E39*AZ39)+(F39*BA39)+(G39*BB39) -> 1026.5746 | BQ39: =B39/2 -> 73.11 | BR39: =G39/2 -> 47.244999
A40: 39329 | B40: 144.92999 | C40: 68.589996 | D40: 56.330002 | E40: 68.779999 | F40: 46.880001 | G40: 93.110001 | L40: =IF(int=Weekly,-$B$4,IF(int=Bi_Weekly,0,IF(int=Monthly,0,IF(int=Quarterly,0,IF(int=Yearly,0,IF(int=None,0,0)))))) -> 0 | M40: =(ABS((L40*$B$29)/B40)) -> 0 | N40: =(ABS((L40*$C$29)/C40)) -> 0 | O40: =(ABS((L40*$D$29)/D40)) -> 0 | P40: =(ABS((L40*$E$29)/E40)) -> 0 | Q40: =(ABS((L40*$F$29)/F40)) -> 0 | R40: =(ABS((L40*$G$29)/G40)) -> 0 | S40: =S39+M40 -> 1.2361286 | T40: =T39+N40 -> 2.6190477 | U40: =U39+O40 -> 1.0019682 | V40: =V39+P40 -> 0.72829965 | W40: =W39+Q40 -> 8.7131655 | X40: =X39+R40 -> 1.4634147 | AE40: =(S40*Y40) -> 0 | AF40: =(T40*Z40) -> 0 | AG40: =(U40*AA40) -> 0 | AH40: =(V40*AB40) -> 0 | AI40: =(W40*AC40) -> 0 | AJ40: =(X40*AD40) -> 0 | AK40: =IF(AE40>0,AE40/B40,0) -> 0 | AL40: =IF(AF40>0,AF40/C40,0) -> 0 | AM40: =IF(AG40>0,AG40/D40,0) -> 0 | AN40: =IF(AH40>0,AH40/E40,0) -> 0 | AO40: =IF(AI40>0,AI40/F40,0) -> 0 | AP40: =IF(AJ40>0,AJ40/G40,0) -> 0 | AQ40: =AK40+AQ39+IF(AK40<0,AK40,0) -> 0 | AR40: =AL40+AR39+IF(AL40<0,AL40,0) -> 0 | AS40: =AM40+AS39+IF(AM40<0,AM40,0) -> 0 | AT40: =AN40+AT39+IF(AN40<0,AN40,0) -> 0 | AU40: =AO40+AU39+IF(AO40<0,AO40,0) -> 0 | AV40: =AP40+AV39+IF(AP40<0,AP40,0) -> 0 | AW40: =S40+AQ40 -> 1.2361286 | AX40: =T40+AR40 -> 2.6190477 | AY40: =U40+AS40 -> 1.0019682 | AZ40: =V40+AT40 -> 0.72829965 | BA40: =W40+AU40 -> 8.7131655 | BB40: =X40+AV40 -> 1.4634147 | BC40: =(AE40+AF40+AG40+AH40+AI40+AJ40) -> 0 | BD40: =BD39+L40 -> -1000 | BE40: =(S40*B40)+(T40*C40)+(U40*D40)+(V40*E40)+(W40*F40)+(X40*G40) -> 1010.0577 | BF40: =(BE40/ABS(BD40))-1 -> 0.010057656 | BG40: =BG39+BC40 -> 0 | BH40: =BE40+BG40 -> 1010.0577 | BI40: =(BH40/ABS(BD40))-1 -> 0.010057656 | BJ40: =(B40*AQ40)+(C40*AR40)+(D40*AS40)+(E40*AT40)+(F40*AU40)+(G40*AV40) -> 0 | BK40: =BE40+BJ40 -> 1010.0577 | BL40: =(BK40/ABS(BD40))-1 -> 0.010057656 | BN40: =ABS(BD40) -> 1000 | BO40: =(B40*AW40)+(C40*AX40)+(D40*AY40)+(E40*AZ40)+(F40*BA40)+(G40*BB40) -> 1010.0577 | BQ40: =B40/2 -> 72.464996 | BR40: =G40/2 -> 46.555
A41: 39335 | B41: 147.38001 | C41: 70.199997 | D41: 56.91 | E41: 69.300003 | F41: 47.529999 | G41: 95.919998 | L41: =IF(int=Weekly,-$B$4,IF(int=Bi_Weekly,-$B$4,IF(int=Monthly,0,IF(int=Quarterly,0,IF(int=Yearly,0,IF(int=None,0,0)))))) -> 0 | M41: =(ABS((L41*$B$29)/B41)) -> 0 | N41: =(ABS((L41*$C$29)/C41)) -> 0 | O41: =(ABS((L41*$D$29)/D41)) -> 0 | P41: =(ABS((L41*$E$29)/E41)) -> 0 | Q41: =(ABS((L41*$F$29)/F41)) -> 0 | R41: =(ABS((L41*$G$29)/G41)) -> 0 | S41: =S40+M41 -> 1.2361286 | T41: =T40+N41 -> 2.6190477 | U41: =U40+O41 -> 1.0019682 | V41: =V40+P41 -> 0.72829965 | W41: =W40+Q41 -> 8.7131655 | X41: =X40+R41 -> 1.4634147 | AE41: =(S41*Y41) -> 0 | AF41: =(T41*Z41) -> 0 | AG41: =(U41*AA41) -> 0 | AH41: =(V41*AB41) -> 0 | AI41: =(W41*AC41) -> 0 | AJ41: =(X41*AD41) -> 0 | AK41: =IF(AE41>0,AE41/B41,0) -> 0 | AL41: =IF(AF41>0,AF41/C41,0) -> 0 | AM41: =IF(AG41>0,AG41/D41,0) -> 0 | AN41: =IF(AH41>0,AH41/E41,0) -> 0 | AO41: =IF(AI41>0,AI41/F41,0) -> 0 | AP41: =IF(AJ41>0,AJ41/G41,0) -> 0 | AQ41: =AK41+AQ40+IF(AK41<0,AK41,0) -> 0 | AR41: =AL41+AR40+IF(AL41<0,AL41,0) -> 0 | AS41: =AM41+AS40+IF(AM41<0,AM41,0) -> 0 | AT41: =AN41+AT40+IF(AN41<0,AN41,0) -> 0 | AU41: =AO41+AU40+IF(AO41<0,AO41,0) -> 0 | AV41: =AP41+AV40+IF(AP41<0,AP41,0) -> 0 | AW41: =S41+AQ41 -> 1.2361286 | AX41: =T41+AR41 -> 2.6190477 | AY41: =U41+AS41 -> 1.0019682 | AZ41: =V41+AT41 -> 0.72829965 | BA41: =W41+AU41 -> 8.7131655 | BB41: =X41+AV41 -> 1.4634147 | BC41: =(AE41+AF41+AG41+AH41+AI41+AJ41) -> 0 | BD41: =BD40+L41 -> -1000 | BE41: =(S41*B41)+(T41*C41)+(U41*D41)+(V41*E41)+(W41*F41)+(X41*G41) -> 1028.0384 | BF41: =(BE41/ABS(BD41))-1 -> 0.028038445 | BG41: =BG40+BC41 -> 0 | BH41: =BE41+BG41 -> 1028.0384 | BI41: =(BH41/ABS(BD41))-1 -> 0.028038445 | BJ41: =(B41*AQ41)+(C41*AR41)+(D41*AS41)+(E41*AT41)+(F41*AU41)+(G41*AV41) -> 0 | BK41: =BE41+BJ41 -> 1028.0384 | BL41: =(BK41/ABS(BD41))-1 -> 0.028038445 | BN41: =ABS(BD41) -> 1000 | BO41: =(B41*AW41)+(C41*AX41)+(D41*AY41)+(E41*AZ41)+(F41*BA41)+(G41*BB41) -> 1028.0384 | BQ41: =B41/2 -> 73.690003 | BR41: =G41/2 -> 47.959999
A42: 39342 | B42: 151.22 | C42: 72.18 | D42: 58.23 | E42: 71.68 | F42: 49.110001 | G42: 100.75 | L42: =IF(int=Weekly,-$B$4,IF(int=Bi_Weekly,0,IF(int=Monthly,0,IF(int=Quarterly,0,IF(int=Yearly,0,IF(int=None,0,0)))))) -> 0 | M42: =(ABS((L42*$B$29)/B42)) -> 0 | N42: =(ABS((L42*$C$29)/C42)) -> 0 | O42: =(ABS((L42*$D$29)/D42)) -> 0 | P42: =(ABS((L42*$E$29)/E42)) -> 0 | Q42: =(ABS((L42*$F$29)/F42)) -> 0 | R42: =(ABS((L42*$G$29)/G42)) -> 0 | S42: =S41+M42 -> 1.2361286 | T42: =T41+N42 -> 2.6190477 | U42: =U41+O42 -> 1.0019682 | V42: =V41+P42 -> 0.72829965 | W42: =W41+Q42 -> 8.7131655 | X42: =X41+R42 -> 1.4634147 | AE42: =(S42*Y42) -> 0 | AF42: =(T42*Z42) -> 0 | AG42: =(U42*AA42) -> 0 | AH42: =(V42*AB42) -> 0 | AI42: =(W42*AC42) -> 0 | AJ42: =(X42*AD42) -> 0 | AK42: =IF(AE42>0,AE42/B42,0) -> 0 | AL42: =IF(AF42>0,AF42/C42,0) -> 0 | AM42: =IF(AG42>0,AG42/D42,0) -> 0 | AN42: =IF(AH42>0,AH42/E42,0) -> 0 | AO42: =IF(AI42>0,AI42/F42,0) -> 0 | AP42: =IF(AJ42>0,AJ42/G42,0) -> 0 | AQ42: =AK42+AQ41+IF(AK42<0,AK42,0) -> 0 | AR42: =AL42+AR41+IF(AL42<0,AL42,0) -> 0 | AS42: =AM42+AS41+IF(AM42<0,AM42,0) -> 0 | AT42: =AN42+AT41+IF(AN42<0,AN42,0) -> 0 | AU42: =AO42+AU41+IF(AO42<0,AO42,0) -> 0 | AV42: =AP42+AV41+IF(AP42<0,AP42,0) -> 0 | AW42: =S42+AQ42 -> 1.2361286 | AX42: =T42+AR42 -> 2.6190477 | AY42: =U42+AS42 -> 1.0019682 | AZ42: =V42+AT42 -> 0.72829965 | BA42: =W42+AU42 -> 8.7131655 | BB42: =X42+AV42 -> 1.4634147 | BC42: =(AE42+AF42+AG42+AH42+AI42+AJ42) -> 0 | BD42: =BD41+L42 -> -1000 | BE42: =(S42*B42)+(T42*C42)+(U42*D42)+(V42*E42)+(W42*F42)+(X42*G42) -> 1061.862 | BF42: =(BE42/ABS(BD42))-1 -> 0.06186196 | BG42: =BG41+BC42 -> 0 | BH42: =BE42+BG42 -> 1061.862 | BI42: =(BH42/ABS(BD42))-1 -> 0.06186196 | BJ42: =(B42*AQ42)+(C42*AR42)+(D42*AS42)+(E42*AT42)+(F42*AU42)+(G42*AV42) -> 0 | BK42: =BE42+BJ42 -> 1061.862 | BL42: =(BK42/ABS(BD42))-1 -> 0.06186196 | BN42: =ABS(BD42) -> 1000 | BO42: =(B42*AW42)+(C42*AX42)+(D42*AY42)+(E42*AZ42)+(F42*BA42)+(G42*BB42) -> 1061.862 | BQ42: =B42/2 -> 75.61 | BR42: =G42/2 -> 50.375
A43: 39349 | B43: 151.2 | C43: 71.510002 | D43: 58.369999 | E43: 70.830002 | F43: 50.139999 | G43: 103.78 | L43: =IF(int=Weekly,-$B$4,IF(int=Bi_Weekly,-$B$4,IF(int=Monthly,-$B$4,IF(int=Quarterly,0,IF(int=Yearly,0,IF(int=None,0,0)))))) -> 0 | M43: =(ABS((L43*$B$29)/B43)) -> 0 | N43: =(ABS((L43*$C$29)/C43)) -> 0 | O43: =(ABS((L43*$D$29)/D43)) -> 0 | P43: =(ABS((L43*$E$29)/E43)) -> 0 | Q43: =(ABS((L43*$F$29)/F43)) -> 0 | R43: =(ABS((L43*$G$29)/G43)) -> 0 | S43: =S42+M43 -> 1.2361286 | T43: =T42+N43 -> 2.6190477 | U43: =U42+O43 -> 1.0019682 | V43: =V42+P43 -> 0.72829965 | W43: =W42+Q43 -> 8.7131655 | X43: =X42+R43 -> 1.4634147 | Y43: 0.321 | Z43: 0.46 | AE43: =(S43*Y43) -> 0.39679729 | AF43: =(T43*Z43) -> 1.204762 | AG43: =(U43*AA43) -> 0 | AH43: =(V43*AB43) -> 0 | AI43: =(W43*AC43) -> 0 | AJ43: =(X43*AD43) -> 0 | AK43: =IF(AE43>0,AE43/B43,0) -> 0.0026243207 | AL43: =IF(AF43>0,AF43/C43,0) -> 0.016847461 | AM43: =IF(AG43>0,AG43/D43,0) -> 0 | AN43: =IF(AH43>0,AH43/E43,0) -> 0 | AO43: =IF(AI43>0,AI43/F43,0) -> 0 | AP43: =IF(AJ43>0,AJ43/G43,0) -> 0 | AQ43: =AK43+AQ42+IF(AK43<0,AK43,0) -> 0.0026243207 | AR43: =AL43+AR42+IF(AL43<0,AL43,0) -> 0.016847461 | AS43: =AM43+AS42+IF(AM43<0,AM43,0) -> 0 | AT43: =AN43+AT42+IF(AN43<0,AN43,0) -> 0 | AU43: =AO43+AU42+IF(AO43<0,AO43,0) -> 0 | AV43: =AP43+AV42+IF(AP43<0,AP43,0) -> 0 | AW43: =S43+AQ43 -> 1.2387529 | AX43: =T43+AR43 -> 2.6358952 | AY43: =U43+AS43 -> 1.0019682 | AZ43: =V43+AT43 -> 0.72829965 | BA43: =W43+AU43 -> 8.7131655 | BB43: =X43+AV43 -> 1.4634147 | BC43: =(AE43+AF43+AG43+AH43+AI43+AJ43) -> 1.6015592 | BD43: =BD42+L43 -> -1000 | BE43: =(S43*B43)+(T43*C43)+(U43*D43)+(V43*E43)+(W43*F43)+(X43*G43) -> 1073.0124 | BF43: =(BE43/ABS(BD43))-1 -> 0.073012385 | BG43: =BG42+BC43 -> 1.6015592 | BH43: =BE43+BG43 -> 1074.6139 | BI43: =(BH43/ABS(BD43))-1 -> 0.074613944 | BJ43: =(B43*AQ43)+(C43*AR43)+(D43*AS43)+(E43*AT43)+(F43*AU43)+(G43*AV43) -> 1.6015592 | BK43: =BE43+BJ43 -> 1074.6139 | BL43: =(BK43/ABS(BD43))-1 -> 0.074613944 | BN43: =ABS(BD43) -> 1000 | BO43: =(B43*AW43)+(C43*AX43)+(D43*AY43)+(E43*AZ43)+(F43*BA43)+(G43*BB43) -> 1074.6139 | BQ43: =B43/2 -> 75.599998 | BR43: =G43/2 -> 51.89
A44: 39356 | B44: 154.61 | C44: 73.120003 | D44: 60.119999 | E44: 73.699997 | F44: 51.130001 | G44: 109.6 | L44: =IF(int=Weekly,-$B$4,IF(int=Bi_Weekly,0,IF(int=Monthly,0,IF(int=Quarterly,0,IF(int=Yearly,0,IF(int=None,0,0)))))) -> 0 | M44: =(ABS((L44*$B$29)/B44)) -> 0 | N44: =(ABS((L44*$C$29)/C44)) -> 0 | O44: =(ABS((L44*$D$29)/D44)) -> 0 | P44: =(ABS((L44*$E$29)/E44)) -> 0 | Q44: =(ABS((L44*$F$29)/F44)) -> 0 | R44: =(ABS((L44*$G$29)/G44)) -> 0 | S44: =S43+M44 -> 1.2361286 | T44: =T43+N44 -> 2.6190477 | U44: =U43+O44 -> 1.0019682 | V44: =V43+P44 -> 0.72829965 | W44: =W43+Q44 -> 8.7131655 | X44: =X43+R44 -> 1.4634147 | AE44: =(S44*Y44) -> 0 | AF44: =(T44*Z44) -> 0 | AG44: =(U44*AA44) -> 0 | AH44: =(V44*AB44) -> 0 | AI44: =(W44*AC44) -> 0 | AJ44: =(X44*AD44) -> 0 | AK44: =IF(AE44>0,AE44/B44,0) -> 0 | AL44: =IF(AF44>0,AF44/C44,0) -> 0 | AM44: =IF(AG44>0,AG44/D44,0) -> 0 | AN44: =IF(AH44>0,AH44/E44,0) -> 0 | AO44: =IF(AI44>0,AI44/F44,0) -> 0 | AP44: =IF(AJ44>0,AJ44/G44,0) -> 0 | AQ44: =AK44+AQ43+IF(AK44<0,AK44,0) -> 0.0026243207 | AR44: =AL44+AR43+IF(AL44<0,AL44,0) -> 0.016847461 | AS44: =AM44+AS43+IF(AM44<0,AM44,0) -> 0 | AT44: =AN44+AT43+IF(AN44<0,AN44,0) -> 0 | AU44: =AO44+AU43+IF(AO44<0,AO44,0) -> 0 | AV44: =AP44+AV43+IF(AP44<0,AP44,0) -> 0 | AW44: =S44+AQ44 -> 1.2387529 | AX44: =T44+AR44 -> 2.6358952 | AY44: =U44+AS44 -> 1.0019682 | AZ44: =V44+AT44 -> 0.72829965 | BA44: =W44+AU44 -> 8.7131655 | BB44: =X44+AV44 -> 1.4634147 | BC44: =(AE44+AF44+AG44+AH44+AI44+AJ44) -> 0 | BD44: =BD43+L44 -> -1000 | BE44: =(S44*B44)+(T44*C44)+(U44*D44)+(V44*E44)+(W44*F44)+(X44*G44) -> 1102.431 | BF44: =(BE44/ABS(BD44))-1 -> 0.10243104 | BG44: =BG43+BC44 -> 1.6015592 | BH44: =BE44+BG44 -> 1104.0326 | BI44: =(BH44/ABS(BD44))-1 -> 0.1040326 | BJ44: =(B44*AQ44)+(C44*AR44)+(D44*AS44)+(E44*AT44)+(F44*AU44)+(G44*AV44) -> 1.6376326 | BK44: =BE44+BJ44 -> 1104.0687 | BL44: =(BK44/ABS(BD44))-1 -> 0.10406867 | BN44: =ABS(BD44) -> 1000 | BO44: =(B44*AW44)+(C44*AX44)+(D44*AY44)+(E44*AZ44)+(F44*BA44)+(G44*BB44) -> 1104.0687 | BQ44: =B44/2 -> 77.305001 | BR44: =G44/2 -> 54.799999
A45: 39363 | B45: 155.08 | C45: 72.93 | D45: 59.84 | E45: 73.029999 | F45: 51.52 | G45: 111.65 | L45: =IF(int=Weekly,-$B$4,IF(int=Bi_Weekly,-$B$4,IF(int=Monthly,0,IF(int=Quarterly,0,IF(int=Yearly,0,IF(int=None,0,0)))))) -> 0 | M45: =(ABS((L45*$B$29)/B45)) -> 0 | N45: =(ABS((L45*$C$29)/C45)) -> 0 | O45: =(ABS((L45*$D$29)/D45)) -> 0 | P45: =(ABS((L45*$E$29)/E45)) -> 0 | Q45: =(ABS((L45*$F$29)/F45)) -> 0 | R45: =(ABS((L45*$G$29)/G45)) -> 0 | S45: =S44+M45 -> 1.2361286 | T45: =T44+N45 -> 2.6190477 | U45: =U44+O45 -> 1.0019682 | V45: =V44+P45 -> 0.72829965 | W45: =W44+Q45 -> 8.7131655 | X45: =X44+R45 -> 1.4634147 | AE45: =(S45*Y45) -> 0 | AF45: =(T45*Z45) -> 0 | AG45: =(U45*AA45) -> 0 | AH45: =(V45*AB45) -> 0 | AI45: =(W45*AC45) -> 0 | AJ45: =(X45*AD45) -> 0 | AK45: =IF(AE45>0,AE45/B45,0) -> 0 | AL45: =IF(AF45>0,AF45/C45,0) -> 0 | AM45: =IF(AG45>0,AG45/D45,0) -> 0 | AN45: =IF(AH45>0,AH45/E45,0) -> 0 | AO45: =IF(AI45>0,AI45/F45,0) -> 0 | AP45: =IF(AJ45>0,AJ45/G45,0) -> 0 | AQ45: =AK45+AQ44+IF(AK45<0,AK45,0) -> 0.0026243207 | AR45: =AL45+AR44+IF(AL45<0,AL45,0) -> 0.016847461 | AS45: =AM45+AS44+IF(AM45<0,AM45,0) -> 0 | AT45: =AN45+AT44+IF(AN45<0,AN45,0) -> 0 | AU45: =AO45+AU44+IF(AO45<0,AO45,0) -> 0 | AV45: =AP45+AV44+IF(AP45<0,AP45,0) -> 0 | AW45: =S45+AQ45 -> 1.2387529 | AX45: =T45+AR45 -> 2.6358952 | AY45: =U45+AS45 -> 1.0019682 | AZ45: =V45+AT45 -> 0.72829965 | BA45: =W45+AU45 -> 8.7131655 | BB45: =X45+AV45 -> 1.4634147 | BC45: =(AE45+AF45+AG45+AH45+AI45+AJ45) -> 0 | BD45: =BD44+L45 -> -1000 | BE45: =(S45*B45)+(T45*C45)+(U45*D45)+(V45*E45)+(W45*F45)+(X45*G45) -> 1108.144 | BF45: =(BE45/ABS(BD45))-1 -> 0.10814402 | BG45: =BG44+BC45 -> 1.6015592 | BH45: =BE45+BG45 -> 1109.7456 | BI45: =(BH45/ABS(BD45))-1 -> 0.10974558 | BJ45: =(B45*AQ45)+(C45*AR45)+(D45*AS45)+(E45*AT45)+(F45*AU45)+(G45*AV45) -> 1.635665 | BK45: =BE45+BJ45 -> 1109.7797 | BL45: =(BK45/ABS(BD45))-1 -> 0.10977968 | BN45: =ABS(BD45) -> 1000 | BO45: =(B45*AW45)+(C45*AX45)+(D45*AY45)+(E45*AZ45)+(F45*BA45)+(G45*BB45) -> 1109.7797 | BQ45: =B45/2 -> 77.540001 | BR45: =G45/2 -> 55.825001
A46: 39370 | B46: 149 | C46: 69.580002 | D46: 57.220001 | E46: 69.029999 | F46: 49.950001 | G46: 106.59 | L46: =IF(int=Weekly,-$B$4,IF(int=Bi_Weekly,0,IF(int=Monthly,0,IF(int=Quarterly,0,IF(int=Yearly,0,IF(int=None,0,0)))))) -> 0 | M46: =(ABS((L46*$B$29)/B46)) -> 0 | N46: =(ABS((L46*$C$29)/C46)) -> 0 | O46: =(ABS((L46*$D$29)/D46)) -> 0 | P46: =(ABS((L46*$E$29)/E46)) -> 0 | Q46: =(ABS((L46*$F$29)/F46)) -> 0 | R46: =(ABS((L46*$G$29)/G46)) -> 0 | S46: =S45+M46 -> 1.2361286 | T46: =T45+N46 -> 2.6190477 | U46: =U45+O46 -> 1.0019682 | V46: =V45+P46 -> 0.72829965 | W46: =W45+Q46 -> 8.7131655 | X46: =X45+R46 -> 1.4634147 | AE46: =(S46*Y46) -> 0 | AF46: =(T46*Z46) -> 0 | AG46: =(U46*AA46) -> 0 | AH46: =(V46*AB46) -> 0 | AI46: =(W46*AC46) -> 0 | AJ46: =(X46*AD46) -> 0 | AK46: =IF(AE46>0,AE46/B46,0) -> 0 | AL46: =IF(AF46>0,AF46/C46,0) -> 0 | AM46: =IF(AG46>0,AG46/D46,0) -> 0 | AN46: =IF(AH46>0,AH46/E46,0) -> 0 | AO46: =IF(AI46>0,AI46/F46,0) -> 0 | AP46: =IF(AJ46>0,AJ46/G46,0) -> 0 | AQ46: =AK46+AQ45+IF(AK46<0,AK46,0) -> 0.0026243207 | AR46: =AL46+AR45+IF(AL46<0,AL46,0) -> 0.016847461 | AS46: =AM46+AS45+IF(AM46<0,AM46,0) -> 0 | AT46: =AN46+AT45+IF(AN46<0,AN46,0) -> 0 | AU46: =AO46+AU45+IF(AO46<0,AO46,0) -> 0 | AV46: =AP46+AV45+IF(AP46<0,AP46,0) -> 0 | AW46: =S46+AQ46 -> 1.2387529 | AX46: =T46+AR46 -> 2.6358952 | AY46: =U46+AS46 -> 1.0019682 | AZ46: =V46+AT46 -> 0.72829965 | BA46: =W46+AU46 -> 8.7131655 | BB46: =X46+AV46 -> 1.4634147 | BC46: =(AE46+AF46+AG46+AH46+AI46+AJ46) -> 0 | BD46: =BD45+L46 -> -1000 | BE46: =(S46*B46)+(T46*C46)+(U46*D46)+(V46*E46)+(W46*F46)+(X46*G46) -> 1065.2316 | BF46: =(BE46/ABS(BD46))-1 -> 0.065231648 | BG46: =BG45+BC46 -> 1.6015592 | BH46: =BE46+BG46 -> 1066.8332 | BI46: =(BH46/ABS(BD46))-1 -> 0.066833207 | BJ46: =(B46*AQ46)+(C46*AR46)+(D46*AS46)+(E46*AT46)+(F46*AU46)+(G46*AV46) -> 1.5632702 | BK46: =BE46+BJ46 -> 1066.7949 | BL46: =(BK46/ABS(BD46))-1 -> 0.066794918 | BN46: =ABS(BD46) -> 1000 | BO46: =(B46*AW46)+(C46*AX46)+(D46*AY46)+(E46*AZ46)+(F46*BA46)+(G46*BB46) -> 1066.7949 | BQ46: =B46/2 -> 74.5 | BR46: =G46/2 -> 53.294998
A47: 39377 | B47: 152.41 | C47: 71.18 | D47: 58.040001 | E47: 71.360001 | F47: 51.57 | G47: 115.14 | L47: =IF(int=Weekly,-$B$4,IF(int=Bi_Weekly,-$B$4,IF(int=Monthly,-$B$4,IF(int=Quarterly,0,IF(int=Yearly,0,IF(int=None,0,0)))))) -> 0 | M47: =(ABS((L47*$B$29)/B47)) -> 0 | N47: =(ABS((L47*$C$29)/C47)) -> 0 | O47: =(ABS((L47*$D$29)/D47)) -> 0 | P47: =(ABS((L47*$E$29)/E47)) -> 0 | Q47: =(ABS((L47*$F$29)/F47)) -> 0 | R47: =(ABS((L47*$G$29)/G47)) -> 0 | S47: =S46+M47 -> 1.2361286 | T47: =T46+N47 -> 2.6190477 | U47: =U46+O47 -> 1.0019682 | V47: =V46+P47 -> 0.72829965 | W47: =W46+Q47 -> 8.7131655 | X47: =X46+R47 -> 1.4634147 | AE47: =(S47*Y47) -> 0 | AF47: =(T47*Z47) -> 0 | AG47: =(U47*AA47) -> 0 | AH47: =(V47*AB47) -> 0 | AI47: =(W47*AC47) -> 0 | AJ47: =(X47*AD47) -> 0 | AK47: =IF(AE47>0,AE47/B47,0) -> 0 | AL47: =IF(AF47>0,AF47/C47,0) -> 0 | AM47: =IF(AG47>0,AG47/D47,0) -> 0 | AN47: =IF(AH47>0,AH47/E47,0) -> 0 | AO47: =IF(AI47>0,AI47/F47,0) -> 0 | AP47: =IF(AJ47>0,AJ47/G47,0) -> 0 | AQ47: =AK47+AQ46+IF(AK47<0,AK47,0) -> 0.0026243207 | AR47: =AL47+AR46+IF(AL47<0,AL47,0) -> 0.016847461 | AS47: =AM47+AS46+IF(AM47<0,AM47,0) -> 0 | AT47: =AN47+AT46+IF(AN47<0,AN47,0) -> 0 | AU47: =AO47+AU46+IF(AO47<0,AO47,0) -> 0 | AV47: =AP47+AV46+IF(AP47<0,AP47,0) -> 0 | AW47: =S47+AQ47 -> 1.2387529 | AX47: =T47+AR47 -> 2.6358952 | AY47: =U47+AS47 -> 1.0019682 | AZ47: =V47+AT47 -> 0.72829965 | BA47: =W47+AU47 -> 8.7131655 | BB47: =X47+AV47 -> 1.4634147 | BC47: =(AE47+AF47+AG47+AH47+AI47+AJ47) -> 0 | BD47: =BD46+L47 -> -1000 | BE47: =(S47*B47)+(T47*C47)+(U47*D47)+(V47*E47)+(W47*F47)+(X47*G47) -> 1102.7834 | BF47: =(BE47/ABS(BD47))-1 -> 0.1027834 | BG47: =BG46+BC47 -> 1.6015592 | BH47: =BE47+BG47 -> 1104.385 | BI47: =(BH47/ABS(BD47))-1 -> 0.10438495 | BJ47: =(B47*AQ47)+(C47*AR47)+(D47*AS47)+(E47*AT47)+(F47*AU47)+(G47*AV47) -> 1.599175 | BK47: =BE47+BJ47 -> 1104.3826 | BL47: =(BK47/ABS(BD47))-1 -> 0.10438257 | BN47: =ABS(BD47) -> 1000 | BO47: =(B47*AW47)+(C47*AX47)+(D47*AY47)+(E47*AZ47)+(F47*BA47)+(G47*BB47) -> 1104.3826 | BQ47: =B47/2 -> 76.205002 | BR47: =G47/2 -> 57.57
A48: 39384 | B48: 149.98 | C48: 69.260002 | D48: 56.75 | E48: 69.07 | F48: 51.349998 | G48: 113.75 | L48: =IF(int=Weekly,-$B$4,IF(int=Bi_Weekly,0,IF(int=Monthly,0,IF(int=Quarterly,-$B$4,IF(int=Yearly,0,IF(int=None,0,0)))))) -> -500 | M48: =(ABS((L48*$B$29)/B48)) -> 0.58674491 | N48: =(ABS((L48*$C$29)/C48)) -> 1.2705746 | O48: =(ABS((L48*$D$29)/D48)) -> 0.49339207 | P48: =(ABS((L48*$E$29)/E48)) -> 0.35471261 | Q48: =(ABS((L48*$F$29)/F48)) -> 4.0019476 | R48: =(ABS((L48*$G$29)/G48)) -> 0.58021978 | S48: =S47+M48 -> 1.8228735 | T48: =T47+N48 -> 3.8896223 | U48: =U47+O48 -> 1.4953602 | V48: =V47+P48 -> 1.0830123 | W48: =W47+Q48 -> 12.715113 | X48: =X47+R48 -> 2.0436345 | AE48: =(S48*Y48) -> 0 | AF48: =(T48*Z48) -> 0 | AG48: =(U48*AA48) -> 0 | AH48: =(V48*AB48) -> 0 | AI48: =(W48*AC48) -> 0 | AJ48: =(X48*AD48) -> 0 | AK48: =IF(AE48>0,AE48/B48,0) -> 0 | AL48: =IF(AF48>0,AF48/C48,0) -> 0 | AM48: =IF(AG48>0,AG48/D48,0) -> 0 | AN48: =IF(AH48>0,AH48/E48,0) -> 0 | AO48: =IF(AI48>0,AI48/F48,0) -> 0 | AP48: =IF(AJ48>0,AJ48/G48,0) -> 0 | AQ48: =AK48+AQ47+IF(AK48<0,AK48,0) -> 0.0026243207 | AR48: =AL48+AR47+IF(AL48<0,AL48,0) -> 0.016847461 | AS48: =AM48+AS47+IF(AM48<0,AM48,0) -> 0 | AT48: =AN48+AT47+IF(AN48<0,AN48,0) -> 0 | AU48: =AO48+AU47+IF(AO48<0,AO48,0) -> 0 | AV48: =AP48+AV47+IF(AP48<0,AP48,0) -> 0 | AW48: =S48+AQ48 -> 1.8254979 | AX48: =T48+AR48 -> 3.9064698 | AY48: =U48+AS48 -> 1.4953602 | AZ48: =V48+AT48 -> 1.0830123 | BA48: =W48+AU48 -> 12.715113 | BB48: =X48+AV48 -> 2.0436345 | BC48: =(AE48+AF48+AG48+AH48+AI48+AJ48) -> 0 | BD48: =BD47+L48 -> -1500 | BE48: =(S48*B48)+(T48*C48)+(U48*D48)+(V48*E48)+(W48*F48)+(X48*G48) -> 1587.8396 | BF48: =(BE48/ABS(BD48))-1 -> 0.058559747 | BG48: =BG47+BC48 -> 1.6015592 | BH48: =BE48+BG48 -> 1589.4412 | BI48: =(BH48/ABS(BD48))-1 -> 0.059627453 | BJ48: =(B48*AQ48)+(C48*AR48)+(D48*AS48)+(E48*AT48)+(F48*AU48)+(G48*AV48) -> 1.5604508 | BK48: =BE48+BJ48 -> 1589.4001 | BL48: =(BK48/ABS(BD48))-1 -> 0.059600048 | BN48: =ABS(BD48) -> 1500 | BO48: =(B48*AW48)+(C48*AX48)+(D48*AY48)+(E48*AZ48)+(F48*BA48)+(G48*BB48) -> 1589.4001 | BQ48: =B48/2 -> 74.989998 | BR48: =G48/2 -> 56.875
A49: 39391 | B49: 144.58 | C49: 67.029999 | D49: 55.459999 | E49: 67.510002 | F49: 49.639999 | G49: 108.64 | L49: =IF(int=Weekly,-$B$4,IF(int=Bi_Weekly,-$B$4,IF(int=Monthly,0,IF(int=Quarterly,0,IF(int=Yearly,0,IF(int=None,0,0)))))) -> 0 | M49: =(ABS((L49*$B$29)/B49)) -> 0 | N49: =(ABS((L49*$C$29)/C49)) -> 0 | O49: =(ABS((L49*$D$29)/D49)) -> 0 | P49: =(ABS((L49*$E$29)/E49)) -> 0 | Q49: =(ABS((L49*$F$29)/F49)) -> 0 | R49: =(ABS((L49*$G$29)/G49)) -> 0 | S49: =S48+M49 -> 1.8228735 | T49: =T48+N49 -> 3.8896223 | U49: =U48+O49 -> 1.4953602 | V49: =V48+P49 -> 1.0830123 | W49: =W48+Q49 -> 12.715113 | X49: =X48+R49 -> 2.0436345 | AE49: =(S49*Y49) -> 0 | AF49: =(T49*Z49) -> 0 | AG49: =(U49*AA49) -> 0 | AH49: =(V49*AB49) -> 0 | AI49: =(W49*AC49) -> 0 | AJ49: =(X49*AD49) -> 0 | AK49: =IF(AE49>0,AE49/B49,0) -> 0 | AL49: =IF(AF49>0,AF49/C49,0) -> 0 | AM49: =IF(AG49>0,AG49/D49,0) -> 0 | AN49: =IF(AH49>0,AH49/E49,0) -> 0 | AO49: =IF(AI49>0,AI49/F49,0) -> 0 | AP49: =IF(AJ49>0,AJ49/G49,0) -> 0 | AQ49: =AK49+AQ48+IF(AK49<0,AK49,0) -> 0.0026243207 | AR49: =AL49+AR48+IF(AL49<0,AL49,0) -> 0.016847461 | AS49: =AM49+AS48+IF(AM49<0,AM49,0) -> 0 | AT49: =AN49+AT48+IF(AN49<0,AN49,0) -> 0 | AU49: =AO49+AU48+IF(AO49<0,AO49,0) -> 0 | AV49: =AP49+AV48+IF(AP49<0,AP49,0) -> 0 | AW49: =S49+AQ49 -> 1.8254979 | AX49: =T49+AR49 -> 3.9064698 | AY49: =U49+AS49 -> 1.4953602 | AZ49: =V49+AT49 -> 1.0830123 | BA49: =W49+AU49 -> 12.715113 | BB49: =X49+AV49 -> 2.0436345 | BC49: =(AE49+AF49+AG49+AH49+AI49+AJ49) -> 0 | BD49: =BD48+L49 -> -1500 | BE49: =(S49*B49)+(T49*C49)+(U49*D49)+(V49*E49)+(W49*F49)+(X49*G49) -> 1533.5179 | BF49: =(BE49/ABS(BD49))-1 -> 0.022345285 | BG49: =BG48+BC49 -> 1.6015592 | BH49: =BE49+BG49 -> 1535.1195 | BI49: =(BH49/ABS(BD49))-1 -> 0.023412991 | BJ49: =(B49*AQ49)+(C49*AR49)+(D49*AS49)+(E49*AT49)+(F49*AU49)+(G49*AV49) -> 1.5087096 | BK49: =BE49+BJ49 -> 1535.0266 | BL49: =(BK49/ABS(BD49))-1 -> 0.023351091 | BN49: =ABS(BD49) -> 1500 | BO49: =(B49*AW49)+(C49*AX49)+(D49*AY49)+(E49*AZ49)+(F49*BA49)+(G49*BB49) -> 1535.0266 | BQ49: =B49/2 -> 72.290001 | BR49: =G49/2 -> 54.32
A50: 39398 | B50: 144.82001 | C50: 66.970001 | D50: 55.07 | E50: 67.089996 | F50: 49.389999 | G50: 107.98 | L50: =IF(int=Weekly,-$B$4,IF(int=Bi_Weekly,0,IF(int=Monthly,0,IF(int=Quarterly,0,IF(int=Yearly,0,IF(int=None,0,0)))))) -> 0 | M50: =(ABS((L50*$B$29)/B50)) -> 0 | N50: =(ABS((L50*$C$29)/C50)) -> 0 | O50: =(ABS((L50*$D$29)/D50)) -> 0 | P50: =(ABS((L50*$E$29)/E50)) -> 0 | Q50: =(ABS((L50*$F$29)/F50)) -> 0 | R50: =(ABS((L50*$G$29)/G50)) -> 0 | S50: =S49+M50 -> 1.8228735 | T50: =T49+N50 -> 3.8896223 | U50: =U49+O50 -> 1.4953602 | V50: =V49+P50 -> 1.0830123 | W50: =W49+Q50 -> 12.715113 | X50: =X49+R50 -> 2.0436345 | AE50: =(S50*Y50) -> 0 | AF50: =(T50*Z50) -> 0 | AG50: =(U50*AA50) -> 0 | AH50: =(V50*AB50) -> 0 | AI50: =(W50*AC50) -> 0 | AJ50: =(X50*AD50) -> 0 | AK50: =IF(AE50>0,AE50/B50,0) -> 0 | AL50: =IF(AF50>0,AF50/C50,0) -> 0 | AM50: =IF(AG50>0,AG50/D50,0) -> 0 | AN50: =IF(AH50>0,AH50/E50,0) -> 0 | AO50: =IF(AI50>0,AI50/F50,0) -> 0 | AP50: =IF(AJ50>0,AJ50/G50,0) -> 0 | AQ50: =AK50+AQ49+IF(AK50<0,AK50,0) -> 0.0026243207 | AR50: =AL50+AR49+IF(AL50<0,AL50,0) -> 0.016847461 | AS50: =AM50+AS49+IF(AM50<0,AM50,0) -> 0 | AT50: =AN50+AT49+IF(AN50<0,AN50,0) -> 0 | AU50: =AO50+AU49+IF(AO50<0,AO50,0) -> 0 | AV50: =AP50+AV49+IF(AP50<0,AP50,0) -> 0 | AW50: =S50+AQ50 -> 1.8254979 | AX50: =T50+AR50 -> 3.9064698 | AY50: =U50+AS50 -> 1.4953602 | AZ50: =V50+AT50 -> 1.0830123 | BA50: =W50+AU50 -> 12.715113 | BB50: =X50+AV50 -> 2.0436345 | BC50: =(AE50+AF50+AG50+AH50+AI50+AJ50) -> 0 | BD50: =BD49+L50 -> -1500 | BE50: =(S50*B50)+(T50*C50)+(U50*D50)+(V50*E50)+(W50*F50)+(X50*G50) -> 1528.1564 | BF50: =(BE50/ABS(BD50))-1 -> 0.018770951 | BG50: =BG49+BC50 -> 1.6015592 | BH50: =BE50+BG50 -> 1529.758 | BI50: =(BH50/ABS(BD50))-1 -> 0.019838657 | BJ50: =(B50*AQ50)+(C50*AR50)+(D50*AS50)+(E50*AT50)+(F50*AU50)+(G50*AV50) -> 1.5083286 | BK50: =BE50+BJ50 -> 1529.6648 | BL50: =(BK50/ABS(BD50))-1 -> 0.019776504 | BN50: =ABS(BD50) -> 1500 | BO50: =(B50*AW50)+(C50*AX50)+(D50*AY50)+(E50*AZ50)+(F50*BA50)+(G50*BB50) -> 1529.6648 | BQ50: =B50/2 -> 72.410004 | BR50: =G50/2 -> 53.990001
A51: 39405 | B51: 142.60001 | C51: 65.839996 | D51: 53.970001 | E51: 65.93 | F51: 49.18 | G51: 103.26 | L51: =IF(int=Weekly,-$B$4,IF(int=Bi_Weekly,-$B$4,IF(int=Monthly,-$B$4,IF(int=Quarterly,0,IF(int=Yearly,0,IF(int=None,0,0)))))) -> 0 | M51: =(ABS((L51*$B$29)/B51)) -> 0 | N51: =(ABS((L51*$C$29)/C51)) -> 0 | O51: =(ABS((L51*$D$29)/D51)) -> 0 | P51: =(ABS((L51*$E$29)/E51)) -> 0 | Q51: =(ABS((L51*$F$29)/F51)) -> 0 | R51: =(ABS((L51*$G$29)/G51)) -> 0 | S51: =S50+M51 -> 1.8228735 | T51: =T50+N51 -> 3.8896223 | U51: =U50+O51 -> 1.4953602 | V51: =V50+P51 -> 1.0830123 | W51: =W50+Q51 -> 12.715113 | X51: =X50+R51 -> 2.0436345 | AE51: =(S51*Y51) -> 0 | AF51: =(T51*Z51) -> 0 | AG51: =(U51*AA51) -> 0 | AH51: =(V51*AB51) -> 0 | AI51: =(W51*AC51) -> 0 | AJ51: =(X51*AD51) -> 0 | AK51: =IF(AE51>0,AE51/B51,0) -> 0 | AL51: =IF(AF51>0,AF51/C51,0) -> 0 | AM51: =IF(AG51>0,AG51/D51,0) -> 0 | AN51: =IF(AH51>0,AH51/E51,0) -> 0 | AO51: =IF(AI51>0,AI51/F51,0) -> 0 | AP51: =IF(AJ51>0,AJ51/G51,0) -> 0 | AQ51: =AK51+AQ50+IF(AK51<0,AK51,0) -> 0.0026243207 | AR51: =AL51+AR50+IF(AL51<0,AL51,0) -> 0.016847461 | AS51: =AM51+AS50+IF(AM51<0,AM51,0) -> 0 | AT51: =AN51+AT50+IF(AN51<0,AN51,0) -> 0 | AU51: =AO51+AU50+IF(AO51<0,AO51,0) -> 0 | AV51: =AP51+AV50+IF(AP51<0,AP51,0) -> 0 | AW51: =S51+AQ51 -> 1.8254979 | AX51: =T51+AR51 -> 3.9064698 | AY51: =U51+AS51 -> 1.4953602 | AZ51: =V51+AT51 -> 1.0830123 | BA51: =W51+AU51 -> 12.715113 | BB51: =X51+AV51 -> 2.0436345 | BC51: =(AE51+AF51+AG51+AH51+AI51+AJ51) -> 0 | BD51: =BD50+L51 -> -1500 | BE51: =(S51*B51)+(T51*C51)+(U51*D51)+(V51*E51)+(W51*F51)+(X51*G51) -> 1504.4971 | BF51: =(BE51/ABS(BD51))-1 -> 0.0029980337 | BG51: =BG50+BC51 -> 1.6015592 | BH51: =BE51+BG51 -> 1506.0986 | BI51: =(BH51/ABS(BD51))-1 -> 0.0040657398 | BJ51: =(B51*AQ51)+(C51*AR51)+(D51*AS51)+(E51*AT51)+(F51*AU51)+(G51*AV51) -> 1.4834649 | BK51: =BE51+BJ51 -> 1505.9805 | BL51: =(BK51/ABS(BD51))-1 -> 0.0039870103 | BN51: =ABS(BD51) -> 1500 | BO51: =(B51*AW51)+(C51*AX51)+(D51*AY51)+(E51*AZ51)+(F51*BA51)+(G51*BB51) -> 1505.9805 | BQ51: =B51/2 -> 71.300003 | BR51: =G51/2 -> 51.630001
A52: 39412 | B52: 146.95 | C52: 68.010002 | D52: 55.169998 | E52: 67.019997 | F52: 50.389999 | G52: 107.28 | L52: =IF(int=Weekly,-$B$4,IF(int=Bi_Weekly,0,IF(int=Monthly,0,IF(int=Quarterly,0,IF(int=Yearly,0,IF(int=None,0,0)))))) -> 0 | M52: =(ABS((L52*$B$29)/B52)) -> 0 | N52: =(ABS((L52*$C$29)/C52)) -> 0 | O52: =(ABS((L52*$D$29)/D52)) -> 0 | P52: =(ABS((L52*$E$29)/E52)) -> 0 | Q52: =(ABS((L52*$F$29)/F52)) -> 0 | R52: =(ABS((L52*$G$29)/G52)) -> 0 | S52: =S51+M52 -> 1.8228735 | T52: =T51+N52 -> 3.8896223 | U52: =U51+O52 -> 1.4953602 | V52: =V51+P52 -> 1.0830123 | W52: =W51+Q52 -> 12.715113 | X52: =X51+R52 -> 2.0436345 | AE52: =(S52*Y52) -> 0 | AF52: =(T52*Z52) -> 0 | AG52: =(U52*AA52) -> 0 | AH52: =(V52*AB52) -> 0 | AI52: =(W52*AC52) -> 0 | AJ52: =(X52*AD52) -> 0 | AK52: =IF(AE52>0,AE52/B52,0) -> 0 | AL52: =IF(AF52>0,AF52/C52,0) -> 0 | AM52: =IF(AG52>0,AG52/D52,0) -> 0 | AN52: =IF(AH52>0,AH52/E52,0) -> 0 | AO52: =IF(AI52>0,AI52/F52,0) -> 0 | AP52: =IF(AJ52>0,AJ52/G52,0) -> 0 | AQ52: =AK52+AQ51+IF(AK52<0,AK52,0) -> 0.0026243207 | AR52: =AL52+AR51+IF(AL52<0,AL52,0) -> 0.016847461 | AS52: =AM52+AS51+IF(AM52<0,AM52,0) -> 0 | AT52: =AN52+AT51+IF(AN52<0,AN52,0) -> 0 | AU52: =AO52+AU51+IF(AO52<0,AO52,0) -> 0 | AV52: =AP52+AV51+IF(AP52<0,AP52,0) -> 0 | AW52: =S52+AQ52 -> 1.8254979 | AX52: =T52+AR52 -> 3.9064698 | AY52: =U52+AS52 -> 1.4953602 | AZ52: =V52+AT52 -> 1.0830123 | BA52: =W52+AU52 -> 12.715113 | BB52: =X52+AV52 -> 2.0436345 | BC52: =(AE52+AF52+AG52+AH52+AI52+AJ52) -> 0 | BD52: =BD51+L52 -> -1500 | BE52: =(S52*B52)+(T52*C52)+(U52*D52)+(V52*E52)+(W52*F52)+(X52*G52) -> 1547.4426 | BF52: =(BE52/ABS(BD52))-1 -> 0.031628416 | BG52: =BG51+BC52 -> 1.6015592 | BH52: =BE52+BG52 -> 1549.0442 | BI52: =(BH52/ABS(BD52))-1 -> 0.032696122 | BJ52: =(B52*AQ52)+(C52*AR52)+(D52*AS52)+(E52*AT52)+(F52*AU52)+(G52*AV52) -> 1.5314398 | BK52: =BE52+BJ52 -> 1548.9741 | BL52: =(BK52/ABS(BD52))-1 -> 0.032649376 | BN52: =ABS(BD52) -> 1500 | BO52: =(B52*AW52)+(C52*AX52)+(D52*AY52)+(E52*AZ52)+(F52*BA52)+(G52*BB52) -> 1548.9741 | BQ52: =B52/2 -> 73.474998 | BR52: =G52/2 -> 53.64
A53: 39419 | B53: 149.60001 | C53: 69.099998 | D53: 56.48 | E53: 68.809998 | F53: 50.82 | G53: 111.67 | L53: =IF(int=Weekly,-$B$4,IF(int=Bi_Weekly,-$B$4,IF(int=Monthly,0,IF(int=Quarterly,0,IF(int=Yearly,0,IF(int=None,0,0)))))) -> 0 | M53: =(ABS((L53*$B$29)/B53)) -> 0 | N53: =(ABS((L53*$C$29)/C53)) -> 0 | O53: =(ABS((L53*$D$29)/D53)) -> 0 | P53: =(ABS((L53*$E$29)/E53)) -> 0 | Q53: =(ABS((L53*$F$29)/F53)) -> 0 | R53: =(ABS((L53*$G$29)/G53)) -> 0 | S53: =S52+M53 -> 1.8228735 | T53: =T52+N53 -> 3.8896223 | U53: =U52+O53 -> 1.4953602 | V53: =V52+P53 -> 1.0830123 | W53: =W52+Q53 -> 12.715113 | X53: =X52+R53 -> 2.0436345 | AE53: =(S53*Y53) -> 0 | AF53: =(T53*Z53) -> 0 | AG53: =(U53*AA53) -> 0 | AH53: =(V53*AB53) -> 0 | AI53: =(W53*AC53) -> 0 | AJ53: =(X53*AD53) -> 0 | AK53: =IF(AE53>0,AE53/B53,0) -> 0 | AL53: =IF(AF53>0,AF53/C53,0) -> 0 | AM53: =IF(AG53>0,AG53/D53,0) -> 0 | AN53: =IF(AH53>0,AH53/E53,0) -> 0 | AO53: =IF(AI53>0,AI53/F53,0) -> 0 | AP53: =IF(AJ53>0,AJ53/G53,0) -> 0 | AQ53: =AK53+AQ52+IF(AK53<0,AK53,0) -> 0.0026243207 | AR53: =AL53+AR52+IF(AL53<0,AL53,0) -> 0.016847461 | AS53: =AM53+AS52+IF(AM53<0,AM53,0) -> 0 | AT53: =AN53+AT52+IF(AN53<0,AN53,0) -> 0 | AU53: =AO53+AU52+IF(AO53<0,AO53,0) -> 0 | AV53: =AP53+AV52+IF(AP53<0,AP53,0) -> 0 | AW53: =S53+AQ53 -> 1.8254979 | AX53: =T53+AR53 -> 3.9064698 | AY53: =U53+AS53 -> 1.4953602 | AZ53: =V53+AT53 -> 1.0830123 | BA53: =W53+AU53 -> 12.715113 | BB53: =X53+AV53 -> 2.0436345 | BC53: =(AE53+AF53+AG53+AH53+AI53+AJ53) -> 0 | BD53: =BD52+L53 -> -1500 | BE53: =(S53*B53)+(T53*C53)+(U53*D53)+(V53*E53)+(W53*F53)+(X53*G53) -> 1574.8495 | BF53: =(BE53/ABS(BD53))-1 -> 0.049899674 | BG53: =BG52+BC53 -> 1.6015592 | BH53: =BE53+BG53 -> 1576.4511 | BI53: =(BH53/ABS(BD53))-1 -> 0.05096738 | BJ53: =(B53*AQ53)+(C53*AR53)+(D53*AS53)+(E53*AT53)+(F53*AU53)+(G53*AV53) -> 1.5567579 | BK53: =BE53+BJ53 -> 1576.4063 | BL53: =(BK53/ABS(BD53))-1 -> 0.050937513 | BN53: =ABS(BD53) -> 1500 | BO53: =(B53*AW53)+(C53*AX53)+(D53*AY53)+(E53*AZ53)+(F53*BA53)+(G53*BB53) -> 1576.4063 | BQ53: =B53/2 -> 74.800003 | BR53: =G53/2 -> 55.834999
A54: 39426 | B54: 145.7 | C54: 67.160004 | D54: 54.299999 | E54: 65.68 | F54: 48.639999 | G54: 105.04 | L54: =IF(int=Weekly,-$B$4,IF(int=Bi_Weekly,0,IF(int=Monthly,0,IF(int=Quarterly,0,IF(int=Yearly,0,IF(int=None,0,0)))))) -> 0 | M54: =(ABS((L54*$B$29)/B54)) -> 0 | N54: =(ABS((L54*$C$29)/C54)) -> 0 | O54: =(ABS((L54*$D$29)/D54)) -> 0 | P54: =(ABS((L54*$E$29)/E54)) -> 0 | Q54: =(ABS((L54*$F$29)/F54)) -> 0 | R54: =(ABS((L54*$G$29)/G54)) -> 0 | S54: =S53+M54 -> 1.8228735 | T54: =T53+N54 -> 3.8896223 | U54: =U53+O54 -> 1.4953602 | V54: =V53+P54 -> 1.0830123 | W54: =W53+Q54 -> 12.715113 | X54: =X53+R54 -> 2.0436345 | AE54: =(S54*Y54) -> 0 | AF54: =(T54*Z54) -> 0 | AG54: =(U54*AA54) -> 0 | AH54: =(V54*AB54) -> 0 | AI54: =(W54*AC54) -> 0 | AJ54: =(X54*AD54) -> 0 | AK54: =IF(AE54>0,AE54/B54,0) -> 0 | AL54: =IF(AF54>0,AF54/C54,0) -> 0 | AM54: =IF(AG54>0,AG54/D54,0) -> 0 | AN54: =IF(AH54>0,AH54/E54,0) -> 0 | AO54: =IF(AI54>0,AI54/F54,0) -> 0 | AP54: =IF(AJ54>0,AJ54/G54,0) -> 0 | AQ54: =AK54+AQ53+IF(AK54<0,AK54,0) -> 0.0026243207 | AR54: =AL54+AR53+IF(AL54<0,AL54,0) -> 0.016847461 | AS54: =AM54+AS53+IF(AM54<0,AM54,0) -> 0 | AT54: =AN54+AT53+IF(AN54<0,AN54,0) -> 0 | AU54: =AO54+AU53+IF(AO54<0,AO54,0) -> 0 | AV54: =AP54+AV53+IF(AP54<0,AP54,0) -> 0 | AW54: =S54+AQ54 -> 1.8254979 | AX54: =T54+AR54 -> 3.9064698 | AY54: =U54+AS54 -> 1.4953602 | AZ54: =V54+AT54 -> 1.0830123 | BA54: =W54+AU54 -> 12.715113 | BB54: =X54+AV54 -> 2.0436345 | BC54: =(AE54+AF54+AG54+AH54+AI54+AJ54) -> 0 | BD54: =BD53+L54 -> -1500 | BE54: =(S54*B54)+(T54*C54)+(U54*D54)+(V54*E54)+(W54*F54)+(X54*G54) -> 1512.2765 | BF54: =(BE54/ABS(BD54))-1 -> 0.0081843207 | BG54: =BG53+BC54 -> 1.6015592 | BH54: =BE54+BG54 -> 1513.878 | BI54: =(BH54/ABS(BD54))-1 -> 0.0092520268 | BJ54: =(B54*AQ54)+(C54*AR54)+(D54*AS54)+(E54*AT54)+(F54*AU54)+(G54*AV54) -> 1.5138391 | BK54: =BE54+BJ54 -> 1513.7903 | BL54: =(BK54/ABS(BD54))-1 -> 0.0091935467 | BN54: =ABS(BD54) -> 1500 | BO54: =(B54*AW54)+(C54*AX54)+(D54*AY54)+(E54*AZ54)+(F54*BA54)+(G54*BB54) -> 1513.7903 | BQ54: =B54/2 -> 72.849998 | BR54: =G54/2 -> 52.520001
A55: 39433 | B55: 146.81 | C55: 67 | D55: 53.790001 | E55: 66.099998 | F55: 48.73 | G55: 106.45 | L55: =IF(int=Weekly,-$B$4,IF(int=Bi_Weekly,-$B$4,IF(int=Monthly,-$B$4,IF(int=Quarterly,0,IF(int=Yearly,0,IF(int=None,0,0)))))) -> 0 | M55: =(ABS((L55*$B$29)/B55)) -> 0 | N55: =(ABS((L55*$C$29)/C55)) -> 0 | O55: =(ABS((L55*$D$29)/D55)) -> 0 | P55: =(ABS((L55*$E$29)/E55)) -> 0 | Q55: =(ABS((L55*$F$29)/F55)) -> 0 | R55: =(ABS((L55*$G$29)/G55)) -> 0 | S55: =S54+M55 -> 1.8228735 | T55: =T54+N55 -> 3.8896223 | U55: =U54+O55 -> 1.4953602 | V55: =V54+P55 -> 1.0830123 | W55: =W54+Q55 -> 12.715113 | X55: =X54+R55 -> 2.0436345 | AE55: =(S55*Y55) -> 0 | AF55: =(T55*Z55) -> 0 | AG55: =(U55*AA55) -> 0 | AH55: =(V55*AB55) -> 0 | AI55: =(W55*AC55) -> 0 | AJ55: =(X55*AD55) -> 0 | AK55: =IF(AE55>0,AE55/B55,0) -> 0 | AL55: =IF(AF55>0,AF55/C55,0) -> 0 | AM55: =IF(AG55>0,AG55/D55,0) -> 0 | AN55: =IF(AH55>0,AH55/E55,0) -> 0 | AO55: =IF(AI55>0,AI55/F55,0) -> 0 | AP55: =IF(AJ55>0,AJ55/G55,0) -> 0 | AQ55: =AK55+AQ54+IF(AK55<0,AK55,0) -> 0.0026243207 | AR55: =AL55+AR54+IF(AL55<0,AL55,0) -> 0.016847461 | AS55: =AM55+AS54+IF(AM55<0,AM55,0) -> 0 | AT55: =AN55+AT54+IF(AN55<0,AN55,0) -> 0 | AU55: =AO55+AU54+IF(AO55<0,AO55,0) -> 0 | AV55: =AP55+AV54+IF(AP55<0,AP55,0) -> 0 | AW55: =S55+AQ55 -> 1.8254979 | AX55: =T55+AR55 -> 3.9064698 | AY55: =U55+AS55 -> 1.4953602 | AZ55: =V55+AT55 -> 1.0830123 | BA55: =W55+AU55 -> 12.715113 | BB55: =X55+AV55 -> 2.0436345 | BC55: =(AE55+AF55+AG55+AH55+AI55+AJ55) -> 0 | BD55: =BD54+L55 -> -1500 | BE55: =(S55*B55)+(T55*C55)+(U55*D55)+(V55*E55)+(W55*F55)+(X55*G55) -> 1517.3956 | BF55: =(BE55/ABS(BD55))-1 -> 0.011597093 | BG55: =BG54+BC55 -> 1.6015592 | BH55: =BE55+BG55 -> 1518.9972 | BI55: =(BH55/ABS(BD55))-1 -> 0.012664799 | BJ55: =(B55*AQ55)+(C55*AR55)+(D55*AS55)+(E55*AT55)+(F55*AU55)+(G55*AV55) -> 1.5140564 | BK55: =BE55+BJ55 -> 1518.9097 | BL55: =(BK55/ABS(BD55))-1 -> 0.012606464 | BN55: =ABS(BD55) -> 1500 | BO55: =(B55*AW55)+(C55*AX55)+(D55*AY55)+(E55*AZ55)+(F55*BA55)+(G55*BB55) -> 1518.9097 | BQ55: =B55/2 -> 73.404999 | BR55: =G55/2 -> 53.224998
A56: 39440 | B56: 145.88001 | C56: 66.800003 | D56: 53.41 | E56: 64.839996 | F56: 48.290001 | G56: 105.42 | L56: =IF(int=Weekly,-$B$4,IF(int=Bi_Weekly,0,IF(int=Monthly,0,IF(int=Quarterly,0,IF(int=Yearly,0,IF(int=None,0,0)))))) -> 0 | M56: =(ABS((L56*$B$29)/B56)) -> 0 | N56: =(ABS((L56*$C$29)/C56)) -> 0 | O56: =(ABS((L56*$D$29)/D56)) -> 0 | P56: =(ABS((L56*$E$29)/E56)) -> 0 | Q56: =(ABS((L56*$F$29)/F56)) -> 0 | R56: =(ABS((L56*$G$29)/G56)) -> 0 | S56: =S55+M56 -> 1.8228735 | T56: =T55+N56 -> 3.8896223 | U56: =U55+O56 -> 1.4953602 | V56: =V55+P56 -> 1.0830123 | W56: =W55+Q56 -> 12.715113 | X56: =X55+R56 -> 2.0436345 | Y56: 0.3855 | Z56: 0.555 | AA56: 1.08 | AB56: 1.509 | AC56: 1.055 | AD56: 0.9845 | AE56: =(S56*Y56) -> 0.70271775 | AF56: =(T56*Z56) -> 2.1587404 | AG56: =(U56*AA56) -> 1.6149891 | AH56: =(V56*AB56) -> 1.6342655 | AI56: =(W56*AC56) -> 13.414444 | AJ56: =(X56*AD56) -> 2.0119581 | AK56: =IF(AE56>0,AE56/B56,0) -> 0.0048170944 | AL56: =IF(AF56>0,AF56/C56,0) -> 0.032316472 | AM56: =IF(AG56>0,AG56/D56,0) -> 0.030237578 | AN56: =IF(AH56>0,AH56/E56,0) -> 0.02520459 | AO56: =IF(AI56>0,AI56/F56,0) -> 0.27778927 | AP56: =IF(AJ56>0,AJ56/G56,0) -> 0.019085166 | AQ56: =AK56+AQ55+IF(AK56<0,AK56,0) -> 0.0074414151 | AR56: =AL56+AR55+IF(AL56<0,AL56,0) -> 0.049163932 | AS56: =AM56+AS55+IF(AM56<0,AM56,0) -> 0.030237578 | AT56: =AN56+AT55+IF(AN56<0,AN56,0) -> 0.02520459 | AU56: =AO56+AU55+IF(AO56<0,AO56,0) -> 0.27778927 | AV56: =AP56+AV55+IF(AP56<0,AP56,0) -> 0.019085166 | AW56: =S56+AQ56 -> 1.830315 | AX56: =T56+AR56 -> 3.9387863 | AY56: =U56+AS56 -> 1.5255978 | AZ56: =V56+AT56 -> 1.1082169 | BA56: =W56+AU56 -> 12.992902 | BB56: =X56+AV56 -> 2.0627196 | BC56: =(AE56+AF56+AG56+AH56+AI56+AJ56) -> 21.537115 | BD56: =BD55+L56 -> -1500 | BE56: =(S56*B56)+(T56*C56)+(U56*D56)+(V56*E56)+(W56*F56)+(X56*G56) -> 1505.2901 | BF56: =(BE56/ABS(BD56))-1 -> 0.0035267013 | BG56: =BG55+BC56 -> 23.138674 | BH56: =BE56+BG56 -> 1528.4287 | BI56: =(BH56/ABS(BD56))-1 -> 0.018952484 | BJ56: =(B56*AQ56)+(C56*AR56)+(D56*AS56)+(E56*AT56)+(F56*AU56)+(G56*AV56) -> 23.045362 | BK56: =BE56+BJ56 -> 1528.3354 | BL56: =(BK56/ABS(BD56))-1 -> 0.018890276 | BN56: =ABS(BD56) -> 1500 | BO56: =(B56*AW56)+(C56*AX56)+(D56*AY56)+(E56*AZ56)+(F56*BA56)+(G56*BB56) -> 1528.3354 | BQ56: =B56/2 -> 72.940003 | BR56: =G56/2 -> 52.709999
A57: 39447 | B57: 139.42999 | C57: 64.269997 | D57: 50.360001 | E57: 60.849998 | F57: 46.84 | G57: 101.53 | L57: =IF(int=Weekly,-$B$4,IF(int=Bi_Weekly,-$B$4,IF(int=Monthly,0,IF(int=Quarterly,0,IF(int=Yearly,0,IF(int=None,0,0)))))) -> 0 | M57: =(ABS((L57*$B$29)/B57)) -> 0 | N57: =(ABS((L57*$C$29)/C57)) -> 0 | O57: =(ABS((L57*$D$29)/D57)) -> 0 | P57: =(ABS((L57*$E$29)/E57)) -> 0 | Q57: =(ABS((L57*$F$29)/F57)) -> 0 | R57: =(ABS((L57*$G$29)/G57)) -> 0 | S57: =S56+M57 -> 1.8228735 | T57: =T56+N57 -> 3.8896223 | U57: =U56+O57 -> 1.4953602 | V57: =V56+P57 -> 1.0830123 | W57: =W56+Q57 -> 12.715113 | X57: =X56+R57 -> 2.0436345 | AE57: =(S57*Y57) -> 0 | AF57: =(T57*Z57) -> 0 | AG57: =(U57*AA57) -> 0 | AH57: =(V57*AB57) -> 0 | AI57: =(W57*AC57) -> 0 | AJ57: =(X57*AD57) -> 0 | AK57: =IF(AE57>0,AE57/B57,0) -> 0 | AL57: =IF(AF57>0,AF57/C57,0) -> 0 | AM57: =IF(AG57>0,AG57/D57,0) -> 0 | AN57: =IF(AH57>0,AH57/E57,0) -> 0 | AO57: =IF(AI57>0,AI57/F57,0) -> 0 | AP57: =IF(AJ57>0,AJ57/G57,0) -> 0 | AQ57: =AK57+AQ56+IF(AK57<0,AK57,0) -> 0.0074414151 | AR57: =AL57+AR56+IF(AL57<0,AL57,0) -> 0.049163932 | AS57: =AM57+AS56+IF(AM57<0,AM57,0) -> 0.030237578 | AT57: =AN57+AT56+IF(AN57<0,AN57,0) -> 0.02520459 | AU57: =AO57+AU56+IF(AO57<0,AO57,0) -> 0.27778927 | AV57: =AP57+AV56+IF(AP57<0,AP57,0) -> 0.019085166 | AW57: =S57+AQ57 -> 1.830315 | AX57: =T57+AR57 -> 3.9387863 | AY57: =U57+AS57 -> 1.5255978 | AZ57: =V57+AT57 -> 1.1082169 | BA57: =W57+AU57 -> 12.992902 | BB57: =X57+AV57 -> 2.0627196 | BC57: =(AE57+AF57+AG57+AH57+AI57+AJ57) -> 0 | BD57: =BD56+L57 -> -1500 | BE57: =(S57*B57)+(T57*C57)+(U57*D57)+(V57*E57)+(W57*F57)+(X57*G57) -> 1448.423 | BF57: =(BE57/ABS(BD57))-1 -> -0.034384666 | BG57: =BG56+BC57 -> 23.138674 | BH57: =BE57+BG57 -> 1471.5617 | BI57: =(BH57/ABS(BD57))-1 -> -0.018958883 | BJ57: =(B57*AQ57)+(C57*AR57)+(D57*AS57)+(E57*AT57)+(F57*AU57)+(G57*AV57) -> 22.203152 | BK57: =BE57+BJ57 -> 1470.6262 | BL57: =(BK57/ABS(BD57))-1 -> -0.019582564 | BN57: =ABS(BD57) -> 1500 | BO57: =(B57*AW57)+(C57*AX57)+(D57*AY57)+(E57*AZ57)+(F57*BA57)+(G57*BB57) -> 1470.6262 | BQ57: =B57/2 -> 69.714996 | BR57: =G57/2 -> 50.765
A58: 39454 | B58: 138.05 | C58: 64.129997 | D58: 49.810001 | E58: 59.57 | F58: 45.959999 | G58: 103.2 | L58: =IF(int=Weekly,-$B$4,IF(int=Bi_Weekly,0,IF(int=Monthly,0,IF(int=Quarterly,0,IF(int=Yearly,0,IF(int=None,0,0)))))) -> 0 | M58: =(ABS((L58*$B$29)/B58)) -> 0 | N58: =(ABS((L58*$C$29)/C58)) -> 0 | O58: =(ABS((L58*$D$29)/D58)) -> 0 | P58: =(ABS((L58*$E$29)/E58)) -> 0 | Q58: =(ABS((L58*$F$29)/F58)) -> 0 | R58: =(ABS((L58*$G$29)/G58)) -> 0 | S58: =S57+M58 -> 1.8228735 | T58: =T57+N58 -> 3.8896223 | U58: =U57+O58 -> 1.4953602 | V58: =V57+P58 -> 1.0830123 | W58: =W57+Q58 -> 12.715113 | X58: =X57+R58 -> 2.0436345 | AE58: =(S58*Y58) -> 0 | AF58: =(T58*Z58) -> 0 | AG58: =(U58*AA58) -> 0 | AH58: =(V58*AB58) -> 0 | AI58: =(W58*AC58) -> 0 | AJ58: =(X58*AD58) -> 0 | AK58: =IF(AE58>0,AE58/B58,0) -> 0 | AL58: =IF(AF58>0,AF58/C58,0) -> 0 | AM58: =IF(AG58>0,AG58/D58,0) -> 0 | AN58: =IF(AH58>0,AH58/E58,0) -> 0 | AO58: =IF(AI58>0,AI58/F58,0) -> 0 | AP58: =IF(AJ58>0,AJ58/G58,0) -> 0 | AQ58: =AK58+AQ57+IF(AK58<0,AK58,0) -> 0.0074414151 | AR58: =AL58+AR57+IF(AL58<0,AL58,0) -> 0.049163932 | AS58: =AM58+AS57+IF(AM58<0,AM58,0) -> 0.030237578 | AT58: =AN58+AT57+IF(AN58<0,AN58,0) -> 0.02520459 | AU58: =AO58+AU57+IF(AO58<0,AO58,0) -> 0.27778927 | AV58: =AP58+AV57+IF(AP58<0,AP58,0) -> 0.019085166 | AW58: =S58+AQ58 -> 1.830315 | AX58: =T58+AR58 -> 3.9387863 | AY58: =U58+AS58 -> 1.5255978 | AZ58: =V58+AT58 -> 1.1082169 | BA58: =W58+AU58 -> 12.992902 | BB58: =X58+AV58 -> 2.0627196 | BC58: =(AE58+AF58+AG58+AH58+AI58+AJ58) -> 0 | BD58: =BD57+L58 -> -1500 | BE58: =(S58*B58)+(T58*C58)+(U58*D58)+(V58*E58)+(W58*F58)+(X58*G58) -> 1435.3778 | BF58: =(BE58/ABS(BD58))-1 -> -0.043081494 | BG58: =BG57+BC58 -> 23.138674 | BH58: =BE58+BG58 -> 1458.5164 | BI58: =(BH58/ABS(BD58))-1 -> -0.027655712 | BJ58: =(B58*AQ58)+(C58*AR58)+(D58*AS58)+(E58*AT58)+(F58*AU58)+(G58*AV58) -> 21.924525 | BK58: =BE58+BJ58 -> 1457.3023 | BL58: =(BK58/ABS(BD58))-1 -> -0.028465144 | BN58: =ABS(BD58) -> 1500 | BO58: =(B58*AW58)+(C58*AX58)+(D58*AY58)+(E58*AZ58)+(F58*BA58)+(G58*BB58) -> 1457.3023 | BQ58: =B58/2 -> 69.025002 | BR58: =G58/2 -> 51.599998
A59: 39461 | B59: 130.57001 | C59: 60.299999 | D59: 47.349998 | E59: 56.900002 | F59: 43.709999 | G59: 95.360001 | L59: =IF(int=Weekly,-$B$4,IF(int=Bi_Weekly,-$B$4,IF(int=Monthly,-$B$4,IF(int=Quarterly,0,IF(int=Yearly,0,IF(int=None,0,0)))))) -> 0 | M59: =(ABS((L59*$B$29)/B59)) -> 0 | N59: =(ABS((L59*$C$29)/C59)) -> 0 | O59: =(ABS((L59*$D$29)/D59)) -> 0 | P59: =(ABS((L59*$E$29)/E59)) -> 0 | Q59: =(ABS((L59*$F$29)/F59)) -> 0 | R59: =(ABS((L59*$G$29)/G59)) -> 0 | S59: =S58+M59 -> 1.8228735 | T59: =T58+N59 -> 3.8896223 | U59: =U58+O59 -> 1.4953602 | V59: =V58+P59 -> 1.0830123 | W59: =W58+Q59 -> 12.715113 | X59: =X58+R59 -> 2.0436345 | AE59: =(S59*Y59) -> 0 | AF59: =(T59*Z59) -> 0 | AG59: =(U59*AA59) -> 0 | AH59: =(V59*AB59) -> 0 | AI59: =(W59*AC59) -> 0 | AJ59: =(X59*AD59) -> 0 | AK59: =IF(AE59>0,AE59/B59,0) -> 0 | AL59: =IF(AF59>0,AF59/C59,0) -> 0 | AM59: =IF(AG59>0,AG59/D59,0) -> 0 | AN59: =IF(AH59>0,AH59/E59,0) -> 0 | AO59: =IF(AI59>0,AI59/F59,0) -> 0 | AP59: =IF(AJ59>0,AJ59/G59,0) -> 0 | AQ59: =AK59+AQ58+IF(AK59<0,AK59,0) -> 0.0074414151 | AR59: =AL59+AR58+IF(AL59<0,AL59,0) -> 0.049163932 | AS59: =AM59+AS58+IF(AM59<0,AM59,0) -> 0.030237578 | AT59: =AN59+AT58+IF(AN59<0,AN59,0) -> 0.02520459 | AU59: =AO59+AU58+IF(AO59<0,AO59,0) -> 0.27778927 | AV59: =AP59+AV58+IF(AP59<0,AP59,0) -> 0.019085166 | AW59: =S59+AQ59 -> 1.830315 | AX59: =T59+AR59 -> 3.9387863 | AY59: =U59+AS59 -> 1.5255978 | AZ59: =V59+AT59 -> 1.1082169 | BA59: =W59+AU59 -> 12.992902 | BB59: =X59+AV59 -> 2.0627196 | BC59: =(AE59+AF59+AG59+AH59+AI59+AJ59) -> 0 | BD59: =BD58+L59 -> -1500 | BE59: =(S59*B59)+(T59*C59)+(U59*D59)+(V59*E59)+(W59*F59)+(X59*G59) -> 1355.6441 | BF59: =(BE59/ABS(BD59))-1 -> -0.096237264 | BG59: =BG58+BC59 -> 23.138674 | BH59: =BE59+BG59 -> 1378.7828 | BI59: =(BH59/ABS(BD59))-1 -> -0.080811481 | BJ59: =(B59*AQ59)+(C59*AR59)+(D59*AS59)+(E59*AT59)+(F59*AU59)+(G59*AV59) -> 20.764231 | BK59: =BE59+BJ59 -> 1376.4083 | BL59: =(BK59/ABS(BD59))-1 -> -0.082394443 | BN59: =ABS(BD59) -> 1500 | BO59: =(B59*AW59)+(C59*AX59)+(D59*AY59)+(E59*AZ59)+(F59*BA59)+(G59*BB59) -> 1376.4083 | BQ59: =B59/2 -> 65.285004 | BR59: =G59/2 -> 47.68
A60: 39469 | B60: 131.41 | C60: 61.049999 | D60: 48.950001 | E60: 59.119999 | F60: 43.369999 | G60: 91.900002 | L60: =IF(int=Weekly,-$B$4,IF(int=Bi_Weekly,0,IF(int=Monthly,0,IF(int=Quarterly,0,IF(int=Yearly,0,IF(int=None,0,0)))))) -> 0 | M60: =(ABS((L60*$B$29)/B60)) -> 0 | N60: =(ABS((L60*$C$29)/C60)) -> 0 | O60: =(ABS((L60*$D$29)/D60)) -> 0 | P60: =(ABS((L60*$E$29)/E60)) -> 0 | Q60: =(ABS((L60*$F$29)/F60)) -> 0 | R60: =(ABS((L60*$G$29)/G60)) -> 0 | S60: =S59+M60 -> 1.8228735 | T60: =T59+N60 -> 3.8896223 | U60: =U59+O60 -> 1.4953602 | V60: =V59+P60 -> 1.0830123 | W60: =W59+Q60 -> 12.715113 | X60: =X59+R60 -> 2.0436345 | AE60: =(S60*Y60) -> 0 | AF60: =(T60*Z60) -> 0 | AG60: =(U60*AA60) -> 0 | AH60: =(V60*AB60) -> 0 | AI60: =(W60*AC60) -> 0 | AJ60: =(X60*AD60) -> 0 | AK60: =IF(AE60>0,AE60/B60,0) -> 0 | AL60: =IF(AF60>0,AF60/C60,0) -> 0 | AM60: =IF(AG60>0,AG60/D60,0) -> 0 | AN60: =IF(AH60>0,AH60/E60,0) -> 0 | AO60: =IF(AI60>0,AI60/F60,0) -> 0 | AP60: =IF(AJ60>0,AJ60/G60,0) -> 0 | AQ60: =AK60+AQ59+IF(AK60<0,AK60,0) -> 0.0074414151 | AR60: =AL60+AR59+IF(AL60<0,AL60,0) -> 0.049163932 | AS60: =AM60+AS59+IF(AM60<0,AM60,0) -> 0.030237578 | AT60: =AN60+AT59+IF(AN60<0,AN60,0) -> 0.02520459 | AU60: =AO60+AU59+IF(AO60<0,AO60,0) -> 0.27778927 | AV60: =AP60+AV59+IF(AP60<0,AP60,0) -> 0.019085166 | AW60: =S60+AQ60 -> 1.830315 | AX60: =T60+AR60 -> 3.9387863 | AY60: =U60+AS60 -> 1.5255978 | AZ60: =V60+AT60 -> 1.1082169 | BA60: =W60+AU60 -> 12.992902 | BB60: =X60+AV60 -> 2.0627196 | BC60: =(AE60+AF60+AG60+AH60+AI60+AJ60) -> 0 | BD60: =BD59+L60 -> -1500 | BE60: =(S60*B60)+(T60*C60)+(U60*D60)+(V60*E60)+(W60*F60)+(X60*G60) -> 1353.4953 | BF60: =(BE60/ABS(BD60))-1 -> -0.097669812 | BG60: =BG59+BC60 -> 23.138674 | BH60: =BE60+BG60 -> 1376.634 | BI60: =(BH60/ABS(BD60))-1 -> -0.082244029 | BJ60: =(B60*AQ60)+(C60*AR60)+(D60*AS60)+(E60*AT60)+(F60*AU60)+(G60*AV60) -> 20.751207 | BK60: =BE60+BJ60 -> 1374.2465 | BL60: =(BK60/ABS(BD60))-1 -> -0.083835674 | BN60: =ABS(BD60) -> 1500 | BO60: =(B60*AW60)+(C60*AX60)+(D60*AY60)+(E60*AZ60)+(F60*BA60)+(G60*BB60) -> 1374.2465 | BQ60: =B60/2 -> 65.705002 | BR60: =G60/2 -> 45.950001
A61: 39475 | B61: 138.39999 | C61: 64.599998 | D61: 52.310001 | E61: 63.599998 | F61: 45 | G61: 97.190002 | L61: =IF(int=Weekly,-$B$4,IF(int=Bi_Weekly,-$B$4,IF(int=Monthly,0,IF(int=Quarterly,-$B$4,IF(int=Yearly,0,IF(int=None,0,0)))))) -> -500 | M61: =(ABS((L61*$B$29)/B61)) -> 0.63583818 | N61: =(ABS((L61*$C$29)/C61)) -> 1.3622291 | O61: =(ABS((L61*$D$29)/D61)) -> 0.53527049 | P61: =(ABS((L61*$E$29)/E61)) -> 0.38522014 | Q61: =(ABS((L61*$F$29)/F61)) -> 4.5666667 | R61: =(ABS((L61*$G$29)/G61)) -> 0.6790822 | S61: =S60+M61 -> 2.4587117 | T61: =T60+N61 -> 5.2518515 | U61: =U60+O61 -> 2.0306307 | V61: =V60+P61 -> 1.4682324 | W61: =W60+Q61 -> 17.28178 | X61: =X60+R61 -> 2.7227167 | AE61: =(S61*Y61) -> 0 | AF61: =(T61*Z61) -> 0 | AG61: =(U61*AA61) -> 0 | AH61: =(V61*AB61) -> 0 | AI61: =(W61*AC61) -> 0 | AJ61: =(X61*AD61) -> 0 | AK61: =IF(AE61>0,AE61/B61,0) -> 0 | AL61: =IF(AF61>0,AF61/C61,0) -> 0 | AM61: =IF(AG61>0,AG61/D61,0) -> 0 | AN61: =IF(AH61>0,AH61/E61,0) -> 0 | AO61: =IF(AI61>0,AI61/F61,0) -> 0 | AP61: =IF(AJ61>0,AJ61/G61,0) -> 0 | AQ61: =AK61+AQ60+IF(AK61<0,AK61,0) -> 0.0074414151 | AR61: =AL61+AR60+IF(AL61<0,AL61,0) -> 0.049163932 | AS61: =AM61+AS60+IF(AM61<0,AM61,0) -> 0.030237578 | AT61: =AN61+AT60+IF(AN61<0,AN61,0) -> 0.02520459 | AU61: =AO61+AU60+IF(AO61<0,AO61,0) -> 0.27778927 | AV61: =AP61+AV60+IF(AP61<0,AP61,0) -> 0.019085166 | AW61: =S61+AQ61 -> 2.4661531 | AX61: =T61+AR61 -> 5.3010154 | AY61: =U61+AS61 -> 2.0608683 | AZ61: =V61+AT61 -> 1.493437 | BA61: =W61+AU61 -> 17.559569 | BB61: =X61+AV61 -> 2.7418018 | BC61: =(AE61+AF61+AG61+AH61+AI61+AJ61) -> 0 | BD61: =BD60+L61 -> -2000 | BE61: =(S61*B61)+(T61*C61)+(U61*D61)+(V61*E61)+(W61*F61)+(X61*G61) -> 1921.4581 | BF61: =(BE61/ABS(BD61))-1 -> -0.039270958 | BG61: =BG60+BC61 -> 23.138674 | BH61: =BE61+BG61 -> 1944.5968 | BI61: =(BH61/ABS(BD61))-1 -> -0.027701621 | BJ61: =(B61*AQ61)+(C61*AR61)+(D61*AS61)+(E61*AT61)+(F61*AU61)+(G61*AV61) -> 21.746026 | BK61: =BE61+BJ61 -> 1943.2041 | BL61: =(BK61/ABS(BD61))-1 -> -0.028397945 | BN61: =ABS(BD61) -> 2000 | BO61: =(B61*AW61)+(C61*AX61)+(D61*AY61)+(E61*AZ61)+(F61*BA61)+(G61*BB61) -> 1943.2041 | BQ61: =B61/2 -> 69.199997 | BR61: =G61/2 -> 48.595001
A62: 39482 | B62: 132.3 | C62: 61.279999 | D62: 49.919998 | E62: 61.389999 | F62: 41.939999 | G62: 92.489998 | L62: =IF(int=Weekly,-$B$4,IF(int=Bi_Weekly,0,IF(int=Monthly,0,IF(int=Quarterly,0,IF(int=Yearly,0,IF(int=None,0,0)))))) -> 0 | M62: =(ABS((L62*$B$29)/B62)) -> 0 | N62: =(ABS((L62*$C$29)/C62)) -> 0 | O62: =(ABS((L62*$D$29)/D62)) -> 0 | P62: =(ABS((L62*$E$29)/E62)) -> 0 | Q62: =(ABS((L62*$F$29)/F62)) -> 0 | R62: =(ABS((L62*$G$29)/G62)) -> 0 | S62: =S61+M62 -> 2.4587117 | T62: =T61+N62 -> 5.2518515 | U62: =U61+O62 -> 2.0306307 | V62: =V61+P62 -> 1.4682324 | W62: =W61+Q62 -> 17.28178 | X62: =X61+R62 -> 2.7227167 | AE62: =(S62*Y62) -> 0 | AF62: =(T62*Z62) -> 0 | AG62: =(U62*AA62) -> 0 | AH62: =(V62*AB62) -> 0 | AI62: =(W62*AC62) -> 0 | AJ62: =(X62*AD62) -> 0 | AK62: =IF(AE62>0,AE62/B62,0) -> 0 | AL62: =IF(AF62>0,AF62/C62,0) -> 0 | AM62: =IF(AG62>0,AG62/D62,0) -> 0 | AN62: =IF(AH62>0,AH62/E62,0) -> 0 | AO62: =IF(AI62>0,AI62/F62,0) -> 0 | AP62: =IF(AJ62>0,AJ62/G62,0) -> 0 | AQ62: =AK62+AQ61+IF(AK62<0,AK62,0) -> 0.0074414151 | AR62: =AL62+AR61+IF(AL62<0,AL62,0) -> 0.049163932 | AS62: =AM62+AS61+IF(AM62<0,AM62,0) -> 0.030237578 | AT62: =AN62+AT61+IF(AN62<0,AN62,0) -> 0.02520459 | AU62: =AO62+AU61+IF(AO62<0,AO62,0) -> 0.27778927 | AV62: =AP62+AV61+IF(AP62<0,AP62,0) -> 0.019085166 | AW62: =S62+AQ62 -> 2.4661531 | AX62: =T62+AR62 -> 5.3010154 | AY62: =U62+AS62 -> 2.0608683 | AZ62: =V62+AT62 -> 1.493437 | BA62: =W62+AU62 -> 17.559569 | BB62: =X62+AV62 -> 2.7418018 | BC62: =(AE62+AF62+AG62+AH62+AI62+AJ62) -> 0 | BD62: =BD61+L62 -> -2000 | BE62: =(S62*B62)+(T62*C62)+(U62*D62)+(V62*E62)+(W62*F62)+(X62*G62) -> 1815.2468 | BF62: =(BE62/ABS(BD62))-1 -> -0.092376613 | BG62: =BG61+BC62 -> 23.138674 | BH62: =BE62+BG62 -> 1838.3854 | BI62: =(BH62/ABS(BD62))-1 -> -0.080807276 | BJ62: =(B62*AQ62)+(C62*AR62)+(D62*AS62)+(E62*AT62)+(F62*AU62)+(G62*AV62) -> 20.469703 | BK62: =BE62+BJ62 -> 1835.7165 | BL62: =(BK62/ABS(BD62))-1 -> -0.082141761 | BN62: =ABS(BD62) -> 2000 | BO62: =(B62*AW62)+(C62*AX62)+(D62*AY62)+(E62*AZ62)+(F62*BA62)+(G62*BB62) -> 1835.7165 | BQ62: =B62/2 -> 66.150002 | BR62: =G62/2 -> 46.244999
A63: 39489 | B63: 134.10001 | C63: 62.029999 | D63: 50.110001 | E63: 61.509998 | F63: 43.18 | G63: 96.449997 | L63: =IF(int=Weekly,-$B$4,IF(int=Bi_Weekly,-$B$4,IF(int=Monthly,-$B$4,IF(int=Quarterly,0,IF(int=Yearly,0,IF(int=None,0,0)))))) -> 0 | M63: =(ABS((L63*$B$29)/B63)) -> 0 | N63: =(ABS((L63*$C$29)/C63)) -> 0 | O63: =(ABS((L63*$D$29)/D63)) -> 0 | P63: =(ABS((L63*$E$29)/E63)) -> 0 | Q63: =(ABS((L63*$F$29)/F63)) -> 0 | R63: =(ABS((L63*$G$29)/G63)) -> 0 | S63: =S62+M63 -> 2.4587117 | T63: =T62+N63 -> 5.2518515 | U63: =U62+O63 -> 2.0306307 | V63: =V62+P63 -> 1.4682324 | W63: =W62+Q63 -> 17.28178 | X63: =X62+R63 -> 2.7227167 | AE63: =(S63*Y63) -> 0 | AF63: =(T63*Z63) -> 0 | AG63: =(U63*AA63) -> 0 | AH63: =(V63*AB63) -> 0 | AI63: =(W63*AC63) -> 0 | AJ63: =(X63*AD63) -> 0 | AK63: =IF(AE63>0,AE63/B63,0) -> 0 | AL63: =IF(AF63>0,AF63/C63,0) -> 0 | AM63: =IF(AG63>0,AG63/D63,0) -> 0 | AN63: =IF(AH63>0,AH63/E63,0) -> 0 | AO63: =IF(AI63>0,AI63/F63,0) -> 0 | AP63: =IF(AJ63>0,AJ63/G63,0) -> 0 | AQ63: =AK63+AQ62+IF(AK63<0,AK63,0) -> 0.0074414151 | AR63: =AL63+AR62+IF(AL63<0,AL63,0) -> 0.049163932 | AS63: =AM63+AS62+IF(AM63<0,AM63,0) -> 0.030237578 | AT63: =AN63+AT62+IF(AN63<0,AN63,0) -> 0.02520459 | AU63: =AO63+AU62+IF(AO63<0,AO63,0) -> 0.27778927 | AV63: =AP63+AV62+IF(AP63<0,AP63,0) -> 0.019085166 | AW63: =S63+AQ63 -> 2.4661531 | AX63: =T63+AR63 -> 5.3010154 | AY63: =U63+AS63 -> 2.0608683 | AZ63: =V63+AT63 -> 1.493437 | BA63: =W63+AU63 -> 17.559569 | BB63: =X63+AV63 -> 2.7418018 | BC63: =(AE63+AF63+AG63+AH63+AI63+AJ63) -> 0 | BD63: =BD62+L63 -> -2000 | BE63: =(S63*B63)+(T63*C63)+(U63*D63)+(V63*E63)+(W63*F63)+(X63*G63) -> 1856.3847 | BF63: =(BE63/ABS(BD63))-1 -> -0.071807629 | BG63: =BG62+BC63 -> 23.138674 | BH63: =BE63+BG63 -> 1879.5234 | BI63: =(BH63/ABS(BD63))-1 -> -0.060238291 | BJ63: =(B63*AQ63)+(C63*AR63)+(D63*AS63)+(E63*AT63)+(F63*AU63)+(G63*AV63) -> 20.948777 | BK63: =BE63+BJ63 -> 1877.3335 | BL63: =(BK63/ABS(BD63))-1 -> -0.06133324 | BN63: =ABS(BD63) -> 2000 | BO63: =(B63*AW63)+(C63*AX63)+(D63*AY63)+(E63*AZ63)+(F63*BA63)+(G63*BB63) -> 1877.3335 | BQ63: =B63/2 -> 67.050003 | BR63: =G63/2 -> 48.224998
A64: 39497 | B64: 134.27 | C64: 62.23 | D64: 50.310001 | E64: 62.200001 | F64: 43.919998 | G64: 98.300003 | L64: =IF(int=Weekly,-$B$4,IF(int=Bi_Weekly,0,IF(int=Monthly,0,IF(int=Quarterly,0,IF(int=Yearly,0,IF(int=None,0,0)))))) -> 0 | M64: =(ABS((L64*$B$29)/B64)) -> 0 | N64: =(ABS((L64*$C$29)/C64)) -> 0 | O64: =(ABS((L64*$D$29)/D64)) -> 0 | P64: =(ABS((L64*$E$29)/E64)) -> 0 | Q64: =(ABS((L64*$F$29)/F64)) -> 0 | R64: =(ABS((L64*$G$29)/G64)) -> 0 | S64: =S63+M64 -> 2.4587117 | T64: =T63+N64 -> 5.2518515 | U64: =U63+O64 -> 2.0306307 | V64: =V63+P64 -> 1.4682324 | W64: =W63+Q64 -> 17.28178 | X64: =X63+R64 -> 2.7227167 | AE64: =(S64*Y64) -> 0 | AF64: =(T64*Z64) -> 0 | AG64: =(U64*AA64) -> 0 | AH64: =(V64*AB64) -> 0 | AI64: =(W64*AC64) -> 0 | AJ64: =(X64*AD64) -> 0 | AK64: =IF(AE64>0,AE64/B64,0) -> 0 | AL64: =IF(AF64>0,AF64/C64,0) -> 0 | AM64: =IF(AG64>0,AG64/D64,0) -> 0 | AN64: =IF(AH64>0,AH64/E64,0) -> 0 | AO64: =IF(AI64>0,AI64/F64,0) -> 0 | AP64: =IF(AJ64>0,AJ64/G64,0) -> 0 | AQ64: =AK64+AQ63+IF(AK64<0,AK64,0) -> 0.0074414151 | AR64: =AL64+AR63+IF(AL64<0,AL64,0) -> 0.049163932 | AS64: =AM64+AS63+IF(AM64<0,AM64,0) -> 0.030237578 | AT64: =AN64+AT63+IF(AN64<0,AN64,0) -> 0.02520459 | AU64: =AO64+AU63+IF(AO64<0,AO64,0) -> 0.27778927 | AV64: =AP64+AV63+IF(AP64<0,AP64,0) -> 0.019085166 | AW64: =S64+AQ64 -> 2.4661531 | AX64: =T64+AR64 -> 5.3010154 | AY64: =U64+AS64 -> 2.0608683 | AZ64: =V64+AT64 -> 1.493437 | BA64: =W64+AU64 -> 17.559569 | BB64: =X64+AV64 -> 2.7418018 | BC64: =(AE64+AF64+AG64+AH64+AI64+AJ64) -> 0 | BD64: =BD63+L64 -> -2000 | BE64: =(S64*B64)+(T64*C64)+(U64*D64)+(V64*E64)+(W64*F64)+(X64*G64) -> 1877.0978 | BF64: =(BE64/ABS(BD64))-1 -> -0.061451085 | BG64: =BG63+BC64 -> 23.138674 | BH64: =BE64+BG64 -> 1900.2365 | BI64: =(BH64/ABS(BD64))-1 -> -0.049881748 | BJ64: =(B64*AQ64)+(C64*AR64)+(D64*AS64)+(E64*AT64)+(F64*AU64)+(G64*AV64) -> 21.224185 | BK64: =BE64+BJ64 -> 1898.322 | BL64: =(BK64/ABS(BD64))-1 -> -0.050838993 | BN64: =ABS(BD64) -> 2000 | BO64: =(B64*AW64)+(C64*AX64)+(D64*AY64)+(E64*AZ64)+(F64*BA64)+(G64*BB64) -> 1898.322 | BQ64: =B64/2 -> 67.135002 | BR64: =G64/2 -> 49.150002
A65: 39503 | B65: 132.8 | C65: 60.779999 | D65: 49.23 | E65: 60.5 | F65: 43.93 | G65: 97.620003 | L65: =IF(int=Weekly,-$B$4,IF(int=Bi_Weekly,-$B$4,IF(int=Monthly,0,IF(int=Quarterly,0,IF(int=Yearly,0,IF(int=None,0,0)))))) -> 0 | M65: =(ABS((L65*$B$29)/B65)) -> 0 | N65: =(ABS((L65*$C$29)/C65)) -> 0 | O65: =(ABS((L65*$D$29)/D65)) -> 0 | P65: =(ABS((L65*$E$29)/E65)) -> 0 | Q65: =(ABS((L65*$F$29)/F65)) -> 0 | R65: =(ABS((L65*$G$29)/G65)) -> 0 | S65: =S64+M65 -> 2.4587117 | T65: =T64+N65 -> 5.2518515 | U65: =U64+O65 -> 2.0306307 | V65: =V64+P65 -> 1.4682324 | W65: =W64+Q65 -> 17.28178 | X65: =X64+R65 -> 2.7227167 | AE65: =(S65*Y65) -> 0 | AF65: =(T65*Z65) -> 0 | AG65: =(U65*AA65) -> 0 | AH65: =(V65*AB65) -> 0 | AI65: =(W65*AC65) -> 0 | AJ65: =(X65*AD65) -> 0 | AK65: =IF(AE65>0,AE65/B65,0) -> 0 | AL65: =IF(AF65>0,AF65/C65,0) -> 0 | AM65: =IF(AG65>0,AG65/D65,0) -> 0 | AN65: =IF(AH65>0,AH65/E65,0) -> 0 | AO65: =IF(AI65>0,AI65/F65,0) -> 0 | AP65: =IF(AJ65>0,AJ65/G65,0) -> 0 | AQ65: =AK65+AQ64+IF(AK65<0,AK65,0) -> 0.0074414151 | AR65: =AL65+AR64+IF(AL65<0,AL65,0) -> 0.049163932 | AS65: =AM65+AS64+IF(AM65<0,AM65,0) -> 0.030237578 | AT65: =AN65+AT64+IF(AN65<0,AN65,0) -> 0.02520459 | AU65: =AO65+AU64+IF(AO65<0,AO65,0) -> 0.27778927 | AV65: =AP65+AV64+IF(AP65<0,AP65,0) -> 0.019085166 | AW65: =S65+AQ65 -> 2.4661531 | AX65: =T65+AR65 -> 5.3010154 | AY65: =U65+AS65 -> 2.0608683 | AZ65: =V65+AT65 -> 1.493437 | BA65: =W65+AU65 -> 17.559569 | BB65: =X65+AV65 -> 2.7418018 | BC65: =(AE65+AF65+AG65+AH65+AI65+AJ65) -> 0 | BD65: =BD64+L65 -> -2000 | BE65: =(S65*B65)+(T65*C65)+(U65*D65)+(V65*E65)+(W65*F65)+(X65*G65) -> 1859.5007 | BF65: =(BE65/ABS(BD65))-1 -> -0.070249672 | BG65: =BG64+BC65 -> 23.138674 | BH65: =BE65+BG65 -> 1882.6393 | BI65: =(BH65/ABS(BD65))-1 -> -0.058680335 | BJ65: =(B65*AQ65)+(C65*AR65)+(D65*AS65)+(E65*AT65)+(F65*AU65)+(G65*AV65) -> 21.056254 | BK65: =BE65+BJ65 -> 1880.5569 | BL65: =(BK65/ABS(BD65))-1 -> -0.059721545 | BN65: =ABS(BD65) -> 2000 | BO65: =(B65*AW65)+(C65*AX65)+(D65*AY65)+(E65*AZ65)+(F65*BA65)+(G65*BB65) -> 1880.5569 | BQ65: =B65/2 -> 66.400002 | BR65: =G65/2 -> 48.810001
A66: 39510 | B66: 128.5 | C66: 58.700001 | D66: 47.77 | E66: 58.360001 | F66: 42.779999 | G66: 94.199997 | L66: =IF(int=Weekly,-$B$4,IF(int=Bi_Weekly,0,IF(int=Monthly,0,IF(int=Quarterly,0,IF(int=Yearly,0,IF(int=None,0,0)))))) -> 0 | M66: =(ABS((L66*$B$29)/B66)) -> 0 | N66: =(ABS((L66*$C$29)/C66)) -> 0 | O66: =(ABS((L66*$D$29)/D66)) -> 0 | P66: =(ABS((L66*$E$29)/E66)) -> 0 | Q66: =(ABS((L66*$F$29)/F66)) -> 0 | R66: =(ABS((L66*$G$29)/G66)) -> 0 | S66: =S65+M66 -> 2.4587117 | T66: =T65+N66 -> 5.2518515 | U66: =U65+O66 -> 2.0306307 | V66: =V65+P66 -> 1.4682324 | W66: =W65+Q66 -> 17.28178 | X66: =X65+R66 -> 2.7227167 | AE66: =(S66*Y66) -> 0 | AF66: =(T66*Z66) -> 0 | AG66: =(U66*AA66) -> 0 | AH66: =(V66*AB66) -> 0 | AI66: =(W66*AC66) -> 0 | AJ66: =(X66*AD66) -> 0 | AK66: =IF(AE66>0,AE66/B66,0) -> 0 | AL66: =IF(AF66>0,AF66/C66,0) -> 0 | AM66: =IF(AG66>0,AG66/D66,0) -> 0 | AN66: =IF(AH66>0,AH66/E66,0) -> 0 | AO66: =IF(AI66>0,AI66/F66,0) -> 0 | AP66: =IF(AJ66>0,AJ66/G66,0) -> 0 | AQ66: =AK66+AQ65+IF(AK66<0,AK66,0) -> 0.0074414151 | AR66: =AL66+AR65+IF(AL66<0,AL66,0) -> 0.049163932 | AS66: =AM66+AS65+IF(AM66<0,AM66,0) -> 0.030237578 | AT66: =AN66+AT65+IF(AN66<0,AN66,0) -> 0.02520459 | AU66: =AO66+AU65+IF(AO66<0,AO66,0) -> 0.27778927 | AV66: =AP66+AV65+IF(AP66<0,AP66,0) -> 0.019085166 | AW66: =S66+AQ66 -> 2.4661531 | AX66: =T66+AR66 -> 5.3010154 | AY66: =U66+AS66 -> 2.0608683 | AZ66: =V66+AT66 -> 1.493437 | BA66: =W66+AU66 -> 17.559569 | BB66: =X66+AV66 -> 2.7418018 | BC66: =(AE66+AF66+AG66+AH66+AI66+AJ66) -> 0 | BD66: =BD65+L66 -> -2000 | BE66: =(S66*B66)+(T66*C66)+(U66*D66)+(V66*E66)+(W66*F66)+(X66*G66) -> 1802.7118 | BF66: =(BE66/ABS(BD66))-1 -> -0.09864408 | BG66: =BG65+BC66 -> 23.138674 | BH66: =BE66+BG66 -> 1825.8505 | BI66: =(BH66/ABS(BD66))-1 -> -0.087074743 | BJ66: =(B66*AQ66)+(C66*AR66)+(D66*AS66)+(E66*AT66)+(F66*AU66)+(G66*AV66) -> 20.439181 | BK66: =BE66+BJ66 -> 1823.151 | BL66: =(BK66/ABS(BD66))-1 -> -0.088424489 | BN66: =ABS(BD66) -> 2000 | BO66: =(B66*AW66)+(C66*AX66)+(D66*AY66)+(E66*AZ66)+(F66*BA66)+(G66*BB66) -> 1823.151 | BQ66: =B66/2 -> 64.25 | BR66: =G66/2 -> 47.099998
A67: 39517 | B67: 128.21001 | C67: 58.689999 | D67: 47.75 | E67: 58.639999 | F67: 42.830002 | G67: 91.779999 | L67: =IF(int=Weekly,-$B$4,IF(int=Bi_Weekly,-$B$4,IF(int=Monthly,-$B$4,IF(int=Quarterly,0,IF(int=Yearly,0,IF(int=None,0,0)))))) -> 0 | M67: =(ABS((L67*$B$29)/B67)) -> 0 | N67: =(ABS((L67*$C$29)/C67)) -> 0 | O67: =(ABS((L67*$D$29)/D67)) -> 0 | P67: =(ABS((L67*$E$29)/E67)) -> 0 | Q67: =(ABS((L67*$F$29)/F67)) -> 0 | R67: =(ABS((L67*$G$29)/G67)) -> 0 | S67: =S66+M67 -> 2.4587117 | T67: =T66+N67 -> 5.2518515 | U67: =U66+O67 -> 2.0306307 | V67: =V66+P67 -> 1.4682324 | W67: =W66+Q67 -> 17.28178 | X67: =X66+R67 -> 2.7227167 | AE67: =(S67*Y67) -> 0 | AF67: =(T67*Z67) -> 0 | AG67: =(U67*AA67) -> 0 | AH67: =(V67*AB67) -> 0 | AI67: =(W67*AC67) -> 0 | AJ67: =(X67*AD67) -> 0 | AK67: =IF(AE67>0,AE67/B67,0) -> 0 | AL67: =IF(AF67>0,AF67/C67,0) -> 0 | AM67: =IF(AG67>0,AG67/D67,0) -> 0 | AN67: =IF(AH67>0,AH67/E67,0) -> 0 | AO67: =IF(AI67>0,AI67/F67,0) -> 0 | AP67: =IF(AJ67>0,AJ67/G67,0) -> 0 | AQ67: =AK67+AQ66+IF(AK67<0,AK67,0) -> 0.0074414151 | AR67: =AL67+AR66+IF(AL67<0,AL67,0) -> 0.049163932 | AS67: =AM67+AS66+IF(AM67<0,AM67,0) -> 0.030237578 | AT67: =AN67+AT66+IF(AN67<0,AN67,0) -> 0.02520459 | AU67: =AO67+AU66+IF(AO67<0,AO67,0) -> 0.27778927 | AV67: =AP67+AV66+IF(AP67<0,AP67,0) -> 0.019085166 | AW67: =S67+AQ67 -> 2.4661531 | AX67: =T67+AR67 -> 5.3010154 | AY67: =U67+AS67 -> 2.0608683 | AZ67: =V67+AT67 -> 1.493437 | BA67: =W67+AU67 -> 17.559569 | BB67: =X67+AV67 -> 2.7418018 | BC67: =(AE67+AF67+AG67+AH67+AI67+AJ67) -> 0 | BD67: =BD66+L67 -> -2000 | BE67: =(S67*B67)+(T67*C67)+(U67*D67)+(V67*E67)+(W67*F67)+(X67*G67) -> 1796.592 | BF67: =(BE67/ABS(BD67))-1 -> -0.10170402 | BG67: =BG66+BC67 -> 23.138674 | BH67: =BE67+BG67 -> 1819.7306 | BI67: =(BH67/ABS(BD67))-1 -> -0.090134681 | BJ67: =(B67*AQ67)+(C67*AR67)+(D67*AS67)+(E67*AT67)+(F67*AU67)+(G67*AV67) -> 20.410688 | BK67: =BE67+BJ67 -> 1817.0027 | BL67: =(BK67/ABS(BD67))-1 -> -0.091498674 | BN67: =ABS(BD67) -> 2000 | BO67: =(B67*AW67)+(C67*AX67)+(D67*AY67)+(E67*AZ67)+(F67*BA67)+(G67*BB67) -> 1817.0027 | BQ67: =B67/2 -> 64.105003 | BR67: =G67/2 -> 45.89
A68: 39524 | B68: 131.16 | C68: 61.150002 | D68: 48.919998 | E68: 60.18 | F68: 42.279999 | G68: 89.959999 | L68: =IF(int=Weekly,-$B$4,IF(int=Bi_Weekly,0,IF(int=Monthly,0,IF(int=Quarterly,0,IF(int=Yearly,0,IF(int=None,0,0)))))) -> 0 | M68: =(ABS((L68*$B$29)/B68)) -> 0 | N68: =(ABS((L68*$C$29)/C68)) -> 0 | O68: =(ABS((L68*$D$29)/D68)) -> 0 | P68: =(ABS((L68*$E$29)/E68)) -> 0 | Q68: =(ABS((L68*$F$29)/F68)) -> 0 | R68: =(ABS((L68*$G$29)/G68)) -> 0 | S68: =S67+M68 -> 2.4587117 | T68: =T67+N68 -> 5.2518515 | U68: =U67+O68 -> 2.0306307 | V68: =V67+P68 -> 1.4682324 | W68: =W67+Q68 -> 17.28178 | X68: =X67+R68 -> 2.7227167 | AE68: =(S68*Y68) -> 0 | AF68: =(T68*Z68) -> 0 | AG68: =(U68*AA68) -> 0 | AH68: =(V68*AB68) -> 0 | AI68: =(W68*AC68) -> 0 | AJ68: =(X68*AD68) -> 0 | AK68: =IF(AE68>0,AE68/B68,0) -> 0 | AL68: =IF(AF68>0,AF68/C68,0) -> 0 | AM68: =IF(AG68>0,AG68/D68,0) -> 0 | AN68: =IF(AH68>0,AH68/E68,0) -> 0 | AO68: =IF(AI68>0,AI68/F68,0) -> 0 | AP68: =IF(AJ68>0,AJ68/G68,0) -> 0 | AQ68: =AK68+AQ67+IF(AK68<0,AK68,0) -> 0.0074414151 | AR68: =AL68+AR67+IF(AL68<0,AL68,0) -> 0.049163932 | AS68: =AM68+AS67+IF(AM68<0,AM68,0) -> 0.030237578 | AT68: =AN68+AT67+IF(AN68<0,AN68,0) -> 0.02520459 | AU68: =AO68+AU67+IF(AO68<0,AO68,0) -> 0.27778927 | AV68: =AP68+AV67+IF(AP68<0,AP68,0) -> 0.019085166 | AW68: =S68+AQ68 -> 2.4661531 | AX68: =T68+AR68 -> 5.3010154 | AY68: =U68+AS68 -> 2.0608683 | AZ68: =V68+AT68 -> 1.493437 | BA68: =W68+AU68 -> 17.559569 | BB68: =X68+AV68 -> 2.7418018 | BC68: =(AE68+AF68+AG68+AH68+AI68+AJ68) -> 0 | BD68: =BD67+L68 -> -2000 | BE68: =(S68*B68)+(T68*C68)+(U68*D68)+(V68*E68)+(W68*F68)+(X68*G68) -> 1806.9413 | BF68: =(BE68/ABS(BD68))-1 -> -0.096529368 | BG68: =BG67+BC68 -> 23.138674 | BH68: =BE68+BG68 -> 1830.0799 | BI68: =(BH68/ABS(BD68))-1 -> -0.084960031 | BJ68: =(B68*AQ68)+(C68*AR68)+(D68*AS68)+(E68*AT68)+(F68*AU68)+(G68*AV68) -> 20.440257 | BK68: =BE68+BJ68 -> 1827.3815 | BL68: =(BK68/ABS(BD68))-1 -> -0.086309239 | BN68: =ABS(BD68) -> 2000 | BO68: =(B68*AW68)+(C68*AX68)+(D68*AY68)+(E68*AZ68)+(F68*BA68)+(G68*BB68) -> 1827.3815 | BQ68: =B68/2 -> 65.580002 | BR68: =G68/2 -> 44.979999
A69: 39531 | B69: 130.34 | C69: 59.77 | D69: 48.439999 | E69: 59.950001 | F69: 43.810001 | G69: 93.480003 | L69: =IF(int=Weekly,-$B$4,IF(int=Bi_Weekly,-$B$4,IF(int=Monthly,0,IF(int=Quarterly,0,IF(int=Yearly,0,IF(int=None,0,0)))))) -> 0 | M69: =(ABS((L69*$B$29)/B69)) -> 0 | N69: =(ABS((L69*$C$29)/C69)) -> 0 | O69: =(ABS((L69*$D$29)/D69)) -> 0 | P69: =(ABS((L69*$E$29)/E69)) -> 0 | Q69: =(ABS((L69*$F$29)/F69)) -> 0 | R69: =(ABS((L69*$G$29)/G69)) -> 0 | S69: =S68+M69 -> 2.4587117 | T69: =T68+N69 -> 5.2518515 | U69: =U68+O69 -> 2.0306307 | V69: =V68+P69 -> 1.4682324 | W69: =W68+Q69 -> 17.28178 | X69: =X68+R69 -> 2.7227167 | AE69: =(S69*Y69) -> 0 | AF69: =(T69*Z69) -> 0 | AG69: =(U69*AA69) -> 0 | AH69: =(V69*AB69) -> 0 | AI69: =(W69*AC69) -> 0 | AJ69: =(X69*AD69) -> 0 | AK69: =IF(AE69>0,AE69/B69,0) -> 0 | AL69: =IF(AF69>0,AF69/C69,0) -> 0 | AM69: =IF(AG69>0,AG69/D69,0) -> 0 | AN69: =IF(AH69>0,AH69/E69,0) -> 0 | AO69: =IF(AI69>0,AI69/F69,0) -> 0 | AP69: =IF(AJ69>0,AJ69/G69,0) -> 0 | AQ69: =AK69+AQ68+IF(AK69<0,AK69,0) -> 0.0074414151 | AR69: =AL69+AR68+IF(AL69<0,AL69,0) -> 0.049163932 | AS69: =AM69+AS68+IF(AM69<0,AM69,0) -> 0.030237578 | AT69: =AN69+AT68+IF(AN69<0,AN69,0) -> 0.02520459 | AU69: =AO69+AU68+IF(AO69<0,AO69,0) -> 0.27778927 | AV69: =AP69+AV68+IF(AP69<0,AP69,0) -> 0.019085166 | AW69: =S69+AQ69 -> 2.4661531 | AX69: =T69+AR69 -> 5.3010154 | AY69: =U69+AS69 -> 2.0608683 | AZ69: =V69+AT69 -> 1.493437 | BA69: =W69+AU69 -> 17.559569 | BB69: =X69+AV69 -> 2.7418018 | BC69: =(AE69+AF69+AG69+AH69+AI69+AJ69) -> 0 | BD69: =BD68+L69 -> -2000 | BE69: =(S69*B69)+(T69*C69)+(U69*D69)+(V69*E69)+(W69*F69)+(X69*G69) -> 1832.3903 | BF69: =(BE69/ABS(BD69))-1 -> -0.083804863 | BG69: =BG68+BC69 -> 23.138674 | BH69: =BE69+BG69 -> 1855.5289 | BI69: =(BH69/ABS(BD69))-1 -> -0.072235526 | BJ69: =(B69*AQ69)+(C69*AR69)+(D69*AS69)+(E69*AT69)+(F69*AU69)+(G69*AV69) -> 20.838195 | BK69: =BE69+BJ69 -> 1853.2285 | BL69: =(BK69/ABS(BD69))-1 -> -0.073385765 | BN69: =ABS(BD69) -> 2000 | BO69: =(B69*AW69)+(C69*AX69)+(D69*AY69)+(E69*AZ69)+(F69*BA69)+(G69*BB69) -> 1853.2285 | BQ69: =B69/2 -> 65.169998 | BR69: =G69/2 -> 46.740001
A70: 39538 | B70: 135.77 | C70: 62.349998 | D70: 50.970001 | E70: 62.599998 | F70: 45.84 | G70: 97.629997 | L70: =IF(int=Weekly,-$B$4,IF(int=Bi_Weekly,0,IF(int=Monthly,0,IF(int=Quarterly,0,IF(int=Yearly,0,IF(int=None,0,0)))))) -> 0 | M70: =(ABS((L70*$B$29)/B70)) -> 0 | N70: =(ABS((L70*$C$29)/C70)) -> 0 | O70: =(ABS((L70*$D$29)/D70)) -> 0 | P70: =(ABS((L70*$E$29)/E70)) -> 0 | Q70: =(ABS((L70*$F$29)/F70)) -> 0 | R70: =(ABS((L70*$G$29)/G70)) -> 0 | S70: =S69+M70 -> 2.4587117 | T70: =T69+N70 -> 5.2518515 | U70: =U69+O70 -> 2.0306307 | V70: =V69+P70 -> 1.4682324 | W70: =W69+Q70 -> 17.28178 | X70: =X69+R70 -> 2.7227167 | AE70: =(S70*Y70) -> 0 | AF70: =(T70*Z70) -> 0 | AG70: =(U70*AA70) -> 0 | AH70: =(V70*AB70) -> 0 | AI70: =(W70*AC70) -> 0 | AJ70: =(X70*AD70) -> 0 | AK70: =IF(AE70>0,AE70/B70,0) -> 0 | AL70: =IF(AF70>0,AF70/C70,0) -> 0 | AM70: =IF(AG70>0,AG70/D70,0) -> 0 | AN70: =IF(AH70>0,AH70/E70,0) -> 0 | AO70: =IF(AI70>0,AI70/F70,0) -> 0 | AP70: =IF(AJ70>0,AJ70/G70,0) -> 0 | AQ70: =AK70+AQ69+IF(AK70<0,AK70,0) -> 0.0074414151 | AR70: =AL70+AR69+IF(AL70<0,AL70,0) -> 0.049163932 | AS70: =AM70+AS69+IF(AM70<0,AM70,0) -> 0.030237578 | AT70: =AN70+AT69+IF(AN70<0,AN70,0) -> 0.02520459 | AU70: =AO70+AU69+IF(AO70<0,AO70,0) -> 0.27778927 | AV70: =AP70+AV69+IF(AP70<0,AP70,0) -> 0.019085166 | AW70: =S70+AQ70 -> 2.4661531 | AX70: =T70+AR70 -> 5.3010154 | AY70: =U70+AS70 -> 2.0608683 | AZ70: =V70+AT70 -> 1.493437 | BA70: =W70+AU70 -> 17.559569 | BB70: =X70+AV70 -> 2.7418018 | BC70: =(AE70+AF70+AG70+AH70+AI70+AJ70) -> 0 | BD70: =BD69+L70 -> -2000 | BE70: =(S70*B70)+(T70*C70)+(U70*D70)+(V70*E70)+(W70*F70)+(X70*G70) -> 1914.7004 | BF70: =(BE70/ABS(BD70))-1 -> -0.042649785 | BG70: =BG69+BC70 -> 23.138674 | BH70: =BE70+BG70 -> 1937.8391 | BI70: =(BH70/ABS(BD70))-1 -> -0.031080448 | BJ70: =(B70*AQ70)+(C70*AR70)+(D70*AS70)+(E70*AT70)+(F70*AU70)+(G70*AV70) -> 21.791854 | BK70: =BE70+BJ70 -> 1936.4923 | BL70: =(BK70/ABS(BD70))-1 -> -0.031753859 | BN70: =ABS(BD70) -> 2000 | BO70: =(B70*AW70)+(C70*AX70)+(D70*AY70)+(E70*AZ70)+(F70*BA70)+(G70*BB70) -> 1936.4923 | BQ70: =B70/2 -> 67.885002 | BR70: =G70/2 -> 48.814999
A71: 39545 | B71: 132.28999 | C71: 60.43 | D71: 49.68 | E71: 60.48 | F71: 44.549999 | G71: 97.010002 | L71: =IF(int=Weekly,-$B$4,IF(int=Bi_Weekly,-$B$4,IF(int=Monthly,-$B$4,IF(int=Quarterly,0,IF(int=Yearly,0,IF(int=None,0,0)))))) -> 0 | M71: =(ABS((L71*$B$29)/B71)) -> 0 | N71: =(ABS((L71*$C$29)/C71)) -> 0 | O71: =(ABS((L71*$D$29)/D71)) -> 0 | P71: =(ABS((L71*$E$29)/E71)) -> 0 | Q71: =(ABS((L71*$F$29)/F71)) -> 0 | R71: =(ABS((L71*$G$29)/G71)) -> 0 | S71: =S70+M71 -> 2.4587117 | T71: =T70+N71 -> 5.2518515 | U71: =U70+O71 -> 2.0306307 | V71: =V70+P71 -> 1.4682324 | W71: =W70+Q71 -> 17.28178 | X71: =X70+R71 -> 2.7227167 | Y71: 0.3115 | Z71: 0.439 | AA71: 0.048 | AB71: 0.046 | AC71: 0.016 | AE71: =(S71*Y71) -> 0.7658887 | AF71: =(T71*Z71) -> 2.3055628 | AG71: =(U71*AA71) -> 0.097470275 | AH71: =(V71*AB71) -> 0.067538691 | AI71: =(W71*AC71) -> 0.27650848 | AJ71: =(X71*AD71) -> 0 | AK71: =IF(AE71>0,AE71/B71,0) -> 0.0057894681 | AL71: =IF(AF71>0,AF71/C71,0) -> 0.03815262 | AM71: =IF(AG71>0,AG71/D71,0) -> 0.0019619621 | AN71: =IF(AH71>0,AH71/E71,0) -> 0.0011167112 | AO71: =IF(AI71>0,AI71/F71,0) -> 0.0062066999 | AP71: =IF(AJ71>0,AJ71/G71,0) -> 0 | AQ71: =AK71+AQ70+IF(AK71<0,AK71,0) -> 0.013230883 | AR71: =AL71+AR70+IF(AL71<0,AL71,0) -> 0.087316552 | AS71: =AM71+AS70+IF(AM71<0,AM71,0) -> 0.03219954 | AT71: =AN71+AT70+IF(AN71<0,AN71,0) -> 0.026321301 | AU71: =AO71+AU70+IF(AO71<0,AO71,0) -> 0.28399597 | AV71: =AP71+AV70+IF(AP71<0,AP71,0) -> 0.019085166 | AW71: =S71+AQ71 -> 2.4719426 | AX71: =T71+AR71 -> 5.339168 | AY71: =U71+AS71 -> 2.0628303 | AZ71: =V71+AT71 -> 1.4945537 | BA71: =W71+AU71 -> 17.565776 | BB71: =X71+AV71 -> 2.7418018 | BC71: =(AE71+AF71+AG71+AH71+AI71+AJ71) -> 3.5129689 | BD71: =BD70+L71 -> -2000 | BE71: =(S71*B71)+(T71*C71)+(U71*D71)+(V71*E71)+(W71*F71)+(X71*G71) -> 1866.3468 | BF71: =(BE71/ABS(BD71))-1 -> -0.066826604 | BG71: =BG70+BC71 -> 26.651643 | BH71: =BE71+BG71 -> 1892.9984 | BI71: =(BH71/ABS(BD71))-1 -> -0.053500782 | BJ71: =(B71*AQ71)+(C71*AR71)+(D71*AS71)+(E71*AT71)+(F71*AU71)+(G71*AV71) -> 24.72191 | BK71: =BE71+BJ71 -> 1891.0687 | BL71: =(BK71/ABS(BD71))-1 -> -0.054465649 | BN71: =ABS(BD71) -> 2000 | BO71: =(B71*AW71)+(C71*AX71)+(D71*AY71)+(E71*AZ71)+(F71*BA71)+(G71*BB71) -> 1891.0687 | BQ71: =B71/2 -> 66.144997 | BR71: =G71/2 -> 48.505001
A72: 39552 | B72: 137.78999 | C72: 62.740002 | D72: 51.73 | E72: 63.080002 | F72: 46.169998 | G72: 101.25 | L72: =IF(int=Weekly,-$B$4,IF(int=Bi_Weekly,0,IF(int=Monthly,0,IF(int=Quarterly,0,IF(int=Yearly,0,IF(int=None,0,0)))))) -> 0 | M72: =(ABS((L72*$B$29)/B72)) -> 0 | N72: =(ABS((L72*$C$29)/C72)) -> 0 | O72: =(ABS((L72*$D$29)/D72)) -> 0 | P72: =(ABS((L72*$E$29)/E72)) -> 0 | Q72: =(ABS((L72*$F$29)/F72)) -> 0 | R72: =(ABS((L72*$G$29)/G72)) -> 0 | S72: =S71+M72 -> 2.4587117 | T72: =T71+N72 -> 5.2518515 | U72: =U71+O72 -> 2.0306307 | V72: =V71+P72 -> 1.4682324 | W72: =W71+Q72 -> 17.28178 | X72: =X71+R72 -> 2.7227167 | AE72: =(S72*Y72) -> 0 | AF72: =(T72*Z72) -> 0 | AG72: =(U72*AA72) -> 0 | AH72: =(V72*AB72) -> 0 | AI72: =(W72*AC72) -> 0 | AJ72: =(X72*AD72) -> 0 | AK72: =IF(AE72>0,AE72/B72,0) -> 0 | AL72: =IF(AF72>0,AF72/C72,0) -> 0 | AM72: =IF(AG72>0,AG72/D72,0) -> 0 | AN72: =IF(AH72>0,AH72/E72,0) -> 0 | AO72: =IF(AI72>0,AI72/F72,0) -> 0 | AP72: =IF(AJ72>0,AJ72/G72,0) -> 0 | AQ72: =AK72+AQ71+IF(AK72<0,AK72,0) -> 0.013230883 | AR72: =AL72+AR71+IF(AL72<0,AL72,0) -> 0.087316552 | AS72: =AM72+AS71+IF(AM72<0,AM72,0) -> 0.03219954 | AT72: =AN72+AT71+IF(AN72<0,AN72,0) -> 0.026321301 | AU72: =AO72+AU71+IF(AO72<0,AO72,0) -> 0.28399597 | AV72: =AP72+AV71+IF(AP72<0,AP72,0) -> 0.019085166 | AW72: =S72+AQ72 -> 2.4719426 | AX72: =T72+AR72 -> 5.339168 | AY72: =U72+AS72 -> 2.0628303 | AZ72: =V72+AT72 -> 1.4945537 | BA72: =W72+AU72 -> 17.565776 | BB72: =X72+AV72 -> 2.7418018 | BC72: =(AE72+AF72+AG72+AH72+AI72+AJ72) -> 0 | BD72: =BD71+L72 -> -2000 | BE72: =(S72*B72)+(T72*C72)+(U72*D72)+(V72*E72)+(W72*F72)+(X72*G72) -> 1939.5225 | BF72: =(BE72/ABS(BD72))-1 -> -0.030238764 | BG72: =BG71+BC72 -> 26.651643 | BH72: =BE72+BG72 -> 1966.1741 | BI72: =(BH72/ABS(BD72))-1 -> -0.016912942 | BJ72: =(B72*AQ72)+(C72*AR72)+(D72*AS72)+(E72*AT72)+(F72*AU72)+(G72*AV72) -> 25.67182 | BK72: =BE72+BJ72 -> 1965.1943 | BL72: =(BK72/ABS(BD72))-1 -> -0.017402853 | BN72: =ABS(BD72) -> 2000 | BO72: =(B72*AW72)+(C72*AX72)+(D72*AY72)+(E72*AZ72)+(F72*BA72)+(G72*BB72) -> 1965.1943 | BQ72: =B72/2 -> 68.894997 | BR72: =G72/2 -> 50.625
A73: 39559 | B73: 138.59 | C73: 63.23 | D73: 51.919998 | E73: 63.41 | F73: 46.470001 | G73: 102.97 | L73: =IF(int=Weekly,-$B$4,IF(int=Bi_Weekly,-$B$4,IF(int=Monthly,0,IF(int=Quarterly,0,IF(int=Yearly,0,IF(int=None,0,0)))))) -> 0 | M73: =(ABS((L73*$B$29)/B73)) -> 0 | N73: =(ABS((L73*$C$29)/C73)) -> 0 | O73: =(ABS((L73*$D$29)/D73)) -> 0 | P73: =(ABS((L73*$E$29)/E73)) -> 0 | Q73: =(ABS((L73*$F$29)/F73)) -> 0 | R73: =(ABS((L73*$G$29)/G73)) -> 0 | S73: =S72+M73 -> 2.4587117 | T73: =T72+N73 -> 5.2518515 | U73: =U72+O73 -> 2.0306307 | V73: =V72+P73 -> 1.4682324 | W73: =W72+Q73 -> 17.28178 | X73: =X72+R73 -> 2.7227167 | AE73: =(S73*Y73) -> 0 | AF73: =(T73*Z73) -> 0 | AG73: =(U73*AA73) -> 0 | AH73: =(V73*AB73) -> 0 | AI73: =(W73*AC73) -> 0 | AJ73: =(X73*AD73) -> 0 | AK73: =IF(AE73>0,AE73/B73,0) -> 0 | AL73: =IF(AF73>0,AF73/C73,0) -> 0 | AM73: =IF(AG73>0,AG73/D73,0) -> 0 | AN73: =IF(AH73>0,AH73/E73,0) -> 0 | AO73: =IF(AI73>0,AI73/F73,0) -> 0 | AP73: =IF(AJ73>0,AJ73/G73,0) -> 0 | AQ73: =AK73+AQ72+IF(AK73<0,AK73,0) -> 0.013230883 | AR73: =AL73+AR72+IF(AL73<0,AL73,0) -> 0.087316552 | AS73: =AM73+AS72+IF(AM73<0,AM73,0) -> 0.03219954 | AT73: =AN73+AT72+IF(AN73<0,AN73,0) -> 0.026321301 | AU73: =AO73+AU72+IF(AO73<0,AO73,0) -> 0.28399597 | AV73: =AP73+AV72+IF(AP73<0,AP73,0) -> 0.019085166 | AW73: =S73+AQ73 -> 2.4719426 | AX73: =T73+AR73 -> 5.339168 | AY73: =U73+AS73 -> 2.0628303 | AZ73: =V73+AT73 -> 1.4945537 | BA73: =W73+AU73 -> 17.565776 | BB73: =X73+AV73 -> 2.7418018 | BC73: =(AE73+AF73+AG73+AH73+AI73+AJ73) -> 0 | BD73: =BD72+L73 -> -2000 | BE73: =(S73*B73)+(T73*C73)+(U73*D73)+(V73*E73)+(W73*F73)+(X73*G73) -> 1954.8008 | BF73: =(BE73/ABS(BD73))-1 -> -0.022599581 | BG73: =BG72+BC73 -> 26.651643 | BH73: =BE73+BG73 -> 1981.4525 | BI73: =(BH73/ABS(BD73))-1 -> -0.0092737598 | BJ73: =(B73*AQ73)+(C73*AR73)+(D73*AS73)+(E73*AT73)+(F73*AU73)+(G73*AV73) -> 25.85802 | BK73: =BE73+BJ73 -> 1980.6589 | BL73: =(BK73/ABS(BD73))-1 -> -0.0096705714 | BN73: =ABS(BD73) -> 2000 | BO73: =(B73*AW73)+(C73*AX73)+(D73*AY73)+(E73*AZ73)+(F73*BA73)+(G73*BB73) -> 1980.6589 | BQ73: =B73/2 -> 69.294998 | BR73: =G73/2 -> 51.485
A74: 39566 | B74: 140.22 | C74: 63.91 | D74: 52.400002 | E74: 64.32 | F74: 46.939999 | G74: 104.13 | L74: =IF(int=Weekly,-$B$4,IF(int=Bi_Weekly,0,IF(int=Monthly,0,IF(int=Quarterly,-$B$4,IF(int=Yearly,0,IF(int=None,0,0)))))) -> -500 | M74: =(ABS((L74*$B$29)/B74)) -> 0.62758522 | N74: =(ABS((L74*$C$29)/C74)) -> 1.3769363 | O74: =(ABS((L74*$D$29)/D74)) -> 0.53435112 | P74: =(ABS((L74*$E$29)/E74)) -> 0.38090796 | Q74: =(ABS((L74*$F$29)/F74)) -> 4.3779294 | R74: =(ABS((L74*$G$29)/G74)) -> 0.63382312 | S74: =S73+M74 -> 3.0862969 | T74: =T73+N74 -> 6.6287878 | U74: =U73+O74 -> 2.5649819 | V74: =V73+P74 -> 1.8491404 | W74: =W73+Q74 -> 21.659709 | X74: =X73+R74 -> 3.3565398 | AE74: =(S74*Y74) -> 0 | AF74: =(T74*Z74) -> 0 | AG74: =(U74*AA74) -> 0 | AH74: =(V74*AB74) -> 0 | AI74: =(W74*AC74) -> 0 | AJ74: =(X74*AD74) -> 0 | AK74: =IF(AE74>0,AE74/B74,0) -> 0 | AL74: =IF(AF74>0,AF74/C74,0) -> 0 | AM74: =IF(AG74>0,AG74/D74,0) -> 0 | AN74: =IF(AH74>0,AH74/E74,0) -> 0 | AO74: =IF(AI74>0,AI74/F74,0) -> 0 | AP74: =IF(AJ74>0,AJ74/G74,0) -> 0 | AQ74: =AK74+AQ73+IF(AK74<0,AK74,0) -> 0.013230883 | AR74: =AL74+AR73+IF(AL74<0,AL74,0) -> 0.087316552 | AS74: =AM74+AS73+IF(AM74<0,AM74,0) -> 0.03219954 | AT74: =AN74+AT73+IF(AN74<0,AN74,0) -> 0.026321301 | AU74: =AO74+AU73+IF(AO74<0,AO74,0) -> 0.28399597 | AV74: =AP74+AV73+IF(AP74<0,AP74,0) -> 0.019085166 | AW74: =S74+AQ74 -> 3.0995278 | AX74: =T74+AR74 -> 6.7161044 | AY74: =U74+AS74 -> 2.5971814 | AZ74: =V74+AT74 -> 1.8754617 | BA74: =W74+AU74 -> 21.943705 | BB74: =X74+AV74 -> 3.3756249 | BC74: =(AE74+AF74+AG74+AH74+AI74+AJ74) -> 0 | BD74: =BD73+L74 -> -2500 | BE74: =(S74*B74)+(T74*C74)+(U74*D74)+(V74*E74)+(W74*F74)+(X74*G74) -> 2475.9714 | BF74: =(BE74/ABS(BD74))-1 -> -0.0096114587 | BG74: =BG73+BC74 -> 26.651643 | BH74: =BE74+BG74 -> 2502.623 | BI74: =(BH74/ABS(BD74))-1 -> 0.0010491986 | BJ74: =(B74*AQ74)+(C74*AR74)+(D74*AS74)+(E74*AT74)+(F74*AU74)+(G74*AV74) -> 26.133986 | BK74: =BE74+BJ74 -> 2502.1053 | BL74: =(BK74/ABS(BD74))-1 -> 0.00084213581 | BN74: =ABS(BD74) -> 2500 | BO74: =(B74*AW74)+(C74*AX74)+(D74*AY74)+(E74*AZ74)+(F74*BA74)+(G74*BB74) -> 2502.1053 | BQ74: =B74/2 -> 70.11 | BR74: =G74/2 -> 52.064999
A75: 39573 | B75: 138.35001 | C75: 62.330002 | D75: 51.970001 | E75: 63.549999 | F75: 46.560001 | G75: 102.11 | L75: =IF(int=Weekly,-$B$4,IF(int=Bi_Weekly,-$B$4,IF(int=Monthly,-$B$4,IF(int=Quarterly,0,IF(int=Yearly,0,IF(int=None,0,0)))))) -> 0 | M75: =(ABS((L75*$B$29)/B75)) -> 0 | N75: =(ABS((L75*$C$29)/C75)) -> 0 | O75: =(ABS((L75*$D$29)/D75)) -> 0 | P75: =(ABS((L75*$E$29)/E75)) -> 0 | Q75: =(ABS((L75*$F$29)/F75)) -> 0 | R75: =(ABS((L75*$G$29)/G75)) -> 0 | S75: =S74+M75 -> 3.0862969 | T75: =T74+N75 -> 6.6287878 | U75: =U74+O75 -> 2.5649819 | V75: =V74+P75 -> 1.8491404 | W75: =W74+Q75 -> 21.659709 | X75: =X74+R75 -> 3.3565398 | AE75: =(S75*Y75) -> 0 | AF75: =(T75*Z75) -> 0 | AG75: =(U75*AA75) -> 0 | AH75: =(V75*AB75) -> 0 | AI75: =(W75*AC75) -> 0 | AJ75: =(X75*AD75) -> 0 | AK75: =IF(AE75>0,AE75/B75,0) -> 0 | AL75: =IF(AF75>0,AF75/C75,0) -> 0 | AM75: =IF(AG75>0,AG75/D75,0) -> 0 | AN75: =IF(AH75>0,AH75/E75,0) -> 0 | AO75: =IF(AI75>0,AI75/F75,0) -> 0 | AP75: =IF(AJ75>0,AJ75/G75,0) -> 0 | AQ75: =AK75+AQ74+IF(AK75<0,AK75,0) -> 0.013230883 | AR75: =AL75+AR74+IF(AL75<0,AL75,0) -> 0.087316552 | AS75: =AM75+AS74+IF(AM75<0,AM75,0) -> 0.03219954 | AT75: =AN75+AT74+IF(AN75<0,AN75,0) -> 0.026321301 | AU75: =AO75+AU74+IF(AO75<0,AO75,0) -> 0.28399597 | AV75: =AP75+AV74+IF(AP75<0,AP75,0) -> 0.019085166 | AW75: =S75+AQ75 -> 3.0995278 | AX75: =T75+AR75 -> 6.7161044 | AY75: =U75+AS75 -> 2.5971814 | AZ75: =V75+AT75 -> 1.8754617 | BA75: =W75+AU75 -> 21.943705 | BB75: =X75+AV75 -> 3.3756249 | BC75: =(AE75+AF75+AG75+AH75+AI75+AJ75) -> 0 | BD75: =BD74+L75 -> -2500 | BE75: =(S75*B75)+(T75*C75)+(U75*D75)+(V75*E75)+(W75*F75)+(X75*G75) -> 2442.1889 | BF75: =(BE75/ABS(BD75))-1 -> -0.023124442 | BG75: =BG74+BC75 -> 26.651643 | BH75: =BE75+BG75 -> 2468.8405 | BI75: =(BH75/ABS(BD75))-1 -> -0.012463785 | BJ75: =(B75*AQ75)+(C75*AR75)+(D75*AS75)+(E75*AT75)+(F75*AU75)+(G75*AV75) -> 25.790702 | BK75: =BE75+BJ75 -> 2467.9796 | BL75: =(BK75/ABS(BD75))-1 -> -0.012808162 | BN75: =ABS(BD75) -> 2500 | BO75: =(B75*AW75)+(C75*AX75)+(D75*AY75)+(E75*AZ75)+(F75*BA75)+(G75*BB75) -> 2467.9796 | BQ75: =B75/2 -> 69.175003 | BR75: =G75/2 -> 51.055
A76: 39580 | B76: 142.11999 | C76: 63.900002 | D76: 53.889999 | E76: 65.589996 | F76: 48.130001 | G76: 106.76 | L76: =IF(int=Weekly,-$B$4,IF(int=Bi_Weekly,0,IF(int=Monthly,0,IF(int=Quarterly,0,IF(int=Yearly,0,IF(int=None,0,0)))))) -> 0 | M76: =(ABS((L76*$B$29)/B76)) -> 0 | N76: =(ABS((L76*$C$29)/C76)) -> 0 | O76: =(ABS((L76*$D$29)/D76)) -> 0 | P76: =(ABS((L76*$E$29)/E76)) -> 0 | Q76: =(ABS((L76*$F$29)/F76)) -> 0 | R76: =(ABS((L76*$G$29)/G76)) -> 0 | S76: =S75+M76 -> 3.0862969 | T76: =T75+N76 -> 6.6287878 | U76: =U75+O76 -> 2.5649819 | V76: =V75+P76 -> 1.8491404 | W76: =W75+Q76 -> 21.659709 | X76: =X75+R76 -> 3.3565398 | AE76: =(S76*Y76) -> 0 | AF76: =(T76*Z76) -> 0 | AG76: =(U76*AA76) -> 0 | AH76: =(V76*AB76) -> 0 | AI76: =(W76*AC76) -> 0 | AJ76: =(X76*AD76) -> 0 | AK76: =IF(AE76>0,AE76/B76,0) -> 0 | AL76: =IF(AF76>0,AF76/C76,0) -> 0 | AM76: =IF(AG76>0,AG76/D76,0) -> 0 | AN76: =IF(AH76>0,AH76/E76,0) -> 0 | AO76: =IF(AI76>0,AI76/F76,0) -> 0 | AP76: =IF(AJ76>0,AJ76/G76,0) -> 0 | AQ76: =AK76+AQ75+IF(AK76<0,AK76,0) -> 0.013230883 | AR76: =AL76+AR75+IF(AL76<0,AL76,0) -> 0.087316552 | AS76: =AM76+AS75+IF(AM76<0,AM76,0) -> 0.03219954 | AT76: =AN76+AT75+IF(AN76<0,AN76,0) -> 0.026321301 | AU76: =AO76+AU75+IF(AO76<0,AO76,0) -> 0.28399597 | AV76: =AP76+AV75+IF(AP76<0,AP76,0) -> 0.019085166 | AW76: =S76+AQ76 -> 3.0995278 | AX76: =T76+AR76 -> 6.7161044 | AY76: =U76+AS76 -> 2.5971814 | AZ76: =V76+AT76 -> 1.8754617 | BA76: =W76+AU76 -> 21.943705 | BB76: =X76+AV76 -> 3.3756249 | BC76: =(AE76+AF76+AG76+AH76+AI76+AJ76) -> 0 | BD76: =BD75+L76 -> -2500 | BE76: =(S76*B76)+(T76*C76)+(U76*D76)+(V76*E76)+(W76*F76)+(X76*G76) -> 2522.5421 | BF76: =(BE76/ABS(BD76))-1 -> 0.0090168216 | BG76: =BG75+BC76 -> 26.651643 | BH76: =BE76+BG76 -> 2549.1937 | BI76: =(BH76/ABS(BD76))-1 -> 0.019677479 | BJ76: =(B76*AQ76)+(C76*AR76)+(D76*AS76)+(E76*AT76)+(F76*AU76)+(G76*AV76) -> 26.627807 | BK76: =BE76+BJ76 -> 2549.1699 | BL76: =(BK76/ABS(BD76))-1 -> 0.019667944 | BN76: =ABS(BD76) -> 2500 | BO76: =(B76*AW76)+(C76*AX76)+(D76*AY76)+(E76*AZ76)+(F76*BA76)+(G76*BB76) -> 2549.1699 | BQ76: =B76/2 -> 71.059997 | BR76: =G76/2 -> 53.380001
A77: 39587 | B77: 137.26 | C77: 61.610001 | D77: 52.27 | E77: 64.089996 | F77: 46.900002 | G77: 102.36 | L77: =IF(int=Weekly,-$B$4,IF(int=Bi_Weekly,-$B$4,IF(int=Monthly,0,IF(int=Quarterly,0,IF(int=Yearly,0,IF(int=None,0,0)))))) -> 0 | M77: =(ABS((L77*$B$29)/B77)) -> 0 | N77: =(ABS((L77*$C$29)/C77)) -> 0 | O77: =(ABS((L77*$D$29)/D77)) -> 0 | P77: =(ABS((L77*$E$29)/E77)) -> 0 | Q77: =(ABS((L77*$F$29)/F77)) -> 0 | R77: =(ABS((L77*$G$29)/G77)) -> 0 | S77: =S76+M77 -> 3.0862969 | T77: =T76+N77 -> 6.6287878 | U77: =U76+O77 -> 2.5649819 | V77: =V76+P77 -> 1.8491404 | W77: =W76+Q77 -> 21.659709 | X77: =X76+R77 -> 3.3565398 | AE77: =(S77*Y77) -> 0 | AF77: =(T77*Z77) -> 0 | AG77: =(U77*AA77) -> 0 | AH77: =(V77*AB77) -> 0 | AI77: =(W77*AC77) -> 0 | AJ77: =(X77*AD77) -> 0 | AK77: =IF(AE77>0,AE77/B77,0) -> 0 | AL77: =IF(AF77>0,AF77/C77,0) -> 0 | AM77: =IF(AG77>0,AG77/D77,0) -> 0 | AN77: =IF(AH77>0,AH77/E77,0) -> 0 | AO77: =IF(AI77>0,AI77/F77,0) -> 0 | AP77: =IF(AJ77>0,AJ77/G77,0) -> 0 | AQ77: =AK77+AQ76+IF(AK77<0,AK77,0) -> 0.013230883 | AR77: =AL77+AR76+IF(AL77<0,AL77,0) -> 0.087316552 | AS77: =AM77+AS76+IF(AM77<0,AM77,0) -> 0.03219954 | AT77: =AN77+AT76+IF(AN77<0,AN77,0) -> 0.026321301 | AU77: =AO77+AU76+IF(AO77<0,AO77,0) -> 0.28399597 | AV77: =AP77+AV76+IF(AP77<0,AP77,0) -> 0.019085166 | AW77: =S77+AQ77 -> 3.0995278 | AX77: =T77+AR77 -> 6.7161044 | AY77: =U77+AS77 -> 2.5971814 | AZ77: =V77+AT77 -> 1.8754617 | BA77: =W77+AU77 -> 21.943705 | BB77: =X77+AV77 -> 3.3756249 | BC77: =(AE77+AF77+AG77+AH77+AI77+AJ77) -> 0 | BD77: =BD76+L77 -> -2500 | BE77: =(S77*B77)+(T77*C77)+(U77*D77)+(V77*E77)+(W77*F77)+(X77*G77) -> 2444.0235 | BF77: =(BE77/ABS(BD77))-1 -> -0.022390583 | BG77: =BG76+BC77 -> 26.651643 | BH77: =BE77+BG77 -> 2470.6752 | BI77: =(BH77/ABS(BD77))-1 -> -0.011729926 | BJ77: =(B77*AQ77)+(C77*AR77)+(D77*AS77)+(E77*AT77)+(F77*AU77)+(G77*AV77) -> 25.838615 | BK77: =BE77+BJ77 -> 2469.8622 | BL77: =(BK77/ABS(BD77))-1 -> -0.012055137 | BN77: =ABS(BD77) -> 2500 | BO77: =(B77*AW77)+(C77*AX77)+(D77*AY77)+(E77*AZ77)+(F77*BA77)+(G77*BB77) -> 2469.8622 | BQ77: =B77/2 -> 68.629998 | BR77: =G77/2 -> 51.18
A78: 39595 | B78: 140.17 | C78: 62.290001 | D78: 53.240002 | E78: 65.650002 | F78: 47.009998 | G78: 103.78 | L78: =IF(int=Weekly,-$B$4,IF(int=Bi_Weekly,0,IF(int=Monthly,0,IF(int=Quarterly,0,IF(int=Yearly,0,IF(int=None,0,0)))))) -> 0 | M78: =(ABS((L78*$B$29)/B78)) -> 0 | N78: =(ABS((L78*$C$29)/C78)) -> 0 | O78: =(ABS((L78*$D$29)/D78)) -> 0 | P78: =(ABS((L78*$E$29)/E78)) -> 0 | Q78: =(ABS((L78*$F$29)/F78)) -> 0 | R78: =(ABS((L78*$G$29)/G78)) -> 0 | S78: =S77+M78 -> 3.0862969 | T78: =T77+N78 -> 6.6287878 | U78: =U77+O78 -> 2.5649819 | V78: =V77+P78 -> 1.8491404 | W78: =W77+Q78 -> 21.659709 | X78: =X77+R78 -> 3.3565398 | AE78: =(S78*Y78) -> 0 | AF78: =(T78*Z78) -> 0 | AG78: =(U78*AA78) -> 0 | AH78: =(V78*AB78) -> 0 | AI78: =(W78*AC78) -> 0 | AJ78: =(X78*AD78) -> 0 | AK78: =IF(AE78>0,AE78/B78,0) -> 0 | AL78: =IF(AF78>0,AF78/C78,0) -> 0 | AM78: =IF(AG78>0,AG78/D78,0) -> 0 | AN78: =IF(AH78>0,AH78/E78,0) -> 0 | AO78: =IF(AI78>0,AI78/F78,0) -> 0 | AP78: =IF(AJ78>0,AJ78/G78,0) -> 0 | AQ78: =AK78+AQ77+IF(AK78<0,AK78,0) -> 0.013230883 | AR78: =AL78+AR77+IF(AL78<0,AL78,0) -> 0.087316552 | AS78: =AM78+AS77+IF(AM78<0,AM78,0) -> 0.03219954 | AT78: =AN78+AT77+IF(AN78<0,AN78,0) -> 0.026321301 | AU78: =AO78+AU77+IF(AO78<0,AO78,0) -> 0.28399597 | AV78: =AP78+AV77+IF(AP78<0,AP78,0) -> 0.019085166 | AW78: =S78+AQ78 -> 3.0995278 | AX78: =T78+AR78 -> 6.7161044 | AY78: =U78+AS78 -> 2.5971814 | AZ78: =V78+AT78 -> 1.8754617 | BA78: =W78+AU78 -> 21.943705 | BB78: =X78+AV78 -> 3.3756249 | BC78: =(AE78+AF78+AG78+AH78+AI78+AJ78) -> 0 | BD78: =BD77+L78 -> -2500 | BE78: =(S78*B78)+(T78*C78)+(U78*D78)+(V78*E78)+(W78*F78)+(X78*G78) -> 2470.0337 | BF78: =(BE78/ABS(BD78))-1 -> -0.011986512 | BG78: =BG77+BC78 -> 26.651643 | BH78: =BE78+BG78 -> 2496.6854 | BI78: =(BH78/ABS(BD78))-1 -> -0.0013258545 | BJ78: =(B78*AQ78)+(C78*AR78)+(D78*AS78)+(E78*AT78)+(F78*AU78)+(G78*AV78) -> 26.067127 | BK78: =BE78+BJ78 -> 2496.1008 | BL78: =(BK78/ABS(BD78))-1 -> -0.0015596612 | BN78: =ABS(BD78) -> 2500 | BO78: =(B78*AW78)+(C78*AX78)+(D78*AY78)+(E78*AZ78)+(F78*BA78)+(G78*BB78) -> 2496.1008 | BQ78: =B78/2 -> 70.084999 | BR78: =G78/2 -> 51.89
A79: 39601 | B79: 136.99 | C79: 60.299999 | D79: 52 | E79: 64.389999 | F79: 45.580002 | G79: 99.379997 | L79: =IF(int=Weekly,-$B$4,IF(int=Bi_Weekly,-$B$4,IF(int=Monthly,-$B$4,IF(int=Quarterly,0,IF(int=Yearly,0,IF(int=None,0,0)))))) -> 0 | M79: =(ABS((L79*$B$29)/B79)) -> 0 | N79: =(ABS((L79*$C$29)/C79)) -> 0 | O79: =(ABS((L79*$D$29)/D79)) -> 0 | P79: =(ABS((L79*$E$29)/E79)) -> 0 | Q79: =(ABS((L79*$F$29)/F79)) -> 0 | R79: =(ABS((L79*$G$29)/G79)) -> 0 | S79: =S78+M79 -> 3.0862969 | T79: =T78+N79 -> 6.6287878 | U79: =U78+O79 -> 2.5649819 | V79: =V78+P79 -> 1.8491404 | W79: =W78+Q79 -> 21.659709 | X79: =X78+R79 -> 3.3565398 | AE79: =(S79*Y79) -> 0 | AF79: =(T79*Z79) -> 0 | AG79: =(U79*AA79) -> 0 | AH79: =(V79*AB79) -> 0 | AI79: =(W79*AC79) -> 0 | AJ79: =(X79*AD79) -> 0 | AK79: =IF(AE79>0,AE79/B79,0) -> 0 | AL79: =IF(AF79>0,AF79/C79,0) -> 0 | AM79: =IF(AG79>0,AG79/D79,0) -> 0 | AN79: =IF(AH79>0,AH79/E79,0) -> 0 | AO79: =IF(AI79>0,AI79/F79,0) -> 0 | AP79: =IF(AJ79>0,AJ79/G79,0) -> 0 | AQ79: =AK79+AQ78+IF(AK79<0,AK79,0) -> 0.013230883 | AR79: =AL79+AR78+IF(AL79<0,AL79,0) -> 0.087316552 | AS79: =AM79+AS78+IF(AM79<0,AM79,0) -> 0.03219954 | AT79: =AN79+AT78+IF(AN79<0,AN79,0) -> 0.026321301 | AU79: =AO79+AU78+IF(AO79<0,AO79,0) -> 0.28399597 | AV79: =AP79+AV78+IF(AP79<0,AP79,0) -> 0.019085166 | AW79: =S79+AQ79 -> 3.0995278 | AX79: =T79+AR79 -> 6.7161044 | AY79: =U79+AS79 -> 2.5971814 | AZ79: =V79+AT79 -> 1.8754617 | BA79: =W79+AU79 -> 21.943705 | BB79: =X79+AV79 -> 3.3756249 | BC79: =(AE79+AF79+AG79+AH79+AI79+AJ79) -> 0 | BD79: =BD78+L79 -> -2500 | BE79: =(S79*B79)+(T79*C79)+(U79*D79)+(V79*E79)+(W79*F79)+(X79*G79) -> 2395.7754 | BF79: =(BE79/ABS(BD79))-1 -> -0.041689827 | BG79: =BG78+BC79 -> 26.651643 | BH79: =BE79+BG79 -> 2422.4271 | BI79: =(BH79/ABS(BD79))-1 -> -0.03102917 | BJ79: =(B79*AQ79)+(C79*AR79)+(D79*AS79)+(E79*AT79)+(F79*AU79)+(G79*AV79) -> 25.288112 | BK79: =BE79+BJ79 -> 2421.0635 | BL79: =(BK79/ABS(BD79))-1 -> -0.031574582 | BN79: =ABS(BD79) -> 2500 | BO79: =(B79*AW79)+(C79*AX79)+(D79*AY79)+(E79*AZ79)+(F79*BA79)+(G79*BB79) -> 2421.0635 | BQ79: =B79/2 -> 68.495002 | BR79: =G79/2 -> 49.689999
A80: 39608 | B80: 136.75 | C80: 60.009998 | D80: 51.529999 | E80: 63.310001 | F80: 44.299999 | G80: 97.150002 | L80: =IF(int=Weekly,-$B$4,IF(int=Bi_Weekly,0,IF(int=Monthly,0,IF(int=Quarterly,0,IF(int=Yearly,0,IF(int=None,0,0)))))) -> 0 | M80: =(ABS((L80*$B$29)/B80)) -> 0 | N80: =(ABS((L80*$C$29)/C80)) -> 0 | O80: =(ABS((L80*$D$29)/D80)) -> 0 | P80: =(ABS((L80*$E$29)/E80)) -> 0 | Q80: =(ABS((L80*$F$29)/F80)) -> 0 | R80: =(ABS((L80*$G$29)/G80)) -> 0 | S80: =S79+M80 -> 3.0862969 | T80: =T79+N80 -> 6.6287878 | U80: =U79+O80 -> 2.5649819 | V80: =V79+P80 -> 1.8491404 | W80: =W79+Q80 -> 21.659709 | X80: =X79+R80 -> 3.3565398 | AE80: =(S80*Y80) -> 0 | AF80: =(T80*Z80) -> 0 | AG80: =(U80*AA80) -> 0 | AH80: =(V80*AB80) -> 0 | AI80: =(W80*AC80) -> 0 | AJ80: =(X80*AD80) -> 0 | AK80: =IF(AE80>0,AE80/B80,0) -> 0 | AL80: =IF(AF80>0,AF80/C80,0) -> 0 | AM80: =IF(AG80>0,AG80/D80,0) -> 0 | AN80: =IF(AH80>0,AH80/E80,0) -> 0 | AO80: =IF(AI80>0,AI80/F80,0) -> 0 | AP80: =IF(AJ80>0,AJ80/G80,0) -> 0 | AQ80: =AK80+AQ79+IF(AK80<0,AK80,0) -> 0.013230883 | AR80: =AL80+AR79+IF(AL80<0,AL80,0) -> 0.087316552 | AS80: =AM80+AS79+IF(AM80<0,AM80,0) -> 0.03219954 | AT80: =AN80+AT79+IF(AN80<0,AN80,0) -> 0.026321301 | AU80: =AO80+AU79+IF(AO80<0,AO80,0) -> 0.28399597 | AV80: =AP80+AV79+IF(AP80<0,AP80,0) -> 0.019085166 | AW80: =S80+AQ80 -> 3.0995278 | AX80: =T80+AR80 -> 6.7161044 | AY80: =U80+AS80 -> 2.5971814 | AZ80: =V80+AT80 -> 1.8754617 | BA80: =W80+AU80 -> 21.943705 | BB80: =X80+AV80 -> 3.3756249 | BC80: =(AE80+AF80+AG80+AH80+AI80+AJ80) -> 0 | BD80: =BD79+L80 -> -2500 | BE80: =(S80*B80)+(T80*C80)+(U80*D80)+(V80*E80)+(W80*F80)+(X80*G80) -> 2354.7002 | BF80: =(BE80/ABS(BD80))-1 -> -0.058119928 | BG80: =BG79+BC80 -> 26.651643 | BH80: =BE80+BG80 -> 2381.3518 | BI80: =(BH80/ABS(BD80))-1 -> -0.047459271 | BJ80: =(B80*AQ80)+(C80*AR80)+(D80*AS80)+(E80*AT80)+(F80*AU80)+(G80*AV80) -> 24.809979 | BK80: =BE80+BJ80 -> 2379.5102 | BL80: =(BK80/ABS(BD80))-1 -> -0.048195937 | BN80: =ABS(BD80) -> 2500 | BO80: =(B80*AW80)+(C80*AX80)+(D80*AY80)+(E80*AZ80)+(F80*BA80)+(G80*BB80) -> 2379.5102 | BQ80: =B80/2 -> 68.375 | BR80: =G80/2 -> 48.575001
A81: 39615 | B81: 66.599998 | C81: 58 | D81: 50 | E81: 61.900002 | F81: 43.220001 | G81: 46.900002 | L81: =IF(int=Weekly,-$B$4,IF(int=Bi_Weekly,-$B$4,IF(int=Monthly,0,IF(int=Quarterly,0,IF(int=Yearly,0,IF(int=None,0,0)))))) -> 0 | M81: =(ABS((L81*$B$29)/B81)) -> 0 | N81: =(ABS((L81*$C$29)/C81)) -> 0 | O81: =(ABS((L81*$D$29)/D81)) -> 0 | P81: =(ABS((L81*$E$29)/E81)) -> 0 | Q81: =(ABS((L81*$F$29)/F81)) -> 0 | R81: =(ABS((L81*$G$29)/G81)) -> 0 | S81: =(2*S80)+M81 -> 6.1725939 | T81: =T80+N81 -> 6.6287878 | U81: =U80+O81 -> 2.5649819 | V81: =V80+P81 -> 1.8491404 | W81: =W80+Q81 -> 21.659709 | X81: =(2*X80)+R81 -> 6.7130796 | AE81: =(S81*Y81) -> 0 | AF81: =(T81*Z81) -> 0 | AG81: =(U81*AA81) -> 0 | AH81: =(V81*AB81) -> 0 | AI81: =(W81*AC81) -> 0 | AJ81: =(X81*AD81) -> 0 | AK81: =IF(AE81>0,AE81/B81,0) -> 0 | AL81: =IF(AF81>0,AF81/C81,0) -> 0 | AM81: =IF(AG81>0,AG81/D81,0) -> 0 | AN81: =IF(AH81>0,AH81/E81,0) -> 0 | AO81: =IF(AI81>0,AI81/F81,0) -> 0 | AP81: =IF(AJ81>0,AJ81/G81,0) -> 0 | AQ81: =AK81+AQ80+IF(AK81<0,AK81,0) -> 0.013230883 | AR81: =AL81+AR80+IF(AL81<0,AL81,0) -> 0.087316552 | AS81: =AM81+AS80+IF(AM81<0,AM81,0) -> 0.03219954 | AT81: =AN81+AT80+IF(AN81<0,AN81,0) -> 0.026321301 | AU81: =AO81+AU80+IF(AO81<0,AO81,0) -> 0.28399597 | AV81: =AP81+AV80+IF(AP81<0,AP81,0) -> 0.019085166 | AW81: =S81+AQ81 -> 6.1858248 | AX81: =T81+AR81 -> 6.7161044 | AY81: =U81+AS81 -> 2.5971814 | AZ81: =V81+AT81 -> 1.8754617 | BA81: =W81+AU81 -> 21.943705 | BB81: =X81+AV81 -> 6.7321647 | BC81: =(AE81+AF81+AG81+AH81+AI81+AJ81) -> 0 | BD81: =BD80+L81 -> -2500 | BE81: =(S81*B81)+(T81*C81)+(U81*D81)+(V81*E81)+(W81*F81)+(X81*G81) -> 2289.2514 | BF81: =(BE81/ABS(BD81))-1 -> -0.084299435 | BG81: =BG80+BC81 -> 26.651643 | BH81: =BE81+BG81 -> 2315.9031 | BI81: =(BH81/ABS(BD81))-1 -> -0.073638778 | BJ81: =(B81*AQ81)+(C81*AR81)+(D81*AS81)+(E81*AT81)+(F81*AU81)+(G81*AV81) -> 22.354203 | BK81: =BE81+BJ81 -> 2311.6056 | BL81: =(BK81/ABS(BD81))-1 -> -0.075357754 | BN81: =ABS(BD81) -> 2500 | BO81: =(B81*AW81)+(C81*AX81)+(D81*AY81)+(E81*AZ81)+(F81*BA81)+(G81*BB81) -> 2311.6056 | BQ81: =B81 -> 66.599998 | BR81: =G81 -> 46.900002
A82: 39622 | B82: 64.220001 | C82: 55.849998 | D82: 48.060001 | E82: 58.82 | F82: 42.66 | G82: 46.59 | L82: =IF(int=Weekly,-$B$4,IF(int=Bi_Weekly,0,IF(int=Monthly,0,IF(int=Quarterly,0,IF(int=Yearly,0,IF(int=None,0,0)))))) -> 0 | M82: =(ABS((L82*$B$29)/B82)) -> 0 | N82: =(ABS((L82*$C$29)/C82)) -> 0 | O82: =(ABS((L82*$D$29)/D82)) -> 0 | P82: =(ABS((L82*$E$29)/E82)) -> 0 | Q82: =(ABS((L82*$F$29)/F82)) -> 0 | R82: =(ABS((L82*$G$29)/G82)) -> 0 | S82: =S81+M82 -> 6.1725939 | T82: =T81+N82 -> 6.6287878 | U82: =U81+O82 -> 2.5649819 | V82: =V81+P82 -> 1.8491404 | W82: =W81+Q82 -> 21.659709 | X82: =X81+R82 -> 6.7130796 | Y82: 0.313 | Z82: 0.416 | AE82: =(S82*Y82) -> 1.9320219 | AF82: =(T82*Z82) -> 2.7575757 | AG82: =(U82*AA82) -> 0 | AH82: =(V82*AB82) -> 0 | AI82: =(W82*AC82) -> 0 | AJ82: =(X82*AD82) -> 0 | AK82: =IF(AE82>0,AE82/B82,0) -> 0.030084426 | AL82: =IF(AF82>0,AF82/C82,0) -> 0.049374679 | AM82: =IF(AG82>0,AG82/D82,0) -> 0 | AN82: =IF(AH82>0,AH82/E82,0) -> 0 | AO82: =IF(AI82>0,AI82/F82,0) -> 0 | AP82: =IF(AJ82>0,AJ82/G82,0) -> 0 | AQ82: =AK82+AQ81+IF(AK82<0,AK82,0) -> 0.043315309 | AR82: =AL82+AR81+IF(AL82<0,AL82,0) -> 0.13669123 | AS82: =AM82+AS81+IF(AM82<0,AM82,0) -> 0.03219954 | AT82: =AN82+AT81+IF(AN82<0,AN82,0) -> 0.026321301 | AU82: =AO82+AU81+IF(AO82<0,AO82,0) -> 0.28399597 | AV82: =AP82+AV81+IF(AP82<0,AP82,0) -> 0.019085166 | AW82: =S82+AQ82 -> 6.2159092 | AX82: =T82+AR82 -> 6.765479 | AY82: =U82+AS82 -> 2.5971814 | AZ82: =V82+AT82 -> 1.8754617 | BA82: =W82+AU82 -> 21.943705 | BB82: =X82+AV82 -> 6.7321647 | BC82: =(AE82+AF82+AG82+AH82+AI82+AJ82) -> 4.6895976 | BD82: =BD81+L82 -> -2500 | BE82: =(S82*B82)+(T82*C82)+(U82*D82)+(V82*E82)+(W82*F82)+(X82*G82) -> 2235.4268 | BF82: =(BE82/ABS(BD82))-1 -> -0.10582928 | BG82: =BG81+BC82 -> 31.341241 | BH82: =BE82+BG82 -> 2266.768 | BI82: =(BH82/ABS(BD82))-1 -> -0.093292781 | BJ82: =(B82*AQ82)+(C82*AR82)+(D82*AS82)+(E82*AT82)+(F82*AU82)+(G82*AV82) -> 26.516089 | BK82: =BE82+BJ82 -> 2261.9429 | BL82: =(BK82/ABS(BD82))-1 -> -0.095222842 | BN82: =ABS(BD82) -> 2500 | BO82: =(B82*AW82)+(C82*AX82)+(D82*AY82)+(E82*AZ82)+(F82*BA82)+(G82*BB82) -> 2261.9429 | BQ82: =B82 -> 64.220001 | BR82: =G82 -> 46.59
A83: 39629 | B83: 63.009998 | C83: 55.310001 | D83: 46.650002 | E83: 56.099998 | F83: 42.029999 | G83: 44.48 | L83: =IF(int=Weekly,-$B$4,IF(int=Bi_Weekly,-$B$4,IF(int=Monthly,-$B$4,IF(int=Quarterly,0,IF(int=Yearly,0,IF(int=None,0,0)))))) -> 0 | M83: =(ABS((L83*$B$29)/B83)) -> 0 | N83: =(ABS((L83*$C$29)/C83)) -> 0 | O83: =(ABS((L83*$D$29)/D83)) -> 0 | P83: =(ABS((L83*$E$29)/E83)) -> 0 | Q83: =(ABS((L83*$F$29)/F83)) -> 0 | R83: =(ABS((L83*$G$29)/G83)) -> 0 | S83: =S82+M83 -> 6.1725939 | T83: =T82+N83 -> 6.6287878 | U83: =U82+O83 -> 2.5649819 | V83: =V82+P83 -> 1.8491404 | W83: =W82+Q83 -> 21.659709 | X83: =X82+R83 -> 6.7130796 | AE83: =(S83*Y83) -> 0 | AF83: =(T83*Z83) -> 0 | AG83: =(U83*AA83) -> 0 | AH83: =(V83*AB83) -> 0 | AI83: =(W83*AC83) -> 0 | AJ83: =(X83*AD83) -> 0 | AK83: =IF(AE83>0,AE83/B83,0) -> 0 | AL83: =IF(AF83>0,AF83/C83,0) -> 0 | AM83: =IF(AG83>0,AG83/D83,0) -> 0 | AN83: =IF(AH83>0,AH83/E83,0) -> 0 | AO83: =IF(AI83>0,AI83/F83,0) -> 0 | AP83: =IF(AJ83>0,AJ83/G83,0) -> 0 | AQ83: =AK83+AQ82+IF(AK83<0,AK83,0) -> 0.043315309 | AR83: =AL83+AR82+IF(AL83<0,AL83,0) -> 0.13669123 | AS83: =AM83+AS82+IF(AM83<0,AM83,0) -> 0.03219954 | AT83: =AN83+AT82+IF(AN83<0,AN83,0) -> 0.026321301 | AU83: =AO83+AU82+IF(AO83<0,AO83,0) -> 0.28399597 | AV83: =AP83+AV82+IF(AP83<0,AP83,0) -> 0.019085166 | AW83: =S83+AQ83 -> 6.2159092 | AX83: =T83+AR83 -> 6.765479 | AY83: =U83+AS83 -> 2.5971814 | AZ83: =V83+AT83 -> 1.8754617 | BA83: =W83+AU83 -> 21.943705 | BB83: =X83+AV83 -> 6.7321647 | BC83: =(AE83+AF83+AG83+AH83+AI83+AJ83) -> 0 | BD83: =BD82+L83 -> -2500 | BE83: =(S83*B83)+(T83*C83)+(U83*D83)+(V83*E83)+(W83*F83)+(X83*G83) -> 2187.9219 | BF83: =(BE83/ABS(BD83))-1 -> -0.12483124 | BG83: =BG82+BC83 -> 31.341241 | BH83: =BE83+BG83 -> 2219.2631 | BI83: =(BH83/ABS(BD83))-1 -> -0.11229474 | BJ83: =(B83*AQ83)+(C83*AR83)+(D83*AS83)+(E83*AT83)+(F83*AU83)+(G83*AV83) -> 26.053682 | BK83: =BE83+BJ83 -> 2213.9756 | BL83: =(BK83/ABS(BD83))-1 -> -0.11440977 | BN83: =ABS(BD83) -> 2500 | BO83: =(B83*AW83)+(C83*AX83)+(D83*AY83)+(E83*AZ83)+(F83*BA83)+(G83*BB83) -> 2213.9756 | BQ83: =B83 -> 63.009998 | BR83: =G83 -> 44.48
A84: 39636 | B84: 62.099998 | C84: 54.18 | D84: 45.880001 | E84: 56.509998 | F84: 40.98 | G84: 44.27 | L84: =IF(int=Weekly,-$B$4,IF(int=Bi_Weekly,0,IF(int=Monthly,0,IF(int=Quarterly,0,IF(int=Yearly,0,IF(int=None,0,0)))))) -> 0 | M84: =(ABS((L84*$B$29)/B84)) -> 0 | N84: =(ABS((L84*$C$29)/C84)) -> 0 | O84: =(ABS((L84*$D$29)/D84)) -> 0 | P84: =(ABS((L84*$E$29)/E84)) -> 0 | Q84: =(ABS((L84*$F$29)/F84)) -> 0 | R84: =(ABS((L84*$G$29)/G84)) -> 0 | S84: =S83+M84 -> 6.1725939 | T84: =T83+N84 -> 6.6287878 | U84: =U83+O84 -> 2.5649819 | V84: =V83+P84 -> 1.8491404 | W84: =W83+Q84 -> 21.659709 | X84: =X83+R84 -> 6.7130796 | AE84: =(S84*Y84) -> 0 | AF84: =(T84*Z84) -> 0 | AG84: =(U84*AA84) -> 0 | AH84: =(V84*AB84) -> 0 | AI84: =(W84*AC84) -> 0 | AJ84: =(X84*AD84) -> 0 | AK84: =IF(AE84>0,AE84/B84,0) -> 0 | AL84: =IF(AF84>0,AF84/C84,0) -> 0 | AM84: =IF(AG84>0,AG84/D84,0) -> 0 | AN84: =IF(AH84>0,AH84/E84,0) -> 0 | AO84: =IF(AI84>0,AI84/F84,0) -> 0 | AP84: =IF(AJ84>0,AJ84/G84,0) -> 0 | AQ84: =AK84+AQ83+IF(AK84<0,AK84,0) -> 0.043315309 | AR84: =AL84+AR83+IF(AL84<0,AL84,0) -> 0.13669123 | AS84: =AM84+AS83+IF(AM84<0,AM84,0) -> 0.03219954 | AT84: =AN84+AT83+IF(AN84<0,AN84,0) -> 0.026321301 | AU84: =AO84+AU83+IF(AO84<0,AO84,0) -> 0.28399597 | AV84: =AP84+AV83+IF(AP84<0,AP84,0) -> 0.019085166 | AW84: =S84+AQ84 -> 6.2159092 | AX84: =T84+AR84 -> 6.765479 | AY84: =U84+AS84 -> 2.5971814 | AZ84: =V84+AT84 -> 1.8754617 | BA84: =W84+AU84 -> 21.943705 | BB84: =X84+AV84 -> 6.7321647 | BC84: =(AE84+AF84+AG84+AH84+AI84+AJ84) -> 0 | BD84: =BD83+L84 -> -2500 | BE84: =(S84*B84)+(T84*C84)+(U84*D84)+(V84*E84)+(W84*F84)+(X84*G84) -> 2149.445 | BF84: =(BE84/ABS(BD84))-1 -> -0.140222 | BG84: =BG83+BC84 -> 31.341241 | BH84: =BE84+BG84 -> 2180.7862 | BI84: =(BH84/ABS(BD84))-1 -> -0.12768551 | BJ84: =(B84*AQ84)+(C84*AR84)+(D84*AS84)+(E84*AT84)+(F84*AU84)+(G84*AV84) -> 25.543598 | BK84: =BE84+BJ84 -> 2174.9886 | BL84: =(BK84/ABS(BD84))-1 -> -0.13000456 | BN84: =ABS(BD84) -> 2500 | BO84: =(B84*AW84)+(C84*AX84)+(D84*AY84)+(E84*AZ84)+(F84*BA84)+(G84*BB84) -> 2174.9886 | BQ84: =B84 -> 62.099998 | BR84: =G84 -> 44.27
A85: 39643 | B85: 63.099998 | C85: 55.549999 | D85: 47.240002 | E85: 58.400002 | F85: 41.919998 | G85: 45 | L85: =IF(int=Weekly,-$B$4,IF(int=Bi_Weekly,-$B$4,IF(int=Monthly,0,IF(int=Quarterly,0,IF(int=Yearly,0,IF(int=None,0,0)))))) -> 0 | M85: =(ABS((L85*$B$29)/B85)) -> 0 | N85: =(ABS((L85*$C$29)/C85)) -> 0 | O85: =(ABS((L85*$D$29)/D85)) -> 0 | P85: =(ABS((L85*$E$29)/E85)) -> 0 | Q85: =(ABS((L85*$F$29)/F85)) -> 0 | R85: =(ABS((L85*$G$29)/G85)) -> 0 | S85: =S84+M85 -> 6.1725939 | T85: =T84+N85 -> 6.6287878 | U85: =U84+O85 -> 2.5649819 | V85: =V84+P85 -> 1.8491404 | W85: =W84+Q85 -> 21.659709 | X85: =X84+R85 -> 6.7130796 | AE85: =(S85*Y85) -> 0 | AF85: =(T85*Z85) -> 0 | AG85: =(U85*AA85) -> 0 | AH85: =(V85*AB85) -> 0 | AI85: =(W85*AC85) -> 0 | AJ85: =(X85*AD85) -> 0 | AK85: =IF(AE85>0,AE85/B85,0) -> 0 | AL85: =IF(AF85>0,AF85/C85,0) -> 0 | AM85: =IF(AG85>0,AG85/D85,0) -> 0 | AN85: =IF(AH85>0,AH85/E85,0) -> 0 | AO85: =IF(AI85>0,AI85/F85,0) -> 0 | AP85: =IF(AJ85>0,AJ85/G85,0) -> 0 | AQ85: =AK85+AQ84+IF(AK85<0,AK85,0) -> 0.043315309 | AR85: =AL85+AR84+IF(AL85<0,AL85,0) -> 0.13669123 | AS85: =AM85+AS84+IF(AM85<0,AM85,0) -> 0.03219954 | AT85: =AN85+AT84+IF(AN85<0,AN85,0) -> 0.026321301 | AU85: =AO85+AU84+IF(AO85<0,AO85,0) -> 0.28399597 | AV85: =AP85+AV84+IF(AP85<0,AP85,0) -> 0.019085166 | AW85: =S85+AQ85 -> 6.2159092 | AX85: =T85+AR85 -> 6.765479 | AY85: =U85+AS85 -> 2.5971814 | AZ85: =V85+AT85 -> 1.8754617 | BA85: =W85+AU85 -> 21.943705 | BB85: =X85+AV85 -> 6.7321647 | BC85: =(AE85+AF85+AG85+AH85+AI85+AJ85) -> 0 | BD85: =BD84+L85 -> -2500 | BE85: =(S85*B85)+(T85*C85)+(U85*D85)+(V85*E85)+(W85*F85)+(X85*G85) -> 2196.9429 | BF85: =(BE85/ABS(BD85))-1 -> -0.12122284 | BG85: =BG84+BC85 -> 31.341241 | BH85: =BE85+BG85 -> 2228.2842 | BI85: =(BH85/ABS(BD85))-1 -> -0.10868634 | BJ85: =(B85*AQ85)+(C85*AR85)+(D85*AS85)+(E85*AT85)+(F85*AU85)+(G85*AV85) -> 26.148607 | BK85: =BE85+BJ85 -> 2223.0915 | BL85: =(BK85/ABS(BD85))-1 -> -0.11076339 | BN85: =ABS(BD85) -> 2500 | BO85: =(B85*AW85)+(C85*AX85)+(D85*AY85)+(E85*AZ85)+(F85*BA85)+(G85*BB85) -> 2223.0915 | BQ85: =B85 -> 63.099998 | BR85: =G85 -> 45
A86: 39650 | B86: 63.099998 | C86: 55.279999 | D86: 46.740002 | E86: 59.790001 | F86: 41.740002 | G86: 44.220001 | L86: =IF(int=Weekly,-$B$4,IF(int=Bi_Weekly,0,IF(int=Monthly,0,IF(int=Quarterly,0,IF(int=Yearly,0,IF(int=None,0,0)))))) -> 0 | M86: =(ABS((L86*$B$29)/B86)) -> 0 | N86: =(ABS((L86*$C$29)/C86)) -> 0 | O86: =(ABS((L86*$D$29)/D86)) -> 0 | P86: =(ABS((L86*$E$29)/E86)) -> 0 | Q86: =(ABS((L86*$F$29)/F86)) -> 0 | R86: =(ABS((L86*$G$29)/G86)) -> 0 | S86: =S85+M86 -> 6.1725939 | T86: =T85+N86 -> 6.6287878 | U86: =U85+O86 -> 2.5649819 | V86: =V85+P86 -> 1.8491404 | W86: =W85+Q86 -> 21.659709 | X86: =X85+R86 -> 6.7130796 | AE86: =(S86*Y86) -> 0 | AF86: =(T86*Z86) -> 0 | AG86: =(U86*AA86) -> 0 | AH86: =(V86*AB86) -> 0 | AI86: =(W86*AC86) -> 0 | AJ86: =(X86*AD86) -> 0 | AK86: =IF(AE86>0,AE86/B86,0) -> 0 | AL86: =IF(AF86>0,AF86/C86,0) -> 0 | AM86: =IF(AG86>0,AG86/D86,0) -> 0 | AN86: =IF(AH86>0,AH86/E86,0) -> 0 | AO86: =IF(AI86>0,AI86/F86,0) -> 0 | AP86: =IF(AJ86>0,AJ86/G86,0) -> 0 | AQ86: =AK86+AQ85+IF(AK86<0,AK86,0) -> 0.043315309 | AR86: =AL86+AR85+IF(AL86<0,AL86,0) -> 0.13669123 | AS86: =AM86+AS85+IF(AM86<0,AM86,0) -> 0.03219954 | AT86: =AN86+AT85+IF(AN86<0,AN86,0) -> 0.026321301 | AU86: =AO86+AU85+IF(AO86<0,AO86,0) -> 0.28399597 | AV86: =AP86+AV85+IF(AP86<0,AP86,0) -> 0.019085166 | AW86: =S86+AQ86 -> 6.2159092 | AX86: =T86+AR86 -> 6.765479 | AY86: =U86+AS86 -> 2.5971814 | AZ86: =V86+AT86 -> 1.8754617 | BA86: =W86+AU86 -> 21.943705 | BB86: =X86+AV86 -> 6.7321647 | BC86: =(AE86+AF86+AG86+AH86+AI86+AJ86) -> 0 | BD86: =BD85+L86 -> -2500 | BE86: =(S86*B86)+(T86*C86)+(U86*D86)+(V86*E86)+(W86*F86)+(X86*G86) -> 2187.3061 | BF86: =(BE86/ABS(BD86))-1 -> -0.12507756 | BG86: =BG85+BC86 -> 31.341241 | BH86: =BE86+BG86 -> 2218.6473 | BI86: =(BH86/ABS(BD86))-1 -> -0.11254107 | BJ86: =(B86*AQ86)+(C86*AR86)+(D86*AS86)+(E86*AT86)+(F86*AU86)+(G86*AV86) -> 26.066183 | BK86: =BE86+BJ86 -> 2213.3723 | BL86: =(BK86/ABS(BD86))-1 -> -0.11465109 | BN86: =ABS(BD86) -> 2500 | BO86: =(B86*AW86)+(C86*AX86)+(D86*AY86)+(E86*AZ86)+(F86*BA86)+(G86*BB86) -> 2213.3723 | BQ86: =B86 -> 63.099998 | BR86: =G86 -> 44.220001
A87: 39657 | B87: 63.41 | C87: 55.740002 | D87: 47.209999 | E87: 60.790001 | F87: 40.900002 | G87: 44.490002 | L87: =IF(int=Weekly,-$B$4,IF(int=Bi_Weekly,-$B$4,IF(int=Monthly,-$B$4,IF(int=Quarterly,-$B$4,IF(int=Yearly,-$B$4,IF(int=None,0,0)))))) -> -500 | M87: =(ABS((L87*$B$29)/B87)) -> 1.3877937 | N87: =(ABS((L87*$C$29)/C87)) -> 1.5787585 | O87: =(ABS((L87*$D$29)/D87)) -> 0.5930947 | P87: =(ABS((L87*$E$29)/E87)) -> 0.40302681 | Q87: =(ABS((L87*$F$29)/F87)) -> 5.0244496 | R87: =(ABS((L87*$G$29)/G87)) -> 1.4834794 | S87: =S86+M87 -> 7.5603876 | T87: =T86+N87 -> 8.2075463 | U87: =U86+O87 -> 3.1580766 | V87: =V86+P87 -> 2.2521672 | W87: =W86+Q87 -> 26.684159 | X87: =X86+R87 -> 8.1965589 | AE87: =(S87*Y87) -> 0 | AF87: =(T87*Z87) -> 0 | AG87: =(U87*AA87) -> 0 | AH87: =(V87*AB87) -> 0 | AI87: =(W87*AC87) -> 0 | AJ87: =(X87*AD87) -> 0 | AK87: =IF(AE87>0,AE87/B87,0) -> 0 | AL87: =IF(AF87>0,AF87/C87,0) -> 0 | AM87: =IF(AG87>0,AG87/D87,0) -> 0 | AN87: =IF(AH87>0,AH87/E87,0) -> 0 | AO87: =IF(AI87>0,AI87/F87,0) -> 0 | AP87: =IF(AJ87>0,AJ87/G87,0) -> 0 | AQ87: =AK87+AQ86+IF(AK87<0,AK87,0) -> 0.043315309 | AR87: =AL87+AR86+IF(AL87<0,AL87,0) -> 0.13669123 | AS87: =AM87+AS86+IF(AM87<0,AM87,0) -> 0.03219954 | AT87: =AN87+AT86+IF(AN87<0,AN87,0) -> 0.026321301 | AU87: =AO87+AU86+IF(AO87<0,AO87,0) -> 0.28399597 | AV87: =AP87+AV86+IF(AP87<0,AP87,0) -> 0.019085166 | AW87: =S87+AQ87 -> 7.6037029 | AX87: =T87+AR87 -> 8.3442375 | AY87: =U87+AS87 -> 3.1902761 | AZ87: =V87+AT87 -> 2.2784885 | BA87: =W87+AU87 -> 26.968155 | BB87: =X87+AV87 -> 8.2156441 | BC87: =(AE87+AF87+AG87+AH87+AI87+AJ87) -> 0 | BD87: =BD86+L87 -> -3000 | BE87: =(S87*B87)+(T87*C87)+(U87*D87)+(V87*E87)+(W87*F87)+(X87*G87) -> 2678.9419 | BF87: =(BE87/ABS(BD87))-1 -> -0.10701936 | BG87: =BG86+BC87 -> 31.341241 | BH87: =BE87+BG87 -> 2710.2832 | BI87: =(BH87/ABS(BD87))-1 -> -0.096572277 | BJ87: =(B87*AQ87)+(C87*AR87)+(D87*AS87)+(E87*AT87)+(F87*AU87)+(G87*AV87) -> 25.95054 | BK87: =BE87+BJ87 -> 2704.8925 | BL87: =(BK87/ABS(BD87))-1 -> -0.098369177 | BN87: =ABS(BD87) -> 3000 | BO87: =(B87*AW87)+(C87*AX87)+(D87*AY87)+(E87*AZ87)+(F87*BA87)+(G87*BB87) -> 2704.8925 | BQ87: =B87 -> 63.41 | BR87: =G87 -> 44.490002
A88: 39664 | B88: 65 | C88: 57.110001 | D88: 48.560001 | E88: 62.209999 | F88: 40.849998 | G88: 43.060001 | L88: =IF(int=Weekly,-$B$4,IF(int=Bi_Weekly,0,IF(int=Monthly,0,IF(int=Quarterly,0,IF(int=Yearly,0,IF(int=None,0,0)))))) -> 0 | M88: =(ABS((L88*$B$29)/B88)) -> 0 | N88: =(ABS((L88*$C$29)/C88)) -> 0 | O88: =(ABS((L88*$D$29)/D88)) -> 0 | P88: =(ABS((L88*$E$29)/E88)) -> 0 | Q88: =(ABS((L88*$F$29)/F88)) -> 0 | R88: =(ABS((L88*$G$29)/G88)) -> 0 | S88: =S87+M88 -> 7.5603876 | T88: =T87+N88 -> 8.2075463 | U88: =U87+O88 -> 3.1580766 | V88: =V87+P88 -> 2.2521672 | W88: =W87+Q88 -> 26.684159 | X88: =X87+R88 -> 8.1965589 | AE88: =(S88*Y88) -> 0 | AF88: =(T88*Z88) -> 0 | AG88: =(U88*AA88) -> 0 | AH88: =(V88*AB88) -> 0 | AI88: =(W88*AC88) -> 0 | AJ88: =(X88*AD88) -> 0 | AK88: =IF(AE88>0,AE88/B88,0) -> 0 | AL88: =IF(AF88>0,AF88/C88,0) -> 0 | AM88: =IF(AG88>0,AG88/D88,0) -> 0 | AN88: =IF(AH88>0,AH88/E88,0) -> 0 | AO88: =IF(AI88>0,AI88/F88,0) -> 0 | AP88: =IF(AJ88>0,AJ88/G88,0) -> 0 | AQ88: =AK88+AQ87+IF(AK88<0,AK88,0) -> 0.043315309 | AR88: =AL88+AR87+IF(AL88<0,AL88,0) -> 0.13669123 | AS88: =AM88+AS87+IF(AM88<0,AM88,0) -> 0.03219954 | AT88: =AN88+AT87+IF(AN88<0,AN88,0) -> 0.026321301 | AU88: =AO88+AU87+IF(AO88<0,AO88,0) -> 0.28399597 | AV88: =AP88+AV87+IF(AP88<0,AP88,0) -> 0.019085166 | AW88: =S88+AQ88 -> 7.6037029 | AX88: =T88+AR88 -> 8.3442375 | AY88: =U88+AS88 -> 3.1902761 | AZ88: =V88+AT88 -> 2.2784885 | BA88: =W88+AU88 -> 26.968155 | BB88: =X88+AV88 -> 8.2156441 | BC88: =(AE88+AF88+AG88+AH88+AI88+AJ88) -> 0 | BD88: =BD87+L88 -> -3000 | BE88: =(S88*B88)+(T88*C88)+(U88*D88)+(V88*E88)+(W88*F88)+(X88*G88) -> 2696.6134 | BF88: =(BE88/ABS(BD88))-1 -> -0.10112888 | BG88: =BG87+BC88 -> 31.341241 | BH88: =BE88+BG88 -> 2727.9546 | BI88: =(BH88/ABS(BD88))-1 -> -0.090681801 | BJ88: =(B88*AQ88)+(C88*AR88)+(D88*AS88)+(E88*AT88)+(F88*AU88)+(G88*AV88) -> 26.246032 | BK88: =BE88+BJ88 -> 2722.8594 | BL88: =(BK88/ABS(BD88))-1 -> -0.092380204 | BN88: =ABS(BD88) -> 3000 | BO88: =(B88*AW88)+(C88*AX88)+(D88*AY88)+(E88*AZ88)+(F88*BA88)+(G88*BB88) -> 2722.8594 | BQ88: =B88 -> 65 | BR88: =G88 -> 43.060001
A89: 39671 | B89: 65.5 | C89: 56.98 | D89: 49.130001 | E89: 63.869999 | F89: 39.5 | G89: 41.970001 | L89: =IF(int=Weekly,-$B$4,IF(int=Bi_Weekly,-$B$4,IF(int=Monthly,0,IF(int=Quarterly,0,IF(int=Yearly,0,IF(int=None,0,0)))))) -> 0 | M89: =(ABS((L89*$B$29)/B89)) -> 0 | N89: =(ABS((L89*$C$29)/C89)) -> 0 | O89: =(ABS((L89*$D$29)/D89)) -> 0 | P89: =(ABS((L89*$E$29)/E89)) -> 0 | Q89: =(ABS((L89*$F$29)/F89)) -> 0 | R89: =(ABS((L89*$G$29)/G89)) -> 0 | S89: =S88+M89 -> 7.5603876 | T89: =T88+N89 -> 8.2075463 | U89: =U88+O89 -> 3.1580766 | V89: =V88+P89 -> 2.2521672 | W89: =W88+Q89 -> 26.684159 | X89: =X88+R89 -> 8.1965589 | AE89: =(S89*Y89) -> 0 | AF89: =(T89*Z89) -> 0 | AG89: =(U89*AA89) -> 0 | AH89: =(V89*AB89) -> 0 | AI89: =(W89*AC89) -> 0 | AJ89: =(X89*AD89) -> 0 | AK89: =IF(AE89>0,AE89/B89,0) -> 0 | AL89: =IF(AF89>0,AF89/C89,0) -> 0 | AM89: =IF(AG89>0,AG89/D89,0) -> 0 | AN89: =IF(AH89>0,AH89/E89,0) -> 0 | AO89: =IF(AI89>0,AI89/F89,0) -> 0 | AP89: =IF(AJ89>0,AJ89/G89,0) -> 0 | AQ89: =AK89+AQ88+IF(AK89<0,AK89,0) -> 0.043315309 | AR89: =AL89+AR88+IF(AL89<0,AL89,0) -> 0.13669123 | AS89: =AM89+AS88+IF(AM89<0,AM89,0) -> 0.03219954 | AT89: =AN89+AT88+IF(AN89<0,AN89,0) -> 0.026321301 | AU89: =AO89+AU88+IF(AO89<0,AO89,0) -> 0.28399597 | AV89: =AP89+AV88+IF(AP89<0,AP89,0) -> 0.019085166 | AW89: =S89+AQ89 -> 7.6037029 | AX89: =T89+AR89 -> 8.3442375 | AY89: =U89+AS89 -> 3.1902761 | AZ89: =V89+AT89 -> 2.2784885 | BA89: =W89+AU89 -> 26.968155 | BB89: =X89+AV89 -> 8.2156441 | BC89: =(AE89+AF89+AG89+AH89+AI89+AJ89) -> 0 | BD89: =BD88+L89 -> -3000 | BE89: =(S89*B89)+(T89*C89)+(U89*D89)+(V89*E89)+(W89*F89)+(X89*G89) -> 2659.9075 | BF89: =(BE89/ABS(BD89))-1 -> -0.11336418 | BG89: =BG88+BC89 -> 31.341241 | BH89: =BE89+BG89 -> 2691.2487 | BI89: =(BH89/ABS(BD89))-1 -> -0.1029171 | BJ89: =(B89*AQ89)+(C89*AR89)+(D89*AS89)+(E89*AT89)+(F89*AU89)+(G89*AV89) -> 25.907769 | BK89: =BE89+BJ89 -> 2685.8152 | BL89: =(BK89/ABS(BD89))-1 -> -0.10472826 | BN89: =ABS(BD89) -> 3000 | BO89: =(B89*AW89)+(C89*AX89)+(D89*AY89)+(E89*AZ89)+(F89*BA89)+(G89*BB89) -> 2685.8152 | BQ89: =B89 -> 65.5 | BR89: =G89 -> 41.970001
A90: 39678 | B90: 65.160004 | C90: 56.580002 | D90: 48.580002 | E90: 62.400002 | F90: 39.459999 | G90: 41.84 | L90: =IF(int=Weekly,-$B$4,IF(int=Bi_Weekly,0,IF(int=Monthly,0,IF(int=Quarterly,0,IF(int=Yearly,0,IF(int=None,0,0)))))) -> 0 | M90: =(ABS((L90*$B$29)/B90)) -> 0 | N90: =(ABS((L90*$C$29)/C90)) -> 0 | O90: =(ABS((L90*$D$29)/D90)) -> 0 | P90: =(ABS((L90*$E$29)/E90)) -> 0 | Q90: =(ABS((L90*$F$29)/F90)) -> 0 | R90: =(ABS((L90*$G$29)/G90)) -> 0 | S90: =S89+M90 -> 7.5603876 | T90: =T89+N90 -> 8.2075463 | U90: =U89+O90 -> 3.1580766 | V90: =V89+P90 -> 2.2521672 | W90: =W89+Q90 -> 26.684159 | X90: =X89+R90 -> 8.1965589 | AE90: =(S90*Y90) -> 0 | AF90: =(T90*Z90) -> 0 | AG90: =(U90*AA90) -> 0 | AH90: =(V90*AB90) -> 0 | AI90: =(W90*AC90) -> 0 | AJ90: =(X90*AD90) -> 0 | AK90: =IF(AE90>0,AE90/B90,0) -> 0 | AL90: =IF(AF90>0,AF90/C90,0) -> 0 | AM90: =IF(AG90>0,AG90/D90,0) -> 0 | AN90: =IF(AH90>0,AH90/E90,0) -> 0 | AO90: =IF(AI90>0,AI90/F90,0) -> 0 | AP90: =IF(AJ90>0,AJ90/G90,0) -> 0 | AQ90: =AK90+AQ89+IF(AK90<0,AK90,0) -> 0.043315309 | AR90: =AL90+AR89+IF(AL90<0,AL90,0) -> 0.13669123 | AS90: =AM90+AS89+IF(AM90<0,AM90,0) -> 0.03219954 | AT90: =AN90+AT89+IF(AN90<0,AN90,0) -> 0.026321301 | AU90: =AO90+AU89+IF(AO90<0,AO90,0) -> 0.28399597 | AV90: =AP90+AV89+IF(AP90<0,AP90,0) -> 0.019085166 | AW90: =S90+AQ90 -> 7.6037029 | AX90: =T90+AR90 -> 8.3442375 | AY90: =U90+AS90 -> 3.1902761 | AZ90: =V90+AT90 -> 2.2784885 | BA90: =W90+AU90 -> 26.968155 | BB90: =X90+AV90 -> 8.2156441 | BC90: =(AE90+AF90+AG90+AH90+AI90+AJ90) -> 0 | BD90: =BD89+L90 -> -3000 | BE90: =(S90*B90)+(T90*C90)+(U90*D90)+(V90*E90)+(W90*F90)+(X90*G90) -> 2646.8734 | BF90: =(BE90/ABS(BD90))-1 -> -0.11770887 | BG90: =BG89+BC90 -> 31.341241 | BH90: =BE90+BG90 -> 2678.2146 | BI90: =(BH90/ABS(BD90))-1 -> -0.10726179 | BJ90: =(B90*AQ90)+(C90*AR90)+(D90*AS90)+(E90*AT90)+(F90*AU90)+(G90*AV90) -> 25.768123 | BK90: =BE90+BJ90 -> 2672.6415 | BL90: =(BK90/ABS(BD90))-1 -> -0.1091195 | BN90: =ABS(BD90) -> 3000 | BO90: =(B90*AW90)+(C90*AX90)+(D90*AY90)+(E90*AZ90)+(F90*BA90)+(G90*BB90) -> 2672.6415 | BQ90: =B90 -> 65.160004 | BR90: =G90 -> 41.84
A91: 39685 | B91: 64.620003 | C91: 56.759998 | D91: 48.779999 | E91: 62.73 | F91: 39.779999 | G91: 41.060001 | L91: =IF(int=Weekly,-$B$4,IF(int=Bi_Weekly,-$B$4,IF(int=Monthly,-$B$4,IF(int=Quarterly,0,IF(int=Yearly,0,IF(int=None,0,0)))))) -> 0 | M91: =(ABS((L91*$B$29)/B91)) -> 0 | N91: =(ABS((L91*$C$29)/C91)) -> 0 | O91: =(ABS((L91*$D$29)/D91)) -> 0 | P91: =(ABS((L91*$E$29)/E91)) -> 0 | Q91: =(ABS((L91*$F$29)/F91)) -> 0 | R91: =(ABS((L91*$G$29)/G91)) -> 0 | S91: =S90+M91 -> 7.5603876 | T91: =T90+N91 -> 8.2075463 | U91: =U90+O91 -> 3.1580766 | V91: =V90+P91 -> 2.2521672 | W91: =W90+Q91 -> 26.684159 | X91: =X90+R91 -> 8.1965589 | AE91: =(S91*Y91) -> 0 | AF91: =(T91*Z91) -> 0 | AG91: =(U91*AA91) -> 0 | AH91: =(V91*AB91) -> 0 | AI91: =(W91*AC91) -> 0 | AJ91: =(X91*AD91) -> 0 | AK91: =IF(AE91>0,AE91/B91,0) -> 0 | AL91: =IF(AF91>0,AF91/C91,0) -> 0 | AM91: =IF(AG91>0,AG91/D91,0) -> 0 | AN91: =IF(AH91>0,AH91/E91,0) -> 0 | AO91: =IF(AI91>0,AI91/F91,0) -> 0 | AP91: =IF(AJ91>0,AJ91/G91,0) -> 0 | AQ91: =AK91+AQ90+IF(AK91<0,AK91,0) -> 0.043315309 | AR91: =AL91+AR90+IF(AL91<0,AL91,0) -> 0.13669123 | AS91: =AM91+AS90+IF(AM91<0,AM91,0) -> 0.03219954 | AT91: =AN91+AT90+IF(AN91<0,AN91,0) -> 0.026321301 | AU91: =AO91+AU90+IF(AO91<0,AO91,0) -> 0.28399597 | AV91: =AP91+AV90+IF(AP91<0,AP91,0) -> 0.019085166 | AW91: =S91+AQ91 -> 7.6037029 | AX91: =T91+AR91 -> 8.3442375 | AY91: =U91+AS91 -> 3.1902761 | AZ91: =V91+AT91 -> 2.2784885 | BA91: =W91+AU91 -> 26.968155 | BB91: =X91+AV91 -> 8.2156441 | BC91: =(AE91+AF91+AG91+AH91+AI91+AJ91) -> 0 | BD91: =BD90+L91 -> -3000 | BE91: =(S91*B91)+(T91*C91)+(U91*D91)+(V91*E91)+(W91*F91)+(X91*G91) -> 2647.7885 | BF91: =(BE91/ABS(BD91))-1 -> -0.11740383 | BG91: =BG90+BC91 -> 31.341241 | BH91: =BE91+BG91 -> 2679.1298 | BI91: =(BH91/ABS(BD91))-1 -> -0.10695675 | BJ91: =(B91*AQ91)+(C91*AR91)+(D91*AS91)+(E91*AT91)+(F91*AU91)+(G91*AV91) -> 25.860455 | BK91: =BE91+BJ91 -> 2673.649 | BL91: =(BK91/ABS(BD91))-1 -> -0.10878367 | BN91: =ABS(BD91) -> 3000 | BO91: =(B91*AW91)+(C91*AX91)+(D91*AY91)+(E91*AZ91)+(F91*BA91)+(G91*BB91) -> 2673.649 | BQ91: =B91 -> 64.620003 | BR91: =G91 -> 41.060001
A92: 39693 | B92: 62.630001 | C92: 55.73 | D92: 47.73 | E92: 61.860001 | F92: 37.23 | G92: 37.900002 | L92: =IF(int=Weekly,-$B$4,IF(int=Bi_Weekly,0,IF(int=Monthly,0,IF(int=Quarterly,0,IF(int=Yearly,0,IF(int=None,0,0)))))) -> 0 | M92: =(ABS((L92*$B$29)/B92)) -> 0 | N92: =(ABS((L92*$C$29)/C92)) -> 0 | O92: =(ABS((L92*$D$29)/D92)) -> 0 | P92: =(ABS((L92*$E$29)/E92)) -> 0 | Q92: =(ABS((L92*$F$29)/F92)) -> 0 | R92: =(ABS((L92*$G$29)/G92)) -> 0 | S92: =S91+M92 -> 7.5603876 | T92: =T91+N92 -> 8.2075463 | U92: =U91+O92 -> 3.1580766 | V92: =V91+P92 -> 2.2521672 | W92: =W91+Q92 -> 26.684159 | X92: =X91+R92 -> 8.1965589 | AE92: =(S92*Y92) -> 0 | AF92: =(T92*Z92) -> 0 | AG92: =(U92*AA92) -> 0 | AH92: =(V92*AB92) -> 0 | AI92: =(W92*AC92) -> 0 | AJ92: =(X92*AD92) -> 0 | AK92: =IF(AE92>0,AE92/B92,0) -> 0 | AL92: =IF(AF92>0,AF92/C92,0) -> 0 | AM92: =IF(AG92>0,AG92/D92,0) -> 0 | AN92: =IF(AH92>0,AH92/E92,0) -> 0 | AO92: =IF(AI92>0,AI92/F92,0) -> 0 | AP92: =IF(AJ92>0,AJ92/G92,0) -> 0 | AQ92: =AK92+AQ91+IF(AK92<0,AK92,0) -> 0.043315309 | AR92: =AL92+AR91+IF(AL92<0,AL92,0) -> 0.13669123 | AS92: =AM92+AS91+IF(AM92<0,AM92,0) -> 0.03219954 | AT92: =AN92+AT91+IF(AN92<0,AN92,0) -> 0.026321301 | AU92: =AO92+AU91+IF(AO92<0,AO92,0) -> 0.28399597 | AV92: =AP92+AV91+IF(AP92<0,AP92,0) -> 0.019085166 | AW92: =S92+AQ92 -> 7.6037029 | AX92: =T92+AR92 -> 8.3442375 | AY92: =U92+AS92 -> 3.1902761 | AZ92: =V92+AT92 -> 2.2784885 | BA92: =W92+AU92 -> 26.968155 | BB92: =X92+AV92 -> 8.2156441 | BC92: =(AE92+AF92+AG92+AH92+AI92+AJ92) -> 0 | BD92: =BD91+L92 -> -3000 | BE92: =(S92*B92)+(T92*C92)+(U92*D92)+(V92*E92)+(W92*F92)+(X92*G92) -> 2525.0685 | BF92: =(BE92/ABS(BD92))-1 -> -0.15831049 | BG92: =BG91+BC92 -> 31.341241 | BH92: =BE92+BG92 -> 2556.4098 | BI92: =(BH92/ABS(BD92))-1 -> -0.14786341 | BJ92: =(B92*AQ92)+(C92*AR92)+(D92*AS92)+(E92*AT92)+(F92*AU92)+(G92*AV92) -> 24.792258 | BK92: =BE92+BJ92 -> 2549.8608 | BL92: =(BK92/ABS(BD92))-1 -> -0.15004641 | BN92: =ABS(BD92) -> 3000 | BO92: =(B92*AW92)+(C92*AX92)+(D92*AY92)+(E92*AZ92)+(F92*BA92)+(G92*BB92) -> 2549.8608 | BQ92: =B92 -> 62.630001 | BR92: =G92 -> 37.900002
A93: 39699 | B93: 63.41 | C93: 55.900002 | D93: 48.330002 | E93: 62.650002 | F93: 37.73 | G93: 37.470001 | L93: =IF(int=Weekly,-$B$4,IF(int=Bi_Weekly,-$B$4,IF(int=Monthly,0,IF(int=Quarterly,0,IF(int=Yearly,0,IF(int=None,0,0)))))) -> 0 | M93: =(ABS((L93*$B$29)/B93)) -> 0 | N93: =(ABS((L93*$C$29)/C93)) -> 0 | O93: =(ABS((L93*$D$29)/D93)) -> 0 | P93: =(ABS((L93*$E$29)/E93)) -> 0 | Q93: =(ABS((L93*$F$29)/F93)) -> 0 | R93: =(ABS((L93*$G$29)/G93)) -> 0 | S93: =S92+M93 -> 7.5603876 | T93: =T92+N93 -> 8.2075463 | U93: =U92+O93 -> 3.1580766 | V93: =V92+P93 -> 2.2521672 | W93: =W92+Q93 -> 26.684159 | X93: =X92+R93 -> 8.1965589 | AE93: =(S93*Y93) -> 0 | AF93: =(T93*Z93) -> 0 | AG93: =(U93*AA93) -> 0 | AH93: =(V93*AB93) -> 0 | AI93: =(W93*AC93) -> 0 | AJ93: =(X93*AD93) -> 0 | AK93: =IF(AE93>0,AE93/B93,0) -> 0 | AL93: =IF(AF93>0,AF93/C93,0) -> 0 | AM93: =IF(AG93>0,AG93/D93,0) -> 0 | AN93: =IF(AH93>0,AH93/E93,0) -> 0 | AO93: =IF(AI93>0,AI93/F93,0) -> 0 | AP93: =IF(AJ93>0,AJ93/G93,0) -> 0 | AQ93: =AK93+AQ92+IF(AK93<0,AK93,0) -> 0.043315309 | AR93: =AL93+AR92+IF(AL93<0,AL93,0) -> 0.13669123 | AS93: =AM93+AS92+IF(AM93<0,AM93,0) -> 0.03219954 | AT93: =AN93+AT92+IF(AN93<0,AN93,0) -> 0.026321301 | AU93: =AO93+AU92+IF(AO93<0,AO93,0) -> 0.28399597 | AV93: =AP93+AV92+IF(AP93<0,AP93,0) -> 0.019085166 | AW93: =S93+AQ93 -> 7.6037029 | AX93: =T93+AR93 -> 8.3442375 | AY93: =U93+AS93 -> 3.1902761 | AZ93: =V93+AT93 -> 2.2784885 | BA93: =W93+AU93 -> 26.968155 | BB93: =X93+AV93 -> 8.2156441 | BC93: =(AE93+AF93+AG93+AH93+AI93+AJ93) -> 0 | BD93: =BD92+L93 -> -3000 | BE93: =(S93*B93)+(T93*C93)+(U93*D93)+(V93*E93)+(W93*F93)+(X93*G93) -> 2545.8525 | BF93: =(BE93/ABS(BD93))-1 -> -0.15138249 | BG93: =BG92+BC93 -> 31.341241 | BH93: =BE93+BG93 -> 2577.1938 | BI93: =(BH93/ABS(BD93))-1 -> -0.14093541 | BJ93: =(B93*AQ93)+(C93*AR93)+(D93*AS93)+(E93*AT93)+(F93*AU93)+(G93*AV93) -> 25.023187 | BK93: =BE93+BJ93 -> 2570.8757 | BL93: =(BK93/ABS(BD93))-1 -> -0.14304143 | BN93: =ABS(BD93) -> 3000 | BO93: =(B93*AW93)+(C93*AX93)+(D93*AY93)+(E93*AZ93)+(F93*BA93)+(G93*BB93) -> 2570.8757 | BQ93: =B93 -> 63.41 | BR93: =G93 -> 37.470001
A94: 39706 | B94: 63.419998 | C94: 56.57 | D94: 48.779999 | E94: 65.019997 | F94: 38.389999 | G94: 38.970001 | L94: =IF(int=Weekly,-$B$4,IF(int=Bi_Weekly,0,IF(int=Monthly,0,IF(int=Quarterly,0,IF(int=Yearly,0,IF(int=None,0,0)))))) -> 0 | M94: =(ABS((L94*$B$29)/B94)) -> 0 | N94: =(ABS((L94*$C$29)/C94)) -> 0 | O94: =(ABS((L94*$D$29)/D94)) -> 0 | P94: =(ABS((L94*$E$29)/E94)) -> 0 | Q94: =(ABS((L94*$F$29)/F94)) -> 0 | R94: =(ABS((L94*$G$29)/G94)) -> 0 | S94: =S93+M94 -> 7.5603876 | T94: =T93+N94 -> 8.2075463 | U94: =U93+O94 -> 3.1580766 | V94: =V93+P94 -> 2.2521672 | W94: =W93+Q94 -> 26.684159 | X94: =X93+R94 -> 8.1965589 | AE94: =(S94*Y94) -> 0 | AF94: =(T94*Z94) -> 0 | AG94: =(U94*AA94) -> 0 | AH94: =(V94*AB94) -> 0 | AI94: =(W94*AC94) -> 0 | AJ94: =(X94*AD94) -> 0 | AK94: =IF(AE94>0,AE94/B94,0) -> 0 | AL94: =IF(AF94>0,AF94/C94,0) -> 0 | AM94: =IF(AG94>0,AG94/D94,0) -> 0 | AN94: =IF(AH94>0,AH94/E94,0) -> 0 | AO94: =IF(AI94>0,AI94/F94,0) -> 0 | AP94: =IF(AJ94>0,AJ94/G94,0) -> 0 | AQ94: =AK94+AQ93+IF(AK94<0,AK94,0) -> 0.043315309 | AR94: =AL94+AR93+IF(AL94<0,AL94,0) -> 0.13669123 | AS94: =AM94+AS93+IF(AM94<0,AM94,0) -> 0.03219954 | AT94: =AN94+AT93+IF(AN94<0,AN94,0) -> 0.026321301 | AU94: =AO94+AU93+IF(AO94<0,AO94,0) -> 0.28399597 | AV94: =AP94+AV93+IF(AP94<0,AP94,0) -> 0.019085166 | AW94: =S94+AQ94 -> 7.6037029 | AX94: =T94+AR94 -> 8.3442375 | AY94: =U94+AS94 -> 3.1902761 | AZ94: =V94+AT94 -> 2.2784885 | BA94: =W94+AU94 -> 26.968155 | BB94: =X94+AV94 -> 8.2156441 | BC94: =(AE94+AF94+AG94+AH94+AI94+AJ94) -> 0 | BD94: =BD93+L94 -> -3000 | BE94: =(S94*B94)+(T94*C94)+(U94*D94)+(V94*E94)+(W94*F94)+(X94*G94) -> 2588.0923 | BF94: =(BE94/ABS(BD94))-1 -> -0.13730258 | BG94: =BG93+BC94 -> 31.341241 | BH94: =BE94+BG94 -> 2619.4335 | BI94: =(BH94/ABS(BD94))-1 -> -0.1268555 | BJ94: =(B94*AQ94)+(C94*AR94)+(D94*AS94)+(E94*AT94)+(F94*AU94)+(G94*AV94) -> 25.408138 | BK94: =BE94+BJ94 -> 2613.5004 | BL94: =(BK94/ABS(BD94))-1 -> -0.1288332 | BN94: =ABS(BD94) -> 3000 | BO94: =(B94*AW94)+(C94*AX94)+(D94*AY94)+(E94*AZ94)+(F94*BA94)+(G94*BB94) -> 2613.5004 | BQ94: =B94 -> 63.419998 | BR94: =G94 -> 38.970001
A95: 39713 | B95: 60.860001 | C95: 54.43 | D95: 46.27 | E95: 61.169998 | F95: 37.400002 | G95: 36.07 | L95: =IF(int=Weekly,-$B$4,IF(int=Bi_Weekly,-$B$4,IF(int=Monthly,-$B$4,IF(int=Quarterly,0,IF(int=Yearly,0,IF(int=None,0,0)))))) -> 0 | M95: =(ABS((L95*$B$29)/B95)) -> 0 | N95: =(ABS((L95*$C$29)/C95)) -> 0 | O95: =(ABS((L95*$D$29)/D95)) -> 0 | P95: =(ABS((L95*$E$29)/E95)) -> 0 | Q95: =(ABS((L95*$F$29)/F95)) -> 0 | R95: =(ABS((L95*$G$29)/G95)) -> 0 | S95: =S94+M95 -> 7.5603876 | T95: =T94+N95 -> 8.2075463 | U95: =U94+O95 -> 3.1580766 | V95: =V94+P95 -> 2.2521672 | W95: =W94+Q95 -> 26.684159 | X95: =X94+R95 -> 8.1965589 | Y95: 0.296 | Z95: 0.457 | AE95: =(S95*Y95) -> 2.2378747 | AF95: =(T95*Z95) -> 3.7508486 | AG95: =(U95*AA95) -> 0 | AH95: =(V95*AB95) -> 0 | AI95: =(W95*AC95) -> 0 | AJ95: =(X95*AD95) -> 0 | AK95: =IF(AE95>0,AE95/B95,0) -> 0.036770863 | AL95: =IF(AF95>0,AF95/C95,0) -> 0.068911421 | AM95: =IF(AG95>0,AG95/D95,0) -> 0 | AN95: =IF(AH95>0,AH95/E95,0) -> 0 | AO95: =IF(AI95>0,AI95/F95,0) -> 0 | AP95: =IF(AJ95>0,AJ95/G95,0) -> 0 | AQ95: =AK95+AQ94+IF(AK95<0,AK95,0) -> 0.080086172 | AR95: =AL95+AR94+IF(AL95<0,AL95,0) -> 0.20560265 | AS95: =AM95+AS94+IF(AM95<0,AM95,0) -> 0.03219954 | AT95: =AN95+AT94+IF(AN95<0,AN95,0) -> 0.026321301 | AU95: =AO95+AU94+IF(AO95<0,AO95,0) -> 0.28399597 | AV95: =AP95+AV94+IF(AP95<0,AP95,0) -> 0.019085166 | AW95: =S95+AQ95 -> 7.6404738 | AX95: =T95+AR95 -> 8.4131489 | AY95: =U95+AS95 -> 3.1902761 | AZ95: =V95+AT95 -> 2.2784885 | BA95: =W95+AU95 -> 26.968155 | BB95: =X95+AV95 -> 8.2156441 | BC95: =(AE95+AF95+AG95+AH95+AI95+AJ95) -> 5.9887234 | BD95: =BD94+L95 -> -3000 | BE95: =(S95*B95)+(T95*C95)+(U95*D95)+(V95*E95)+(W95*F95)+(X95*G95) -> 2484.3887 | BF95: =(BE95/ABS(BD95))-1 -> -0.17187044 | BG95: =BG94+BC95 -> 37.329964 | BH95: =BE95+BG95 -> 2521.7186 | BI95: =(BH95/ABS(BD95))-1 -> -0.15942712 | BJ95: =(B95*AQ95)+(C95*AR95)+(D95*AS95)+(E95*AT95)+(F95*AU95)+(G95*AV95) -> 30.474795 | BK95: =BE95+BJ95 -> 2514.8635 | BL95: =(BK95/ABS(BD95))-1 -> -0.16171218 | BN95: =ABS(BD95) -> 3000 | BO95: =(B95*AW95)+(C95*AX95)+(D95*AY95)+(E95*AZ95)+(F95*BA95)+(G95*BB95) -> 2514.8635 | BQ95: =B95 -> 60.860001 | BR95: =G95 -> 36.07
A96: 39720 | B96: 54.82 | C96: 50 | D96: 41.16 | E96: 54.48 | F96: 33.400002 | G96: 31.200001 | L96: =IF(int=Weekly,-$B$4,IF(int=Bi_Weekly,0,IF(int=Monthly,0,IF(int=Quarterly,0,IF(int=Yearly,0,IF(int=None,0,0)))))) -> 0 | M96: =(ABS((L96*$B$29)/B96)) -> 0 | N96: =(ABS((L96*$C$29)/C96)) -> 0 | O96: =(ABS((L96*$D$29)/D96)) -> 0 | P96: =(ABS((L96*$E$29)/E96)) -> 0 | Q96: =(ABS((L96*$F$29)/F96)) -> 0 | R96: =(ABS((L96*$G$29)/G96)) -> 0 | S96: =S95+M96 -> 7.5603876 | T96: =T95+N96 -> 8.2075463 | U96: =U95+O96 -> 3.1580766 | V96: =V95+P96 -> 2.2521672 | W96: =W95+Q96 -> 26.684159 | X96: =X95+R96 -> 8.1965589 | AE96: =(S96*Y96) -> 0 | AF96: =(T96*Z96) -> 0 | AG96: =(U96*AA96) -> 0 | AH96: =(V96*AB96) -> 0 | AI96: =(W96*AC96) -> 0 | AJ96: =(X96*AD96) -> 0 | AK96: =IF(AE96>0,AE96/B96,0) -> 0 | AL96: =IF(AF96>0,AF96/C96,0) -> 0 | AM96: =IF(AG96>0,AG96/D96,0) -> 0 | AN96: =IF(AH96>0,AH96/E96,0) -> 0 | AO96: =IF(AI96>0,AI96/F96,0) -> 0 | AP96: =IF(AJ96>0,AJ96/G96,0) -> 0 | AQ96: =AK96+AQ95+IF(AK96<0,AK96,0) -> 0.080086172 | AR96: =AL96+AR95+IF(AL96<0,AL96,0) -> 0.20560265 | AS96: =AM96+AS95+IF(AM96<0,AM96,0) -> 0.03219954 | AT96: =AN96+AT95+IF(AN96<0,AN96,0) -> 0.026321301 | AU96: =AO96+AU95+IF(AO96<0,AO96,0) -> 0.28399597 | AV96: =AP96+AV95+IF(AP96<0,AP96,0) -> 0.019085166 | AW96: =S96+AQ96 -> 7.6404738 | AX96: =T96+AR96 -> 8.4131489 | AY96: =U96+AS96 -> 3.1902761 | AZ96: =V96+AT96 -> 2.2784885 | BA96: =W96+AU96 -> 26.968155 | BB96: =X96+AV96 -> 8.2156441 | BC96: =(AE96+AF96+AG96+AH96+AI96+AJ96) -> 0 | BD96: =BD95+L96 -> -3000 | BE96: =(S96*B96)+(T96*C96)+(U96*D96)+(V96*E96)+(W96*F96)+(X96*G96) -> 2224.5059 | BF96: =(BE96/ABS(BD96))-1 -> -0.25849805 | BG96: =BG95+BC96 -> 37.329964 | BH96: =BE96+BG96 -> 2261.8358 | BI96: =(BH96/ABS(BD96))-1 -> -0.24605472 | BJ96: =(B96*AQ96)+(C96*AR96)+(D96*AS96)+(E96*AT96)+(F96*AU96)+(G96*AV96) -> 27.510697 | BK96: =BE96+BJ96 -> 2252.0166 | BL96: =(BK96/ABS(BD96))-1 -> -0.24932781 | BN96: =ABS(BD96) -> 3000 | BO96: =(B96*AW96)+(C96*AX96)+(D96*AY96)+(E96*AZ96)+(F96*BA96)+(G96*BB96) -> 2252.0166 | BQ96: =B96 -> 54.82 | BR96: =G96 -> 31.200001
A97: 39727 | B97: 44.349998 | C97: 41.09 | D97: 33.09 | E97: 45.549999 | F97: 26.74 | G97: 24.799999 | L97: =IF(int=Weekly,-$B$4,IF(int=Bi_Weekly,-$B$4,IF(int=Monthly,0,IF(int=Quarterly,0,IF(int=Yearly,0,IF(int=None,0,0)))))) -> 0 | M97: =(ABS((L97*$B$29)/B97)) -> 0 | N97: =(ABS((L97*$C$29)/C97)) -> 0 | O97: =(ABS((L97*$D$29)/D97)) -> 0 | P97: =(ABS((L97*$E$29)/E97)) -> 0 | Q97: =(ABS((L97*$F$29)/F97)) -> 0 | R97: =(ABS((L97*$G$29)/G97)) -> 0 | S97: =S96+M97 -> 7.5603876 | T97: =T96+N97 -> 8.2075463 | U97: =U96+O97 -> 3.1580766 | V97: =V96+P97 -> 2.2521672 | W97: =W96+Q97 -> 26.684159 | X97: =X96+R97 -> 8.1965589 | AE97: =(S97*Y97) -> 0 | AF97: =(T97*Z97) -> 0 | AG97: =(U97*AA97) -> 0 | AH97: =(V97*AB97) -> 0 | AI97: =(W97*AC97) -> 0 | AJ97: =(X97*AD97) -> 0 | AK97: =IF(AE97>0,AE97/B97,0) -> 0 | AL97: =IF(AF97>0,AF97/C97,0) -> 0 | AM97: =IF(AG97>0,AG97/D97,0) -> 0 | AN97: =IF(AH97>0,AH97/E97,0) -> 0 | AO97: =IF(AI97>0,AI97/F97,0) -> 0 | AP97: =IF(AJ97>0,AJ97/G97,0) -> 0 | AQ97: =AK97+AQ96+IF(AK97<0,AK97,0) -> 0.080086172 | AR97: =AL97+AR96+IF(AL97<0,AL97,0) -> 0.20560265 | AS97: =AM97+AS96+IF(AM97<0,AM97,0) -> 0.03219954 | AT97: =AN97+AT96+IF(AN97<0,AN97,0) -> 0.026321301 | AU97: =AO97+AU96+IF(AO97<0,AO97,0) -> 0.28399597 | AV97: =AP97+AV96+IF(AP97<0,AP97,0) -> 0.019085166 | AW97: =S97+AQ97 -> 7.6404738 | AX97: =T97+AR97 -> 8.4131489 | AY97: =U97+AS97 -> 3.1902761 | AZ97: =V97+AT97 -> 2.2784885 | BA97: =W97+AU97 -> 26.968155 | BB97: =X97+AV97 -> 8.2156441 | BC97: =(AE97+AF97+AG97+AH97+AI97+AJ97) -> 0 | BD97: =BD96+L97 -> -3000 | BE97: =(S97*B97)+(T97*C97)+(U97*D97)+(V97*E97)+(W97*F97)+(X97*G97) -> 1796.4473 | BF97: =(BE97/ABS(BD97))-1 -> -0.40118424 | BG97: =BG96+BC97 -> 37.329964 | BH97: =BE97+BG97 -> 1833.7772 | BI97: =(BH97/ABS(BD97))-1 -> -0.38874092 | BJ97: =(B97*AQ97)+(C97*AR97)+(D97*AS97)+(E97*AT97)+(F97*AU97)+(G97*AV97) -> 22.331817 | BK97: =BE97+BJ97 -> 1818.7791 | BL97: =(BK97/ABS(BD97))-1 -> -0.3937403 | BN97: =ABS(BD97) -> 3000 | BO97: =(B97*AW97)+(C97*AX97)+(D97*AY97)+(E97*AZ97)+(F97*BA97)+(G97*BB97) -> 1818.7791 | BQ97: =B97 -> 44.349998 | BR97: =G97 -> 24.799999
A98: 39734 | B98: 46.599998 | C98: 42.27 | D98: 34.139999 | E98: 45.509998 | F98: 27.799999 | G98: 25.1 | L98: =IF(int=Weekly,-$B$4,IF(int=Bi_Weekly,0,IF(int=Monthly,0,IF(int=Quarterly,0,IF(int=Yearly,0,IF(int=None,0,0)))))) -> 0 | M98: =(ABS((L98*$B$29)/B98)) -> 0 | N98: =(ABS((L98*$C$29)/C98)) -> 0 | O98: =(ABS((L98*$D$29)/D98)) -> 0 | P98: =(ABS((L98*$E$29)/E98)) -> 0 | Q98: =(ABS((L98*$F$29)/F98)) -> 0 | R98: =(ABS((L98*$G$29)/G98)) -> 0 | S98: =S97+M98 -> 7.5603876 | T98: =T97+N98 -> 8.2075463 | U98: =U97+O98 -> 3.1580766 | V98: =V97+P98 -> 2.2521672 | W98: =W97+Q98 -> 26.684159 | X98: =X97+R98 -> 8.1965589 | AE98: =(S98*Y98) -> 0 | AF98: =(T98*Z98) -> 0 | AG98: =(U98*AA98) -> 0 | AH98: =(V98*AB98) -> 0 | AI98: =(W98*AC98) -> 0 | AJ98: =(X98*AD98) -> 0 | AK98: =IF(AE98>0,AE98/B98,0) -> 0 | AL98: =IF(AF98>0,AF98/C98,0) -> 0 | AM98: =IF(AG98>0,AG98/D98,0) -> 0 | AN98: =IF(AH98>0,AH98/E98,0) -> 0 | AO98: =IF(AI98>0,AI98/F98,0) -> 0 | AP98: =IF(AJ98>0,AJ98/G98,0) -> 0 | AQ98: =AK98+AQ97+IF(AK98<0,AK98,0) -> 0.080086172 | AR98: =AL98+AR97+IF(AL98<0,AL98,0) -> 0.20560265 | AS98: =AM98+AS97+IF(AM98<0,AM98,0) -> 0.03219954 | AT98: =AN98+AT97+IF(AN98<0,AN98,0) -> 0.026321301 | AU98: =AO98+AU97+IF(AO98<0,AO98,0) -> 0.28399597 | AV98: =AP98+AV97+IF(AP98<0,AP98,0) -> 0.019085166 | AW98: =S98+AQ98 -> 7.6404738 | AX98: =T98+AR98 -> 8.4131489 | AY98: =U98+AS98 -> 3.1902761 | AZ98: =V98+AT98 -> 2.2784885 | BA98: =W98+AU98 -> 26.968155 | BB98: =X98+AV98 -> 8.2156441 | BC98: =(AE98+AF98+AG98+AH98+AI98+AJ98) -> 0 | BD98: =BD97+L98 -> -3000 | BE98: =(S98*B98)+(T98*C98)+(U98*D98)+(V98*E98)+(W98*F98)+(X98*G98) -> 1857.1131 | BF98: =(BE98/ABS(BD98))-1 -> -0.3809623 | BG98: =BG97+BC98 -> 37.329964 | BH98: =BE98+BG98 -> 1894.4431 | BI98: =(BH98/ABS(BD98))-1 -> -0.36851898 | BJ98: =(B98*AQ98)+(C98*AR98)+(D98*AS98)+(E98*AT98)+(F98*AU98)+(G98*AV98) -> 23.09414 | BK98: =BE98+BJ98 -> 1880.2072 | BL98: =(BK98/ABS(BD98))-1 -> -0.37326425 | BN98: =ABS(BD98) -> 3000 | BO98: =(B98*AW98)+(C98*AX98)+(D98*AY98)+(E98*AZ98)+(F98*BA98)+(G98*BB98) -> 1880.2072 | BQ98: =B98 -> 46.599998 | BR98: =G98 -> 25.1
A99: 39741 | B99: 43.240002 | C99: 39.82 | D99: 31.01 | E99: 41.029999 | F99: 24.75 | G99: 20.450001 | L99: =IF(int=Weekly,-$B$4,IF(int=Bi_Weekly,-$B$4,IF(int=Monthly,-$B$4,IF(int=Quarterly,0,IF(int=Yearly,0,IF(int=None,0,0)))))) -> 0 | M99: =(ABS((L99*$B$29)/B99)) -> 0 | N99: =(ABS((L99*$C$29)/C99)) -> 0 | O99: =(ABS((L99*$D$29)/D99)) -> 0 | P99: =(ABS((L99*$E$29)/E99)) -> 0 | Q99: =(ABS((L99*$F$29)/F99)) -> 0 | R99: =(ABS((L99*$G$29)/G99)) -> 0 | S99: =S98+M99 -> 7.5603876 | T99: =T98+N99 -> 8.2075463 | U99: =U98+O99 -> 3.1580766 | V99: =V98+P99 -> 2.2521672 | W99: =W98+Q99 -> 26.684159 | X99: =X98+R99 -> 8.1965589 | AE99: =(S99*Y99) -> 0 | AF99: =(T99*Z99) -> 0 | AG99: =(U99*AA99) -> 0 | AH99: =(V99*AB99) -> 0 | AI99: =(W99*AC99) -> 0 | AJ99: =(X99*AD99) -> 0 | AK99: =IF(AE99>0,AE99/B99,0) -> 0 | AL99: =IF(AF99>0,AF99/C99,0) -> 0 | AM99: =IF(AG99>0,AG99/D99,0) -> 0 | AN99: =IF(AH99>0,AH99/E99,0) -> 0 | AO99: =IF(AI99>0,AI99/F99,0) -> 0 | AP99: =IF(AJ99>0,AJ99/G99,0) -> 0 | AQ99: =AK99+AQ98+IF(AK99<0,AK99,0) -> 0.080086172 | AR99: =AL99+AR98+IF(AL99<0,AL99,0) -> 0.20560265 | AS99: =AM99+AS98+IF(AM99<0,AM99,0) -> 0.03219954 | AT99: =AN99+AT98+IF(AN99<0,AN99,0) -> 0.026321301 | AU99: =AO99+AU98+IF(AO99<0,AO99,0) -> 0.28399597 | AV99: =AP99+AV98+IF(AP99<0,AP99,0) -> 0.019085166 | AW99: =S99+AQ99 -> 7.6404738 | AX99: =T99+AR99 -> 8.4131489 | AY99: =U99+AS99 -> 3.1902761 | AZ99: =V99+AT99 -> 2.2784885 | BA99: =W99+AU99 -> 26.968155 | BB99: =X99+AV99 -> 8.2156441 | BC99: =(AE99+AF99+AG99+AH99+AI99+AJ99) -> 0 | BD99: =BD98+L99 -> -3000 | BE99: =(S99*B99)+(T99*C99)+(U99*D99)+(V99*E99)+(W99*F99)+(X99*G99) -> 1672.1266 | BF99: =(BE99/ABS(BD99))-1 -> -0.44262446 | BG99: =BG98+BC99 -> 37.329964 | BH99: =BE99+BG99 -> 1709.4566 | BI99: =(BH99/ABS(BD99))-1 -> -0.43018114 | BJ99: =(B99*AQ99)+(C99*AR99)+(D99*AS99)+(E99*AT99)+(F99*AU99)+(G99*AV99) -> 21.147687 | BK99: =BE99+BJ99 -> 1693.2743 | BL99: =(BK99/ABS(BD99))-1 -> -0.43557524 | BN99: =ABS(BD99) -> 3000 | BO99: =(B99*AW99)+(C99*AX99)+(D99*AY99)+(E99*AZ99)+(F99*BA99)+(G99*BB99) -> 1693.2743 | BQ99: =B99 -> 43.240002 | BR99: =G99 -> 20.450001
A100: 39748 | B100: 48.16 | C100: 43.91 | D100: 34.490002 | E100: 46.349998 | F100: 27.940001 | G100: 25.209999 | L100: =IF(int=Weekly,-$B$4,IF(int=Bi_Weekly,0,IF(int=Monthly,0,IF(int=Quarterly,-$B$4,IF(int=Yearly,0,IF(int=None,0,0)))))) -> -500 | M100: =(ABS((L100*$B$29)/B100)) -> 1.8272425 | N100: =(ABS((L100*$C$29)/C100)) -> 2.0040993 | O100: =(ABS((L100*$D$29)/D100)) -> 0.81182947 | P100: =(ABS((L100*$E$29)/E100)) -> 0.52858686 | Q100: =(ABS((L100*$F$29)/F100)) -> 7.3550463 | R100: =(ABS((L100*$G$29)/G100)) -> 2.6180088 | S100: =S99+M100 -> 9.3876301 | T100: =T99+N100 -> 10.211646 | U100: =U99+O100 -> 3.969906 | V100: =V99+P100 -> 2.780754 | W100: =W99+Q100 -> 34.039205 | X100: =X99+R100 -> 10.814568 | AE100: =(S100*Y100) -> 0 | AF100: =(T100*Z100) -> 0 | AG100: =(U100*AA100) -> 0 | AH100: =(V100*AB100) -> 0 | AI100: =(W100*AC100) -> 0 | AJ100: =(X100*AD100) -> 0 | AK100: =IF(AE100>0,AE100/B100,0) -> 0 | AL100: =IF(AF100>0,AF100/C100,0) -> 0 | AM100: =IF(AG100>0,AG100/D100,0) -> 0 | AN100: =IF(AH100>0,AH100/E100,0) -> 0 | AO100: =IF(AI100>0,AI100/F100,0) -> 0 | AP100: =IF(AJ100>0,AJ100/G100,0) -> 0 | AQ100: =AK100+AQ99+IF(AK100<0,AK100,0) -> 0.080086172 | AR100: =AL100+AR99+IF(AL100<0,AL100,0) -> 0.20560265 | AS100: =AM100+AS99+IF(AM100<0,AM100,0) -> 0.03219954 | AT100: =AN100+AT99+IF(AN100<0,AN100,0) -> 0.026321301 | AU100: =AO100+AU99+IF(AO100<0,AO100,0) -> 0.28399597 | AV100: =AP100+AV99+IF(AP100<0,AP100,0) -> 0.019085166 | AW100: =S100+AQ100 -> 9.4677163 | AX100: =T100+AR100 -> 10.417248 | AY100: =U100+AS100 -> 4.0021056 | AZ100: =V100+AT100 -> 2.8070753 | BA100: =W100+AU100 -> 34.323201 | BB100: =X100+AV100 -> 10.833653 | BC100: =(AE100+AF100+AG100+AH100+AI100+AJ100) -> 0 | BD100: =BD99+L100 -> -3500 | BE100: =(S100*B100)+(T100*C100)+(U100*D100)+(V100*E100)+(W100*F100)+(X100*G100) -> 2390.0023 | BF100: =(BE100/ABS(BD100))-1 -> -0.3171422 | BG100: =BG99+BC100 -> 37.329964 | BH100: =BE100+BG100 -> 2427.3323 | BI100: =(BH100/ABS(BD100))-1 -> -0.3064765 | BJ100: =(B100*AQ100)+(C100*AR100)+(D100*AS100)+(E100*AT100)+(F100*AU100)+(G100*AV100) -> 23.631502 | BK100: =BE100+BJ100 -> 2413.6338 | BL100: =(BK100/ABS(BD100))-1 -> -0.31039034 | BN100: =ABS(BD100) -> 3500 | BO100: =(B100*AW100)+(C100*AX100)+(D100*AY100)+(E100*AZ100)+(F100*BA100)+(G100*BB100) -> 2413.6338 | BQ100: =B100 -> 48.16 | BR100: =G100 -> 25.209999
A101: 39755 | B101: 46.110001 | C101: 42.150002 | D101: 33.240002 | E101: 43.939999 | F101: 27.959999 | G101: 24.870001 | L101: =IF(int=Weekly,-$B$4,IF(int=Bi_Weekly,-$B$4,IF(int=Monthly,0,IF(int=Quarterly,0,IF(int=Yearly,0,IF(int=None,0,0)))))) -> 0 | M101: =(ABS((L101*$B$29)/B101)) -> 0 | N101: =(ABS((L101*$C$29)/C101)) -> 0 | O101: =(ABS((L101*$D$29)/D101)) -> 0 | P101: =(ABS((L101*$E$29)/E101)) -> 0 | Q101: =(ABS((L101*$F$29)/F101)) -> 0 | R101: =(ABS((L101*$G$29)/G101)) -> 0 | S101: =S100+M101 -> 9.3876301 | T101: =T100+N101 -> 10.211646 | U101: =U100+O101 -> 3.969906 | V101: =V100+P101 -> 2.780754 | W101: =W100+Q101 -> 34.039205 | X101: =X100+R101 -> 10.814568 | AE101: =(S101*Y101) -> 0 | AF101: =(T101*Z101) -> 0 | AG101: =(U101*AA101) -> 0 | AH101: =(V101*AB101) -> 0 | AI101: =(W101*AC101) -> 0 | AJ101: =(X101*AD101) -> 0 | AK101: =IF(AE101>0,AE101/B101,0) -> 0 | AL101: =IF(AF101>0,AF101/C101,0) -> 0 | AM101: =IF(AG101>0,AG101/D101,0) -> 0 | AN101: =IF(AH101>0,AH101/E101,0) -> 0 | AO101: =IF(AI101>0,AI101/F101,0) -> 0 | AP101: =IF(AJ101>0,AJ101/G101,0) -> 0 | AQ101: =AK101+AQ100+IF(AK101<0,AK101,0) -> 0.080086172 | AR101: =AL101+AR100+IF(AL101<0,AL101,0) -> 0.20560265 | AS101: =AM101+AS100+IF(AM101<0,AM101,0) -> 0.03219954 | AT101: =AN101+AT100+IF(AN101<0,AN101,0) -> 0.026321301 | AU101: =AO101+AU100+IF(AO101<0,AO101,0) -> 0.28399597 | AV101: =AP101+AV100+IF(AP101<0,AP101,0) -> 0.019085166 | AW101: =S101+AQ101 -> 9.4677163 | AX101: =T101+AR101 -> 10.417248 | AY101: =U101+AS101 -> 4.0021056 | AZ101: =V101+AT101 -> 2.8070753 | BA101: =W101+AU101 -> 34.323201 | BB101: =X101+AV101 -> 10.833653 | BC101: =(AE101+AF101+AG101+AH101+AI101+AJ101) -> 0 | BD101: =BD100+L101 -> -3500 | BE101: =(S101*B101)+(T101*C101)+(U101*D101)+(V101*E101)+(W101*F101)+(X101*G101) -> 2338.125 | BF101: =(BE101/ABS(BD101))-1 -> -0.33196429 | BG101: =BG100+BC101 -> 37.329964 | BH101: =BE101+BG101 -> 2375.4549 | BI101: =(BH101/ABS(BD101))-1 -> -0.32129859 | BJ101: =(B101*AQ101)+(C101*AR101)+(D101*AS101)+(E101*AT101)+(F101*AU101)+(G101*AV101) -> 23.000972 | BK101: =BE101+BJ101 -> 2361.1259 | BL101: =(BK101/ABS(BD101))-1 -> -0.32539259 | BN101: =ABS(BD101) -> 3500 | BO101: =(B101*AW101)+(C101*AX101)+(D101*AY101)+(E101*AZ101)+(F101*BA101)+(G101*BB101) -> 2361.1259 | BQ101: =B101 -> 46.110001 | BR101: =G101 -> 24.870001
A102: 39762 | B102: 43.150002 | C102: 39.580002 | D102: 30.799999 | E102: 39.98 | F102: 25.68 | G102: 22.469999 | L102: =IF(int=Weekly,-$B$4,IF(int=Bi_Weekly,0,IF(int=Monthly,0,IF(int=Quarterly,0,IF(int=Yearly,0,IF(int=None,0,0)))))) -> 0 | M102: =(ABS((L102*$B$29)/B102)) -> 0 | N102: =(ABS((L102*$C$29)/C102)) -> 0 | O102: =(ABS((L102*$D$29)/D102)) -> 0 | P102: =(ABS((L102*$E$29)/E102)) -> 0 | Q102: =(ABS((L102*$F$29)/F102)) -> 0 | R102: =(ABS((L102*$G$29)/G102)) -> 0 | S102: =S101+M102 -> 9.3876301 | T102: =T101+N102 -> 10.211646 | U102: =U101+O102 -> 3.969906 | V102: =V101+P102 -> 2.780754 | W102: =W101+Q102 -> 34.039205 | X102: =X101+R102 -> 10.814568 | AE102: =(S102*Y102) -> 0 | AF102: =(T102*Z102) -> 0 | AG102: =(U102*AA102) -> 0 | AH102: =(V102*AB102) -> 0 | AI102: =(W102*AC102) -> 0 | AJ102: =(X102*AD102) -> 0 | AK102: =IF(AE102>0,AE102/B102,0) -> 0 | AL102: =IF(AF102>0,AF102/C102,0) -> 0 | AM102: =IF(AG102>0,AG102/D102,0) -> 0 | AN102: =IF(AH102>0,AH102/E102,0) -> 0 | AO102: =IF(AI102>0,AI102/F102,0) -> 0 | AP102: =IF(AJ102>0,AJ102/G102,0) -> 0 | AQ102: =AK102+AQ101+IF(AK102<0,AK102,0) -> 0.080086172 | AR102: =AL102+AR101+IF(AL102<0,AL102,0) -> 0.20560265 | AS102: =AM102+AS101+IF(AM102<0,AM102,0) -> 0.03219954 | AT102: =AN102+AT101+IF(AN102<0,AN102,0) -> 0.026321301 | AU102: =AO102+AU101+IF(AO102<0,AO102,0) -> 0.28399597 | AV102: =AP102+AV101+IF(AP102<0,AP102,0) -> 0.019085166 | AW102: =S102+AQ102 -> 9.4677163 | AX102: =T102+AR102 -> 10.417248 | AY102: =U102+AS102 -> 4.0021056 | AZ102: =V102+AT102 -> 2.8070753 | BA102: =W102+AU102 -> 34.323201 | BB102: =X102+AV102 -> 10.833653 | BC102: =(AE102+AF102+AG102+AH102+AI102+AJ102) -> 0 | BD102: =BD101+L102 -> -3500 | BE102: =(S102*B102)+(T102*C102)+(U102*D102)+(V102*E102)+(W102*F102)+(X102*G102) -> 2159.831 | BF102: =(BE102/ABS(BD102))-1 -> -0.38290544 | BG102: =BG101+BC102 -> 37.329964 | BH102: =BE102+BG102 -> 2197.1609 | BI102: =(BH102/ABS(BD102))-1 -> -0.37223973 | BJ102: =(B102*AQ102)+(C102*AR102)+(D102*AS102)+(E102*AT102)+(F102*AU102)+(G102*AV102) -> 21.359404 | BK102: =BE102+BJ102 -> 2181.1904 | BL102: =(BK102/ABS(BD102))-1 -> -0.37680275 | BN102: =ABS(BD102) -> 3500 | BO102: =(B102*AW102)+(C102*AX102)+(D102*AY102)+(E102*AZ102)+(F102*BA102)+(G102*BB102) -> 2181.1904 | BQ102: =B102 -> 43.150002 | BR102: =G102 -> 22.469999
A103: 39769 | B103: 39.290001 | C103: 36.009998 | D103: 27.23 | E103: 35.52 | F103: 23.719999 | G103: 21 | L103: =IF(int=Weekly,-$B$4,IF(int=Bi_Weekly,-$B$4,IF(int=Monthly,-$B$4,IF(int=Quarterly,0,IF(int=Yearly,0,IF(int=None,0,0)))))) -> 0 | M103: =(ABS((L103*$B$29)/B103)) -> 0 | N103: =(ABS((L103*$C$29)/C103)) -> 0 | O103: =(ABS((L103*$D$29)/D103)) -> 0 | P103: =(ABS((L103*$E$29)/E103)) -> 0 | Q103: =(ABS((L103*$F$29)/F103)) -> 0 | R103: =(ABS((L103*$G$29)/G103)) -> 0 | S103: =S102+M103 -> 9.3876301 | T103: =T102+N103 -> 10.211646 | U103: =U102+O103 -> 3.969906 | V103: =V102+P103 -> 2.780754 | W103: =W102+Q103 -> 34.039205 | X103: =X102+R103 -> 10.814568 | AE103: =(S103*Y103) -> 0 | AF103: =(T103*Z103) -> 0 | AG103: =(U103*AA103) -> 0 | AH103: =(V103*AB103) -> 0 | AI103: =(W103*AC103) -> 0 | AJ103: =(X103*AD103) -> 0 | AK103: =IF(AE103>0,AE103/B103,0) -> 0 | AL103: =IF(AF103>0,AF103/C103,0) -> 0 | AM103: =IF(AG103>0,AG103/D103,0) -> 0 | AN103: =IF(AH103>0,AH103/E103,0) -> 0 | AO103: =IF(AI103>0,AI103/F103,0) -> 0 | AP103: =IF(AJ103>0,AJ103/G103,0) -> 0 | AQ103: =AK103+AQ102+IF(AK103<0,AK103,0) -> 0.080086172 | AR103: =AL103+AR102+IF(AL103<0,AL103,0) -> 0.20560265 | AS103: =AM103+AS102+IF(AM103<0,AM103,0) -> 0.03219954 | AT103: =AN103+AT102+IF(AN103<0,AN103,0) -> 0.026321301 | AU103: =AO103+AU102+IF(AO103<0,AO103,0) -> 0.28399597 | AV103: =AP103+AV102+IF(AP103<0,AP103,0) -> 0.019085166 | AW103: =S103+AQ103 -> 9.4677163 | AX103: =T103+AR103 -> 10.417248 | AY103: =U103+AS103 -> 4.0021056 | AZ103: =V103+AT103 -> 2.8070753 | BA103: =W103+AU103 -> 34.323201 | BB103: =X103+AV103 -> 10.833653 | BC103: =(AE103+AF103+AG103+AH103+AI103+AJ103) -> 0 | BD103: =BD102+L103 -> -3500 | BE103: =(S103*B103)+(T103*C103)+(U103*D103)+(V103*E103)+(W103*F103)+(X103*G103) -> 1977.9501 | BF103: =(BE103/ABS(BD103))-1 -> -0.4348714 | BG103: =BG102+BC103 -> 37.329964 | BH103: =BE103+BG103 -> 2015.2801 | BI103: =(BH103/ABS(BD103))-1 -> -0.4242057 | BJ103: =(B103*AQ103)+(C103*AR103)+(D103*AS103)+(E103*AT103)+(F103*AU103)+(G103*AV103) -> 19.499236 | BK103: =BE103+BJ103 -> 1997.4493 | BL103: =(BK103/ABS(BD103))-1 -> -0.42930019 | BN103: =ABS(BD103) -> 3500 | BO103: =(B103*AW103)+(C103*AX103)+(D103*AY103)+(E103*AZ103)+(F103*BA103)+(G103*BB103) -> 1997.4493 | BQ103: =B103 -> 39.290001 | BR103: =G103 -> 21
A104: 39776 | B104: 44.299999 | C104: 40.990002 | D104: 31.83 | E104: 41.919998 | F104: 26.09 | G104: 23.030001 | L104: =IF(int=Weekly,-$B$4,IF(int=Bi_Weekly,0,IF(int=Monthly,0,IF(int=Quarterly,0,IF(int=Yearly,0,IF(int=None,0,0)))))) -> 0 | M104: =(ABS((L104*$B$29)/B104)) -> 0 | N104: =(ABS((L104*$C$29)/C104)) -> 0 | O104: =(ABS((L104*$D$29)/D104)) -> 0 | P104: =(ABS((L104*$E$29)/E104)) -> 0 | Q104: =(ABS((L104*$F$29)/F104)) -> 0 | R104: =(ABS((L104*$G$29)/G104)) -> 0 | S104: =S103+M104 -> 9.3876301 | T104: =T103+N104 -> 10.211646 | U104: =U103+O104 -> 3.969906 | V104: =V103+P104 -> 2.780754 | W104: =W103+Q104 -> 34.039205 | X104: =X103+R104 -> 10.814568 | AE104: =(S104*Y104) -> 0 | AF104: =(T104*Z104) -> 0 | AG104: =(U104*AA104) -> 0 | AH104: =(V104*AB104) -> 0 | AI104: =(W104*AC104) -> 0 | AJ104: =(X104*AD104) -> 0 | AK104: =IF(AE104>0,AE104/B104,0) -> 0 | AL104: =IF(AF104>0,AF104/C104,0) -> 0 | AM104: =IF(AG104>0,AG104/D104,0) -> 0 | AN104: =IF(AH104>0,AH104/E104,0) -> 0 | AO104: =IF(AI104>0,AI104/F104,0) -> 0 | AP104: =IF(AJ104>0,AJ104/G104,0) -> 0 | AQ104: =AK104+AQ103+IF(AK104<0,AK104,0) -> 0.080086172 | AR104: =AL104+AR103+IF(AL104<0,AL104,0) -> 0.20560265 | AS104: =AM104+AS103+IF(AM104<0,AM104,0) -> 0.03219954 | AT104: =AN104+AT103+IF(AN104<0,AN104,0) -> 0.026321301 | AU104: =AO104+AU103+IF(AO104<0,AO104,0) -> 0.28399597 | AV104: =AP104+AV103+IF(AP104<0,AP104,0) -> 0.019085166 | AW104: =S104+AQ104 -> 9.4677163 | AX104: =T104+AR104 -> 10.417248 | AY104: =U104+AS104 -> 4.0021056 | AZ104: =V104+AT104 -> 2.8070753 | BA104: =W104+AU104 -> 34.323201 | BB104: =X104+AV104 -> 10.833653 | BC104: =(AE104+AF104+AG104+AH104+AI104+AJ104) -> 0 | BD104: =BD103+L104 -> -3500 | BE104: =(S104*B104)+(T104*C104)+(U104*D104)+(V104*E104)+(W104*F104)+(X104*G104) -> 2214.5211 | BF104: =(BE104/ABS(BD104))-1 -> -0.3672797 | BG104: =BG103+BC104 -> 37.329964 | BH104: =BE104+BG104 -> 2251.851 | BI104: =(BH104/ABS(BD104))-1 -> -0.35661399 | BJ104: =(B104*AQ104)+(C104*AR104)+(D104*AS104)+(E104*AT104)+(F104*AU104)+(G104*AV104) -> 21.952757 | BK104: =BE104+BJ104 -> 2236.4738 | BL104: =(BK104/ABS(BD104))-1 -> -0.36100748 | BN104: =ABS(BD104) -> 3500 | BO104: =(B104*AW104)+(C104*AX104)+(D104*AY104)+(E104*AZ104)+(F104*BA104)+(G104*BB104) -> 2236.4738 | BQ104: =B104 -> 44.299999 | BR104: =G104 -> 23.030001
A105: 39783 | B105: 43.209999 | C105: 40.369999 | D105: 31.139999 | E105: 40.549999 | F105: 25.26 | G105: 22.58 | L105: =IF(int=Weekly,-$B$4,IF(int=Bi_Weekly,-$B$4,IF(int=Monthly,0,IF(int=Quarterly,0,IF(int=Yearly,0,IF(int=None,0,0)))))) -> 0 | M105: =(ABS((L105*$B$29)/B105)) -> 0 | N105: =(ABS((L105*$C$29)/C105)) -> 0 | O105: =(ABS((L105*$D$29)/D105)) -> 0 | P105: =(ABS((L105*$E$29)/E105)) -> 0 | Q105: =(ABS((L105*$F$29)/F105)) -> 0 | R105: =(ABS((L105*$G$29)/G105)) -> 0 | S105: =S104+M105 -> 9.3876301 | T105: =T104+N105 -> 10.211646 | U105: =U104+O105 -> 3.969906 | V105: =V104+P105 -> 2.780754 | W105: =W104+Q105 -> 34.039205 | X105: =X104+R105 -> 10.814568 | AE105: =(S105*Y105) -> 0 | AF105: =(T105*Z105) -> 0 | AG105: =(U105*AA105) -> 0 | AH105: =(V105*AB105) -> 0 | AI105: =(W105*AC105) -> 0 | AJ105: =(X105*AD105) -> 0 | AK105: =IF(AE105>0,AE105/B105,0) -> 0 | AL105: =IF(AF105>0,AF105/C105,0) -> 0 | AM105: =IF(AG105>0,AG105/D105,0) -> 0 | AN105: =IF(AH105>0,AH105/E105,0) -> 0 | AO105: =IF(AI105>0,AI105/F105,0) -> 0 | AP105: =IF(AJ105>0,AJ105/G105,0) -> 0 | AQ105: =AK105+AQ104+IF(AK105<0,AK105,0) -> 0.080086172 | AR105: =AL105+AR104+IF(AL105<0,AL105,0) -> 0.20560265 | AS105: =AM105+AS104+IF(AM105<0,AM105,0) -> 0.03219954 | AT105: =AN105+AT104+IF(AN105<0,AN105,0) -> 0.026321301 | AU105: =AO105+AU104+IF(AO105<0,AO105,0) -> 0.28399597 | AV105: =AP105+AV104+IF(AP105<0,AP105,0) -> 0.019085166 | AW105: =S105+AQ105 -> 9.4677163 | AX105: =T105+AR105 -> 10.417248 | AY105: =U105+AS105 -> 4.0021056 | AZ105: =V105+AT105 -> 2.8070753 | BA105: =W105+AU105 -> 34.323201 | BB105: =X105+AV105 -> 10.833653 | BC105: =(AE105+AF105+AG105+AH105+AI105+AJ105) -> 0 | BD105: =BD104+L105 -> -3500 | BE105: =(S105*B105)+(T105*C105)+(U105*D105)+(V105*E105)+(W105*F105)+(X105*G105) -> 2158.2893 | BF105: =(BE105/ABS(BD105))-1 -> -0.38334591 | BG105: =BG104+BC105 -> 37.329964 | BH105: =BE105+BG105 -> 2195.6193 | BI105: =(BH105/ABS(BD105))-1 -> -0.37268021 | BJ105: =(B105*AQ105)+(C105*AR105)+(D105*AS105)+(E105*AT105)+(F105*AU105)+(G105*AV105) -> 21.435406 | BK105: =BE105+BJ105 -> 2179.7247 | BL105: =(BK105/ABS(BD105))-1 -> -0.37722151 | BN105: =ABS(BD105) -> 3500 | BO105: =(B105*AW105)+(C105*AX105)+(D105*AY105)+(E105*AZ105)+(F105*BA105)+(G105*BB105) -> 2179.7247 | BQ105: =B105 -> 43.209999 | BR105: =G105 -> 22.58
A106: 39790 | B106: 43.720001 | C106: 40.540001 | D106: 31.74 | E106: 41.02 | F106: 26.879999 | G106: 24.57 | L106: =IF(int=Weekly,-$B$4,IF(int=Bi_Weekly,0,IF(int=Monthly,0,IF(int=Quarterly,0,IF(int=Yearly,0,IF(int=None,0,0)))))) -> 0 | M106: =(ABS((L106*$B$29)/B106)) -> 0 | N106: =(ABS((L106*$C$29)/C106)) -> 0 | O106: =(ABS((L106*$D$29)/D106)) -> 0 | P106: =(ABS((L106*$E$29)/E106)) -> 0 | Q106: =(ABS((L106*$F$29)/F106)) -> 0 | R106: =(ABS((L106*$G$29)/G106)) -> 0 | S106: =S105+M106 -> 9.3876301 | T106: =T105+N106 -> 10.211646 | U106: =U105+O106 -> 3.969906 | V106: =V105+P106 -> 2.780754 | W106: =W105+Q106 -> 34.039205 | X106: =X105+R106 -> 10.814568 | AE106: =(S106*Y106) -> 0 | AF106: =(T106*Z106) -> 0 | AG106: =(U106*AA106) -> 0 | AH106: =(V106*AB106) -> 0 | AI106: =(W106*AC106) -> 0 | AJ106: =(X106*AD106) -> 0 | AK106: =IF(AE106>0,AE106/B106,0) -> 0 | AL106: =IF(AF106>0,AF106/C106,0) -> 0 | AM106: =IF(AG106>0,AG106/D106,0) -> 0 | AN106: =IF(AH106>0,AH106/E106,0) -> 0 | AO106: =IF(AI106>0,AI106/F106,0) -> 0 | AP106: =IF(AJ106>0,AJ106/G106,0) -> 0 | AQ106: =AK106+AQ105+IF(AK106<0,AK106,0) -> 0.080086172 | AR106: =AL106+AR105+IF(AL106<0,AL106,0) -> 0.20560265 | AS106: =AM106+AS105+IF(AM106<0,AM106,0) -> 0.03219954 | AT106: =AN106+AT105+IF(AN106<0,AN106,0) -> 0.026321301 | AU106: =AO106+AU105+IF(AO106<0,AO106,0) -> 0.28399597 | AV106: =AP106+AV105+IF(AP106<0,AP106,0) -> 0.019085166 | AW106: =S106+AQ106 -> 9.4677163 | AX106: =T106+AR106 -> 10.417248 | AY106: =U106+AS106 -> 4.0021056 | AZ106: =V106+AT106 -> 2.8070753 | BA106: =W106+AU106 -> 34.323201 | BB106: =X106+AV106 -> 10.833653 | BC106: =(AE106+AF106+AG106+AH106+AI106+AJ106) -> 0 | BD106: =BD105+L106 -> -3500 | BE106: =(S106*B106)+(T106*C106)+(U106*D106)+(V106*E106)+(W106*F106)+(X106*G106) -> 2245.1664 | BF106: =(BE106/ABS(BD106))-1 -> -0.35852389 | BG106: =BG105+BC106 -> 37.329964 | BH106: =BE106+BG106 -> 2282.4964 | BI106: =(BH106/ABS(BD106))-1 -> -0.34785818 | BJ106: =(B106*AQ106)+(C106*AR106)+(D106*AS106)+(E106*AT106)+(F106*AU106)+(G106*AV106) -> 22.040946 | BK106: =BE106+BJ106 -> 2267.2073 | BL106: =(BK106/ABS(BD106))-1 -> -0.35222647 | BN106: =ABS(BD106) -> 3500 | BO106: =(B106*AW106)+(C106*AX106)+(D106*AY106)+(E106*AZ106)+(F106*BA106)+(G106*BB106) -> 2267.2073 | BQ106: =B106 -> 43.720001 | BR106: =G106 -> 24.57
A107: 39797 | B107: 44.110001 | C107: 40.52 | D107: 32.720001 | E107: 42.529999 | F107: 27.09 | G107: 25.040001 | L107: =IF(int=Weekly,-$B$4,IF(int=Bi_Weekly,-$B$4,IF(int=Monthly,-$B$4,IF(int=Quarterly,0,IF(int=Yearly,0,IF(int=None,0,0)))))) -> 0 | M107: =(ABS((L107*$B$29)/B107)) -> 0 | N107: =(ABS((L107*$C$29)/C107)) -> 0 | O107: =(ABS((L107*$D$29)/D107)) -> 0 | P107: =(ABS((L107*$E$29)/E107)) -> 0 | Q107: =(ABS((L107*$F$29)/F107)) -> 0 | R107: =(ABS((L107*$G$29)/G107)) -> 0 | S107: =S106+M107 -> 9.3876301 | T107: =T106+N107 -> 10.211646 | U107: =U106+O107 -> 3.969906 | V107: =V106+P107 -> 2.780754 | W107: =W106+Q107 -> 34.039205 | X107: =X106+R107 -> 10.814568 | AE107: =(S107*Y107) -> 0 | AF107: =(T107*Z107) -> 0 | AG107: =(U107*AA107) -> 0 | AH107: =(V107*AB107) -> 0 | AI107: =(W107*AC107) -> 0 | AJ107: =(X107*AD107) -> 0 | AK107: =IF(AE107>0,AE107/B107,0) -> 0 | AL107: =IF(AF107>0,AF107/C107,0) -> 0 | AM107: =IF(AG107>0,AG107/D107,0) -> 0 | AN107: =IF(AH107>0,AH107/E107,0) -> 0 | AO107: =IF(AI107>0,AI107/F107,0) -> 0 | AP107: =IF(AJ107>0,AJ107/G107,0) -> 0 | AQ107: =AK107+AQ106+IF(AK107<0,AK107,0) -> 0.080086172 | AR107: =AL107+AR106+IF(AL107<0,AL107,0) -> 0.20560265 | AS107: =AM107+AS106+IF(AM107<0,AM107,0) -> 0.03219954 | AT107: =AN107+AT106+IF(AN107<0,AN107,0) -> 0.026321301 | AU107: =AO107+AU106+IF(AO107<0,AO107,0) -> 0.28399597 | AV107: =AP107+AV106+IF(AP107<0,AP107,0) -> 0.019085166 | AW107: =S107+AQ107 -> 9.4677163 | AX107: =T107+AR107 -> 10.417248 | AY107: =U107+AS107 -> 4.0021056 | AZ107: =V107+AT107 -> 2.8070753 | BA107: =W107+AU107 -> 34.323201 | BB107: =X107+AV107 -> 10.833653 | BC107: =(AE107+AF107+AG107+AH107+AI107+AJ107) -> 0 | BD107: =BD106+L107 -> -3500 | BE107: =(S107*B107)+(T107*C107)+(U107*D107)+(V107*E107)+(W107*F107)+(X107*G107) -> 2268.9439 | BF107: =(BE107/ABS(BD107))-1 -> -0.35173031 | BG107: =BG106+BC107 -> 37.329964 | BH107: =BE107+BG107 -> 2306.2739 | BI107: =(BH107/ABS(BD107))-1 -> -0.34106461 | BJ107: =(B107*AQ107)+(C107*AR107)+(D107*AS107)+(E107*AT107)+(F107*AU107)+(G107*AV107) -> 22.207978 | BK107: =BE107+BJ107 -> 2291.1519 | BL107: =(BK107/ABS(BD107))-1 -> -0.34538518 | BN107: =ABS(BD107) -> 3500 | BO107: =(B107*AW107)+(C107*AX107)+(D107*AY107)+(E107*AZ107)+(F107*BA107)+(G107*BB107) -> 2291.1519 | BQ107: =B107 -> 44.110001 | BR107: =G107 -> 25.040001
A108: 39804 | B108: 43.32 | C108: 39.599998 | D108: 31.41 | E108: 40.459999 | F108: 26.24 | G108: 22.969999 | L108: =IF(int=Weekly,-$B$4,IF(int=Bi_Weekly,0,IF(int=Monthly,0,IF(int=Quarterly,0,IF(int=Yearly,0,IF(int=None,0,0)))))) -> 0 | M108: =(ABS((L108*$B$29)/B108)) -> 0 | N108: =(ABS((L108*$C$29)/C108)) -> 0 | O108: =(ABS((L108*$D$29)/D108)) -> 0 | P108: =(ABS((L108*$E$29)/E108)) -> 0 | Q108: =(ABS((L108*$F$29)/F108)) -> 0 | R108: =(ABS((L108*$G$29)/G108)) -> 0 | S108: =S107+M108 -> 9.3876301 | T108: =T107+N108 -> 10.211646 | U108: =U107+O108 -> 3.969906 | V108: =V107+P108 -> 2.780754 | W108: =W107+Q108 -> 34.039205 | X108: =X107+R108 -> 10.814568 | Y108: 0.335 | Z108: 0.431 | AA108: 0.857 | AB108: 1.267 | AC108: 0.914 | AD108: 1.178 | AE108: =(S108*Y108) -> 3.1448561 | AF108: =(T108*Z108) -> 4.4012192 | AG108: =(U108*AA108) -> 3.4022095 | AH108: =(V108*AB108) -> 3.5232154 | AI108: =(W108*AC108) -> 31.111833 | AJ108: =(X108*AD108) -> 12.739561 | AK108: =IF(AE108>0,AE108/B108,0) -> 0.072595939 | AL108: =IF(AF108>0,AF108/C108,0) -> 0.11114191 | AM108: =IF(AG108>0,AG108/D108,0) -> 0.10831612 | AN108: =IF(AH108>0,AH108/E108,0) -> 0.087078978 | AO108: =IF(AI108>0,AI108/F108,0) -> 1.1856644 | AP108: =IF(AJ108>0,AJ108/G108,0) -> 0.55461739 | AQ108: =AK108+AQ107+IF(AK108<0,AK108,0) -> 0.15268211 | AR108: =AL108+AR107+IF(AL108<0,AL108,0) -> 0.31674456 | AS108: =AM108+AS107+IF(AM108<0,AM108,0) -> 0.14051566 | AT108: =AN108+AT107+IF(AN108<0,AN108,0) -> 0.11340028 | AU108: =AO108+AU107+IF(AO108<0,AO108,0) -> 1.4696604 | AV108: =AP108+AV107+IF(AP108<0,AP108,0) -> 0.57370255 | AW108: =S108+AQ108 -> 9.5403122 | AX108: =T108+AR108 -> 10.52839 | AY108: =U108+AS108 -> 4.1104217 | AZ108: =V108+AT108 -> 2.8941543 | BA108: =W108+AU108 -> 35.508865 | BB108: =X108+AV108 -> 11.38827 | BC108: =(AE108+AF108+AG108+AH108+AI108+AJ108) -> 58.322894 | BD108: =BD107+L108 -> -3500 | BE108: =(S108*B108)+(T108*C108)+(U108*D108)+(V108*E108)+(W108*F108)+(X108*G108) -> 2189.8567 | BF108: =(BE108/ABS(BD108))-1 -> -0.37432666 | BG108: =BG107+BC108 -> 95.652859 | BH108: =BE108+BG108 -> 2285.5095 | BI108: =(BH108/ABS(BD108))-1 -> -0.34699727 | BJ108: =(B108*AQ108)+(C108*AR108)+(D108*AS108)+(E108*AT108)+(F108*AU108)+(G108*AV108) -> 79.90088 | BK108: =BE108+BJ108 -> 2269.7576 | BL108: =(BK108/ABS(BD108))-1 -> -0.35149784 | BN108: =ABS(BD108) -> 3500 | BO108: =(B108*AW108)+(C108*AX108)+(D108*AY108)+(E108*AZ108)+(F108*BA108)+(G108*BB108) -> 2269.7576 | BQ108: =B108 -> 43.32 | BR108: =G108 -> 22.969999
A109: 39811 | B109: 46.029999 | C109: 42.299999 | D109: 33.650002 | E109: 43.049999 | F109: 27.639999 | G109: 24.83 | L109: =IF(int=Weekly,-$B$4,IF(int=Bi_Weekly,-$B$4,IF(int=Monthly,0,IF(int=Quarterly,0,IF(int=Yearly,0,IF(int=None,0,0)))))) -> 0 | M109: =(ABS((L109*$B$29)/B109)) -> 0 | N109: =(ABS((L109*$C$29)/C109)) -> 0 | O109: =(ABS((L109*$D$29)/D109)) -> 0 | P109: =(ABS((L109*$E$29)/E109)) -> 0 | Q109: =(ABS((L109*$F$29)/F109)) -> 0 | R109: =(ABS((L109*$G$29)/G109)) -> 0 | S109: =S108+M109 -> 9.3876301 | T109: =T108+N109 -> 10.211646 | U109: =U108+O109 -> 3.969906 | V109: =V108+P109 -> 2.780754 | W109: =W108+Q109 -> 34.039205 | X109: =X108+R109 -> 10.814568 | AE109: =(S109*Y109) -> 0 | AF109: =(T109*Z109) -> 0 | AG109: =(U109*AA109) -> 0 | AH109: =(V109*AB109) -> 0 | AI109: =(W109*AC109) -> 0 | AJ109: =(X109*AD109) -> 0 | AK109: =IF(AE109>0,AE109/B109,0) -> 0 | AL109: =IF(AF109>0,AF109/C109,0) -> 0 | AM109: =IF(AG109>0,AG109/D109,0) -> 0 | AN109: =IF(AH109>0,AH109/E109,0) -> 0 | AO109: =IF(AI109>0,AI109/F109,0) -> 0 | AP109: =IF(AJ109>0,AJ109/G109,0) -> 0 | AQ109: =AK109+AQ108+IF(AK109<0,AK109,0) -> 0.15268211 | AR109: =AL109+AR108+IF(AL109<0,AL109,0) -> 0.31674456 | AS109: =AM109+AS108+IF(AM109<0,AM109,0) -> 0.14051566 | AT109: =AN109+AT108+IF(AN109<0,AN109,0) -> 0.11340028 | AU109: =AO109+AU108+IF(AO109<0,AO109,0) -> 1.4696604 | AV109: =AP109+AV108+IF(AP109<0,AP109,0) -> 0.57370255 | AW109: =S109+AQ109 -> 9.5403122 | AX109: =T109+AR109 -> 10.52839 | AY109: =U109+AS109 -> 4.1104217 | AZ109: =V109+AT109 -> 2.8941543 | BA109: =W109+AU109 -> 35.508865 | BB109: =X109+AV109 -> 11.38827 | BC109: =(AE109+AF109+AG109+AH109+AI109+AJ109) -> 0 | BD109: =BD108+L109 -> -3500 | BE109: =(S109*B109)+(T109*C109)+(U109*D109)+(V109*E109)+(W109*F109)+(X109*G109) -> 2326.7333 | BF109: =(BE109/ABS(BD109))-1 -> -0.33521905 | BG109: =BG108+BC109 -> 95.652859 | BH109: =BE109+BG109 -> 2422.3862 | BI109: =(BH109/ABS(BD109))-1 -> -0.30788966 | BJ109: =(B109*AQ109)+(C109*AR109)+(D109*AS109)+(E109*AT109)+(F109*AU109)+(G109*AV109) -> 84.902931 | BK109: =BE109+BJ109 -> 2411.6362 | BL109: =(BK109/ABS(BD109))-1 -> -0.31096107 | BN109: =ABS(BD109) -> 3500 | BO109: =(B109*AW109)+(C109*AX109)+(D109*AY109)+(E109*AZ109)+(F109*BA109)+(G109*BB109) -> 2411.6362 | BQ109: =B109 -> 46.029999 | BR109: =G109 -> 24.83
A110: 39818 | B110: 44.189999 | C110: 40.310001 | D110: 32.700001 | E110: 41.310001 | F110: 26.629999 | G110: 23.58 | L110: =IF(int=Weekly,-$B$4,IF(int=Bi_Weekly,0,IF(int=Monthly,0,IF(int=Quarterly,0,IF(int=Yearly,0,IF(int=None,0,0)))))) -> 0 | M110: =(ABS((L110*$B$29)/B110)) -> 0 | N110: =(ABS((L110*$C$29)/C110)) -> 0 | O110: =(ABS((L110*$D$29)/D110)) -> 0 | P110: =(ABS((L110*$E$29)/E110)) -> 0 | Q110: =(ABS((L110*$F$29)/F110)) -> 0 | R110: =(ABS((L110*$G$29)/G110)) -> 0 | S110: =S109+M110 -> 9.3876301 | T110: =T109+N110 -> 10.211646 | U110: =U109+O110 -> 3.969906 | V110: =V109+P110 -> 2.780754 | W110: =W109+Q110 -> 34.039205 | X110: =X109+R110 -> 10.814568 | AE110: =(S110*Y110) -> 0 | AF110: =(T110*Z110) -> 0 | AG110: =(U110*AA110) -> 0 | AH110: =(V110*AB110) -> 0 | AI110: =(W110*AC110) -> 0 | AJ110: =(X110*AD110) -> 0 | AK110: =IF(AE110>0,AE110/B110,0) -> 0 | AL110: =IF(AF110>0,AF110/C110,0) -> 0 | AM110: =IF(AG110>0,AG110/D110,0) -> 0 | AN110: =IF(AH110>0,AH110/E110,0) -> 0 | AO110: =IF(AI110>0,AI110/F110,0) -> 0 | AP110: =IF(AJ110>0,AJ110/G110,0) -> 0 | AQ110: =AK110+AQ109+IF(AK110<0,AK110,0) -> 0.15268211 | AR110: =AL110+AR109+IF(AL110<0,AL110,0) -> 0.31674456 | AS110: =AM110+AS109+IF(AM110<0,AM110,0) -> 0.14051566 | AT110: =AN110+AT109+IF(AN110<0,AN110,0) -> 0.11340028 | AU110: =AO110+AU109+IF(AO110<0,AO110,0) -> 1.4696604 | AV110: =AP110+AV109+IF(AP110<0,AP110,0) -> 0.57370255 | AW110: =S110+AQ110 -> 9.5403122 | AX110: =T110+AR110 -> 10.52839 | AY110: =U110+AS110 -> 4.1104217 | AZ110: =V110+AT110 -> 2.8941543 | BA110: =W110+AU110 -> 35.508865 | BB110: =X110+AV110 -> 11.38827 | BC110: =(AE110+AF110+AG110+AH110+AI110+AJ110) -> 0 | BD110: =BD109+L110 -> -3500 | BE110: =(S110*B110)+(T110*C110)+(U110*D110)+(V110*E110)+(W110*F110)+(X110*G110) -> 2232.6312 | BF110: =(BE110/ABS(BD110))-1 -> -0.36210537 | BG110: =BG109+BC110 -> 95.652859 | BH110: =BE110+BG110 -> 2328.2841 | BI110: =(BH110/ABS(BD110))-1 -> -0.33477598 | BJ110: =(B110*AQ110)+(C110*AR110)+(D110*AS110)+(E110*AT110)+(F110*AU110)+(G110*AV110) -> 81.459384 | BK110: =BE110+BJ110 -> 2314.0906 | BL110: =(BK110/ABS(BD110))-1 -> -0.33883126 | BN110: =ABS(BD110) -> 3500 | BO110: =(B110*AW110)+(C110*AX110)+(D110*AY110)+(E110*AZ110)+(F110*BA110)+(G110*BB110) -> 2314.0906 | BQ110: =B110 -> 44.189999 | BR110: =G110 -> 23.58
A111: 39825 | B111: 42.330002 | C111: 37.810001 | D111: 31.280001 | E111: 39.560001 | F111: 24.860001 | G111: 22.120001 | L111: =IF(int=Weekly,-$B$4,IF(int=Bi_Weekly,-$B$4,IF(int=Monthly,-$B$4,IF(int=Quarterly,0,IF(int=Yearly,0,IF(int=None,0,0)))))) -> 0 | M111: =(ABS((L111*$B$29)/B111)) -> 0 | N111: =(ABS((L111*$C$29)/C111)) -> 0 | O111: =(ABS((L111*$D$29)/D111)) -> 0 | P111: =(ABS((L111*$E$29)/E111)) -> 0 | Q111: =(ABS((L111*$F$29)/F111)) -> 0 | R111: =(ABS((L111*$G$29)/G111)) -> 0 | S111: =S110+M111 -> 9.3876301 | T111: =T110+N111 -> 10.211646 | U111: =U110+O111 -> 3.969906 | V111: =V110+P111 -> 2.780754 | W111: =W110+Q111 -> 34.039205 | X111: =X110+R111 -> 10.814568 | AE111: =(S111*Y111) -> 0 | AF111: =(T111*Z111) -> 0 | AG111: =(U111*AA111) -> 0 | AH111: =(V111*AB111) -> 0 | AI111: =(W111*AC111) -> 0 | AJ111: =(X111*AD111) -> 0 | AK111: =IF(AE111>0,AE111/B111,0) -> 0 | AL111: =IF(AF111>0,AF111/C111,0) -> 0 | AM111: =IF(AG111>0,AG111/D111,0) -> 0 | AN111: =IF(AH111>0,AH111/E111,0) -> 0 | AO111: =IF(AI111>0,AI111/F111,0) -> 0 | AP111: =IF(AJ111>0,AJ111/G111,0) -> 0 | AQ111: =AK111+AQ110+IF(AK111<0,AK111,0) -> 0.15268211 | AR111: =AL111+AR110+IF(AL111<0,AL111,0) -> 0.31674456 | AS111: =AM111+AS110+IF(AM111<0,AM111,0) -> 0.14051566 | AT111: =AN111+AT110+IF(AN111<0,AN111,0) -> 0.11340028 | AU111: =AO111+AU110+IF(AO111<0,AO111,0) -> 1.4696604 | AV111: =AP111+AV110+IF(AP111<0,AP111,0) -> 0.57370255 | AW111: =S111+AQ111 -> 9.5403122 | AX111: =T111+AR111 -> 10.52839 | AY111: =U111+AS111 -> 4.1104217 | AZ111: =V111+AT111 -> 2.8941543 | BA111: =W111+AU111 -> 35.508865 | BB111: =X111+AV111 -> 11.38827 | BC111: =(AE111+AF111+AG111+AH111+AI111+AJ111) -> 0 | BD111: =BD110+L111 -> -3500 | BE111: =(S111*B111)+(T111*C111)+(U111*D111)+(V111*E111)+(W111*F111)+(X111*G111) -> 2103.0989 | BF111: =(BE111/ABS(BD111))-1 -> -0.39911459 | BG111: =BG110+BC111 -> 95.652859 | BH111: =BE111+BG111 -> 2198.7518 | BI111: =(BH111/ABS(BD111))-1 -> -0.3717852 | BJ111: =(B111*AQ111)+(C111*AR111)+(D111*AS111)+(E111*AT111)+(F111*AU111)+(G111*AV111) -> 76.54665 | BK111: =BE111+BJ111 -> 2179.6456 | BL111: =(BK111/ABS(BD111))-1 -> -0.37724411 | BN111: =ABS(BD111) -> 3500 | BO111: =(B111*AW111)+(C111*AX111)+(D111*AY111)+(E111*AZ111)+(F111*BA111)+(G111*BB111) -> 2179.6456 | BQ111: =B111 -> 42.330002 | BR111: =G111 -> 22.120001
...

Sheet Value Average (Model)
A1: Value Cost Average Method (VCA)
A2: Initial Investment | B2: 5000 | E2: % Change | F2: =AVERAGE((B31*B29)+(C31*C29)+(D31*D29)+(E31*E29)+(F31*F29)+(G31*G29)) -> 0.13730492
A3: Interval | B3: Monthly | E3: Period (Yr.) | F3: =COUNT(A35:A526)/52 -> 9.4615385
A4: Increment | B4: 100 | E4: Return on Principal | F4: =BL33 -> 0.38670859
E5: Gain/Loss | F5: =BK33+BJ33 -> 4711.8925
E6: Annual Return | F6: =((BK33/ABS(BJ33))^(1/F3))-1 -> 0.035157818
F7: Dividends Retained | H7: Dividends Reinvested
E8: Total Return (%) | F8: =BO33 -> 0.61906809 | H8: =BR33 -> 0.66905465
E9: Gain/Loss | F9: =BN33+BJ33 -> 7543.1019 | H9: =BQ33+BJ33 -> 8152.1686
E10: Annual Return | F10: =((BN33/ABS(BJ33))^(1/F3))-1 -> 0.052246406 | H10: =((BQ33/ABS(BJ33))^(1/F3))-1 -> 0.055633462
B15: Weekly
B16: Bi-weekly
B17: Monthly
B18: Quarterly
B19: Yearly
B20: None
A28: Symbol | B28: VTI | C28: VTV | D28: VOE | E28: VBR | F28: VEA | G28: VWO | M28: VTI | N28: VTV | O28: VOE | P28: VBR | Q28: VEA | R28: VWO
A29: Portfolio Weight | B29: 0.176 | C29: 0.176 | D29: 0.056 | E29: 0.049 | F29: 0.411 | G29: 0.132 | J29: =SUM(B29:G29) -> 1 | L29: Discount Rate | M29: =M30-B30 -> -2.3165325 | N29: =N30-C30 -> -15.214073 | O29: =O30-D30 -> -27.7341 | P29: =P30-E30 -> -38.033652 | Q29: =Q30-F30 -> -2.1631635 | R29: =R30-G30 -> -1.1371332
A30: Average Price | B30: =AVERAGE(BZ35:BZ80,B81:B526) -> 77.831077 | C30: =AVERAGE(C35:C526) -> 63.830793 | D30: =AVERAGE(D35:D526) -> 63.394837 | E30: =AVERAGE(E35:E526) -> 76.877317 | F30: =AVERAGE(F35:F526) -> 36.556667 | G30: =AVERAGE(CA35:CA80,G81:G526) -> 40.316646 | L30: Aerage Cost per Share | M30: =M32/M31 -> 75.514545 | N30: =N32/N31 -> 48.61672 | O30: =O32/O31 -> 35.660738 | P30: =P32/P31 -> 38.843664 | Q30: =Q32/Q31 -> 34.393503 | R30: =R32/R31 -> 39.179513
A31: IRR | B31: =(B526-($B$35/2))/($B$35/2) -> 0.61989038 | C31: =(C526-$C$35)/$C$35 -> 0.38407747 | D31: =(D526-$D$35)/$D$35 -> 0.73895158 | E31: =(E526-$E$35)/$E$35 -> 0.79845425 | F31: =(F526-$F$35)/$F$35 -> -0.22535504 | G31: =(G526-($G$35/2))/($G$35/2) -> -0.20665188 | L31: Average Shares Purchased | M31: =AVERAGE(S35:S526) -> 0.036592087 | N31: =AVERAGE(T35:T526) -> 0.065323765 | O31: =AVERAGE(U35:U526) -> 0.019528415 | P31: =AVERAGE(V35:V526) -> 0.013795669 | Q31: =AVERAGE(W35:W526) -> 0.38707686 | R31: =AVERAGE(X35:X526) -> 0.10927139
L32: Average Amount Invested | M32: =ABS((AVERAGE(M35:M526))) -> 2.7632348 | N32: =ABS((AVERAGE(N35:N526))) -> 3.1758271 | O32: =ABS((AVERAGE(O35:O526))) -> 0.69639767 | P32: =ABS((AVERAGE(P35:P526))) -> 0.53587432 | Q32: =ABS((AVERAGE(Q35:Q526))) -> 13.312929 | R32: =ABS((AVERAGE(R35:R526))) -> 4.2811999
A33: Date | B33: NAV ($) | C33: NAV ($) | D33: NAV ($) | E33: NAV ($) | F33: NAV ($) | G33: NAV ($) | L33: Total | M33: =ABS(SUM(M35:M526)) -> 1359.5115 | N33: =ABS(SUM(N35:N526)) -> 1562.507 | O33: =ABS(SUM(O35:O526)) -> 342.62765 | P33: =ABS(SUM(P35:P526)) -> 263.65016 | Q33: =ABS(SUM(Q35:Q526)) -> 6549.9612 | R33: =ABS(SUM(R35:R526)) -> 2106.3504 | S33: =SUM(S35:S526) -> 18.003307 | T33: =SUM(T35:T526) -> 32.139292 | U33: =SUM(U35:U526) -> 9.60798 | V33: =SUM(V35:V526) -> 6.7874689 | W33: =SUM(W35:W526) -> 190.44182 | X33: =SUM(X35:X526) -> 53.761524 | Y33: =Y526 -> 25.840375 | Z33: =Z526 -> 32.139292 | AA33: =AA526 -> 9.60798 | AB33: =AB526 -> 6.7874689 | AC33: =AC526 -> 190.44182 | AD33: =AD526 -> 61.863759 | BJ33: =BJ526 -> -12184.608 | BK33: =BK526 -> 16896.5 | BL33: =BL526 -> 0.38670859 | BM33: =BM526 -> 2831.2093 | BN33: =BN526 -> 19727.71 | BO33: =BO526 -> 0.61906809 | BP33: =BP526 -> 3440.276 | BQ33: =BQ526 -> 20336.776 | BR33: =BR526 -> 0.66905465
L34: Set Value | M34: Amount Invested ($) | S34: Shares (#) | Y34: Total Shares (#) | AE34: Dividend Payout/Share ($) | AK34: Dividend ($) | AQ34: Additional Shares | AW34: Total Additional Shares | BC34: New Total Shares (#) | BI34: Dividend Payout ($) | BJ34: Principal ($) | BK34: Total Value | BL34: Return (%) | BM34: Dividend Value ($) | BN34: Total Value ($) | BO34: Return (%) | BP34: Divdend Value ($) | BQ34: Total Value ($) | BR34: Return (%) | BU34: Principal ($) | BV34: Total Value | BX34: Absolute Total Invested | BY34: Return | BZ34: VTI | CA34: VWO
A35: 39293 | B35: 142.38001 | C35: 67.199997 | D35: 55.889999 | E35: 67.279999 | F35: 47.169998 | G35: 90.199997 | L35: =B2 -> 5000 | M35: =-$L$35*B29 -> -880 | N35: =-$L$35*C29 -> -880 | O35: =-$L$35*D29 -> -280 | P35: =-$L$35*E29 -> -245 | Q35: =-$L$35*F29 -> -2055 | R35: =-$L$35*G29 -> -660 | S35: =-((M35)/B35) -> 6.1806431 | T35: =-((N35)/C35) -> 13.095239 | U35: =-(O35)/D35 -> 5.0098408 | V35: =-(P35)/E35 -> 3.6414983 | W35: =-(Q35)/F35 -> 43.565828 | X35: =-(R35)/G35 -> 7.3170734 | Y35: =S35 -> 6.1806431 | Z35: =T35 -> 13.095239 | AA35: =U35 -> 5.0098408 | AB35: =V35 -> 3.6414983 | AC35: =W35 -> 43.565828 | AD35: =X35 -> 7.3170734 | AK35: =(Y35*AE35) -> 0 | AL35: =(Z35*AF35) -> 0 | AM35: =(AA35*AG35) -> 0 | AN35: =(AB35*AH35) -> 0 | AO35: =(AC35*AI35) -> 0 | AP35: =(AD35*AJ35) -> 0 | AQ35: =IF(AK35>0,AK35/B35,0) -> 0 | AR35: =IF(AL35>0,AL35/C35,0) -> 0 | AS35: =IF(AM35>0,AM35/D35,0) -> 0 | AT35: =IF(AN35>0,AN35/E35,0) -> 0 | AU35: =IF(AO35>0,AO35/F35,0) -> 0 | AV35: =IF(AP35>0,AP35/G35,0) -> 0 | AW35: =AQ35 -> 0 | AX35: =AR35 -> 0 | AY35: =AS35 -> 0 | AZ35: =AT35 -> 0 | BA35: =AU35 -> 0 | BB35: =AV35 -> 0 | BC35: =Y35+AQ35 -> 6.1806431 | BD35: =Z35+AR35 -> 13.095239 | BE35: =AA35+AS35 -> 5.0098408 | BF35: =AB35+AT35 -> 3.6414983 | BG35: =AC35+AU35 -> 43.565828 | BH35: =AD35+AV35 -> 7.3170734 | BI35: =(AK35+AL35+AM35+AN35+AO35+AP35) -> 0 | BJ35: =M35+N35+O35+P35+Q35+R35 -> -5000 | BK35: =(Y35*B35)+(Z35*C35)+(AA35*D35)+(AB35*E35)+(AC35*F35)+(AD35*G35) -> 5000 | BL35: =BK35/ABS(BJ35)-1 -> 0 | BM35: =BI35 -> 0 | BN35: =BK35+BM35 -> 5000 | BO35: =BN35/ABS(BJ35)-1 -> 0 | BP35: =(B35*AW35)+(C35*AX35)+(D35*AY35)+(E35*AZ35)+(F35*BA35)+(G35*BB35) -> 0 | BQ35: =(B35*BC35)+(C35*BD35)+(D35*BE35)+(E35*BF35)+(F35*BG35)+(G35*BH35) -> 5000 | BR35: =(BQ35/ABS(BJ35))-1 -> 0 | BU35: =M35+N35+O35+P35+Q35+R35 -> -5000 | BV35: =(Y35*B35)+(Z35*C35)+(AA35*D35)+(AB35*E35)+(AC35*F35)+(AD35*G35) -> 5000 | BX35: =ABS(BJ35) -> 5000 | BY35: =IRR(BJ35:BK35) -> 0 | BZ35: =B35/2 -> 71.190003 | CA35: =G35/2 -> 45.099998
A36: 39300 | B36: 143.72 | C36: 68.300003 | D36: 56.41 | E36: 69.68 | F36: 46.59 | G36: 90.449997 | L36: =IF(inter=Weekly_2,L35+$B$4,IF(inter=Bi_weekly_2,0,IF(inter=Monthly_2,0,IF(inter=Quarterly_2,0,IF(inter=Yearly_2,0,IF(inter=None_2,0,0)))))) -> 0 | M36: =IF(L36=0,0,-((L36*$B$29)-(Y35*B36))) -> 0 | N36: =IF(L36=0,0,-((L36*$C$29)-(Z35*C36))) -> 0 | O36: =IF(L36=0,0,-((L36*$D$29)-(AA35*D36))) -> 0 | P36: =IF(L36=0,0,-((L36*$E$29)-(AB35*E36))) -> 0 | Q36: =IF(L36=0,0,-((L36*$F$29)-(AC35*F36))) -> 0 | R36: =IF(L36=0,0,-((L36*$G$29)-(AD35*G36))) -> 0 | S36: =-((M36)/B36) -> 0 | T36: =-((N36)/C36) -> 0 | U36: =-(O36)/D36 -> 0 | V36: =-(P36)/E36 -> 0 | W36: =-(Q36)/F36 -> 0 | X36: =-(R36)/G36 -> 0 | Y36: =Y35+S36 -> 6.1806431 | Z36: =Z35+T36 -> 13.095239 | AA36: =AA35+U36 -> 5.0098408 | AB36: =AB35+V36 -> 3.6414983 | AC36: =AC35+W36 -> 43.565828 | AD36: =AD35+X36 -> 7.3170734 | AK36: =(Y36*AE36) -> 0 | AL36: =(Z36*AF36) -> 0 | AM36: =(AA36*AG36) -> 0 | AN36: =(AB36*AH36) -> 0 | AO36: =(AC36*AI36) -> 0 | AP36: =(AD36*AJ36) -> 0 | AQ36: =IF(AK36>0,AK36/B36,0) -> 0 | AR36: =IF(AL36>0,AL36/C36,0) -> 0 | AS36: =IF(AM36>0,AM36/D36,0) -> 0 | AT36: =IF(AN36>0,AN36/E36,0) -> 0 | AU36: =IF(AO36>0,AO36/F36,0) -> 0 | AV36: =IF(AP36>0,AP36/G36,0) -> 0 | AW36: =AQ36+AW35+IF(AQ36<0,AQ36,0) -> 0 | AX36: =AR36+AX35+IF(AR36<0,AR36,0) -> 0 | AY36: =AS36+AY35+IF(AS36<0,AS36,0) -> 0 | AZ36: =AT36+AZ35+IF(AT36<0,AT36,0) -> 0 | BA36: =AU36+BA35+IF(AU36<0,AU36,0) -> 0 | BB36: =AV36+BB35+IF(AV36<0,AV36,0) -> 0 | BC36: =Y36+AW36 -> 6.1806431 | BD36: =Z36+AX36 -> 13.095239 | BE36: =AA36+AY36 -> 5.0098408 | BF36: =AB36+AZ36 -> 3.6414983 | BG36: =AC36+BA36 -> 43.565828 | BH36: =AD36+BB36 -> 7.3170734 | BI36: =(AK36+AL36+AM36+AN36+AO36+AP36) -> 0 | BJ36: =BJ35+M36+N36+O36+P36+Q36+R36 -> -5000 | BK36: =(Y36*B36)+(Z36*C36)+(AA36*D36)+(AB36*E36)+(AC36*F36)+(AD36*G36) -> 5010.5928 | BL36: =BK36/ABS(BJ36)-1 -> 0.0021185551 | BM36: =BM35+BI36 -> 0 | BN36: =BK36+BM36 -> 5010.5928 | BO36: =BN36/ABS(BJ36)-1 -> 0.0021185551 | BP36: =(B36*AW36)+(C36*AX36)+(D36*AY36)+(E36*AZ36)+(F36*BA36)+(G36*BB36) -> 0 | BQ36: =(B36*BC36)+(C36*BD36)+(D36*BE36)+(E36*BF36)+(F36*BG36)+(G36*BH36) -> 5010.5928 | BR36: =(BQ36/ABS(BJ36))-1 -> 0.0021185551 | BU36: =BU35+M36+N36+O36+P36+Q36+R36 -> -5000 | BV36: =(Y36*B36)+(Z36*C36)+(AA36*D36)+(AB36*E36)+(AC36*F36)+(AD36*G36) -> 5010.5928 | BX36: =ABS(BJ36) -> 5000 | BY36: =IRR(BJ36:BK36) -> 0.0021185551 | BZ36: =B36/2 -> 71.86 | CA36: =G36/2 -> 45.224998
A37: 39307 | B37: 143.06 | C37: 68.809998 | D37: 55.959999 | E37: 69.309998 | F37: 45.400002 | G37: 85.559998 | L37: =IF(inter=Weekly_2,L36+$B$4,IF(inter=Bi_weekly_2,L35+$B$4,IF(inter=Monthly_2,0,IF(inter=Quarterly_2,0,IF(inter=Yearly_2,0,IF(inter=None_2,0,0)))))) -> 0 | M37: =IF(L37=0,0,-((L37*$B$29)-(Y36*B37))) -> 0 | N37: =IF(L37=0,0,-((L37*$C$29)-(Z36*C37))) -> 0 | O37: =IF(L37=0,0,-((L37*$D$29)-(AA36*D37))) -> 0 | P37: =IF(L37=0,0,-((L37*$E$29)-(AB36*E37))) -> 0 | Q37: =IF(L37=0,0,-((L37*$F$29)-(AC36*F37))) -> 0 | R37: =IF(L37=0,0,-((L37*$G$29)-(AD36*G37))) -> 0 | S37: =-((M37)/B37) -> 0 | T37: =-((N37)/C37) -> 0 | U37: =-(O37)/D37 -> 0 | V37: =-(P37)/E37 -> 0 | W37: =-(Q37)/F37 -> 0 | X37: =-(R37)/G37 -> 0 | Y37: =Y36+S37 -> 6.1806431 | Z37: =Z36+T37 -> 13.095239 | AA37: =AA36+U37 -> 5.0098408 | AB37: =AB36+V37 -> 3.6414983 | AC37: =AC36+W37 -> 43.565828 | AD37: =AD36+X37 -> 7.3170734 | AK37: =(Y37*AE37) -> 0 | AL37: =(Z37*AF37) -> 0 | AM37: =(AA37*AG37) -> 0 | AN37: =(AB37*AH37) -> 0 | AO37: =(AC37*AI37) -> 0 | AP37: =(AD37*AJ37) -> 0 | AQ37: =IF(AK37>0,AK37/B37,0) -> 0 | AR37: =IF(AL37>0,AL37/C37,0) -> 0 | AS37: =IF(AM37>0,AM37/D37,0) -> 0 | AT37: =IF(AN37>0,AN37/E37,0) -> 0 | AU37: =IF(AO37>0,AO37/F37,0) -> 0 | AV37: =IF(AP37>0,AP37/G37,0) -> 0 | AW37: =AQ37+AW36+IF(AQ37<0,AQ37,0) -> 0 | AX37: =AR37+AX36+IF(AR37<0,AR37,0) -> 0 | AY37: =AS37+AY36+IF(AS37<0,AS37,0) -> 0 | AZ37: =AT37+AZ36+IF(AT37<0,AT37,0) -> 0 | BA37: =AU37+BA36+IF(AU37<0,AU37,0) -> 0 | BB37: =AV37+BB36+IF(AV37<0,AV37,0) -> 0 | BC37: =Y37+AW37 -> 6.1806431 | BD37: =Z37+AX37 -> 13.095239 | BE37: =AA37+AY37 -> 5.0098408 | BF37: =AB37+AZ37 -> 3.6414983 | BG37: =AC37+BA37 -> 43.565828 | BH37: =AD37+BB37 -> 7.3170734 | BI37: =(AK37+AL37+AM37+AN37+AO37+AP37) -> 0 | BJ37: =BJ36+M37+N37+O37+P37+Q37+R37 -> -5000 | BK37: =(Y37*B37)+(Z37*C37)+(AA37*D37)+(AB37*E37)+(AC37*F37)+(AD37*G37) -> 4921.9665 | BL37: =BK37/ABS(BJ37)-1 -> -0.015606697 | BM37: =BM36+BI37 -> 0 | BN37: =BK37+BM37 -> 4921.9665 | BO37: =BN37/ABS(BJ37)-1 -> -0.015606697 | BP37: =(B37*AW37)+(C37*AX37)+(D37*AY37)+(E37*AZ37)+(F37*BA37)+(G37*BB37) -> 0 | BQ37: =(B37*BC37)+(C37*BD37)+(D37*BE37)+(E37*BF37)+(F37*BG37)+(G37*BH37) -> 4921.9665 | BR37: =(BQ37/ABS(BJ37))-1 -> -0.015606697 | BU37: =BU36+M37+N37+O37+P37+Q37+R37 -> -5000 | BV37: =(Y37*B37)+(Z37*C37)+(AA37*D37)+(AB37*E37)+(AC37*F37)+(AD37*G37) -> 4921.9665 | BX37: =ABS(BJ37) -> 5000 | BY37: =IRR(BJ37:BK37) -> -0.015606697 | BZ37: =B37/2 -> 71.529999 | CA37: =G37/2 -> 42.779999
A38: 39314 | B38: 146.85001 | C38: 70.290001 | D38: 57.66 | E38: 70.949997 | F38: 47.540001 | G38: 91.620003 | L38: =IF(inter=Weekly_2,L37+$B$4,IF(inter=Bi_weekly_2,0,IF(inter=Monthly_2,0,IF(inter=Quarterly_2,0,IF(inter=Yearly_2,0,IF(inter=None_2,0,0)))))) -> 0 | M38: =IF(L38=0,0,-((L38*$B$29)-(Y37*B38))) -> 0 | N38: =IF(L38=0,0,-((L38*$C$29)-(Z37*C38))) -> 0 | O38: =IF(L38=0,0,-((L38*$D$29)-(AA37*D38))) -> 0 | P38: =IF(L38=0,0,-((L38*$E$29)-(AB37*E38))) -> 0 | Q38: =IF(L38=0,0,-((L38*$F$29)-(AC37*F38))) -> 0 | R38: =IF(L38=0,0,-((L38*$G$29)-(AD37*G38))) -> 0 | S38: =-((M38)/B38) -> 0 | T38: =-((N38)/C38) -> 0 | U38: =-(O38)/D38 -> 0 | V38: =-(P38)/E38 -> 0 | W38: =-(Q38)/F38 -> 0 | X38: =-(R38)/G38 -> 0 | Y38: =Y37+S38 -> 6.1806431 | Z38: =Z37+T38 -> 13.095239 | AA38: =AA37+U38 -> 5.0098408 | AB38: =AB37+V38 -> 3.6414983 | AC38: =AC37+W38 -> 43.565828 | AD38: =AD37+X38 -> 7.3170734 | AK38: =(Y38*AE38) -> 0 | AL38: =(Z38*AF38) -> 0 | AM38: =(AA38*AG38) -> 0 | AN38: =(AB38*AH38) -> 0 | AO38: =(AC38*AI38) -> 0 | AP38: =(AD38*AJ38) -> 0 | AQ38: =IF(AK38>0,AK38/B38,0) -> 0 | AR38: =IF(AL38>0,AL38/C38,0) -> 0 | AS38: =IF(AM38>0,AM38/D38,0) -> 0 | AT38: =IF(AN38>0,AN38/E38,0) -> 0 | AU38: =IF(AO38>0,AO38/F38,0) -> 0 | AV38: =IF(AP38>0,AP38/G38,0) -> 0 | AW38: =AQ38+AW37+IF(AQ38<0,AQ38,0) -> 0 | AX38: =AR38+AX37+IF(AR38<0,AR38,0) -> 0 | AY38: =AS38+AY37+IF(AS38<0,AS38,0) -> 0 | AZ38: =AT38+AZ37+IF(AT38<0,AT38,0) -> 0 | BA38: =AU38+BA37+IF(AU38<0,AU38,0) -> 0 | BB38: =AV38+BB37+IF(AV38<0,AV38,0) -> 0 | BC38: =Y38+AW38 -> 6.1806431 | BD38: =Z38+AX38 -> 13.095239 | BE38: =AA38+AY38 -> 5.0098408 | BF38: =AB38+AZ38 -> 3.6414983 | BG38: =AC38+BA38 -> 43.565828 | BH38: =AD38+BB38 -> 7.3170734 | BI38: =(AK38+AL38+AM38+AN38+AO38+AP38) -> 0 | BJ38: =BJ37+M38+N38+O38+P38+Q38+R38 -> -5000 | BK38: =(Y38*B38)+(Z38*C38)+(AA38*D38)+(AB38*E38)+(AC38*F38)+(AD38*G38) -> 5116.8333 | BL38: =BK38/ABS(BJ38)-1 -> 0.023366662 | BM38: =BM37+BI38 -> 0 | BN38: =BK38+BM38 -> 5116.8333 | BO38: =BN38/ABS(BJ38)-1 -> 0.023366662 | BP38: =(B38*AW38)+(C38*AX38)+(D38*AY38)+(E38*AZ38)+(F38*BA38)+(G38*BB38) -> 0 | BQ38: =(B38*BC38)+(C38*BD38)+(D38*BE38)+(E38*BF38)+(F38*BG38)+(G38*BH38) -> 5116.8333 | BR38: =(BQ38/ABS(BJ38))-1 -> 0.023366662 | BU38: =BU37+M38+N38+O38+P38+Q38+R38 -> -5000 | BV38: =(Y38*B38)+(Z38*C38)+(AA38*D38)+(AB38*E38)+(AC38*F38)+(AD38*G38) -> 5116.8333 | BX38: =ABS(BJ38) -> 5000 | BY38: =IRR(BJ38:BK38) -> 0.023366662 | BZ38: =B38/2 -> 73.425003 | CA38: =G38/2 -> 45.810001
A39: 39321 | B39: 146.22 | C39: 69.5 | D39: 57.259998 | E39: 70.220001 | F39: 47.860001 | G39: 94.489998 | L39: =IF(inter=Weekly_2,L38+$B$4,IF(inter=Bi_weekly_2,L37+$B$4,IF(inter=Monthly_2,L35+$B$4,IF(inter=Quarterly_2,0,IF(inter=Yearly_2,0,IF(inter=None_2,0,0)))))) -> 5100 | M39: =IF(L39=0,0,-((L39*$B$29)-(Y38*B39))) -> 6.1336449 | N39: =IF(L39=0,0,-((L39*$C$29)-(Z38*C39))) -> 12.519088 | O39: =IF(L39=0,0,-((L39*$D$29)-(AA38*D39))) -> 1.263477 | P39: =IF(L39=0,0,-((L39*$E$29)-(AB38*E39))) -> 5.8060122 | Q39: =IF(L39=0,0,-((L39*$F$29)-(AC38*F39))) -> -11.039448 | R39: =IF(L39=0,0,-((L39*$G$29)-(AD38*G39))) -> 18.190252 | S39: =-((M39)/B39) -> -0.041948057 | T39: =-((N39)/C39) -> -0.18013077 | U39: =-(O39)/D39 -> -0.022065613 | V39: =-(P39)/E39 -> -0.082683169 | W39: =-(Q39)/F39 -> 0.23066126 | X39: =-(R39)/G39 -> -0.19250982 | Y39: =Y38+S39 -> 6.1386951 | Z39: =Z38+T39 -> 12.915108 | AA39: =AA38+U39 -> 4.9877752 | AB39: =AB38+V39 -> 3.5588151 | AC39: =AC38+W39 -> 43.796489 | AD39: =AD38+X39 -> 7.1245636 | AK39: =(Y39*AE39) -> 0 | AL39: =(Z39*AF39) -> 0 | AM39: =(AA39*AG39) -> 0 | AN39: =(AB39*AH39) -> 0 | AO39: =(AC39*AI39) -> 0 | AP39: =(AD39*AJ39) -> 0 | AQ39: =IF(AK39>0,AK39/B39,0) -> 0 | AR39: =IF(AL39>0,AL39/C39,0) -> 0 | AS39: =IF(AM39>0,AM39/D39,0) -> 0 | AT39: =IF(AN39>0,AN39/E39,0) -> 0 | AU39: =IF(AO39>0,AO39/F39,0) -> 0 | AV39: =IF(AP39>0,AP39/G39,0) -> 0 | AW39: =AQ39+AW38+IF(AQ39<0,AQ39,0) -> 0 | AX39: =AR39+AX38+IF(AR39<0,AR39,0) -> 0 | AY39: =AS39+AY38+IF(AS39<0,AS39,0) -> 0 | AZ39: =AT39+AZ38+IF(AT39<0,AT39,0) -> 0 | BA39: =AU39+BA38+IF(AU39<0,AU39,0) -> 0 | BB39: =AV39+BB38+IF(AV39<0,AV39,0) -> 0 | BC39: =Y39+AW39 -> 6.1386951 | BD39: =Z39+AX39 -> 12.915108 | BE39: =AA39+AY39 -> 4.9877752 | BF39: =AB39+AZ39 -> 3.5588151 | BG39: =AC39+BA39 -> 43.796489 | BH39: =AD39+BB39 -> 7.1245636 | BI39: =(AK39+AL39+AM39+AN39+AO39+AP39) -> 0 | BJ39: =BJ38+M39+N39+O39+P39+Q39+R39 -> -4967.127 | BK39: =(Y39*B39)+(Z39*C39)+(AA39*D39)+(AB39*E39)+(AC39*F39)+(AD39*G39) -> 5100 | BL39: =BK39/ABS(BJ39)-1 -> 0.026750479 | BM39: =BM38+BI39 -> 0 | BN39: =BK39+BM39 -> 5100 | BO39: =BN39/ABS(BJ39)-1 -> 0.026750479 | BP39: =(B39*AW39)+(C39*AX39)+(D39*AY39)+(E39*AZ39)+(F39*BA39)+(G39*BB39) -> 0 | BQ39: =(B39*BC39)+(C39*BD39)+(D39*BE39)+(E39*BF39)+(F39*BG39)+(G39*BH39) -> 5100 | BR39: =(BQ39/ABS(BJ39))-1 -> 0.026750479 | BU39: =BU38+M39+N39+O39+P39+Q39+R39 -> -4967.127 | BV39: =(Y39*B39)+(Z39*C39)+(AA39*D39)+(AB39*E39)+(AC39*F39)+(AD39*G39) -> 5100 | BX39: =ABS(BJ39) -> 4967.127 | BY39: =IRR(BJ39:BK39) -> 0.026750479 | BZ39: =B39/2 -> 73.11 | CA39: =G39/2 -> 47.244999
A40: 39329 | B40: 144.92999 | C40: 68.589996 | D40: 56.330002 | E40: 68.779999 | F40: 46.880001 | G40: 93.110001 | L40: =IF(inter=Weekly_2,L39+$B$4,IF(inter=Bi_weekly_2,0,IF(inter=Monthly_2,0,IF(inter=Quarterly_2,0,IF(inter=Yearly_2,0,IF(inter=None_2,0,0)))))) -> 0 | M40: =IF(L40=0,0,-((L40*$B$29)-(Y39*B40))) -> 0 | N40: =IF(L40=0,0,-((L40*$C$29)-(Z39*C40))) -> 0 | O40: =IF(L40=0,0,-((L40*$D$29)-(AA39*D40))) -> 0 | P40: =IF(L40=0,0,-((L40*$E$29)-(AB39*E40))) -> 0 | Q40: =IF(L40=0,0,-((L40*$F$29)-(AC39*F40))) -> 0 | R40: =IF(L40=0,0,-((L40*$G$29)-(AD39*G40))) -> 0 | S40: =-((M40)/B40) -> 0 | T40: =-((N40)/C40) -> 0 | U40: =-(O40)/D40 -> 0 | V40: =-(P40)/E40 -> 0 | W40: =-(Q40)/F40 -> 0 | X40: =-(R40)/G40 -> 0 | Y40: =Y39+S40 -> 6.1386951 | Z40: =Z39+T40 -> 12.915108 | AA40: =AA39+U40 -> 4.9877752 | AB40: =AB39+V40 -> 3.5588151 | AC40: =AC39+W40 -> 43.796489 | AD40: =AD39+X40 -> 7.1245636 | AK40: =(Y40*AE40) -> 0 | AL40: =(Z40*AF40) -> 0 | AM40: =(AA40*AG40) -> 0 | AN40: =(AB40*AH40) -> 0 | AO40: =(AC40*AI40) -> 0 | AP40: =(AD40*AJ40) -> 0 | AQ40: =IF(AK40>0,AK40/B40,0) -> 0 | AR40: =IF(AL40>0,AL40/C40,0) -> 0 | AS40: =IF(AM40>0,AM40/D40,0) -> 0 | AT40: =IF(AN40>0,AN40/E40,0) -> 0 | AU40: =IF(AO40>0,AO40/F40,0) -> 0 | AV40: =IF(AP40>0,AP40/G40,0) -> 0 | AW40: =AQ40+AW39+IF(AQ40<0,AQ40,0) -> 0 | AX40: =AR40+AX39+IF(AR40<0,AR40,0) -> 0 | AY40: =AS40+AY39+IF(AS40<0,AS40,0) -> 0 | AZ40: =AT40+AZ39+IF(AT40<0,AT40,0) -> 0 | BA40: =AU40+BA39+IF(AU40<0,AU40,0) -> 0 | BB40: =AV40+BB39+IF(AV40<0,AV40,0) -> 0 | BC40: =Y40+AW40 -> 6.1386951 | BD40: =Z40+AX40 -> 12.915108 | BE40: =AA40+AY40 -> 4.9877752 | BF40: =AB40+AZ40 -> 3.5588151 | BG40: =AC40+BA40 -> 43.796489 | BH40: =AD40+BB40 -> 7.1245636 | BI40: =(AK40+AL40+AM40+AN40+AO40+AP40) -> 0 | BJ40: =BJ39+M40+N40+O40+P40+Q40+R40 -> -4967.127 | BK40: =(Y40*B40)+(Z40*C40)+(AA40*D40)+(AB40*E40)+(AC40*F40)+(AD40*G40) -> 5017.8125 | BL40: =BK40/ABS(BJ40)-1 -> 0.010204191 | BM40: =BM39+BI40 -> 0 | BN40: =BK40+BM40 -> 5017.8125 | BO40: =BN40/ABS(BJ40)-1 -> 0.010204191 | BP40: =(B40*AW40)+(C40*AX40)+(D40*AY40)+(E40*AZ40)+(F40*BA40)+(G40*BB40) -> 0 | BQ40: =(B40*BC40)+(C40*BD40)+(D40*BE40)+(E40*BF40)+(F40*BG40)+(G40*BH40) -> 5017.8125 | BR40: =(BQ40/ABS(BJ40))-1 -> 0.010204191 | BU40: =BU39+M40+N40+O40+P40+Q40+R40 -> -4967.127 | BV40: =(Y40*B40)+(Z40*C40)+(AA40*D40)+(AB40*E40)+(AC40*F40)+(AD40*G40) -> 5017.8125 | BX40: =ABS(BJ40) -> 4967.127 | BY40: =IRR(BJ40:BK40) -> 0.010204191 | BZ40: =B40/2 -> 72.464996 | CA40: =G40/2 -> 46.555
A41: 39335 | B41: 147.38001 | C41: 70.199997 | D41: 56.91 | E41: 69.300003 | F41: 47.529999 | G41: 95.919998 | L41: =IF(inter=Weekly_2,L40+$B$4,IF(inter=Bi_weekly_2,L39+$B$4,IF(inter=Monthly_2,0,IF(inter=Quarterly_2,0,IF(inter=Yearly_2,0,IF(inter=None_2,0,0)))))) -> 0 | M41: =IF(L41=0,0,-((L41*$B$29)-(Y40*B41))) -> 0 | N41: =IF(L41=0,0,-((L41*$C$29)-(Z40*C41))) -> 0 | O41: =IF(L41=0,0,-((L41*$D$29)-(AA40*D41))) -> 0 | P41: =IF(L41=0,0,-((L41*$E$29)-(AB40*E41))) -> 0 | Q41: =IF(L41=0,0,-((L41*$F$29)-(AC40*F41))) -> 0 | R41: =IF(L41=0,0,-((L41*$G$29)-(AD40*G41))) -> 0 | S41: =-((M41)/B41) -> 0 | T41: =-((N41)/C41) -> 0 | U41: =-(O41)/D41 -> 0 | V41: =-(P41)/E41 -> 0 | W41: =-(Q41)/F41 -> 0 | X41: =-(R41)/G41 -> 0 | Y41: =Y40+S41 -> 6.1386951 | Z41: =Z40+T41 -> 12.915108 | AA41: =AA40+U41 -> 4.9877752 | AB41: =AB40+V41 -> 3.5588151 | AC41: =AC40+W41 -> 43.796489 | AD41: =AD40+X41 -> 7.1245636 | AK41: =(Y41*AE41) -> 0 | AL41: =(Z41*AF41) -> 0 | AM41: =(AA41*AG41) -> 0 | AN41: =(AB41*AH41) -> 0 | AO41: =(AC41*AI41) -> 0 | AP41: =(AD41*AJ41) -> 0 | AQ41: =IF(AK41>0,AK41/B41,0) -> 0 | AR41: =IF(AL41>0,AL41/C41,0) -> 0 | AS41: =IF(AM41>0,AM41/D41,0) -> 0 | AT41: =IF(AN41>0,AN41/E41,0) -> 0 | AU41: =IF(AO41>0,AO41/F41,0) -> 0 | AV41: =IF(AP41>0,AP41/G41,0) -> 0 | AW41: =AQ41+AW40+IF(AQ41<0,AQ41,0) -> 0 | AX41: =AR41+AX40+IF(AR41<0,AR41,0) -> 0 | AY41: =AS41+AY40+IF(AS41<0,AS41,0) -> 0 | AZ41: =AT41+AZ40+IF(AT41<0,AT41,0) -> 0 | BA41: =AU41+BA40+IF(AU41<0,AU41,0) -> 0 | BB41: =AV41+BB40+IF(AV41<0,AV41,0) -> 0 | BC41: =Y41+AW41 -> 6.1386951 | BD41: =Z41+AX41 -> 12.915108 | BE41: =AA41+AY41 -> 4.9877752 | BF41: =AB41+AZ41 -> 3.5588151 | BG41: =AC41+BA41 -> 43.796489 | BH41: =AD41+BB41 -> 7.1245636 | BI41: =(AK41+AL41+AM41+AN41+AO41+AP41) -> 0 | BJ41: =BJ40+M41+N41+O41+P41+Q41+R41 -> -4967.127 | BK41: =(Y41*B41)+(Z41*C41)+(AA41*D41)+(AB41*E41)+(AC41*F41)+(AD41*G41) -> 5106.8768 | BL41: =BK41/ABS(BJ41)-1 -> 0.028134948 | BM41: =BM40+BI41 -> 0 | BN41: =BK41+BM41 -> 5106.8768 | BO41: =BN41/ABS(BJ41)-1 -> 0.028134948 | BP41: =(B41*AW41)+(C41*AX41)+(D41*AY41)+(E41*AZ41)+(F41*BA41)+(G41*BB41) -> 0 | BQ41: =(B41*BC41)+(C41*BD41)+(D41*BE41)+(E41*BF41)+(F41*BG41)+(G41*BH41) -> 5106.8768 | BR41: =(BQ41/ABS(BJ41))-1 -> 0.028134948 | BU41: =BU40+M41+N41+O41+P41+Q41+R41 -> -4967.127 | BV41: =(Y41*B41)+(Z41*C41)+(AA41*D41)+(AB41*E41)+(AC41*F41)+(AD41*G41) -> 5106.8768 | BX41: =ABS(BJ41) -> 4967.127 | BY41: =IRR(BJ41:BK41) -> 0.028134948 | BZ41: =B41/2 -> 73.690003 | CA41: =G41/2 -> 47.959999
A42: 39342 | B42: 151.22 | C42: 72.18 | D42: 58.23 | E42: 71.68 | F42: 49.110001 | G42: 100.75 | L42: =IF(inter=Weekly_2,L41+$B$4,IF(inter=Bi_weekly_2,0,IF(inter=Monthly_2,0,IF(inter=Quarterly_2,0,IF(inter=Yearly_2,0,IF(inter=None_2,0,0)))))) -> 0 | M42: =IF(L42=0,0,-((L42*$B$29)-(Y41*B42))) -> 0 | N42: =IF(L42=0,0,-((L42*$C$29)-(Z41*C42))) -> 0 | O42: =IF(L42=0,0,-((L42*$D$29)-(AA41*D42))) -> 0 | P42: =IF(L42=0,0,-((L42*$E$29)-(AB41*E42))) -> 0 | Q42: =IF(L42=0,0,-((L42*$F$29)-(AC41*F42))) -> 0 | R42: =IF(L42=0,0,-((L42*$G$29)-(AD41*G42))) -> 0 | S42: =-((M42)/B42) -> 0 | T42: =-((N42)/C42) -> 0 | U42: =-(O42)/D42 -> 0 | V42: =-(P42)/E42 -> 0 | W42: =-(Q42)/F42 -> 0 | X42: =-(R42)/G42 -> 0 | Y42: =Y41+S42 -> 6.1386951 | Z42: =Z41+T42 -> 12.915108 | AA42: =AA41+U42 -> 4.9877752 | AB42: =AB41+V42 -> 3.5588151 | AC42: =AC41+W42 -> 43.796489 | AD42: =AD41+X42 -> 7.1245636 | AK42: =(Y42*AE42) -> 0 | AL42: =(Z42*AF42) -> 0 | AM42: =(AA42*AG42) -> 0 | AN42: =(AB42*AH42) -> 0 | AO42: =(AC42*AI42) -> 0 | AP42: =(AD42*AJ42) -> 0 | AQ42: =IF(AK42>0,AK42/B42,0) -> 0 | AR42: =IF(AL42>0,AL42/C42,0) -> 0 | AS42: =IF(AM42>0,AM42/D42,0) -> 0 | AT42: =IF(AN42>0,AN42/E42,0) -> 0 | AU42: =IF(AO42>0,AO42/F42,0) -> 0 | AV42: =IF(AP42>0,AP42/G42,0) -> 0 | AW42: =AQ42+AW41+IF(AQ42<0,AQ42,0) -> 0 | AX42: =AR42+AX41+IF(AR42<0,AR42,0) -> 0 | AY42: =AS42+AY41+IF(AS42<0,AS42,0) -> 0 | AZ42: =AT42+AZ41+IF(AT42<0,AT42,0) -> 0 | BA42: =AU42+BA41+IF(AU42<0,AU42,0) -> 0 | BB42: =AV42+BB41+IF(AV42<0,AV42,0) -> 0 | BC42: =Y42+AW42 -> 6.1386951 | BD42: =Z42+AX42 -> 12.915108 | BE42: =AA42+AY42 -> 4.9877752 | BF42: =AB42+AZ42 -> 3.5588151 | BG42: =AC42+BA42 -> 43.796489 | BH42: =AD42+BB42 -> 7.1245636 | BI42: =(AK42+AL42+AM42+AN42+AO42+AP42) -> 0 | BJ42: =BJ41+M42+N42+O42+P42+Q42+R42 -> -4967.127 | BK42: =(Y42*B42)+(Z42*C42)+(AA42*D42)+(AB42*E42)+(AC42*F42)+(AD42*G42) -> 5274.6854 | BL42: =BK42/ABS(BJ42)-1 -> 0.061918772 | BM42: =BM41+BI42 -> 0 | BN42: =BK42+BM42 -> 5274.6854 | BO42: =BN42/ABS(BJ42)-1 -> 0.061918772 | BP42: =(B42*AW42)+(C42*AX42)+(D42*AY42)+(E42*AZ42)+(F42*BA42)+(G42*BB42) -> 0 | BQ42: =(B42*BC42)+(C42*BD42)+(D42*BE42)+(E42*BF42)+(F42*BG42)+(G42*BH42) -> 5274.6854 | BR42: =(BQ42/ABS(BJ42))-1 -> 0.061918772 | BU42: =BU41+M42+N42+O42+P42+Q42+R42 -> -4967.127 | BV42: =(Y42*B42)+(Z42*C42)+(AA42*D42)+(AB42*E42)+(AC42*F42)+(AD42*G42) -> 5274.6854 | BX42: =ABS(BJ42) -> 4967.127 | BY42: =IRR(BJ42:BK42) -> 0.061918772 | BZ42: =B42/2 -> 75.61 | CA42: =G42/2 -> 50.375
